Workbook
Name 経費範囲: #REF!
Name 現場調査費: #REF!
Name 現調単価: #REF!
Name 合計: #REF!
Name 材料範囲: #REF!
Name 諸経費率: #REF!
Name 範囲: #REF!
Name 労務範囲: #REF!

Sheet No.1
C1: 年 組織法人経営体に関する経営分析調査 肥育豚生産費 集計結果検討表 №１
F3: 集計番号 | I3: 集計名称 | T3: 都道府県等 | Y3: 規模階層
A4: 本年 | U4: =IF(T4<>"",DGET(リスト!A2:B71,"都道府県等",リスト!B73:B74),"") | Z4: =IF(Y4<>"",DGET(リスト!D2:E7,"規模階層",リスト!E9:E10),"")
A5: 前年
A7: 【生産費総括（肥育豚１頭当たり）】 | AQ7: 単位：円、％
H8: 購 入 | Q8: 内 給 | Z8: 償 却 | AI8: 計
H9: 本年 | K9: 前年 | N9: 増減率 | Q9: 本年 | T9: 前年 | W9: 増減率 | Z9: 本年 | AC9: 前年 | AF9: 増減率 | AI9: 本年 | AL9: 前年 | AO9: 増減率
A10: 物財費 | N10: =IF(H10="-", "-", IF(K10="-", "-", IF(ABS(K10)=0, "-", ROUND(100*(H10-K10)/ABS(K10),1)))) -> - | W10: =IF(Q10="-", "-", IF(T10="-", "-", IF(ABS(T10)=0, "-", ROUND(100*(Q10-T10)/ABS(T10),1)))) -> - | AF10: =IF(Z10="-", "-", IF(AC10="-", "-", IF(ABS(AC10)=0, "-", ROUND(100*(Z10-AC10)/ABS(AC10),1)))) -> - | AO10: =IF(AI10="-", "-", IF(AL10="-", "-", IF(ABS(AL10)=0, "-", ROUND(100*(AI10-AL10)/ABS(AL10),1)))) -> -
B11: 種付料 | N11: =IF(H11="-", "-", IF(K11="-", "-", IF(ABS(K11)=0, "-", ROUND(100*(H11-K11)/ABS(K11),1)))) -> - | AO11: =IF(AI11="-", "-", IF(AL11="-", "-", IF(ABS(AL11)=0, "-", ROUND(100*(AI11-AL11)/ABS(AL11),1)))) -> -
B12: もと畜費 | N12: =IF(H12="-", "-", IF(K12="-", "-", IF(ABS(K12)=0, "-", ROUND(100*(H12-K12)/ABS(K12),1)))) -> - | AO12: =IF(AI12="-", "-", IF(AL12="-", "-", IF(ABS(AL12)=0, "-", ROUND(100*(AI12-AL12)/ABS(AL12),1)))) -> -
B13: 飼料費 | N13: =IF(H13="-", "-", IF(K13="-", "-", IF(ABS(K13)=0, "-", ROUND(100*(H13-K13)/ABS(K13),1)))) -> - | W13: =IF(Q13="-", "-", IF(T13="-", "-", IF(ABS(T13)=0, "-", ROUND(100*(Q13-T13)/ABS(T13),1)))) -> - | AO13: =IF(AI13="-", "-", IF(AL13="-", "-", IF(ABS(AL13)=0, "-", ROUND(100*(AI13-AL13)/ABS(AL13),1)))) -> -
C14: 流通飼料費 | N14: =IF(H14="-", "-", IF(K14="-", "-", IF(ABS(K14)=0, "-", ROUND(100*(H14-K14)/ABS(K14),1)))) -> - | W14: =IF(Q14="-", "-", IF(T14="-", "-", IF(ABS(T14)=0, "-", ROUND(100*(Q14-T14)/ABS(T14),1)))) -> - | AO14: =IF(AI14="-", "-", IF(AL14="-", "-", IF(ABS(AL14)=0, "-", ROUND(100*(AI14-AL14)/ABS(AL14),1)))) -> -
C15: 牧草・放牧・採草費 | W15: =IF(Q15="-", "-", IF(T15="-", "-", IF(ABS(T15)=0, "-", ROUND(100*(Q15-T15)/ABS(T15),1)))) -> - | AO15: =IF(AI15="-", "-", IF(AL15="-", "-", IF(ABS(AL15)=0, "-", ROUND(100*(AI15-AL15)/ABS(AL15),1)))) -> -
B16: 敷料費 | N16: =IF(H16="-", "-", IF(K16="-", "-", IF(ABS(K16)=0, "-", ROUND(100*(H16-K16)/ABS(K16),1)))) -> - | W16: =IF(Q16="-", "-", IF(T16="-", "-", IF(ABS(T16)=0, "-", ROUND(100*(Q16-T16)/ABS(T16),1)))) -> - | AO16: =IF(AI16="-", "-", IF(AL16="-", "-", IF(ABS(AL16)=0, "-", ROUND(100*(AI16-AL16)/ABS(AL16),1)))) -> -
B17: 光熱動力費 | N17: =IF(H17="-", "-", IF(K17="-", "-", IF(ABS(K17)=0, "-", ROUND(100*(H17-K17)/ABS(K17),1)))) -> - | W17: =IF(Q17="-", "-", IF(T17="-", "-", IF(ABS(T17)=0, "-", ROUND(100*(Q17-T17)/ABS(T17),1)))) -> - | AO17: =IF(AI17="-", "-", IF(AL17="-", "-", IF(ABS(AL17)=0, "-", ROUND(100*(AI17-AL17)/ABS(AL17),1)))) -> -
B18: その他の諸材料費 | N18: =IF(H18="-", "-", IF(K18="-", "-", IF(ABS(K18)=0, "-", ROUND(100*(H18-K18)/ABS(K18),1)))) -> - | W18: =IF(Q18="-", "-", IF(T18="-", "-", IF(ABS(T18)=0, "-", ROUND(100*(Q18-T18)/ABS(T18),1)))) -> - | AO18: =IF(AI18="-", "-", IF(AL18="-", "-", IF(ABS(AL18)=0, "-", ROUND(100*(AI18-AL18)/ABS(AL18),1)))) -> -
B19: 獣医師料及び医薬品費 | N19: =IF(H19="-", "-", IF(K19="-", "-", IF(ABS(K19)=0, "-", ROUND(100*(H19-K19)/ABS(K19),1)))) -> - | AO19: =IF(AI19="-", "-", IF(AL19="-", "-", IF(ABS(AL19)=0, "-", ROUND(100*(AI19-AL19)/ABS(AL19),1)))) -> -
B20: 賃借料及び料金 | N20: =IF(H20="-", "-", IF(K20="-", "-", IF(ABS(K20)=0, "-", ROUND(100*(H20-K20)/ABS(K20),1)))) -> - | AO20: =IF(AI20="-", "-", IF(AL20="-", "-", IF(ABS(AL20)=0, "-", ROUND(100*(AI20-AL20)/ABS(AL20),1)))) -> -
B21: 物件税･公課諸負担 | N21: =IF(H21="-", "-", IF(K21="-", "-", IF(ABS(K21)=0, "-", ROUND(100*(H21-K21)/ABS(K21),1)))) -> - | AO21: =IF(AI21="-", "-", IF(AL21="-", "-", IF(ABS(AL21)=0, "-", ROUND(100*(AI21-AL21)/ABS(AL21),1)))) -> -
B22: 繁殖雌豚費 | N22: =IF(H22="-", "-", IF(K22="-", "-", IF(ABS(K22)=0, "-", ROUND(100*(H22-K22)/ABS(K22),1)))) -> - | AO22: =IF(AI22="-", "-", IF(AL22="-", "-", IF(ABS(AL22)=0, "-", ROUND(100*(AI22-AL22)/ABS(AL22),1)))) -> -
B23: 種雄豚費 | N23: =IF(H23="-", "-", IF(K23="-", "-", IF(ABS(K23)=0, "-", ROUND(100*(H23-K23)/ABS(K23),1)))) -> - | AO23: =IF(AI23="-", "-", IF(AL23="-", "-", IF(ABS(AL23)=0, "-", ROUND(100*(AI23-AL23)/ABS(AL23),1)))) -> -
B24: 建物費 | N24: =IF(H24="-", "-", IF(K24="-", "-", IF(ABS(K24)=0, "-", ROUND(100*(H24-K24)/ABS(K24),1)))) -> - | AF24: =IF(Z24="-", "-", IF(AC24="-", "-", IF(ABS(AC24)=0, "-", ROUND(100*(Z24-AC24)/ABS(AC24),1)))) -> - | AO24: =IF(AI24="-", "-", IF(AL24="-", "-", IF(ABS(AL24)=0, "-", ROUND(100*(AI24-AL24)/ABS(AL24),1)))) -> -
B25: 自動車費 | N25: =IF(H25="-", "-", IF(K25="-", "-", IF(ABS(K25)=0, "-", ROUND(100*(H25-K25)/ABS(K25),1)))) -> - | AF25: =IF(Z25="-", "-", IF(AC25="-", "-", IF(ABS(AC25)=0, "-", ROUND(100*(Z25-AC25)/ABS(AC25),1)))) -> - | AO25: =IF(AI25="-", "-", IF(AL25="-", "-", IF(ABS(AL25)=0, "-", ROUND(100*(AI25-AL25)/ABS(AL25),1)))) -> -
B26: 農機具費 | N26: =IF(H26="-", "-", IF(K26="-", "-", IF(ABS(K26)=0, "-", ROUND(100*(H26-K26)/ABS(K26),1)))) -> - | AF26: =IF(Z26="-", "-", IF(AC26="-", "-", IF(ABS(AC26)=0, "-", ROUND(100*(Z26-AC26)/ABS(AC26),1)))) -> - | AO26: =IF(AI26="-", "-", IF(AL26="-", "-", IF(ABS(AL26)=0, "-", ROUND(100*(AI26-AL26)/ABS(AL26),1)))) -> -
B27: 生産管理費 | N27: =IF(H27="-", "-", IF(K27="-", "-", IF(ABS(K27)=0, "-", ROUND(100*(H27-K27)/ABS(K27),1)))) -> - | AF27: =IF(Z27="-", "-", IF(AC27="-", "-", IF(ABS(AC27)=0, "-", ROUND(100*(Z27-AC27)/ABS(AC27),1)))) -> - | AO27: =IF(AI27="-", "-", IF(AL27="-", "-", IF(ABS(AL27)=0, "-", ROUND(100*(AI27-AL27)/ABS(AL27),1)))) -> -
A28: 労働費 | N28: =IF(H28="-", "-", IF(K28="-", "-", IF(ABS(K28)=0, "-", ROUND(100*(H28-K28)/ABS(K28),1)))) -> - | W28: =IF(Q28="-", "-", IF(T28="-", "-", IF(ABS(T28)=0, "-", ROUND(100*(Q28-T28)/ABS(T28),1)))) -> - | AO28: =IF(AI28="-", "-", IF(AL28="-", "-", IF(ABS(AL28)=0, "-", ROUND(100*(AI28-AL28)/ABS(AL28),1)))) -> -
B29: 直接労働費 | N29: =IF(H29="-", "-", IF(K29="-", "-", IF(ABS(K29)=0, "-", ROUND(100*(H29-K29)/ABS(K29),1)))) -> - | W29: =IF(Q29="-", "-", IF(T29="-", "-", IF(ABS(T29)=0, "-", ROUND(100*(Q29-T29)/ABS(T29),1)))) -> - | AO29: =IF(AI29="-", "-", IF(AL29="-", "-", IF(ABS(AL29)=0, "-", ROUND(100*(AI29-AL29)/ABS(AL29),1)))) -> -
B30: 間接労働費 | N30: =IF(H30="-", "-", IF(K30="-", "-", IF(ABS(K30)=0, "-", ROUND(100*(H30-K30)/ABS(K30),1)))) -> - | W30: =IF(Q30="-", "-", IF(T30="-", "-", IF(ABS(T30)=0, "-", ROUND(100*(Q30-T30)/ABS(T30),1)))) -> - | AO30: =IF(AI30="-", "-", IF(AL30="-", "-", IF(ABS(AL30)=0, "-", ROUND(100*(AI30-AL30)/ABS(AL30),1)))) -> -
A31: 費用合計 | N31: =IF(H31="-", "-", IF(K31="-", "-", IF(ABS(K31)=0, "-", ROUND(100*(H31-K31)/ABS(K31),1)))) -> - | W31: =IF(Q31="-", "-", IF(T31="-", "-", IF(ABS(T31)=0, "-", ROUND(100*(Q31-T31)/ABS(T31),1)))) -> - | AF31: =IF(Z31="-", "-", IF(AC31="-", "-", IF(ABS(AC31)=0, "-", ROUND(100*(Z31-AC31)/ABS(AC31),1)))) -> - | AO31: =IF(AI31="-", "-", IF(AL31="-", "-", IF(ABS(AL31)=0, "-", ROUND(100*(AI31-AL31)/ABS(AL31),1)))) -> -
A32: 副産物価額 | AO32: =IF(AI32="-", "-", IF(AL32="-", "-", IF(ABS(AL32)=0, "-", ROUND(100*(AI32-AL32)/ABS(AL32),1)))) -> -
A33: 生産費 | AO33: =IF(AI33="-", "-", IF(AL33="-", "-", IF(ABS(AL33)=0, "-", ROUND(100*(AI33-AL33)/ABS(AL33),1)))) -> -
A34: 支払利子 | AO34: =IF(AI34="-", "-", IF(AL34="-", "-", IF(ABS(AL34)=0, "-", ROUND(100*(AI34-AL34)/ABS(AL34),1)))) -> -
A35: 支払地代 | AO35: =IF(AI35="-", "-", IF(AL35="-", "-", IF(ABS(AL35)=0, "-", ROUND(100*(AI35-AL35)/ABS(AL35),1)))) -> -
A36: 利子･地代算入生産費 | AO36: =IF(AI36="-", "-", IF(AL36="-", "-", IF(ABS(AL36)=0, "-", ROUND(100*(AI36-AL36)/ABS(AL36),1)))) -> -
A37: 自己資本利子 | AO37: =IF(AI37="-", "-", IF(AL37="-", "-", IF(ABS(AL37)=0, "-", ROUND(100*(AI37-AL37)/ABS(AL37),1)))) -> -
A38: 自作地地代 | AO38: =IF(AI38="-", "-", IF(AL38="-", "-", IF(ABS(AL38)=0, "-", ROUND(100*(AI38-AL38)/ABS(AL38),1)))) -> -
A39: 全算入生産費 | AO39: =IF(AI39="-", "-", IF(AL39="-", "-", IF(ABS(AL39)=0, "-", ROUND(100*(AI39-AL39)/ABS(AL39),1)))) -> -

Sheet No.2
A1: =IF(No.1!A1="","",No.1!A1) | C1: 年 組織法人経営体に関する経営分析調査 肥育豚生産費 集計結果検討表 №２
F3: 集計番号 | I3: 集計名称 | T3: 都道府県等 | Y3: 規模階層
A4: 本年 | F4: =IF(No.1!F4="","",No.1!F4) | I4: =IF(No.1!I4="","",No.1!I4) | T4: =IF(No.1!T4="","",No.1!T4) | U4: =IF(No.1!U4="","",No.1!U4) | Y4: =IF(No.1!Y4="","",No.1!Y4) | Z4: =IF(No.1!Z4="","",No.1!Z4)
A5: 前年 | F5: =IF(No.1!F5="","",No.1!F5) | I5: =IF(No.1!I5="","",No.1!I5)
A7: 【生産費総括（生体100kg当たり）】 | AQ7: 単位：円、％
H8: 購 入 | Q8: 内 給 | Z8: 償 却 | AI8: 計
H9: 本年 | K9: 前年 | N9: 増減率 | Q9: 本年 | T9: 前年 | W9: 増減率 | Z9: 本年 | AC9: 前年 | AF9: 増減率 | AI9: 本年 | AL9: 前年 | AO9: 増減率
A10: 物財費 | N10: =IF(H10="-", "-", IF(K10="-", "-", IF(ABS(K10)=0, "-", ROUND(100*(H10-K10)/ABS(K10),1)))) -> - | W10: =IF(Q10="-", "-", IF(T10="-", "-", IF(ABS(T10)=0, "-", ROUND(100*(Q10-T10)/ABS(T10),1)))) -> - | AF10: =IF(Z10="-", "-", IF(AC10="-", "-", IF(ABS(AC10)=0, "-", ROUND(100*(Z10-AC10)/ABS(AC10),1)))) -> - | AO10: =IF(AI10="-", "-", IF(AL10="-", "-", IF(ABS(AL10)=0, "-", ROUND(100*(AI10-AL10)/ABS(AL10),1)))) -> -
B11: 種付料 | N11: =IF(H11="-", "-", IF(K11="-", "-", IF(ABS(K11)=0, "-", ROUND(100*(H11-K11)/ABS(K11),1)))) -> - | AO11: =IF(AI11="-", "-", IF(AL11="-", "-", IF(ABS(AL11)=0, "-", ROUND(100*(AI11-AL11)/ABS(AL11),1)))) -> -
B12: もと畜費 | N12: =IF(H12="-", "-", IF(K12="-", "-", IF(ABS(K12)=0, "-", ROUND(100*(H12-K12)/ABS(K12),1)))) -> - | AO12: =IF(AI12="-", "-", IF(AL12="-", "-", IF(ABS(AL12)=0, "-", ROUND(100*(AI12-AL12)/ABS(AL12),1)))) -> -
B13: 飼料費 | N13: =IF(H13="-", "-", IF(K13="-", "-", IF(ABS(K13)=0, "-", ROUND(100*(H13-K13)/ABS(K13),1)))) -> - | W13: =IF(Q13="-", "-", IF(T13="-", "-", IF(ABS(T13)=0, "-", ROUND(100*(Q13-T13)/ABS(T13),1)))) -> - | AO13: =IF(AI13="-", "-", IF(AL13="-", "-", IF(ABS(AL13)=0, "-", ROUND(100*(AI13-AL13)/ABS(AL13),1)))) -> -
C14: 流通飼料費 | N14: =IF(H14="-", "-", IF(K14="-", "-", IF(ABS(K14)=0, "-", ROUND(100*(H14-K14)/ABS(K14),1)))) -> - | W14: =IF(Q14="-", "-", IF(T14="-", "-", IF(ABS(T14)=0, "-", ROUND(100*(Q14-T14)/ABS(T14),1)))) -> - | AO14: =IF(AI14="-", "-", IF(AL14="-", "-", IF(ABS(AL14)=0, "-", ROUND(100*(AI14-AL14)/ABS(AL14),1)))) -> -
C15: 牧草・放牧・採草費 | W15: =IF(Q15="-", "-", IF(T15="-", "-", IF(ABS(T15)=0, "-", ROUND(100*(Q15-T15)/ABS(T15),1)))) -> - | AO15: =IF(AI15="-", "-", IF(AL15="-", "-", IF(ABS(AL15)=0, "-", ROUND(100*(AI15-AL15)/ABS(AL15),1)))) -> -
B16: 敷料費 | N16: =IF(H16="-", "-", IF(K16="-", "-", IF(ABS(K16)=0, "-", ROUND(100*(H16-K16)/ABS(K16),1)))) -> - | W16: =IF(Q16="-", "-", IF(T16="-", "-", IF(ABS(T16)=0, "-", ROUND(100*(Q16-T16)/ABS(T16),1)))) -> - | AO16: =IF(AI16="-", "-", IF(AL16="-", "-", IF(ABS(AL16)=0, "-", ROUND(100*(AI16-AL16)/ABS(AL16),1)))) -> -
B17: 光熱動力費 | N17: =IF(H17="-", "-", IF(K17="-", "-", IF(ABS(K17)=0, "-", ROUND(100*(H17-K17)/ABS(K17),1)))) -> - | W17: =IF(Q17="-", "-", IF(T17="-", "-", IF(ABS(T17)=0, "-", ROUND(100*(Q17-T17)/ABS(T17),1)))) -> - | AO17: =IF(AI17="-", "-", IF(AL17="-", "-", IF(ABS(AL17)=0, "-", ROUND(100*(AI17-AL17)/ABS(AL17),1)))) -> -
B18: その他の諸材料費 | N18: =IF(H18="-", "-", IF(K18="-", "-", IF(ABS(K18)=0, "-", ROUND(100*(H18-K18)/ABS(K18),1)))) -> - | W18: =IF(Q18="-", "-", IF(T18="-", "-", IF(ABS(T18)=0, "-", ROUND(100*(Q18-T18)/ABS(T18),1)))) -> - | AO18: =IF(AI18="-", "-", IF(AL18="-", "-", IF(ABS(AL18)=0, "-", ROUND(100*(AI18-AL18)/ABS(AL18),1)))) -> -
B19: 獣医師料及び医薬品費 | N19: =IF(H19="-", "-", IF(K19="-", "-", IF(ABS(K19)=0, "-", ROUND(100*(H19-K19)/ABS(K19),1)))) -> - | AO19: =IF(AI19="-", "-", IF(AL19="-", "-", IF(ABS(AL19)=0, "-", ROUND(100*(AI19-AL19)/ABS(AL19),1)))) -> -
B20: 賃借料及び料金 | N20: =IF(H20="-", "-", IF(K20="-", "-", IF(ABS(K20)=0, "-", ROUND(100*(H20-K20)/ABS(K20),1)))) -> - | AO20: =IF(AI20="-", "-", IF(AL20="-", "-", IF(ABS(AL20)=0, "-", ROUND(100*(AI20-AL20)/ABS(AL20),1)))) -> -
B21: 物件税･公課諸負担 | N21: =IF(H21="-", "-", IF(K21="-", "-", IF(ABS(K21)=0, "-", ROUND(100*(H21-K21)/ABS(K21),1)))) -> - | AO21: =IF(AI21="-", "-", IF(AL21="-", "-", IF(ABS(AL21)=0, "-", ROUND(100*(AI21-AL21)/ABS(AL21),1)))) -> -
B22: 繁殖雌豚費 | N22: =IF(H22="-", "-", IF(K22="-", "-", IF(ABS(K22)=0, "-", ROUND(100*(H22-K22)/ABS(K22),1)))) -> - | AO22: =IF(AI22="-", "-", IF(AL22="-", "-", IF(ABS(AL22)=0, "-", ROUND(100*(AI22-AL22)/ABS(AL22),1)))) -> -
B23: 種雄豚費 | N23: =IF(H23="-", "-", IF(K23="-", "-", IF(ABS(K23)=0, "-", ROUND(100*(H23-K23)/ABS(K23),1)))) -> - | AO23: =IF(AI23="-", "-", IF(AL23="-", "-", IF(ABS(AL23)=0, "-", ROUND(100*(AI23-AL23)/ABS(AL23),1)))) -> -
B24: 建物費 | N24: =IF(H24="-", "-", IF(K24="-", "-", IF(ABS(K24)=0, "-", ROUND(100*(H24-K24)/ABS(K24),1)))) -> - | AF24: =IF(Z24="-", "-", IF(AC24="-", "-", IF(ABS(AC24)=0, "-", ROUND(100*(Z24-AC24)/ABS(AC24),1)))) -> - | AO24: =IF(AI24="-", "-", IF(AL24="-", "-", IF(ABS(AL24)=0, "-", ROUND(100*(AI24-AL24)/ABS(AL24),1)))) -> -
B25: 自動車費 | N25: =IF(H25="-", "-", IF(K25="-", "-", IF(ABS(K25)=0, "-", ROUND(100*(H25-K25)/ABS(K25),1)))) -> - | AF25: =IF(Z25="-", "-", IF(AC25="-", "-", IF(ABS(AC25)=0, "-", ROUND(100*(Z25-AC25)/ABS(AC25),1)))) -> - | AO25: =IF(AI25="-", "-", IF(AL25="-", "-", IF(ABS(AL25)=0, "-", ROUND(100*(AI25-AL25)/ABS(AL25),1)))) -> -
B26: 農機具費 | N26: =IF(H26="-", "-", IF(K26="-", "-", IF(ABS(K26)=0, "-", ROUND(100*(H26-K26)/ABS(K26),1)))) -> - | AF26: =IF(Z26="-", "-", IF(AC26="-", "-", IF(ABS(AC26)=0, "-", ROUND(100*(Z26-AC26)/ABS(AC26),1)))) -> - | AO26: =IF(AI26="-", "-", IF(AL26="-", "-", IF(ABS(AL26)=0, "-", ROUND(100*(AI26-AL26)/ABS(AL26),1)))) -> -
B27: 生産管理費 | N27: =IF(H27="-", "-", IF(K27="-", "-", IF(ABS(K27)=0, "-", ROUND(100*(H27-K27)/ABS(K27),1)))) -> - | AF27: =IF(Z27="-", "-", IF(AC27="-", "-", IF(ABS(AC27)=0, "-", ROUND(100*(Z27-AC27)/ABS(AC27),1)))) -> - | AO27: =IF(AI27="-", "-", IF(AL27="-", "-", IF(ABS(AL27)=0, "-", ROUND(100*(AI27-AL27)/ABS(AL27),1)))) -> -
A28: 労働費 | N28: =IF(H28="-", "-", IF(K28="-", "-", IF(ABS(K28)=0, "-", ROUND(100*(H28-K28)/ABS(K28),1)))) -> - | W28: =IF(Q28="-", "-", IF(T28="-", "-", IF(ABS(T28)=0, "-", ROUND(100*(Q28-T28)/ABS(T28),1)))) -> - | AO28: =IF(AI28="-", "-", IF(AL28="-", "-", IF(ABS(AL28)=0, "-", ROUND(100*(AI28-AL28)/ABS(AL28),1)))) -> -
B29: 直接労働費 | N29: =IF(H29="-", "-", IF(K29="-", "-", IF(ABS(K29)=0, "-", ROUND(100*(H29-K29)/ABS(K29),1)))) -> - | W29: =IF(Q29="-", "-", IF(T29="-", "-", IF(ABS(T29)=0, "-", ROUND(100*(Q29-T29)/ABS(T29),1)))) -> - | AO29: =IF(AI29="-", "-", IF(AL29="-", "-", IF(ABS(AL29)=0, "-", ROUND(100*(AI29-AL29)/ABS(AL29),1)))) -> -
B30: 間接労働費 | N30: =IF(H30="-", "-", IF(K30="-", "-", IF(ABS(K30)=0, "-", ROUND(100*(H30-K30)/ABS(K30),1)))) -> - | W30: =IF(Q30="-", "-", IF(T30="-", "-", IF(ABS(T30)=0, "-", ROUND(100*(Q30-T30)/ABS(T30),1)))) -> - | AO30: =IF(AI30="-", "-", IF(AL30="-", "-", IF(ABS(AL30)=0, "-", ROUND(100*(AI30-AL30)/ABS(AL30),1)))) -> -
A31: 費用合計 | N31: =IF(H31="-", "-", IF(K31="-", "-", IF(ABS(K31)=0, "-", ROUND(100*(H31-K31)/ABS(K31),1)))) -> - | W31: =IF(Q31="-", "-", IF(T31="-", "-", IF(ABS(T31)=0, "-", ROUND(100*(Q31-T31)/ABS(T31),1)))) -> - | AF31: =IF(Z31="-", "-", IF(AC31="-", "-", IF(ABS(AC31)=0, "-", ROUND(100*(Z31-AC31)/ABS(AC31),1)))) -> - | AO31: =IF(AI31="-", "-", IF(AL31="-", "-", IF(ABS(AL31)=0, "-", ROUND(100*(AI31-AL31)/ABS(AL31),1)))) -> -
A32: 副産物価額 | AO32: =IF(AI32="-", "-", IF(AL32="-", "-", IF(ABS(AL32)=0, "-", ROUND(100*(AI32-AL32)/ABS(AL32),1)))) -> -
A33: 生産費 | AO33: =IF(AI33="-", "-", IF(AL33="-", "-", IF(ABS(AL33)=0, "-", ROUND(100*(AI33-AL33)/ABS(AL33),1)))) -> -
A34: 支払利子 | AO34: =IF(AI34="-", "-", IF(AL34="-", "-", IF(ABS(AL34)=0, "-", ROUND(100*(AI34-AL34)/ABS(AL34),1)))) -> -
A35: 支払地代 | AO35: =IF(AI35="-", "-", IF(AL35="-", "-", IF(ABS(AL35)=0, "-", ROUND(100*(AI35-AL35)/ABS(AL35),1)))) -> -
A36: 利子･地代算入生産費 | AO36: =IF(AI36="-", "-", IF(AL36="-", "-", IF(ABS(AL36)=0, "-", ROUND(100*(AI36-AL36)/ABS(AL36),1)))) -> -
A37: 自己資本利子 | AO37: =IF(AI37="-", "-", IF(AL37="-", "-", IF(ABS(AL37)=0, "-", ROUND(100*(AI37-AL37)/ABS(AL37),1)))) -> -
A38: 自作地地代 | AO38: =IF(AI38="-", "-", IF(AL38="-", "-", IF(ABS(AL38)=0, "-", ROUND(100*(AI38-AL38)/ABS(AL38),1)))) -> -
A39: 全算入生産費 | AO39: =IF(AI39="-", "-", IF(AL39="-", "-", IF(ABS(AL39)=0, "-", ROUND(100*(AI39-AL39)/ABS(AL39),1)))) -> -

Sheet No.3
A1: =IF(No.1!A1="","",No.1!A1) | C1: 年 組織法人経営体に関する経営分析調査 肥育豚生産費 集計結果検討表 №３
F3: 集計番号 | I3: 集計名称 | T3: 都道府県等 | Y3: 規模階層
A4: 本年 | F4: =IF(No.1!F4="","",No.1!F4) | I4: =IF(No.1!I4="","",No.1!I4) | T4: =IF(No.1!T4="","",No.1!T4) | U4: =IF(No.1!U4="","",No.1!U4) | Y4: =IF(No.1!Y4="","",No.1!Y4) | Z4: =IF(No.1!Z4="","",No.1!Z4)
A5: 前年 | F5: =IF(No.1!F5="","",No.1!F5) | I5: =IF(No.1!I5="","",No.1!I5)
A7: 肥育豚１頭当たり
A8: 【構成員数等】 | P8: 単位：人、戸、％ | AK8: 【資本額】 | AZ8: 単位：円、％
H9: １経営体当たり | AR9: 本年 | AU9: 前年 | AX9: 増減率
H10: 本年 | K10: 前年 | N10: 増減率 | AK10: 計 | AX10: =IF(AR10="-", "-", IF(AU10="-", "-", IF(ABS(AU10)=0, "-", ROUND(100*(AR10-AU10)/ABS(AU10),1)))) -> -
A11: 構成員 | N11: =IF(H11="-", "-", IF(K11="-", "-", IF(ABS(K11)=0, "-", ROUND(100*(H11-K11)/ABS(K11),1)))) -> - | AL11: 借入資本 | AX11: =IF(AR11="-", "-", IF(AU11="-", "-", IF(ABS(AU11)=0, "-", ROUND(100*(AR11-AU11)/ABS(AU11),1)))) -> -
A12: 農業年雇 | N12: =IF(H12="-", "-", IF(K12="-", "-", IF(ABS(K12)=0, "-", ROUND(100*(H12-K12)/ABS(K12),1)))) -> - | AL12: 自己資本 | AX12: =IF(AR12="-", "-", IF(AU12="-", "-", IF(ABS(AU12)=0, "-", ROUND(100*(AR12-AU12)/ABS(AU12),1)))) -> -
A13: 構成農家世帯 | N13: =IF(H13="-", "-", IF(K13="-", "-", IF(ABS(K13)=0, "-", ROUND(100*(H13-K13)/ABS(K13),1)))) -> - | AK13: 資産別内訳 | AL13: 流動資本 | AX13: =IF(AR13="-", "-", IF(AU13="-", "-", IF(ABS(AU13)=0, "-", ROUND(100*(AR13-AU13)/ABS(AU13),1)))) -> -
AL14: 労賃資本 | AX14: =IF(AR14="-", "-", IF(AU14="-", "-", IF(ABS(AU14)=0, "-", ROUND(100*(AR14-AU14)/ABS(AU14),1)))) -> -
AL15: 固定資本 | AX15: =IF(AR15="-", "-", IF(AU15="-", "-", IF(ABS(AU15)=0, "-", ROUND(100*(AR15-AU15)/ABS(AU15),1)))) -> -
AM16: 建物 | AX16: =IF(AR16="-", "-", IF(AU16="-", "-", IF(ABS(AU16)=0, "-", ROUND(100*(AR16-AU16)/ABS(AU16),1)))) -> -
A17: 【経営耕地（調査開始時）】１経営体当たり | AH17: 単位：ａ、％ | AM17: 自動車 | AX17: =IF(AR17="-", "-", IF(AU17="-", "-", IF(ABS(AU17)=0, "-", ROUND(100*(AR17-AU17)/ABS(AU17),1)))) -> -
H18: 所 有 地 | Q18: 借 入 地 | Z18: 計 | AM18: 農機具 | AX18: =IF(AR18="-", "-", IF(AU18="-", "-", IF(ABS(AU18)=0, "-", ROUND(100*(AR18-AU18)/ABS(AU18),1)))) -> -
H19: 本年 | K19: 前年 | N19: 増減率 | Q19: 本年 | T19: 前年 | W19: 増減率 | Z19: 本年 | AC19: 前年 | AF19: 増減率
A20: 田 | N20: =IF(H20="-", "-", IF(K20="-", "-", IF(ABS(K20)=0, "-", ROUND(100*(H20-K20)/ABS(K20),1)))) -> - | W20: =IF(Q20="-", "-", IF(T20="-", "-", IF(ABS(T20)=0, "-", ROUND(100*(Q20-T20)/ABS(T20),1)))) -> - | AF20: =IF(Z20="-", "-", IF(AC20="-", "-", IF(ABS(AC20)=0, "-", ROUND(100*(Z20-AC20)/ABS(AC20),1)))) -> - | AK20: 【資本利子】 | AZ20: 単位：円、％
A21: 普通畑 | N21: =IF(H21="-", "-", IF(K21="-", "-", IF(ABS(K21)=0, "-", ROUND(100*(H21-K21)/ABS(K21),1)))) -> - | W21: =IF(Q21="-", "-", IF(T21="-", "-", IF(ABS(T21)=0, "-", ROUND(100*(Q21-T21)/ABS(T21),1)))) -> - | AF21: =IF(Z21="-", "-", IF(AC21="-", "-", IF(ABS(AC21)=0, "-", ROUND(100*(Z21-AC21)/ABS(AC21),1)))) -> - | AR21: 本年 | AU21: 前年 | AX21: 増減率
A22: 樹園地 | N22: =IF(H22="-", "-", IF(K22="-", "-", IF(ABS(K22)=0, "-", ROUND(100*(H22-K22)/ABS(K22),1)))) -> - | W22: =IF(Q22="-", "-", IF(T22="-", "-", IF(ABS(T22)=0, "-", ROUND(100*(Q22-T22)/ABS(T22),1)))) -> - | AF22: =IF(Z22="-", "-", IF(AC22="-", "-", IF(ABS(AC22)=0, "-", ROUND(100*(Z22-AC22)/ABS(AC22),1)))) -> - | AK22: 計 | AX22: =IF(AR22="-", "-", IF(AU22="-", "-", IF(ABS(AU22)=0, "-", ROUND(100*(AR22-AU22)/ABS(AU22),1)))) -> -
A23: 牧草地 | N23: =IF(H23="-", "-", IF(K23="-", "-", IF(ABS(K23)=0, "-", ROUND(100*(H23-K23)/ABS(K23),1)))) -> - | W23: =IF(Q23="-", "-", IF(T23="-", "-", IF(ABS(T23)=0, "-", ROUND(100*(Q23-T23)/ABS(T23),1)))) -> - | AF23: =IF(Z23="-", "-", IF(AC23="-", "-", IF(ABS(AC23)=0, "-", ROUND(100*(Z23-AC23)/ABS(AC23),1)))) -> - | AL23: 支払利子 | AX23: =IF(AR23="-", "-", IF(AU23="-", "-", IF(ABS(AU23)=0, "-", ROUND(100*(AR23-AU23)/ABS(AU23),1)))) -> -
A24: 計 | N24: =IF(H24="-", "-", IF(K24="-", "-", IF(ABS(K24)=0, "-", ROUND(100*(H24-K24)/ABS(K24),1)))) -> - | W24: =IF(Q24="-", "-", IF(T24="-", "-", IF(ABS(T24)=0, "-", ROUND(100*(Q24-T24)/ABS(T24),1)))) -> - | AF24: =IF(Z24="-", "-", IF(AC24="-", "-", IF(ABS(AC24)=0, "-", ROUND(100*(Z24-AC24)/ABS(AC24),1)))) -> - | AL24: 自己資本利子 | AX24: =IF(AR24="-", "-", IF(AU24="-", "-", IF(ABS(AU24)=0, "-", ROUND(100*(AR24-AU24)/ABS(AU24),1)))) -> -
A27: 【肉豚の月始め飼養頭数（肥育豚＋子豚）】 | S27: 【繁殖豚の飼養状況（年始め飼養頭数）】 | AK27: 【分べん状況】１経営体当たり | AZ27: 単位：頭、％
A28: １経営体当たり | P28: 単位：頭、％ | S28: １経営体当たり | AH28: 単位：頭、％ | AR28: 本年 | AU28: 前年 | AX28: 増減率
H29: 本年 | K29: 前年 | N29: 増減率 | Z29: 本年 | AC29: 前年 | AF29: 増減率 | AK29: 分べんした繁殖雌豚頭数 | AX29: =IF(AR29="-", "-", IF(AU29="-", "-", IF(ABS(AU29)=0, "-", ROUND(100*(AR29-AU29)/ABS(AU29),1)))) -> -
A30: 月 | N30: =IF(H30="-", "-", IF(K30="-", "-", IF(ABS(K30)=0, "-", ROUND(100*(H30-K30)/ABS(K30),1)))) -> - | S30: 繁殖雌豚 | AF30: =IF(Z30="-", "-", IF(AC30="-", "-", IF(ABS(AC30)=0, "-", ROUND(100*(Z30-AC30)/ABS(AC30),1)))) -> - | AK30: 子豚の分べん頭数 | AX30: =IF(AR30="-", "-", IF(AU30="-", "-", IF(ABS(AU30)=0, "-", ROUND(100*(AR30-AU30)/ABS(AU30),1)))) -> -
A31: 月 | N31: =IF(H31="-", "-", IF(K31="-", "-", IF(ABS(K31)=0, "-", ROUND(100*(H31-K31)/ABS(K31),1)))) -> - | S31: 種雄豚 | AF31: =IF(Z31="-", "-", IF(AC31="-", "-", IF(ABS(AC31)=0, "-", ROUND(100*(Z31-AC31)/ABS(AC31),1)))) -> -
A32: 月 | N32: =IF(H32="-", "-", IF(K32="-", "-", IF(ABS(K32)=0, "-", ROUND(100*(H32-K32)/ABS(K32),1)))) -> - | S32: 後継繁殖雌豚 | AF32: =IF(Z32="-", "-", IF(AC32="-", "-", IF(ABS(AC32)=0, "-", ROUND(100*(Z32-AC32)/ABS(AC32),1)))) -> - | AK32: 【子豚の導入頭数】１経営体当たり | AZ32: 単位：頭、％
A33: 月 | N33: =IF(H33="-", "-", IF(K33="-", "-", IF(ABS(K33)=0, "-", ROUND(100*(H33-K33)/ABS(K33),1)))) -> - | S33: 後継種雄豚 | AF33: =IF(Z33="-", "-", IF(AC33="-", "-", IF(ABS(AC33)=0, "-", ROUND(100*(Z33-AC33)/ABS(AC33),1)))) -> - | AR33: 本年 | AU33: 前年 | AX33: 増減率
A34: 月 | N34: =IF(H34="-", "-", IF(K34="-", "-", IF(ABS(K34)=0, "-", ROUND(100*(H34-K34)/ABS(K34),1)))) -> - | AK34: 子豚導入頭数 | AX34: =IF(AR34="-", "-", IF(AU34="-", "-", IF(ABS(AU34)=0, "-", ROUND(100*(AR34-AU34)/ABS(AU34),1)))) -> -
A35: 月 | N35: =IF(H35="-", "-", IF(K35="-", "-", IF(ABS(K35)=0, "-", ROUND(100*(H35-K35)/ABS(K35),1)))) -> -
A36: 月 | N36: =IF(H36="-", "-", IF(K36="-", "-", IF(ABS(K36)=0, "-", ROUND(100*(H36-K36)/ABS(K36),1)))) -> -
A37: 月 | N37: =IF(H37="-", "-", IF(K37="-", "-", IF(ABS(K37)=0, "-", ROUND(100*(H37-K37)/ABS(K37),1)))) -> -
A38: 月 | N38: =IF(H38="-", "-", IF(K38="-", "-", IF(ABS(K38)=0, "-", ROUND(100*(H38-K38)/ABS(K38),1)))) -> -
A39: 月 | N39: =IF(H39="-", "-", IF(K39="-", "-", IF(ABS(K39)=0, "-", ROUND(100*(H39-K39)/ABS(K39),1)))) -> -
A40: 月 | N40: =IF(H40="-", "-", IF(K40="-", "-", IF(ABS(K40)=0, "-", ROUND(100*(H40-K40)/ABS(K40),1)))) -> -
A41: 月 | N41: =IF(H41="-", "-", IF(K41="-", "-", IF(ABS(K41)=0, "-", ROUND(100*(H41-K41)/ABS(K41),1)))) -> -
A42: 計 | N42: =IF(H42="-", "-", IF(K42="-", "-", IF(ABS(K42)=0, "-", ROUND(100*(H42-K42)/ABS(K42),1)))) -> -
A43: 飼養月平均頭数 | N43: =IF(H43="-", "-", IF(K43="-", "-", IF(ABS(K43)=0, "-", ROUND(100*(H43-K43)/ABS(K43),1)))) -> -

Sheet No.4
A1: =IF(No.1!A1="","",No.1!A1) | C1: 年 組織法人経営体に関する経営分析調査 肥育豚生産費 集計結果検討表 №４
F3: 集計番号 | I3: 集計名称 | T3: 都道府県等 | Y3: 規模階層
A4: 本年 | F4: =IF(No.1!F4="","",No.1!F4) | I4: =IF(No.1!I4="","",No.1!I4) | T4: =IF(No.1!T4="","",No.1!T4) | U4: =IF(No.1!U4="","",No.1!U4) | Y4: =IF(No.1!Y4="","",No.1!Y4) | Z4: =IF(No.1!Z4="","",No.1!Z4)
A5: 前年 | F5: =IF(No.1!F5="","",No.1!F5) | I5: =IF(No.1!I5="","",No.1!I5)
A7: 肥育豚１頭当たり
A8: 【主産物の概要】 | P8: 単位：頭、kg、円、月、％ | AK8: 【〔参考１〕収益性等】 | AZ8: 単位：円、％
H9: 計 | AR9: 本年 | AU9: 前年 | AX9: 増減率
H10: 本年 | K10: 前年 | N10: 増減率 | AK10: 粗収益 | AX10: =IF(AR10="-", "-", IF(AU10="-", "-", IF(ABS(AU10)=0, "-", ROUND(100*(AR10-AU10)/ABS(AU10),1)))) -> -
A11: 販売 | B11: 総頭数 | N11: =IF(H11="-", "-", IF(K11="-", "-", IF(ABS(K11)=0, "-", ROUND(100*(H11-K11)/ABS(K11),1)))) -> - | AK11: 生産費総額 | AX11: =IF(AR11="-", "-", IF(AU11="-", "-", IF(ABS(AU11)=0, "-", ROUND(100*(AR11-AU11)/ABS(AU11),1)))) -> -
B12: 月齢 | N12: =IF(H12="-", "-", IF(K12="-", "-", IF(ABS(K12)=0, "-", ROUND(100*(H12-K12)/ABS(K12),1)))) -> - | AK12: 利潤 | AX12: =IF(AR12="-", "-", IF(AU12="-", "-", IF(ABS(AU12)=0, "-", ROUND(100*(AR12-AU12)/ABS(AU12),1)))) -> -
B13: 生体重 | N13: =IF(H13="-", "-", IF(K13="-", "-", IF(ABS(K13)=0, "-", ROUND(100*(H13-K13)/ABS(K13),1)))) -> - | AK13: 所得 | AX13: =IF(AR13="-", "-", IF(AU13="-", "-", IF(ABS(AU13)=0, "-", ROUND(100*(AR13-AU13)/ABS(AU13),1)))) -> -
B14: 評価額 | N14: =IF(H14="-", "-", IF(K14="-", "-", IF(ABS(K14)=0, "-", ROUND(100*(H14-K14)/ABS(K14),1)))) -> - | AL14: １日当たり | AX14: =IF(AR14="-", "-", IF(AU14="-", "-", IF(ABS(AU14)=0, "-", ROUND(100*(AR14-AU14)/ABS(AU14),1)))) -> -
A15: 死亡・とうた頭数 | N15: =IF(H15="-", "-", IF(K15="-", "-", IF(ABS(K15)=0, "-", ROUND(100*(H15-K15)/ABS(K15),1)))) -> - | AK15: 構成員労働報酬 | AX15: =IF(AR15="-", "-", IF(AU15="-", "-", IF(ABS(AU15)=0, "-", ROUND(100*(AR15-AU15)/ABS(AU15),1)))) -> -
A16: 注：販売総頭数、死亡・とうた頭数は１経営体当たり | AL16: １日当たり | AX16: =IF(AR16="-", "-", IF(AU16="-", "-", IF(ABS(AU16)=0, "-", ROUND(100*(AR16-AU16)/ABS(AU16),1)))) -> -
A18: 【副産物】 | AH18: 単位：㎏、頭、円、％ | AK18: 【〔参考２〕消費税】 | AZ18: 単位：円、％
H19: 数 量 | Q19: 価 額 | Z19: 単 価 | AR19: 本年 | AU19: 前年 | AX19: 増減率
H20: 本年 | K20: 前年 | N20: 増減率 | Q20: 本年 | T20: 前年 | W20: 増減率 | Z20: 本年 | AC20: 前年 | AF20: 増減率 | AK20: 消費税 | AX20: =IF(AR20="-", "-", IF(AU20="-", "-", IF(ABS(AU20)=0, "-", ROUND(100*(AR20-AU20)/ABS(AU20),1)))) -> -
A21: きゅう肥 | B21: 利用計 | N21: =IF(H21="-", "-", IF(K21="-", "-", IF(ABS(K21)=0, "-", ROUND(100*(H21-K21)/ABS(K21),1)))) -> - | W21: =IF(Q21="-", "-", IF(T21="-", "-", IF(ABS(T21)=0, "-", ROUND(100*(Q21-T21)/ABS(T21),1)))) -> - | AF21: =IF(Z21="-", "-", IF(AC21="-", "-", IF(ABS(AC21)=0, "-", ROUND(100*(Z21-AC21)/ABS(AC21),1)))) -> -
C22: 販売 | N22: =IF(H22="-", "-", IF(K22="-", "-", IF(ABS(K22)=0, "-", ROUND(100*(H22-K22)/ABS(K22),1)))) -> - | W22: =IF(Q22="-", "-", IF(T22="-", "-", IF(ABS(T22)=0, "-", ROUND(100*(Q22-T22)/ABS(T22),1)))) -> - | AF22: =IF(Z22="-", "-", IF(AC22="-", "-", IF(ABS(AC22)=0, "-", ROUND(100*(Z22-AC22)/ABS(AC22),1)))) -> -
C23: 組織内利用 | N23: =IF(H23="-", "-", IF(K23="-", "-", IF(ABS(K23)=0, "-", ROUND(100*(H23-K23)/ABS(K23),1)))) -> - | W23: =IF(Q23="-", "-", IF(T23="-", "-", IF(ABS(T23)=0, "-", ROUND(100*(Q23-T23)/ABS(T23),1)))) -> - | AF23: =IF(Z23="-", "-", IF(AC23="-", "-", IF(ABS(AC23)=0, "-", ROUND(100*(Z23-AC23)/ABS(AC23),1)))) -> -
B24: その他数量 | N24: =IF(H24="-", "-", IF(K24="-", "-", IF(ABS(K24)=0, "-", ROUND(100*(H24-K24)/ABS(K24),1)))) -> -
B25: 搬出量 | N25: =IF(H25="-", "-", IF(K25="-", "-", IF(ABS(K25)=0, "-", ROUND(100*(H25-K25)/ABS(K25),1)))) -> -
A26: 事故畜 | N26: =IF(H26="-", "-", IF(K26="-", "-", IF(ABS(K26)=0, "-", ROUND(100*(H26-K26)/ABS(K26),1)))) -> - | W26: =IF(Q26="-", "-", IF(T26="-", "-", IF(ABS(T26)=0, "-", ROUND(100*(Q26-T26)/ABS(T26),1)))) -> - | AF26: =IF(Z26="-", "-", IF(AC26="-", "-", IF(ABS(AC26)=0, "-", ROUND(100*(Z26-AC26)/ABS(AC26),1)))) -> -
A27: 繁殖雌豚 | N27: =IF(H27="-", "-", IF(K27="-", "-", IF(ABS(K27)=0, "-", ROUND(100*(H27-K27)/ABS(K27),1)))) -> - | W27: =IF(Q27="-", "-", IF(T27="-", "-", IF(ABS(T27)=0, "-", ROUND(100*(Q27-T27)/ABS(T27),1)))) -> - | AF27: =IF(Z27="-", "-", IF(AC27="-", "-", IF(ABS(AC27)=0, "-", ROUND(100*(Z27-AC27)/ABS(AC27),1)))) -> -
A28: 種雄豚 | N28: =IF(H28="-", "-", IF(K28="-", "-", IF(ABS(K28)=0, "-", ROUND(100*(H28-K28)/ABS(K28),1)))) -> - | W28: =IF(Q28="-", "-", IF(T28="-", "-", IF(ABS(T28)=0, "-", ROUND(100*(Q28-T28)/ABS(T28),1)))) -> - | AF28: =IF(Z28="-", "-", IF(AC28="-", "-", IF(ABS(AC28)=0, "-", ROUND(100*(Z28-AC28)/ABS(AC28),1)))) -> -
A29: 子豚 | N29: =IF(H29="-", "-", IF(K29="-", "-", IF(ABS(K29)=0, "-", ROUND(100*(H29-K29)/ABS(K29),1)))) -> - | W29: =IF(Q29="-", "-", IF(T29="-", "-", IF(ABS(T29)=0, "-", ROUND(100*(Q29-T29)/ABS(T29),1)))) -> - | AF29: =IF(Z29="-", "-", IF(AC29="-", "-", IF(ABS(AC29)=0, "-", ROUND(100*(Z29-AC29)/ABS(AC29),1)))) -> -
A30: 計 | W30: =IF(Q30="-", "-", IF(T30="-", "-", IF(ABS(T30)=0, "-", ROUND(100*(Q30-T30)/ABS(T30),1)))) -> -

Sheet No.5
A1: =IF(No.1!A1="","",No.1!A1) | C1: 年 組織法人経営体に関する経営分析調査 肥育豚生産費 集計結果検討表 №５
F3: 集計番号 | I3: 集計名称 | T3: 都道府県等 | Y3: 規模階層
A4: 本年 | F4: =IF(No.1!F4="","",No.1!F4) | I4: =IF(No.1!I4="","",No.1!I4) | T4: =IF(No.1!T4="","",No.1!T4) | U4: =IF(No.1!U4="","",No.1!U4) | Y4: =IF(No.1!Y4="","",No.1!Y4) | Z4: =IF(No.1!Z4="","",No.1!Z4)
A5: 前年 | F5: =IF(No.1!F5="","",No.1!F5) | I5: =IF(No.1!I5="","",No.1!I5)
A7: 肥育豚１頭当たり
A8: 【流通飼料（購入飼料）の給与量と価額】 | AQ8: 単位：㎏、円、％
H9: 数 量 | Q9: 価 額 | Z9: 単 価 | AI9: TDN換算率 | AL9: TDN換算量
H10: 本年 | K10: 前年 | N10: 増減率 | Q10: 本年 | T10: 前年 | W10: 増減率 | Z10: 本年 | AC10: 前年 | AF10: 増減率 | AL10: 本年 | AO10: 前年
A11: 穀類計 | N11: =IF(H11="-", "-", IF(K11="-", "-", IF(ABS(K11)=0, "-", ROUND(100*(H11-K11)/ABS(K11),1)))) -> - | W11: =IF(Q11="-", "-", IF(T11="-", "-", IF(ABS(T11)=0, "-", ROUND(100*(Q11-T11)/ABS(T11),1)))) -> -
B12: 大麦 | N12: =IF(H12="-", "-", IF(K12="-", "-", IF(ABS(K12)=0, "-", ROUND(100*(H12-K12)/ABS(K12),1)))) -> - | W12: =IF(Q12="-", "-", IF(T12="-", "-", IF(ABS(T12)=0, "-", ROUND(100*(Q12-T12)/ABS(T12),1)))) -> - | AF12: =IF(Z12="-", "-", IF(AC12="-", "-", IF(ABS(AC12)=0, "-", ROUND(100*(Z12-AC12)/ABS(AC12),1)))) -> - | AI12: 70.6
B13: その他の麦 | N13: =IF(H13="-", "-", IF(K13="-", "-", IF(ABS(K13)=0, "-", ROUND(100*(H13-K13)/ABS(K13),1)))) -> - | W13: =IF(Q13="-", "-", IF(T13="-", "-", IF(ABS(T13)=0, "-", ROUND(100*(Q13-T13)/ABS(T13),1)))) -> - | AF13: =IF(Z13="-", "-", IF(AC13="-", "-", IF(ABS(AC13)=0, "-", ROUND(100*(Z13-AC13)/ABS(AC13),1)))) -> - | AI13: 70.4
B14: とうもろこし | N14: =IF(H14="-", "-", IF(K14="-", "-", IF(ABS(K14)=0, "-", ROUND(100*(H14-K14)/ABS(K14),1)))) -> - | W14: =IF(Q14="-", "-", IF(T14="-", "-", IF(ABS(T14)=0, "-", ROUND(100*(Q14-T14)/ABS(T14),1)))) -> - | AF14: =IF(Z14="-", "-", IF(AC14="-", "-", IF(ABS(AC14)=0, "-", ROUND(100*(Z14-AC14)/ABS(AC14),1)))) -> - | AI14: 80.8
B15: 飼料用米 | N15: =IF(H15="-", "-", IF(K15="-", "-", IF(ABS(K15)=0, "-", ROUND(100*(H15-K15)/ABS(K15),1)))) -> - | W15: =IF(Q15="-", "-", IF(T15="-", "-", IF(ABS(T15)=0, "-", ROUND(100*(Q15-T15)/ABS(T15),1)))) -> - | AF15: =IF(Z15="-", "-", IF(AC15="-", "-", IF(ABS(AC15)=0, "-", ROUND(100*(Z15-AC15)/ABS(AC15),1)))) -> - | AI15: 82
B16: その他 | N16: =IF(H16="-", "-", IF(K16="-", "-", IF(ABS(K16)=0, "-", ROUND(100*(H16-K16)/ABS(K16),1)))) -> - | W16: =IF(Q16="-", "-", IF(T16="-", "-", IF(ABS(T16)=0, "-", ROUND(100*(Q16-T16)/ABS(T16),1)))) -> - | AF16: =IF(Z16="-", "-", IF(AC16="-", "-", IF(ABS(AC16)=0, "-", ROUND(100*(Z16-AC16)/ABS(AC16),1)))) -> - | AI16: 79.6
A17: ぬか・ふすま計 | N17: =IF(H17="-", "-", IF(K17="-", "-", IF(ABS(K17)=0, "-", ROUND(100*(H17-K17)/ABS(K17),1)))) -> - | W17: =IF(Q17="-", "-", IF(T17="-", "-", IF(ABS(T17)=0, "-", ROUND(100*(Q17-T17)/ABS(T17),1)))) -> -
B18: ふすま | N18: =IF(H18="-", "-", IF(K18="-", "-", IF(ABS(K18)=0, "-", ROUND(100*(H18-K18)/ABS(K18),1)))) -> - | W18: =IF(Q18="-", "-", IF(T18="-", "-", IF(ABS(T18)=0, "-", ROUND(100*(Q18-T18)/ABS(T18),1)))) -> - | AF18: =IF(Z18="-", "-", IF(AC18="-", "-", IF(ABS(AC18)=0, "-", ROUND(100*(Z18-AC18)/ABS(AC18),1)))) -> - | AI18: 68.3
B19: その他 | N19: =IF(H19="-", "-", IF(K19="-", "-", IF(ABS(K19)=0, "-", ROUND(100*(H19-K19)/ABS(K19),1)))) -> - | W19: =IF(Q19="-", "-", IF(T19="-", "-", IF(ABS(T19)=0, "-", ROUND(100*(Q19-T19)/ABS(T19),1)))) -> - | AF19: =IF(Z19="-", "-", IF(AC19="-", "-", IF(ABS(AC19)=0, "-", ROUND(100*(Z19-AC19)/ABS(AC19),1)))) -> - | AI19: 63
A20: 植物性かす類 | N20: =IF(H20="-", "-", IF(K20="-", "-", IF(ABS(K20)=0, "-", ROUND(100*(H20-K20)/ABS(K20),1)))) -> - | W20: =IF(Q20="-", "-", IF(T20="-", "-", IF(ABS(T20)=0, "-", ROUND(100*(Q20-T20)/ABS(T20),1)))) -> - | AF20: =IF(Z20="-", "-", IF(AC20="-", "-", IF(ABS(AC20)=0, "-", ROUND(100*(Z20-AC20)/ABS(AC20),1)))) -> - | AI20: 71.1
A21: 配合飼料 | N21: =IF(H21="-", "-", IF(K21="-", "-", IF(ABS(K21)=0, "-", ROUND(100*(H21-K21)/ABS(K21),1)))) -> - | W21: =IF(Q21="-", "-", IF(T21="-", "-", IF(ABS(T21)=0, "-", ROUND(100*(Q21-T21)/ABS(T21),1)))) -> - | AF21: =IF(Z21="-", "-", IF(AC21="-", "-", IF(ABS(AC21)=0, "-", ROUND(100*(Z21-AC21)/ABS(AC21),1)))) -> - | AI21: 76.4
A22: エコフィード | N22: =IF(H22="-", "-", IF(K22="-", "-", IF(ABS(K22)=0, "-", ROUND(100*(H22-K22)/ABS(K22),1)))) -> - | W22: =IF(Q22="-", "-", IF(T22="-", "-", IF(ABS(T22)=0, "-", ROUND(100*(Q22-T22)/ABS(T22),1)))) -> - | AF22: =IF(Z22="-", "-", IF(AC22="-", "-", IF(ABS(AC22)=0, "-", ROUND(100*(Z22-AC22)/ABS(AC22),1)))) -> - | AI22: 51.8
A23: 脱脂乳 | N23: =IF(H23="-", "-", IF(K23="-", "-", IF(ABS(K23)=0, "-", ROUND(100*(H23-K23)/ABS(K23),1)))) -> - | W23: =IF(Q23="-", "-", IF(T23="-", "-", IF(ABS(T23)=0, "-", ROUND(100*(Q23-T23)/ABS(T23),1)))) -> - | AF23: =IF(Z23="-", "-", IF(AC23="-", "-", IF(ABS(AC23)=0, "-", ROUND(100*(Z23-AC23)/ABS(AC23),1)))) -> - | AI23: 82.7
A24: いも類及び野菜類 | N24: =IF(H24="-", "-", IF(K24="-", "-", IF(ABS(K24)=0, "-", ROUND(100*(H24-K24)/ABS(K24),1)))) -> - | W24: =IF(Q24="-", "-", IF(T24="-", "-", IF(ABS(T24)=0, "-", ROUND(100*(Q24-T24)/ABS(T24),1)))) -> - | AF24: =IF(Z24="-", "-", IF(AC24="-", "-", IF(ABS(AC24)=0, "-", ROUND(100*(Z24-AC24)/ABS(AC24),1)))) -> - | AI24: 12.3
A25: その他 | W25: =IF(Q25="-", "-", IF(T25="-", "-", IF(ABS(T25)=0, "-", ROUND(100*(Q25-T25)/ABS(T25),1)))) -> -
A26: 合計 | W26: =IF(Q26="-", "-", IF(T26="-", "-", IF(ABS(T26)=0, "-", ROUND(100*(Q26-T26)/ABS(T26),1)))) -> -
AI27: 計 | AL27: =SUM(AL28:AN29) -> 0 | AO27: =SUM(AO28:AQ29) -> 0
A28: 【流通飼料（内給飼料）の給与量と価額】 | P28: 単位：円、％ | AI28: 濃厚飼料 | AL28: =SUM(AL12:AL16,AL18:AL23) -> 0 | AO28: =SUM(AO12:AO16,AO18:AO23) -> 0
H29: 本年 | K29: 前年 | N29: 増減率 | AI29: 粗飼料 | AL29: =SUM(AL24) -> 0 | AO29: =SUM(AO24) -> 0
A30: 価額 | N30: =IF(H30="-", "-", IF(K30="-", "-", IF(ABS(K30)=0, "-", ROUND(100*(H30-K30)/ABS(K30),1)))) -> -
A33: 【地代】 | AZ33: 単位：ａ、円、％
H34: 建物敷地 | Q34: 運 動 場 | Z34: 牧草栽培 | AI34: 採 草 地 | AR34: 計
H35: 本年 | K35: 前年 | N35: 増減率 | Q35: 本年 | T35: 前年 | W35: 増減率 | Z35: 本年 | AC35: 前年 | AF35: 増減率 | AI35: 本年 | AL35: 前年 | AO35: 増減率 | AR35: 本年 | AU35: 前年 | AX35: 増減率
A36: 所有地 | B36: 使用地面積 | N36: =IF(H36="-", "-", IF(K36="-", "-", IF(ABS(K36)=0, "-", ROUND(100*(H36-K36)/ABS(K36),1)))) -> - | W36: =IF(Q36="-", "-", IF(T36="-", "-", IF(ABS(T36)=0, "-", ROUND(100*(Q36-T36)/ABS(T36),1)))) -> - | AF36: =IF(Z36="-", "-", IF(AC36="-", "-", IF(ABS(AC36)=0, "-", ROUND(100*(Z36-AC36)/ABS(AC36),1)))) -> - | AO36: =IF(AI36="-", "-", IF(AL36="-", "-", IF(ABS(AL36)=0, "-", ROUND(100*(AI36-AL36)/ABS(AL36),1)))) -> - | AX36: =IF(AR36="-", "-", IF(AU36="-", "-", IF(ABS(AU36)=0, "-", ROUND(100*(AR36-AU36)/ABS(AU36),1)))) -> -
B37: 10ａ当たり地代 | N37: =IF(H37="-", "-", IF(K37="-", "-", IF(ABS(K37)=0, "-", ROUND(100*(H37-K37)/ABS(K37),1)))) -> - | W37: =IF(Q37="-", "-", IF(T37="-", "-", IF(ABS(T37)=0, "-", ROUND(100*(Q37-T37)/ABS(T37),1)))) -> - | AF37: =IF(Z37="-", "-", IF(AC37="-", "-", IF(ABS(AC37)=0, "-", ROUND(100*(Z37-AC37)/ABS(AC37),1)))) -> - | AO37: =IF(AI37="-", "-", IF(AL37="-", "-", IF(ABS(AL37)=0, "-", ROUND(100*(AI37-AL37)/ABS(AL37),1)))) -> - | AX37: =IF(AR37="-", "-", IF(AU37="-", "-", IF(ABS(AU37)=0, "-", ROUND(100*(AR37-AU37)/ABS(AU37),1)))) -> -
B38: 対象畜負担地代 | N38: =IF(H38="-", "-", IF(K38="-", "-", IF(ABS(K38)=0, "-", ROUND(100*(H38-K38)/ABS(K38),1)))) -> - | W38: =IF(Q38="-", "-", IF(T38="-", "-", IF(ABS(T38)=0, "-", ROUND(100*(Q38-T38)/ABS(T38),1)))) -> - | AF38: =IF(Z38="-", "-", IF(AC38="-", "-", IF(ABS(AC38)=0, "-", ROUND(100*(Z38-AC38)/ABS(AC38),1)))) -> - | AO38: =IF(AI38="-", "-", IF(AL38="-", "-", IF(ABS(AL38)=0, "-", ROUND(100*(AI38-AL38)/ABS(AL38),1)))) -> - | AX38: =IF(AR38="-", "-", IF(AU38="-", "-", IF(ABS(AU38)=0, "-", ROUND(100*(AR38-AU38)/ABS(AU38),1)))) -> -
A39: 借入地 | B39: 使用地面積 | N39: =IF(H39="-", "-", IF(K39="-", "-", IF(ABS(K39)=0, "-", ROUND(100*(H39-K39)/ABS(K39),1)))) -> - | W39: =IF(Q39="-", "-", IF(T39="-", "-", IF(ABS(T39)=0, "-", ROUND(100*(Q39-T39)/ABS(T39),1)))) -> - | AF39: =IF(Z39="-", "-", IF(AC39="-", "-", IF(ABS(AC39)=0, "-", ROUND(100*(Z39-AC39)/ABS(AC39),1)))) -> - | AO39: =IF(AI39="-", "-", IF(AL39="-", "-", IF(ABS(AL39)=0, "-", ROUND(100*(AI39-AL39)/ABS(AL39),1)))) -> - | AX39: =IF(AR39="-", "-", IF(AU39="-", "-", IF(ABS(AU39)=0, "-", ROUND(100*(AR39-AU39)/ABS(AU39),1)))) -> -
B40: 10ａ当たり地代 | N40: =IF(H40="-", "-", IF(K40="-", "-", IF(ABS(K40)=0, "-", ROUND(100*(H40-K40)/ABS(K40),1)))) -> - | W40: =IF(Q40="-", "-", IF(T40="-", "-", IF(ABS(T40)=0, "-", ROUND(100*(Q40-T40)/ABS(T40),1)))) -> - | AF40: =IF(Z40="-", "-", IF(AC40="-", "-", IF(ABS(AC40)=0, "-", ROUND(100*(Z40-AC40)/ABS(AC40),1)))) -> - | AO40: =IF(AI40="-", "-", IF(AL40="-", "-", IF(ABS(AL40)=0, "-", ROUND(100*(AI40-AL40)/ABS(AL40),1)))) -> - | AX40: =IF(AR40="-", "-", IF(AU40="-", "-", IF(ABS(AU40)=0, "-", ROUND(100*(AR40-AU40)/ABS(AU40),1)))) -> -
B41: 対象畜負担地代 | N41: =IF(H41="-", "-", IF(K41="-", "-", IF(ABS(K41)=0, "-", ROUND(100*(H41-K41)/ABS(K41),1)))) -> - | W41: =IF(Q41="-", "-", IF(T41="-", "-", IF(ABS(T41)=0, "-", ROUND(100*(Q41-T41)/ABS(T41),1)))) -> - | AF41: =IF(Z41="-", "-", IF(AC41="-", "-", IF(ABS(AC41)=0, "-", ROUND(100*(Z41-AC41)/ABS(AC41),1)))) -> - | AO41: =IF(AI41="-", "-", IF(AL41="-", "-", IF(ABS(AL41)=0, "-", ROUND(100*(AI41-AL41)/ABS(AL41),1)))) -> - | AX41: =IF(AR41="-", "-", IF(AU41="-", "-", IF(ABS(AU41)=0, "-", ROUND(100*(AR41-AU41)/ABS(AU41),1)))) -> -

Sheet No.6
A1: =IF(No.1!A1="","",No.1!A1) | C1: 年 組織法人経営体に関する経営分析調査 肥育豚生産費 集計結果検討表 №６
F3: 集計番号 | I3: 集計名称 | T3: 都道府県等 | Y3: 規模階層
A4: 本年 | F4: =IF(No.1!F4="","",No.1!F4) | I4: =IF(No.1!I4="","",No.1!I4) | T4: =IF(No.1!T4="","",No.1!T4) | U4: =IF(No.1!U4="","",No.1!U4) | Y4: =IF(No.1!Y4="","",No.1!Y4) | Z4: =IF(No.1!Z4="","",No.1!Z4)
A5: 前年 | F5: =IF(No.1!F5="","",No.1!F5) | I5: =IF(No.1!I5="","",No.1!I5)
A7: 肥育豚１頭当たり
A8: 【物件税及び公課諸負担】 | P8: 単位：円、％ | AB8: 【出荷に要した費用】 | AQ8: 単位：円、％
H9: 本年 | K9: 前年 | N9: 増減率 | AI9: 本年 | AL9: 前年 | AO9: 増減率
A10: 物件税 | N10: =IF(H10="-", "-", IF(K10="-", "-", IF(ABS(K10)=0, "-", ROUND(100*(H10-K10)/ABS(K10),1)))) -> - | AB10: 材料費 | AO10: =IF(AI10="-", "-", IF(AL10="-", "-", IF(ABS(AL10)=0, "-", ROUND(100*(AI10-AL10)/ABS(AL10),1)))) -> -
A11: 公課諸負担 | N11: =IF(H11="-", "-", IF(K11="-", "-", IF(ABS(K11)=0, "-", ROUND(100*(H11-K11)/ABS(K11),1)))) -> - | AB11: 料金 | AO11: =IF(AI11="-", "-", IF(AL11="-", "-", IF(ABS(AL11)=0, "-", ROUND(100*(AI11-AL11)/ABS(AL11),1)))) -> -
A12: 計 | N12: =IF(H12="-", "-", IF(K12="-", "-", IF(ABS(K12)=0, "-", ROUND(100*(H12-K12)/ABS(K12),1)))) -> - | AB12: 労働費 | AO12: =IF(AI12="-", "-", IF(AL12="-", "-", IF(ABS(AL12)=0, "-", ROUND(100*(AI12-AL12)/ABS(AL12),1)))) -> -
AB13: 計 | AO13: =IF(AI13="-", "-", IF(AL13="-", "-", IF(ABS(AL13)=0, "-", ROUND(100*(AI13-AL13)/ABS(AL13),1)))) -> -
A14: 【借入金】 | Y14: 単位：円、％
H15: 決算期首未償還額 | Q15: 支払利子
H16: 本年 | K16: 前年 | N16: 増減率 | Q16: 本年 | T16: 前年 | W16: 増減率
A17: 借入金 | N17: =IF(H17="-", "-", IF(K17="-", "-", IF(ABS(K17)=0, "-", ROUND(100*(H17-K17)/ABS(K17),1)))) -> - | W17: =IF(Q17="-", "-", IF(T17="-", "-", IF(ABS(T17)=0, "-", ROUND(100*(Q17-T17)/ABS(T17),1)))) -> -
A19: 【固定資産の所有状況】
A20: （建物等） | Y20: 単位：円、％ | AB20: （自動車） | AZ20: 単位：台、円、％
G21: 所有状況 | Q21: 償 却 費 | AI21: 所有台数 | AR21: 償 却 費
G22: 単位 | H22: 本年 | K22: 前年 | N22: 増減率 | Q22: 本年 | T22: 前年 | W22: 増減率 | AI22: 本年 | AL22: 前年 | AO22: 増減率 | AR22: 本年 | AU22: 前年 | AX22: 増減率
AB23: 貨物自動車 | AO23: =IF(AI23="-", "-", IF(AL23="-", "-", IF(ABS(AL23)=0, "-", ROUND(100*(AI23-AL23)/ABS(AL23),1)))) -> - | AX23: =IF(AR23="-", "-", IF(AU23="-", "-", IF(ABS(AU23)=0, "-", ROUND(100*(AR23-AU23)/ABS(AU23),1)))) -> -
A24: 畜舎 | G24: ㎡ | N24: =IF(H24="-", "-", IF(K24="-", "-", IF(ABS(K24)=0, "-", ROUND(100*(H24-K24)/ABS(K24),1)))) -> - | W24: =IF(Q24="-", "-", IF(T24="-", "-", IF(ABS(T24)=0, "-", ROUND(100*(Q24-T24)/ABS(T24),1)))) -> - | AB24: その他 | AX24: =IF(AR24="-", "-", IF(AU24="-", "-", IF(ABS(AU24)=0, "-", ROUND(100*(AR24-AU24)/ABS(AU24),1)))) -> -
A25: たい肥舎 | G25: ㎡ | N25: =IF(H25="-", "-", IF(K25="-", "-", IF(ABS(K25)=0, "-", ROUND(100*(H25-K25)/ABS(K25),1)))) -> - | W25: =IF(Q25="-", "-", IF(T25="-", "-", IF(ABS(T25)=0, "-", ROUND(100*(Q25-T25)/ABS(T25),1)))) -> - | AB25: 計 | AX25: =IF(AR25="-", "-", IF(AU25="-", "-", IF(ABS(AU25)=0, "-", ROUND(100*(AR25-AU25)/ABS(AU25),1)))) -> -
A26: ふん尿貯留槽 | G26: 基 | N26: =IF(H26="-", "-", IF(K26="-", "-", IF(ABS(K26)=0, "-", ROUND(100*(H26-K26)/ABS(K26),1)))) -> - | W26: =IF(Q26="-", "-", IF(T26="-", "-", IF(ABS(T26)=0, "-", ROUND(100*(Q26-T26)/ABS(T26),1)))) -> - | AB26: 注：所有台数は10経営体当たり
A27: 脱臭施設 | G27: 基 | N27: =IF(H27="-", "-", IF(K27="-", "-", IF(ABS(K27)=0, "-", ROUND(100*(H27-K27)/ABS(K27),1)))) -> - | W27: =IF(Q27="-", "-", IF(T27="-", "-", IF(ABS(T27)=0, "-", ROUND(100*(Q27-T27)/ABS(T27),1)))) -> -
A28: 浄化処理施設 | G28: 基 | N28: =IF(H28="-", "-", IF(K28="-", "-", IF(ABS(K28)=0, "-", ROUND(100*(H28-K28)/ABS(K28),1)))) -> - | W28: =IF(Q28="-", "-", IF(T28="-", "-", IF(ABS(T28)=0, "-", ROUND(100*(Q28-T28)/ABS(T28),1)))) -> - | AB28: （農機具） | AZ28: 単位：台、円、％
A29: ふん乾燥施設 | G29: 基 | N29: =IF(H29="-", "-", IF(K29="-", "-", IF(ABS(K29)=0, "-", ROUND(100*(H29-K29)/ABS(K29),1)))) -> - | W29: =IF(Q29="-", "-", IF(T29="-", "-", IF(ABS(T29)=0, "-", ROUND(100*(Q29-T29)/ABS(T29),1)))) -> - | AI29: 所有台数 | AR29: 償 却 費
A30: 飼料用タンク | G30: 基 | N30: =IF(H30="-", "-", IF(K30="-", "-", IF(ABS(K30)=0, "-", ROUND(100*(H30-K30)/ABS(K30),1)))) -> - | W30: =IF(Q30="-", "-", IF(T30="-", "-", IF(ABS(T30)=0, "-", ROUND(100*(Q30-T30)/ABS(T30),1)))) -> - | AI30: 本年 | AL30: 前年 | AO30: 増減率 | AR30: 本年 | AU30: 前年 | AX30: 増減率
A31: その他 | G31: － | W31: =IF(Q31="-", "-", IF(T31="-", "-", IF(ABS(T31)=0, "-", ROUND(100*(Q31-T31)/ABS(T31),1)))) -> - | AB31: バキュームカー | AO31: =IF(AI31="-", "-", IF(AL31="-", "-", IF(ABS(AL31)=0, "-", ROUND(100*(AI31-AL31)/ABS(AL31),1)))) -> - | AX31: =IF(AR31="-", "-", IF(AU31="-", "-", IF(ABS(AU31)=0, "-", ROUND(100*(AR31-AU31)/ABS(AU31),1)))) -> -
A32: 計 | G32: － | W32: =IF(Q32="-", "-", IF(T32="-", "-", IF(ABS(T32)=0, "-", ROUND(100*(Q32-T32)/ABS(T32),1)))) -> - | AB32: マニュアスプレッダー | AO32: =IF(AI32="-", "-", IF(AL32="-", "-", IF(ABS(AL32)=0, "-", ROUND(100*(AI32-AL32)/ABS(AL32),1)))) -> - | AX32: =IF(AR32="-", "-", IF(AU32="-", "-", IF(ABS(AU32)=0, "-", ROUND(100*(AR32-AU32)/ABS(AU32),1)))) -> -
A33: 注：所有状況は１経営体当たり | AB33: 固液分離機 | AO33: =IF(AI33="-", "-", IF(AL33="-", "-", IF(ABS(AL33)=0, "-", ROUND(100*(AI33-AL33)/ABS(AL33),1)))) -> - | AX33: =IF(AR33="-", "-", IF(AU33="-", "-", IF(ABS(AU33)=0, "-", ROUND(100*(AR33-AU33)/ABS(AU33),1)))) -> -
AB34: 切り返し機(ﾛｰﾀﾞｰ) | AO34: =IF(AI34="-", "-", IF(AL34="-", "-", IF(ABS(AL34)=0, "-", ROUND(100*(AI34-AL34)/ABS(AL34),1)))) -> - | AX34: =IF(AR34="-", "-", IF(AU34="-", "-", IF(ABS(AU34)=0, "-", ROUND(100*(AR34-AU34)/ABS(AU34),1)))) -> -
A35: 【処分差損失】 | AB35: 動力噴霧機 | AO35: =IF(AI35="-", "-", IF(AL35="-", "-", IF(ABS(AL35)=0, "-", ROUND(100*(AI35-AL35)/ABS(AL35),1)))) -> - | AX35: =IF(AR35="-", "-", IF(AU35="-", "-", IF(ABS(AU35)=0, "-", ROUND(100*(AR35-AU35)/ABS(AU35),1)))) -> -
H36: 本年 | K36: 前年 | N36: 増減率 | AB36: トラクター | AO36: =IF(AI36="-", "-", IF(AL36="-", "-", IF(ABS(AL36)=0, "-", ROUND(100*(AI36-AL36)/ABS(AL36),1)))) -> - | AX36: =IF(AR36="-", "-", IF(AU36="-", "-", IF(ABS(AU36)=0, "-", ROUND(100*(AR36-AU36)/ABS(AU36),1)))) -> -
A37: 建物 | N37: =IF(H37="-", "-", IF(K37="-", "-", IF(ABS(K37)=0, "-", ROUND(100*(H37-K37)/ABS(K37),1)))) -> - | AB37: 飼料粉砕機 | AO37: =IF(AI37="-", "-", IF(AL37="-", "-", IF(ABS(AL37)=0, "-", ROUND(100*(AI37-AL37)/ABS(AL37),1)))) -> - | AX37: =IF(AR37="-", "-", IF(AU37="-", "-", IF(ABS(AU37)=0, "-", ROUND(100*(AR37-AU37)/ABS(AU37),1)))) -> -
A38: 自動車 | N38: =IF(H38="-", "-", IF(K38="-", "-", IF(ABS(K38)=0, "-", ROUND(100*(H38-K38)/ABS(K38),1)))) -> - | AB38: 飼料配合機 | AO38: =IF(AI38="-", "-", IF(AL38="-", "-", IF(ABS(AL38)=0, "-", ROUND(100*(AI38-AL38)/ABS(AL38),1)))) -> - | AX38: =IF(AR38="-", "-", IF(AU38="-", "-", IF(ABS(AU38)=0, "-", ROUND(100*(AR38-AU38)/ABS(AU38),1)))) -> -
A39: 農機具 | N39: =IF(H39="-", "-", IF(K39="-", "-", IF(ABS(K39)=0, "-", ROUND(100*(H39-K39)/ABS(K39),1)))) -> - | AB39: 自動給餌機 | AO39: =IF(AI39="-", "-", IF(AL39="-", "-", IF(ABS(AL39)=0, "-", ROUND(100*(AI39-AL39)/ABS(AL39),1)))) -> - | AX39: =IF(AR39="-", "-", IF(AU39="-", "-", IF(ABS(AU39)=0, "-", ROUND(100*(AR39-AU39)/ABS(AU39),1)))) -> -
A40: 生産管理機器 | N40: =IF(H40="-", "-", IF(K40="-", "-", IF(ABS(K40)=0, "-", ROUND(100*(H40-K40)/ABS(K40),1)))) -> - | AB40: 自動給水機 | AO40: =IF(AI40="-", "-", IF(AL40="-", "-", IF(ABS(AL40)=0, "-", ROUND(100*(AI40-AL40)/ABS(AL40),1)))) -> - | AX40: =IF(AR40="-", "-", IF(AU40="-", "-", IF(ABS(AU40)=0, "-", ROUND(100*(AR40-AU40)/ABS(AU40),1)))) -> -
AB41: その他 | AX41: =IF(AR41="-", "-", IF(AU41="-", "-", IF(ABS(AU41)=0, "-", ROUND(100*(AR41-AU41)/ABS(AU41),1)))) -> -
AB42: 計 | AX42: =IF(AR42="-", "-", IF(AU42="-", "-", IF(ABS(AU42)=0, "-", ROUND(100*(AR42-AU42)/ABS(AU42),1)))) -> -
AB43: 注：所有台数は10経営体当たり

Sheet No.7
A1: =IF(No.1!A1="","",No.1!A1) | D1: 年 組織法人経営体に関する経営分析調査 肥育豚生産費 集計結果検討表 №７
F3: 集計番号 | I3: 集計名称 | T3: 都道府県等 | Y3: 規模階層
A4: 本年 | F4: =IF(No.1!F4="","",No.1!F4) | I4: =IF(No.1!I4="","",No.1!I4) | T4: =IF(No.1!T4="","",No.1!T4) | U4: =IF(No.1!U4="","",No.1!U4) | Y4: =IF(No.1!Y4="","",No.1!Y4) | Z4: =IF(No.1!Z4="","",No.1!Z4)
A5: 前年 | F5: =IF(No.1!F5="","",No.1!F5) | I5: =IF(No.1!I5="","",No.1!I5)
A7: 肥育豚１頭当たり
A8: 【作業別労働時間及び労働費】 | AE8: 単位：時間、円、％
H9: 構 成 員 | P9: 雇 用 | X9: 合 計
H10: 本年 | K10: 前年 | N10: 増減率 | P10: 本年 | S10: 前年 | V10: 増減率 | X10: 本年 | AA10: 前年 | AD10: 増減率
A11: 直接労働時間計 | N11: =IF(H11="-", "-", IF(K11="-", "-", IF(ABS(K11)=0, "-", ROUND(100*(H11-K11)/ABS(K11),1)))) -> - | V11: =IF(P11="-", "-", IF(S11="-", "-", IF(ABS(S11)=0, "-", ROUND(100*(P11-S11)/ABS(S11),1)))) -> - | AD11: =IF(X11="-", "-", IF(AA11="-", "-", IF(ABS(AA11)=0, "-", ROUND(100*(X11-AA11)/ABS(AA11),1)))) -> -
B12: 飼料調理・給与・給水 | N12: =IF(H12="-", "-", IF(K12="-", "-", IF(ABS(K12)=0, "-", ROUND(100*(H12-K12)/ABS(K12),1)))) -> - | V12: =IF(P12="-", "-", IF(S12="-", "-", IF(ABS(S12)=0, "-", ROUND(100*(P12-S12)/ABS(S12),1)))) -> - | AD12: =IF(X12="-", "-", IF(AA12="-", "-", IF(ABS(AA12)=0, "-", ROUND(100*(X12-AA12)/ABS(AA12),1)))) -> -
B13: 敷料搬入･きゅう肥搬出 | N13: =IF(H13="-", "-", IF(K13="-", "-", IF(ABS(K13)=0, "-", ROUND(100*(H13-K13)/ABS(K13),1)))) -> - | V13: =IF(P13="-", "-", IF(S13="-", "-", IF(ABS(S13)=0, "-", ROUND(100*(P13-S13)/ABS(S13),1)))) -> - | AD13: =IF(X13="-", "-", IF(AA13="-", "-", IF(ABS(AA13)=0, "-", ROUND(100*(X13-AA13)/ABS(AA13),1)))) -> -
B14: その他 | N14: =IF(H14="-", "-", IF(K14="-", "-", IF(ABS(K14)=0, "-", ROUND(100*(H14-K14)/ABS(K14),1)))) -> - | V14: =IF(P14="-", "-", IF(S14="-", "-", IF(ABS(S14)=0, "-", ROUND(100*(P14-S14)/ABS(S14),1)))) -> - | AD14: =IF(X14="-", "-", IF(AA14="-", "-", IF(ABS(AA14)=0, "-", ROUND(100*(X14-AA14)/ABS(AA14),1)))) -> -
A15: 間接労働時間 | N15: =IF(H15="-", "-", IF(K15="-", "-", IF(ABS(K15)=0, "-", ROUND(100*(H15-K15)/ABS(K15),1)))) -> - | V15: =IF(P15="-", "-", IF(S15="-", "-", IF(ABS(S15)=0, "-", ROUND(100*(P15-S15)/ABS(S15),1)))) -> - | AD15: =IF(X15="-", "-", IF(AA15="-", "-", IF(ABS(AA15)=0, "-", ROUND(100*(X15-AA15)/ABS(AA15),1)))) -> -
A16: 労働時間合計 | N16: =IF(H16="-", "-", IF(K16="-", "-", IF(ABS(K16)=0, "-", ROUND(100*(H16-K16)/ABS(K16),1)))) -> - | V16: =IF(P16="-", "-", IF(S16="-", "-", IF(ABS(S16)=0, "-", ROUND(100*(P16-S16)/ABS(S16),1)))) -> - | AD16: =IF(X16="-", "-", IF(AA16="-", "-", IF(ABS(AA16)=0, "-", ROUND(100*(X16-AA16)/ABS(AA16),1)))) -> -
A17: 労働費 | N17: =IF(H17="-", "-", IF(K17="-", "-", IF(ABS(K17)=0, "-", ROUND(100*(H17-K17)/ABS(K17),1)))) -> - | V17: =IF(P17="-", "-", IF(S17="-", "-", IF(ABS(S17)=0, "-", ROUND(100*(P17-S17)/ABS(S17),1)))) -> - | AD17: =IF(X17="-", "-", IF(AA17="-", "-", IF(ABS(AA17)=0, "-", ROUND(100*(X17-AA17)/ABS(AA17),1)))) -> -
B18: 直接労働費 | N18: =IF(H18="-", "-", IF(K18="-", "-", IF(ABS(K18)=0, "-", ROUND(100*(H18-K18)/ABS(K18),1)))) -> - | V18: =IF(P18="-", "-", IF(S18="-", "-", IF(ABS(S18)=0, "-", ROUND(100*(P18-S18)/ABS(S18),1)))) -> - | AD18: =IF(X18="-", "-", IF(AA18="-", "-", IF(ABS(AA18)=0, "-", ROUND(100*(X18-AA18)/ABS(AA18),1)))) -> -
C19: 敷料搬入･きゅう肥搬出 | N19: =IF(H19="-", "-", IF(K19="-", "-", IF(ABS(K19)=0, "-", ROUND(100*(H19-K19)/ABS(K19),1)))) -> -
B20: 間接労働費 | N20: =IF(H20="-", "-", IF(K20="-", "-", IF(ABS(K20)=0, "-", ROUND(100*(H20-K20)/ABS(K20),1)))) -> - | V20: =IF(P20="-", "-", IF(S20="-", "-", IF(ABS(S20)=0, "-", ROUND(100*(P20-S20)/ABS(S20),1)))) -> - | AD20: =IF(X20="-", "-", IF(AA20="-", "-", IF(ABS(AA20)=0, "-", ROUND(100*(X20-AA20)/ABS(AA20),1)))) -> -
A23: 【年齢階層別構成員労働時間及び労働評価額】 | AE23: 単位：時間、円、％
H24: 計算対象畜負担労働時間 | P24: 労賃単価 | X24: 計算対象畜負担労働評価額
H25: 本年 | K25: 前年 | N25: 増減率 | P25: 本年 | S25: 前年 | V25: 増減率 | X25: 本年 | AA25: 前年 | AD25: 増減率
A26: 65歳未満 | N26: =IF(H26="-", "-", IF(K26="-", "-", IF(ABS(K26)=0, "-", ROUND(100*(H26-K26)/ABS(K26),1)))) -> - | V26: =IF(P26="-", "-", IF(S26="-", "-", IF(ABS(S26)=0, "-", ROUND(100*(P26-S26)/ABS(S26),1)))) -> - | AD26: =IF(X26="-", "-", IF(AA26="-", "-", IF(ABS(AA26)=0, "-", ROUND(100*(X26-AA26)/ABS(AA26),1)))) -> -
A27: 65 ～ 70 | N27: =IF(H27="-", "-", IF(K27="-", "-", IF(ABS(K27)=0, "-", ROUND(100*(H27-K27)/ABS(K27),1)))) -> - | V27: =IF(P27="-", "-", IF(S27="-", "-", IF(ABS(S27)=0, "-", ROUND(100*(P27-S27)/ABS(S27),1)))) -> - | AD27: =IF(X27="-", "-", IF(AA27="-", "-", IF(ABS(AA27)=0, "-", ROUND(100*(X27-AA27)/ABS(AA27),1)))) -> -
A28: 70 ～ 75 | N28: =IF(H28="-", "-", IF(K28="-", "-", IF(ABS(K28)=0, "-", ROUND(100*(H28-K28)/ABS(K28),1)))) -> - | V28: =IF(P28="-", "-", IF(S28="-", "-", IF(ABS(S28)=0, "-", ROUND(100*(P28-S28)/ABS(S28),1)))) -> - | AD28: =IF(X28="-", "-", IF(AA28="-", "-", IF(ABS(AA28)=0, "-", ROUND(100*(X28-AA28)/ABS(AA28),1)))) -> -
A29: 75歳以上 | N29: =IF(H29="-", "-", IF(K29="-", "-", IF(ABS(K29)=0, "-", ROUND(100*(H29-K29)/ABS(K29),1)))) -> - | V29: =IF(P29="-", "-", IF(S29="-", "-", IF(ABS(S29)=0, "-", ROUND(100*(P29-S29)/ABS(S29),1)))) -> - | AD29: =IF(X29="-", "-", IF(AA29="-", "-", IF(ABS(AA29)=0, "-", ROUND(100*(X29-AA29)/ABS(AA29),1)))) -> -
A30: 計 | N30: =IF(H30="-", "-", IF(K30="-", "-", IF(ABS(K30)=0, "-", ROUND(100*(H30-K30)/ABS(K30),1)))) -> - | V30: =IF(P30="-", "-", IF(S30="-", "-", IF(ABS(S30)=0, "-", ROUND(100*(P30-S30)/ABS(S30),1)))) -> - | AD30: =IF(X30="-", "-", IF(AA30="-", "-", IF(ABS(AA30)=0, "-", ROUND(100*(X30-AA30)/ABS(AA30),1)))) -> -
A31: 注：労賃単価は「労働評価額÷労働時間」

Sheet リスト
A2: 都道府県等 | B2: コード | D2: 規模階層 | E2: コード
A3: 全国 | B3: 0 | D3: 平均 | E3: 0
A4: 都府県平均 | B4: 60 | D4: 1.0-999.9 | E4: 1
A5: 北海道 | B5: 1 | D5: 1,000.0-1,999.9 | E5: 2
A6: 東北 | B6: 61 | D6: 2,000.0-9,999.9 | E6: 3
A7: 北陸 | B7: 62 | D7: 10,000.0-999,999.9 | E7: 4
A8: 関東・東山 | B8: 63
A9: 東海 | B9: 67 | E9: コード
A10: 近畿 | B10: 68 | E10: ="="&No.1!Y4 -> =
A11: 中国 | B11: 71
A12: 四国 | B12: 74
A13: 九州 | B13: 75
A14: 沖縄 | B14: 47
A15: 北関東 | B15: 64
A16: 南関東 | B16: 65
A17: 東山 | B17: 66
A18: 北東北 | B18: 69
A19: 南東北 | B19: 70
A20: 山陰 | B20: 72
A21: 山陽 | B21: 73
A22: 北九州 | B22: 76
... A71: 鹿児島 | B71: 46
B73: コード
B74: ="="&No.1!T4 -> =
