Workbook

Sheet No.1
B1: =AB4 -> 0 | E1: 年産 組織法人経営体に関する経営分析調査（麦類・そば・なたね・畑作物生産費（組織法人経営）） 集計結果検討表 Ｎｏ．１
G3: 集計番号 | J3: 集計名称 | Q3: 集計経営体数 | V3: 集計倍率 | AB3: 調査年 | AG3: 都道府県等 | AL3: 経営種類 | AQ3: 生産費区分 | AV3: 規模階層 | BA3: 平均値種類 | BF3: 加重・総和の別 | BK3: 集計区分 | BP3: 田畑区分 | BU3: ビール麦販売区分 | BZ3: てんさい栽培区分
B4: 本年産 | AH4: =IF(AG4<>"",DGET(リスト!A2:B71,"都道府県番号",リスト!B73:B74),"") | AM4: =IF(AL4>0,DGET(リスト!AE2:AF4,"経営種類",リスト!AF6:AF7),"") | AR4: =IF(AQ4>0,DGET(リスト!D2:E13,"生産費区分",リスト!E15:E16),"") | AW4: =IF(AV4<>"",IF(OR(AQ4=77,AQ4=78,AQ4=79),DGET(リスト!J20:K24,"規模階層",リスト!K16:K17),IF(AQ4=76,DGET(リスト!J27:K35,"規模階層",リスト!K16:K17),IF(AQ4=84,DGET(リスト!J38:K42,"規模階層",リスト!K16:K17),IF(AQ4=75,DGET(リスト!M3:N7,"規模階層",リスト!K16:K17),IF(AQ4=86,DGET(リスト!M10:N15,"規模階層",リスト!K16:K17),IF(AQ4=85,DGET(リスト!M18:N22,"規模階層",リスト!K16:K17),"")))))),"") | BB4: =IF(BA4<>"",DGET(リスト!V2:W7,"平均値種類",リスト!W9:W10),"") | BG4: =IF(BF4>0,DGET(リスト!Y2:Z4,"加重・総和の別",リスト!Z6:Z7),"") | BL4: =IF(BK4>0,DGET(リスト!G2:H8,"集計区分",リスト!H10:H11),"") | BQ4: =IF(BP4<>"",DGET(リスト!S2:T6,"田畑区分",リスト!T8:T9),"") | BV4: =IF(BU4<>"",DGET(リスト!P2:Q7,"ビール麦販売区分",リスト!Q9:Q10),"") | CA4: =IF(BZ4<>"",DGET(リスト!AB2:AC6,"てんさい栽培区分",リスト!AC8:AC9),"")
B5: 前年産
B7: １ 生産費総括 | AZ7: 単位：円 | BD7: ４ 調査作物収入 | CG7: 単位：円、kg
I8: 購入 | T8: 自給 | AE8: 償却 | AP8: 計 | BL8: 数量 | BW8: 価額
I9: =IF($B$1<>"",$B$1,"") -> 0 | M9: =IF($B$1<>"",$B$1-1,"") -> -1 | Q9: 増減率 | T9: =IF($B$1<>"",$B$1,"") -> 0 | X9: =IF($B$1<>"",$B$1-1,"") -> -1 | AB9: 増減率 | AE9: =IF($B$1<>"",$B$1,"") -> 0 | AI9: =IF($B$1<>"",$B$1-1,"") -> -1 | AM9: 増減率 | AP9: =IF($B$1<>"",$B$1,"") -> 0 | AT9: =IF($B$1<>"",$B$1-1,"") -> -1 | AX9: 増減率 | BL9: =IF($B$1<>"",$B$1,"") -> 0 | BP9: =IF($B$1<>"",$B$1-1,"") -> -1 | BT9: 増減率 | BW9: =IF($B$1<>"",$B$1,"") -> 0 | CA9: =IF($B$1<>"",$B$1-1,"") -> -1 | CE9: 増減率
B10: 物財費 | Q10: =IF(I10="-", "-", IF(M10="-", "-", IF(ABS(M10)=0, "-", ROUND(100*(I10-M10)/ABS(M10), 1)))) -> - | R10: =IF(N10="-", "-", IF(P10="-", "-", IF(ABS(P10)=0, "-", ROUND(100*(N10-P10)/ABS(P10), 1)))) -> - | S10: =IF(O10="-", "-", IF(Q10="-", "-", IF(ABS(Q10)=0, "-", ROUND(100*(O10-Q10)/ABS(Q10), 1)))) -> - | AB10: =IF(T10="-", "-", IF(X10="-", "-", IF(ABS(X10)=0, "-", ROUND(100*(T10-X10)/ABS(X10), 1)))) -> - | AC10: =IF(Y10="-", "-", IF(AA10="-", "-", IF(ABS(AA10)=0, "-", ROUND(100*(Y10-AA10)/ABS(AA10), 1)))) -> - | AD10: =IF(Z10="-", "-", IF(AB10="-", "-", IF(ABS(AB10)=0, "-", ROUND(100*(Z10-AB10)/ABS(AB10), 1)))) -> - | AM10: =IF(AE10="-", "-", IF(AI10="-", "-", IF(ABS(AI10)=0, "-", ROUND(100*(AE10-AI10)/ABS(AI10), 1)))) -> - | AN10: =IF(AJ10="-", "-", IF(AL10="-", "-", IF(ABS(AL10)=0, "-", ROUND(100*(AJ10-AL10)/ABS(AL10), 1)))) -> - | AO10: =IF(AK10="-", "-", IF(AM10="-", "-", IF(ABS(AM10)=0, "-", ROUND(100*(AK10-AM10)/ABS(AM10), 1)))) -> - | AX10: =IF(AP10="-", "-", IF(AT10="-", "-", IF(ABS(AT10)=0, "-", ROUND(100*(AP10-AT10)/ABS(AT10), 1)))) -> - | AY10: =IF(AU10="-", "-", IF(AW10="-", "-", IF(ABS(AW10)=0, "-", ROUND(100*(AU10-AW10)/ABS(AW10), 1)))) -> - | AZ10: =IF(AV10="-", "-", IF(AX10="-", "-", IF(ABS(AX10)=0, "-", ROUND(100*(AV10-AX10)/ABS(AX10), 1)))) -> - | BD10: 主産物 | BE10: 販売用 | BT10: =IF(BL10="-", "-", IF(BP10="-", "-", IF(ABS(BP10)=0, "-", ROUND(100*(BL10-BP10)/ABS(BP10), 1)))) -> - | BU10: =IF(BQ10="-", "-", IF(BS10="-", "-", IF(ABS(BS10)=0, "-", ROUND(100*(BQ10-BS10)/ABS(BS10), 1)))) -> - | BV10: =IF(BR10="-", "-", IF(BT10="-", "-", IF(ABS(BT10)=0, "-", ROUND(100*(BR10-BT10)/ABS(BT10), 1)))) -> - | CE10: =IF(BW10="-", "-", IF(CA10="-", "-", IF(ABS(CA10)=0, "-", ROUND(100*(BW10-CA10)/ABS(CA10), 1)))) -> - | CF10: =IF(CB10="-", "-", IF(CD10="-", "-", IF(ABS(CD10)=0, "-", ROUND(100*(CB10-CD10)/ABS(CD10), 1)))) -> - | CG10: =IF(CC10="-", "-", IF(CE10="-", "-", IF(ABS(CE10)=0, "-", ROUND(100*(CC10-CE10)/ABS(CE10), 1)))) -> -
C11: 種苗費 | Q11: =IF(I11="-", "-", IF(M11="-", "-", IF(ABS(M11)=0, "-", ROUND(100*(I11-M11)/ABS(M11), 1)))) -> - | R11: =IF(N11="-", "-", IF(P11="-", "-", IF(ABS(P11)=0, "-", ROUND(100*(N11-P11)/ABS(P11), 1)))) -> - | S11: =IF(O11="-", "-", IF(Q11="-", "-", IF(ABS(Q11)=0, "-", ROUND(100*(O11-Q11)/ABS(Q11), 1)))) -> - | AB11: =IF(T11="-", "-", IF(X11="-", "-", IF(ABS(X11)=0, "-", ROUND(100*(T11-X11)/ABS(X11), 1)))) -> - | AC11: =IF(Y11="-", "-", IF(AA11="-", "-", IF(ABS(AA11)=0, "-", ROUND(100*(Y11-AA11)/ABS(AA11), 1)))) -> - | AD11: =IF(Z11="-", "-", IF(AB11="-", "-", IF(ABS(AB11)=0, "-", ROUND(100*(Z11-AB11)/ABS(AB11), 1)))) -> - | AX11: =IF(AP11="-", "-", IF(AT11="-", "-", IF(ABS(AT11)=0, "-", ROUND(100*(AP11-AT11)/ABS(AT11), 1)))) -> - | AY11: =IF(AU11="-", "-", IF(AW11="-", "-", IF(ABS(AW11)=0, "-", ROUND(100*(AU11-AW11)/ABS(AW11), 1)))) -> - | AZ11: =IF(AV11="-", "-", IF(AX11="-", "-", IF(ABS(AX11)=0, "-", ROUND(100*(AV11-AX11)/ABS(AX11), 1)))) -> - | BE11: 組織用 | BT11: =IF(BL11="-", "-", IF(BP11="-", "-", IF(ABS(BP11)=0, "-", ROUND(100*(BL11-BP11)/ABS(BP11), 1)))) -> - | BU11: =IF(BQ11="-", "-", IF(BS11="-", "-", IF(ABS(BS11)=0, "-", ROUND(100*(BQ11-BS11)/ABS(BS11), 1)))) -> - | BV11: =IF(BR11="-", "-", IF(BT11="-", "-", IF(ABS(BT11)=0, "-", ROUND(100*(BR11-BT11)/ABS(BT11), 1)))) -> - | CE11: =IF(BW11="-", "-", IF(CA11="-", "-", IF(ABS(CA11)=0, "-", ROUND(100*(BW11-CA11)/ABS(CA11), 1)))) -> - | CF11: =IF(CB11="-", "-", IF(CD11="-", "-", IF(ABS(CD11)=0, "-", ROUND(100*(CB11-CD11)/ABS(CD11), 1)))) -> - | CG11: =IF(CC11="-", "-", IF(CE11="-", "-", IF(ABS(CE11)=0, "-", ROUND(100*(CC11-CE11)/ABS(CE11), 1)))) -> -
C12: 肥料費 | Q12: =IF(I12="-", "-", IF(M12="-", "-", IF(ABS(M12)=0, "-", ROUND(100*(I12-M12)/ABS(M12), 1)))) -> - | R12: =IF(N12="-", "-", IF(P12="-", "-", IF(ABS(P12)=0, "-", ROUND(100*(N12-P12)/ABS(P12), 1)))) -> - | S12: =IF(O12="-", "-", IF(Q12="-", "-", IF(ABS(Q12)=0, "-", ROUND(100*(O12-Q12)/ABS(Q12), 1)))) -> - | AB12: =IF(T12="-", "-", IF(X12="-", "-", IF(ABS(X12)=0, "-", ROUND(100*(T12-X12)/ABS(X12), 1)))) -> - | AC12: =IF(Y12="-", "-", IF(AA12="-", "-", IF(ABS(AA12)=0, "-", ROUND(100*(Y12-AA12)/ABS(AA12), 1)))) -> - | AD12: =IF(Z12="-", "-", IF(AB12="-", "-", IF(ABS(AB12)=0, "-", ROUND(100*(Z12-AB12)/ABS(AB12), 1)))) -> - | AX12: =IF(AP12="-", "-", IF(AT12="-", "-", IF(ABS(AT12)=0, "-", ROUND(100*(AP12-AT12)/ABS(AT12), 1)))) -> - | AY12: =IF(AU12="-", "-", IF(AW12="-", "-", IF(ABS(AW12)=0, "-", ROUND(100*(AU12-AW12)/ABS(AW12), 1)))) -> - | AZ12: =IF(AV12="-", "-", IF(AX12="-", "-", IF(ABS(AX12)=0, "-", ROUND(100*(AV12-AX12)/ABS(AX12), 1)))) -> - | BE12: 計 | BT12: =IF(BL12="-", "-", IF(BP12="-", "-", IF(ABS(BP12)=0, "-", ROUND(100*(BL12-BP12)/ABS(BP12), 1)))) -> - | BU12: =IF(BQ12="-", "-", IF(BS12="-", "-", IF(ABS(BS12)=0, "-", ROUND(100*(BQ12-BS12)/ABS(BS12), 1)))) -> - | BV12: =IF(BR12="-", "-", IF(BT12="-", "-", IF(ABS(BT12)=0, "-", ROUND(100*(BR12-BT12)/ABS(BT12), 1)))) -> - | CE12: =IF(BW12="-", "-", IF(CA12="-", "-", IF(ABS(CA12)=0, "-", ROUND(100*(BW12-CA12)/ABS(CA12), 1)))) -> - | CF12: =IF(CB12="-", "-", IF(CD12="-", "-", IF(ABS(CD12)=0, "-", ROUND(100*(CB12-CD12)/ABS(CD12), 1)))) -> - | CG12: =IF(CC12="-", "-", IF(CE12="-", "-", IF(ABS(CE12)=0, "-", ROUND(100*(CC12-CE12)/ABS(CE12), 1)))) -> -
C13: 農業薬剤費 | Q13: =IF(I13="-", "-", IF(M13="-", "-", IF(ABS(M13)=0, "-", ROUND(100*(I13-M13)/ABS(M13), 1)))) -> - | R13: =IF(N13="-", "-", IF(P13="-", "-", IF(ABS(P13)=0, "-", ROUND(100*(N13-P13)/ABS(P13), 1)))) -> - | S13: =IF(O13="-", "-", IF(Q13="-", "-", IF(ABS(Q13)=0, "-", ROUND(100*(O13-Q13)/ABS(Q13), 1)))) -> - | AX13: =IF(AP13="-", "-", IF(AT13="-", "-", IF(ABS(AT13)=0, "-", ROUND(100*(AP13-AT13)/ABS(AT13), 1)))) -> - | AY13: =IF(AU13="-", "-", IF(AW13="-", "-", IF(ABS(AW13)=0, "-", ROUND(100*(AU13-AW13)/ABS(AW13), 1)))) -> - | AZ13: =IF(AV13="-", "-", IF(AX13="-", "-", IF(ABS(AX13)=0, "-", ROUND(100*(AV13-AX13)/ABS(AX13), 1)))) -> - | BD13: 副産物 | BT13: =IF(BL13="-", "-", IF(BP13="-", "-", IF(ABS(BP13)=0, "-", ROUND(100*(BL13-BP13)/ABS(BP13), 1)))) -> - | BU13: =IF(BQ13="-", "-", IF(BS13="-", "-", IF(ABS(BS13)=0, "-", ROUND(100*(BQ13-BS13)/ABS(BS13), 1)))) -> - | BV13: =IF(BR13="-", "-", IF(BT13="-", "-", IF(ABS(BT13)=0, "-", ROUND(100*(BR13-BT13)/ABS(BT13), 1)))) -> - | CE13: =IF(BW13="-", "-", IF(CA13="-", "-", IF(ABS(CA13)=0, "-", ROUND(100*(BW13-CA13)/ABS(CA13), 1)))) -> - | CF13: =IF(CB13="-", "-", IF(CD13="-", "-", IF(ABS(CD13)=0, "-", ROUND(100*(CB13-CD13)/ABS(CD13), 1)))) -> - | CG13: =IF(CC13="-", "-", IF(CE13="-", "-", IF(ABS(CE13)=0, "-", ROUND(100*(CC13-CE13)/ABS(CE13), 1)))) -> -
C14: 光熱動力費 | Q14: =IF(I14="-", "-", IF(M14="-", "-", IF(ABS(M14)=0, "-", ROUND(100*(I14-M14)/ABS(M14), 1)))) -> - | R14: =IF(N14="-", "-", IF(P14="-", "-", IF(ABS(P14)=0, "-", ROUND(100*(N14-P14)/ABS(P14), 1)))) -> - | S14: =IF(O14="-", "-", IF(Q14="-", "-", IF(ABS(Q14)=0, "-", ROUND(100*(O14-Q14)/ABS(Q14), 1)))) -> - | AB14: =IF(T14="-", "-", IF(X14="-", "-", IF(ABS(X14)=0, "-", ROUND(100*(T14-X14)/ABS(X14), 1)))) -> - | AC14: =IF(Y14="-", "-", IF(AA14="-", "-", IF(ABS(AA14)=0, "-", ROUND(100*(Y14-AA14)/ABS(AA14), 1)))) -> - | AD14: =IF(Z14="-", "-", IF(AB14="-", "-", IF(ABS(AB14)=0, "-", ROUND(100*(Z14-AB14)/ABS(AB14), 1)))) -> - | AX14: =IF(AP14="-", "-", IF(AT14="-", "-", IF(ABS(AT14)=0, "-", ROUND(100*(AP14-AT14)/ABS(AT14), 1)))) -> - | AY14: =IF(AU14="-", "-", IF(AW14="-", "-", IF(ABS(AW14)=0, "-", ROUND(100*(AU14-AW14)/ABS(AW14), 1)))) -> - | AZ14: =IF(AV14="-", "-", IF(AX14="-", "-", IF(ABS(AX14)=0, "-", ROUND(100*(AV14-AX14)/ABS(AX14), 1)))) -> - | BD14: 粗収益 | CE14: =IF(BW14="-", "-", IF(CA14="-", "-", IF(ABS(CA14)=0, "-", ROUND(100*(BW14-CA14)/ABS(CA14), 1)))) -> - | CF14: =IF(CB14="-", "-", IF(CD14="-", "-", IF(ABS(CD14)=0, "-", ROUND(100*(CB14-CD14)/ABS(CD14), 1)))) -> - | CG14: =IF(CC14="-", "-", IF(CE14="-", "-", IF(ABS(CE14)=0, "-", ROUND(100*(CC14-CE14)/ABS(CE14), 1)))) -> -
C15: その他の諸材料費 | Q15: =IF(I15="-", "-", IF(M15="-", "-", IF(ABS(M15)=0, "-", ROUND(100*(I15-M15)/ABS(M15), 1)))) -> - | R15: =IF(N15="-", "-", IF(P15="-", "-", IF(ABS(P15)=0, "-", ROUND(100*(N15-P15)/ABS(P15), 1)))) -> - | S15: =IF(O15="-", "-", IF(Q15="-", "-", IF(ABS(Q15)=0, "-", ROUND(100*(O15-Q15)/ABS(Q15), 1)))) -> - | AB15: =IF(T15="-", "-", IF(X15="-", "-", IF(ABS(X15)=0, "-", ROUND(100*(T15-X15)/ABS(X15), 1)))) -> - | AC15: =IF(Y15="-", "-", IF(AA15="-", "-", IF(ABS(AA15)=0, "-", ROUND(100*(Y15-AA15)/ABS(AA15), 1)))) -> - | AD15: =IF(Z15="-", "-", IF(AB15="-", "-", IF(ABS(AB15)=0, "-", ROUND(100*(Z15-AB15)/ABS(AB15), 1)))) -> - | AX15: =IF(AP15="-", "-", IF(AT15="-", "-", IF(ABS(AT15)=0, "-", ROUND(100*(AP15-AT15)/ABS(AT15), 1)))) -> - | AY15: =IF(AU15="-", "-", IF(AW15="-", "-", IF(ABS(AW15)=0, "-", ROUND(100*(AU15-AW15)/ABS(AW15), 1)))) -> - | AZ15: =IF(AV15="-", "-", IF(AX15="-", "-", IF(ABS(AX15)=0, "-", ROUND(100*(AV15-AX15)/ABS(AX15), 1)))) -> - | BD15: （参考）奨励金 | CE15: =IF(BW15="-", "-", IF(CA15="-", "-", IF(ABS(CA15)=0, "-", ROUND(100*(BW15-CA15)/ABS(CA15), 1)))) -> - | CF15: =IF(CB15="-", "-", IF(CD15="-", "-", IF(ABS(CD15)=0, "-", ROUND(100*(CB15-CD15)/ABS(CD15), 1)))) -> - | CG15: =IF(CC15="-", "-", IF(CE15="-", "-", IF(ABS(CE15)=0, "-", ROUND(100*(CC15-CE15)/ABS(CE15), 1)))) -> -
C16: 土地改良及び水利費 | Q16: =IF(I16="-", "-", IF(M16="-", "-", IF(ABS(M16)=0, "-", ROUND(100*(I16-M16)/ABS(M16), 1)))) -> - | R16: =IF(N16="-", "-", IF(P16="-", "-", IF(ABS(P16)=0, "-", ROUND(100*(N16-P16)/ABS(P16), 1)))) -> - | S16: =IF(O16="-", "-", IF(Q16="-", "-", IF(ABS(Q16)=0, "-", ROUND(100*(O16-Q16)/ABS(Q16), 1)))) -> - | AX16: =IF(AP16="-", "-", IF(AT16="-", "-", IF(ABS(AT16)=0, "-", ROUND(100*(AP16-AT16)/ABS(AT16), 1)))) -> - | AY16: =IF(AU16="-", "-", IF(AW16="-", "-", IF(ABS(AW16)=0, "-", ROUND(100*(AU16-AW16)/ABS(AW16), 1)))) -> - | AZ16: =IF(AV16="-", "-", IF(AX16="-", "-", IF(ABS(AX16)=0, "-", ROUND(100*(AV16-AX16)/ABS(AX16), 1)))) -> -
C17: 賃借料及び料金 | Q17: =IF(I17="-", "-", IF(M17="-", "-", IF(ABS(M17)=0, "-", ROUND(100*(I17-M17)/ABS(M17), 1)))) -> - | R17: =IF(N17="-", "-", IF(P17="-", "-", IF(ABS(P17)=0, "-", ROUND(100*(N17-P17)/ABS(P17), 1)))) -> - | S17: =IF(O17="-", "-", IF(Q17="-", "-", IF(ABS(Q17)=0, "-", ROUND(100*(O17-Q17)/ABS(Q17), 1)))) -> - | AX17: =IF(AP17="-", "-", IF(AT17="-", "-", IF(ABS(AT17)=0, "-", ROUND(100*(AP17-AT17)/ABS(AT17), 1)))) -> - | AY17: =IF(AU17="-", "-", IF(AW17="-", "-", IF(ABS(AW17)=0, "-", ROUND(100*(AU17-AW17)/ABS(AW17), 1)))) -> - | AZ17: =IF(AV17="-", "-", IF(AX17="-", "-", IF(ABS(AX17)=0, "-", ROUND(100*(AV17-AX17)/ABS(AX17), 1)))) -> -
C18: 物件税及び公課諸負担 | Q18: =IF(I18="-", "-", IF(M18="-", "-", IF(ABS(M18)=0, "-", ROUND(100*(I18-M18)/ABS(M18), 1)))) -> - | R18: =IF(N18="-", "-", IF(P18="-", "-", IF(ABS(P18)=0, "-", ROUND(100*(N18-P18)/ABS(P18), 1)))) -> - | S18: =IF(O18="-", "-", IF(Q18="-", "-", IF(ABS(Q18)=0, "-", ROUND(100*(O18-Q18)/ABS(Q18), 1)))) -> - | AX18: =IF(AP18="-", "-", IF(AT18="-", "-", IF(ABS(AT18)=0, "-", ROUND(100*(AP18-AT18)/ABS(AT18), 1)))) -> - | AY18: =IF(AU18="-", "-", IF(AW18="-", "-", IF(ABS(AW18)=0, "-", ROUND(100*(AU18-AW18)/ABS(AW18), 1)))) -> - | AZ18: =IF(AV18="-", "-", IF(AX18="-", "-", IF(ABS(AX18)=0, "-", ROUND(100*(AV18-AX18)/ABS(AX18), 1)))) -> - | BD18: ５ 農業共済金、各種助成措置の状況 | CG18: 単位：円
C19: 建物費 | Q19: =IF(I19="-", "-", IF(M19="-", "-", IF(ABS(M19)=0, "-", ROUND(100*(I19-M19)/ABS(M19), 1)))) -> - | R19: =IF(N19="-", "-", IF(P19="-", "-", IF(ABS(P19)=0, "-", ROUND(100*(N19-P19)/ABS(P19), 1)))) -> - | S19: =IF(O19="-", "-", IF(Q19="-", "-", IF(ABS(Q19)=0, "-", ROUND(100*(O19-Q19)/ABS(Q19), 1)))) -> - | AM19: =IF(AE19="-", "-", IF(AI19="-", "-", IF(ABS(AI19)=0, "-", ROUND(100*(AE19-AI19)/ABS(AI19), 1)))) -> - | AN19: =IF(AJ19="-", "-", IF(AL19="-", "-", IF(ABS(AL19)=0, "-", ROUND(100*(AJ19-AL19)/ABS(AL19), 1)))) -> - | AO19: =IF(AK19="-", "-", IF(AM19="-", "-", IF(ABS(AM19)=0, "-", ROUND(100*(AK19-AM19)/ABS(AM19), 1)))) -> - | AX19: =IF(AP19="-", "-", IF(AT19="-", "-", IF(ABS(AT19)=0, "-", ROUND(100*(AP19-AT19)/ABS(AT19), 1)))) -> - | AY19: =IF(AU19="-", "-", IF(AW19="-", "-", IF(ABS(AW19)=0, "-", ROUND(100*(AU19-AW19)/ABS(AW19), 1)))) -> - | AZ19: =IF(AV19="-", "-", IF(AX19="-", "-", IF(ABS(AX19)=0, "-", ROUND(100*(AV19-AX19)/ABS(AX19), 1)))) -> - | BL19: 拠出金 | BW19: 受取金
C20: 自動車費 | Q20: =IF(I20="-", "-", IF(M20="-", "-", IF(ABS(M20)=0, "-", ROUND(100*(I20-M20)/ABS(M20), 1)))) -> - | R20: =IF(N20="-", "-", IF(P20="-", "-", IF(ABS(P20)=0, "-", ROUND(100*(N20-P20)/ABS(P20), 1)))) -> - | S20: =IF(O20="-", "-", IF(Q20="-", "-", IF(ABS(Q20)=0, "-", ROUND(100*(O20-Q20)/ABS(Q20), 1)))) -> - | AM20: =IF(AE20="-", "-", IF(AI20="-", "-", IF(ABS(AI20)=0, "-", ROUND(100*(AE20-AI20)/ABS(AI20), 1)))) -> - | AN20: =IF(AJ20="-", "-", IF(AL20="-", "-", IF(ABS(AL20)=0, "-", ROUND(100*(AJ20-AL20)/ABS(AL20), 1)))) -> - | AO20: =IF(AK20="-", "-", IF(AM20="-", "-", IF(ABS(AM20)=0, "-", ROUND(100*(AK20-AM20)/ABS(AM20), 1)))) -> - | AX20: =IF(AP20="-", "-", IF(AT20="-", "-", IF(ABS(AT20)=0, "-", ROUND(100*(AP20-AT20)/ABS(AT20), 1)))) -> - | AY20: =IF(AU20="-", "-", IF(AW20="-", "-", IF(ABS(AW20)=0, "-", ROUND(100*(AU20-AW20)/ABS(AW20), 1)))) -> - | AZ20: =IF(AV20="-", "-", IF(AX20="-", "-", IF(ABS(AX20)=0, "-", ROUND(100*(AV20-AX20)/ABS(AX20), 1)))) -> - | BL20: =IF($B$1<>"",$B$1,"") -> 0 | BP20: =IF($B$1<>"",$B$1-1,"") -> -1 | BT20: 増減率 | BW20: =IF($B$1<>"",$B$1,"") -> 0 | CA20: =IF($B$1<>"",$B$1-1,"") -> -1 | CE20: 増減率
C21: 農機具費 | Q21: =IF(I21="-", "-", IF(M21="-", "-", IF(ABS(M21)=0, "-", ROUND(100*(I21-M21)/ABS(M21), 1)))) -> - | R21: =IF(N21="-", "-", IF(P21="-", "-", IF(ABS(P21)=0, "-", ROUND(100*(N21-P21)/ABS(P21), 1)))) -> - | S21: =IF(O21="-", "-", IF(Q21="-", "-", IF(ABS(Q21)=0, "-", ROUND(100*(O21-Q21)/ABS(Q21), 1)))) -> - | AM21: =IF(AE21="-", "-", IF(AI21="-", "-", IF(ABS(AI21)=0, "-", ROUND(100*(AE21-AI21)/ABS(AI21), 1)))) -> - | AN21: =IF(AJ21="-", "-", IF(AL21="-", "-", IF(ABS(AL21)=0, "-", ROUND(100*(AJ21-AL21)/ABS(AL21), 1)))) -> - | AO21: =IF(AK21="-", "-", IF(AM21="-", "-", IF(ABS(AM21)=0, "-", ROUND(100*(AK21-AM21)/ABS(AM21), 1)))) -> - | AX21: =IF(AP21="-", "-", IF(AT21="-", "-", IF(ABS(AT21)=0, "-", ROUND(100*(AP21-AT21)/ABS(AT21), 1)))) -> - | AY21: =IF(AU21="-", "-", IF(AW21="-", "-", IF(ABS(AW21)=0, "-", ROUND(100*(AU21-AW21)/ABS(AW21), 1)))) -> - | AZ21: =IF(AV21="-", "-", IF(AX21="-", "-", IF(ABS(AX21)=0, "-", ROUND(100*(AV21-AX21)/ABS(AX21), 1)))) -> - | BD21: 農業共済金 | BT21: =IF(BL21="-", "-", IF(BP21="-", "-", IF(ABS(BP21)=0, "-", ROUND(100*(BL21-BP21)/ABS(BP21), 1)))) -> - | BU21: =IF(BQ21="-", "-", IF(BS21="-", "-", IF(ABS(BS21)=0, "-", ROUND(100*(BQ21-BS21)/ABS(BS21), 1)))) -> - | BV21: =IF(BR21="-", "-", IF(BT21="-", "-", IF(ABS(BT21)=0, "-", ROUND(100*(BR21-BT21)/ABS(BT21), 1)))) -> - | CE21: =IF(BW21="-", "-", IF(CA21="-", "-", IF(ABS(CA21)=0, "-", ROUND(100*(BW21-CA21)/ABS(CA21), 1)))) -> - | CF21: =IF(CB21="-", "-", IF(CD21="-", "-", IF(ABS(CD21)=0, "-", ROUND(100*(CB21-CD21)/ABS(CD21), 1)))) -> - | CG21: =IF(CC21="-", "-", IF(CE21="-", "-", IF(ABS(CE21)=0, "-", ROUND(100*(CC21-CE21)/ABS(CE21), 1)))) -> -
C22: 生産管理費 | Q22: =IF(I22="-", "-", IF(M22="-", "-", IF(ABS(M22)=0, "-", ROUND(100*(I22-M22)/ABS(M22), 1)))) -> - | R22: =IF(N22="-", "-", IF(P22="-", "-", IF(ABS(P22)=0, "-", ROUND(100*(N22-P22)/ABS(P22), 1)))) -> - | S22: =IF(O22="-", "-", IF(Q22="-", "-", IF(ABS(Q22)=0, "-", ROUND(100*(O22-Q22)/ABS(Q22), 1)))) -> - | AM22: =IF(AE22="-", "-", IF(AI22="-", "-", IF(ABS(AI22)=0, "-", ROUND(100*(AE22-AI22)/ABS(AI22), 1)))) -> - | AN22: =IF(AJ22="-", "-", IF(AL22="-", "-", IF(ABS(AL22)=0, "-", ROUND(100*(AJ22-AL22)/ABS(AL22), 1)))) -> - | AO22: =IF(AK22="-", "-", IF(AM22="-", "-", IF(ABS(AM22)=0, "-", ROUND(100*(AK22-AM22)/ABS(AM22), 1)))) -> - | AX22: =IF(AP22="-", "-", IF(AT22="-", "-", IF(ABS(AT22)=0, "-", ROUND(100*(AP22-AT22)/ABS(AT22), 1)))) -> - | AY22: =IF(AU22="-", "-", IF(AW22="-", "-", IF(ABS(AW22)=0, "-", ROUND(100*(AU22-AW22)/ABS(AW22), 1)))) -> - | AZ22: =IF(AV22="-", "-", IF(AX22="-", "-", IF(ABS(AX22)=0, "-", ROUND(100*(AV22-AX22)/ABS(AX22), 1)))) -> - | BD22: 畑作物の直接 支払交付金 | BH22: 面積払 | CE22: =IF(BW22="-", "-", IF(CA22="-", "-", IF(ABS(CA22)=0, "-", ROUND(100*(BW22-CA22)/ABS(CA22), 1)))) -> - | CF22: =IF(CB22="-", "-", IF(CD22="-", "-", IF(ABS(CD22)=0, "-", ROUND(100*(CB22-CD22)/ABS(CD22), 1)))) -> - | CG22: =IF(CC22="-", "-", IF(CE22="-", "-", IF(ABS(CE22)=0, "-", ROUND(100*(CC22-CE22)/ABS(CE22), 1)))) -> -
B23: 労働費 | Q23: =IF(I23="-", "-", IF(M23="-", "-", IF(ABS(M23)=0, "-", ROUND(100*(I23-M23)/ABS(M23), 1)))) -> - | R23: =IF(N23="-", "-", IF(P23="-", "-", IF(ABS(P23)=0, "-", ROUND(100*(N23-P23)/ABS(P23), 1)))) -> - | S23: =IF(O23="-", "-", IF(Q23="-", "-", IF(ABS(Q23)=0, "-", ROUND(100*(O23-Q23)/ABS(Q23), 1)))) -> - | AB23: =IF(T23="-", "-", IF(X23="-", "-", IF(ABS(X23)=0, "-", ROUND(100*(T23-X23)/ABS(X23), 1)))) -> - | AC23: =IF(Y23="-", "-", IF(AA23="-", "-", IF(ABS(AA23)=0, "-", ROUND(100*(Y23-AA23)/ABS(AA23), 1)))) -> - | AD23: =IF(Z23="-", "-", IF(AB23="-", "-", IF(ABS(AB23)=0, "-", ROUND(100*(Z23-AB23)/ABS(AB23), 1)))) -> - | AX23: =IF(AP23="-", "-", IF(AT23="-", "-", IF(ABS(AT23)=0, "-", ROUND(100*(AP23-AT23)/ABS(AT23), 1)))) -> - | AY23: =IF(AU23="-", "-", IF(AW23="-", "-", IF(ABS(AW23)=0, "-", ROUND(100*(AU23-AW23)/ABS(AW23), 1)))) -> - | AZ23: =IF(AV23="-", "-", IF(AX23="-", "-", IF(ABS(AX23)=0, "-", ROUND(100*(AV23-AX23)/ABS(AX23), 1)))) -> - | BH23: 数量払 | CE23: =IF(BW23="-", "-", IF(CA23="-", "-", IF(ABS(CA23)=0, "-", ROUND(100*(BW23-CA23)/ABS(CA23), 1)))) -> - | CF23: =IF(CB23="-", "-", IF(CD23="-", "-", IF(ABS(CD23)=0, "-", ROUND(100*(CB23-CD23)/ABS(CD23), 1)))) -> - | CG23: =IF(CC23="-", "-", IF(CE23="-", "-", IF(ABS(CE23)=0, "-", ROUND(100*(CC23-CE23)/ABS(CE23), 1)))) -> -
C24: 直接労働費 | Q24: =IF(I24="-", "-", IF(M24="-", "-", IF(ABS(M24)=0, "-", ROUND(100*(I24-M24)/ABS(M24), 1)))) -> - | R24: =IF(N24="-", "-", IF(P24="-", "-", IF(ABS(P24)=0, "-", ROUND(100*(N24-P24)/ABS(P24), 1)))) -> - | S24: =IF(O24="-", "-", IF(Q24="-", "-", IF(ABS(Q24)=0, "-", ROUND(100*(O24-Q24)/ABS(Q24), 1)))) -> - | AB24: =IF(T24="-", "-", IF(X24="-", "-", IF(ABS(X24)=0, "-", ROUND(100*(T24-X24)/ABS(X24), 1)))) -> - | AC24: =IF(Y24="-", "-", IF(AA24="-", "-", IF(ABS(AA24)=0, "-", ROUND(100*(Y24-AA24)/ABS(AA24), 1)))) -> - | AD24: =IF(Z24="-", "-", IF(AB24="-", "-", IF(ABS(AB24)=0, "-", ROUND(100*(Z24-AB24)/ABS(AB24), 1)))) -> - | AX24: =IF(AP24="-", "-", IF(AT24="-", "-", IF(ABS(AT24)=0, "-", ROUND(100*(AP24-AT24)/ABS(AT24), 1)))) -> - | AY24: =IF(AU24="-", "-", IF(AW24="-", "-", IF(ABS(AW24)=0, "-", ROUND(100*(AU24-AW24)/ABS(AW24), 1)))) -> - | AZ24: =IF(AV24="-", "-", IF(AX24="-", "-", IF(ABS(AX24)=0, "-", ROUND(100*(AV24-AX24)/ABS(AX24), 1)))) -> - | BD24: 水田活用の直接支払交付金 | CE24: =IF(BW24="-", "-", IF(CA24="-", "-", IF(ABS(CA24)=0, "-", ROUND(100*(BW24-CA24)/ABS(CA24), 1)))) -> - | CF24: =IF(CB24="-", "-", IF(CD24="-", "-", IF(ABS(CD24)=0, "-", ROUND(100*(CB24-CD24)/ABS(CD24), 1)))) -> - | CG24: =IF(CC24="-", "-", IF(CE24="-", "-", IF(ABS(CE24)=0, "-", ROUND(100*(CC24-CE24)/ABS(CE24), 1)))) -> -
C25: 間接労働費 | Q25: =IF(I25="-", "-", IF(M25="-", "-", IF(ABS(M25)=0, "-", ROUND(100*(I25-M25)/ABS(M25), 1)))) -> - | R25: =IF(N25="-", "-", IF(P25="-", "-", IF(ABS(P25)=0, "-", ROUND(100*(N25-P25)/ABS(P25), 1)))) -> - | S25: =IF(O25="-", "-", IF(Q25="-", "-", IF(ABS(Q25)=0, "-", ROUND(100*(O25-Q25)/ABS(Q25), 1)))) -> - | AB25: =IF(T25="-", "-", IF(X25="-", "-", IF(ABS(X25)=0, "-", ROUND(100*(T25-X25)/ABS(X25), 1)))) -> - | AC25: =IF(Y25="-", "-", IF(AA25="-", "-", IF(ABS(AA25)=0, "-", ROUND(100*(Y25-AA25)/ABS(AA25), 1)))) -> - | AD25: =IF(Z25="-", "-", IF(AB25="-", "-", IF(ABS(AB25)=0, "-", ROUND(100*(Z25-AB25)/ABS(AB25), 1)))) -> - | AX25: =IF(AP25="-", "-", IF(AT25="-", "-", IF(ABS(AT25)=0, "-", ROUND(100*(AP25-AT25)/ABS(AT25), 1)))) -> - | AY25: =IF(AU25="-", "-", IF(AW25="-", "-", IF(ABS(AW25)=0, "-", ROUND(100*(AU25-AW25)/ABS(AW25), 1)))) -> - | AZ25: =IF(AV25="-", "-", IF(AX25="-", "-", IF(ABS(AX25)=0, "-", ROUND(100*(AV25-AX25)/ABS(AX25), 1)))) -> - | BE25: 戦略作物助成 | CE25: =IF(BW25="-", "-", IF(CA25="-", "-", IF(ABS(CA25)=0, "-", ROUND(100*(BW25-CA25)/ABS(CA25), 1)))) -> - | CF25: =IF(CB25="-", "-", IF(CD25="-", "-", IF(ABS(CD25)=0, "-", ROUND(100*(CB25-CD25)/ABS(CD25), 1)))) -> - | CG25: =IF(CC25="-", "-", IF(CE25="-", "-", IF(ABS(CE25)=0, "-", ROUND(100*(CC25-CE25)/ABS(CE25), 1)))) -> -
B26: 費用合計 | Q26: =IF(I26="-", "-", IF(M26="-", "-", IF(ABS(M26)=0, "-", ROUND(100*(I26-M26)/ABS(M26), 1)))) -> - | R26: =IF(N26="-", "-", IF(P26="-", "-", IF(ABS(P26)=0, "-", ROUND(100*(N26-P26)/ABS(P26), 1)))) -> - | S26: =IF(O26="-", "-", IF(Q26="-", "-", IF(ABS(Q26)=0, "-", ROUND(100*(O26-Q26)/ABS(Q26), 1)))) -> - | AB26: =IF(T26="-", "-", IF(X26="-", "-", IF(ABS(X26)=0, "-", ROUND(100*(T26-X26)/ABS(X26), 1)))) -> - | AC26: =IF(Y26="-", "-", IF(AA26="-", "-", IF(ABS(AA26)=0, "-", ROUND(100*(Y26-AA26)/ABS(AA26), 1)))) -> - | AD26: =IF(Z26="-", "-", IF(AB26="-", "-", IF(ABS(AB26)=0, "-", ROUND(100*(Z26-AB26)/ABS(AB26), 1)))) -> - | AM26: =IF(AE26="-", "-", IF(AI26="-", "-", IF(ABS(AI26)=0, "-", ROUND(100*(AE26-AI26)/ABS(AI26), 1)))) -> - | AN26: =IF(AJ26="-", "-", IF(AL26="-", "-", IF(ABS(AL26)=0, "-", ROUND(100*(AJ26-AL26)/ABS(AL26), 1)))) -> - | AO26: =IF(AK26="-", "-", IF(AM26="-", "-", IF(ABS(AM26)=0, "-", ROUND(100*(AK26-AM26)/ABS(AM26), 1)))) -> - | AX26: =IF(AP26="-", "-", IF(AT26="-", "-", IF(ABS(AT26)=0, "-", ROUND(100*(AP26-AT26)/ABS(AT26), 1)))) -> - | AY26: =IF(AU26="-", "-", IF(AW26="-", "-", IF(ABS(AW26)=0, "-", ROUND(100*(AU26-AW26)/ABS(AW26), 1)))) -> - | AZ26: =IF(AV26="-", "-", IF(AX26="-", "-", IF(ABS(AX26)=0, "-", ROUND(100*(AV26-AX26)/ABS(AX26), 1)))) -> - | BE26: 産地交付金 | CE26: =IF(BW26="-", "-", IF(CA26="-", "-", IF(ABS(CA26)=0, "-", ROUND(100*(BW26-CA26)/ABS(CA26), 1)))) -> - | CF26: =IF(CB26="-", "-", IF(CD26="-", "-", IF(ABS(CD26)=0, "-", ROUND(100*(CB26-CD26)/ABS(CD26), 1)))) -> - | CG26: =IF(CC26="-", "-", IF(CE26="-", "-", IF(ABS(CE26)=0, "-", ROUND(100*(CC26-CE26)/ABS(CE26), 1)))) -> -
B27: 副産物価額 | AX27: =IF(AP27="-", "-", IF(AT27="-", "-", IF(ABS(AT27)=0, "-", ROUND(100*(AP27-AT27)/ABS(AT27), 1)))) -> - | AY27: =IF(AU27="-", "-", IF(AW27="-", "-", IF(ABS(AW27)=0, "-", ROUND(100*(AU27-AW27)/ABS(AW27), 1)))) -> - | AZ27: =IF(AV27="-", "-", IF(AX27="-", "-", IF(ABS(AX27)=0, "-", ROUND(100*(AV27-AX27)/ABS(AX27), 1)))) -> - | BT27: =IF(BL27="-", "-", IF(BP27="-", "-", IF(ABS(BP27)=0, "-", ROUND(100*(BL27-BP27)/ABS(BP27), 1)))) -> - | BU27: =IF(BQ27="-", "-", IF(BS27="-", "-", IF(ABS(BS27)=0, "-", ROUND(100*(BQ27-BS27)/ABS(BS27), 1)))) -> - | BV27: =IF(BR27="-", "-", IF(BT27="-", "-", IF(ABS(BT27)=0, "-", ROUND(100*(BR27-BT27)/ABS(BT27), 1)))) -> - | CE27: =IF(BW27="-", "-", IF(CA27="-", "-", IF(ABS(CA27)=0, "-", ROUND(100*(BW27-CA27)/ABS(CA27), 1)))) -> - | CF27: =IF(CB27="-", "-", IF(CD27="-", "-", IF(ABS(CD27)=0, "-", ROUND(100*(CB27-CD27)/ABS(CD27), 1)))) -> - | CG27: =IF(CC27="-", "-", IF(CE27="-", "-", IF(ABS(CE27)=0, "-", ROUND(100*(CC27-CE27)/ABS(CE27), 1)))) -> -
B28: 生産費 | AX28: =IF(AP28="-", "-", IF(AT28="-", "-", IF(ABS(AT28)=0, "-", ROUND(100*(AP28-AT28)/ABS(AT28), 1)))) -> - | AY28: =IF(AU28="-", "-", IF(AW28="-", "-", IF(ABS(AW28)=0, "-", ROUND(100*(AU28-AW28)/ABS(AW28), 1)))) -> - | AZ28: =IF(AV28="-", "-", IF(AX28="-", "-", IF(ABS(AX28)=0, "-", ROUND(100*(AV28-AX28)/ABS(AX28), 1)))) -> - | BT28: =IF(BL28="-", "-", IF(BP28="-", "-", IF(ABS(BP28)=0, "-", ROUND(100*(BL28-BP28)/ABS(BP28), 1)))) -> - | BU28: =IF(BQ28="-", "-", IF(BS28="-", "-", IF(ABS(BS28)=0, "-", ROUND(100*(BQ28-BS28)/ABS(BS28), 1)))) -> - | BV28: =IF(BR28="-", "-", IF(BT28="-", "-", IF(ABS(BT28)=0, "-", ROUND(100*(BR28-BT28)/ABS(BT28), 1)))) -> - | CE28: =IF(BW28="-", "-", IF(CA28="-", "-", IF(ABS(CA28)=0, "-", ROUND(100*(BW28-CA28)/ABS(CA28), 1)))) -> - | CF28: =IF(CB28="-", "-", IF(CD28="-", "-", IF(ABS(CD28)=0, "-", ROUND(100*(CB28-CD28)/ABS(CD28), 1)))) -> - | CG28: =IF(CC28="-", "-", IF(CE28="-", "-", IF(ABS(CE28)=0, "-", ROUND(100*(CC28-CE28)/ABS(CE28), 1)))) -> -
B29: 支払利子 | AX29: =IF(AP29="-", "-", IF(AT29="-", "-", IF(ABS(AT29)=0, "-", ROUND(100*(AP29-AT29)/ABS(AT29), 1)))) -> - | AY29: =IF(AU29="-", "-", IF(AW29="-", "-", IF(ABS(AW29)=0, "-", ROUND(100*(AU29-AW29)/ABS(AW29), 1)))) -> - | AZ29: =IF(AV29="-", "-", IF(AX29="-", "-", IF(ABS(AX29)=0, "-", ROUND(100*(AV29-AX29)/ABS(AX29), 1)))) -> - | BT29: =IF(BL29="-", "-", IF(BP29="-", "-", IF(ABS(BP29)=0, "-", ROUND(100*(BL29-BP29)/ABS(BP29), 1)))) -> - | BU29: =IF(BQ29="-", "-", IF(BS29="-", "-", IF(ABS(BS29)=0, "-", ROUND(100*(BQ29-BS29)/ABS(BS29), 1)))) -> - | BV29: =IF(BR29="-", "-", IF(BT29="-", "-", IF(ABS(BT29)=0, "-", ROUND(100*(BR29-BT29)/ABS(BT29), 1)))) -> - | CE29: =IF(BW29="-", "-", IF(CA29="-", "-", IF(ABS(CA29)=0, "-", ROUND(100*(BW29-CA29)/ABS(CA29), 1)))) -> - | CF29: =IF(CB29="-", "-", IF(CD29="-", "-", IF(ABS(CD29)=0, "-", ROUND(100*(CB29-CD29)/ABS(CD29), 1)))) -> - | CG29: =IF(CC29="-", "-", IF(CE29="-", "-", IF(ABS(CE29)=0, "-", ROUND(100*(CC29-CE29)/ABS(CE29), 1)))) -> -
B30: 支払地代 | AX30: =IF(AP30="-", "-", IF(AT30="-", "-", IF(ABS(AT30)=0, "-", ROUND(100*(AP30-AT30)/ABS(AT30), 1)))) -> - | AY30: =IF(AU30="-", "-", IF(AW30="-", "-", IF(ABS(AW30)=0, "-", ROUND(100*(AU30-AW30)/ABS(AW30), 1)))) -> - | AZ30: =IF(AV30="-", "-", IF(AX30="-", "-", IF(ABS(AX30)=0, "-", ROUND(100*(AV30-AX30)/ABS(AX30), 1)))) -> -
B31: 利子・地代算入生産費 | AX31: =IF(AP31="-", "-", IF(AT31="-", "-", IF(ABS(AT31)=0, "-", ROUND(100*(AP31-AT31)/ABS(AT31), 1)))) -> - | AY31: =IF(AU31="-", "-", IF(AW31="-", "-", IF(ABS(AW31)=0, "-", ROUND(100*(AU31-AW31)/ABS(AW31), 1)))) -> - | AZ31: =IF(AV31="-", "-", IF(AX31="-", "-", IF(ABS(AX31)=0, "-", ROUND(100*(AV31-AX31)/ABS(AX31), 1)))) -> -
B32: 自己資本利子 | AX32: =IF(AP32="-", "-", IF(AT32="-", "-", IF(ABS(AT32)=0, "-", ROUND(100*(AP32-AT32)/ABS(AT32), 1)))) -> - | AY32: =IF(AU32="-", "-", IF(AW32="-", "-", IF(ABS(AW32)=0, "-", ROUND(100*(AU32-AW32)/ABS(AW32), 1)))) -> - | AZ32: =IF(AV32="-", "-", IF(AX32="-", "-", IF(ABS(AX32)=0, "-", ROUND(100*(AV32-AX32)/ABS(AX32), 1)))) -> -
B33: 自作地地代 | AX33: =IF(AP33="-", "-", IF(AT33="-", "-", IF(ABS(AT33)=0, "-", ROUND(100*(AP33-AT33)/ABS(AT33), 1)))) -> - | AY33: =IF(AU33="-", "-", IF(AW33="-", "-", IF(ABS(AW33)=0, "-", ROUND(100*(AU33-AW33)/ABS(AW33), 1)))) -> - | AZ33: =IF(AV33="-", "-", IF(AX33="-", "-", IF(ABS(AX33)=0, "-", ROUND(100*(AV33-AX33)/ABS(AX33), 1)))) -> -
B34: 全算入生産費 | AX34: =IF(AP34="-", "-", IF(AT34="-", "-", IF(ABS(AT34)=0, "-", ROUND(100*(AP34-AT34)/ABS(AT34), 1)))) -> - | AY34: =IF(AU34="-", "-", IF(AW34="-", "-", IF(ABS(AW34)=0, "-", ROUND(100*(AU34-AW34)/ABS(AW34), 1)))) -> - | AZ34: =IF(AV34="-", "-", IF(AX34="-", "-", IF(ABS(AX34)=0, "-", ROUND(100*(AV34-AX34)/ABS(AX34), 1)))) -> -
B37: ２ 資本額及び資本利子 | AD37: 単位：円 | BD37: ６ 収益性 | BV37: 単位：円
I38: 資本額 | T38: 利子額 | BL38: =IF($B$1<>"",$B$1,"") -> 0 | BP38: =IF($B$1<>"",$B$1-1,"") -> -1 | BT38: 増減率
I39: =IF($B$1<>"",$B$1,"") -> 0 | M39: =IF($B$1<>"",$B$1-1,"") -> -1 | Q39: 増減率 | T39: =IF($B$1<>"",$B$1,"") -> 0 | X39: =IF($B$1<>"",$B$1-1,"") -> -1 | AB39: 増減率 | BD39: 粗収益 | BT39: =IF(BL39="-", "-", IF(BP39="-", "-", IF(ABS(BP39)=0, "-", ROUND(100*(BL39-BP39)/ABS(BP39), 1)))) -> - | BU39: =IF(BQ39="-", "-", IF(BS39="-", "-", IF(ABS(BS39)=0, "-", ROUND(100*(BQ39-BS39)/ABS(BS39), 1)))) -> - | BV39: =IF(BR39="-", "-", IF(BT39="-", "-", IF(ABS(BT39)=0, "-", ROUND(100*(BR39-BT39)/ABS(BT39), 1)))) -> -
B40: 資本額 | Q40: =IF(I40="-", "-", IF(M40="-", "-", IF(ABS(M40)=0, "-", ROUND(100*(I40-M40)/ABS(M40), 1)))) -> - | R40: =IF(N40="-", "-", IF(P40="-", "-", IF(ABS(P40)=0, "-", ROUND(100*(N40-P40)/ABS(P40), 1)))) -> - | S40: =IF(O40="-", "-", IF(Q40="-", "-", IF(ABS(Q40)=0, "-", ROUND(100*(O40-Q40)/ABS(Q40), 1)))) -> - | AB40: =IF(T40="-", "-", IF(X40="-", "-", IF(ABS(X40)=0, "-", ROUND(100*(T40-X40)/ABS(X40), 1)))) -> - | AC40: =IF(Y40="-", "-", IF(AA40="-", "-", IF(ABS(AA40)=0, "-", ROUND(100*(Y40-AA40)/ABS(AA40), 1)))) -> - | AD40: =IF(Z40="-", "-", IF(AB40="-", "-", IF(ABS(AB40)=0, "-", ROUND(100*(Z40-AB40)/ABS(AB40), 1)))) -> - | BD40: 生産費総額 | BT40: =IF(BL40="-", "-", IF(BP40="-", "-", IF(ABS(BP40)=0, "-", ROUND(100*(BL40-BP40)/ABS(BP40), 1)))) -> - | BU40: =IF(BQ40="-", "-", IF(BS40="-", "-", IF(ABS(BS40)=0, "-", ROUND(100*(BQ40-BS40)/ABS(BS40), 1)))) -> - | BV40: =IF(BR40="-", "-", IF(BT40="-", "-", IF(ABS(BT40)=0, "-", ROUND(100*(BR40-BT40)/ABS(BT40), 1)))) -> -
C41: 借入資本 | Q41: =IF(I41="-", "-", IF(M41="-", "-", IF(ABS(M41)=0, "-", ROUND(100*(I41-M41)/ABS(M41), 1)))) -> - | R41: =IF(N41="-", "-", IF(P41="-", "-", IF(ABS(P41)=0, "-", ROUND(100*(N41-P41)/ABS(P41), 1)))) -> - | S41: =IF(O41="-", "-", IF(Q41="-", "-", IF(ABS(Q41)=0, "-", ROUND(100*(O41-Q41)/ABS(Q41), 1)))) -> - | AB41: =IF(T41="-", "-", IF(X41="-", "-", IF(ABS(X41)=0, "-", ROUND(100*(T41-X41)/ABS(X41), 1)))) -> - | AC41: =IF(Y41="-", "-", IF(AA41="-", "-", IF(ABS(AA41)=0, "-", ROUND(100*(Y41-AA41)/ABS(AA41), 1)))) -> - | AD41: =IF(Z41="-", "-", IF(AB41="-", "-", IF(ABS(AB41)=0, "-", ROUND(100*(Z41-AB41)/ABS(AB41), 1)))) -> - | BD41: 利潤 | BT41: =IF(BL41="-", "-", IF(BP41="-", "-", IF(ABS(BP41)=0, "-", ROUND(100*(BL41-BP41)/ABS(BP41), 1)))) -> - | BU41: =IF(BQ41="-", "-", IF(BS41="-", "-", IF(ABS(BS41)=0, "-", ROUND(100*(BQ41-BS41)/ABS(BS41), 1)))) -> - | BV41: =IF(BR41="-", "-", IF(BT41="-", "-", IF(ABS(BT41)=0, "-", ROUND(100*(BR41-BT41)/ABS(BT41), 1)))) -> -
C42: 自己資本 | Q42: =IF(I42="-", "-", IF(M42="-", "-", IF(ABS(M42)=0, "-", ROUND(100*(I42-M42)/ABS(M42), 1)))) -> - | R42: =IF(N42="-", "-", IF(P42="-", "-", IF(ABS(P42)=0, "-", ROUND(100*(N42-P42)/ABS(P42), 1)))) -> - | S42: =IF(O42="-", "-", IF(Q42="-", "-", IF(ABS(Q42)=0, "-", ROUND(100*(O42-Q42)/ABS(Q42), 1)))) -> - | AB42: =IF(T42="-", "-", IF(X42="-", "-", IF(ABS(X42)=0, "-", ROUND(100*(T42-X42)/ABS(X42), 1)))) -> - | AC42: =IF(Y42="-", "-", IF(AA42="-", "-", IF(ABS(AA42)=0, "-", ROUND(100*(Y42-AA42)/ABS(AA42), 1)))) -> - | AD42: =IF(Z42="-", "-", IF(AB42="-", "-", IF(ABS(AB42)=0, "-", ROUND(100*(Z42-AB42)/ABS(AB42), 1)))) -> - | BD42: 所得 | BT42: =IF(BL42="-", "-", IF(BP42="-", "-", IF(ABS(BP42)=0, "-", ROUND(100*(BL42-BP42)/ABS(BP42), 1)))) -> - | BU42: =IF(BQ42="-", "-", IF(BS42="-", "-", IF(ABS(BS42)=0, "-", ROUND(100*(BQ42-BS42)/ABS(BS42), 1)))) -> - | BV42: =IF(BR42="-", "-", IF(BT42="-", "-", IF(ABS(BT42)=0, "-", ROUND(100*(BR42-BT42)/ABS(BT42), 1)))) -> -
B43: 資産別内訳 | C43: 流動資本 | Q43: =IF(I43="-", "-", IF(M43="-", "-", IF(ABS(M43)=0, "-", ROUND(100*(I43-M43)/ABS(M43), 1)))) -> - | R43: =IF(N43="-", "-", IF(P43="-", "-", IF(ABS(P43)=0, "-", ROUND(100*(N43-P43)/ABS(P43), 1)))) -> - | S43: =IF(O43="-", "-", IF(Q43="-", "-", IF(ABS(Q43)=0, "-", ROUND(100*(O43-Q43)/ABS(Q43), 1)))) -> - | BE43: １日当たり | BT43: =IF(BL43="-", "-", IF(BP43="-", "-", IF(ABS(BP43)=0, "-", ROUND(100*(BL43-BP43)/ABS(BP43), 1)))) -> - | BU43: =IF(BQ43="-", "-", IF(BS43="-", "-", IF(ABS(BS43)=0, "-", ROUND(100*(BQ43-BS43)/ABS(BS43), 1)))) -> - | BV43: =IF(BR43="-", "-", IF(BT43="-", "-", IF(ABS(BT43)=0, "-", ROUND(100*(BR43-BT43)/ABS(BT43), 1)))) -> -
C44: 労賃資本 | Q44: =IF(I44="-", "-", IF(M44="-", "-", IF(ABS(M44)=0, "-", ROUND(100*(I44-M44)/ABS(M44), 1)))) -> - | R44: =IF(N44="-", "-", IF(P44="-", "-", IF(ABS(P44)=0, "-", ROUND(100*(N44-P44)/ABS(P44), 1)))) -> - | S44: =IF(O44="-", "-", IF(Q44="-", "-", IF(ABS(Q44)=0, "-", ROUND(100*(O44-Q44)/ABS(Q44), 1)))) -> - | BD44: 構成員労働報酬 | BT44: =IF(BL44="-", "-", IF(BP44="-", "-", IF(ABS(BP44)=0, "-", ROUND(100*(BL44-BP44)/ABS(BP44), 1)))) -> - | BU44: =IF(BQ44="-", "-", IF(BS44="-", "-", IF(ABS(BS44)=0, "-", ROUND(100*(BQ44-BS44)/ABS(BS44), 1)))) -> - | BV44: =IF(BR44="-", "-", IF(BT44="-", "-", IF(ABS(BT44)=0, "-", ROUND(100*(BR44-BT44)/ABS(BT44), 1)))) -> -
C45: 固定資本 | Q45: =IF(I45="-", "-", IF(M45="-", "-", IF(ABS(M45)=0, "-", ROUND(100*(I45-M45)/ABS(M45), 1)))) -> - | R45: =IF(N45="-", "-", IF(P45="-", "-", IF(ABS(P45)=0, "-", ROUND(100*(N45-P45)/ABS(P45), 1)))) -> - | S45: =IF(O45="-", "-", IF(Q45="-", "-", IF(ABS(Q45)=0, "-", ROUND(100*(O45-Q45)/ABS(Q45), 1)))) -> - | BE45: １日当たり | BT45: =IF(BL45="-", "-", IF(BP45="-", "-", IF(ABS(BP45)=0, "-", ROUND(100*(BL45-BP45)/ABS(BP45), 1)))) -> - | BU45: =IF(BQ45="-", "-", IF(BS45="-", "-", IF(ABS(BS45)=0, "-", ROUND(100*(BQ45-BS45)/ABS(BS45), 1)))) -> - | BV45: =IF(BR45="-", "-", IF(BT45="-", "-", IF(ABS(BT45)=0, "-", ROUND(100*(BR45-BT45)/ABS(BT45), 1)))) -> -
D46: 建物・構築物 | Q46: =IF(I46="-", "-", IF(M46="-", "-", IF(ABS(M46)=0, "-", ROUND(100*(I46-M46)/ABS(M46), 1)))) -> - | R46: =IF(N46="-", "-", IF(P46="-", "-", IF(ABS(P46)=0, "-", ROUND(100*(N46-P46)/ABS(P46), 1)))) -> - | S46: =IF(O46="-", "-", IF(Q46="-", "-", IF(ABS(Q46)=0, "-", ROUND(100*(O46-Q46)/ABS(Q46), 1)))) -> -
D47: 土地改良設備 | Q47: =IF(I47="-", "-", IF(M47="-", "-", IF(ABS(M47)=0, "-", ROUND(100*(I47-M47)/ABS(M47), 1)))) -> - | R47: =IF(N47="-", "-", IF(P47="-", "-", IF(ABS(P47)=0, "-", ROUND(100*(N47-P47)/ABS(P47), 1)))) -> - | S47: =IF(O47="-", "-", IF(Q47="-", "-", IF(ABS(Q47)=0, "-", ROUND(100*(O47-Q47)/ABS(Q47), 1)))) -> -
D48: 自動車 | Q48: =IF(I48="-", "-", IF(M48="-", "-", IF(ABS(M48)=0, "-", ROUND(100*(I48-M48)/ABS(M48), 1)))) -> - | R48: =IF(N48="-", "-", IF(P48="-", "-", IF(ABS(P48)=0, "-", ROUND(100*(N48-P48)/ABS(P48), 1)))) -> - | S48: =IF(O48="-", "-", IF(Q48="-", "-", IF(ABS(Q48)=0, "-", ROUND(100*(O48-Q48)/ABS(Q48), 1)))) -> - | BD48: ［参考］各種助成措置を加えた場合 | BV48: 単位：円
D49: 農機具等 | Q49: =IF(I49="-", "-", IF(M49="-", "-", IF(ABS(M49)=0, "-", ROUND(100*(I49-M49)/ABS(M49), 1)))) -> - | R49: =IF(N49="-", "-", IF(P49="-", "-", IF(ABS(P49)=0, "-", ROUND(100*(N49-P49)/ABS(P49), 1)))) -> - | S49: =IF(O49="-", "-", IF(Q49="-", "-", IF(ABS(Q49)=0, "-", ROUND(100*(O49-Q49)/ABS(Q49), 1)))) -> - | BL49: =IF($B$1<>"",$B$1,"") -> 0 | BP49: =IF($B$1<>"",$B$1-1,"") -> -1 | BT49: 増減率
BD50: 粗収益 | BT50: =IF(BL50="-", "-", IF(BP50="-", "-", IF(ABS(BP50)=0, "-", ROUND(100*(BL50-BP50)/ABS(BP50), 1)))) -> - | BU50: =IF(BQ50="-", "-", IF(BS50="-", "-", IF(ABS(BS50)=0, "-", ROUND(100*(BQ50-BS50)/ABS(BS50), 1)))) -> - | BV50: =IF(BR50="-", "-", IF(BT50="-", "-", IF(ABS(BT50)=0, "-", ROUND(100*(BR50-BT50)/ABS(BT50), 1)))) -> -
BD51: 生産費総額 | BT51: =IF(BL51="-", "-", IF(BP51="-", "-", IF(ABS(BP51)=0, "-", ROUND(100*(BL51-BP51)/ABS(BP51), 1)))) -> - | BU51: =IF(BQ51="-", "-", IF(BS51="-", "-", IF(ABS(BS51)=0, "-", ROUND(100*(BQ51-BS51)/ABS(BS51), 1)))) -> - | BV51: =IF(BR51="-", "-", IF(BT51="-", "-", IF(ABS(BT51)=0, "-", ROUND(100*(BR51-BT51)/ABS(BT51), 1)))) -> -
B52: ３ 借入金 | AD52: 単位：円 | BD52: 利潤 | BT52: =IF(BL52="-", "-", IF(BP52="-", "-", IF(ABS(BP52)=0, "-", ROUND(100*(BL52-BP52)/ABS(BP52), 1)))) -> - | BU52: =IF(BQ52="-", "-", IF(BS52="-", "-", IF(ABS(BS52)=0, "-", ROUND(100*(BQ52-BS52)/ABS(BS52), 1)))) -> - | BV52: =IF(BR52="-", "-", IF(BT52="-", "-", IF(ABS(BT52)=0, "-", ROUND(100*(BR52-BT52)/ABS(BT52), 1)))) -> -
I53: 調査開始時未償還残高 | T53: 利子額 | BD53: 所得 | BT53: =IF(BL53="-", "-", IF(BP53="-", "-", IF(ABS(BP53)=0, "-", ROUND(100*(BL53-BP53)/ABS(BP53), 1)))) -> - | BU53: =IF(BQ53="-", "-", IF(BS53="-", "-", IF(ABS(BS53)=0, "-", ROUND(100*(BQ53-BS53)/ABS(BS53), 1)))) -> - | BV53: =IF(BR53="-", "-", IF(BT53="-", "-", IF(ABS(BT53)=0, "-", ROUND(100*(BR53-BT53)/ABS(BT53), 1)))) -> -
I54: =IF($B$1<>"",$B$1,"") -> 0 | M54: =IF($B$1<>"",$B$1-1,"") -> -1 | Q54: 増減率 | T54: =IF($B$1<>"",$B$1,"") -> 0 | X54: =IF($B$1<>"",$B$1-1,"") -> -1 | AB54: 増減率 | BE54: １日当たり | BT54: =IF(BL54="-", "-", IF(BP54="-", "-", IF(ABS(BP54)=0, "-", ROUND(100*(BL54-BP54)/ABS(BP54), 1)))) -> - | BU54: =IF(BQ54="-", "-", IF(BS54="-", "-", IF(ABS(BS54)=0, "-", ROUND(100*(BQ54-BS54)/ABS(BS54), 1)))) -> - | BV54: =IF(BR54="-", "-", IF(BT54="-", "-", IF(ABS(BT54)=0, "-", ROUND(100*(BR54-BT54)/ABS(BT54), 1)))) -> -
B55: 借入金 | Q55: =IF(I55="-", "-", IF(M55="-", "-", IF(ABS(M55)=0, "-", ROUND(100*(I55-M55)/ABS(M55), 1)))) -> - | R55: =IF(N55="-", "-", IF(P55="-", "-", IF(ABS(P55)=0, "-", ROUND(100*(N55-P55)/ABS(P55), 1)))) -> - | S55: =IF(O55="-", "-", IF(Q55="-", "-", IF(ABS(Q55)=0, "-", ROUND(100*(O55-Q55)/ABS(Q55), 1)))) -> - | AB55: =IF(T55="-", "-", IF(X55="-", "-", IF(ABS(X55)=0, "-", ROUND(100*(T55-X55)/ABS(X55), 1)))) -> - | AC55: =IF(Y55="-", "-", IF(AA55="-", "-", IF(ABS(AA55)=0, "-", ROUND(100*(Y55-AA55)/ABS(AA55), 1)))) -> - | AD55: =IF(Z55="-", "-", IF(AB55="-", "-", IF(ABS(AB55)=0, "-", ROUND(100*(Z55-AB55)/ABS(AB55), 1)))) -> - | BD55: 構成員労働報酬 | BT55: =IF(BL55="-", "-", IF(BP55="-", "-", IF(ABS(BP55)=0, "-", ROUND(100*(BL55-BP55)/ABS(BP55), 1)))) -> - | BU55: =IF(BQ55="-", "-", IF(BS55="-", "-", IF(ABS(BS55)=0, "-", ROUND(100*(BQ55-BS55)/ABS(BS55), 1)))) -> - | BV55: =IF(BR55="-", "-", IF(BT55="-", "-", IF(ABS(BT55)=0, "-", ROUND(100*(BR55-BT55)/ABS(BT55), 1)))) -> -
BE56: １日当たり | BT56: =IF(BL56="-", "-", IF(BP56="-", "-", IF(ABS(BP56)=0, "-", ROUND(100*(BL56-BP56)/ABS(BP56), 1)))) -> - | BU56: =IF(BQ56="-", "-", IF(BS56="-", "-", IF(ABS(BS56)=0, "-", ROUND(100*(BQ56-BS56)/ABS(BS56), 1)))) -> - | BV56: =IF(BR56="-", "-", IF(BT56="-", "-", IF(ABS(BT56)=0, "-", ROUND(100*(BR56-BT56)/ABS(BT56), 1)))) -> -

Sheet No.2
B1: =AB4 | E1: 年産 組織法人経営体に関する経営分析調査（麦類・そば・なたね・畑作物生産費（組織法人経営）） 集計結果検討表 Ｎｏ．２
G3: 集計番号 | J3: 集計名称 | Q3: 集計経営体数 | V3: 集計倍率 | AB3: 調査年 | AG3: 都道府県等 | AL3: 経営種類 | AQ3: 生産費区分 | AV3: 規模階層 | BA3: 平均値種類 | BF3: 加重・総和の別 | BK3: 集計区分 | BP3: 田畑区分 | BU3: ビール麦販売区分 | BZ3: てんさい栽培区分
B4: 本年産 | G4: =IF(No.1!G4="","",No.1!G4) | H4: =IF(No.1!H4="","",No.1!H4) | I4: =IF(No.1!I4="","",No.1!I4) | J4: =IF(No.1!J4="","",No.1!J4) | K4: =IF(No.1!K4="","",No.1!K4) | L4: =IF(No.1!L4="","",No.1!L4) | M4: =IF(No.1!M4="","",No.1!M4) | N4: =IF(No.1!N4="","",No.1!N4) | ... Z4: =IF(No.1!Z4="","",No.1!Z4) | AB4: =IF(No.1!AB4="","",No.1!AB4) | AC4: =IF(No.1!AC4="","",No.1!AC4) | AD4: =IF(No.1!AD4="","",No.1!AD4) | AE4: =IF(No.1!AE4="","",No.1!AE4) | AF4: =IF(No.1!AF4="","",No.1!AF4) | AG4: =IF(No.1!AG4="","",No.1!AG4) | AH4: =IF(No.1!AH4="","",No.1!AH4) | AI4: =IF(No.1!AI4="","",No.1!AI4) | ... CD4: =IF(No.1!CD4="","",No.1!CD4)
B5: 前年産 | G5: =IF(No.1!G5="","",No.1!G5) | H5: =IF(No.1!H5="","",No.1!H5) | I5: =IF(No.1!I5="","",No.1!I5) | J5: =IF(No.1!J5="","",No.1!J5) | K5: =IF(No.1!K5="","",No.1!K5) | L5: =IF(No.1!L5="","",No.1!L5) | M5: =IF(No.1!M5="","",No.1!M5) | N5: =IF(No.1!N5="","",No.1!N5) | ... Z5: =IF(No.1!Z5="","",No.1!Z5)
B7: ７ 経営耕地（１経営体当たり） | AO7: 単位：ａ | AT7: 14 地 代（面積は１経営体当たり） | CG7: 単位：円、ａ
I8: 所有地 | T8: 借入地 | AE8: 計 | BA8: 自作地 | BL8: 借入地 | BW8: 計
I9: =IF($B$1<>"",$B$1,"") | M9: =IF($B$1<>"",$B$1-1,"") | Q9: 増減率 | T9: =IF($B$1<>"",$B$1,"") | X9: =IF($B$1<>"",$B$1-1,"") | AB9: 増減率 | AE9: =IF($B$1<>"",$B$1,"") | AI9: =IF($B$1<>"",$B$1-1,"") | AM9: 増減率 | BA9: =IF($B$1<>"",$B$1,"") | BE9: =IF($B$1<>"",$B$1-1,"") | BI9: 増減率 | BL9: =IF($B$1<>"",$B$1,"") | BP9: =IF($B$1<>"",$B$1-1,"") | BT9: 増減率 | BW9: =IF($B$1<>"",$B$1,"") | CA9: =IF($B$1<>"",$B$1-1,"") | CE9: 増減率
B10: 田 | Q10: =IF(I10="-", "-", IF(M10="-", "-", IF(ABS(M10)=0, "-", ROUND(100*(I10-M10)/ABS(M10), 1)))) -> - | R10: =IF(N10="-", "-", IF(P10="-", "-", IF(ABS(P10)=0, "-", ROUND(100*(N10-P10)/ABS(P10), 1)))) -> - | S10: =IF(O10="-", "-", IF(Q10="-", "-", IF(ABS(Q10)=0, "-", ROUND(100*(O10-Q10)/ABS(Q10), 1)))) -> - | AB10: =IF(T10="-", "-", IF(X10="-", "-", IF(ABS(X10)=0, "-", ROUND(100*(T10-X10)/ABS(X10), 1)))) -> - | AC10: =IF(Y10="-", "-", IF(AA10="-", "-", IF(ABS(AA10)=0, "-", ROUND(100*(Y10-AA10)/ABS(AA10), 1)))) -> - | AD10: =IF(Z10="-", "-", IF(AB10="-", "-", IF(ABS(AB10)=0, "-", ROUND(100*(Z10-AB10)/ABS(AB10), 1)))) -> - | AM10: =IF(AE10="-", "-", IF(AI10="-", "-", IF(ABS(AI10)=0, "-", ROUND(100*(AE10-AI10)/ABS(AI10), 1)))) -> - | AN10: =IF(AJ10="-", "-", IF(AL10="-", "-", IF(ABS(AL10)=0, "-", ROUND(100*(AJ10-AL10)/ABS(AL10), 1)))) -> - | AO10: =IF(AK10="-", "-", IF(AM10="-", "-", IF(ABS(AM10)=0, "-", ROUND(100*(AK10-AM10)/ABS(AM10), 1)))) -> - | AT10: 作付地 | AV10: 作付実面積 | BI10: =IF(BA10="-", "-", IF(BE10="-", "-", IF(ABS(BE10)=0, "-", ROUND(100*(BA10-BE10)/ABS(BE10), 1)))) -> - | BJ10: =IF(BF10="-", "-", IF(BH10="-", "-", IF(ABS(BH10)=0, "-", ROUND(100*(BF10-BH10)/ABS(BH10), 1)))) -> - | BK10: =IF(BG10="-", "-", IF(BI10="-", "-", IF(ABS(BI10)=0, "-", ROUND(100*(BG10-BI10)/ABS(BI10), 1)))) -> - | BT10: =IF(BL10="-", "-", IF(BP10="-", "-", IF(ABS(BP10)=0, "-", ROUND(100*(BL10-BP10)/ABS(BP10), 1)))) -> - | BU10: =IF(BQ10="-", "-", IF(BS10="-", "-", IF(ABS(BS10)=0, "-", ROUND(100*(BQ10-BS10)/ABS(BS10), 1)))) -> - | BV10: =IF(BR10="-", "-", IF(BT10="-", "-", IF(ABS(BT10)=0, "-", ROUND(100*(BR10-BT10)/ABS(BT10), 1)))) -> - | CE10: =IF(BW10="-", "-", IF(CA10="-", "-", IF(ABS(CA10)=0, "-", ROUND(100*(BW10-CA10)/ABS(CA10), 1)))) -> - | CF10: =IF(CB10="-", "-", IF(CD10="-", "-", IF(ABS(CD10)=0, "-", ROUND(100*(CB10-CD10)/ABS(CD10), 1)))) -> - | CG10: =IF(CC10="-", "-", IF(CE10="-", "-", IF(ABS(CE10)=0, "-", ROUND(100*(CC10-CE10)/ABS(CE10), 1)))) -> -
B11: 普通畑 | Q11: =IF(I11="-", "-", IF(M11="-", "-", IF(ABS(M11)=0, "-", ROUND(100*(I11-M11)/ABS(M11), 1)))) -> - | R11: =IF(N11="-", "-", IF(P11="-", "-", IF(ABS(P11)=0, "-", ROUND(100*(N11-P11)/ABS(P11), 1)))) -> - | S11: =IF(O11="-", "-", IF(Q11="-", "-", IF(ABS(Q11)=0, "-", ROUND(100*(O11-Q11)/ABS(Q11), 1)))) -> - | AB11: =IF(T11="-", "-", IF(X11="-", "-", IF(ABS(X11)=0, "-", ROUND(100*(T11-X11)/ABS(X11), 1)))) -> - | AC11: =IF(Y11="-", "-", IF(AA11="-", "-", IF(ABS(AA11)=0, "-", ROUND(100*(Y11-AA11)/ABS(AA11), 1)))) -> - | AD11: =IF(Z11="-", "-", IF(AB11="-", "-", IF(ABS(AB11)=0, "-", ROUND(100*(Z11-AB11)/ABS(AB11), 1)))) -> - | AM11: =IF(AE11="-", "-", IF(AI11="-", "-", IF(ABS(AI11)=0, "-", ROUND(100*(AE11-AI11)/ABS(AI11), 1)))) -> - | AN11: =IF(AJ11="-", "-", IF(AL11="-", "-", IF(ABS(AL11)=0, "-", ROUND(100*(AJ11-AL11)/ABS(AL11), 1)))) -> - | AO11: =IF(AK11="-", "-", IF(AM11="-", "-", IF(ABS(AM11)=0, "-", ROUND(100*(AK11-AM11)/ABS(AM11), 1)))) -> - | AV11: 土地台帳面積 | BI11: =IF(BA11="-", "-", IF(BE11="-", "-", IF(ABS(BE11)=0, "-", ROUND(100*(BA11-BE11)/ABS(BE11), 1)))) -> - | BJ11: =IF(BF11="-", "-", IF(BH11="-", "-", IF(ABS(BH11)=0, "-", ROUND(100*(BF11-BH11)/ABS(BH11), 1)))) -> - | BK11: =IF(BG11="-", "-", IF(BI11="-", "-", IF(ABS(BI11)=0, "-", ROUND(100*(BG11-BI11)/ABS(BI11), 1)))) -> - | BT11: =IF(BL11="-", "-", IF(BP11="-", "-", IF(ABS(BP11)=0, "-", ROUND(100*(BL11-BP11)/ABS(BP11), 1)))) -> - | BU11: =IF(BQ11="-", "-", IF(BS11="-", "-", IF(ABS(BS11)=0, "-", ROUND(100*(BQ11-BS11)/ABS(BS11), 1)))) -> - | BV11: =IF(BR11="-", "-", IF(BT11="-", "-", IF(ABS(BT11)=0, "-", ROUND(100*(BR11-BT11)/ABS(BT11), 1)))) -> - | CE11: =IF(BW11="-", "-", IF(CA11="-", "-", IF(ABS(CA11)=0, "-", ROUND(100*(BW11-CA11)/ABS(CA11), 1)))) -> - | CF11: =IF(CB11="-", "-", IF(CD11="-", "-", IF(ABS(CD11)=0, "-", ROUND(100*(CB11-CD11)/ABS(CD11), 1)))) -> - | CG11: =IF(CC11="-", "-", IF(CE11="-", "-", IF(ABS(CE11)=0, "-", ROUND(100*(CC11-CE11)/ABS(CE11), 1)))) -> -
B12: 樹園地 | Q12: =IF(I12="-", "-", IF(M12="-", "-", IF(ABS(M12)=0, "-", ROUND(100*(I12-M12)/ABS(M12), 1)))) -> - | R12: =IF(N12="-", "-", IF(P12="-", "-", IF(ABS(P12)=0, "-", ROUND(100*(N12-P12)/ABS(P12), 1)))) -> - | S12: =IF(O12="-", "-", IF(Q12="-", "-", IF(ABS(Q12)=0, "-", ROUND(100*(O12-Q12)/ABS(Q12), 1)))) -> - | AB12: =IF(T12="-", "-", IF(X12="-", "-", IF(ABS(X12)=0, "-", ROUND(100*(T12-X12)/ABS(X12), 1)))) -> - | AC12: =IF(Y12="-", "-", IF(AA12="-", "-", IF(ABS(AA12)=0, "-", ROUND(100*(Y12-AA12)/ABS(AA12), 1)))) -> - | AD12: =IF(Z12="-", "-", IF(AB12="-", "-", IF(ABS(AB12)=0, "-", ROUND(100*(Z12-AB12)/ABS(AB12), 1)))) -> - | AM12: =IF(AE12="-", "-", IF(AI12="-", "-", IF(ABS(AI12)=0, "-", ROUND(100*(AE12-AI12)/ABS(AI12), 1)))) -> - | AN12: =IF(AJ12="-", "-", IF(AL12="-", "-", IF(ABS(AL12)=0, "-", ROUND(100*(AJ12-AL12)/ABS(AL12), 1)))) -> - | AO12: =IF(AK12="-", "-", IF(AM12="-", "-", IF(ABS(AM12)=0, "-", ROUND(100*(AK12-AM12)/ABS(AM12), 1)))) -> - | AV12: 地代総額 | BI12: =IF(BA12="-", "-", IF(BE12="-", "-", IF(ABS(BE12)=0, "-", ROUND(100*(BA12-BE12)/ABS(BE12), 1)))) -> - | BJ12: =IF(BF12="-", "-", IF(BH12="-", "-", IF(ABS(BH12)=0, "-", ROUND(100*(BF12-BH12)/ABS(BH12), 1)))) -> - | BK12: =IF(BG12="-", "-", IF(BI12="-", "-", IF(ABS(BI12)=0, "-", ROUND(100*(BG12-BI12)/ABS(BI12), 1)))) -> - | BT12: =IF(BL12="-", "-", IF(BP12="-", "-", IF(ABS(BP12)=0, "-", ROUND(100*(BL12-BP12)/ABS(BP12), 1)))) -> - | BU12: =IF(BQ12="-", "-", IF(BS12="-", "-", IF(ABS(BS12)=0, "-", ROUND(100*(BQ12-BS12)/ABS(BS12), 1)))) -> - | BV12: =IF(BR12="-", "-", IF(BT12="-", "-", IF(ABS(BT12)=0, "-", ROUND(100*(BR12-BT12)/ABS(BT12), 1)))) -> - | CE12: =IF(BW12="-", "-", IF(CA12="-", "-", IF(ABS(CA12)=0, "-", ROUND(100*(BW12-CA12)/ABS(CA12), 1)))) -> - | CF12: =IF(CB12="-", "-", IF(CD12="-", "-", IF(ABS(CD12)=0, "-", ROUND(100*(CB12-CD12)/ABS(CD12), 1)))) -> - | CG12: =IF(CC12="-", "-", IF(CE12="-", "-", IF(ABS(CE12)=0, "-", ROUND(100*(CC12-CE12)/ABS(CE12), 1)))) -> -
B13: 牧草地 | Q13: =IF(I13="-", "-", IF(M13="-", "-", IF(ABS(M13)=0, "-", ROUND(100*(I13-M13)/ABS(M13), 1)))) -> - | AB13: =IF(T13="-", "-", IF(X13="-", "-", IF(ABS(X13)=0, "-", ROUND(100*(T13-X13)/ABS(X13), 1)))) -> - | AM13: =IF(AE13="-", "-", IF(AI13="-", "-", IF(ABS(AI13)=0, "-", ROUND(100*(AE13-AI13)/ABS(AI13), 1)))) -> - | AV13: 負担地代 | BI13: =IF(BA13="-", "-", IF(BE13="-", "-", IF(ABS(BE13)=0, "-", ROUND(100*(BA13-BE13)/ABS(BE13), 1)))) -> - | BJ13: =IF(BF13="-", "-", IF(BH13="-", "-", IF(ABS(BH13)=0, "-", ROUND(100*(BF13-BH13)/ABS(BH13), 1)))) -> - | BK13: =IF(BG13="-", "-", IF(BI13="-", "-", IF(ABS(BI13)=0, "-", ROUND(100*(BG13-BI13)/ABS(BI13), 1)))) -> - | BT13: =IF(BL13="-", "-", IF(BP13="-", "-", IF(ABS(BP13)=0, "-", ROUND(100*(BL13-BP13)/ABS(BP13), 1)))) -> - | BU13: =IF(BQ13="-", "-", IF(BS13="-", "-", IF(ABS(BS13)=0, "-", ROUND(100*(BQ13-BS13)/ABS(BS13), 1)))) -> - | BV13: =IF(BR13="-", "-", IF(BT13="-", "-", IF(ABS(BT13)=0, "-", ROUND(100*(BR13-BT13)/ABS(BT13), 1)))) -> - | CE13: =IF(BW13="-", "-", IF(CA13="-", "-", IF(ABS(CA13)=0, "-", ROUND(100*(BW13-CA13)/ABS(CA13), 1)))) -> - | CF13: =IF(CB13="-", "-", IF(CD13="-", "-", IF(ABS(CD13)=0, "-", ROUND(100*(CB13-CD13)/ABS(CD13), 1)))) -> - | CG13: =IF(CC13="-", "-", IF(CE13="-", "-", IF(ABS(CE13)=0, "-", ROUND(100*(CC13-CE13)/ABS(CE13), 1)))) -> -
B14: 計 | Q14: =IF(I14="-", "-", IF(M14="-", "-", IF(ABS(M14)=0, "-", ROUND(100*(I14-M14)/ABS(M14), 1)))) -> - | R14: =IF(N14="-", "-", IF(P14="-", "-", IF(ABS(P14)=0, "-", ROUND(100*(N14-P14)/ABS(P14), 1)))) -> - | S14: =IF(O14="-", "-", IF(Q14="-", "-", IF(ABS(Q14)=0, "-", ROUND(100*(O14-Q14)/ABS(Q14), 1)))) -> - | AB14: =IF(T14="-", "-", IF(X14="-", "-", IF(ABS(X14)=0, "-", ROUND(100*(T14-X14)/ABS(X14), 1)))) -> - | AC14: =IF(Y14="-", "-", IF(AA14="-", "-", IF(ABS(AA14)=0, "-", ROUND(100*(Y14-AA14)/ABS(AA14), 1)))) -> - | AD14: =IF(Z14="-", "-", IF(AB14="-", "-", IF(ABS(AB14)=0, "-", ROUND(100*(Z14-AB14)/ABS(AB14), 1)))) -> - | AM14: =IF(AE14="-", "-", IF(AI14="-", "-", IF(ABS(AI14)=0, "-", ROUND(100*(AE14-AI14)/ABS(AI14), 1)))) -> - | AN14: =IF(AJ14="-", "-", IF(AL14="-", "-", IF(ABS(AL14)=0, "-", ROUND(100*(AJ14-AL14)/ABS(AL14), 1)))) -> - | AO14: =IF(AK14="-", "-", IF(AM14="-", "-", IF(ABS(AM14)=0, "-", ROUND(100*(AK14-AM14)/ABS(AM14), 1)))) -> - | AT14: 以 外作付地 | AV14: 使用面積 | BI14: =IF(BA14="-", "-", IF(BE14="-", "-", IF(ABS(BE14)=0, "-", ROUND(100*(BA14-BE14)/ABS(BE14), 1)))) -> - | BJ14: =IF(BF14="-", "-", IF(BH14="-", "-", IF(ABS(BH14)=0, "-", ROUND(100*(BF14-BH14)/ABS(BH14), 1)))) -> - | BK14: =IF(BG14="-", "-", IF(BI14="-", "-", IF(ABS(BI14)=0, "-", ROUND(100*(BG14-BI14)/ABS(BI14), 1)))) -> - | BT14: =IF(BL14="-", "-", IF(BP14="-", "-", IF(ABS(BP14)=0, "-", ROUND(100*(BL14-BP14)/ABS(BP14), 1)))) -> - | BU14: =IF(BQ14="-", "-", IF(BS14="-", "-", IF(ABS(BS14)=0, "-", ROUND(100*(BQ14-BS14)/ABS(BS14), 1)))) -> - | BV14: =IF(BR14="-", "-", IF(BT14="-", "-", IF(ABS(BT14)=0, "-", ROUND(100*(BR14-BT14)/ABS(BT14), 1)))) -> - | CE14: =IF(BW14="-", "-", IF(CA14="-", "-", IF(ABS(CA14)=0, "-", ROUND(100*(BW14-CA14)/ABS(CA14), 1)))) -> - | CF14: =IF(CB14="-", "-", IF(CD14="-", "-", IF(ABS(CD14)=0, "-", ROUND(100*(CB14-CD14)/ABS(CD14), 1)))) -> - | CG14: =IF(CC14="-", "-", IF(CE14="-", "-", IF(ABS(CE14)=0, "-", ROUND(100*(CC14-CE14)/ABS(CE14), 1)))) -> -
AV15: 賃借料総額 | BI15: =IF(BA15="-", "-", IF(BE15="-", "-", IF(ABS(BE15)=0, "-", ROUND(100*(BA15-BE15)/ABS(BE15), 1)))) -> - | BJ15: =IF(BF15="-", "-", IF(BH15="-", "-", IF(ABS(BH15)=0, "-", ROUND(100*(BF15-BH15)/ABS(BH15), 1)))) -> - | BK15: =IF(BG15="-", "-", IF(BI15="-", "-", IF(ABS(BI15)=0, "-", ROUND(100*(BG15-BI15)/ABS(BI15), 1)))) -> - | BT15: =IF(BL15="-", "-", IF(BP15="-", "-", IF(ABS(BP15)=0, "-", ROUND(100*(BL15-BP15)/ABS(BP15), 1)))) -> - | BU15: =IF(BQ15="-", "-", IF(BS15="-", "-", IF(ABS(BS15)=0, "-", ROUND(100*(BQ15-BS15)/ABS(BS15), 1)))) -> - | BV15: =IF(BR15="-", "-", IF(BT15="-", "-", IF(ABS(BT15)=0, "-", ROUND(100*(BR15-BT15)/ABS(BT15), 1)))) -> - | CE15: =IF(BW15="-", "-", IF(CA15="-", "-", IF(ABS(CA15)=0, "-", ROUND(100*(BW15-CA15)/ABS(CA15), 1)))) -> - | CF15: =IF(CB15="-", "-", IF(CD15="-", "-", IF(ABS(CD15)=0, "-", ROUND(100*(CB15-CD15)/ABS(CD15), 1)))) -> - | CG15: =IF(CC15="-", "-", IF(CE15="-", "-", IF(ABS(CE15)=0, "-", ROUND(100*(CC15-CE15)/ABS(CE15), 1)))) -> -
AV16: 負担地代 | BI16: =IF(BA16="-", "-", IF(BE16="-", "-", IF(ABS(BE16)=0, "-", ROUND(100*(BA16-BE16)/ABS(BE16), 1)))) -> - | BJ16: =IF(BF16="-", "-", IF(BH16="-", "-", IF(ABS(BH16)=0, "-", ROUND(100*(BF16-BH16)/ABS(BH16), 1)))) -> - | BK16: =IF(BG16="-", "-", IF(BI16="-", "-", IF(ABS(BI16)=0, "-", ROUND(100*(BG16-BI16)/ABS(BI16), 1)))) -> - | BT16: =IF(BL16="-", "-", IF(BP16="-", "-", IF(ABS(BP16)=0, "-", ROUND(100*(BL16-BP16)/ABS(BP16), 1)))) -> - | BU16: =IF(BQ16="-", "-", IF(BS16="-", "-", IF(ABS(BS16)=0, "-", ROUND(100*(BQ16-BS16)/ABS(BS16), 1)))) -> - | BV16: =IF(BR16="-", "-", IF(BT16="-", "-", IF(ABS(BT16)=0, "-", ROUND(100*(BR16-BT16)/ABS(BT16), 1)))) -> - | CE16: =IF(BW16="-", "-", IF(CA16="-", "-", IF(ABS(CA16)=0, "-", ROUND(100*(BW16-CA16)/ABS(CA16), 1)))) -> - | CF16: =IF(CB16="-", "-", IF(CD16="-", "-", IF(ABS(CD16)=0, "-", ROUND(100*(CB16-CD16)/ABS(CD16), 1)))) -> - | CG16: =IF(CC16="-", "-", IF(CE16="-", "-", IF(ABS(CE16)=0, "-", ROUND(100*(CC16-CE16)/ABS(CE16), 1)))) -> -
B17: ８ 調査作物の作付面積（１経営体当たり） | S17: 単位：ａ | AT17: 実勢地代 | BI17: =IF(BA17="-", "-", IF(BE17="-", "-", IF(ABS(BE17)=0, "-", ROUND(100*(BA17-BE17)/ABS(BE17), 1)))) -> - | BJ17: =IF(BF17="-", "-", IF(BH17="-", "-", IF(ABS(BH17)=0, "-", ROUND(100*(BF17-BH17)/ABS(BH17), 1)))) -> - | BK17: =IF(BG17="-", "-", IF(BI17="-", "-", IF(ABS(BI17)=0, "-", ROUND(100*(BG17-BI17)/ABS(BI17), 1)))) -> - | BT17: =IF(BL17="-", "-", IF(BP17="-", "-", IF(ABS(BP17)=0, "-", ROUND(100*(BL17-BP17)/ABS(BP17), 1)))) -> - | BU17: =IF(BQ17="-", "-", IF(BS17="-", "-", IF(ABS(BS17)=0, "-", ROUND(100*(BQ17-BS17)/ABS(BS17), 1)))) -> - | BV17: =IF(BR17="-", "-", IF(BT17="-", "-", IF(ABS(BT17)=0, "-", ROUND(100*(BR17-BT17)/ABS(BT17), 1)))) -> - | CE17: =IF(BW17="-", "-", IF(CA17="-", "-", IF(ABS(CA17)=0, "-", ROUND(100*(BW17-CA17)/ABS(CA17), 1)))) -> - | CF17: =IF(CB17="-", "-", IF(CD17="-", "-", IF(ABS(CD17)=0, "-", ROUND(100*(CB17-CD17)/ABS(CD17), 1)))) -> - | CG17: =IF(CC17="-", "-", IF(CE17="-", "-", IF(ABS(CE17)=0, "-", ROUND(100*(CC17-CE17)/ABS(CE17), 1)))) -> -
I18: =IF($B$1<>"",$B$1,"") | M18: =IF($B$1<>"",$B$1-1,"") | Q18: 増減率
B19: 田 | Q19: =IF(I19="-", "-", IF(M19="-", "-", IF(ABS(M19)=0, "-", ROUND(100*(I19-M19)/ABS(M19), 1)))) -> - | R19: =IF(N19="-", "-", IF(P19="-", "-", IF(ABS(P19)=0, "-", ROUND(100*(N19-P19)/ABS(P19), 1)))) -> - | S19: =IF(O19="-", "-", IF(Q19="-", "-", IF(ABS(Q19)=0, "-", ROUND(100*(O19-Q19)/ABS(Q19), 1)))) -> -
B20: 畑 | Q20: =IF(I20="-", "-", IF(M20="-", "-", IF(ABS(M20)=0, "-", ROUND(100*(I20-M20)/ABS(M20), 1)))) -> - | R20: =IF(N20="-", "-", IF(P20="-", "-", IF(ABS(P20)=0, "-", ROUND(100*(N20-P20)/ABS(P20), 1)))) -> - | S20: =IF(O20="-", "-", IF(Q20="-", "-", IF(ABS(Q20)=0, "-", ROUND(100*(O20-Q20)/ABS(Q20), 1)))) -> - | AT20: 15 調査作物の品種別作付面積（１経営体当たり） | CC20: 単位：ａ
B21: 計 | Q21: =IF(I21="-", "-", IF(M21="-", "-", IF(ABS(M21)=0, "-", ROUND(100*(I21-M21)/ABS(M21), 1)))) -> - | R21: =IF(N21="-", "-", IF(P21="-", "-", IF(ABS(P21)=0, "-", ROUND(100*(N21-P21)/ABS(P21), 1)))) -> - | S21: =IF(O21="-", "-", IF(Q21="-", "-", IF(ABS(Q21)=0, "-", ROUND(100*(O21-Q21)/ABS(Q21), 1)))) -> - | BA21: =IF($B$1<>"",$B$1,"") | BE21: =IF($B$1<>"",$B$1-1,"") | BI21: 増減率 | BS21: =IF($B$1<>"",$B$1,"") | BW21: =IF($B$1<>"",$B$1-1,"") | CA21: 増減率
AT22: 計 | BI22: =IF(BA22="-", "-", IF(BE22="-", "-", IF(ABS(BE22)=0, "-", ROUND(100*(BA22-BE22)/ABS(BE22), 1)))) -> - | BJ22: =IF(BF22="-", "-", IF(BH22="-", "-", IF(ABS(BH22)=0, "-", ROUND(100*(BF22-BH22)/ABS(BH22), 1)))) -> - | BK22: =IF(BG22="-", "-", IF(BI22="-", "-", IF(ABS(BI22)=0, "-", ROUND(100*(BG22-BI22)/ABS(BI22), 1)))) -> -
AT23: コード１ | BI23: =IF(BA23="-", "-", IF(BE23="-", "-", IF(ABS(BE23)=0, "-", ROUND(100*(BA23-BE23)/ABS(BE23), 1)))) -> - | BJ23: =IF(BF23="-", "-", IF(BH23="-", "-", IF(ABS(BH23)=0, "-", ROUND(100*(BF23-BH23)/ABS(BH23), 1)))) -> - | BK23: =IF(BG23="-", "-", IF(BI23="-", "-", IF(ABS(BI23)=0, "-", ROUND(100*(BG23-BI23)/ABS(BI23), 1)))) -> - | BL23: コード１１ | CA23: =IF(BS23="-", "-", IF(BW23="-", "-", IF(ABS(BW23)=0, "-", ROUND(100*(BS23-BW23)/ABS(BW23), 1)))) -> - | CB23: =IF(BX23="-", "-", IF(BZ23="-", "-", IF(ABS(BZ23)=0, "-", ROUND(100*(BX23-BZ23)/ABS(BZ23), 1)))) -> - | CC23: =IF(BY23="-", "-", IF(CA23="-", "-", IF(ABS(CA23)=0, "-", ROUND(100*(BY23-CA23)/ABS(CA23), 1)))) -> -
B24: ９ 調査作物作業の受託状況（１経営体当たり） | X24: 10 調査作物作業の委託状況（１経営体当たり） | AT24: コード２ | BI24: =IF(BA24="-", "-", IF(BE24="-", "-", IF(ABS(BE24)=0, "-", ROUND(100*(BA24-BE24)/ABS(BE24), 1)))) -> - | BJ24: =IF(BF24="-", "-", IF(BH24="-", "-", IF(ABS(BH24)=0, "-", ROUND(100*(BF24-BH24)/ABS(BH24), 1)))) -> - | BK24: =IF(BG24="-", "-", IF(BI24="-", "-", IF(ABS(BI24)=0, "-", ROUND(100*(BG24-BI24)/ABS(BI24), 1)))) -> - | BL24: コード１２ | CA24: =IF(BS24="-", "-", IF(BW24="-", "-", IF(ABS(BW24)=0, "-", ROUND(100*(BS24-BW24)/ABS(BW24), 1)))) -> - | CB24: =IF(BX24="-", "-", IF(BZ24="-", "-", IF(ABS(BZ24)=0, "-", ROUND(100*(BX24-BZ24)/ABS(BZ24), 1)))) -> - | CC24: =IF(BY24="-", "-", IF(CA24="-", "-", IF(ABS(CA24)=0, "-", ROUND(100*(BY24-CA24)/ABS(CA24), 1)))) -> -
J25: 数量 | AF25: 数量 | AT25: コード３ | BI25: =IF(BA25="-", "-", IF(BE25="-", "-", IF(ABS(BE25)=0, "-", ROUND(100*(BA25-BE25)/ABS(BE25), 1)))) -> - | BJ25: =IF(BF25="-", "-", IF(BH25="-", "-", IF(ABS(BH25)=0, "-", ROUND(100*(BF25-BH25)/ABS(BH25), 1)))) -> - | BK25: =IF(BG25="-", "-", IF(BI25="-", "-", IF(ABS(BI25)=0, "-", ROUND(100*(BG25-BI25)/ABS(BI25), 1)))) -> - | BL25: コード１３ | CA25: =IF(BS25="-", "-", IF(BW25="-", "-", IF(ABS(BW25)=0, "-", ROUND(100*(BS25-BW25)/ABS(BW25), 1)))) -> - | CB25: =IF(BX25="-", "-", IF(BZ25="-", "-", IF(ABS(BZ25)=0, "-", ROUND(100*(BX25-BZ25)/ABS(BZ25), 1)))) -> - | CC25: =IF(BY25="-", "-", IF(CA25="-", "-", IF(ABS(CA25)=0, "-", ROUND(100*(BY25-CA25)/ABS(CA25), 1)))) -> -
J26: =IF($B$1<>"",$B$1,"") | N26: =IF($B$1<>"",$B$1-1,"") | R26: 増減率 | AF26: =IF($B$1<>"",$B$1,"") | AJ26: =IF($B$1<>"",$B$1-1,"") | AN26: 増減率 | AT26: コード４ | BI26: =IF(BA26="-", "-", IF(BE26="-", "-", IF(ABS(BE26)=0, "-", ROUND(100*(BA26-BE26)/ABS(BE26), 1)))) -> - | BJ26: =IF(BF26="-", "-", IF(BH26="-", "-", IF(ABS(BH26)=0, "-", ROUND(100*(BF26-BH26)/ABS(BH26), 1)))) -> - | BK26: =IF(BG26="-", "-", IF(BI26="-", "-", IF(ABS(BI26)=0, "-", ROUND(100*(BG26-BI26)/ABS(BI26), 1)))) -> - | BL26: コード１４ | CA26: =IF(BS26="-", "-", IF(BW26="-", "-", IF(ABS(BW26)=0, "-", ROUND(100*(BS26-BW26)/ABS(BW26), 1)))) -> - | CB26: =IF(BX26="-", "-", IF(BZ26="-", "-", IF(ABS(BZ26)=0, "-", ROUND(100*(BX26-BZ26)/ABS(BZ26), 1)))) -> - | CC26: =IF(BY26="-", "-", IF(CA26="-", "-", IF(ABS(CA26)=0, "-", ROUND(100*(BY26-CA26)/ABS(CA26), 1)))) -> -
B27: 全作業 | I27: ａ | R27: =IF(J27="-", "-", IF(N27="-", "-", IF(ABS(N27)=0, "-", ROUND(100*(J27-N27)/ABS(N27), 1)))) -> - | S27: =IF(O27="-", "-", IF(Q27="-", "-", IF(ABS(Q27)=0, "-", ROUND(100*(O27-Q27)/ABS(Q27), 1)))) -> - | T27: =IF(P27="-", "-", IF(R27="-", "-", IF(ABS(R27)=0, "-", ROUND(100*(P27-R27)/ABS(R27), 1)))) -> - | X27: 耕うん・整地 | AE27: ａ | AN27: =IF(AF27="-", "-", IF(AJ27="-", "-", IF(ABS(AJ27)=0, "-", ROUND(100*(AF27-AJ27)/ABS(AJ27), 1)))) -> - | AO27: =IF(AK27="-", "-", IF(AM27="-", "-", IF(ABS(AM27)=0, "-", ROUND(100*(AK27-AM27)/ABS(AM27), 1)))) -> - | AP27: =IF(AL27="-", "-", IF(AN27="-", "-", IF(ABS(AN27)=0, "-", ROUND(100*(AL27-AN27)/ABS(AN27), 1)))) -> - | AT27: コード５ | BI27: =IF(BA27="-", "-", IF(BE27="-", "-", IF(ABS(BE27)=0, "-", ROUND(100*(BA27-BE27)/ABS(BE27), 1)))) -> - | BJ27: =IF(BF27="-", "-", IF(BH27="-", "-", IF(ABS(BH27)=0, "-", ROUND(100*(BF27-BH27)/ABS(BH27), 1)))) -> - | BK27: =IF(BG27="-", "-", IF(BI27="-", "-", IF(ABS(BI27)=0, "-", ROUND(100*(BG27-BI27)/ABS(BI27), 1)))) -> - | BL27: コード１５ | CA27: =IF(BS27="-", "-", IF(BW27="-", "-", IF(ABS(BW27)=0, "-", ROUND(100*(BS27-BW27)/ABS(BW27), 1)))) -> - | CB27: =IF(BX27="-", "-", IF(BZ27="-", "-", IF(ABS(BZ27)=0, "-", ROUND(100*(BX27-BZ27)/ABS(BZ27), 1)))) -> - | CC27: =IF(BY27="-", "-", IF(CA27="-", "-", IF(ABS(CA27)=0, "-", ROUND(100*(BY27-CA27)/ABS(CA27), 1)))) -> -
B28: 耕うん・整地 | I28: ａ | R28: =IF(J28="-", "-", IF(N28="-", "-", IF(ABS(N28)=0, "-", ROUND(100*(J28-N28)/ABS(N28), 1)))) -> - | S28: =IF(O28="-", "-", IF(Q28="-", "-", IF(ABS(Q28)=0, "-", ROUND(100*(O28-Q28)/ABS(Q28), 1)))) -> - | T28: =IF(P28="-", "-", IF(R28="-", "-", IF(ABS(R28)=0, "-", ROUND(100*(P28-R28)/ABS(R28), 1)))) -> - | X28: は種 | AE28: ａ | AN28: =IF(AF28="-", "-", IF(AJ28="-", "-", IF(ABS(AJ28)=0, "-", ROUND(100*(AF28-AJ28)/ABS(AJ28), 1)))) -> - | AO28: =IF(AK28="-", "-", IF(AM28="-", "-", IF(ABS(AM28)=0, "-", ROUND(100*(AK28-AM28)/ABS(AM28), 1)))) -> - | AP28: =IF(AL28="-", "-", IF(AN28="-", "-", IF(ABS(AN28)=0, "-", ROUND(100*(AL28-AN28)/ABS(AN28), 1)))) -> - | AT28: コード６ | BI28: =IF(BA28="-", "-", IF(BE28="-", "-", IF(ABS(BE28)=0, "-", ROUND(100*(BA28-BE28)/ABS(BE28), 1)))) -> - | BJ28: =IF(BF28="-", "-", IF(BH28="-", "-", IF(ABS(BH28)=0, "-", ROUND(100*(BF28-BH28)/ABS(BH28), 1)))) -> - | BK28: =IF(BG28="-", "-", IF(BI28="-", "-", IF(ABS(BI28)=0, "-", ROUND(100*(BG28-BI28)/ABS(BI28), 1)))) -> - | BL28: コード１６ | CA28: =IF(BS28="-", "-", IF(BW28="-", "-", IF(ABS(BW28)=0, "-", ROUND(100*(BS28-BW28)/ABS(BW28), 1)))) -> - | CB28: =IF(BX28="-", "-", IF(BZ28="-", "-", IF(ABS(BZ28)=0, "-", ROUND(100*(BX28-BZ28)/ABS(BZ28), 1)))) -> - | CC28: =IF(BY28="-", "-", IF(CA28="-", "-", IF(ABS(CA28)=0, "-", ROUND(100*(BY28-CA28)/ABS(CA28), 1)))) -> -
B29: は種 | I29: ａ | R29: =IF(J29="-", "-", IF(N29="-", "-", IF(ABS(N29)=0, "-", ROUND(100*(J29-N29)/ABS(N29), 1)))) -> - | S29: =IF(O29="-", "-", IF(Q29="-", "-", IF(ABS(Q29)=0, "-", ROUND(100*(O29-Q29)/ABS(Q29), 1)))) -> - | T29: =IF(P29="-", "-", IF(R29="-", "-", IF(ABS(R29)=0, "-", ROUND(100*(P29-R29)/ABS(R29), 1)))) -> - | X29: 防除 | AE29: ａ | AN29: =IF(AF29="-", "-", IF(AJ29="-", "-", IF(ABS(AJ29)=0, "-", ROUND(100*(AF29-AJ29)/ABS(AJ29), 1)))) -> - | AO29: =IF(AK29="-", "-", IF(AM29="-", "-", IF(ABS(AM29)=0, "-", ROUND(100*(AK29-AM29)/ABS(AM29), 1)))) -> - | AP29: =IF(AL29="-", "-", IF(AN29="-", "-", IF(ABS(AN29)=0, "-", ROUND(100*(AL29-AN29)/ABS(AN29), 1)))) -> - | AT29: コード７ | BI29: =IF(BA29="-", "-", IF(BE29="-", "-", IF(ABS(BE29)=0, "-", ROUND(100*(BA29-BE29)/ABS(BE29), 1)))) -> - | BJ29: =IF(BF29="-", "-", IF(BH29="-", "-", IF(ABS(BH29)=0, "-", ROUND(100*(BF29-BH29)/ABS(BH29), 1)))) -> - | BK29: =IF(BG29="-", "-", IF(BI29="-", "-", IF(ABS(BI29)=0, "-", ROUND(100*(BG29-BI29)/ABS(BI29), 1)))) -> - | BL29: コード１７ | CA29: =IF(BS29="-", "-", IF(BW29="-", "-", IF(ABS(BW29)=0, "-", ROUND(100*(BS29-BW29)/ABS(BW29), 1)))) -> - | CB29: =IF(BX29="-", "-", IF(BZ29="-", "-", IF(ABS(BZ29)=0, "-", ROUND(100*(BX29-BZ29)/ABS(BZ29), 1)))) -> - | CC29: =IF(BY29="-", "-", IF(CA29="-", "-", IF(ABS(CA29)=0, "-", ROUND(100*(BY29-CA29)/ABS(CA29), 1)))) -> -
B30: 防除 | I30: ａ | R30: =IF(J30="-", "-", IF(N30="-", "-", IF(ABS(N30)=0, "-", ROUND(100*(J30-N30)/ABS(N30), 1)))) -> - | S30: =IF(O30="-", "-", IF(Q30="-", "-", IF(ABS(Q30)=0, "-", ROUND(100*(O30-Q30)/ABS(Q30), 1)))) -> - | T30: =IF(P30="-", "-", IF(R30="-", "-", IF(ABS(R30)=0, "-", ROUND(100*(P30-R30)/ABS(R30), 1)))) -> - | X30: 刈取・脱穀 | AE30: ａ | AN30: =IF(AF30="-", "-", IF(AJ30="-", "-", IF(ABS(AJ30)=0, "-", ROUND(100*(AF30-AJ30)/ABS(AJ30), 1)))) -> - | AO30: =IF(AK30="-", "-", IF(AM30="-", "-", IF(ABS(AM30)=0, "-", ROUND(100*(AK30-AM30)/ABS(AM30), 1)))) -> - | AP30: =IF(AL30="-", "-", IF(AN30="-", "-", IF(ABS(AN30)=0, "-", ROUND(100*(AL30-AN30)/ABS(AN30), 1)))) -> - | AT30: コード８ | BI30: =IF(BA30="-", "-", IF(BE30="-", "-", IF(ABS(BE30)=0, "-", ROUND(100*(BA30-BE30)/ABS(BE30), 1)))) -> - | BJ30: =IF(BF30="-", "-", IF(BH30="-", "-", IF(ABS(BH30)=0, "-", ROUND(100*(BF30-BH30)/ABS(BH30), 1)))) -> - | BK30: =IF(BG30="-", "-", IF(BI30="-", "-", IF(ABS(BI30)=0, "-", ROUND(100*(BG30-BI30)/ABS(BI30), 1)))) -> - | BL30: コード１８ | CA30: =IF(BS30="-", "-", IF(BW30="-", "-", IF(ABS(BW30)=0, "-", ROUND(100*(BS30-BW30)/ABS(BW30), 1)))) -> - | CB30: =IF(BX30="-", "-", IF(BZ30="-", "-", IF(ABS(BZ30)=0, "-", ROUND(100*(BX30-BZ30)/ABS(BZ30), 1)))) -> - | CC30: =IF(BY30="-", "-", IF(CA30="-", "-", IF(ABS(CA30)=0, "-", ROUND(100*(BY30-CA30)/ABS(CA30), 1)))) -> -
B31: 刈取・脱穀 | I31: ａ | R31: =IF(J31="-", "-", IF(N31="-", "-", IF(ABS(N31)=0, "-", ROUND(100*(J31-N31)/ABS(N31), 1)))) -> - | S31: =IF(O31="-", "-", IF(Q31="-", "-", IF(ABS(Q31)=0, "-", ROUND(100*(O31-Q31)/ABS(Q31), 1)))) -> - | T31: =IF(P31="-", "-", IF(R31="-", "-", IF(ABS(R31)=0, "-", ROUND(100*(P31-R31)/ABS(R31), 1)))) -> - | X31: 乾燥・調製 | AE31: kg | AN31: =IF(AF31="-", "-", IF(AJ31="-", "-", IF(ABS(AJ31)=0, "-", ROUND(100*(AF31-AJ31)/ABS(AJ31), 1)))) -> - | AO31: =IF(AK31="-", "-", IF(AM31="-", "-", IF(ABS(AM31)=0, "-", ROUND(100*(AK31-AM31)/ABS(AM31), 1)))) -> - | AP31: =IF(AL31="-", "-", IF(AN31="-", "-", IF(ABS(AN31)=0, "-", ROUND(100*(AL31-AN31)/ABS(AN31), 1)))) -> - | AT31: コード９ | BI31: =IF(BA31="-", "-", IF(BE31="-", "-", IF(ABS(BE31)=0, "-", ROUND(100*(BA31-BE31)/ABS(BE31), 1)))) -> - | BJ31: =IF(BF31="-", "-", IF(BH31="-", "-", IF(ABS(BH31)=0, "-", ROUND(100*(BF31-BH31)/ABS(BH31), 1)))) -> - | BK31: =IF(BG31="-", "-", IF(BI31="-", "-", IF(ABS(BI31)=0, "-", ROUND(100*(BG31-BI31)/ABS(BI31), 1)))) -> - | BL31: コード１９ | CA31: =IF(BS31="-", "-", IF(BW31="-", "-", IF(ABS(BW31)=0, "-", ROUND(100*(BS31-BW31)/ABS(BW31), 1)))) -> - | CB31: =IF(BX31="-", "-", IF(BZ31="-", "-", IF(ABS(BZ31)=0, "-", ROUND(100*(BX31-BZ31)/ABS(BZ31), 1)))) -> - | CC31: =IF(BY31="-", "-", IF(CA31="-", "-", IF(ABS(CA31)=0, "-", ROUND(100*(BY31-CA31)/ABS(CA31), 1)))) -> -
B32: 乾燥・調製 | I32: kg | R32: =IF(J32="-", "-", IF(N32="-", "-", IF(ABS(N32)=0, "-", ROUND(100*(J32-N32)/ABS(N32), 1)))) -> - | S32: =IF(O32="-", "-", IF(Q32="-", "-", IF(ABS(Q32)=0, "-", ROUND(100*(O32-Q32)/ABS(Q32), 1)))) -> - | T32: =IF(P32="-", "-", IF(R32="-", "-", IF(ABS(R32)=0, "-", ROUND(100*(P32-R32)/ABS(R32), 1)))) -> - | AT32: コード１０ | BI32: =IF(BA32="-", "-", IF(BE32="-", "-", IF(ABS(BE32)=0, "-", ROUND(100*(BA32-BE32)/ABS(BE32), 1)))) -> - | BJ32: =IF(BF32="-", "-", IF(BH32="-", "-", IF(ABS(BH32)=0, "-", ROUND(100*(BF32-BH32)/ABS(BH32), 1)))) -> - | BK32: =IF(BG32="-", "-", IF(BI32="-", "-", IF(ABS(BI32)=0, "-", ROUND(100*(BG32-BI32)/ABS(BI32), 1)))) -> - | BL32: コード２０ | CA32: =IF(BS32="-", "-", IF(BW32="-", "-", IF(ABS(BW32)=0, "-", ROUND(100*(BS32-BW32)/ABS(BW32), 1)))) -> - | CB32: =IF(BX32="-", "-", IF(BZ32="-", "-", IF(ABS(BZ32)=0, "-", ROUND(100*(BX32-BZ32)/ABS(BZ32), 1)))) -> - | CC32: =IF(BY32="-", "-", IF(CA32="-", "-", IF(ABS(CA32)=0, "-", ROUND(100*(BY32-CA32)/ABS(CA32), 1)))) -> -
B35: 11 物件税及び公課諸負担 | S35: 単位：円
I36: =IF($B$1<>"",$B$1,"") | M36: =IF($B$1<>"",$B$1-1,"") | Q36: 増減率
B37: 物件税 | Q37: =IF(I37="-", "-", IF(M37="-", "-", IF(ABS(M37)=0, "-", ROUND(100*(I37-M37)/ABS(M37), 1)))) -> - | R37: =IF(N37="-", "-", IF(P37="-", "-", IF(ABS(P37)=0, "-", ROUND(100*(N37-P37)/ABS(P37), 1)))) -> - | S37: =IF(O37="-", "-", IF(Q37="-", "-", IF(ABS(Q37)=0, "-", ROUND(100*(O37-Q37)/ABS(Q37), 1)))) -> -
B38: 公課諸負担 | Q38: =IF(I38="-", "-", IF(M38="-", "-", IF(ABS(M38)=0, "-", ROUND(100*(I38-M38)/ABS(M38), 1)))) -> - | R38: =IF(N38="-", "-", IF(P38="-", "-", IF(ABS(P38)=0, "-", ROUND(100*(N38-P38)/ABS(P38), 1)))) -> - | S38: =IF(O38="-", "-", IF(Q38="-", "-", IF(ABS(Q38)=0, "-", ROUND(100*(O38-Q38)/ABS(Q38), 1)))) -> -
B41: 12 調査作物の栽培型別面積（１経営体当たり）
B42: てんさい作付面積 | AH42: 単位：ａ
B43: 直まき | M43: 移 植 | X43: 計
B44: =IF($B$1<>"",$B$1,"") | F44: =IF($B$1<>"",$B$1-1,"") | J44: 増減率 | M44: =IF($B$1<>"",$B$1,"") | Q44: =IF($B$1<>"",$B$1-1,"") | U44: 増減率 | X44: =IF($B$1<>"",$B$1,"") | AB44: =IF($B$1<>"",$B$1-1,"") | AF44: 増減率
J45: =IF(B45="-", "-", IF(F45="-", "-", IF(ABS(F45)=0, "-", ROUND(100*(B45-F45)/ABS(F45), 1)))) -> - | K45: =IF(G45="-", "-", IF(I45="-", "-", IF(ABS(I45)=0, "-", ROUND(100*(G45-I45)/ABS(I45), 1)))) -> - | L45: =IF(H45="-", "-", IF(J45="-", "-", IF(ABS(J45)=0, "-", ROUND(100*(H45-J45)/ABS(J45), 1)))) -> - | U45: =IF(M45="-", "-", IF(Q45="-", "-", IF(ABS(Q45)=0, "-", ROUND(100*(M45-Q45)/ABS(Q45), 1)))) -> - | V45: =IF(R45="-", "-", IF(T45="-", "-", IF(ABS(T45)=0, "-", ROUND(100*(R45-T45)/ABS(T45), 1)))) -> - | W45: =IF(S45="-", "-", IF(U45="-", "-", IF(ABS(U45)=0, "-", ROUND(100*(S45-U45)/ABS(U45), 1)))) -> - | AF45: =IF(X45="-", "-", IF(AB45="-", "-", IF(ABS(AB45)=0, "-", ROUND(100*(X45-AB45)/ABS(AB45), 1)))) -> - | AG45: =IF(AC45="-", "-", IF(AE45="-", "-", IF(ABS(AE45)=0, "-", ROUND(100*(AC45-AE45)/ABS(AE45), 1)))) -> - | AH45: =IF(AD45="-", "-", IF(AF45="-", "-", IF(ABS(AF45)=0, "-", ROUND(100*(AD45-AF45)/ABS(AF45), 1)))) -> - | BL45: 任意項目
BS46: =IF($B$1<>"",$B$1,"") | BW46: =IF($B$1<>"",$B$1-1,"") | CA46: 増減率
B47: さとうきび作付面積 | AS47: 単位：ａ | BL47: 任意項目１ | CA47: =IF(BS47="-", "-", IF(BW47="-", "-", IF(ABS(BW47)=0, "-", ROUND(100*(BS47-BW47)/ABS(BW47), 1)))) -> - | CB47: =IF(BX47="-", "-", IF(BZ47="-", "-", IF(ABS(BZ47)=0, "-", ROUND(100*(BX47-BZ47)/ABS(BZ47), 1)))) -> - | CC47: =IF(BY47="-", "-", IF(CA47="-", "-", IF(ABS(CA47)=0, "-", ROUND(100*(BY47-CA47)/ABS(CA47), 1)))) -> -
B48: 株出し | M48: 春植え | X48: 夏植え | AI48: 計 | BL48: 任意項目２ | CA48: =IF(BS48="-", "-", IF(BW48="-", "-", IF(ABS(BW48)=0, "-", ROUND(100*(BS48-BW48)/ABS(BW48), 1)))) -> - | CB48: =IF(BX48="-", "-", IF(BZ48="-", "-", IF(ABS(BZ48)=0, "-", ROUND(100*(BX48-BZ48)/ABS(BZ48), 1)))) -> - | CC48: =IF(BY48="-", "-", IF(CA48="-", "-", IF(ABS(CA48)=0, "-", ROUND(100*(BY48-CA48)/ABS(CA48), 1)))) -> -
B49: =IF($B$1<>"",$B$1,"") | F49: =IF($B$1<>"",$B$1-1,"") | J49: 増減率 | M49: =IF($B$1<>"",$B$1,"") | Q49: =IF($B$1<>"",$B$1-1,"") | U49: 増減率 | X49: =IF($B$1<>"",$B$1,"") | AB49: =IF($B$1<>"",$B$1-1,"") | AF49: 増減率 | AI49: =IF($B$1<>"",$B$1,"") | AM49: =IF($B$1<>"",$B$1-1,"") | AQ49: 増減率 | BL49: 任意項目３ | CA49: =IF(BS49="-", "-", IF(BW49="-", "-", IF(ABS(BW49)=0, "-", ROUND(100*(BS49-BW49)/ABS(BW49), 1)))) -> - | CB49: =IF(BX49="-", "-", IF(BZ49="-", "-", IF(ABS(BZ49)=0, "-", ROUND(100*(BX49-BZ49)/ABS(BZ49), 1)))) -> - | CC49: =IF(BY49="-", "-", IF(CA49="-", "-", IF(ABS(CA49)=0, "-", ROUND(100*(BY49-CA49)/ABS(CA49), 1)))) -> -
J50: =IF(B50="-", "-", IF(F50="-", "-", IF(ABS(F50)=0, "-", ROUND(100*(B50-F50)/ABS(F50), 1)))) -> - | K50: =IF(G50="-", "-", IF(I50="-", "-", IF(ABS(I50)=0, "-", ROUND(100*(G50-I50)/ABS(I50), 1)))) -> - | L50: =IF(H50="-", "-", IF(J50="-", "-", IF(ABS(J50)=0, "-", ROUND(100*(H50-J50)/ABS(J50), 1)))) -> - | U50: =IF(M50="-", "-", IF(Q50="-", "-", IF(ABS(Q50)=0, "-", ROUND(100*(M50-Q50)/ABS(Q50), 1)))) -> - | V50: =IF(R50="-", "-", IF(T50="-", "-", IF(ABS(T50)=0, "-", ROUND(100*(R50-T50)/ABS(T50), 1)))) -> - | W50: =IF(S50="-", "-", IF(U50="-", "-", IF(ABS(U50)=0, "-", ROUND(100*(S50-U50)/ABS(U50), 1)))) -> - | AF50: =IF(X50="-", "-", IF(AB50="-", "-", IF(ABS(AB50)=0, "-", ROUND(100*(X50-AB50)/ABS(AB50), 1)))) -> - | AG50: =IF(AC50="-", "-", IF(AE50="-", "-", IF(ABS(AE50)=0, "-", ROUND(100*(AC50-AE50)/ABS(AE50), 1)))) -> - | AH50: =IF(AD50="-", "-", IF(AF50="-", "-", IF(ABS(AF50)=0, "-", ROUND(100*(AD50-AF50)/ABS(AF50), 1)))) -> - | AQ50: =IF(AI50="-", "-", IF(AM50="-", "-", IF(ABS(AM50)=0, "-", ROUND(100*(AI50-AM50)/ABS(AM50), 1)))) -> - | AR50: =IF(AN50="-", "-", IF(AP50="-", "-", IF(ABS(AP50)=0, "-", ROUND(100*(AN50-AP50)/ABS(AP50), 1)))) -> - | AS50: =IF(AO50="-", "-", IF(AQ50="-", "-", IF(ABS(AQ50)=0, "-", ROUND(100*(AO50-AQ50)/ABS(AQ50), 1)))) -> - | BL50: 任意項目４ | CA50: =IF(BS50="-", "-", IF(BW50="-", "-", IF(ABS(BW50)=0, "-", ROUND(100*(BS50-BW50)/ABS(BW50), 1)))) -> - | CB50: =IF(BX50="-", "-", IF(BZ50="-", "-", IF(ABS(BZ50)=0, "-", ROUND(100*(BX50-BZ50)/ABS(BZ50), 1)))) -> - | CC50: =IF(BY50="-", "-", IF(CA50="-", "-", IF(ABS(CA50)=0, "-", ROUND(100*(BY50-CA50)/ABS(CA50), 1)))) -> -
BL51: 任意項目５ | CA51: =IF(BS51="-", "-", IF(BW51="-", "-", IF(ABS(BW51)=0, "-", ROUND(100*(BS51-BW51)/ABS(BW51), 1)))) -> - | CB51: =IF(BX51="-", "-", IF(BZ51="-", "-", IF(ABS(BZ51)=0, "-", ROUND(100*(BX51-BZ51)/ABS(BZ51), 1)))) -> - | CC51: =IF(BY51="-", "-", IF(CA51="-", "-", IF(ABS(CA51)=0, "-", ROUND(100*(BY51-CA51)/ABS(CA51), 1)))) -> -
BL52: 任意項目６ | CA52: =IF(BS52="-", "-", IF(BW52="-", "-", IF(ABS(BW52)=0, "-", ROUND(100*(BS52-BW52)/ABS(BW52), 1)))) -> - | CB52: =IF(BX52="-", "-", IF(BZ52="-", "-", IF(ABS(BZ52)=0, "-", ROUND(100*(BX52-BZ52)/ABS(BZ52), 1)))) -> - | CC52: =IF(BY52="-", "-", IF(CA52="-", "-", IF(ABS(CA52)=0, "-", ROUND(100*(BY52-CA52)/ABS(CA52), 1)))) -> -
B53: 13 取引糖度（てんさい、さとうきび） | BL53: 任意項目７ | CA53: =IF(BS53="-", "-", IF(BW53="-", "-", IF(ABS(BW53)=0, "-", ROUND(100*(BS53-BW53)/ABS(BW53), 1)))) -> - | CB53: =IF(BX53="-", "-", IF(BZ53="-", "-", IF(ABS(BZ53)=0, "-", ROUND(100*(BX53-BZ53)/ABS(BZ53), 1)))) -> - | CC53: =IF(BY53="-", "-", IF(CA53="-", "-", IF(ABS(CA53)=0, "-", ROUND(100*(BY53-CA53)/ABS(CA53), 1)))) -> -
B54: 出荷量（kg） | M54: 糖度換算出荷量（kg） | X54: 取引糖度（％） | BL54: 任意項目８ | CA54: =IF(BS54="-", "-", IF(BW54="-", "-", IF(ABS(BW54)=0, "-", ROUND(100*(BS54-BW54)/ABS(BW54), 1)))) -> - | CB54: =IF(BX54="-", "-", IF(BZ54="-", "-", IF(ABS(BZ54)=0, "-", ROUND(100*(BX54-BZ54)/ABS(BZ54), 1)))) -> - | CC54: =IF(BY54="-", "-", IF(CA54="-", "-", IF(ABS(CA54)=0, "-", ROUND(100*(BY54-CA54)/ABS(CA54), 1)))) -> -
B55: =IF($B$1<>"",$B$1,"") | F55: =IF($B$1<>"",$B$1-1,"") | J55: 増減率 | M55: =IF($B$1<>"",$B$1,"") | Q55: =IF($B$1<>"",$B$1-1,"") | U55: 増減率 | X55: =IF($B$1<>"",$B$1,"") | AB55: =IF($B$1<>"",$B$1-1,"") | AF55: 増減差 | BL55: 任意項目９ | CA55: =IF(BS55="-", "-", IF(BW55="-", "-", IF(ABS(BW55)=0, "-", ROUND(100*(BS55-BW55)/ABS(BW55), 1)))) -> - | CB55: =IF(BX55="-", "-", IF(BZ55="-", "-", IF(ABS(BZ55)=0, "-", ROUND(100*(BX55-BZ55)/ABS(BZ55), 1)))) -> - | CC55: =IF(BY55="-", "-", IF(CA55="-", "-", IF(ABS(CA55)=0, "-", ROUND(100*(BY55-CA55)/ABS(CA55), 1)))) -> -
J56: =IF(B56="-", "-", IF(F56="-", "-", IF(ABS(F56)=0, "-", ROUND(100*(B56-F56)/ABS(F56), 1)))) -> - | K56: =IF(G56="-", "-", IF(I56="-", "-", IF(ABS(I56)=0, "-", ROUND(100*(G56-I56)/ABS(I56), 1)))) -> - | L56: =IF(H56="-", "-", IF(J56="-", "-", IF(ABS(J56)=0, "-", ROUND(100*(H56-J56)/ABS(J56), 1)))) -> - | U56: =IF(M56="-", "-", IF(Q56="-", "-", IF(ABS(Q56)=0, "-", ROUND(100*(M56-Q56)/ABS(Q56), 1)))) -> - | V56: =IF(R56="-", "-", IF(T56="-", "-", IF(ABS(T56)=0, "-", ROUND(100*(R56-T56)/ABS(T56), 1)))) -> - | W56: =IF(S56="-", "-", IF(U56="-", "-", IF(ABS(U56)=0, "-", ROUND(100*(S56-U56)/ABS(U56), 1)))) -> - | AF56: =IF(X56="-", "-", IF(AB56="-", "-", IF(ABS(AB56)=0, "-", X56-AB56))) -> - | AG56: =IF(AC56="-", "-", IF(AE56="-", "-", IF(ABS(AE56)=0, "-", ROUND(100*(AC56-AE56)/ABS(AE56), 1)))) -> - | AH56: =IF(AD56="-", "-", IF(AF56="-", "-", IF(ABS(AF56)=0, "-", ROUND(100*(AD56-AF56)/ABS(AF56), 1)))) -> - | BL56: 任意項目１０ | CA56: =IF(BS56="-", "-", IF(BW56="-", "-", IF(ABS(BW56)=0, "-", ROUND(100*(BS56-BW56)/ABS(BW56), 1)))) -> - | CB56: =IF(BX56="-", "-", IF(BZ56="-", "-", IF(ABS(BZ56)=0, "-", ROUND(100*(BX56-BZ56)/ABS(BZ56), 1)))) -> - | CC56: =IF(BY56="-", "-", IF(CA56="-", "-", IF(ABS(CA56)=0, "-", ROUND(100*(BY56-CA56)/ABS(CA56), 1)))) -> -

Sheet No.3
B1: =AB4 | E1: 年産 組織法人経営体に関する経営分析調査（麦類・そば・なたね・畑作物生産費（組織法人経営）） 集計結果検討表 Ｎｏ．３
G3: 集計番号 | J3: 集計名称 | Q3: 集計経営体数 | V3: 集計倍率 | AB3: 調査年 | AG3: 都道府県等 | AL3: 経営種類 | AQ3: 生産費区分 | AV3: 規模階層 | BA3: 平均値種類 | BF3: 加重・総和の別 | BK3: 集計区分 | BP3: 田畑区分 | BU3: ビール麦販売区分 | BZ3: てんさい栽培区分
B4: 本年産 | G4: =IF(No.1!G4="","",No.1!G4) | H4: =IF(No.1!H4="","",No.1!H4) | I4: =IF(No.1!I4="","",No.1!I4) | J4: =IF(No.1!J4="","",No.1!J4) | K4: =IF(No.1!K4="","",No.1!K4) | L4: =IF(No.1!L4="","",No.1!L4) | M4: =IF(No.1!M4="","",No.1!M4) | N4: =IF(No.1!N4="","",No.1!N4) | ... Z4: =IF(No.1!Z4="","",No.1!Z4) | AB4: =IF(No.1!AB4="","",No.1!AB4) | AC4: =IF(No.1!AC4="","",No.1!AC4) | AD4: =IF(No.1!AD4="","",No.1!AD4) | AE4: =IF(No.1!AE4="","",No.1!AE4) | AF4: =IF(No.1!AF4="","",No.1!AF4) | AG4: =IF(No.1!AG4="","",No.1!AG4) | AH4: =IF(No.1!AH4="","",No.1!AH4) | AI4: =IF(No.1!AI4="","",No.1!AI4) | ... CD4: =IF(No.1!CD4="","",No.1!CD4)
B5: 前年産 | G5: =IF(No.1!G5="","",No.1!G5) | H5: =IF(No.1!H5="","",No.1!H5) | I5: =IF(No.1!I5="","",No.1!I5) | J5: =IF(No.1!J5="","",No.1!J5) | K5: =IF(No.1!K5="","",No.1!K5) | L5: =IF(No.1!L5="","",No.1!L5) | M5: =IF(No.1!M5="","",No.1!M5) | N5: =IF(No.1!N5="","",No.1!N5) | ... Z5: =IF(No.1!Z5="","",No.1!Z5)
B7: 16 投下労働時間 | AO7: 単位：時間
I8: 構成員 | T8: 雇用 | AE8: 合計
I9: =IF($B$1<>"",$B$1,"") | M9: =IF($B$1<>"",$B$1-1,"") | Q9: 増減率 | T9: =IF($B$1<>"",$B$1,"") | X9: =IF($B$1<>"",$B$1-1,"") | AB9: 増減率 | AE9: =IF($B$1<>"",$B$1,"") | AI9: =IF($B$1<>"",$B$1-1,"") | AM9: 増減率
B10: 直接労働時間 | C10: 種子予措 | Q10: =IF(I10="-", "-", IF(M10="-", "-", IF(ABS(M10)=0, "-", ROUND(100*(I10-M10)/ABS(M10), 1)))) -> - | R10: =IF(N10="-", "-", IF(P10="-", "-", IF(ABS(P10)=0, "-", ROUND(100*(N10-P10)/ABS(P10), 1)))) -> - | S10: =IF(O10="-", "-", IF(Q10="-", "-", IF(ABS(Q10)=0, "-", ROUND(100*(O10-Q10)/ABS(Q10), 1)))) -> - | AB10: =IF(T10="-", "-", IF(X10="-", "-", IF(ABS(X10)=0, "-", ROUND(100*(T10-X10)/ABS(X10), 1)))) -> - | AC10: =IF(Y10="-", "-", IF(AA10="-", "-", IF(ABS(AA10)=0, "-", ROUND(100*(Y10-AA10)/ABS(AA10), 1)))) -> - | AD10: =IF(Z10="-", "-", IF(AB10="-", "-", IF(ABS(AB10)=0, "-", ROUND(100*(Z10-AB10)/ABS(AB10), 1)))) -> - | AM10: =IF(AE10="-", "-", IF(AI10="-", "-", IF(ABS(AI10)=0, "-", ROUND(100*(AE10-AI10)/ABS(AI10), 1)))) -> - | AN10: =IF(AJ10="-", "-", IF(AL10="-", "-", IF(ABS(AL10)=0, "-", ROUND(100*(AJ10-AL10)/ABS(AL10), 1)))) -> - | AO10: =IF(AK10="-", "-", IF(AM10="-", "-", IF(ABS(AM10)=0, "-", ROUND(100*(AK10-AM10)/ABS(AM10), 1)))) -> -
C11: 育苗 | Q11: =IF(I11="-", "-", IF(M11="-", "-", IF(ABS(M11)=0, "-", ROUND(100*(I11-M11)/ABS(M11), 1)))) -> - | R11: =IF(N11="-", "-", IF(P11="-", "-", IF(ABS(P11)=0, "-", ROUND(100*(N11-P11)/ABS(P11), 1)))) -> - | S11: =IF(O11="-", "-", IF(Q11="-", "-", IF(ABS(Q11)=0, "-", ROUND(100*(O11-Q11)/ABS(Q11), 1)))) -> - | AB11: =IF(T11="-", "-", IF(X11="-", "-", IF(ABS(X11)=0, "-", ROUND(100*(T11-X11)/ABS(X11), 1)))) -> - | AC11: =IF(Y11="-", "-", IF(AA11="-", "-", IF(ABS(AA11)=0, "-", ROUND(100*(Y11-AA11)/ABS(AA11), 1)))) -> - | AD11: =IF(Z11="-", "-", IF(AB11="-", "-", IF(ABS(AB11)=0, "-", ROUND(100*(Z11-AB11)/ABS(AB11), 1)))) -> - | AM11: =IF(AE11="-", "-", IF(AI11="-", "-", IF(ABS(AI11)=0, "-", ROUND(100*(AE11-AI11)/ABS(AI11), 1)))) -> - | AN11: =IF(AJ11="-", "-", IF(AL11="-", "-", IF(ABS(AL11)=0, "-", ROUND(100*(AJ11-AL11)/ABS(AL11), 1)))) -> - | AO11: =IF(AK11="-", "-", IF(AM11="-", "-", IF(ABS(AM11)=0, "-", ROUND(100*(AK11-AM11)/ABS(AM11), 1)))) -> -
C12: 耕起整地 | Q12: =IF(I12="-", "-", IF(M12="-", "-", IF(ABS(M12)=0, "-", ROUND(100*(I12-M12)/ABS(M12), 1)))) -> - | R12: =IF(N12="-", "-", IF(P12="-", "-", IF(ABS(P12)=0, "-", ROUND(100*(N12-P12)/ABS(P12), 1)))) -> - | S12: =IF(O12="-", "-", IF(Q12="-", "-", IF(ABS(Q12)=0, "-", ROUND(100*(O12-Q12)/ABS(Q12), 1)))) -> - | AB12: =IF(T12="-", "-", IF(X12="-", "-", IF(ABS(X12)=0, "-", ROUND(100*(T12-X12)/ABS(X12), 1)))) -> - | AC12: =IF(Y12="-", "-", IF(AA12="-", "-", IF(ABS(AA12)=0, "-", ROUND(100*(Y12-AA12)/ABS(AA12), 1)))) -> - | AD12: =IF(Z12="-", "-", IF(AB12="-", "-", IF(ABS(AB12)=0, "-", ROUND(100*(Z12-AB12)/ABS(AB12), 1)))) -> - | AM12: =IF(AE12="-", "-", IF(AI12="-", "-", IF(ABS(AI12)=0, "-", ROUND(100*(AE12-AI12)/ABS(AI12), 1)))) -> - | AN12: =IF(AJ12="-", "-", IF(AL12="-", "-", IF(ABS(AL12)=0, "-", ROUND(100*(AJ12-AL12)/ABS(AL12), 1)))) -> - | AO12: =IF(AK12="-", "-", IF(AM12="-", "-", IF(ABS(AM12)=0, "-", ROUND(100*(AK12-AM12)/ABS(AM12), 1)))) -> -
C13: 基肥 | Q13: =IF(I13="-", "-", IF(M13="-", "-", IF(ABS(M13)=0, "-", ROUND(100*(I13-M13)/ABS(M13), 1)))) -> - | R13: =IF(N13="-", "-", IF(P13="-", "-", IF(ABS(P13)=0, "-", ROUND(100*(N13-P13)/ABS(P13), 1)))) -> - | S13: =IF(O13="-", "-", IF(Q13="-", "-", IF(ABS(Q13)=0, "-", ROUND(100*(O13-Q13)/ABS(Q13), 1)))) -> - | AB13: =IF(T13="-", "-", IF(X13="-", "-", IF(ABS(X13)=0, "-", ROUND(100*(T13-X13)/ABS(X13), 1)))) -> - | AC13: =IF(Y13="-", "-", IF(AA13="-", "-", IF(ABS(AA13)=0, "-", ROUND(100*(Y13-AA13)/ABS(AA13), 1)))) -> - | AD13: =IF(Z13="-", "-", IF(AB13="-", "-", IF(ABS(AB13)=0, "-", ROUND(100*(Z13-AB13)/ABS(AB13), 1)))) -> - | AM13: =IF(AE13="-", "-", IF(AI13="-", "-", IF(ABS(AI13)=0, "-", ROUND(100*(AE13-AI13)/ABS(AI13), 1)))) -> - | AN13: =IF(AJ13="-", "-", IF(AL13="-", "-", IF(ABS(AL13)=0, "-", ROUND(100*(AJ13-AL13)/ABS(AL13), 1)))) -> - | AO13: =IF(AK13="-", "-", IF(AM13="-", "-", IF(ABS(AM13)=0, "-", ROUND(100*(AK13-AM13)/ABS(AM13), 1)))) -> -
C14: は種 | Q14: =IF(I14="-", "-", IF(M14="-", "-", IF(ABS(M14)=0, "-", ROUND(100*(I14-M14)/ABS(M14), 1)))) -> - | R14: =IF(N14="-", "-", IF(P14="-", "-", IF(ABS(P14)=0, "-", ROUND(100*(N14-P14)/ABS(P14), 1)))) -> - | S14: =IF(O14="-", "-", IF(Q14="-", "-", IF(ABS(Q14)=0, "-", ROUND(100*(O14-Q14)/ABS(Q14), 1)))) -> - | AB14: =IF(T14="-", "-", IF(X14="-", "-", IF(ABS(X14)=0, "-", ROUND(100*(T14-X14)/ABS(X14), 1)))) -> - | AC14: =IF(Y14="-", "-", IF(AA14="-", "-", IF(ABS(AA14)=0, "-", ROUND(100*(Y14-AA14)/ABS(AA14), 1)))) -> - | AD14: =IF(Z14="-", "-", IF(AB14="-", "-", IF(ABS(AB14)=0, "-", ROUND(100*(Z14-AB14)/ABS(AB14), 1)))) -> - | AM14: =IF(AE14="-", "-", IF(AI14="-", "-", IF(ABS(AI14)=0, "-", ROUND(100*(AE14-AI14)/ABS(AI14), 1)))) -> - | AN14: =IF(AJ14="-", "-", IF(AL14="-", "-", IF(ABS(AL14)=0, "-", ROUND(100*(AJ14-AL14)/ABS(AL14), 1)))) -> - | AO14: =IF(AK14="-", "-", IF(AM14="-", "-", IF(ABS(AM14)=0, "-", ROUND(100*(AK14-AM14)/ABS(AM14), 1)))) -> -
C15: 定植 | Q15: =IF(I15="-", "-", IF(M15="-", "-", IF(ABS(M15)=0, "-", ROUND(100*(I15-M15)/ABS(M15), 1)))) -> - | R15: =IF(N15="-", "-", IF(P15="-", "-", IF(ABS(P15)=0, "-", ROUND(100*(N15-P15)/ABS(P15), 1)))) -> - | S15: =IF(O15="-", "-", IF(Q15="-", "-", IF(ABS(Q15)=0, "-", ROUND(100*(O15-Q15)/ABS(Q15), 1)))) -> - | AB15: =IF(T15="-", "-", IF(X15="-", "-", IF(ABS(X15)=0, "-", ROUND(100*(T15-X15)/ABS(X15), 1)))) -> - | AC15: =IF(Y15="-", "-", IF(AA15="-", "-", IF(ABS(AA15)=0, "-", ROUND(100*(Y15-AA15)/ABS(AA15), 1)))) -> - | AD15: =IF(Z15="-", "-", IF(AB15="-", "-", IF(ABS(AB15)=0, "-", ROUND(100*(Z15-AB15)/ABS(AB15), 1)))) -> - | AM15: =IF(AE15="-", "-", IF(AI15="-", "-", IF(ABS(AI15)=0, "-", ROUND(100*(AE15-AI15)/ABS(AI15), 1)))) -> - | AN15: =IF(AJ15="-", "-", IF(AL15="-", "-", IF(ABS(AL15)=0, "-", ROUND(100*(AJ15-AL15)/ABS(AL15), 1)))) -> - | AO15: =IF(AK15="-", "-", IF(AM15="-", "-", IF(ABS(AM15)=0, "-", ROUND(100*(AK15-AM15)/ABS(AM15), 1)))) -> -
C16: 株分け | Q16: =IF(I16="-", "-", IF(M16="-", "-", IF(ABS(M16)=0, "-", ROUND(100*(I16-M16)/ABS(M16), 1)))) -> - | R16: =IF(N16="-", "-", IF(P16="-", "-", IF(ABS(P16)=0, "-", ROUND(100*(N16-P16)/ABS(P16), 1)))) -> - | S16: =IF(O16="-", "-", IF(Q16="-", "-", IF(ABS(Q16)=0, "-", ROUND(100*(O16-Q16)/ABS(Q16), 1)))) -> - | AB16: =IF(T16="-", "-", IF(X16="-", "-", IF(ABS(X16)=0, "-", ROUND(100*(T16-X16)/ABS(X16), 1)))) -> - | AC16: =IF(Y16="-", "-", IF(AA16="-", "-", IF(ABS(AA16)=0, "-", ROUND(100*(Y16-AA16)/ABS(AA16), 1)))) -> - | AD16: =IF(Z16="-", "-", IF(AB16="-", "-", IF(ABS(AB16)=0, "-", ROUND(100*(Z16-AB16)/ABS(AB16), 1)))) -> - | AM16: =IF(AE16="-", "-", IF(AI16="-", "-", IF(ABS(AI16)=0, "-", ROUND(100*(AE16-AI16)/ABS(AI16), 1)))) -> - | AN16: =IF(AJ16="-", "-", IF(AL16="-", "-", IF(ABS(AL16)=0, "-", ROUND(100*(AJ16-AL16)/ABS(AL16), 1)))) -> - | AO16: =IF(AK16="-", "-", IF(AM16="-", "-", IF(ABS(AM16)=0, "-", ROUND(100*(AK16-AM16)/ABS(AM16), 1)))) -> -
C17: 追肥 | Q17: =IF(I17="-", "-", IF(M17="-", "-", IF(ABS(M17)=0, "-", ROUND(100*(I17-M17)/ABS(M17), 1)))) -> - | R17: =IF(N17="-", "-", IF(P17="-", "-", IF(ABS(P17)=0, "-", ROUND(100*(N17-P17)/ABS(P17), 1)))) -> - | S17: =IF(O17="-", "-", IF(Q17="-", "-", IF(ABS(Q17)=0, "-", ROUND(100*(O17-Q17)/ABS(Q17), 1)))) -> - | AB17: =IF(T17="-", "-", IF(X17="-", "-", IF(ABS(X17)=0, "-", ROUND(100*(T17-X17)/ABS(X17), 1)))) -> - | AC17: =IF(Y17="-", "-", IF(AA17="-", "-", IF(ABS(AA17)=0, "-", ROUND(100*(Y17-AA17)/ABS(AA17), 1)))) -> - | AD17: =IF(Z17="-", "-", IF(AB17="-", "-", IF(ABS(AB17)=0, "-", ROUND(100*(Z17-AB17)/ABS(AB17), 1)))) -> - | AM17: =IF(AE17="-", "-", IF(AI17="-", "-", IF(ABS(AI17)=0, "-", ROUND(100*(AE17-AI17)/ABS(AI17), 1)))) -> - | AN17: =IF(AJ17="-", "-", IF(AL17="-", "-", IF(ABS(AL17)=0, "-", ROUND(100*(AJ17-AL17)/ABS(AL17), 1)))) -> - | AO17: =IF(AK17="-", "-", IF(AM17="-", "-", IF(ABS(AM17)=0, "-", ROUND(100*(AK17-AM17)/ABS(AM17), 1)))) -> -
C18: 中耕除草 | Q18: =IF(I18="-", "-", IF(M18="-", "-", IF(ABS(M18)=0, "-", ROUND(100*(I18-M18)/ABS(M18), 1)))) -> - | R18: =IF(N18="-", "-", IF(P18="-", "-", IF(ABS(P18)=0, "-", ROUND(100*(N18-P18)/ABS(P18), 1)))) -> - | S18: =IF(O18="-", "-", IF(Q18="-", "-", IF(ABS(Q18)=0, "-", ROUND(100*(O18-Q18)/ABS(Q18), 1)))) -> - | AB18: =IF(T18="-", "-", IF(X18="-", "-", IF(ABS(X18)=0, "-", ROUND(100*(T18-X18)/ABS(X18), 1)))) -> - | AC18: =IF(Y18="-", "-", IF(AA18="-", "-", IF(ABS(AA18)=0, "-", ROUND(100*(Y18-AA18)/ABS(AA18), 1)))) -> - | AD18: =IF(Z18="-", "-", IF(AB18="-", "-", IF(ABS(AB18)=0, "-", ROUND(100*(Z18-AB18)/ABS(AB18), 1)))) -> - | AM18: =IF(AE18="-", "-", IF(AI18="-", "-", IF(ABS(AI18)=0, "-", ROUND(100*(AE18-AI18)/ABS(AI18), 1)))) -> - | AN18: =IF(AJ18="-", "-", IF(AL18="-", "-", IF(ABS(AL18)=0, "-", ROUND(100*(AJ18-AL18)/ABS(AL18), 1)))) -> - | AO18: =IF(AK18="-", "-", IF(AM18="-", "-", IF(ABS(AM18)=0, "-", ROUND(100*(AK18-AM18)/ABS(AM18), 1)))) -> -
C19: 麦踏み | Q19: =IF(I19="-", "-", IF(M19="-", "-", IF(ABS(M19)=0, "-", ROUND(100*(I19-M19)/ABS(M19), 1)))) -> - | R19: =IF(N19="-", "-", IF(P19="-", "-", IF(ABS(P19)=0, "-", ROUND(100*(N19-P19)/ABS(P19), 1)))) -> - | S19: =IF(O19="-", "-", IF(Q19="-", "-", IF(ABS(Q19)=0, "-", ROUND(100*(O19-Q19)/ABS(Q19), 1)))) -> - | AB19: =IF(T19="-", "-", IF(X19="-", "-", IF(ABS(X19)=0, "-", ROUND(100*(T19-X19)/ABS(X19), 1)))) -> - | AC19: =IF(Y19="-", "-", IF(AA19="-", "-", IF(ABS(AA19)=0, "-", ROUND(100*(Y19-AA19)/ABS(AA19), 1)))) -> - | AD19: =IF(Z19="-", "-", IF(AB19="-", "-", IF(ABS(AB19)=0, "-", ROUND(100*(Z19-AB19)/ABS(AB19), 1)))) -> - | AM19: =IF(AE19="-", "-", IF(AI19="-", "-", IF(ABS(AI19)=0, "-", ROUND(100*(AE19-AI19)/ABS(AI19), 1)))) -> - | AN19: =IF(AJ19="-", "-", IF(AL19="-", "-", IF(ABS(AL19)=0, "-", ROUND(100*(AJ19-AL19)/ABS(AL19), 1)))) -> - | AO19: =IF(AK19="-", "-", IF(AM19="-", "-", IF(ABS(AM19)=0, "-", ROUND(100*(AK19-AM19)/ABS(AM19), 1)))) -> -
C20: 管理 | Q20: =IF(I20="-", "-", IF(M20="-", "-", IF(ABS(M20)=0, "-", ROUND(100*(I20-M20)/ABS(M20), 1)))) -> - | R20: =IF(N20="-", "-", IF(P20="-", "-", IF(ABS(P20)=0, "-", ROUND(100*(N20-P20)/ABS(P20), 1)))) -> - | S20: =IF(O20="-", "-", IF(Q20="-", "-", IF(ABS(Q20)=0, "-", ROUND(100*(O20-Q20)/ABS(Q20), 1)))) -> - | AB20: =IF(T20="-", "-", IF(X20="-", "-", IF(ABS(X20)=0, "-", ROUND(100*(T20-X20)/ABS(X20), 1)))) -> - | AC20: =IF(Y20="-", "-", IF(AA20="-", "-", IF(ABS(AA20)=0, "-", ROUND(100*(Y20-AA20)/ABS(AA20), 1)))) -> - | AD20: =IF(Z20="-", "-", IF(AB20="-", "-", IF(ABS(AB20)=0, "-", ROUND(100*(Z20-AB20)/ABS(AB20), 1)))) -> - | AM20: =IF(AE20="-", "-", IF(AI20="-", "-", IF(ABS(AI20)=0, "-", ROUND(100*(AE20-AI20)/ABS(AI20), 1)))) -> - | AN20: =IF(AJ20="-", "-", IF(AL20="-", "-", IF(ABS(AL20)=0, "-", ROUND(100*(AJ20-AL20)/ABS(AL20), 1)))) -> - | AO20: =IF(AK20="-", "-", IF(AM20="-", "-", IF(ABS(AM20)=0, "-", ROUND(100*(AK20-AM20)/ABS(AM20), 1)))) -> -
C21: 防除 | Q21: =IF(I21="-", "-", IF(M21="-", "-", IF(ABS(M21)=0, "-", ROUND(100*(I21-M21)/ABS(M21), 1)))) -> - | R21: =IF(N21="-", "-", IF(P21="-", "-", IF(ABS(P21)=0, "-", ROUND(100*(N21-P21)/ABS(P21), 1)))) -> - | S21: =IF(O21="-", "-", IF(Q21="-", "-", IF(ABS(Q21)=0, "-", ROUND(100*(O21-Q21)/ABS(Q21), 1)))) -> - | AB21: =IF(T21="-", "-", IF(X21="-", "-", IF(ABS(X21)=0, "-", ROUND(100*(T21-X21)/ABS(X21), 1)))) -> - | AC21: =IF(Y21="-", "-", IF(AA21="-", "-", IF(ABS(AA21)=0, "-", ROUND(100*(Y21-AA21)/ABS(AA21), 1)))) -> - | AD21: =IF(Z21="-", "-", IF(AB21="-", "-", IF(ABS(AB21)=0, "-", ROUND(100*(Z21-AB21)/ABS(AB21), 1)))) -> - | AM21: =IF(AE21="-", "-", IF(AI21="-", "-", IF(ABS(AI21)=0, "-", ROUND(100*(AE21-AI21)/ABS(AI21), 1)))) -> - | AN21: =IF(AJ21="-", "-", IF(AL21="-", "-", IF(ABS(AL21)=0, "-", ROUND(100*(AJ21-AL21)/ABS(AL21), 1)))) -> - | AO21: =IF(AK21="-", "-", IF(AM21="-", "-", IF(ABS(AM21)=0, "-", ROUND(100*(AK21-AM21)/ABS(AM21), 1)))) -> -
C22: はく葉 | Q22: =IF(I22="-", "-", IF(M22="-", "-", IF(ABS(M22)=0, "-", ROUND(100*(I22-M22)/ABS(M22), 1)))) -> - | R22: =IF(N22="-", "-", IF(P22="-", "-", IF(ABS(P22)=0, "-", ROUND(100*(N22-P22)/ABS(P22), 1)))) -> - | S22: =IF(O22="-", "-", IF(Q22="-", "-", IF(ABS(Q22)=0, "-", ROUND(100*(O22-Q22)/ABS(Q22), 1)))) -> - | AB22: =IF(T22="-", "-", IF(X22="-", "-", IF(ABS(X22)=0, "-", ROUND(100*(T22-X22)/ABS(X22), 1)))) -> - | AC22: =IF(Y22="-", "-", IF(AA22="-", "-", IF(ABS(AA22)=0, "-", ROUND(100*(Y22-AA22)/ABS(AA22), 1)))) -> - | AD22: =IF(Z22="-", "-", IF(AB22="-", "-", IF(ABS(AB22)=0, "-", ROUND(100*(Z22-AB22)/ABS(AB22), 1)))) -> - | AM22: =IF(AE22="-", "-", IF(AI22="-", "-", IF(ABS(AI22)=0, "-", ROUND(100*(AE22-AI22)/ABS(AI22), 1)))) -> - | AN22: =IF(AJ22="-", "-", IF(AL22="-", "-", IF(ABS(AL22)=0, "-", ROUND(100*(AJ22-AL22)/ABS(AL22), 1)))) -> - | AO22: =IF(AK22="-", "-", IF(AM22="-", "-", IF(ABS(AM22)=0, "-", ROUND(100*(AK22-AM22)/ABS(AM22), 1)))) -> -
... C24: 乾燥 | Q24: =IF(I24="-", "-", IF(M24="-", "-", IF(ABS(M24)=0, "-", ROUND(100*(I24-M24)/ABS(M24), 1)))) -> - | R24: =IF(N24="-", "-", IF(P24="-", "-", IF(ABS(P24)=0, "-", ROUND(100*(N24-P24)/ABS(P24), 1)))) -> - | S24: =IF(O24="-", "-", IF(Q24="-", "-", IF(ABS(Q24)=0, "-", ROUND(100*(O24-Q24)/ABS(Q24), 1)))) -> - | AB24: =IF(T24="-", "-", IF(X24="-", "-", IF(ABS(X24)=0, "-", ROUND(100*(T24-X24)/ABS(X24), 1)))) -> - | AC24: =IF(Y24="-", "-", IF(AA24="-", "-", IF(ABS(AA24)=0, "-", ROUND(100*(Y24-AA24)/ABS(AA24), 1)))) -> - | AD24: =IF(Z24="-", "-", IF(AB24="-", "-", IF(ABS(AB24)=0, "-", ROUND(100*(Z24-AB24)/ABS(AB24), 1)))) -> - | AM24: =IF(AE24="-", "-", IF(AI24="-", "-", IF(ABS(AI24)=0, "-", ROUND(100*(AE24-AI24)/ABS(AI24), 1)))) -> - | AN24: =IF(AJ24="-", "-", IF(AL24="-", "-", IF(ABS(AL24)=0, "-", ROUND(100*(AJ24-AL24)/ABS(AL24), 1)))) -> - | AO24: =IF(AK24="-", "-", IF(AM24="-", "-", IF(ABS(AM24)=0, "-", ROUND(100*(AK24-AM24)/ABS(AM24), 1)))) -> -
C25: 生産管理 | Q25: =IF(I25="-", "-", IF(M25="-", "-", IF(ABS(M25)=0, "-", ROUND(100*(I25-M25)/ABS(M25), 1)))) -> - | R25: =IF(N25="-", "-", IF(P25="-", "-", IF(ABS(P25)=0, "-", ROUND(100*(N25-P25)/ABS(P25), 1)))) -> - | S25: =IF(O25="-", "-", IF(Q25="-", "-", IF(ABS(Q25)=0, "-", ROUND(100*(O25-Q25)/ABS(Q25), 1)))) -> - | AM25: =IF(AE25="-", "-", IF(AI25="-", "-", IF(ABS(AI25)=0, "-", ROUND(100*(AE25-AI25)/ABS(AI25), 1)))) -> - | AN25: =IF(AJ25="-", "-", IF(AL25="-", "-", IF(ABS(AL25)=0, "-", ROUND(100*(AJ25-AL25)/ABS(AL25), 1)))) -> - | AO25: =IF(AK25="-", "-", IF(AM25="-", "-", IF(ABS(AM25)=0, "-", ROUND(100*(AK25-AM25)/ABS(AM25), 1)))) -> -
B26: 計 | Q26: =IF(I26="-", "-", IF(M26="-", "-", IF(ABS(M26)=0, "-", ROUND(100*(I26-M26)/ABS(M26), 1)))) -> - | R26: =IF(N26="-", "-", IF(P26="-", "-", IF(ABS(P26)=0, "-", ROUND(100*(N26-P26)/ABS(P26), 1)))) -> - | S26: =IF(O26="-", "-", IF(Q26="-", "-", IF(ABS(Q26)=0, "-", ROUND(100*(O26-Q26)/ABS(Q26), 1)))) -> - | AB26: =IF(T26="-", "-", IF(X26="-", "-", IF(ABS(X26)=0, "-", ROUND(100*(T26-X26)/ABS(X26), 1)))) -> - | AC26: =IF(Y26="-", "-", IF(AA26="-", "-", IF(ABS(AA26)=0, "-", ROUND(100*(Y26-AA26)/ABS(AA26), 1)))) -> - | AD26: =IF(Z26="-", "-", IF(AB26="-", "-", IF(ABS(AB26)=0, "-", ROUND(100*(Z26-AB26)/ABS(AB26), 1)))) -> - | AM26: =IF(AE26="-", "-", IF(AI26="-", "-", IF(ABS(AI26)=0, "-", ROUND(100*(AE26-AI26)/ABS(AI26), 1)))) -> - | AN26: =IF(AJ26="-", "-", IF(AL26="-", "-", IF(ABS(AL26)=0, "-", ROUND(100*(AJ26-AL26)/ABS(AL26), 1)))) -> - | AO26: =IF(AK26="-", "-", IF(AM26="-", "-", IF(ABS(AM26)=0, "-", ROUND(100*(AK26-AM26)/ABS(AM26), 1)))) -> -
B27: 間接労働時間 | Q27: =IF(I27="-", "-", IF(M27="-", "-", IF(ABS(M27)=0, "-", ROUND(100*(I27-M27)/ABS(M27), 1)))) -> - | R27: =IF(N27="-", "-", IF(P27="-", "-", IF(ABS(P27)=0, "-", ROUND(100*(N27-P27)/ABS(P27), 1)))) -> - | S27: =IF(O27="-", "-", IF(Q27="-", "-", IF(ABS(Q27)=0, "-", ROUND(100*(O27-Q27)/ABS(Q27), 1)))) -> - | AB27: =IF(T27="-", "-", IF(X27="-", "-", IF(ABS(X27)=0, "-", ROUND(100*(T27-X27)/ABS(X27), 1)))) -> - | AC27: =IF(Y27="-", "-", IF(AA27="-", "-", IF(ABS(AA27)=0, "-", ROUND(100*(Y27-AA27)/ABS(AA27), 1)))) -> - | AD27: =IF(Z27="-", "-", IF(AB27="-", "-", IF(ABS(AB27)=0, "-", ROUND(100*(Z27-AB27)/ABS(AB27), 1)))) -> - | AM27: =IF(AE27="-", "-", IF(AI27="-", "-", IF(ABS(AI27)=0, "-", ROUND(100*(AE27-AI27)/ABS(AI27), 1)))) -> - | AN27: =IF(AJ27="-", "-", IF(AL27="-", "-", IF(ABS(AL27)=0, "-", ROUND(100*(AJ27-AL27)/ABS(AL27), 1)))) -> - | AO27: =IF(AK27="-", "-", IF(AM27="-", "-", IF(ABS(AM27)=0, "-", ROUND(100*(AK27-AM27)/ABS(AM27), 1)))) -> -
B28: 労働時間合計 | Q28: =IF(I28="-", "-", IF(M28="-", "-", IF(ABS(M28)=0, "-", ROUND(100*(I28-M28)/ABS(M28), 1)))) -> - | R28: =IF(N28="-", "-", IF(P28="-", "-", IF(ABS(P28)=0, "-", ROUND(100*(N28-P28)/ABS(P28), 1)))) -> - | S28: =IF(O28="-", "-", IF(Q28="-", "-", IF(ABS(Q28)=0, "-", ROUND(100*(O28-Q28)/ABS(Q28), 1)))) -> - | AB28: =IF(T28="-", "-", IF(X28="-", "-", IF(ABS(X28)=0, "-", ROUND(100*(T28-X28)/ABS(X28), 1)))) -> - | AC28: =IF(Y28="-", "-", IF(AA28="-", "-", IF(ABS(AA28)=0, "-", ROUND(100*(Y28-AA28)/ABS(AA28), 1)))) -> - | AD28: =IF(Z28="-", "-", IF(AB28="-", "-", IF(ABS(AB28)=0, "-", ROUND(100*(Z28-AB28)/ABS(AB28), 1)))) -> - | AM28: =IF(AE28="-", "-", IF(AI28="-", "-", IF(ABS(AI28)=0, "-", ROUND(100*(AE28-AI28)/ABS(AI28), 1)))) -> - | AN28: =IF(AJ28="-", "-", IF(AL28="-", "-", IF(ABS(AL28)=0, "-", ROUND(100*(AJ28-AL28)/ABS(AL28), 1)))) -> - | AO28: =IF(AK28="-", "-", IF(AM28="-", "-", IF(ABS(AM28)=0, "-", ROUND(100*(AK28-AM28)/ABS(AM28), 1)))) -> -
B31: 17 年齢階層別構成員労働時間及び労働評価 | AO31: 単位：時間、円
I32: 調査作物負担構成員労働時間 | AE32: 調査作物構成員 労働評価額
I33: 直接労働 | T33: 間接労働
I34: =IF($B$1<>"",$B$1,"") | M34: =IF($B$1<>"",$B$1-1,"") | Q34: 増減率 | T34: =IF($B$1<>"",$B$1,"") | X34: =IF($B$1<>"",$B$1-1,"") | AB34: 増減率 | AE34: =IF($B$1<>"",$B$1,"") | AI34: =IF($B$1<>"",$B$1-1,"") | AM34: 増減率
B35: ６５歳未満 | Q35: =IF(I35="-", "-", IF(M35="-", "-", IF(ABS(M35)=0, "-", ROUND(100*(I35-M35)/ABS(M35), 1)))) -> - | R35: =IF(N35="-", "-", IF(P35="-", "-", IF(ABS(P35)=0, "-", ROUND(100*(N35-P35)/ABS(P35), 1)))) -> - | S35: =IF(O35="-", "-", IF(Q35="-", "-", IF(ABS(Q35)=0, "-", ROUND(100*(O35-Q35)/ABS(Q35), 1)))) -> - | AB35: =IF(T35="-", "-", IF(X35="-", "-", IF(ABS(X35)=0, "-", ROUND(100*(T35-X35)/ABS(X35), 1)))) -> - | AC35: =IF(Y35="-", "-", IF(AA35="-", "-", IF(ABS(AA35)=0, "-", ROUND(100*(Y35-AA35)/ABS(AA35), 1)))) -> - | AD35: =IF(Z35="-", "-", IF(AB35="-", "-", IF(ABS(AB35)=0, "-", ROUND(100*(Z35-AB35)/ABS(AB35), 1)))) -> - | AM35: =IF(AE35="-", "-", IF(AI35="-", "-", IF(ABS(AI35)=0, "-", ROUND(100*(AE35-AI35)/ABS(AI35), 1)))) -> - | AN35: =IF(AJ35="-", "-", IF(AL35="-", "-", IF(ABS(AL35)=0, "-", ROUND(100*(AJ35-AL35)/ABS(AL35), 1)))) -> - | AO35: =IF(AK35="-", "-", IF(AM35="-", "-", IF(ABS(AM35)=0, "-", ROUND(100*(AK35-AM35)/ABS(AM35), 1)))) -> -
B36: ６５～７０ | Q36: =IF(I36="-", "-", IF(M36="-", "-", IF(ABS(M36)=0, "-", ROUND(100*(I36-M36)/ABS(M36), 1)))) -> - | R36: =IF(N36="-", "-", IF(P36="-", "-", IF(ABS(P36)=0, "-", ROUND(100*(N36-P36)/ABS(P36), 1)))) -> - | S36: =IF(O36="-", "-", IF(Q36="-", "-", IF(ABS(Q36)=0, "-", ROUND(100*(O36-Q36)/ABS(Q36), 1)))) -> - | AB36: =IF(T36="-", "-", IF(X36="-", "-", IF(ABS(X36)=0, "-", ROUND(100*(T36-X36)/ABS(X36), 1)))) -> - | AC36: =IF(Y36="-", "-", IF(AA36="-", "-", IF(ABS(AA36)=0, "-", ROUND(100*(Y36-AA36)/ABS(AA36), 1)))) -> - | AD36: =IF(Z36="-", "-", IF(AB36="-", "-", IF(ABS(AB36)=0, "-", ROUND(100*(Z36-AB36)/ABS(AB36), 1)))) -> - | AM36: =IF(AE36="-", "-", IF(AI36="-", "-", IF(ABS(AI36)=0, "-", ROUND(100*(AE36-AI36)/ABS(AI36), 1)))) -> - | AN36: =IF(AJ36="-", "-", IF(AL36="-", "-", IF(ABS(AL36)=0, "-", ROUND(100*(AJ36-AL36)/ABS(AL36), 1)))) -> - | AO36: =IF(AK36="-", "-", IF(AM36="-", "-", IF(ABS(AM36)=0, "-", ROUND(100*(AK36-AM36)/ABS(AM36), 1)))) -> -
B37: ７０～７５ | Q37: =IF(I37="-", "-", IF(M37="-", "-", IF(ABS(M37)=0, "-", ROUND(100*(I37-M37)/ABS(M37), 1)))) -> - | R37: =IF(N37="-", "-", IF(P37="-", "-", IF(ABS(P37)=0, "-", ROUND(100*(N37-P37)/ABS(P37), 1)))) -> - | S37: =IF(O37="-", "-", IF(Q37="-", "-", IF(ABS(Q37)=0, "-", ROUND(100*(O37-Q37)/ABS(Q37), 1)))) -> - | AB37: =IF(T37="-", "-", IF(X37="-", "-", IF(ABS(X37)=0, "-", ROUND(100*(T37-X37)/ABS(X37), 1)))) -> - | AC37: =IF(Y37="-", "-", IF(AA37="-", "-", IF(ABS(AA37)=0, "-", ROUND(100*(Y37-AA37)/ABS(AA37), 1)))) -> - | AD37: =IF(Z37="-", "-", IF(AB37="-", "-", IF(ABS(AB37)=0, "-", ROUND(100*(Z37-AB37)/ABS(AB37), 1)))) -> - | AM37: =IF(AE37="-", "-", IF(AI37="-", "-", IF(ABS(AI37)=0, "-", ROUND(100*(AE37-AI37)/ABS(AI37), 1)))) -> - | AN37: =IF(AJ37="-", "-", IF(AL37="-", "-", IF(ABS(AL37)=0, "-", ROUND(100*(AJ37-AL37)/ABS(AL37), 1)))) -> - | AO37: =IF(AK37="-", "-", IF(AM37="-", "-", IF(ABS(AM37)=0, "-", ROUND(100*(AK37-AM37)/ABS(AM37), 1)))) -> -
B38: ７５歳以上 | Q38: =IF(I38="-", "-", IF(M38="-", "-", IF(ABS(M38)=0, "-", ROUND(100*(I38-M38)/ABS(M38), 1)))) -> - | R38: =IF(N38="-", "-", IF(P38="-", "-", IF(ABS(P38)=0, "-", ROUND(100*(N38-P38)/ABS(P38), 1)))) -> - | S38: =IF(O38="-", "-", IF(Q38="-", "-", IF(ABS(Q38)=0, "-", ROUND(100*(O38-Q38)/ABS(Q38), 1)))) -> - | AB38: =IF(T38="-", "-", IF(X38="-", "-", IF(ABS(X38)=0, "-", ROUND(100*(T38-X38)/ABS(X38), 1)))) -> - | AC38: =IF(Y38="-", "-", IF(AA38="-", "-", IF(ABS(AA38)=0, "-", ROUND(100*(Y38-AA38)/ABS(AA38), 1)))) -> - | AD38: =IF(Z38="-", "-", IF(AB38="-", "-", IF(ABS(AB38)=0, "-", ROUND(100*(Z38-AB38)/ABS(AB38), 1)))) -> - | AM38: =IF(AE38="-", "-", IF(AI38="-", "-", IF(ABS(AI38)=0, "-", ROUND(100*(AE38-AI38)/ABS(AI38), 1)))) -> - | AN38: =IF(AJ38="-", "-", IF(AL38="-", "-", IF(ABS(AL38)=0, "-", ROUND(100*(AJ38-AL38)/ABS(AL38), 1)))) -> - | AO38: =IF(AK38="-", "-", IF(AM38="-", "-", IF(ABS(AM38)=0, "-", ROUND(100*(AK38-AM38)/ABS(AM38), 1)))) -> -
B39: 計 | Q39: =IF(I39="-", "-", IF(M39="-", "-", IF(ABS(M39)=0, "-", ROUND(100*(I39-M39)/ABS(M39), 1)))) -> - | R39: =IF(N39="-", "-", IF(P39="-", "-", IF(ABS(P39)=0, "-", ROUND(100*(N39-P39)/ABS(P39), 1)))) -> - | S39: =IF(O39="-", "-", IF(Q39="-", "-", IF(ABS(Q39)=0, "-", ROUND(100*(O39-Q39)/ABS(Q39), 1)))) -> - | AB39: =IF(T39="-", "-", IF(X39="-", "-", IF(ABS(X39)=0, "-", ROUND(100*(T39-X39)/ABS(X39), 1)))) -> - | AC39: =IF(Y39="-", "-", IF(AA39="-", "-", IF(ABS(AA39)=0, "-", ROUND(100*(Y39-AA39)/ABS(AA39), 1)))) -> - | AD39: =IF(Z39="-", "-", IF(AB39="-", "-", IF(ABS(AB39)=0, "-", ROUND(100*(Z39-AB39)/ABS(AB39), 1)))) -> - | AM39: =IF(AE39="-", "-", IF(AI39="-", "-", IF(ABS(AI39)=0, "-", ROUND(100*(AE39-AI39)/ABS(AI39), 1)))) -> - | AN39: =IF(AJ39="-", "-", IF(AL39="-", "-", IF(ABS(AL39)=0, "-", ROUND(100*(AJ39-AL39)/ABS(AL39), 1)))) -> - | AO39: =IF(AK39="-", "-", IF(AM39="-", "-", IF(ABS(AM39)=0, "-", ROUND(100*(AK39-AM39)/ABS(AM39), 1)))) -> -
B42: 18 構成員数等（１経営体当たり） | AT42: 19 労働時間及び労働費 | BV42: 単位：時間、円
I43: =IF($B$1<>"",$B$1,"") | M43: =IF($B$1<>"",$B$1-1,"") | Q43: 増減率 | BA43: 労働時間 | BL43: 労働費
B44: 構成員（人） | Q44: =IF(I44="-", "-", IF(M44="-", "-", IF(ABS(M44)=0, "-", ROUND(100*(I44-M44)/ABS(M44), 1)))) -> - | R44: =IF(N44="-", "-", IF(P44="-", "-", IF(ABS(P44)=0, "-", ROUND(100*(N44-P44)/ABS(P44), 1)))) -> - | S44: =IF(O44="-", "-", IF(Q44="-", "-", IF(ABS(Q44)=0, "-", ROUND(100*(O44-Q44)/ABS(Q44), 1)))) -> - | BA44: =IF($B$1<>"",$B$1,"") | BE44: =IF($B$1<>"",$B$1-1,"") | BI44: 増減率 | BL44: =IF($B$1<>"",$B$1,"") | BP44: =IF($B$1<>"",$B$1-1,"") | BT44: 増減率
B45: 農業年雇（人） | Q45: =IF(I45="-", "-", IF(M45="-", "-", IF(ABS(M45)=0, "-", ROUND(100*(I45-M45)/ABS(M45), 1)))) -> - | R45: =IF(N45="-", "-", IF(P45="-", "-", IF(ABS(P45)=0, "-", ROUND(100*(N45-P45)/ABS(P45), 1)))) -> - | S45: =IF(O45="-", "-", IF(Q45="-", "-", IF(ABS(Q45)=0, "-", ROUND(100*(O45-Q45)/ABS(Q45), 1)))) -> - | AT45: 調査作物負担分 | AU45: 構成員 | BI45: =IF(BA45="-", "-", IF(BE45="-", "-", IF(ABS(BE45)=0, "-", ROUND(100*(BA45-BE45)/ABS(BE45), 1)))) -> - | BJ45: =IF(BF45="-", "-", IF(BH45="-", "-", IF(ABS(BH45)=0, "-", ROUND(100*(BF45-BH45)/ABS(BH45), 1)))) -> - | BK45: =IF(BG45="-", "-", IF(BI45="-", "-", IF(ABS(BI45)=0, "-", ROUND(100*(BG45-BI45)/ABS(BI45), 1)))) -> - | BT45: =IF(BL45="-", "-", IF(BP45="-", "-", IF(ABS(BP45)=0, "-", ROUND(100*(BL45-BP45)/ABS(BP45), 1)))) -> - | BU45: =IF(BQ45="-", "-", IF(BS45="-", "-", IF(ABS(BS45)=0, "-", ROUND(100*(BQ45-BS45)/ABS(BS45), 1)))) -> - | BV45: =IF(BR45="-", "-", IF(BT45="-", "-", IF(ABS(BT45)=0, "-", ROUND(100*(BR45-BT45)/ABS(BT45), 1)))) -> -
B46: 構成農家世帯（戸） | Q46: =IF(I46="-", "-", IF(M46="-", "-", IF(ABS(M46)=0, "-", ROUND(100*(I46-M46)/ABS(M46), 1)))) -> - | R46: =IF(N46="-", "-", IF(P46="-", "-", IF(ABS(P46)=0, "-", ROUND(100*(N46-P46)/ABS(P46), 1)))) -> - | S46: =IF(O46="-", "-", IF(Q46="-", "-", IF(ABS(Q46)=0, "-", ROUND(100*(O46-Q46)/ABS(Q46), 1)))) -> - | AV46: 直接労働 | BI46: =IF(BA46="-", "-", IF(BE46="-", "-", IF(ABS(BE46)=0, "-", ROUND(100*(BA46-BE46)/ABS(BE46), 1)))) -> - | BJ46: =IF(BF46="-", "-", IF(BH46="-", "-", IF(ABS(BH46)=0, "-", ROUND(100*(BF46-BH46)/ABS(BH46), 1)))) -> - | BK46: =IF(BG46="-", "-", IF(BI46="-", "-", IF(ABS(BI46)=0, "-", ROUND(100*(BG46-BI46)/ABS(BI46), 1)))) -> - | BT46: =IF(BL46="-", "-", IF(BP46="-", "-", IF(ABS(BP46)=0, "-", ROUND(100*(BL46-BP46)/ABS(BP46), 1)))) -> - | BU46: =IF(BQ46="-", "-", IF(BS46="-", "-", IF(ABS(BS46)=0, "-", ROUND(100*(BQ46-BS46)/ABS(BS46), 1)))) -> - | BV46: =IF(BR46="-", "-", IF(BT46="-", "-", IF(ABS(BT46)=0, "-", ROUND(100*(BR46-BT46)/ABS(BT46), 1)))) -> -
AV47: 間接労働 | BI47: =IF(BA47="-", "-", IF(BE47="-", "-", IF(ABS(BE47)=0, "-", ROUND(100*(BA47-BE47)/ABS(BE47), 1)))) -> - | BJ47: =IF(BF47="-", "-", IF(BH47="-", "-", IF(ABS(BH47)=0, "-", ROUND(100*(BF47-BH47)/ABS(BH47), 1)))) -> - | BK47: =IF(BG47="-", "-", IF(BI47="-", "-", IF(ABS(BI47)=0, "-", ROUND(100*(BG47-BI47)/ABS(BI47), 1)))) -> - | BT47: =IF(BL47="-", "-", IF(BP47="-", "-", IF(ABS(BP47)=0, "-", ROUND(100*(BL47-BP47)/ABS(BP47), 1)))) -> - | BU47: =IF(BQ47="-", "-", IF(BS47="-", "-", IF(ABS(BS47)=0, "-", ROUND(100*(BQ47-BS47)/ABS(BS47), 1)))) -> - | BV47: =IF(BR47="-", "-", IF(BT47="-", "-", IF(ABS(BT47)=0, "-", ROUND(100*(BR47-BT47)/ABS(BT47), 1)))) -> -
AU48: 雇用 | BI48: =IF(BA48="-", "-", IF(BE48="-", "-", IF(ABS(BE48)=0, "-", ROUND(100*(BA48-BE48)/ABS(BE48), 1)))) -> - | BJ48: =IF(BF48="-", "-", IF(BH48="-", "-", IF(ABS(BH48)=0, "-", ROUND(100*(BF48-BH48)/ABS(BH48), 1)))) -> - | BK48: =IF(BG48="-", "-", IF(BI48="-", "-", IF(ABS(BI48)=0, "-", ROUND(100*(BG48-BI48)/ABS(BI48), 1)))) -> - | BT48: =IF(BL48="-", "-", IF(BP48="-", "-", IF(ABS(BP48)=0, "-", ROUND(100*(BL48-BP48)/ABS(BP48), 1)))) -> - | BU48: =IF(BQ48="-", "-", IF(BS48="-", "-", IF(ABS(BS48)=0, "-", ROUND(100*(BQ48-BS48)/ABS(BS48), 1)))) -> - | BV48: =IF(BR48="-", "-", IF(BT48="-", "-", IF(ABS(BT48)=0, "-", ROUND(100*(BR48-BT48)/ABS(BT48), 1)))) -> -
AV49: 直接労働 | BI49: =IF(BA49="-", "-", IF(BE49="-", "-", IF(ABS(BE49)=0, "-", ROUND(100*(BA49-BE49)/ABS(BE49), 1)))) -> - | BJ49: =IF(BF49="-", "-", IF(BH49="-", "-", IF(ABS(BH49)=0, "-", ROUND(100*(BF49-BH49)/ABS(BH49), 1)))) -> - | BK49: =IF(BG49="-", "-", IF(BI49="-", "-", IF(ABS(BI49)=0, "-", ROUND(100*(BG49-BI49)/ABS(BI49), 1)))) -> - | BT49: =IF(BL49="-", "-", IF(BP49="-", "-", IF(ABS(BP49)=0, "-", ROUND(100*(BL49-BP49)/ABS(BP49), 1)))) -> - | BU49: =IF(BQ49="-", "-", IF(BS49="-", "-", IF(ABS(BS49)=0, "-", ROUND(100*(BQ49-BS49)/ABS(BS49), 1)))) -> - | BV49: =IF(BR49="-", "-", IF(BT49="-", "-", IF(ABS(BT49)=0, "-", ROUND(100*(BR49-BT49)/ABS(BT49), 1)))) -> -
AV50: 間接労働 | BI50: =IF(BA50="-", "-", IF(BE50="-", "-", IF(ABS(BE50)=0, "-", ROUND(100*(BA50-BE50)/ABS(BE50), 1)))) -> - | BJ50: =IF(BF50="-", "-", IF(BH50="-", "-", IF(ABS(BH50)=0, "-", ROUND(100*(BF50-BH50)/ABS(BH50), 1)))) -> - | BK50: =IF(BG50="-", "-", IF(BI50="-", "-", IF(ABS(BI50)=0, "-", ROUND(100*(BG50-BI50)/ABS(BI50), 1)))) -> - | BT50: =IF(BL50="-", "-", IF(BP50="-", "-", IF(ABS(BP50)=0, "-", ROUND(100*(BL50-BP50)/ABS(BP50), 1)))) -> - | BU50: =IF(BQ50="-", "-", IF(BS50="-", "-", IF(ABS(BS50)=0, "-", ROUND(100*(BQ50-BS50)/ABS(BS50), 1)))) -> - | BV50: =IF(BR50="-", "-", IF(BT50="-", "-", IF(ABS(BT50)=0, "-", ROUND(100*(BR50-BT50)/ABS(BT50), 1)))) -> -
AU51: 合計 | BI51: =IF(BA51="-", "-", IF(BE51="-", "-", IF(ABS(BE51)=0, "-", ROUND(100*(BA51-BE51)/ABS(BE51), 1)))) -> - | BJ51: =IF(BF51="-", "-", IF(BH51="-", "-", IF(ABS(BH51)=0, "-", ROUND(100*(BF51-BH51)/ABS(BH51), 1)))) -> - | BK51: =IF(BG51="-", "-", IF(BI51="-", "-", IF(ABS(BI51)=0, "-", ROUND(100*(BG51-BI51)/ABS(BI51), 1)))) -> - | BT51: =IF(BL51="-", "-", IF(BP51="-", "-", IF(ABS(BP51)=0, "-", ROUND(100*(BL51-BP51)/ABS(BP51), 1)))) -> - | BU51: =IF(BQ51="-", "-", IF(BS51="-", "-", IF(ABS(BS51)=0, "-", ROUND(100*(BQ51-BS51)/ABS(BS51), 1)))) -> - | BV51: =IF(BR51="-", "-", IF(BT51="-", "-", IF(ABS(BT51)=0, "-", ROUND(100*(BR51-BT51)/ABS(BT51), 1)))) -> -
AV52: 直接労働 | BI52: =IF(BA52="-", "-", IF(BE52="-", "-", IF(ABS(BE52)=0, "-", ROUND(100*(BA52-BE52)/ABS(BE52), 1)))) -> - | BJ52: =IF(BF52="-", "-", IF(BH52="-", "-", IF(ABS(BH52)=0, "-", ROUND(100*(BF52-BH52)/ABS(BH52), 1)))) -> - | BK52: =IF(BG52="-", "-", IF(BI52="-", "-", IF(ABS(BI52)=0, "-", ROUND(100*(BG52-BI52)/ABS(BI52), 1)))) -> - | BT52: =IF(BL52="-", "-", IF(BP52="-", "-", IF(ABS(BP52)=0, "-", ROUND(100*(BL52-BP52)/ABS(BP52), 1)))) -> - | BU52: =IF(BQ52="-", "-", IF(BS52="-", "-", IF(ABS(BS52)=0, "-", ROUND(100*(BQ52-BS52)/ABS(BS52), 1)))) -> - | BV52: =IF(BR52="-", "-", IF(BT52="-", "-", IF(ABS(BT52)=0, "-", ROUND(100*(BR52-BT52)/ABS(BT52), 1)))) -> -
AV53: 間接労働 | BI53: =IF(BA53="-", "-", IF(BE53="-", "-", IF(ABS(BE53)=0, "-", ROUND(100*(BA53-BE53)/ABS(BE53), 1)))) -> - | BJ53: =IF(BF53="-", "-", IF(BH53="-", "-", IF(ABS(BH53)=0, "-", ROUND(100*(BF53-BH53)/ABS(BH53), 1)))) -> - | BK53: =IF(BG53="-", "-", IF(BI53="-", "-", IF(ABS(BI53)=0, "-", ROUND(100*(BG53-BI53)/ABS(BI53), 1)))) -> - | BT53: =IF(BL53="-", "-", IF(BP53="-", "-", IF(ABS(BP53)=0, "-", ROUND(100*(BL53-BP53)/ABS(BP53), 1)))) -> - | BU53: =IF(BQ53="-", "-", IF(BS53="-", "-", IF(ABS(BS53)=0, "-", ROUND(100*(BQ53-BS53)/ABS(BS53), 1)))) -> - | BV53: =IF(BR53="-", "-", IF(BT53="-", "-", IF(ABS(BT53)=0, "-", ROUND(100*(BR53-BT53)/ABS(BT53), 1)))) -> -

Sheet No.4
B1: =AB4 | E1: 年産 組織法人経営体に関する経営分析調査（麦類・そば・なたね・畑作物生産費（組織法人経営）） 集計結果検討表 Ｎｏ．４
G3: 集計番号 | J3: 集計名称 | Q3: 集計経営体数 | V3: 集計倍率 | AB3: 調査年 | AG3: 都道府県等 | AL3: 経営種類 | AQ3: 生産費区分 | AV3: 規模階層 | BA3: 平均値種類 | BF3: 加重・総和の別 | BK3: 集計区分 | BP3: 田畑区分 | BU3: ビール麦販売区分 | BZ3: てんさい栽培区分
B4: 本年産 | G4: =IF(No.1!G4="","",No.1!G4) | H4: =IF(No.1!H4="","",No.1!H4) | I4: =IF(No.1!I4="","",No.1!I4) | J4: =IF(No.1!J4="","",No.1!J4) | K4: =IF(No.1!K4="","",No.1!K4) | L4: =IF(No.1!L4="","",No.1!L4) | M4: =IF(No.1!M4="","",No.1!M4) | N4: =IF(No.1!N4="","",No.1!N4) | ... Z4: =IF(No.1!Z4="","",No.1!Z4) | AB4: =IF(No.1!AB4="","",No.1!AB4) | AC4: =IF(No.1!AC4="","",No.1!AC4) | AD4: =IF(No.1!AD4="","",No.1!AD4) | AE4: =IF(No.1!AE4="","",No.1!AE4) | AF4: =IF(No.1!AF4="","",No.1!AF4) | AG4: =IF(No.1!AG4="","",No.1!AG4) | AH4: =IF(No.1!AH4="","",No.1!AH4) | AI4: =IF(No.1!AI4="","",No.1!AI4) | ... CD4: =IF(No.1!CD4="","",No.1!CD4)
B5: 前年産 | G5: =IF(No.1!G5="","",No.1!G5) | H5: =IF(No.1!H5="","",No.1!H5) | I5: =IF(No.1!I5="","",No.1!I5) | J5: =IF(No.1!J5="","",No.1!J5) | K5: =IF(No.1!K5="","",No.1!K5) | L5: =IF(No.1!L5="","",No.1!L5) | M5: =IF(No.1!M5="","",No.1!M5) | N5: =IF(No.1!N5="","",No.1!N5) | ... Z5: =IF(No.1!Z5="","",No.1!Z5)
B7: 20 生産物の処分内訳 | AO7: 単位：円、kg | AT7: 21 減価償却費 | BW7: 単位：円、台
B8: 麦類 | I8: 数量 | T8: 価額 | AE8: 単価 | BM8: 調査作物負担分
I9: =IF($B$1<>"",$B$1,"") | M9: =IF($B$1<>"",$B$1-1,"") | Q9: 増減率 | T9: =IF($B$1<>"",$B$1,"") | X9: =IF($B$1<>"",$B$1-1,"") | AB9: 増減率 | AE9: =IF($B$1<>"",$B$1,"") | AI9: =IF($B$1<>"",$B$1-1,"") | AM9: 増減率 | BB9: =IF($B$1<>"",$B$1,"") | BF9: =IF($B$1<>"",$B$1-1,"") | BJ9: 増減率 | BM9: =IF($B$1<>"",$B$1,"") | BQ9: =IF($B$1<>"",$B$1-1,"") | BU9: 増減率
B10: 主産物 | C10: 販売用 | D10: １等 | Q10: =IF(I10="-", "-", IF(M10="-", "-", IF(ABS(M10)=0, "-", ROUND(100*(I10-M10)/ABS(M10), 1)))) -> - | R10: =IF(N10="-", "-", IF(P10="-", "-", IF(ABS(P10)=0, "-", ROUND(100*(N10-P10)/ABS(P10), 1)))) -> - | S10: =IF(O10="-", "-", IF(Q10="-", "-", IF(ABS(Q10)=0, "-", ROUND(100*(O10-Q10)/ABS(Q10), 1)))) -> - | AB10: =IF(T10="-", "-", IF(X10="-", "-", IF(ABS(X10)=0, "-", ROUND(100*(T10-X10)/ABS(X10), 1)))) -> - | AC10: =IF(Y10="-", "-", IF(AA10="-", "-", IF(ABS(AA10)=0, "-", ROUND(100*(Y10-AA10)/ABS(AA10), 1)))) -> - | AD10: =IF(Z10="-", "-", IF(AB10="-", "-", IF(ABS(AB10)=0, "-", ROUND(100*(Z10-AB10)/ABS(AB10), 1)))) -> - | AM10: =IF(AE10="-", "-", IF(AI10="-", "-", IF(ABS(AI10)=0, "-", ROUND(100*(AE10-AI10)/ABS(AI10), 1)))) -> - | AN10: =IF(AJ10="-", "-", IF(AL10="-", "-", IF(ABS(AL10)=0, "-", ROUND(100*(AJ10-AL10)/ABS(AL10), 1)))) -> - | AO10: =IF(AK10="-", "-", IF(AM10="-", "-", IF(ABS(AM10)=0, "-", ROUND(100*(AK10-AM10)/ABS(AM10), 1)))) -> - | AT10: 建物・構築物 | AU10: 住宅 | BU10: =IF(BM10="-", "-", IF(BQ10="-", "-", IF(ABS(BQ10)=0, "-", ROUND(100*(BM10-BQ10)/ABS(BQ10), 1)))) -> - | BV10: =IF(BR10="-", "-", IF(BT10="-", "-", IF(ABS(BT10)=0, "-", ROUND(100*(BR10-BT10)/ABS(BT10), 1)))) -> - | BW10: =IF(BS10="-", "-", IF(BU10="-", "-", IF(ABS(BU10)=0, "-", ROUND(100*(BS10-BU10)/ABS(BU10), 1)))) -> -
D11: ２等 | Q11: =IF(I11="-", "-", IF(M11="-", "-", IF(ABS(M11)=0, "-", ROUND(100*(I11-M11)/ABS(M11), 1)))) -> - | R11: =IF(N11="-", "-", IF(P11="-", "-", IF(ABS(P11)=0, "-", ROUND(100*(N11-P11)/ABS(P11), 1)))) -> - | S11: =IF(O11="-", "-", IF(Q11="-", "-", IF(ABS(Q11)=0, "-", ROUND(100*(O11-Q11)/ABS(Q11), 1)))) -> - | AB11: =IF(T11="-", "-", IF(X11="-", "-", IF(ABS(X11)=0, "-", ROUND(100*(T11-X11)/ABS(X11), 1)))) -> - | AC11: =IF(Y11="-", "-", IF(AA11="-", "-", IF(ABS(AA11)=0, "-", ROUND(100*(Y11-AA11)/ABS(AA11), 1)))) -> - | AD11: =IF(Z11="-", "-", IF(AB11="-", "-", IF(ABS(AB11)=0, "-", ROUND(100*(Z11-AB11)/ABS(AB11), 1)))) -> - | AM11: =IF(AE11="-", "-", IF(AI11="-", "-", IF(ABS(AI11)=0, "-", ROUND(100*(AE11-AI11)/ABS(AI11), 1)))) -> - | AN11: =IF(AJ11="-", "-", IF(AL11="-", "-", IF(ABS(AL11)=0, "-", ROUND(100*(AJ11-AL11)/ABS(AL11), 1)))) -> - | AO11: =IF(AK11="-", "-", IF(AM11="-", "-", IF(ABS(AM11)=0, "-", ROUND(100*(AK11-AM11)/ABS(AM11), 1)))) -> - | AU11: 納屋・倉庫 | BU11: =IF(BM11="-", "-", IF(BQ11="-", "-", IF(ABS(BQ11)=0, "-", ROUND(100*(BM11-BQ11)/ABS(BQ11), 1)))) -> - | BV11: =IF(BR11="-", "-", IF(BT11="-", "-", IF(ABS(BT11)=0, "-", ROUND(100*(BR11-BT11)/ABS(BT11), 1)))) -> - | BW11: =IF(BS11="-", "-", IF(BU11="-", "-", IF(ABS(BU11)=0, "-", ROUND(100*(BS11-BU11)/ABS(BU11), 1)))) -> -
D12: 規格外Ａ | Q12: =IF(I12="-", "-", IF(M12="-", "-", IF(ABS(M12)=0, "-", ROUND(100*(I12-M12)/ABS(M12), 1)))) -> - | R12: =IF(N12="-", "-", IF(P12="-", "-", IF(ABS(P12)=0, "-", ROUND(100*(N12-P12)/ABS(P12), 1)))) -> - | S12: =IF(O12="-", "-", IF(Q12="-", "-", IF(ABS(Q12)=0, "-", ROUND(100*(O12-Q12)/ABS(Q12), 1)))) -> - | AB12: =IF(T12="-", "-", IF(X12="-", "-", IF(ABS(X12)=0, "-", ROUND(100*(T12-X12)/ABS(X12), 1)))) -> - | AC12: =IF(Y12="-", "-", IF(AA12="-", "-", IF(ABS(AA12)=0, "-", ROUND(100*(Y12-AA12)/ABS(AA12), 1)))) -> - | AD12: =IF(Z12="-", "-", IF(AB12="-", "-", IF(ABS(AB12)=0, "-", ROUND(100*(Z12-AB12)/ABS(AB12), 1)))) -> - | AM12: =IF(AE12="-", "-", IF(AI12="-", "-", IF(ABS(AI12)=0, "-", ROUND(100*(AE12-AI12)/ABS(AI12), 1)))) -> - | AN12: =IF(AJ12="-", "-", IF(AL12="-", "-", IF(ABS(AL12)=0, "-", ROUND(100*(AJ12-AL12)/ABS(AL12), 1)))) -> - | AO12: =IF(AK12="-", "-", IF(AM12="-", "-", IF(ABS(AM12)=0, "-", ROUND(100*(AK12-AM12)/ABS(AM12), 1)))) -> - | AU12: 用水路 | BU12: =IF(BM12="-", "-", IF(BQ12="-", "-", IF(ABS(BQ12)=0, "-", ROUND(100*(BM12-BQ12)/ABS(BQ12), 1)))) -> - | BV12: =IF(BR12="-", "-", IF(BT12="-", "-", IF(ABS(BT12)=0, "-", ROUND(100*(BR12-BT12)/ABS(BT12), 1)))) -> - | BW12: =IF(BS12="-", "-", IF(BU12="-", "-", IF(ABS(BU12)=0, "-", ROUND(100*(BS12-BU12)/ABS(BU12), 1)))) -> -
D13: その他 | Q13: =IF(I13="-", "-", IF(M13="-", "-", IF(ABS(M13)=0, "-", ROUND(100*(I13-M13)/ABS(M13), 1)))) -> - | R13: =IF(N13="-", "-", IF(P13="-", "-", IF(ABS(P13)=0, "-", ROUND(100*(N13-P13)/ABS(P13), 1)))) -> - | S13: =IF(O13="-", "-", IF(Q13="-", "-", IF(ABS(Q13)=0, "-", ROUND(100*(O13-Q13)/ABS(Q13), 1)))) -> - | AB13: =IF(T13="-", "-", IF(X13="-", "-", IF(ABS(X13)=0, "-", ROUND(100*(T13-X13)/ABS(X13), 1)))) -> - | AC13: =IF(Y13="-", "-", IF(AA13="-", "-", IF(ABS(AA13)=0, "-", ROUND(100*(Y13-AA13)/ABS(AA13), 1)))) -> - | AD13: =IF(Z13="-", "-", IF(AB13="-", "-", IF(ABS(AB13)=0, "-", ROUND(100*(Z13-AB13)/ABS(AB13), 1)))) -> - | AM13: =IF(AE13="-", "-", IF(AI13="-", "-", IF(ABS(AI13)=0, "-", ROUND(100*(AE13-AI13)/ABS(AI13), 1)))) -> - | AN13: =IF(AJ13="-", "-", IF(AL13="-", "-", IF(ABS(AL13)=0, "-", ROUND(100*(AJ13-AL13)/ABS(AL13), 1)))) -> - | AO13: =IF(AK13="-", "-", IF(AM13="-", "-", IF(ABS(AM13)=0, "-", ROUND(100*(AK13-AM13)/ABS(AM13), 1)))) -> - | AU13: 暗きょ排水施設 | BU13: =IF(BM13="-", "-", IF(BQ13="-", "-", IF(ABS(BQ13)=0, "-", ROUND(100*(BM13-BQ13)/ABS(BQ13), 1)))) -> - | BV13: =IF(BR13="-", "-", IF(BT13="-", "-", IF(ABS(BT13)=0, "-", ROUND(100*(BR13-BT13)/ABS(BT13), 1)))) -> - | BW13: =IF(BS13="-", "-", IF(BU13="-", "-", IF(ABS(BU13)=0, "-", ROUND(100*(BS13-BU13)/ABS(BU13), 1)))) -> -
D14: 小計 | Q14: =IF(I14="-", "-", IF(M14="-", "-", IF(ABS(M14)=0, "-", ROUND(100*(I14-M14)/ABS(M14), 1)))) -> - | R14: =IF(N14="-", "-", IF(P14="-", "-", IF(ABS(P14)=0, "-", ROUND(100*(N14-P14)/ABS(P14), 1)))) -> - | S14: =IF(O14="-", "-", IF(Q14="-", "-", IF(ABS(Q14)=0, "-", ROUND(100*(O14-Q14)/ABS(Q14), 1)))) -> - | AB14: =IF(T14="-", "-", IF(X14="-", "-", IF(ABS(X14)=0, "-", ROUND(100*(T14-X14)/ABS(X14), 1)))) -> - | AC14: =IF(Y14="-", "-", IF(AA14="-", "-", IF(ABS(AA14)=0, "-", ROUND(100*(Y14-AA14)/ABS(AA14), 1)))) -> - | AD14: =IF(Z14="-", "-", IF(AB14="-", "-", IF(ABS(AB14)=0, "-", ROUND(100*(Z14-AB14)/ABS(AB14), 1)))) -> - | AM14: =IF(AE14="-", "-", IF(AI14="-", "-", IF(ABS(AI14)=0, "-", ROUND(100*(AE14-AI14)/ABS(AI14), 1)))) -> - | AN14: =IF(AJ14="-", "-", IF(AL14="-", "-", IF(ABS(AL14)=0, "-", ROUND(100*(AJ14-AL14)/ABS(AL14), 1)))) -> - | AO14: =IF(AK14="-", "-", IF(AM14="-", "-", IF(ABS(AM14)=0, "-", ROUND(100*(AK14-AM14)/ABS(AM14), 1)))) -> - | AU14: コンクリートけい畔 | BU14: =IF(BM14="-", "-", IF(BQ14="-", "-", IF(ABS(BQ14)=0, "-", ROUND(100*(BM14-BQ14)/ABS(BQ14), 1)))) -> - | BV14: =IF(BR14="-", "-", IF(BT14="-", "-", IF(ABS(BT14)=0, "-", ROUND(100*(BR14-BT14)/ABS(BT14), 1)))) -> - | BW14: =IF(BS14="-", "-", IF(BU14="-", "-", IF(ABS(BU14)=0, "-", ROUND(100*(BS14-BU14)/ABS(BU14), 1)))) -> -
C15: 組織用 | D15: 食用 | Q15: =IF(I15="-", "-", IF(M15="-", "-", IF(ABS(M15)=0, "-", ROUND(100*(I15-M15)/ABS(M15), 1)))) -> - | R15: =IF(N15="-", "-", IF(P15="-", "-", IF(ABS(P15)=0, "-", ROUND(100*(N15-P15)/ABS(P15), 1)))) -> - | S15: =IF(O15="-", "-", IF(Q15="-", "-", IF(ABS(Q15)=0, "-", ROUND(100*(O15-Q15)/ABS(Q15), 1)))) -> - | AB15: =IF(T15="-", "-", IF(X15="-", "-", IF(ABS(X15)=0, "-", ROUND(100*(T15-X15)/ABS(X15), 1)))) -> - | AC15: =IF(Y15="-", "-", IF(AA15="-", "-", IF(ABS(AA15)=0, "-", ROUND(100*(Y15-AA15)/ABS(AA15), 1)))) -> - | AD15: =IF(Z15="-", "-", IF(AB15="-", "-", IF(ABS(AB15)=0, "-", ROUND(100*(Z15-AB15)/ABS(AB15), 1)))) -> - | AM15: =IF(AE15="-", "-", IF(AI15="-", "-", IF(ABS(AI15)=0, "-", ROUND(100*(AE15-AI15)/ABS(AI15), 1)))) -> - | AN15: =IF(AJ15="-", "-", IF(AL15="-", "-", IF(ABS(AL15)=0, "-", ROUND(100*(AJ15-AL15)/ABS(AL15), 1)))) -> - | AO15: =IF(AK15="-", "-", IF(AM15="-", "-", IF(ABS(AM15)=0, "-", ROUND(100*(AK15-AM15)/ABS(AM15), 1)))) -> - | AU15: 客土 | BU15: =IF(BM15="-", "-", IF(BQ15="-", "-", IF(ABS(BQ15)=0, "-", ROUND(100*(BM15-BQ15)/ABS(BQ15), 1)))) -> - | BV15: =IF(BR15="-", "-", IF(BT15="-", "-", IF(ABS(BT15)=0, "-", ROUND(100*(BR15-BT15)/ABS(BT15), 1)))) -> - | BW15: =IF(BS15="-", "-", IF(BU15="-", "-", IF(ABS(BU15)=0, "-", ROUND(100*(BS15-BU15)/ABS(BU15), 1)))) -> -
D16: 種子用 | Q16: =IF(I16="-", "-", IF(M16="-", "-", IF(ABS(M16)=0, "-", ROUND(100*(I16-M16)/ABS(M16), 1)))) -> - | R16: =IF(N16="-", "-", IF(P16="-", "-", IF(ABS(P16)=0, "-", ROUND(100*(N16-P16)/ABS(P16), 1)))) -> - | S16: =IF(O16="-", "-", IF(Q16="-", "-", IF(ABS(Q16)=0, "-", ROUND(100*(O16-Q16)/ABS(Q16), 1)))) -> - | AB16: =IF(T16="-", "-", IF(X16="-", "-", IF(ABS(X16)=0, "-", ROUND(100*(T16-X16)/ABS(X16), 1)))) -> - | AC16: =IF(Y16="-", "-", IF(AA16="-", "-", IF(ABS(AA16)=0, "-", ROUND(100*(Y16-AA16)/ABS(AA16), 1)))) -> - | AD16: =IF(Z16="-", "-", IF(AB16="-", "-", IF(ABS(AB16)=0, "-", ROUND(100*(Z16-AB16)/ABS(AB16), 1)))) -> - | AM16: =IF(AE16="-", "-", IF(AI16="-", "-", IF(ABS(AI16)=0, "-", ROUND(100*(AE16-AI16)/ABS(AI16), 1)))) -> - | AN16: =IF(AJ16="-", "-", IF(AL16="-", "-", IF(ABS(AL16)=0, "-", ROUND(100*(AJ16-AL16)/ABS(AL16), 1)))) -> - | AO16: =IF(AK16="-", "-", IF(AM16="-", "-", IF(ABS(AM16)=0, "-", ROUND(100*(AK16-AM16)/ABS(AM16), 1)))) -> - | AU16: たい肥盤 | BU16: =IF(BM16="-", "-", IF(BQ16="-", "-", IF(ABS(BQ16)=0, "-", ROUND(100*(BM16-BQ16)/ABS(BQ16), 1)))) -> - | BV16: =IF(BR16="-", "-", IF(BT16="-", "-", IF(ABS(BT16)=0, "-", ROUND(100*(BR16-BT16)/ABS(BT16), 1)))) -> - | BW16: =IF(BS16="-", "-", IF(BU16="-", "-", IF(ABS(BU16)=0, "-", ROUND(100*(BS16-BU16)/ABS(BU16), 1)))) -> -
D17: その他 | Q17: =IF(I17="-", "-", IF(M17="-", "-", IF(ABS(M17)=0, "-", ROUND(100*(I17-M17)/ABS(M17), 1)))) -> - | R17: =IF(N17="-", "-", IF(P17="-", "-", IF(ABS(P17)=0, "-", ROUND(100*(N17-P17)/ABS(P17), 1)))) -> - | S17: =IF(O17="-", "-", IF(Q17="-", "-", IF(ABS(Q17)=0, "-", ROUND(100*(O17-Q17)/ABS(Q17), 1)))) -> - | AB17: =IF(T17="-", "-", IF(X17="-", "-", IF(ABS(X17)=0, "-", ROUND(100*(T17-X17)/ABS(X17), 1)))) -> - | AC17: =IF(Y17="-", "-", IF(AA17="-", "-", IF(ABS(AA17)=0, "-", ROUND(100*(Y17-AA17)/ABS(AA17), 1)))) -> - | AD17: =IF(Z17="-", "-", IF(AB17="-", "-", IF(ABS(AB17)=0, "-", ROUND(100*(Z17-AB17)/ABS(AB17), 1)))) -> - | AM17: =IF(AE17="-", "-", IF(AI17="-", "-", IF(ABS(AI17)=0, "-", ROUND(100*(AE17-AI17)/ABS(AI17), 1)))) -> - | AN17: =IF(AJ17="-", "-", IF(AL17="-", "-", IF(ABS(AL17)=0, "-", ROUND(100*(AJ17-AL17)/ABS(AL17), 1)))) -> - | AO17: =IF(AK17="-", "-", IF(AM17="-", "-", IF(ABS(AM17)=0, "-", ROUND(100*(AK17-AM17)/ABS(AM17), 1)))) -> - | AU17: その他 | BU17: =IF(BM17="-", "-", IF(BQ17="-", "-", IF(ABS(BQ17)=0, "-", ROUND(100*(BM17-BQ17)/ABS(BQ17), 1)))) -> - | BV17: =IF(BR17="-", "-", IF(BT17="-", "-", IF(ABS(BT17)=0, "-", ROUND(100*(BR17-BT17)/ABS(BT17), 1)))) -> - | BW17: =IF(BS17="-", "-", IF(BU17="-", "-", IF(ABS(BU17)=0, "-", ROUND(100*(BS17-BU17)/ABS(BU17), 1)))) -> -
D18: 小計 | Q18: =IF(I18="-", "-", IF(M18="-", "-", IF(ABS(M18)=0, "-", ROUND(100*(I18-M18)/ABS(M18), 1)))) -> - | R18: =IF(N18="-", "-", IF(P18="-", "-", IF(ABS(P18)=0, "-", ROUND(100*(N18-P18)/ABS(P18), 1)))) -> - | S18: =IF(O18="-", "-", IF(Q18="-", "-", IF(ABS(Q18)=0, "-", ROUND(100*(O18-Q18)/ABS(Q18), 1)))) -> - | AB18: =IF(T18="-", "-", IF(X18="-", "-", IF(ABS(X18)=0, "-", ROUND(100*(T18-X18)/ABS(X18), 1)))) -> - | AC18: =IF(Y18="-", "-", IF(AA18="-", "-", IF(ABS(AA18)=0, "-", ROUND(100*(Y18-AA18)/ABS(AA18), 1)))) -> - | AD18: =IF(Z18="-", "-", IF(AB18="-", "-", IF(ABS(AB18)=0, "-", ROUND(100*(Z18-AB18)/ABS(AB18), 1)))) -> - | AM18: =IF(AE18="-", "-", IF(AI18="-", "-", IF(ABS(AI18)=0, "-", ROUND(100*(AE18-AI18)/ABS(AI18), 1)))) -> - | AN18: =IF(AJ18="-", "-", IF(AL18="-", "-", IF(ABS(AL18)=0, "-", ROUND(100*(AJ18-AL18)/ABS(AL18), 1)))) -> - | AO18: =IF(AK18="-", "-", IF(AM18="-", "-", IF(ABS(AM18)=0, "-", ROUND(100*(AK18-AM18)/ABS(AM18), 1)))) -> - | AU18: 計 | BU18: =IF(BM18="-", "-", IF(BQ18="-", "-", IF(ABS(BQ18)=0, "-", ROUND(100*(BM18-BQ18)/ABS(BQ18), 1)))) -> - | BV18: =IF(BR18="-", "-", IF(BT18="-", "-", IF(ABS(BT18)=0, "-", ROUND(100*(BR18-BT18)/ABS(BT18), 1)))) -> - | BW18: =IF(BS18="-", "-", IF(BU18="-", "-", IF(ABS(BU18)=0, "-", ROUND(100*(BS18-BU18)/ABS(BU18), 1)))) -> -
C19: 合計 | Q19: =IF(I19="-", "-", IF(M19="-", "-", IF(ABS(M19)=0, "-", ROUND(100*(I19-M19)/ABS(M19), 1)))) -> - | R19: =IF(N19="-", "-", IF(P19="-", "-", IF(ABS(P19)=0, "-", ROUND(100*(N19-P19)/ABS(P19), 1)))) -> - | S19: =IF(O19="-", "-", IF(Q19="-", "-", IF(ABS(Q19)=0, "-", ROUND(100*(O19-Q19)/ABS(Q19), 1)))) -> - | AB19: =IF(T19="-", "-", IF(X19="-", "-", IF(ABS(X19)=0, "-", ROUND(100*(T19-X19)/ABS(X19), 1)))) -> - | AC19: =IF(Y19="-", "-", IF(AA19="-", "-", IF(ABS(AA19)=0, "-", ROUND(100*(Y19-AA19)/ABS(AA19), 1)))) -> - | AD19: =IF(Z19="-", "-", IF(AB19="-", "-", IF(ABS(AB19)=0, "-", ROUND(100*(Z19-AB19)/ABS(AB19), 1)))) -> - | AM19: =IF(AE19="-", "-", IF(AI19="-", "-", IF(ABS(AI19)=0, "-", ROUND(100*(AE19-AI19)/ABS(AI19), 1)))) -> - | AN19: =IF(AJ19="-", "-", IF(AL19="-", "-", IF(ABS(AL19)=0, "-", ROUND(100*(AJ19-AL19)/ABS(AL19), 1)))) -> - | AO19: =IF(AK19="-", "-", IF(AM19="-", "-", IF(ABS(AM19)=0, "-", ROUND(100*(AK19-AM19)/ABS(AM19), 1)))) -> - | AW19: 処分差損失 | BU19: =IF(BM19="-", "-", IF(BQ19="-", "-", IF(ABS(BQ19)=0, "-", ROUND(100*(BM19-BQ19)/ABS(BQ19), 1)))) -> - | BV19: =IF(BR19="-", "-", IF(BT19="-", "-", IF(ABS(BT19)=0, "-", ROUND(100*(BR19-BT19)/ABS(BT19), 1)))) -> - | BW19: =IF(BS19="-", "-", IF(BU19="-", "-", IF(ABS(BU19)=0, "-", ROUND(100*(BS19-BU19)/ABS(BU19), 1)))) -> -
B20: 副産物 | C20: 販売用 | D20: 規格外Ｂ | Q20: =IF(I20="-", "-", IF(M20="-", "-", IF(ABS(M20)=0, "-", ROUND(100*(I20-M20)/ABS(M20), 1)))) -> - | R20: =IF(N20="-", "-", IF(P20="-", "-", IF(ABS(P20)=0, "-", ROUND(100*(N20-P20)/ABS(P20), 1)))) -> - | S20: =IF(O20="-", "-", IF(Q20="-", "-", IF(ABS(Q20)=0, "-", ROUND(100*(O20-Q20)/ABS(Q20), 1)))) -> - | AB20: =IF(T20="-", "-", IF(X20="-", "-", IF(ABS(X20)=0, "-", ROUND(100*(T20-X20)/ABS(X20), 1)))) -> - | AC20: =IF(Y20="-", "-", IF(AA20="-", "-", IF(ABS(AA20)=0, "-", ROUND(100*(Y20-AA20)/ABS(AA20), 1)))) -> - | AD20: =IF(Z20="-", "-", IF(AB20="-", "-", IF(ABS(AB20)=0, "-", ROUND(100*(Z20-AB20)/ABS(AB20), 1)))) -> - | AM20: =IF(AE20="-", "-", IF(AI20="-", "-", IF(ABS(AI20)=0, "-", ROUND(100*(AE20-AI20)/ABS(AI20), 1)))) -> - | AN20: =IF(AJ20="-", "-", IF(AL20="-", "-", IF(ABS(AL20)=0, "-", ROUND(100*(AJ20-AL20)/ABS(AL20), 1)))) -> - | AO20: =IF(AK20="-", "-", IF(AM20="-", "-", IF(ABS(AM20)=0, "-", ROUND(100*(AK20-AM20)/ABS(AM20), 1)))) -> - | BB20: 所有台数（10経営体当たり） | BM20: 調査作物負担分
D21: 規格外Ｃ | Q21: =IF(I21="-", "-", IF(M21="-", "-", IF(ABS(M21)=0, "-", ROUND(100*(I21-M21)/ABS(M21), 1)))) -> - | R21: =IF(N21="-", "-", IF(P21="-", "-", IF(ABS(P21)=0, "-", ROUND(100*(N21-P21)/ABS(P21), 1)))) -> - | S21: =IF(O21="-", "-", IF(Q21="-", "-", IF(ABS(Q21)=0, "-", ROUND(100*(O21-Q21)/ABS(Q21), 1)))) -> - | AB21: =IF(T21="-", "-", IF(X21="-", "-", IF(ABS(X21)=0, "-", ROUND(100*(T21-X21)/ABS(X21), 1)))) -> - | AC21: =IF(Y21="-", "-", IF(AA21="-", "-", IF(ABS(AA21)=0, "-", ROUND(100*(Y21-AA21)/ABS(AA21), 1)))) -> - | AD21: =IF(Z21="-", "-", IF(AB21="-", "-", IF(ABS(AB21)=0, "-", ROUND(100*(Z21-AB21)/ABS(AB21), 1)))) -> - | AM21: =IF(AE21="-", "-", IF(AI21="-", "-", IF(ABS(AI21)=0, "-", ROUND(100*(AE21-AI21)/ABS(AI21), 1)))) -> - | AN21: =IF(AJ21="-", "-", IF(AL21="-", "-", IF(ABS(AL21)=0, "-", ROUND(100*(AJ21-AL21)/ABS(AL21), 1)))) -> - | AO21: =IF(AK21="-", "-", IF(AM21="-", "-", IF(ABS(AM21)=0, "-", ROUND(100*(AK21-AM21)/ABS(AM21), 1)))) -> - | AT21: 自動車 | AU21: 貨物自動車 | BJ21: =IF(BB21="-", "-", IF(BF21="-", "-", IF(ABS(BF21)=0, "-", ROUND(100*(BB21-BF21)/ABS(BF21), 1)))) -> - | BK21: =IF(BG21="-", "-", IF(BI21="-", "-", IF(ABS(BI21)=0, "-", ROUND(100*(BG21-BI21)/ABS(BI21), 1)))) -> - | BL21: =IF(BH21="-", "-", IF(BJ21="-", "-", IF(ABS(BJ21)=0, "-", ROUND(100*(BH21-BJ21)/ABS(BJ21), 1)))) -> - | BU21: =IF(BM21="-", "-", IF(BQ21="-", "-", IF(ABS(BQ21)=0, "-", ROUND(100*(BM21-BQ21)/ABS(BQ21), 1)))) -> - | BV21: =IF(BR21="-", "-", IF(BT21="-", "-", IF(ABS(BT21)=0, "-", ROUND(100*(BR21-BT21)/ABS(BT21), 1)))) -> - | BW21: =IF(BS21="-", "-", IF(BU21="-", "-", IF(ABS(BU21)=0, "-", ROUND(100*(BS21-BU21)/ABS(BU21), 1)))) -> -
D22: くず麦 | Q22: =IF(I22="-", "-", IF(M22="-", "-", IF(ABS(M22)=0, "-", ROUND(100*(I22-M22)/ABS(M22), 1)))) -> - | R22: =IF(N22="-", "-", IF(P22="-", "-", IF(ABS(P22)=0, "-", ROUND(100*(N22-P22)/ABS(P22), 1)))) -> - | S22: =IF(O22="-", "-", IF(Q22="-", "-", IF(ABS(Q22)=0, "-", ROUND(100*(O22-Q22)/ABS(Q22), 1)))) -> - | AB22: =IF(T22="-", "-", IF(X22="-", "-", IF(ABS(X22)=0, "-", ROUND(100*(T22-X22)/ABS(X22), 1)))) -> - | AC22: =IF(Y22="-", "-", IF(AA22="-", "-", IF(ABS(AA22)=0, "-", ROUND(100*(Y22-AA22)/ABS(AA22), 1)))) -> - | AD22: =IF(Z22="-", "-", IF(AB22="-", "-", IF(ABS(AB22)=0, "-", ROUND(100*(Z22-AB22)/ABS(AB22), 1)))) -> - | AM22: =IF(AE22="-", "-", IF(AI22="-", "-", IF(ABS(AI22)=0, "-", ROUND(100*(AE22-AI22)/ABS(AI22), 1)))) -> - | AN22: =IF(AJ22="-", "-", IF(AL22="-", "-", IF(ABS(AL22)=0, "-", ROUND(100*(AJ22-AL22)/ABS(AL22), 1)))) -> - | AO22: =IF(AK22="-", "-", IF(AM22="-", "-", IF(ABS(AM22)=0, "-", ROUND(100*(AK22-AM22)/ABS(AM22), 1)))) -> - | AU22: その他 | BU22: =IF(BM22="-", "-", IF(BQ22="-", "-", IF(ABS(BQ22)=0, "-", ROUND(100*(BM22-BQ22)/ABS(BQ22), 1)))) -> - | BV22: =IF(BR22="-", "-", IF(BT22="-", "-", IF(ABS(BT22)=0, "-", ROUND(100*(BR22-BT22)/ABS(BT22), 1)))) -> - | BW22: =IF(BS22="-", "-", IF(BU22="-", "-", IF(ABS(BU22)=0, "-", ROUND(100*(BS22-BU22)/ABS(BU22), 1)))) -> -
D23: 麦わら | Q23: =IF(I23="-", "-", IF(M23="-", "-", IF(ABS(M23)=0, "-", ROUND(100*(I23-M23)/ABS(M23), 1)))) -> - | R23: =IF(N23="-", "-", IF(P23="-", "-", IF(ABS(P23)=0, "-", ROUND(100*(N23-P23)/ABS(P23), 1)))) -> - | S23: =IF(O23="-", "-", IF(Q23="-", "-", IF(ABS(Q23)=0, "-", ROUND(100*(O23-Q23)/ABS(Q23), 1)))) -> - | AB23: =IF(T23="-", "-", IF(X23="-", "-", IF(ABS(X23)=0, "-", ROUND(100*(T23-X23)/ABS(X23), 1)))) -> - | AC23: =IF(Y23="-", "-", IF(AA23="-", "-", IF(ABS(AA23)=0, "-", ROUND(100*(Y23-AA23)/ABS(AA23), 1)))) -> - | AD23: =IF(Z23="-", "-", IF(AB23="-", "-", IF(ABS(AB23)=0, "-", ROUND(100*(Z23-AB23)/ABS(AB23), 1)))) -> - | AM23: =IF(AE23="-", "-", IF(AI23="-", "-", IF(ABS(AI23)=0, "-", ROUND(100*(AE23-AI23)/ABS(AI23), 1)))) -> - | AN23: =IF(AJ23="-", "-", IF(AL23="-", "-", IF(ABS(AL23)=0, "-", ROUND(100*(AJ23-AL23)/ABS(AL23), 1)))) -> - | AO23: =IF(AK23="-", "-", IF(AM23="-", "-", IF(ABS(AM23)=0, "-", ROUND(100*(AK23-AM23)/ABS(AM23), 1)))) -> - | AU23: 計 | BU23: =IF(BM23="-", "-", IF(BQ23="-", "-", IF(ABS(BQ23)=0, "-", ROUND(100*(BM23-BQ23)/ABS(BQ23), 1)))) -> - | BV23: =IF(BR23="-", "-", IF(BT23="-", "-", IF(ABS(BT23)=0, "-", ROUND(100*(BR23-BT23)/ABS(BT23), 1)))) -> - | BW23: =IF(BS23="-", "-", IF(BU23="-", "-", IF(ABS(BU23)=0, "-", ROUND(100*(BS23-BU23)/ABS(BU23), 1)))) -> -
D24: 小計 | AB24: =IF(T24="-", "-", IF(X24="-", "-", IF(ABS(X24)=0, "-", ROUND(100*(T24-X24)/ABS(X24), 1)))) -> - | AC24: =IF(Y24="-", "-", IF(AA24="-", "-", IF(ABS(AA24)=0, "-", ROUND(100*(Y24-AA24)/ABS(AA24), 1)))) -> - | AD24: =IF(Z24="-", "-", IF(AB24="-", "-", IF(ABS(AB24)=0, "-", ROUND(100*(Z24-AB24)/ABS(AB24), 1)))) -> - | AW24: 処分差損失 | BU24: =IF(BM24="-", "-", IF(BQ24="-", "-", IF(ABS(BQ24)=0, "-", ROUND(100*(BM24-BQ24)/ABS(BQ24), 1)))) -> - | BV24: =IF(BR24="-", "-", IF(BT24="-", "-", IF(ABS(BT24)=0, "-", ROUND(100*(BR24-BT24)/ABS(BT24), 1)))) -> - | BW24: =IF(BS24="-", "-", IF(BU24="-", "-", IF(ABS(BU24)=0, "-", ROUND(100*(BS24-BU24)/ABS(BU24), 1)))) -> -
C25: 組織用 | D25: 規格外Ｂ | Q25: =IF(I25="-", "-", IF(M25="-", "-", IF(ABS(M25)=0, "-", ROUND(100*(I25-M25)/ABS(M25), 1)))) -> - | R25: =IF(N25="-", "-", IF(P25="-", "-", IF(ABS(P25)=0, "-", ROUND(100*(N25-P25)/ABS(P25), 1)))) -> - | S25: =IF(O25="-", "-", IF(Q25="-", "-", IF(ABS(Q25)=0, "-", ROUND(100*(O25-Q25)/ABS(Q25), 1)))) -> - | AB25: =IF(T25="-", "-", IF(X25="-", "-", IF(ABS(X25)=0, "-", ROUND(100*(T25-X25)/ABS(X25), 1)))) -> - | AC25: =IF(Y25="-", "-", IF(AA25="-", "-", IF(ABS(AA25)=0, "-", ROUND(100*(Y25-AA25)/ABS(AA25), 1)))) -> - | AD25: =IF(Z25="-", "-", IF(AB25="-", "-", IF(ABS(AB25)=0, "-", ROUND(100*(Z25-AB25)/ABS(AB25), 1)))) -> - | AM25: =IF(AE25="-", "-", IF(AI25="-", "-", IF(ABS(AI25)=0, "-", ROUND(100*(AE25-AI25)/ABS(AI25), 1)))) -> - | AN25: =IF(AJ25="-", "-", IF(AL25="-", "-", IF(ABS(AL25)=0, "-", ROUND(100*(AJ25-AL25)/ABS(AL25), 1)))) -> - | AO25: =IF(AK25="-", "-", IF(AM25="-", "-", IF(ABS(AM25)=0, "-", ROUND(100*(AK25-AM25)/ABS(AM25), 1)))) -> - | BB25: 所有台数（10経営体当たり） | BM25: 調査作物負担分
D26: 規格外Ｃ | Q26: =IF(I26="-", "-", IF(M26="-", "-", IF(ABS(M26)=0, "-", ROUND(100*(I26-M26)/ABS(M26), 1)))) -> - | R26: =IF(N26="-", "-", IF(P26="-", "-", IF(ABS(P26)=0, "-", ROUND(100*(N26-P26)/ABS(P26), 1)))) -> - | S26: =IF(O26="-", "-", IF(Q26="-", "-", IF(ABS(Q26)=0, "-", ROUND(100*(O26-Q26)/ABS(Q26), 1)))) -> - | AB26: =IF(T26="-", "-", IF(X26="-", "-", IF(ABS(X26)=0, "-", ROUND(100*(T26-X26)/ABS(X26), 1)))) -> - | AC26: =IF(Y26="-", "-", IF(AA26="-", "-", IF(ABS(AA26)=0, "-", ROUND(100*(Y26-AA26)/ABS(AA26), 1)))) -> - | AD26: =IF(Z26="-", "-", IF(AB26="-", "-", IF(ABS(AB26)=0, "-", ROUND(100*(Z26-AB26)/ABS(AB26), 1)))) -> - | AM26: =IF(AE26="-", "-", IF(AI26="-", "-", IF(ABS(AI26)=0, "-", ROUND(100*(AE26-AI26)/ABS(AI26), 1)))) -> - | AN26: =IF(AJ26="-", "-", IF(AL26="-", "-", IF(ABS(AL26)=0, "-", ROUND(100*(AJ26-AL26)/ABS(AL26), 1)))) -> - | AO26: =IF(AK26="-", "-", IF(AM26="-", "-", IF(ABS(AM26)=0, "-", ROUND(100*(AK26-AM26)/ABS(AM26), 1)))) -> - | AT26: 農機具 | AU26: 乗用トラクター | AX26: 20馬力未満 | BJ26: =IF(BB26="-", "-", IF(BF26="-", "-", IF(ABS(BF26)=0, "-", ROUND(100*(BB26-BF26)/ABS(BF26), 1)))) -> - | BK26: =IF(BG26="-", "-", IF(BI26="-", "-", IF(ABS(BI26)=0, "-", ROUND(100*(BG26-BI26)/ABS(BI26), 1)))) -> - | BL26: =IF(BH26="-", "-", IF(BJ26="-", "-", IF(ABS(BJ26)=0, "-", ROUND(100*(BH26-BJ26)/ABS(BJ26), 1)))) -> - | BU26: =IF(BM26="-", "-", IF(BQ26="-", "-", IF(ABS(BQ26)=0, "-", ROUND(100*(BM26-BQ26)/ABS(BQ26), 1)))) -> - | BV26: =IF(BR26="-", "-", IF(BT26="-", "-", IF(ABS(BT26)=0, "-", ROUND(100*(BR26-BT26)/ABS(BT26), 1)))) -> - | BW26: =IF(BS26="-", "-", IF(BU26="-", "-", IF(ABS(BU26)=0, "-", ROUND(100*(BS26-BU26)/ABS(BU26), 1)))) -> -
D27: くず麦 | Q27: =IF(I27="-", "-", IF(M27="-", "-", IF(ABS(M27)=0, "-", ROUND(100*(I27-M27)/ABS(M27), 1)))) -> - | R27: =IF(N27="-", "-", IF(P27="-", "-", IF(ABS(P27)=0, "-", ROUND(100*(N27-P27)/ABS(P27), 1)))) -> - | S27: =IF(O27="-", "-", IF(Q27="-", "-", IF(ABS(Q27)=0, "-", ROUND(100*(O27-Q27)/ABS(Q27), 1)))) -> - | AB27: =IF(T27="-", "-", IF(X27="-", "-", IF(ABS(X27)=0, "-", ROUND(100*(T27-X27)/ABS(X27), 1)))) -> - | AC27: =IF(Y27="-", "-", IF(AA27="-", "-", IF(ABS(AA27)=0, "-", ROUND(100*(Y27-AA27)/ABS(AA27), 1)))) -> - | AD27: =IF(Z27="-", "-", IF(AB27="-", "-", IF(ABS(AB27)=0, "-", ROUND(100*(Z27-AB27)/ABS(AB27), 1)))) -> - | AM27: =IF(AE27="-", "-", IF(AI27="-", "-", IF(ABS(AI27)=0, "-", ROUND(100*(AE27-AI27)/ABS(AI27), 1)))) -> - | AN27: =IF(AJ27="-", "-", IF(AL27="-", "-", IF(ABS(AL27)=0, "-", ROUND(100*(AJ27-AL27)/ABS(AL27), 1)))) -> - | AO27: =IF(AK27="-", "-", IF(AM27="-", "-", IF(ABS(AM27)=0, "-", ROUND(100*(AK27-AM27)/ABS(AM27), 1)))) -> - | AX27: 20～50馬力未満 | BJ27: =IF(BB27="-", "-", IF(BF27="-", "-", IF(ABS(BF27)=0, "-", ROUND(100*(BB27-BF27)/ABS(BF27), 1)))) -> - | BK27: =IF(BG27="-", "-", IF(BI27="-", "-", IF(ABS(BI27)=0, "-", ROUND(100*(BG27-BI27)/ABS(BI27), 1)))) -> - | BL27: =IF(BH27="-", "-", IF(BJ27="-", "-", IF(ABS(BJ27)=0, "-", ROUND(100*(BH27-BJ27)/ABS(BJ27), 1)))) -> - | BU27: =IF(BM27="-", "-", IF(BQ27="-", "-", IF(ABS(BQ27)=0, "-", ROUND(100*(BM27-BQ27)/ABS(BQ27), 1)))) -> - | BV27: =IF(BR27="-", "-", IF(BT27="-", "-", IF(ABS(BT27)=0, "-", ROUND(100*(BR27-BT27)/ABS(BT27), 1)))) -> - | BW27: =IF(BS27="-", "-", IF(BU27="-", "-", IF(ABS(BU27)=0, "-", ROUND(100*(BS27-BU27)/ABS(BU27), 1)))) -> -
D28: 麦わら | Q28: =IF(I28="-", "-", IF(M28="-", "-", IF(ABS(M28)=0, "-", ROUND(100*(I28-M28)/ABS(M28), 1)))) -> - | R28: =IF(N28="-", "-", IF(P28="-", "-", IF(ABS(P28)=0, "-", ROUND(100*(N28-P28)/ABS(P28), 1)))) -> - | S28: =IF(O28="-", "-", IF(Q28="-", "-", IF(ABS(Q28)=0, "-", ROUND(100*(O28-Q28)/ABS(Q28), 1)))) -> - | AB28: =IF(T28="-", "-", IF(X28="-", "-", IF(ABS(X28)=0, "-", ROUND(100*(T28-X28)/ABS(X28), 1)))) -> - | AC28: =IF(Y28="-", "-", IF(AA28="-", "-", IF(ABS(AA28)=0, "-", ROUND(100*(Y28-AA28)/ABS(AA28), 1)))) -> - | AD28: =IF(Z28="-", "-", IF(AB28="-", "-", IF(ABS(AB28)=0, "-", ROUND(100*(Z28-AB28)/ABS(AB28), 1)))) -> - | AM28: =IF(AE28="-", "-", IF(AI28="-", "-", IF(ABS(AI28)=0, "-", ROUND(100*(AE28-AI28)/ABS(AI28), 1)))) -> - | AN28: =IF(AJ28="-", "-", IF(AL28="-", "-", IF(ABS(AL28)=0, "-", ROUND(100*(AJ28-AL28)/ABS(AL28), 1)))) -> - | AO28: =IF(AK28="-", "-", IF(AM28="-", "-", IF(ABS(AM28)=0, "-", ROUND(100*(AK28-AM28)/ABS(AM28), 1)))) -> - | AX28: 50馬力以上 | BJ28: =IF(BB28="-", "-", IF(BF28="-", "-", IF(ABS(BF28)=0, "-", ROUND(100*(BB28-BF28)/ABS(BF28), 1)))) -> - | BK28: =IF(BG28="-", "-", IF(BI28="-", "-", IF(ABS(BI28)=0, "-", ROUND(100*(BG28-BI28)/ABS(BI28), 1)))) -> - | BL28: =IF(BH28="-", "-", IF(BJ28="-", "-", IF(ABS(BJ28)=0, "-", ROUND(100*(BH28-BJ28)/ABS(BJ28), 1)))) -> - | BU28: =IF(BM28="-", "-", IF(BQ28="-", "-", IF(ABS(BQ28)=0, "-", ROUND(100*(BM28-BQ28)/ABS(BQ28), 1)))) -> - | BV28: =IF(BR28="-", "-", IF(BT28="-", "-", IF(ABS(BT28)=0, "-", ROUND(100*(BR28-BT28)/ABS(BT28), 1)))) -> - | BW28: =IF(BS28="-", "-", IF(BU28="-", "-", IF(ABS(BU28)=0, "-", ROUND(100*(BS28-BU28)/ABS(BU28), 1)))) -> -
E29: 無評価 | Q29: =IF(I29="-", "-", IF(M29="-", "-", IF(ABS(M29)=0, "-", ROUND(100*(I29-M29)/ABS(M29), 1)))) -> - | R29: =IF(N29="-", "-", IF(P29="-", "-", IF(ABS(P29)=0, "-", ROUND(100*(N29-P29)/ABS(P29), 1)))) -> - | S29: =IF(O29="-", "-", IF(Q29="-", "-", IF(ABS(Q29)=0, "-", ROUND(100*(O29-Q29)/ABS(Q29), 1)))) -> - | AU29: 歩行用トラクター | BJ29: =IF(BB29="-", "-", IF(BF29="-", "-", IF(ABS(BF29)=0, "-", ROUND(100*(BB29-BF29)/ABS(BF29), 1)))) -> - | BK29: =IF(BG29="-", "-", IF(BI29="-", "-", IF(ABS(BI29)=0, "-", ROUND(100*(BG29-BI29)/ABS(BI29), 1)))) -> - | BL29: =IF(BH29="-", "-", IF(BJ29="-", "-", IF(ABS(BJ29)=0, "-", ROUND(100*(BH29-BJ29)/ABS(BJ29), 1)))) -> - | BU29: =IF(BM29="-", "-", IF(BQ29="-", "-", IF(ABS(BQ29)=0, "-", ROUND(100*(BM29-BQ29)/ABS(BQ29), 1)))) -> - | BV29: =IF(BR29="-", "-", IF(BT29="-", "-", IF(ABS(BT29)=0, "-", ROUND(100*(BR29-BT29)/ABS(BT29), 1)))) -> - | BW29: =IF(BS29="-", "-", IF(BU29="-", "-", IF(ABS(BU29)=0, "-", ROUND(100*(BS29-BU29)/ABS(BU29), 1)))) -> -
D30: 小計 | AB30: =IF(T30="-", "-", IF(X30="-", "-", IF(ABS(X30)=0, "-", ROUND(100*(T30-X30)/ABS(X30), 1)))) -> - | AC30: =IF(Y30="-", "-", IF(AA30="-", "-", IF(ABS(AA30)=0, "-", ROUND(100*(Y30-AA30)/ABS(AA30), 1)))) -> - | AD30: =IF(Z30="-", "-", IF(AB30="-", "-", IF(ABS(AB30)=0, "-", ROUND(100*(Z30-AB30)/ABS(AB30), 1)))) -> - | AU30: たい肥等散布機 | BJ30: =IF(BB30="-", "-", IF(BF30="-", "-", IF(ABS(BF30)=0, "-", ROUND(100*(BB30-BF30)/ABS(BF30), 1)))) -> - | BK30: =IF(BG30="-", "-", IF(BI30="-", "-", IF(ABS(BI30)=0, "-", ROUND(100*(BG30-BI30)/ABS(BI30), 1)))) -> - | BL30: =IF(BH30="-", "-", IF(BJ30="-", "-", IF(ABS(BJ30)=0, "-", ROUND(100*(BH30-BJ30)/ABS(BJ30), 1)))) -> - | BU30: =IF(BM30="-", "-", IF(BQ30="-", "-", IF(ABS(BQ30)=0, "-", ROUND(100*(BM30-BQ30)/ABS(BQ30), 1)))) -> - | BV30: =IF(BR30="-", "-", IF(BT30="-", "-", IF(ABS(BT30)=0, "-", ROUND(100*(BR30-BT30)/ABS(BT30), 1)))) -> - | BW30: =IF(BS30="-", "-", IF(BU30="-", "-", IF(ABS(BU30)=0, "-", ROUND(100*(BS30-BU30)/ABS(BU30), 1)))) -> -
C31: 合計 | AB31: =IF(T31="-", "-", IF(X31="-", "-", IF(ABS(X31)=0, "-", ROUND(100*(T31-X31)/ABS(X31), 1)))) -> - | AC31: =IF(Y31="-", "-", IF(AA31="-", "-", IF(ABS(AA31)=0, "-", ROUND(100*(Y31-AA31)/ABS(AA31), 1)))) -> - | AD31: =IF(Z31="-", "-", IF(AB31="-", "-", IF(ABS(AB31)=0, "-", ROUND(100*(Z31-AB31)/ABS(AB31), 1)))) -> - | AU31: 総合は種機 | BJ31: =IF(BB31="-", "-", IF(BF31="-", "-", IF(ABS(BF31)=0, "-", ROUND(100*(BB31-BF31)/ABS(BF31), 1)))) -> - | BK31: =IF(BG31="-", "-", IF(BI31="-", "-", IF(ABS(BI31)=0, "-", ROUND(100*(BG31-BI31)/ABS(BI31), 1)))) -> - | BL31: =IF(BH31="-", "-", IF(BJ31="-", "-", IF(ABS(BJ31)=0, "-", ROUND(100*(BH31-BJ31)/ABS(BJ31), 1)))) -> - | BU31: =IF(BM31="-", "-", IF(BQ31="-", "-", IF(ABS(BQ31)=0, "-", ROUND(100*(BM31-BQ31)/ABS(BQ31), 1)))) -> - | BV31: =IF(BR31="-", "-", IF(BT31="-", "-", IF(ABS(BT31)=0, "-", ROUND(100*(BR31-BT31)/ABS(BT31), 1)))) -> - | BW31: =IF(BS31="-", "-", IF(BU31="-", "-", IF(ABS(BU31)=0, "-", ROUND(100*(BS31-BU31)/ABS(BU31), 1)))) -> -
B32: そば | I32: 数量 | T32: 価額 | AE32: 単価 | AU32: 移植機 | BJ32: =IF(BB32="-", "-", IF(BF32="-", "-", IF(ABS(BF32)=0, "-", ROUND(100*(BB32-BF32)/ABS(BF32), 1)))) -> - | BK32: =IF(BG32="-", "-", IF(BI32="-", "-", IF(ABS(BI32)=0, "-", ROUND(100*(BG32-BI32)/ABS(BI32), 1)))) -> - | BL32: =IF(BH32="-", "-", IF(BJ32="-", "-", IF(ABS(BJ32)=0, "-", ROUND(100*(BH32-BJ32)/ABS(BJ32), 1)))) -> - | BU32: =IF(BM32="-", "-", IF(BQ32="-", "-", IF(ABS(BQ32)=0, "-", ROUND(100*(BM32-BQ32)/ABS(BQ32), 1)))) -> - | BV32: =IF(BR32="-", "-", IF(BT32="-", "-", IF(ABS(BT32)=0, "-", ROUND(100*(BR32-BT32)/ABS(BT32), 1)))) -> - | BW32: =IF(BS32="-", "-", IF(BU32="-", "-", IF(ABS(BU32)=0, "-", ROUND(100*(BS32-BU32)/ABS(BU32), 1)))) -> -
I33: =IF($B$1<>"",$B$1,"") | M33: =IF($B$1<>"",$B$1-1,"") | Q33: 増減率 | T33: =IF($B$1<>"",$B$1,"") | X33: =IF($B$1<>"",$B$1-1,"") | AB33: 増減率 | AE33: =IF($B$1<>"",$B$1,"") | AI33: =IF($B$1<>"",$B$1-1,"") | AM33: 増減率 | AU33: 中耕除草機 | BJ33: =IF(BB33="-", "-", IF(BF33="-", "-", IF(ABS(BF33)=0, "-", ROUND(100*(BB33-BF33)/ABS(BF33), 1)))) -> - | BK33: =IF(BG33="-", "-", IF(BI33="-", "-", IF(ABS(BI33)=0, "-", ROUND(100*(BG33-BI33)/ABS(BI33), 1)))) -> - | BL33: =IF(BH33="-", "-", IF(BJ33="-", "-", IF(ABS(BJ33)=0, "-", ROUND(100*(BH33-BJ33)/ABS(BJ33), 1)))) -> - | BU33: =IF(BM33="-", "-", IF(BQ33="-", "-", IF(ABS(BQ33)=0, "-", ROUND(100*(BM33-BQ33)/ABS(BQ33), 1)))) -> - | BV33: =IF(BR33="-", "-", IF(BT33="-", "-", IF(ABS(BT33)=0, "-", ROUND(100*(BR33-BT33)/ABS(BT33), 1)))) -> - | BW33: =IF(BS33="-", "-", IF(BU33="-", "-", IF(ABS(BU33)=0, "-", ROUND(100*(BS33-BU33)/ABS(BU33), 1)))) -> -
B34: 主産物 | C34: 販売用 | D34: そば | E34: １等 | Q34: =IF(I34="-", "-", IF(M34="-", "-", IF(ABS(M34)=0, "-", ROUND(100*(I34-M34)/ABS(M34), 1)))) -> - | R34: =IF(N34="-", "-", IF(P34="-", "-", IF(ABS(P34)=0, "-", ROUND(100*(N34-P34)/ABS(P34), 1)))) -> - | S34: =IF(O34="-", "-", IF(Q34="-", "-", IF(ABS(Q34)=0, "-", ROUND(100*(O34-Q34)/ABS(Q34), 1)))) -> - | AB34: =IF(T34="-", "-", IF(X34="-", "-", IF(ABS(X34)=0, "-", ROUND(100*(T34-X34)/ABS(X34), 1)))) -> - | AC34: =IF(Y34="-", "-", IF(AA34="-", "-", IF(ABS(AA34)=0, "-", ROUND(100*(Y34-AA34)/ABS(AA34), 1)))) -> - | AD34: =IF(Z34="-", "-", IF(AB34="-", "-", IF(ABS(AB34)=0, "-", ROUND(100*(Z34-AB34)/ABS(AB34), 1)))) -> - | AM34: =IF(AE34="-", "-", IF(AI34="-", "-", IF(ABS(AI34)=0, "-", ROUND(100*(AE34-AI34)/ABS(AI34), 1)))) -> - | AN34: =IF(AJ34="-", "-", IF(AL34="-", "-", IF(ABS(AL34)=0, "-", ROUND(100*(AJ34-AL34)/ABS(AL34), 1)))) -> - | AO34: =IF(AK34="-", "-", IF(AM34="-", "-", IF(ABS(AM34)=0, "-", ROUND(100*(AK34-AM34)/ABS(AM34), 1)))) -> - | AU34: 肥料散布機 | BJ34: =IF(BB34="-", "-", IF(BF34="-", "-", IF(ABS(BF34)=0, "-", ROUND(100*(BB34-BF34)/ABS(BF34), 1)))) -> - | BK34: =IF(BG34="-", "-", IF(BI34="-", "-", IF(ABS(BI34)=0, "-", ROUND(100*(BG34-BI34)/ABS(BI34), 1)))) -> - | BL34: =IF(BH34="-", "-", IF(BJ34="-", "-", IF(ABS(BJ34)=0, "-", ROUND(100*(BH34-BJ34)/ABS(BJ34), 1)))) -> - | BU34: =IF(BM34="-", "-", IF(BQ34="-", "-", IF(ABS(BQ34)=0, "-", ROUND(100*(BM34-BQ34)/ABS(BQ34), 1)))) -> - | BV34: =IF(BR34="-", "-", IF(BT34="-", "-", IF(ABS(BT34)=0, "-", ROUND(100*(BR34-BT34)/ABS(BT34), 1)))) -> - | BW34: =IF(BS34="-", "-", IF(BU34="-", "-", IF(ABS(BU34)=0, "-", ROUND(100*(BS34-BU34)/ABS(BU34), 1)))) -> -
E35: ２等 | Q35: =IF(I35="-", "-", IF(M35="-", "-", IF(ABS(M35)=0, "-", ROUND(100*(I35-M35)/ABS(M35), 1)))) -> - | R35: =IF(N35="-", "-", IF(P35="-", "-", IF(ABS(P35)=0, "-", ROUND(100*(N35-P35)/ABS(P35), 1)))) -> - | S35: =IF(O35="-", "-", IF(Q35="-", "-", IF(ABS(Q35)=0, "-", ROUND(100*(O35-Q35)/ABS(Q35), 1)))) -> - | AB35: =IF(T35="-", "-", IF(X35="-", "-", IF(ABS(X35)=0, "-", ROUND(100*(T35-X35)/ABS(X35), 1)))) -> - | AC35: =IF(Y35="-", "-", IF(AA35="-", "-", IF(ABS(AA35)=0, "-", ROUND(100*(Y35-AA35)/ABS(AA35), 1)))) -> - | AD35: =IF(Z35="-", "-", IF(AB35="-", "-", IF(ABS(AB35)=0, "-", ROUND(100*(Z35-AB35)/ABS(AB35), 1)))) -> - | AM35: =IF(AE35="-", "-", IF(AI35="-", "-", IF(ABS(AI35)=0, "-", ROUND(100*(AE35-AI35)/ABS(AI35), 1)))) -> - | AN35: =IF(AJ35="-", "-", IF(AL35="-", "-", IF(ABS(AL35)=0, "-", ROUND(100*(AJ35-AL35)/ABS(AL35), 1)))) -> - | AO35: =IF(AK35="-", "-", IF(AM35="-", "-", IF(ABS(AM35)=0, "-", ROUND(100*(AK35-AM35)/ABS(AM35), 1)))) -> - | AU35: 動力噴霧機 | BJ35: =IF(BB35="-", "-", IF(BF35="-", "-", IF(ABS(BF35)=0, "-", ROUND(100*(BB35-BF35)/ABS(BF35), 1)))) -> - | BK35: =IF(BG35="-", "-", IF(BI35="-", "-", IF(ABS(BI35)=0, "-", ROUND(100*(BG35-BI35)/ABS(BI35), 1)))) -> - | BL35: =IF(BH35="-", "-", IF(BJ35="-", "-", IF(ABS(BJ35)=0, "-", ROUND(100*(BH35-BJ35)/ABS(BJ35), 1)))) -> - | BU35: =IF(BM35="-", "-", IF(BQ35="-", "-", IF(ABS(BQ35)=0, "-", ROUND(100*(BM35-BQ35)/ABS(BQ35), 1)))) -> - | BV35: =IF(BR35="-", "-", IF(BT35="-", "-", IF(ABS(BT35)=0, "-", ROUND(100*(BR35-BT35)/ABS(BT35), 1)))) -> - | BW35: =IF(BS35="-", "-", IF(BU35="-", "-", IF(ABS(BU35)=0, "-", ROUND(100*(BS35-BU35)/ABS(BU35), 1)))) -> -
E36: 規格外 | Q36: =IF(I36="-", "-", IF(M36="-", "-", IF(ABS(M36)=0, "-", ROUND(100*(I36-M36)/ABS(M36), 1)))) -> - | R36: =IF(N36="-", "-", IF(P36="-", "-", IF(ABS(P36)=0, "-", ROUND(100*(N36-P36)/ABS(P36), 1)))) -> - | S36: =IF(O36="-", "-", IF(Q36="-", "-", IF(ABS(Q36)=0, "-", ROUND(100*(O36-Q36)/ABS(Q36), 1)))) -> - | AB36: =IF(T36="-", "-", IF(X36="-", "-", IF(ABS(X36)=0, "-", ROUND(100*(T36-X36)/ABS(X36), 1)))) -> - | AC36: =IF(Y36="-", "-", IF(AA36="-", "-", IF(ABS(AA36)=0, "-", ROUND(100*(Y36-AA36)/ABS(AA36), 1)))) -> - | AD36: =IF(Z36="-", "-", IF(AB36="-", "-", IF(ABS(AB36)=0, "-", ROUND(100*(Z36-AB36)/ABS(AB36), 1)))) -> - | AM36: =IF(AE36="-", "-", IF(AI36="-", "-", IF(ABS(AI36)=0, "-", ROUND(100*(AE36-AI36)/ABS(AI36), 1)))) -> - | AN36: =IF(AJ36="-", "-", IF(AL36="-", "-", IF(ABS(AL36)=0, "-", ROUND(100*(AJ36-AL36)/ABS(AL36), 1)))) -> - | AO36: =IF(AK36="-", "-", IF(AM36="-", "-", IF(ABS(AM36)=0, "-", ROUND(100*(AK36-AM36)/ABS(AM36), 1)))) -> - | AU36: 動力散粉機 | BJ36: =IF(BB36="-", "-", IF(BF36="-", "-", IF(ABS(BF36)=0, "-", ROUND(100*(BB36-BF36)/ABS(BF36), 1)))) -> - | BK36: =IF(BG36="-", "-", IF(BI36="-", "-", IF(ABS(BI36)=0, "-", ROUND(100*(BG36-BI36)/ABS(BI36), 1)))) -> - | BL36: =IF(BH36="-", "-", IF(BJ36="-", "-", IF(ABS(BJ36)=0, "-", ROUND(100*(BH36-BJ36)/ABS(BJ36), 1)))) -> - | BU36: =IF(BM36="-", "-", IF(BQ36="-", "-", IF(ABS(BQ36)=0, "-", ROUND(100*(BM36-BQ36)/ABS(BQ36), 1)))) -> - | BV36: =IF(BR36="-", "-", IF(BT36="-", "-", IF(ABS(BT36)=0, "-", ROUND(100*(BR36-BT36)/ABS(BT36), 1)))) -> - | BW36: =IF(BS36="-", "-", IF(BU36="-", "-", IF(ABS(BU36)=0, "-", ROUND(100*(BS36-BU36)/ABS(BU36), 1)))) -> -
D37: その他 | Q37: =IF(I37="-", "-", IF(M37="-", "-", IF(ABS(M37)=0, "-", ROUND(100*(I37-M37)/ABS(M37), 1)))) -> - | R37: =IF(N37="-", "-", IF(P37="-", "-", IF(ABS(P37)=0, "-", ROUND(100*(N37-P37)/ABS(P37), 1)))) -> - | S37: =IF(O37="-", "-", IF(Q37="-", "-", IF(ABS(Q37)=0, "-", ROUND(100*(O37-Q37)/ABS(Q37), 1)))) -> - | AB37: =IF(T37="-", "-", IF(X37="-", "-", IF(ABS(X37)=0, "-", ROUND(100*(T37-X37)/ABS(X37), 1)))) -> - | AC37: =IF(Y37="-", "-", IF(AA37="-", "-", IF(ABS(AA37)=0, "-", ROUND(100*(Y37-AA37)/ABS(AA37), 1)))) -> - | AD37: =IF(Z37="-", "-", IF(AB37="-", "-", IF(ABS(AB37)=0, "-", ROUND(100*(Z37-AB37)/ABS(AB37), 1)))) -> - | AM37: =IF(AE37="-", "-", IF(AI37="-", "-", IF(ABS(AI37)=0, "-", ROUND(100*(AE37-AI37)/ABS(AI37), 1)))) -> - | AN37: =IF(AJ37="-", "-", IF(AL37="-", "-", IF(ABS(AL37)=0, "-", ROUND(100*(AJ37-AL37)/ABS(AL37), 1)))) -> - | AO37: =IF(AK37="-", "-", IF(AM37="-", "-", IF(ABS(AM37)=0, "-", ROUND(100*(AK37-AM37)/ABS(AM37), 1)))) -> - | AU37: 自脱型コンバイン | AX37: ３条以下 | BJ37: =IF(BB37="-", "-", IF(BF37="-", "-", IF(ABS(BF37)=0, "-", ROUND(100*(BB37-BF37)/ABS(BF37), 1)))) -> - | BK37: =IF(BG37="-", "-", IF(BI37="-", "-", IF(ABS(BI37)=0, "-", ROUND(100*(BG37-BI37)/ABS(BI37), 1)))) -> - | BL37: =IF(BH37="-", "-", IF(BJ37="-", "-", IF(ABS(BJ37)=0, "-", ROUND(100*(BH37-BJ37)/ABS(BJ37), 1)))) -> - | BU37: =IF(BM37="-", "-", IF(BQ37="-", "-", IF(ABS(BQ37)=0, "-", ROUND(100*(BM37-BQ37)/ABS(BQ37), 1)))) -> - | BV37: =IF(BR37="-", "-", IF(BT37="-", "-", IF(ABS(BT37)=0, "-", ROUND(100*(BR37-BT37)/ABS(BT37), 1)))) -> - | BW37: =IF(BS37="-", "-", IF(BU37="-", "-", IF(ABS(BU37)=0, "-", ROUND(100*(BS37-BU37)/ABS(BU37), 1)))) -> -
D38: 小計 | Q38: =IF(I38="-", "-", IF(M38="-", "-", IF(ABS(M38)=0, "-", ROUND(100*(I38-M38)/ABS(M38), 1)))) -> - | R38: =IF(N38="-", "-", IF(P38="-", "-", IF(ABS(P38)=0, "-", ROUND(100*(N38-P38)/ABS(P38), 1)))) -> - | S38: =IF(O38="-", "-", IF(Q38="-", "-", IF(ABS(Q38)=0, "-", ROUND(100*(O38-Q38)/ABS(Q38), 1)))) -> - | AB38: =IF(T38="-", "-", IF(X38="-", "-", IF(ABS(X38)=0, "-", ROUND(100*(T38-X38)/ABS(X38), 1)))) -> - | AC38: =IF(Y38="-", "-", IF(AA38="-", "-", IF(ABS(AA38)=0, "-", ROUND(100*(Y38-AA38)/ABS(AA38), 1)))) -> - | AD38: =IF(Z38="-", "-", IF(AB38="-", "-", IF(ABS(AB38)=0, "-", ROUND(100*(Z38-AB38)/ABS(AB38), 1)))) -> - | AM38: =IF(AE38="-", "-", IF(AI38="-", "-", IF(ABS(AI38)=0, "-", ROUND(100*(AE38-AI38)/ABS(AI38), 1)))) -> - | AN38: =IF(AJ38="-", "-", IF(AL38="-", "-", IF(ABS(AL38)=0, "-", ROUND(100*(AJ38-AL38)/ABS(AL38), 1)))) -> - | AO38: =IF(AK38="-", "-", IF(AM38="-", "-", IF(ABS(AM38)=0, "-", ROUND(100*(AK38-AM38)/ABS(AM38), 1)))) -> - | AX38: ４条以上 | BJ38: =IF(BB38="-", "-", IF(BF38="-", "-", IF(ABS(BF38)=0, "-", ROUND(100*(BB38-BF38)/ABS(BF38), 1)))) -> - | BK38: =IF(BG38="-", "-", IF(BI38="-", "-", IF(ABS(BI38)=0, "-", ROUND(100*(BG38-BI38)/ABS(BI38), 1)))) -> - | BL38: =IF(BH38="-", "-", IF(BJ38="-", "-", IF(ABS(BJ38)=0, "-", ROUND(100*(BH38-BJ38)/ABS(BJ38), 1)))) -> - | BU38: =IF(BM38="-", "-", IF(BQ38="-", "-", IF(ABS(BQ38)=0, "-", ROUND(100*(BM38-BQ38)/ABS(BQ38), 1)))) -> - | BV38: =IF(BR38="-", "-", IF(BT38="-", "-", IF(ABS(BT38)=0, "-", ROUND(100*(BR38-BT38)/ABS(BT38), 1)))) -> - | BW38: =IF(BS38="-", "-", IF(BU38="-", "-", IF(ABS(BU38)=0, "-", ROUND(100*(BS38-BU38)/ABS(BU38), 1)))) -> -
C39: 組織用 | D39: 食用 | Q39: =IF(I39="-", "-", IF(M39="-", "-", IF(ABS(M39)=0, "-", ROUND(100*(I39-M39)/ABS(M39), 1)))) -> - | R39: =IF(N39="-", "-", IF(P39="-", "-", IF(ABS(P39)=0, "-", ROUND(100*(N39-P39)/ABS(P39), 1)))) -> - | S39: =IF(O39="-", "-", IF(Q39="-", "-", IF(ABS(Q39)=0, "-", ROUND(100*(O39-Q39)/ABS(Q39), 1)))) -> - | AB39: =IF(T39="-", "-", IF(X39="-", "-", IF(ABS(X39)=0, "-", ROUND(100*(T39-X39)/ABS(X39), 1)))) -> - | AC39: =IF(Y39="-", "-", IF(AA39="-", "-", IF(ABS(AA39)=0, "-", ROUND(100*(Y39-AA39)/ABS(AA39), 1)))) -> - | AD39: =IF(Z39="-", "-", IF(AB39="-", "-", IF(ABS(AB39)=0, "-", ROUND(100*(Z39-AB39)/ABS(AB39), 1)))) -> - | AM39: =IF(AE39="-", "-", IF(AI39="-", "-", IF(ABS(AI39)=0, "-", ROUND(100*(AE39-AI39)/ABS(AI39), 1)))) -> - | AN39: =IF(AJ39="-", "-", IF(AL39="-", "-", IF(ABS(AL39)=0, "-", ROUND(100*(AJ39-AL39)/ABS(AL39), 1)))) -> - | AO39: =IF(AK39="-", "-", IF(AM39="-", "-", IF(ABS(AM39)=0, "-", ROUND(100*(AK39-AM39)/ABS(AM39), 1)))) -> - | AU39: 普通型コンバイン | BJ39: =IF(BB39="-", "-", IF(BF39="-", "-", IF(ABS(BF39)=0, "-", ROUND(100*(BB39-BF39)/ABS(BF39), 1)))) -> - | BK39: =IF(BG39="-", "-", IF(BI39="-", "-", IF(ABS(BI39)=0, "-", ROUND(100*(BG39-BI39)/ABS(BI39), 1)))) -> - | BL39: =IF(BH39="-", "-", IF(BJ39="-", "-", IF(ABS(BJ39)=0, "-", ROUND(100*(BH39-BJ39)/ABS(BJ39), 1)))) -> - | BU39: =IF(BM39="-", "-", IF(BQ39="-", "-", IF(ABS(BQ39)=0, "-", ROUND(100*(BM39-BQ39)/ABS(BQ39), 1)))) -> - | BV39: =IF(BR39="-", "-", IF(BT39="-", "-", IF(ABS(BT39)=0, "-", ROUND(100*(BR39-BT39)/ABS(BT39), 1)))) -> - | BW39: =IF(BS39="-", "-", IF(BU39="-", "-", IF(ABS(BU39)=0, "-", ROUND(100*(BS39-BU39)/ABS(BU39), 1)))) -> -
D40: 種子用 | Q40: =IF(I40="-", "-", IF(M40="-", "-", IF(ABS(M40)=0, "-", ROUND(100*(I40-M40)/ABS(M40), 1)))) -> - | R40: =IF(N40="-", "-", IF(P40="-", "-", IF(ABS(P40)=0, "-", ROUND(100*(N40-P40)/ABS(P40), 1)))) -> - | S40: =IF(O40="-", "-", IF(Q40="-", "-", IF(ABS(Q40)=0, "-", ROUND(100*(O40-Q40)/ABS(Q40), 1)))) -> - | AB40: =IF(T40="-", "-", IF(X40="-", "-", IF(ABS(X40)=0, "-", ROUND(100*(T40-X40)/ABS(X40), 1)))) -> - | AC40: =IF(Y40="-", "-", IF(AA40="-", "-", IF(ABS(AA40)=0, "-", ROUND(100*(Y40-AA40)/ABS(AA40), 1)))) -> - | AD40: =IF(Z40="-", "-", IF(AB40="-", "-", IF(ABS(AB40)=0, "-", ROUND(100*(Z40-AB40)/ABS(AB40), 1)))) -> - | AM40: =IF(AE40="-", "-", IF(AI40="-", "-", IF(ABS(AI40)=0, "-", ROUND(100*(AE40-AI40)/ABS(AI40), 1)))) -> - | AN40: =IF(AJ40="-", "-", IF(AL40="-", "-", IF(ABS(AL40)=0, "-", ROUND(100*(AJ40-AL40)/ABS(AL40), 1)))) -> - | AO40: =IF(AK40="-", "-", IF(AM40="-", "-", IF(ABS(AM40)=0, "-", ROUND(100*(AK40-AM40)/ABS(AM40), 1)))) -> - | AU40: 調査作物収穫機 | BJ40: =IF(BB40="-", "-", IF(BF40="-", "-", IF(ABS(BF40)=0, "-", ROUND(100*(BB40-BF40)/ABS(BF40), 1)))) -> - | BK40: =IF(BG40="-", "-", IF(BI40="-", "-", IF(ABS(BI40)=0, "-", ROUND(100*(BG40-BI40)/ABS(BI40), 1)))) -> - | BL40: =IF(BH40="-", "-", IF(BJ40="-", "-", IF(ABS(BJ40)=0, "-", ROUND(100*(BH40-BJ40)/ABS(BJ40), 1)))) -> - | BU40: =IF(BM40="-", "-", IF(BQ40="-", "-", IF(ABS(BQ40)=0, "-", ROUND(100*(BM40-BQ40)/ABS(BQ40), 1)))) -> - | BV40: =IF(BR40="-", "-", IF(BT40="-", "-", IF(ABS(BT40)=0, "-", ROUND(100*(BR40-BT40)/ABS(BT40), 1)))) -> - | BW40: =IF(BS40="-", "-", IF(BU40="-", "-", IF(ABS(BU40)=0, "-", ROUND(100*(BS40-BU40)/ABS(BU40), 1)))) -> -
D41: その他 | Q41: =IF(I41="-", "-", IF(M41="-", "-", IF(ABS(M41)=0, "-", ROUND(100*(I41-M41)/ABS(M41), 1)))) -> - | R41: =IF(N41="-", "-", IF(P41="-", "-", IF(ABS(P41)=0, "-", ROUND(100*(N41-P41)/ABS(P41), 1)))) -> - | S41: =IF(O41="-", "-", IF(Q41="-", "-", IF(ABS(Q41)=0, "-", ROUND(100*(O41-Q41)/ABS(Q41), 1)))) -> - | AB41: =IF(T41="-", "-", IF(X41="-", "-", IF(ABS(X41)=0, "-", ROUND(100*(T41-X41)/ABS(X41), 1)))) -> - | AC41: =IF(Y41="-", "-", IF(AA41="-", "-", IF(ABS(AA41)=0, "-", ROUND(100*(Y41-AA41)/ABS(AA41), 1)))) -> - | AD41: =IF(Z41="-", "-", IF(AB41="-", "-", IF(ABS(AB41)=0, "-", ROUND(100*(Z41-AB41)/ABS(AB41), 1)))) -> - | AM41: =IF(AE41="-", "-", IF(AI41="-", "-", IF(ABS(AI41)=0, "-", ROUND(100*(AE41-AI41)/ABS(AI41), 1)))) -> - | AN41: =IF(AJ41="-", "-", IF(AL41="-", "-", IF(ABS(AL41)=0, "-", ROUND(100*(AJ41-AL41)/ABS(AL41), 1)))) -> - | AO41: =IF(AK41="-", "-", IF(AM41="-", "-", IF(ABS(AM41)=0, "-", ROUND(100*(AK41-AM41)/ABS(AM41), 1)))) -> - | AU41: 脱穀機 | BJ41: =IF(BB41="-", "-", IF(BF41="-", "-", IF(ABS(BF41)=0, "-", ROUND(100*(BB41-BF41)/ABS(BF41), 1)))) -> - | BK41: =IF(BG41="-", "-", IF(BI41="-", "-", IF(ABS(BI41)=0, "-", ROUND(100*(BG41-BI41)/ABS(BI41), 1)))) -> - | BL41: =IF(BH41="-", "-", IF(BJ41="-", "-", IF(ABS(BJ41)=0, "-", ROUND(100*(BH41-BJ41)/ABS(BJ41), 1)))) -> - | BU41: =IF(BM41="-", "-", IF(BQ41="-", "-", IF(ABS(BQ41)=0, "-", ROUND(100*(BM41-BQ41)/ABS(BQ41), 1)))) -> - | BV41: =IF(BR41="-", "-", IF(BT41="-", "-", IF(ABS(BT41)=0, "-", ROUND(100*(BR41-BT41)/ABS(BT41), 1)))) -> - | BW41: =IF(BS41="-", "-", IF(BU41="-", "-", IF(ABS(BU41)=0, "-", ROUND(100*(BS41-BU41)/ABS(BU41), 1)))) -> -
D42: 小計 | Q42: =IF(I42="-", "-", IF(M42="-", "-", IF(ABS(M42)=0, "-", ROUND(100*(I42-M42)/ABS(M42), 1)))) -> - | R42: =IF(N42="-", "-", IF(P42="-", "-", IF(ABS(P42)=0, "-", ROUND(100*(N42-P42)/ABS(P42), 1)))) -> - | S42: =IF(O42="-", "-", IF(Q42="-", "-", IF(ABS(Q42)=0, "-", ROUND(100*(O42-Q42)/ABS(Q42), 1)))) -> - | AB42: =IF(T42="-", "-", IF(X42="-", "-", IF(ABS(X42)=0, "-", ROUND(100*(T42-X42)/ABS(X42), 1)))) -> - | AC42: =IF(Y42="-", "-", IF(AA42="-", "-", IF(ABS(AA42)=0, "-", ROUND(100*(Y42-AA42)/ABS(AA42), 1)))) -> - | AD42: =IF(Z42="-", "-", IF(AB42="-", "-", IF(ABS(AB42)=0, "-", ROUND(100*(Z42-AB42)/ABS(AB42), 1)))) -> - | AM42: =IF(AE42="-", "-", IF(AI42="-", "-", IF(ABS(AI42)=0, "-", ROUND(100*(AE42-AI42)/ABS(AI42), 1)))) -> - | AN42: =IF(AJ42="-", "-", IF(AL42="-", "-", IF(ABS(AL42)=0, "-", ROUND(100*(AJ42-AL42)/ABS(AL42), 1)))) -> - | AO42: =IF(AK42="-", "-", IF(AM42="-", "-", IF(ABS(AM42)=0, "-", ROUND(100*(AK42-AM42)/ABS(AM42), 1)))) -> - | AU42: きび脱葉機 | BJ42: =IF(BB42="-", "-", IF(BF42="-", "-", IF(ABS(BF42)=0, "-", ROUND(100*(BB42-BF42)/ABS(BF42), 1)))) -> - | BK42: =IF(BG42="-", "-", IF(BI42="-", "-", IF(ABS(BI42)=0, "-", ROUND(100*(BG42-BI42)/ABS(BI42), 1)))) -> - | BL42: =IF(BH42="-", "-", IF(BJ42="-", "-", IF(ABS(BJ42)=0, "-", ROUND(100*(BH42-BJ42)/ABS(BJ42), 1)))) -> - | BU42: =IF(BM42="-", "-", IF(BQ42="-", "-", IF(ABS(BQ42)=0, "-", ROUND(100*(BM42-BQ42)/ABS(BQ42), 1)))) -> - | BV42: =IF(BR42="-", "-", IF(BT42="-", "-", IF(ABS(BT42)=0, "-", ROUND(100*(BR42-BT42)/ABS(BT42), 1)))) -> - | BW42: =IF(BS42="-", "-", IF(BU42="-", "-", IF(ABS(BU42)=0, "-", ROUND(100*(BS42-BU42)/ABS(BU42), 1)))) -> -
C43: 合計 | Q43: =IF(I43="-", "-", IF(M43="-", "-", IF(ABS(M43)=0, "-", ROUND(100*(I43-M43)/ABS(M43), 1)))) -> - | R43: =IF(N43="-", "-", IF(P43="-", "-", IF(ABS(P43)=0, "-", ROUND(100*(N43-P43)/ABS(P43), 1)))) -> - | S43: =IF(O43="-", "-", IF(Q43="-", "-", IF(ABS(Q43)=0, "-", ROUND(100*(O43-Q43)/ABS(Q43), 1)))) -> - | AB43: =IF(T43="-", "-", IF(X43="-", "-", IF(ABS(X43)=0, "-", ROUND(100*(T43-X43)/ABS(X43), 1)))) -> - | AC43: =IF(Y43="-", "-", IF(AA43="-", "-", IF(ABS(AA43)=0, "-", ROUND(100*(Y43-AA43)/ABS(AA43), 1)))) -> - | AD43: =IF(Z43="-", "-", IF(AB43="-", "-", IF(ABS(AB43)=0, "-", ROUND(100*(Z43-AB43)/ABS(AB43), 1)))) -> - | AM43: =IF(AE43="-", "-", IF(AI43="-", "-", IF(ABS(AI43)=0, "-", ROUND(100*(AE43-AI43)/ABS(AI43), 1)))) -> - | AN43: =IF(AJ43="-", "-", IF(AL43="-", "-", IF(ABS(AL43)=0, "-", ROUND(100*(AJ43-AL43)/ABS(AL43), 1)))) -> - | AO43: =IF(AK43="-", "-", IF(AM43="-", "-", IF(ABS(AM43)=0, "-", ROUND(100*(AK43-AM43)/ABS(AM43), 1)))) -> - | AU43: 乾燥機 | BJ43: =IF(BB43="-", "-", IF(BF43="-", "-", IF(ABS(BF43)=0, "-", ROUND(100*(BB43-BF43)/ABS(BF43), 1)))) -> - | BK43: =IF(BG43="-", "-", IF(BI43="-", "-", IF(ABS(BI43)=0, "-", ROUND(100*(BG43-BI43)/ABS(BI43), 1)))) -> - | BL43: =IF(BH43="-", "-", IF(BJ43="-", "-", IF(ABS(BJ43)=0, "-", ROUND(100*(BH43-BJ43)/ABS(BJ43), 1)))) -> - | BU43: =IF(BM43="-", "-", IF(BQ43="-", "-", IF(ABS(BQ43)=0, "-", ROUND(100*(BM43-BQ43)/ABS(BQ43), 1)))) -> - | BV43: =IF(BR43="-", "-", IF(BT43="-", "-", IF(ABS(BT43)=0, "-", ROUND(100*(BR43-BT43)/ABS(BT43), 1)))) -> - | BW43: =IF(BS43="-", "-", IF(BU43="-", "-", IF(ABS(BU43)=0, "-", ROUND(100*(BS43-BU43)/ABS(BU43), 1)))) -> -
B44: 副産物 | C44: 販売用 | Q44: =IF(I44="-", "-", IF(M44="-", "-", IF(ABS(M44)=0, "-", ROUND(100*(I44-M44)/ABS(M44), 1)))) -> - | R44: =IF(N44="-", "-", IF(P44="-", "-", IF(ABS(P44)=0, "-", ROUND(100*(N44-P44)/ABS(P44), 1)))) -> - | S44: =IF(O44="-", "-", IF(Q44="-", "-", IF(ABS(Q44)=0, "-", ROUND(100*(O44-Q44)/ABS(Q44), 1)))) -> - | AB44: =IF(T44="-", "-", IF(X44="-", "-", IF(ABS(X44)=0, "-", ROUND(100*(T44-X44)/ABS(X44), 1)))) -> - | AC44: =IF(Y44="-", "-", IF(AA44="-", "-", IF(ABS(AA44)=0, "-", ROUND(100*(Y44-AA44)/ABS(AA44), 1)))) -> - | AD44: =IF(Z44="-", "-", IF(AB44="-", "-", IF(ABS(AB44)=0, "-", ROUND(100*(Z44-AB44)/ABS(AB44), 1)))) -> - | AM44: =IF(AE44="-", "-", IF(AI44="-", "-", IF(ABS(AI44)=0, "-", ROUND(100*(AE44-AI44)/ABS(AI44), 1)))) -> - | AN44: =IF(AJ44="-", "-", IF(AL44="-", "-", IF(ABS(AL44)=0, "-", ROUND(100*(AJ44-AL44)/ABS(AL44), 1)))) -> - | AO44: =IF(AK44="-", "-", IF(AM44="-", "-", IF(ABS(AM44)=0, "-", ROUND(100*(AK44-AM44)/ABS(AM44), 1)))) -> - | AU44: トレーラー | BJ44: =IF(BB44="-", "-", IF(BF44="-", "-", IF(ABS(BF44)=0, "-", ROUND(100*(BB44-BF44)/ABS(BF44), 1)))) -> - | BK44: =IF(BG44="-", "-", IF(BI44="-", "-", IF(ABS(BI44)=0, "-", ROUND(100*(BG44-BI44)/ABS(BI44), 1)))) -> - | BL44: =IF(BH44="-", "-", IF(BJ44="-", "-", IF(ABS(BJ44)=0, "-", ROUND(100*(BH44-BJ44)/ABS(BJ44), 1)))) -> - | BU44: =IF(BM44="-", "-", IF(BQ44="-", "-", IF(ABS(BQ44)=0, "-", ROUND(100*(BM44-BQ44)/ABS(BQ44), 1)))) -> - | BV44: =IF(BR44="-", "-", IF(BT44="-", "-", IF(ABS(BT44)=0, "-", ROUND(100*(BR44-BT44)/ABS(BT44), 1)))) -> - | BW44: =IF(BS44="-", "-", IF(BU44="-", "-", IF(ABS(BU44)=0, "-", ROUND(100*(BS44-BU44)/ABS(BU44), 1)))) -> -
C45: 組織用 | Q45: =IF(I45="-", "-", IF(M45="-", "-", IF(ABS(M45)=0, "-", ROUND(100*(I45-M45)/ABS(M45), 1)))) -> - | R45: =IF(N45="-", "-", IF(P45="-", "-", IF(ABS(P45)=0, "-", ROUND(100*(N45-P45)/ABS(P45), 1)))) -> - | S45: =IF(O45="-", "-", IF(Q45="-", "-", IF(ABS(Q45)=0, "-", ROUND(100*(O45-Q45)/ABS(Q45), 1)))) -> - | AB45: =IF(T45="-", "-", IF(X45="-", "-", IF(ABS(X45)=0, "-", ROUND(100*(T45-X45)/ABS(X45), 1)))) -> - | AC45: =IF(Y45="-", "-", IF(AA45="-", "-", IF(ABS(AA45)=0, "-", ROUND(100*(Y45-AA45)/ABS(AA45), 1)))) -> - | AD45: =IF(Z45="-", "-", IF(AB45="-", "-", IF(ABS(AB45)=0, "-", ROUND(100*(Z45-AB45)/ABS(AB45), 1)))) -> - | AM45: =IF(AE45="-", "-", IF(AI45="-", "-", IF(ABS(AI45)=0, "-", ROUND(100*(AE45-AI45)/ABS(AI45), 1)))) -> - | AN45: =IF(AJ45="-", "-", IF(AL45="-", "-", IF(ABS(AL45)=0, "-", ROUND(100*(AJ45-AL45)/ABS(AL45), 1)))) -> - | AO45: =IF(AK45="-", "-", IF(AM45="-", "-", IF(ABS(AM45)=0, "-", ROUND(100*(AK45-AM45)/ABS(AM45), 1)))) -> - | AU45: その他 | BU45: =IF(BM45="-", "-", IF(BQ45="-", "-", IF(ABS(BQ45)=0, "-", ROUND(100*(BM45-BQ45)/ABS(BQ45), 1)))) -> - | BV45: =IF(BR45="-", "-", IF(BT45="-", "-", IF(ABS(BT45)=0, "-", ROUND(100*(BR45-BT45)/ABS(BT45), 1)))) -> - | BW45: =IF(BS45="-", "-", IF(BU45="-", "-", IF(ABS(BU45)=0, "-", ROUND(100*(BS45-BU45)/ABS(BU45), 1)))) -> -
C46: 計 | Q46: =IF(I46="-", "-", IF(M46="-", "-", IF(ABS(M46)=0, "-", ROUND(100*(I46-M46)/ABS(M46), 1)))) -> - | R46: =IF(N46="-", "-", IF(P46="-", "-", IF(ABS(P46)=0, "-", ROUND(100*(N46-P46)/ABS(P46), 1)))) -> - | S46: =IF(O46="-", "-", IF(Q46="-", "-", IF(ABS(Q46)=0, "-", ROUND(100*(O46-Q46)/ABS(Q46), 1)))) -> - | AB46: =IF(T46="-", "-", IF(X46="-", "-", IF(ABS(X46)=0, "-", ROUND(100*(T46-X46)/ABS(X46), 1)))) -> - | AC46: =IF(Y46="-", "-", IF(AA46="-", "-", IF(ABS(AA46)=0, "-", ROUND(100*(Y46-AA46)/ABS(AA46), 1)))) -> - | AD46: =IF(Z46="-", "-", IF(AB46="-", "-", IF(ABS(AB46)=0, "-", ROUND(100*(Z46-AB46)/ABS(AB46), 1)))) -> - | AM46: =IF(AE46="-", "-", IF(AI46="-", "-", IF(ABS(AI46)=0, "-", ROUND(100*(AE46-AI46)/ABS(AI46), 1)))) -> - | AN46: =IF(AJ46="-", "-", IF(AL46="-", "-", IF(ABS(AL46)=0, "-", ROUND(100*(AJ46-AL46)/ABS(AL46), 1)))) -> - | AO46: =IF(AK46="-", "-", IF(AM46="-", "-", IF(ABS(AM46)=0, "-", ROUND(100*(AK46-AM46)/ABS(AM46), 1)))) -> - | AU46: 計 | BU46: =IF(BM46="-", "-", IF(BQ46="-", "-", IF(ABS(BQ46)=0, "-", ROUND(100*(BM46-BQ46)/ABS(BQ46), 1)))) -> - | BV46: =IF(BR46="-", "-", IF(BT46="-", "-", IF(ABS(BT46)=0, "-", ROUND(100*(BR46-BT46)/ABS(BT46), 1)))) -> - | BW46: =IF(BS46="-", "-", IF(BU46="-", "-", IF(ABS(BU46)=0, "-", ROUND(100*(BS46-BU46)/ABS(BU46), 1)))) -> -
B47: 畑作物・なたね | I47: 数量 | T47: 価額 | AE47: 単価 | AW47: 処分差損失 | BU47: =IF(BM47="-", "-", IF(BQ47="-", "-", IF(ABS(BQ47)=0, "-", ROUND(100*(BM47-BQ47)/ABS(BQ47), 1)))) -> - | BV47: =IF(BR47="-", "-", IF(BT47="-", "-", IF(ABS(BT47)=0, "-", ROUND(100*(BR47-BT47)/ABS(BT47), 1)))) -> - | BW47: =IF(BS47="-", "-", IF(BU47="-", "-", IF(ABS(BU47)=0, "-", ROUND(100*(BS47-BU47)/ABS(BU47), 1)))) -> -
I48: =IF($B$1<>"",$B$1,"") | M48: =IF($B$1<>"",$B$1-1,"") | Q48: 増減率 | T48: =IF($B$1<>"",$B$1,"") | X48: =IF($B$1<>"",$B$1-1,"") | AB48: 増減率 | AE48: =IF($B$1<>"",$B$1,"") | AI48: =IF($B$1<>"",$B$1-1,"") | AM48: 増減率 | BM48: 調査作物負担分
B49: 主産物 | C49: 販売用 | Q49: =IF(I49="-", "-", IF(M49="-", "-", IF(ABS(M49)=0, "-", ROUND(100*(I49-M49)/ABS(M49), 1)))) -> - | R49: =IF(N49="-", "-", IF(P49="-", "-", IF(ABS(P49)=0, "-", ROUND(100*(N49-P49)/ABS(P49), 1)))) -> - | S49: =IF(O49="-", "-", IF(Q49="-", "-", IF(ABS(Q49)=0, "-", ROUND(100*(O49-Q49)/ABS(Q49), 1)))) -> - | AB49: =IF(T49="-", "-", IF(X49="-", "-", IF(ABS(X49)=0, "-", ROUND(100*(T49-X49)/ABS(X49), 1)))) -> - | AC49: =IF(Y49="-", "-", IF(AA49="-", "-", IF(ABS(AA49)=0, "-", ROUND(100*(Y49-AA49)/ABS(AA49), 1)))) -> - | AD49: =IF(Z49="-", "-", IF(AB49="-", "-", IF(ABS(AB49)=0, "-", ROUND(100*(Z49-AB49)/ABS(AB49), 1)))) -> - | AM49: =IF(AE49="-", "-", IF(AI49="-", "-", IF(ABS(AI49)=0, "-", ROUND(100*(AE49-AI49)/ABS(AI49), 1)))) -> - | AN49: =IF(AJ49="-", "-", IF(AL49="-", "-", IF(ABS(AL49)=0, "-", ROUND(100*(AJ49-AL49)/ABS(AL49), 1)))) -> - | AO49: =IF(AK49="-", "-", IF(AM49="-", "-", IF(ABS(AM49)=0, "-", ROUND(100*(AK49-AM49)/ABS(AM49), 1)))) -> - | AT49: 生産管理機器 | BU49: =IF(BM49="-", "-", IF(BQ49="-", "-", IF(ABS(BQ49)=0, "-", ROUND(100*(BM49-BQ49)/ABS(BQ49), 1)))) -> - | BV49: =IF(BR49="-", "-", IF(BT49="-", "-", IF(ABS(BT49)=0, "-", ROUND(100*(BR49-BT49)/ABS(BT49), 1)))) -> - | BW49: =IF(BS49="-", "-", IF(BU49="-", "-", IF(ABS(BU49)=0, "-", ROUND(100*(BS49-BU49)/ABS(BU49), 1)))) -> -
C50: 組織用 | D50: 食用 | Q50: =IF(I50="-", "-", IF(M50="-", "-", IF(ABS(M50)=0, "-", ROUND(100*(I50-M50)/ABS(M50), 1)))) -> - | R50: =IF(N50="-", "-", IF(P50="-", "-", IF(ABS(P50)=0, "-", ROUND(100*(N50-P50)/ABS(P50), 1)))) -> - | S50: =IF(O50="-", "-", IF(Q50="-", "-", IF(ABS(Q50)=0, "-", ROUND(100*(O50-Q50)/ABS(Q50), 1)))) -> - | AB50: =IF(T50="-", "-", IF(X50="-", "-", IF(ABS(X50)=0, "-", ROUND(100*(T50-X50)/ABS(X50), 1)))) -> - | AC50: =IF(Y50="-", "-", IF(AA50="-", "-", IF(ABS(AA50)=0, "-", ROUND(100*(Y50-AA50)/ABS(AA50), 1)))) -> - | AD50: =IF(Z50="-", "-", IF(AB50="-", "-", IF(ABS(AB50)=0, "-", ROUND(100*(Z50-AB50)/ABS(AB50), 1)))) -> - | AM50: =IF(AE50="-", "-", IF(AI50="-", "-", IF(ABS(AI50)=0, "-", ROUND(100*(AE50-AI50)/ABS(AI50), 1)))) -> - | AN50: =IF(AJ50="-", "-", IF(AL50="-", "-", IF(ABS(AL50)=0, "-", ROUND(100*(AJ50-AL50)/ABS(AL50), 1)))) -> - | AO50: =IF(AK50="-", "-", IF(AM50="-", "-", IF(ABS(AM50)=0, "-", ROUND(100*(AK50-AM50)/ABS(AM50), 1)))) -> - | AU50: 処分差損失 | BU50: =IF(BM50="-", "-", IF(BQ50="-", "-", IF(ABS(BQ50)=0, "-", ROUND(100*(BM50-BQ50)/ABS(BQ50), 1)))) -> - | BV50: =IF(BR50="-", "-", IF(BT50="-", "-", IF(ABS(BT50)=0, "-", ROUND(100*(BR50-BT50)/ABS(BT50), 1)))) -> - | BW50: =IF(BS50="-", "-", IF(BU50="-", "-", IF(ABS(BU50)=0, "-", ROUND(100*(BS50-BU50)/ABS(BU50), 1)))) -> -
D51: 種苗用 | Q51: =IF(I51="-", "-", IF(M51="-", "-", IF(ABS(M51)=0, "-", ROUND(100*(I51-M51)/ABS(M51), 1)))) -> - | R51: =IF(N51="-", "-", IF(P51="-", "-", IF(ABS(P51)=0, "-", ROUND(100*(N51-P51)/ABS(P51), 1)))) -> - | S51: =IF(O51="-", "-", IF(Q51="-", "-", IF(ABS(Q51)=0, "-", ROUND(100*(O51-Q51)/ABS(Q51), 1)))) -> - | AB51: =IF(T51="-", "-", IF(X51="-", "-", IF(ABS(X51)=0, "-", ROUND(100*(T51-X51)/ABS(X51), 1)))) -> - | AC51: =IF(Y51="-", "-", IF(AA51="-", "-", IF(ABS(AA51)=0, "-", ROUND(100*(Y51-AA51)/ABS(AA51), 1)))) -> - | AD51: =IF(Z51="-", "-", IF(AB51="-", "-", IF(ABS(AB51)=0, "-", ROUND(100*(Z51-AB51)/ABS(AB51), 1)))) -> - | AM51: =IF(AE51="-", "-", IF(AI51="-", "-", IF(ABS(AI51)=0, "-", ROUND(100*(AE51-AI51)/ABS(AI51), 1)))) -> - | AN51: =IF(AJ51="-", "-", IF(AL51="-", "-", IF(ABS(AL51)=0, "-", ROUND(100*(AJ51-AL51)/ABS(AL51), 1)))) -> - | AO51: =IF(AK51="-", "-", IF(AM51="-", "-", IF(ABS(AM51)=0, "-", ROUND(100*(AK51-AM51)/ABS(AM51), 1)))) -> -
D52: その他 | Q52: =IF(I52="-", "-", IF(M52="-", "-", IF(ABS(M52)=0, "-", ROUND(100*(I52-M52)/ABS(M52), 1)))) -> - | R52: =IF(N52="-", "-", IF(P52="-", "-", IF(ABS(P52)=0, "-", ROUND(100*(N52-P52)/ABS(P52), 1)))) -> - | S52: =IF(O52="-", "-", IF(Q52="-", "-", IF(ABS(Q52)=0, "-", ROUND(100*(O52-Q52)/ABS(Q52), 1)))) -> - | AB52: =IF(T52="-", "-", IF(X52="-", "-", IF(ABS(X52)=0, "-", ROUND(100*(T52-X52)/ABS(X52), 1)))) -> - | AC52: =IF(Y52="-", "-", IF(AA52="-", "-", IF(ABS(AA52)=0, "-", ROUND(100*(Y52-AA52)/ABS(AA52), 1)))) -> - | AD52: =IF(Z52="-", "-", IF(AB52="-", "-", IF(ABS(AB52)=0, "-", ROUND(100*(Z52-AB52)/ABS(AB52), 1)))) -> - | AM52: =IF(AE52="-", "-", IF(AI52="-", "-", IF(ABS(AI52)=0, "-", ROUND(100*(AE52-AI52)/ABS(AI52), 1)))) -> - | AN52: =IF(AJ52="-", "-", IF(AL52="-", "-", IF(ABS(AL52)=0, "-", ROUND(100*(AJ52-AL52)/ABS(AL52), 1)))) -> - | AO52: =IF(AK52="-", "-", IF(AM52="-", "-", IF(ABS(AM52)=0, "-", ROUND(100*(AK52-AM52)/ABS(AM52), 1)))) -> - | AT52: 22 二条大麦のうち、ビール麦の販売内訳 | CH52: 単位：kg、円
D53: 小計 | Q53: =IF(I53="-", "-", IF(M53="-", "-", IF(ABS(M53)=0, "-", ROUND(100*(I53-M53)/ABS(M53), 1)))) -> - | R53: =IF(N53="-", "-", IF(P53="-", "-", IF(ABS(P53)=0, "-", ROUND(100*(N53-P53)/ABS(P53), 1)))) -> - | S53: =IF(O53="-", "-", IF(Q53="-", "-", IF(ABS(Q53)=0, "-", ROUND(100*(O53-Q53)/ABS(Q53), 1)))) -> - | AB53: =IF(T53="-", "-", IF(X53="-", "-", IF(ABS(X53)=0, "-", ROUND(100*(T53-X53)/ABS(X53), 1)))) -> - | AC53: =IF(Y53="-", "-", IF(AA53="-", "-", IF(ABS(AA53)=0, "-", ROUND(100*(Y53-AA53)/ABS(AA53), 1)))) -> - | AD53: =IF(Z53="-", "-", IF(AB53="-", "-", IF(ABS(AB53)=0, "-", ROUND(100*(Z53-AB53)/ABS(AB53), 1)))) -> - | AM53: =IF(AE53="-", "-", IF(AI53="-", "-", IF(ABS(AI53)=0, "-", ROUND(100*(AE53-AI53)/ABS(AI53), 1)))) -> - | AN53: =IF(AJ53="-", "-", IF(AL53="-", "-", IF(ABS(AL53)=0, "-", ROUND(100*(AJ53-AL53)/ABS(AL53), 1)))) -> - | AO53: =IF(AK53="-", "-", IF(AM53="-", "-", IF(ABS(AM53)=0, "-", ROUND(100*(AK53-AM53)/ABS(AM53), 1)))) -> - | BB53: 数量 | BM53: 価額 | BX53: 単価
C54: 合計 | Q54: =IF(I54="-", "-", IF(M54="-", "-", IF(ABS(M54)=0, "-", ROUND(100*(I54-M54)/ABS(M54), 1)))) -> - | R54: =IF(N54="-", "-", IF(P54="-", "-", IF(ABS(P54)=0, "-", ROUND(100*(N54-P54)/ABS(P54), 1)))) -> - | S54: =IF(O54="-", "-", IF(Q54="-", "-", IF(ABS(Q54)=0, "-", ROUND(100*(O54-Q54)/ABS(Q54), 1)))) -> - | AB54: =IF(T54="-", "-", IF(X54="-", "-", IF(ABS(X54)=0, "-", ROUND(100*(T54-X54)/ABS(X54), 1)))) -> - | AC54: =IF(Y54="-", "-", IF(AA54="-", "-", IF(ABS(AA54)=0, "-", ROUND(100*(Y54-AA54)/ABS(AA54), 1)))) -> - | AD54: =IF(Z54="-", "-", IF(AB54="-", "-", IF(ABS(AB54)=0, "-", ROUND(100*(Z54-AB54)/ABS(AB54), 1)))) -> - | AM54: =IF(AE54="-", "-", IF(AI54="-", "-", IF(ABS(AI54)=0, "-", ROUND(100*(AE54-AI54)/ABS(AI54), 1)))) -> - | AN54: =IF(AJ54="-", "-", IF(AL54="-", "-", IF(ABS(AL54)=0, "-", ROUND(100*(AJ54-AL54)/ABS(AL54), 1)))) -> - | AO54: =IF(AK54="-", "-", IF(AM54="-", "-", IF(ABS(AM54)=0, "-", ROUND(100*(AK54-AM54)/ABS(AM54), 1)))) -> - | BB54: =IF($B$1<>"",$B$1,"") | BF54: =IF($B$1<>"",$B$1-1,"") | BJ54: 増減率 | BM54: =IF($B$1<>"",$B$1,"") | BQ54: =IF($B$1<>"",$B$1-1,"") | BU54: 増減率 | BX54: =IF($B$1<>"",$B$1,"") | CB54: =IF($B$1<>"",$B$1-1,"") | CF54: 増減率
B55: 副産物 | C55: 販売用 | Q55: =IF(I55="-", "-", IF(M55="-", "-", IF(ABS(M55)=0, "-", ROUND(100*(I55-M55)/ABS(M55), 1)))) -> - | R55: =IF(N55="-", "-", IF(P55="-", "-", IF(ABS(P55)=0, "-", ROUND(100*(N55-P55)/ABS(P55), 1)))) -> - | S55: =IF(O55="-", "-", IF(Q55="-", "-", IF(ABS(Q55)=0, "-", ROUND(100*(O55-Q55)/ABS(Q55), 1)))) -> - | AB55: =IF(T55="-", "-", IF(X55="-", "-", IF(ABS(X55)=0, "-", ROUND(100*(T55-X55)/ABS(X55), 1)))) -> - | AC55: =IF(Y55="-", "-", IF(AA55="-", "-", IF(ABS(AA55)=0, "-", ROUND(100*(Y55-AA55)/ABS(AA55), 1)))) -> - | AD55: =IF(Z55="-", "-", IF(AB55="-", "-", IF(ABS(AB55)=0, "-", ROUND(100*(Z55-AB55)/ABS(AB55), 1)))) -> - | AM55: =IF(AE55="-", "-", IF(AI55="-", "-", IF(ABS(AI55)=0, "-", ROUND(100*(AE55-AI55)/ABS(AI55), 1)))) -> - | AN55: =IF(AJ55="-", "-", IF(AL55="-", "-", IF(ABS(AL55)=0, "-", ROUND(100*(AJ55-AL55)/ABS(AL55), 1)))) -> - | AO55: =IF(AK55="-", "-", IF(AM55="-", "-", IF(ABS(AM55)=0, "-", ROUND(100*(AK55-AM55)/ABS(AM55), 1)))) -> - | AT55: 主産物 | AU55: 販売用 | AV55: １等 | BJ55: =IF(BB55="-", "-", IF(BF55="-", "-", IF(ABS(BF55)=0, "-", ROUND(100*(BB55-BF55)/ABS(BF55), 1)))) -> - | BK55: =IF(BG55="-", "-", IF(BI55="-", "-", IF(ABS(BI55)=0, "-", ROUND(100*(BG55-BI55)/ABS(BI55), 1)))) -> - | BL55: =IF(BH55="-", "-", IF(BJ55="-", "-", IF(ABS(BJ55)=0, "-", ROUND(100*(BH55-BJ55)/ABS(BJ55), 1)))) -> - | BU55: =IF(BM55="-", "-", IF(BQ55="-", "-", IF(ABS(BQ55)=0, "-", ROUND(100*(BM55-BQ55)/ABS(BQ55), 1)))) -> - | BV55: =IF(BR55="-", "-", IF(BT55="-", "-", IF(ABS(BT55)=0, "-", ROUND(100*(BR55-BT55)/ABS(BT55), 1)))) -> - | BW55: =IF(BS55="-", "-", IF(BU55="-", "-", IF(ABS(BU55)=0, "-", ROUND(100*(BS55-BU55)/ABS(BU55), 1)))) -> - | CF55: =IF(BX55="-", "-", IF(CB55="-", "-", IF(ABS(CB55)=0, "-", ROUND(100*(BX55-CB55)/ABS(CB55), 1)))) -> - | CG55: =IF(CC55="-", "-", IF(CE55="-", "-", IF(ABS(CE55)=0, "-", ROUND(100*(CC55-CE55)/ABS(CE55), 1)))) -> - | CH55: =IF(CD55="-", "-", IF(CF55="-", "-", IF(ABS(CF55)=0, "-", ROUND(100*(CD55-CF55)/ABS(CF55), 1)))) -> -
C56: 組織用 | Q56: =IF(I56="-", "-", IF(M56="-", "-", IF(ABS(M56)=0, "-", ROUND(100*(I56-M56)/ABS(M56), 1)))) -> - | R56: =IF(N56="-", "-", IF(P56="-", "-", IF(ABS(P56)=0, "-", ROUND(100*(N56-P56)/ABS(P56), 1)))) -> - | S56: =IF(O56="-", "-", IF(Q56="-", "-", IF(ABS(Q56)=0, "-", ROUND(100*(O56-Q56)/ABS(Q56), 1)))) -> - | AB56: =IF(T56="-", "-", IF(X56="-", "-", IF(ABS(X56)=0, "-", ROUND(100*(T56-X56)/ABS(X56), 1)))) -> - | AC56: =IF(Y56="-", "-", IF(AA56="-", "-", IF(ABS(AA56)=0, "-", ROUND(100*(Y56-AA56)/ABS(AA56), 1)))) -> - | AD56: =IF(Z56="-", "-", IF(AB56="-", "-", IF(ABS(AB56)=0, "-", ROUND(100*(Z56-AB56)/ABS(AB56), 1)))) -> - | AM56: =IF(AE56="-", "-", IF(AI56="-", "-", IF(ABS(AI56)=0, "-", ROUND(100*(AE56-AI56)/ABS(AI56), 1)))) -> - | AN56: =IF(AJ56="-", "-", IF(AL56="-", "-", IF(ABS(AL56)=0, "-", ROUND(100*(AJ56-AL56)/ABS(AL56), 1)))) -> - | AO56: =IF(AK56="-", "-", IF(AM56="-", "-", IF(ABS(AM56)=0, "-", ROUND(100*(AK56-AM56)/ABS(AM56), 1)))) -> - | AV56: ２等 | BJ56: =IF(BB56="-", "-", IF(BF56="-", "-", IF(ABS(BF56)=0, "-", ROUND(100*(BB56-BF56)/ABS(BF56), 1)))) -> - | BK56: =IF(BG56="-", "-", IF(BI56="-", "-", IF(ABS(BI56)=0, "-", ROUND(100*(BG56-BI56)/ABS(BI56), 1)))) -> - | BL56: =IF(BH56="-", "-", IF(BJ56="-", "-", IF(ABS(BJ56)=0, "-", ROUND(100*(BH56-BJ56)/ABS(BJ56), 1)))) -> - | BU56: =IF(BM56="-", "-", IF(BQ56="-", "-", IF(ABS(BQ56)=0, "-", ROUND(100*(BM56-BQ56)/ABS(BQ56), 1)))) -> - | BV56: =IF(BR56="-", "-", IF(BT56="-", "-", IF(ABS(BT56)=0, "-", ROUND(100*(BR56-BT56)/ABS(BT56), 1)))) -> - | BW56: =IF(BS56="-", "-", IF(BU56="-", "-", IF(ABS(BU56)=0, "-", ROUND(100*(BS56-BU56)/ABS(BU56), 1)))) -> - | CF56: =IF(BX56="-", "-", IF(CB56="-", "-", IF(ABS(CB56)=0, "-", ROUND(100*(BX56-CB56)/ABS(CB56), 1)))) -> - | CG56: =IF(CC56="-", "-", IF(CE56="-", "-", IF(ABS(CE56)=0, "-", ROUND(100*(CC56-CE56)/ABS(CE56), 1)))) -> - | CH56: =IF(CD56="-", "-", IF(CF56="-", "-", IF(ABS(CF56)=0, "-", ROUND(100*(CD56-CF56)/ABS(CF56), 1)))) -> -
C57: 計 | Q57: =IF(I57="-", "-", IF(M57="-", "-", IF(ABS(M57)=0, "-", ROUND(100*(I57-M57)/ABS(M57), 1)))) -> - | R57: =IF(N57="-", "-", IF(P57="-", "-", IF(ABS(P57)=0, "-", ROUND(100*(N57-P57)/ABS(P57), 1)))) -> - | S57: =IF(O57="-", "-", IF(Q57="-", "-", IF(ABS(Q57)=0, "-", ROUND(100*(O57-Q57)/ABS(Q57), 1)))) -> - | AB57: =IF(T57="-", "-", IF(X57="-", "-", IF(ABS(X57)=0, "-", ROUND(100*(T57-X57)/ABS(X57), 1)))) -> - | AC57: =IF(Y57="-", "-", IF(AA57="-", "-", IF(ABS(AA57)=0, "-", ROUND(100*(Y57-AA57)/ABS(AA57), 1)))) -> - | AD57: =IF(Z57="-", "-", IF(AB57="-", "-", IF(ABS(AB57)=0, "-", ROUND(100*(Z57-AB57)/ABS(AB57), 1)))) -> - | AM57: =IF(AE57="-", "-", IF(AI57="-", "-", IF(ABS(AI57)=0, "-", ROUND(100*(AE57-AI57)/ABS(AI57), 1)))) -> - | AN57: =IF(AJ57="-", "-", IF(AL57="-", "-", IF(ABS(AL57)=0, "-", ROUND(100*(AJ57-AL57)/ABS(AL57), 1)))) -> - | AO57: =IF(AK57="-", "-", IF(AM57="-", "-", IF(ABS(AM57)=0, "-", ROUND(100*(AK57-AM57)/ABS(AM57), 1)))) -> - | AV57: 等外上 | BJ57: =IF(BB57="-", "-", IF(BF57="-", "-", IF(ABS(BF57)=0, "-", ROUND(100*(BB57-BF57)/ABS(BF57), 1)))) -> - | BK57: =IF(BG57="-", "-", IF(BI57="-", "-", IF(ABS(BI57)=0, "-", ROUND(100*(BG57-BI57)/ABS(BI57), 1)))) -> - | BL57: =IF(BH57="-", "-", IF(BJ57="-", "-", IF(ABS(BJ57)=0, "-", ROUND(100*(BH57-BJ57)/ABS(BJ57), 1)))) -> - | BU57: =IF(BM57="-", "-", IF(BQ57="-", "-", IF(ABS(BQ57)=0, "-", ROUND(100*(BM57-BQ57)/ABS(BQ57), 1)))) -> - | BV57: =IF(BR57="-", "-", IF(BT57="-", "-", IF(ABS(BT57)=0, "-", ROUND(100*(BR57-BT57)/ABS(BT57), 1)))) -> - | BW57: =IF(BS57="-", "-", IF(BU57="-", "-", IF(ABS(BU57)=0, "-", ROUND(100*(BS57-BU57)/ABS(BU57), 1)))) -> - | CF57: =IF(BX57="-", "-", IF(CB57="-", "-", IF(ABS(CB57)=0, "-", ROUND(100*(BX57-CB57)/ABS(CB57), 1)))) -> - | CG57: =IF(CC57="-", "-", IF(CE57="-", "-", IF(ABS(CE57)=0, "-", ROUND(100*(CC57-CE57)/ABS(CE57), 1)))) -> - | CH57: =IF(CD57="-", "-", IF(CF57="-", "-", IF(ABS(CF57)=0, "-", ROUND(100*(CD57-CF57)/ABS(CF57), 1)))) -> -
AV58: 小計 | BJ58: =IF(BB58="-", "-", IF(BF58="-", "-", IF(ABS(BF58)=0, "-", ROUND(100*(BB58-BF58)/ABS(BF58), 1)))) -> - | BK58: =IF(BG58="-", "-", IF(BI58="-", "-", IF(ABS(BI58)=0, "-", ROUND(100*(BG58-BI58)/ABS(BI58), 1)))) -> - | BL58: =IF(BH58="-", "-", IF(BJ58="-", "-", IF(ABS(BJ58)=0, "-", ROUND(100*(BH58-BJ58)/ABS(BJ58), 1)))) -> - | BU58: =IF(BM58="-", "-", IF(BQ58="-", "-", IF(ABS(BQ58)=0, "-", ROUND(100*(BM58-BQ58)/ABS(BQ58), 1)))) -> - | BV58: =IF(BR58="-", "-", IF(BT58="-", "-", IF(ABS(BT58)=0, "-", ROUND(100*(BR58-BT58)/ABS(BT58), 1)))) -> - | BW58: =IF(BS58="-", "-", IF(BU58="-", "-", IF(ABS(BU58)=0, "-", ROUND(100*(BS58-BU58)/ABS(BU58), 1)))) -> - | CF58: =IF(BX58="-", "-", IF(CB58="-", "-", IF(ABS(CB58)=0, "-", ROUND(100*(BX58-CB58)/ABS(CB58), 1)))) -> - | CG58: =IF(CC58="-", "-", IF(CE58="-", "-", IF(ABS(CE58)=0, "-", ROUND(100*(CC58-CE58)/ABS(CE58), 1)))) -> - | CH58: =IF(CD58="-", "-", IF(CF58="-", "-", IF(ABS(CF58)=0, "-", ROUND(100*(CD58-CF58)/ABS(CF58), 1)))) -> -
AU59: 組織用 | AV59: 食用 | BJ59: =IF(BB59="-", "-", IF(BF59="-", "-", IF(ABS(BF59)=0, "-", ROUND(100*(BB59-BF59)/ABS(BF59), 1)))) -> - | BK59: =IF(BG59="-", "-", IF(BI59="-", "-", IF(ABS(BI59)=0, "-", ROUND(100*(BG59-BI59)/ABS(BI59), 1)))) -> - | BL59: =IF(BH59="-", "-", IF(BJ59="-", "-", IF(ABS(BJ59)=0, "-", ROUND(100*(BH59-BJ59)/ABS(BJ59), 1)))) -> - | BU59: =IF(BM59="-", "-", IF(BQ59="-", "-", IF(ABS(BQ59)=0, "-", ROUND(100*(BM59-BQ59)/ABS(BQ59), 1)))) -> - | BV59: =IF(BR59="-", "-", IF(BT59="-", "-", IF(ABS(BT59)=0, "-", ROUND(100*(BR59-BT59)/ABS(BT59), 1)))) -> - | BW59: =IF(BS59="-", "-", IF(BU59="-", "-", IF(ABS(BU59)=0, "-", ROUND(100*(BS59-BU59)/ABS(BU59), 1)))) -> - | CF59: =IF(BX59="-", "-", IF(CB59="-", "-", IF(ABS(CB59)=0, "-", ROUND(100*(BX59-CB59)/ABS(CB59), 1)))) -> - | CG59: =IF(CC59="-", "-", IF(CE59="-", "-", IF(ABS(CE59)=0, "-", ROUND(100*(CC59-CE59)/ABS(CE59), 1)))) -> - | CH59: =IF(CD59="-", "-", IF(CF59="-", "-", IF(ABS(CF59)=0, "-", ROUND(100*(CD59-CF59)/ABS(CF59), 1)))) -> -
AV60: 種子用 | BJ60: =IF(BB60="-", "-", IF(BF60="-", "-", IF(ABS(BF60)=0, "-", ROUND(100*(BB60-BF60)/ABS(BF60), 1)))) -> - | BK60: =IF(BG60="-", "-", IF(BI60="-", "-", IF(ABS(BI60)=0, "-", ROUND(100*(BG60-BI60)/ABS(BI60), 1)))) -> - | BL60: =IF(BH60="-", "-", IF(BJ60="-", "-", IF(ABS(BJ60)=0, "-", ROUND(100*(BH60-BJ60)/ABS(BJ60), 1)))) -> - | BU60: =IF(BM60="-", "-", IF(BQ60="-", "-", IF(ABS(BQ60)=0, "-", ROUND(100*(BM60-BQ60)/ABS(BQ60), 1)))) -> - | BV60: =IF(BR60="-", "-", IF(BT60="-", "-", IF(ABS(BT60)=0, "-", ROUND(100*(BR60-BT60)/ABS(BT60), 1)))) -> - | BW60: =IF(BS60="-", "-", IF(BU60="-", "-", IF(ABS(BU60)=0, "-", ROUND(100*(BS60-BU60)/ABS(BU60), 1)))) -> - | CF60: =IF(BX60="-", "-", IF(CB60="-", "-", IF(ABS(CB60)=0, "-", ROUND(100*(BX60-CB60)/ABS(CB60), 1)))) -> - | CG60: =IF(CC60="-", "-", IF(CE60="-", "-", IF(ABS(CE60)=0, "-", ROUND(100*(CC60-CE60)/ABS(CE60), 1)))) -> - | CH60: =IF(CD60="-", "-", IF(CF60="-", "-", IF(ABS(CF60)=0, "-", ROUND(100*(CD60-CF60)/ABS(CF60), 1)))) -> -
AV61: その他 | BJ61: =IF(BB61="-", "-", IF(BF61="-", "-", IF(ABS(BF61)=0, "-", ROUND(100*(BB61-BF61)/ABS(BF61), 1)))) -> - | BK61: =IF(BG61="-", "-", IF(BI61="-", "-", IF(ABS(BI61)=0, "-", ROUND(100*(BG61-BI61)/ABS(BI61), 1)))) -> - | BL61: =IF(BH61="-", "-", IF(BJ61="-", "-", IF(ABS(BJ61)=0, "-", ROUND(100*(BH61-BJ61)/ABS(BJ61), 1)))) -> - | BU61: =IF(BM61="-", "-", IF(BQ61="-", "-", IF(ABS(BQ61)=0, "-", ROUND(100*(BM61-BQ61)/ABS(BQ61), 1)))) -> - | BV61: =IF(BR61="-", "-", IF(BT61="-", "-", IF(ABS(BT61)=0, "-", ROUND(100*(BR61-BT61)/ABS(BT61), 1)))) -> - | BW61: =IF(BS61="-", "-", IF(BU61="-", "-", IF(ABS(BU61)=0, "-", ROUND(100*(BS61-BU61)/ABS(BU61), 1)))) -> - | CF61: =IF(BX61="-", "-", IF(CB61="-", "-", IF(ABS(CB61)=0, "-", ROUND(100*(BX61-CB61)/ABS(CB61), 1)))) -> - | CG61: =IF(CC61="-", "-", IF(CE61="-", "-", IF(ABS(CE61)=0, "-", ROUND(100*(CC61-CE61)/ABS(CE61), 1)))) -> - | CH61: =IF(CD61="-", "-", IF(CF61="-", "-", IF(ABS(CF61)=0, "-", ROUND(100*(CD61-CF61)/ABS(CF61), 1)))) -> -
AV62: 小計 | BJ62: =IF(BB62="-", "-", IF(BF62="-", "-", IF(ABS(BF62)=0, "-", ROUND(100*(BB62-BF62)/ABS(BF62), 1)))) -> - | BK62: =IF(BG62="-", "-", IF(BI62="-", "-", IF(ABS(BI62)=0, "-", ROUND(100*(BG62-BI62)/ABS(BI62), 1)))) -> - | BL62: =IF(BH62="-", "-", IF(BJ62="-", "-", IF(ABS(BJ62)=0, "-", ROUND(100*(BH62-BJ62)/ABS(BJ62), 1)))) -> - | BU62: =IF(BM62="-", "-", IF(BQ62="-", "-", IF(ABS(BQ62)=0, "-", ROUND(100*(BM62-BQ62)/ABS(BQ62), 1)))) -> - | BV62: =IF(BR62="-", "-", IF(BT62="-", "-", IF(ABS(BT62)=0, "-", ROUND(100*(BR62-BT62)/ABS(BT62), 1)))) -> - | BW62: =IF(BS62="-", "-", IF(BU62="-", "-", IF(ABS(BU62)=0, "-", ROUND(100*(BS62-BU62)/ABS(BU62), 1)))) -> - | CF62: =IF(BX62="-", "-", IF(CB62="-", "-", IF(ABS(CB62)=0, "-", ROUND(100*(BX62-CB62)/ABS(CB62), 1)))) -> - | CG62: =IF(CC62="-", "-", IF(CE62="-", "-", IF(ABS(CE62)=0, "-", ROUND(100*(CC62-CE62)/ABS(CE62), 1)))) -> - | CH62: =IF(CD62="-", "-", IF(CF62="-", "-", IF(ABS(CF62)=0, "-", ROUND(100*(CD62-CF62)/ABS(CF62), 1)))) -> -
AU63: 合計 | BJ63: =IF(BB63="-", "-", IF(BF63="-", "-", IF(ABS(BF63)=0, "-", ROUND(100*(BB63-BF63)/ABS(BF63), 1)))) -> - | BK63: =IF(BG63="-", "-", IF(BI63="-", "-", IF(ABS(BI63)=0, "-", ROUND(100*(BG63-BI63)/ABS(BI63), 1)))) -> - | BL63: =IF(BH63="-", "-", IF(BJ63="-", "-", IF(ABS(BJ63)=0, "-", ROUND(100*(BH63-BJ63)/ABS(BJ63), 1)))) -> - | BU63: =IF(BM63="-", "-", IF(BQ63="-", "-", IF(ABS(BQ63)=0, "-", ROUND(100*(BM63-BQ63)/ABS(BQ63), 1)))) -> - | BV63: =IF(BR63="-", "-", IF(BT63="-", "-", IF(ABS(BT63)=0, "-", ROUND(100*(BR63-BT63)/ABS(BT63), 1)))) -> - | BW63: =IF(BS63="-", "-", IF(BU63="-", "-", IF(ABS(BU63)=0, "-", ROUND(100*(BS63-BU63)/ABS(BU63), 1)))) -> - | CF63: =IF(BX63="-", "-", IF(CB63="-", "-", IF(ABS(CB63)=0, "-", ROUND(100*(BX63-CB63)/ABS(CB63), 1)))) -> - | CG63: =IF(CC63="-", "-", IF(CE63="-", "-", IF(ABS(CE63)=0, "-", ROUND(100*(CC63-CE63)/ABS(CE63), 1)))) -> - | CH63: =IF(CD63="-", "-", IF(CF63="-", "-", IF(ABS(CF63)=0, "-", ROUND(100*(CD63-CF63)/ABS(CF63), 1)))) -> -

Sheet リスト
A2: 都道府県番号 | B2: コード | D2: 生産費区分 | E2: コード | G2: 集計区分 | H2: コード | M2: なたね | P2: ビール麦販売区分 | Q2: コード | S2: 田畑区分 | T2: コード | V2: 平均値種類 | W2: コード | Y2: 加重・総和の別 | Z2: コード | AB2: てんさい栽培区分 | AC2: コード | AE2: 経営種類 | AF2: コード
A3: 全国 | B3: 0 | D3: なたね | E3: 75 | G3: 全調査対象 | H3: 1 | M3: 規模階層 | N3: コード | P3: ビール麦100％ | Q3: 1 | S3: 田畑計 | T3: 3 | V3: 通常 | W3: 0 | Y3: 加重平均 | Z3: 1 | AB3: 移植有 | AC3: 1 | AE3: 個別経営体 | AF3: 1
A4: 都府県平均 | B4: 60 | D4: そば | E4: 76 | M4: 平均 | N4: 0 | P4: ビール麦100％未満 | Q4: 2 | S4: 田 | T4: 1 | V4: 総数 | W4: 1 | Y4: 総和平均 | Z4: 2 | AB4: 移植無 | AC4: 2 | AE4: 組織法人経営体 | AF4: 2
A5: 北海道 | B5: 1 | D5: 二条大麦 | E5: 77 | M5: 1.0ha未満 | N5: 1 | P5: ビール麦無 | Q5: 3 | S5: 畑 | T5: 2 | V5: 10ａ当たり | W5: 2 | AB5: 指定しない | AC5: 3
A6: 東北 | B6: 61 | D6: 六条大麦 | E6: 78 | M6: 1.0～3.0 | N6: 2 | P6: 指定しない | Q6: 4 | S6: － | T6: 0 | V6: 単位数量当たり | W6: 3 | Z6: コード | AB6: － | AC6: 0 | AF6: コード
A7: 北陸 | B7: 62 | D7: はだか麦 | E7: 79 | M7: 3.0ha以上 | N7: 3 | P7: － | Q7: 0 | V7: １経営体当たり | W7: 4 | Z7: ="="&No.1!BF4 -> = | AF7: ="="&No.1!AL4 -> =
A8: 関東・東山 | B8: 63 | G8: 集計対象 | H8: 2 | T8: コード | AC8: コード
A9: 東海 | B9: 67 | M9: てんさい | Q9: コード | T9: ="="&No.1!BP4 -> = | W9: コード | AC9: ="="&No.1!BZ4 -> =
A10: 近畿 | B10: 68 | H10: コード | M10: 規模階層 | N10: コード | Q10: ="="&No.1!BU4 -> = | W10: ="="&No.1!BA4 -> =
A11: 中国 | B11: 71 | D11: 原料用ばれいしょ | E11: 84 | H11: ="="&No.1!BK4 -> = | M11: 平均 | N11: 0
A12: 四国 | B12: 74 | D12: さとうきび | E12: 85 | M12: 10.0ha未満 | N12: 1
A13: 九州 | B13: 75 | D13: てんさい | E13: 86 | M13: 10.0ha以上 | N13: 2
A14: 沖縄 | B14: 47 | M14: 10.0～20.0 | N14: 3
A15: 北関東 | B15: 64 | E15: コード | M15: 20.0ha以上 | N15: 4
A16: 南関東 | B16: 65 | E16: ="="&No.1!AQ4 -> = | K16: コード
A17: 東山 | B17: 66 | K17: ="="&No.1!AV4 -> = | M17: さとうきび
A18: 北東北 | B18: 69 | M18: 規模階層 | N18: コード
A19: 南東北 | B19: 70 | J19: 二条大麦・はだか麦・六条大麦 | M19: 平均 | N19: 0
A20: 山陰 | B20: 72 | J20: 規模階層 | K20: コード | M20: 5.0ha未満 | N20: 1
A21: 山陽 | B21: 73 | J21: 平均 | K21: 0 | M21: 5.0～10.0 | N21: 2
A22: 北九州 | B22: 76 | J22: 5.0ha未満 | K22: 1 | M22: 10.0ha以上 | N22: 3
A23: 南九州 | B23: 77 | J23: 5.0～10.0 | K23: 2
A24: 関東農政局 | B24: 93 | J24: 10.0ha以上 | K24: 3
A25: 東海農政局 | B25: 94
A26: 中国四国局 | B26: 95 | J26: そば
A27: 青森 | B27: 2 | J27: 規模階層 | K27: コード
A28: 岩手 | B28: 3 | J28: 平均 | K28: 0
A29: 宮城 | B29: 4 | J29: 5.0ha未満 | K29: 1
A30: 秋田 | B30: 5 | J30: 5.0～10.0 | K30: 2
A31: 山形 | B31: 6 | J31: 10.0ha以上 | K31: 3
A32: 福島 | B32: 7 | J32: 10.0～15.0 | K32: 4
A33: 茨城 | B33: 8 | J33: 15.0ha以上 | K33: 5
A34: 栃木 | B34: 9 | J34: 15.0～20.0 | K34: 6
A35: 群馬 | B35: 10 | J35: 20.0ha以上 | K35: 7
A36: 埼玉 | B36: 11
A37: 千葉 | B37: 12 | J37: 原料用ばれいしょ
A38: 東京 | B38: 13 | J38: 規模階層 | K38: コード
A39: 神奈川 | B39: 14 | J39: 平均 | K39: 0
A40: 新潟 | B40: 15 | J40: 5.0ha未満 | K40: 1
A41: 富山 | B41: 16 | J41: 5.0～15.0 | K41: 2
A42: 石川 | B42: 17 | J42: 15.0ha以上 | K42: 3
A43: 福井 | B43: 18
A44: 山梨 | B44: 19
A45: 長野 | B45: 20
A46: 岐阜 | B46: 21
A47: 静岡 | B47: 22
A48: 愛知 | B48: 23
A49: 三重 | B49: 24
A50: 滋賀 | B50: 25 | J50: 原料用ばれいしょ
A51: 京都 | B51: 26 | J51: 規模階層 | K51: コード
A52: 大阪 | B52: 27 | J52: 3.0ha未満 | K52: 1
A53: 兵庫 | B53: 28 | J53: 3.0～5.0 | K53: 2
A54: 奈良 | B54: 29 | J54: 5.0～7.0 | K54: 3
A55: 和歌山 | B55: 30 | J55: 7.0～10.0 | K55: 4
A56: 鳥取 | B56: 31 | J56: 10.0ha以上 | K56: 5
A57: 島根 | B57: 32
A58: 岡山 | B58: 33
A59: 広島 | B59: 34
A60: 山口 | B60: 35
A61: 徳島 | B61: 36
A62: 香川 | B62: 37
A63: 愛媛 | B63: 38
A64: 高知 | B64: 39
A65: 福岡 | B65: 40
A66: 佐賀 | B66: 41
A67: 長崎 | B67: 42
A68: 熊本 | B68: 43
... A71: 鹿児島 | B71: 46
B73: コード
B74: ="="&No.1!AG4 -> =
