Workbook
Name 経費範囲: #REF!
Name 現場調査費: #REF!
Name 現調単価: #REF!
Name 合計: #REF!
Name 材料範囲: #REF!
Name 諸経費率: #REF!
Name 範囲: #REF!
Name 労務範囲: #REF!

Sheet No.1
B1: =AB4 -> 0 | E1: 年産 米生産費統計結果（組織法人経営体） 集計結果検討表 Ｎｏ．１
G3: 集計番号 | J3: 集計名称 | Q3: 集計経営体数 | V3: 集計倍率 | AB3: 調査年 | AG3: 都道府県等 | AL3: 経営種類 | AQ3: 生産費区分 | AV3: 規模階層 | BA3: 平均値種類 | BF3: 加重・総和の別 | BK3: 集計区分
B4: 本年産 | AH4: =IF(AG4<>"",DGET(リスト!A2:B71,"都道府県番号",リスト!B73:B74),"") | AM4: =IF(AL4>0,DGET(リスト!S2:T4,"経営種類",リスト!T6:T7),"") | AR4: =IF(AQ4>0,DGET(リスト!D2:E13,"生産費区分",リスト!E15:E16),"") | AW4: =IF(AV4<>"",DGET(リスト!J3:K17,"規模階層",リスト!K19:K20),"") | BB4: =IF(BA4<>"",DGET(リスト!M2:N7,"平均値種類",リスト!N9:N10),"") | BG4: =IF(BF4>0,DGET(リスト!P2:Q4,"加重・総和の別",リスト!Q6:Q7),"") | BL4: =IF(BK4>0,DGET(リスト!G2:H7,"集計区分",リスト!H9:H10),"")
B5: 前年産
B7: １ 生産費総括 | AZ7: 単位：円 | BE7: ４ 調査作物収入 | CG7: 単位：円、kg
I8: 購入 | T8: 自給 | AE8: 償却 | AP8: 計 | BL8: 数量 | BW8: 価額
I9: =IF($B$1<>"",$B$1,"") -> 0 | M9: =IF($B$1<>"",$B$1-1,"") -> -1 | Q9: 増減率 | T9: =IF($B$1<>"",$B$1,"") -> 0 | X9: =IF($B$1<>"",$B$1-1,"") -> -1 | AB9: 増減率 | AE9: =IF($B$1<>"",$B$1,"") -> 0 | AI9: =IF($B$1<>"",$B$1-1,"") -> -1 | AM9: 増減率 | AP9: =IF($B$1<>"",$B$1,"") -> 0 | AT9: =IF($B$1<>"",$B$1-1,"") -> -1 | AX9: 増減率 | BL9: =IF($B$1<>"",$B$1,"") -> 0 | BP9: =IF($B$1<>"",$B$1-1,"") -> -1 | BT9: 増減率 | BW9: =IF($B$1<>"",$B$1,"") -> 0 | CA9: =IF($B$1<>"",$B$1-1,"") -> -1 | CE9: 増減率
B10: 物財費 | Q10: =IF(I10="-", "-", IF(M10="-", "-", IF(ABS(M10)=0, "-", ROUND(100*(I10-M10)/ABS(M10), 10)))) -> - | R10: =IF(N10="-", "-", IF(P10="-", "-", IF(ABS(P10)=0, "-", ROUND(100*(N10-P10)/ABS(P10), 1)))) -> - | S10: =IF(O10="-", "-", IF(Q10="-", "-", IF(ABS(Q10)=0, "-", ROUND(100*(O10-Q10)/ABS(Q10), 1)))) -> - | AB10: =IF(T10="-", "-", IF(X10="-", "-", IF(ABS(X10)=0, "-", ROUND(100*(T10-X10)/ABS(X10), 10)))) -> - | AC10: =IF(Y10="-", "-", IF(AA10="-", "-", IF(ABS(AA10)=0, "-", ROUND(100*(Y10-AA10)/ABS(AA10), 1)))) -> - | AD10: =IF(Z10="-", "-", IF(AB10="-", "-", IF(ABS(AB10)=0, "-", ROUND(100*(Z10-AB10)/ABS(AB10), 1)))) -> - | AM10: =IF(AE10="-", "-", IF(AI10="-", "-", IF(ABS(AI10)=0, "-", ROUND(100*(AE10-AI10)/ABS(AI10), 10)))) -> - | AN10: =IF(AJ10="-", "-", IF(AL10="-", "-", IF(ABS(AL10)=0, "-", ROUND(100*(AJ10-AL10)/ABS(AL10), 1)))) -> - | AO10: =IF(AK10="-", "-", IF(AM10="-", "-", IF(ABS(AM10)=0, "-", ROUND(100*(AK10-AM10)/ABS(AM10), 1)))) -> - | AX10: =IF(AP10="-", "-", IF(AT10="-", "-", IF(ABS(AT10)=0, "-", ROUND(100*(AP10-AT10)/ABS(AT10), 10)))) -> - | AY10: =IF(AU10="-", "-", IF(AW10="-", "-", IF(ABS(AW10)=0, "-", ROUND(100*(AU10-AW10)/ABS(AW10), 1)))) -> - | AZ10: =IF(AV10="-", "-", IF(AX10="-", "-", IF(ABS(AX10)=0, "-", ROUND(100*(AV10-AX10)/ABS(AX10), 1)))) -> - | BE10: 主産物 | BF10: 販売用 | BT10: =IF(BL10="-", "-", IF(BP10="-", "-", IF(ABS(BP10)=0, "-", ROUND(100*(BL10-BP10)/ABS(BP10), 10)))) -> - | BU10: =IF(BQ10="-", "-", IF(BS10="-", "-", IF(ABS(BS10)=0, "-", ROUND(100*(BQ10-BS10)/ABS(BS10), 1)))) -> - | BV10: =IF(BR10="-", "-", IF(BT10="-", "-", IF(ABS(BT10)=0, "-", ROUND(100*(BR10-BT10)/ABS(BT10), 1)))) -> - | CE10: =IF(BW10="-", "-", IF(CA10="-", "-", IF(ABS(CA10)=0, "-", ROUND(100*(BW10-CA10)/ABS(CA10), 10)))) -> - | CF10: =IF(CB10="-", "-", IF(CD10="-", "-", IF(ABS(CD10)=0, "-", ROUND(100*(CB10-CD10)/ABS(CD10), 1)))) -> - | CG10: =IF(CC10="-", "-", IF(CE10="-", "-", IF(ABS(CE10)=0, "-", ROUND(100*(CC10-CE10)/ABS(CE10), 1)))) -> -
C11: 種苗費 | Q11: =IF(I11="-", "-", IF(M11="-", "-", IF(ABS(M11)=0, "-", ROUND(100*(I11-M11)/ABS(M11), 10)))) -> - | R11: =IF(N11="-", "-", IF(P11="-", "-", IF(ABS(P11)=0, "-", ROUND(100*(N11-P11)/ABS(P11), 1)))) -> - | S11: =IF(O11="-", "-", IF(Q11="-", "-", IF(ABS(Q11)=0, "-", ROUND(100*(O11-Q11)/ABS(Q11), 1)))) -> - | AB11: =IF(T11="-", "-", IF(X11="-", "-", IF(ABS(X11)=0, "-", ROUND(100*(T11-X11)/ABS(X11), 10)))) -> - | AC11: =IF(Y11="-", "-", IF(AA11="-", "-", IF(ABS(AA11)=0, "-", ROUND(100*(Y11-AA11)/ABS(AA11), 1)))) -> - | AD11: =IF(Z11="-", "-", IF(AB11="-", "-", IF(ABS(AB11)=0, "-", ROUND(100*(Z11-AB11)/ABS(AB11), 1)))) -> - | AX11: =IF(AP11="-", "-", IF(AT11="-", "-", IF(ABS(AT11)=0, "-", ROUND(100*(AP11-AT11)/ABS(AT11), 10)))) -> - | AY11: =IF(AU11="-", "-", IF(AW11="-", "-", IF(ABS(AW11)=0, "-", ROUND(100*(AU11-AW11)/ABS(AW11), 1)))) -> - | AZ11: =IF(AV11="-", "-", IF(AX11="-", "-", IF(ABS(AX11)=0, "-", ROUND(100*(AV11-AX11)/ABS(AX11), 1)))) -> - | BF11: 組織用 | BT11: =IF(BL11="-", "-", IF(BP11="-", "-", IF(ABS(BP11)=0, "-", ROUND(100*(BL11-BP11)/ABS(BP11), 10)))) -> - | BU11: =IF(BQ11="-", "-", IF(BS11="-", "-", IF(ABS(BS11)=0, "-", ROUND(100*(BQ11-BS11)/ABS(BS11), 1)))) -> - | BV11: =IF(BR11="-", "-", IF(BT11="-", "-", IF(ABS(BT11)=0, "-", ROUND(100*(BR11-BT11)/ABS(BT11), 1)))) -> - | CE11: =IF(BW11="-", "-", IF(CA11="-", "-", IF(ABS(CA11)=0, "-", ROUND(100*(BW11-CA11)/ABS(CA11), 10)))) -> - | CF11: =IF(CB11="-", "-", IF(CD11="-", "-", IF(ABS(CD11)=0, "-", ROUND(100*(CB11-CD11)/ABS(CD11), 1)))) -> - | CG11: =IF(CC11="-", "-", IF(CE11="-", "-", IF(ABS(CE11)=0, "-", ROUND(100*(CC11-CE11)/ABS(CE11), 1)))) -> -
C12: 肥料費 | Q12: =IF(I12="-", "-", IF(M12="-", "-", IF(ABS(M12)=0, "-", ROUND(100*(I12-M12)/ABS(M12), 10)))) -> - | R12: =IF(N12="-", "-", IF(P12="-", "-", IF(ABS(P12)=0, "-", ROUND(100*(N12-P12)/ABS(P12), 1)))) -> - | S12: =IF(O12="-", "-", IF(Q12="-", "-", IF(ABS(Q12)=0, "-", ROUND(100*(O12-Q12)/ABS(Q12), 1)))) -> - | AB12: =IF(T12="-", "-", IF(X12="-", "-", IF(ABS(X12)=0, "-", ROUND(100*(T12-X12)/ABS(X12), 10)))) -> - | AC12: =IF(Y12="-", "-", IF(AA12="-", "-", IF(ABS(AA12)=0, "-", ROUND(100*(Y12-AA12)/ABS(AA12), 1)))) -> - | AD12: =IF(Z12="-", "-", IF(AB12="-", "-", IF(ABS(AB12)=0, "-", ROUND(100*(Z12-AB12)/ABS(AB12), 1)))) -> - | AX12: =IF(AP12="-", "-", IF(AT12="-", "-", IF(ABS(AT12)=0, "-", ROUND(100*(AP12-AT12)/ABS(AT12), 10)))) -> - | AY12: =IF(AU12="-", "-", IF(AW12="-", "-", IF(ABS(AW12)=0, "-", ROUND(100*(AU12-AW12)/ABS(AW12), 1)))) -> - | AZ12: =IF(AV12="-", "-", IF(AX12="-", "-", IF(ABS(AX12)=0, "-", ROUND(100*(AV12-AX12)/ABS(AX12), 1)))) -> - | BF12: 計 | BT12: =IF(BL12="-", "-", IF(BP12="-", "-", IF(ABS(BP12)=0, "-", ROUND(100*(BL12-BP12)/ABS(BP12), 10)))) -> - | BU12: =IF(BQ12="-", "-", IF(BS12="-", "-", IF(ABS(BS12)=0, "-", ROUND(100*(BQ12-BS12)/ABS(BS12), 1)))) -> - | BV12: =IF(BR12="-", "-", IF(BT12="-", "-", IF(ABS(BT12)=0, "-", ROUND(100*(BR12-BT12)/ABS(BT12), 1)))) -> - | CE12: =IF(BW12="-", "-", IF(CA12="-", "-", IF(ABS(CA12)=0, "-", ROUND(100*(BW12-CA12)/ABS(CA12), 10)))) -> - | CF12: =IF(CB12="-", "-", IF(CD12="-", "-", IF(ABS(CD12)=0, "-", ROUND(100*(CB12-CD12)/ABS(CD12), 1)))) -> - | CG12: =IF(CC12="-", "-", IF(CE12="-", "-", IF(ABS(CE12)=0, "-", ROUND(100*(CC12-CE12)/ABS(CE12), 1)))) -> -
C13: 農業薬剤費 | Q13: =IF(I13="-", "-", IF(M13="-", "-", IF(ABS(M13)=0, "-", ROUND(100*(I13-M13)/ABS(M13), 10)))) -> - | R13: =IF(N13="-", "-", IF(P13="-", "-", IF(ABS(P13)=0, "-", ROUND(100*(N13-P13)/ABS(P13), 1)))) -> - | S13: =IF(O13="-", "-", IF(Q13="-", "-", IF(ABS(Q13)=0, "-", ROUND(100*(O13-Q13)/ABS(Q13), 1)))) -> - | AX13: =IF(AP13="-", "-", IF(AT13="-", "-", IF(ABS(AT13)=0, "-", ROUND(100*(AP13-AT13)/ABS(AT13), 10)))) -> - | AY13: =IF(AU13="-", "-", IF(AW13="-", "-", IF(ABS(AW13)=0, "-", ROUND(100*(AU13-AW13)/ABS(AW13), 1)))) -> - | AZ13: =IF(AV13="-", "-", IF(AX13="-", "-", IF(ABS(AX13)=0, "-", ROUND(100*(AV13-AX13)/ABS(AX13), 1)))) -> - | BE13: 副産物 | BF13: くず米 | BT13: =IF(BL13="-", "-", IF(BP13="-", "-", IF(ABS(BP13)=0, "-", ROUND(100*(BL13-BP13)/ABS(BP13), 10)))) -> - | BU13: =IF(BQ13="-", "-", IF(BS13="-", "-", IF(ABS(BS13)=0, "-", ROUND(100*(BQ13-BS13)/ABS(BS13), 1)))) -> - | BV13: =IF(BR13="-", "-", IF(BT13="-", "-", IF(ABS(BT13)=0, "-", ROUND(100*(BR13-BT13)/ABS(BT13), 1)))) -> - | CE13: =IF(BW13="-", "-", IF(CA13="-", "-", IF(ABS(CA13)=0, "-", ROUND(100*(BW13-CA13)/ABS(CA13), 10)))) -> - | CF13: =IF(CB13="-", "-", IF(CD13="-", "-", IF(ABS(CD13)=0, "-", ROUND(100*(CB13-CD13)/ABS(CD13), 1)))) -> - | CG13: =IF(CC13="-", "-", IF(CE13="-", "-", IF(ABS(CE13)=0, "-", ROUND(100*(CC13-CE13)/ABS(CE13), 1)))) -> -
C14: 光熱動力費 | Q14: =IF(I14="-", "-", IF(M14="-", "-", IF(ABS(M14)=0, "-", ROUND(100*(I14-M14)/ABS(M14), 10)))) -> - | R14: =IF(N14="-", "-", IF(P14="-", "-", IF(ABS(P14)=0, "-", ROUND(100*(N14-P14)/ABS(P14), 1)))) -> - | S14: =IF(O14="-", "-", IF(Q14="-", "-", IF(ABS(Q14)=0, "-", ROUND(100*(O14-Q14)/ABS(Q14), 1)))) -> - | AB14: =IF(T14="-", "-", IF(X14="-", "-", IF(ABS(X14)=0, "-", ROUND(100*(T14-X14)/ABS(X14), 10)))) -> - | AC14: =IF(Y14="-", "-", IF(AA14="-", "-", IF(ABS(AA14)=0, "-", ROUND(100*(Y14-AA14)/ABS(AA14), 1)))) -> - | AD14: =IF(Z14="-", "-", IF(AB14="-", "-", IF(ABS(AB14)=0, "-", ROUND(100*(Z14-AB14)/ABS(AB14), 1)))) -> - | AX14: =IF(AP14="-", "-", IF(AT14="-", "-", IF(ABS(AT14)=0, "-", ROUND(100*(AP14-AT14)/ABS(AT14), 10)))) -> - | AY14: =IF(AU14="-", "-", IF(AW14="-", "-", IF(ABS(AW14)=0, "-", ROUND(100*(AU14-AW14)/ABS(AW14), 1)))) -> - | AZ14: =IF(AV14="-", "-", IF(AX14="-", "-", IF(ABS(AX14)=0, "-", ROUND(100*(AV14-AX14)/ABS(AX14), 1)))) -> - | BF14: 稲わら(もみがら含む) | BT14: =IF(BL14="-", "-", IF(BP14="-", "-", IF(ABS(BP14)=0, "-", ROUND(100*(BL14-BP14)/ABS(BP14), 10)))) -> - | BU14: =IF(BQ14="-", "-", IF(BS14="-", "-", IF(ABS(BS14)=0, "-", ROUND(100*(BQ14-BS14)/ABS(BS14), 1)))) -> - | BV14: =IF(BR14="-", "-", IF(BT14="-", "-", IF(ABS(BT14)=0, "-", ROUND(100*(BR14-BT14)/ABS(BT14), 1)))) -> - | CE14: =IF(BW14="-", "-", IF(CA14="-", "-", IF(ABS(CA14)=0, "-", ROUND(100*(BW14-CA14)/ABS(CA14), 10)))) -> - | CF14: =IF(CB14="-", "-", IF(CD14="-", "-", IF(ABS(CD14)=0, "-", ROUND(100*(CB14-CD14)/ABS(CD14), 1)))) -> - | CG14: =IF(CC14="-", "-", IF(CE14="-", "-", IF(ABS(CE14)=0, "-", ROUND(100*(CC14-CE14)/ABS(CE14), 1)))) -> -
C15: その他の諸材料費 | Q15: =IF(I15="-", "-", IF(M15="-", "-", IF(ABS(M15)=0, "-", ROUND(100*(I15-M15)/ABS(M15), 10)))) -> - | R15: =IF(N15="-", "-", IF(P15="-", "-", IF(ABS(P15)=0, "-", ROUND(100*(N15-P15)/ABS(P15), 1)))) -> - | S15: =IF(O15="-", "-", IF(Q15="-", "-", IF(ABS(Q15)=0, "-", ROUND(100*(O15-Q15)/ABS(Q15), 1)))) -> - | AB15: =IF(T15="-", "-", IF(X15="-", "-", IF(ABS(X15)=0, "-", ROUND(100*(T15-X15)/ABS(X15), 10)))) -> - | AC15: =IF(Y15="-", "-", IF(AA15="-", "-", IF(ABS(AA15)=0, "-", ROUND(100*(Y15-AA15)/ABS(AA15), 1)))) -> - | AD15: =IF(Z15="-", "-", IF(AB15="-", "-", IF(ABS(AB15)=0, "-", ROUND(100*(Z15-AB15)/ABS(AB15), 1)))) -> - | AX15: =IF(AP15="-", "-", IF(AT15="-", "-", IF(ABS(AT15)=0, "-", ROUND(100*(AP15-AT15)/ABS(AT15), 10)))) -> - | AY15: =IF(AU15="-", "-", IF(AW15="-", "-", IF(ABS(AW15)=0, "-", ROUND(100*(AU15-AW15)/ABS(AW15), 1)))) -> - | AZ15: =IF(AV15="-", "-", IF(AX15="-", "-", IF(ABS(AX15)=0, "-", ROUND(100*(AV15-AX15)/ABS(AX15), 1)))) -> - | BF15: 計 | CE15: =IF(BW15="-", "-", IF(CA15="-", "-", IF(ABS(CA15)=0, "-", ROUND(100*(BW15-CA15)/ABS(CA15), 10)))) -> - | CF15: =IF(CB15="-", "-", IF(CD15="-", "-", IF(ABS(CD15)=0, "-", ROUND(100*(CB15-CD15)/ABS(CD15), 1)))) -> - | CG15: =IF(CC15="-", "-", IF(CE15="-", "-", IF(ABS(CE15)=0, "-", ROUND(100*(CC15-CE15)/ABS(CE15), 1)))) -> -
C16: 土地改良及び水利費 | Q16: =IF(I16="-", "-", IF(M16="-", "-", IF(ABS(M16)=0, "-", ROUND(100*(I16-M16)/ABS(M16), 10)))) -> - | R16: =IF(N16="-", "-", IF(P16="-", "-", IF(ABS(P16)=0, "-", ROUND(100*(N16-P16)/ABS(P16), 1)))) -> - | S16: =IF(O16="-", "-", IF(Q16="-", "-", IF(ABS(Q16)=0, "-", ROUND(100*(O16-Q16)/ABS(Q16), 1)))) -> - | AX16: =IF(AP16="-", "-", IF(AT16="-", "-", IF(ABS(AT16)=0, "-", ROUND(100*(AP16-AT16)/ABS(AT16), 10)))) -> - | AY16: =IF(AU16="-", "-", IF(AW16="-", "-", IF(ABS(AW16)=0, "-", ROUND(100*(AU16-AW16)/ABS(AW16), 1)))) -> - | AZ16: =IF(AV16="-", "-", IF(AX16="-", "-", IF(ABS(AX16)=0, "-", ROUND(100*(AV16-AX16)/ABS(AX16), 1)))) -> - | BE16: 粗収益 | CE16: =IF(BW16="-", "-", IF(CA16="-", "-", IF(ABS(CA16)=0, "-", ROUND(100*(BW16-CA16)/ABS(CA16), 10)))) -> - | CF16: =IF(CB16="-", "-", IF(CD16="-", "-", IF(ABS(CD16)=0, "-", ROUND(100*(CB16-CD16)/ABS(CD16), 1)))) -> - | CG16: =IF(CC16="-", "-", IF(CE16="-", "-", IF(ABS(CE16)=0, "-", ROUND(100*(CC16-CE16)/ABS(CE16), 1)))) -> -
C17: 賃借料及び料金 | Q17: =IF(I17="-", "-", IF(M17="-", "-", IF(ABS(M17)=0, "-", ROUND(100*(I17-M17)/ABS(M17), 10)))) -> - | R17: =IF(N17="-", "-", IF(P17="-", "-", IF(ABS(P17)=0, "-", ROUND(100*(N17-P17)/ABS(P17), 1)))) -> - | S17: =IF(O17="-", "-", IF(Q17="-", "-", IF(ABS(Q17)=0, "-", ROUND(100*(O17-Q17)/ABS(Q17), 1)))) -> - | AX17: =IF(AP17="-", "-", IF(AT17="-", "-", IF(ABS(AT17)=0, "-", ROUND(100*(AP17-AT17)/ABS(AT17), 10)))) -> - | AY17: =IF(AU17="-", "-", IF(AW17="-", "-", IF(ABS(AW17)=0, "-", ROUND(100*(AU17-AW17)/ABS(AW17), 1)))) -> - | AZ17: =IF(AV17="-", "-", IF(AX17="-", "-", IF(ABS(AX17)=0, "-", ROUND(100*(AV17-AX17)/ABS(AX17), 1)))) -> -
C18: 物件税及び公課諸負担 | Q18: =IF(I18="-", "-", IF(M18="-", "-", IF(ABS(M18)=0, "-", ROUND(100*(I18-M18)/ABS(M18), 10)))) -> - | R18: =IF(N18="-", "-", IF(P18="-", "-", IF(ABS(P18)=0, "-", ROUND(100*(N18-P18)/ABS(P18), 1)))) -> - | S18: =IF(O18="-", "-", IF(Q18="-", "-", IF(ABS(Q18)=0, "-", ROUND(100*(O18-Q18)/ABS(Q18), 1)))) -> - | AX18: =IF(AP18="-", "-", IF(AT18="-", "-", IF(ABS(AT18)=0, "-", ROUND(100*(AP18-AT18)/ABS(AT18), 10)))) -> - | AY18: =IF(AU18="-", "-", IF(AW18="-", "-", IF(ABS(AW18)=0, "-", ROUND(100*(AU18-AW18)/ABS(AW18), 1)))) -> - | AZ18: =IF(AV18="-", "-", IF(AX18="-", "-", IF(ABS(AX18)=0, "-", ROUND(100*(AV18-AX18)/ABS(AX18), 1)))) -> -
C19: 建物費 | Q19: =IF(I19="-", "-", IF(M19="-", "-", IF(ABS(M19)=0, "-", ROUND(100*(I19-M19)/ABS(M19), 10)))) -> - | R19: =IF(N19="-", "-", IF(P19="-", "-", IF(ABS(P19)=0, "-", ROUND(100*(N19-P19)/ABS(P19), 1)))) -> - | S19: =IF(O19="-", "-", IF(Q19="-", "-", IF(ABS(Q19)=0, "-", ROUND(100*(O19-Q19)/ABS(Q19), 1)))) -> - | AM19: =IF(AE19="-", "-", IF(AI19="-", "-", IF(ABS(AI19)=0, "-", ROUND(100*(AE19-AI19)/ABS(AI19), 10)))) -> - | AN19: =IF(AJ19="-", "-", IF(AL19="-", "-", IF(ABS(AL19)=0, "-", ROUND(100*(AJ19-AL19)/ABS(AL19), 1)))) -> - | AO19: =IF(AK19="-", "-", IF(AM19="-", "-", IF(ABS(AM19)=0, "-", ROUND(100*(AK19-AM19)/ABS(AM19), 1)))) -> - | AX19: =IF(AP19="-", "-", IF(AT19="-", "-", IF(ABS(AT19)=0, "-", ROUND(100*(AP19-AT19)/ABS(AT19), 10)))) -> - | AY19: =IF(AU19="-", "-", IF(AW19="-", "-", IF(ABS(AW19)=0, "-", ROUND(100*(AU19-AW19)/ABS(AW19), 1)))) -> - | AZ19: =IF(AV19="-", "-", IF(AX19="-", "-", IF(ABS(AX19)=0, "-", ROUND(100*(AV19-AX19)/ABS(AX19), 1)))) -> -
C20: 自動車費 | Q20: =IF(I20="-", "-", IF(M20="-", "-", IF(ABS(M20)=0, "-", ROUND(100*(I20-M20)/ABS(M20), 10)))) -> - | R20: =IF(N20="-", "-", IF(P20="-", "-", IF(ABS(P20)=0, "-", ROUND(100*(N20-P20)/ABS(P20), 1)))) -> - | S20: =IF(O20="-", "-", IF(Q20="-", "-", IF(ABS(Q20)=0, "-", ROUND(100*(O20-Q20)/ABS(Q20), 1)))) -> - | AM20: =IF(AE20="-", "-", IF(AI20="-", "-", IF(ABS(AI20)=0, "-", ROUND(100*(AE20-AI20)/ABS(AI20), 10)))) -> - | AN20: =IF(AJ20="-", "-", IF(AL20="-", "-", IF(ABS(AL20)=0, "-", ROUND(100*(AJ20-AL20)/ABS(AL20), 1)))) -> - | AO20: =IF(AK20="-", "-", IF(AM20="-", "-", IF(ABS(AM20)=0, "-", ROUND(100*(AK20-AM20)/ABS(AM20), 1)))) -> - | AX20: =IF(AP20="-", "-", IF(AT20="-", "-", IF(ABS(AT20)=0, "-", ROUND(100*(AP20-AT20)/ABS(AT20), 10)))) -> - | AY20: =IF(AU20="-", "-", IF(AW20="-", "-", IF(ABS(AW20)=0, "-", ROUND(100*(AU20-AW20)/ABS(AW20), 1)))) -> - | AZ20: =IF(AV20="-", "-", IF(AX20="-", "-", IF(ABS(AX20)=0, "-", ROUND(100*(AV20-AX20)/ABS(AX20), 1)))) -> -
C21: 農機具費 | Q21: =IF(I21="-", "-", IF(M21="-", "-", IF(ABS(M21)=0, "-", ROUND(100*(I21-M21)/ABS(M21), 10)))) -> - | R21: =IF(N21="-", "-", IF(P21="-", "-", IF(ABS(P21)=0, "-", ROUND(100*(N21-P21)/ABS(P21), 1)))) -> - | S21: =IF(O21="-", "-", IF(Q21="-", "-", IF(ABS(Q21)=0, "-", ROUND(100*(O21-Q21)/ABS(Q21), 1)))) -> - | AM21: =IF(AE21="-", "-", IF(AI21="-", "-", IF(ABS(AI21)=0, "-", ROUND(100*(AE21-AI21)/ABS(AI21), 10)))) -> - | AN21: =IF(AJ21="-", "-", IF(AL21="-", "-", IF(ABS(AL21)=0, "-", ROUND(100*(AJ21-AL21)/ABS(AL21), 1)))) -> - | AO21: =IF(AK21="-", "-", IF(AM21="-", "-", IF(ABS(AM21)=0, "-", ROUND(100*(AK21-AM21)/ABS(AM21), 1)))) -> - | AX21: =IF(AP21="-", "-", IF(AT21="-", "-", IF(ABS(AT21)=0, "-", ROUND(100*(AP21-AT21)/ABS(AT21), 10)))) -> - | AY21: =IF(AU21="-", "-", IF(AW21="-", "-", IF(ABS(AW21)=0, "-", ROUND(100*(AU21-AW21)/ABS(AW21), 1)))) -> - | AZ21: =IF(AV21="-", "-", IF(AX21="-", "-", IF(ABS(AX21)=0, "-", ROUND(100*(AV21-AX21)/ABS(AX21), 1)))) -> - | BE21: ５ 収益性 | BV21: 単位：円
C22: 生産管理費 | Q22: =IF(I22="-", "-", IF(M22="-", "-", IF(ABS(M22)=0, "-", ROUND(100*(I22-M22)/ABS(M22), 10)))) -> - | R22: =IF(N22="-", "-", IF(P22="-", "-", IF(ABS(P22)=0, "-", ROUND(100*(N22-P22)/ABS(P22), 1)))) -> - | S22: =IF(O22="-", "-", IF(Q22="-", "-", IF(ABS(Q22)=0, "-", ROUND(100*(O22-Q22)/ABS(Q22), 1)))) -> - | AM22: =IF(AE22="-", "-", IF(AI22="-", "-", IF(ABS(AI22)=0, "-", ROUND(100*(AE22-AI22)/ABS(AI22), 10)))) -> - | AN22: =IF(AJ22="-", "-", IF(AL22="-", "-", IF(ABS(AL22)=0, "-", ROUND(100*(AJ22-AL22)/ABS(AL22), 1)))) -> - | AO22: =IF(AK22="-", "-", IF(AM22="-", "-", IF(ABS(AM22)=0, "-", ROUND(100*(AK22-AM22)/ABS(AM22), 1)))) -> - | AX22: =IF(AP22="-", "-", IF(AT22="-", "-", IF(ABS(AT22)=0, "-", ROUND(100*(AP22-AT22)/ABS(AT22), 10)))) -> - | AY22: =IF(AU22="-", "-", IF(AW22="-", "-", IF(ABS(AW22)=0, "-", ROUND(100*(AU22-AW22)/ABS(AW22), 1)))) -> - | AZ22: =IF(AV22="-", "-", IF(AX22="-", "-", IF(ABS(AX22)=0, "-", ROUND(100*(AV22-AX22)/ABS(AX22), 1)))) -> - | BL22: =IF($B$1<>"",$B$1,"") -> 0 | BP22: =IF($B$1<>"",$B$1-1,"") -> -1 | BT22: 増減率
B23: 労働費 | Q23: =IF(I23="-", "-", IF(M23="-", "-", IF(ABS(M23)=0, "-", ROUND(100*(I23-M23)/ABS(M23), 10)))) -> - | R23: =IF(N23="-", "-", IF(P23="-", "-", IF(ABS(P23)=0, "-", ROUND(100*(N23-P23)/ABS(P23), 1)))) -> - | S23: =IF(O23="-", "-", IF(Q23="-", "-", IF(ABS(Q23)=0, "-", ROUND(100*(O23-Q23)/ABS(Q23), 1)))) -> - | AB23: =IF(T23="-", "-", IF(X23="-", "-", IF(ABS(X23)=0, "-", ROUND(100*(T23-X23)/ABS(X23), 10)))) -> - | AC23: =IF(Y23="-", "-", IF(AA23="-", "-", IF(ABS(AA23)=0, "-", ROUND(100*(Y23-AA23)/ABS(AA23), 1)))) -> - | AD23: =IF(Z23="-", "-", IF(AB23="-", "-", IF(ABS(AB23)=0, "-", ROUND(100*(Z23-AB23)/ABS(AB23), 1)))) -> - | AX23: =IF(AP23="-", "-", IF(AT23="-", "-", IF(ABS(AT23)=0, "-", ROUND(100*(AP23-AT23)/ABS(AT23), 10)))) -> - | AY23: =IF(AU23="-", "-", IF(AW23="-", "-", IF(ABS(AW23)=0, "-", ROUND(100*(AU23-AW23)/ABS(AW23), 1)))) -> - | AZ23: =IF(AV23="-", "-", IF(AX23="-", "-", IF(ABS(AX23)=0, "-", ROUND(100*(AV23-AX23)/ABS(AX23), 1)))) -> - | BE23: 粗収益 | BT23: =IF(BL23="-", "-", IF(BP23="-", "-", IF(ABS(BP23)=0, "-", ROUND(100*(BL23-BP23)/ABS(BP23), 10)))) -> - | BU23: =IF(BQ23="-", "-", IF(BS23="-", "-", IF(ABS(BS23)=0, "-", ROUND(100*(BQ23-BS23)/ABS(BS23), 1)))) -> - | BV23: =IF(BR23="-", "-", IF(BT23="-", "-", IF(ABS(BT23)=0, "-", ROUND(100*(BR23-BT23)/ABS(BT23), 1)))) -> -
C24: 直接労働費 | Q24: =IF(I24="-", "-", IF(M24="-", "-", IF(ABS(M24)=0, "-", ROUND(100*(I24-M24)/ABS(M24), 10)))) -> - | R24: =IF(N24="-", "-", IF(P24="-", "-", IF(ABS(P24)=0, "-", ROUND(100*(N24-P24)/ABS(P24), 1)))) -> - | S24: =IF(O24="-", "-", IF(Q24="-", "-", IF(ABS(Q24)=0, "-", ROUND(100*(O24-Q24)/ABS(Q24), 1)))) -> - | AB24: =IF(T24="-", "-", IF(X24="-", "-", IF(ABS(X24)=0, "-", ROUND(100*(T24-X24)/ABS(X24), 10)))) -> - | AC24: =IF(Y24="-", "-", IF(AA24="-", "-", IF(ABS(AA24)=0, "-", ROUND(100*(Y24-AA24)/ABS(AA24), 1)))) -> - | AD24: =IF(Z24="-", "-", IF(AB24="-", "-", IF(ABS(AB24)=0, "-", ROUND(100*(Z24-AB24)/ABS(AB24), 1)))) -> - | AX24: =IF(AP24="-", "-", IF(AT24="-", "-", IF(ABS(AT24)=0, "-", ROUND(100*(AP24-AT24)/ABS(AT24), 10)))) -> - | AY24: =IF(AU24="-", "-", IF(AW24="-", "-", IF(ABS(AW24)=0, "-", ROUND(100*(AU24-AW24)/ABS(AW24), 1)))) -> - | AZ24: =IF(AV24="-", "-", IF(AX24="-", "-", IF(ABS(AX24)=0, "-", ROUND(100*(AV24-AX24)/ABS(AX24), 1)))) -> - | BE24: 生産費総額 | BT24: =IF(BL24="-", "-", IF(BP24="-", "-", IF(ABS(BP24)=0, "-", ROUND(100*(BL24-BP24)/ABS(BP24), 10)))) -> - | BU24: =IF(BQ24="-", "-", IF(BS24="-", "-", IF(ABS(BS24)=0, "-", ROUND(100*(BQ24-BS24)/ABS(BS24), 1)))) -> - | BV24: =IF(BR24="-", "-", IF(BT24="-", "-", IF(ABS(BT24)=0, "-", ROUND(100*(BR24-BT24)/ABS(BT24), 1)))) -> -
C25: 間接労働費 | Q25: =IF(I25="-", "-", IF(M25="-", "-", IF(ABS(M25)=0, "-", ROUND(100*(I25-M25)/ABS(M25), 10)))) -> - | R25: =IF(N25="-", "-", IF(P25="-", "-", IF(ABS(P25)=0, "-", ROUND(100*(N25-P25)/ABS(P25), 1)))) -> - | S25: =IF(O25="-", "-", IF(Q25="-", "-", IF(ABS(Q25)=0, "-", ROUND(100*(O25-Q25)/ABS(Q25), 1)))) -> - | AB25: =IF(T25="-", "-", IF(X25="-", "-", IF(ABS(X25)=0, "-", ROUND(100*(T25-X25)/ABS(X25), 10)))) -> - | AC25: =IF(Y25="-", "-", IF(AA25="-", "-", IF(ABS(AA25)=0, "-", ROUND(100*(Y25-AA25)/ABS(AA25), 1)))) -> - | AD25: =IF(Z25="-", "-", IF(AB25="-", "-", IF(ABS(AB25)=0, "-", ROUND(100*(Z25-AB25)/ABS(AB25), 1)))) -> - | AX25: =IF(AP25="-", "-", IF(AT25="-", "-", IF(ABS(AT25)=0, "-", ROUND(100*(AP25-AT25)/ABS(AT25), 10)))) -> - | AY25: =IF(AU25="-", "-", IF(AW25="-", "-", IF(ABS(AW25)=0, "-", ROUND(100*(AU25-AW25)/ABS(AW25), 1)))) -> - | AZ25: =IF(AV25="-", "-", IF(AX25="-", "-", IF(ABS(AX25)=0, "-", ROUND(100*(AV25-AX25)/ABS(AX25), 1)))) -> - | BE25: 利潤 | BT25: =IF(BL25="-", "-", IF(BP25="-", "-", IF(ABS(BP25)=0, "-", ROUND(100*(BL25-BP25)/ABS(BP25), 10)))) -> - | BU25: =IF(BQ25="-", "-", IF(BS25="-", "-", IF(ABS(BS25)=0, "-", ROUND(100*(BQ25-BS25)/ABS(BS25), 1)))) -> - | BV25: =IF(BR25="-", "-", IF(BT25="-", "-", IF(ABS(BT25)=0, "-", ROUND(100*(BR25-BT25)/ABS(BT25), 1)))) -> -
B26: 費用合計 | Q26: =IF(I26="-", "-", IF(M26="-", "-", IF(ABS(M26)=0, "-", ROUND(100*(I26-M26)/ABS(M26), 10)))) -> - | R26: =IF(N26="-", "-", IF(P26="-", "-", IF(ABS(P26)=0, "-", ROUND(100*(N26-P26)/ABS(P26), 1)))) -> - | S26: =IF(O26="-", "-", IF(Q26="-", "-", IF(ABS(Q26)=0, "-", ROUND(100*(O26-Q26)/ABS(Q26), 1)))) -> - | AB26: =IF(T26="-", "-", IF(X26="-", "-", IF(ABS(X26)=0, "-", ROUND(100*(T26-X26)/ABS(X26), 10)))) -> - | AC26: =IF(Y26="-", "-", IF(AA26="-", "-", IF(ABS(AA26)=0, "-", ROUND(100*(Y26-AA26)/ABS(AA26), 1)))) -> - | AD26: =IF(Z26="-", "-", IF(AB26="-", "-", IF(ABS(AB26)=0, "-", ROUND(100*(Z26-AB26)/ABS(AB26), 1)))) -> - | AM26: =IF(AE26="-", "-", IF(AI26="-", "-", IF(ABS(AI26)=0, "-", ROUND(100*(AE26-AI26)/ABS(AI26), 10)))) -> - | AN26: =IF(AJ26="-", "-", IF(AL26="-", "-", IF(ABS(AL26)=0, "-", ROUND(100*(AJ26-AL26)/ABS(AL26), 1)))) -> - | AO26: =IF(AK26="-", "-", IF(AM26="-", "-", IF(ABS(AM26)=0, "-", ROUND(100*(AK26-AM26)/ABS(AM26), 1)))) -> - | AX26: =IF(AP26="-", "-", IF(AT26="-", "-", IF(ABS(AT26)=0, "-", ROUND(100*(AP26-AT26)/ABS(AT26), 10)))) -> - | AY26: =IF(AU26="-", "-", IF(AW26="-", "-", IF(ABS(AW26)=0, "-", ROUND(100*(AU26-AW26)/ABS(AW26), 1)))) -> - | AZ26: =IF(AV26="-", "-", IF(AX26="-", "-", IF(ABS(AX26)=0, "-", ROUND(100*(AV26-AX26)/ABS(AX26), 1)))) -> - | BE26: 所得 | BT26: =IF(BL26="-", "-", IF(BP26="-", "-", IF(ABS(BP26)=0, "-", ROUND(100*(BL26-BP26)/ABS(BP26), 10)))) -> - | BU26: =IF(BQ26="-", "-", IF(BS26="-", "-", IF(ABS(BS26)=0, "-", ROUND(100*(BQ26-BS26)/ABS(BS26), 1)))) -> - | BV26: =IF(BR26="-", "-", IF(BT26="-", "-", IF(ABS(BT26)=0, "-", ROUND(100*(BR26-BT26)/ABS(BT26), 1)))) -> -
B27: 副産物価額 | AX27: =IF(AP27="-", "-", IF(AT27="-", "-", IF(ABS(AT27)=0, "-", ROUND(100*(AP27-AT27)/ABS(AT27), 10)))) -> - | AY27: =IF(AU27="-", "-", IF(AW27="-", "-", IF(ABS(AW27)=0, "-", ROUND(100*(AU27-AW27)/ABS(AW27), 1)))) -> - | AZ27: =IF(AV27="-", "-", IF(AX27="-", "-", IF(ABS(AX27)=0, "-", ROUND(100*(AV27-AX27)/ABS(AX27), 1)))) -> - | BF27: １日当たり | BT27: =IF(BL27="-", "-", IF(BP27="-", "-", IF(ABS(BP27)=0, "-", ROUND(100*(BL27-BP27)/ABS(BP27), 10)))) -> - | BU27: =IF(BQ27="-", "-", IF(BS27="-", "-", IF(ABS(BS27)=0, "-", ROUND(100*(BQ27-BS27)/ABS(BS27), 1)))) -> - | BV27: =IF(BR27="-", "-", IF(BT27="-", "-", IF(ABS(BT27)=0, "-", ROUND(100*(BR27-BT27)/ABS(BT27), 1)))) -> -
B28: 生産費 | AX28: =IF(AP28="-", "-", IF(AT28="-", "-", IF(ABS(AT28)=0, "-", ROUND(100*(AP28-AT28)/ABS(AT28), 10)))) -> - | AY28: =IF(AU28="-", "-", IF(AW28="-", "-", IF(ABS(AW28)=0, "-", ROUND(100*(AU28-AW28)/ABS(AW28), 1)))) -> - | AZ28: =IF(AV28="-", "-", IF(AX28="-", "-", IF(ABS(AX28)=0, "-", ROUND(100*(AV28-AX28)/ABS(AX28), 1)))) -> - | BE28: 構成員労働報酬 | BT28: =IF(BL28="-", "-", IF(BP28="-", "-", IF(ABS(BP28)=0, "-", ROUND(100*(BL28-BP28)/ABS(BP28), 10)))) -> - | BU28: =IF(BQ28="-", "-", IF(BS28="-", "-", IF(ABS(BS28)=0, "-", ROUND(100*(BQ28-BS28)/ABS(BS28), 1)))) -> - | BV28: =IF(BR28="-", "-", IF(BT28="-", "-", IF(ABS(BT28)=0, "-", ROUND(100*(BR28-BT28)/ABS(BT28), 1)))) -> -
B29: 支払利子 | AX29: =IF(AP29="-", "-", IF(AT29="-", "-", IF(ABS(AT29)=0, "-", ROUND(100*(AP29-AT29)/ABS(AT29), 10)))) -> - | AY29: =IF(AU29="-", "-", IF(AW29="-", "-", IF(ABS(AW29)=0, "-", ROUND(100*(AU29-AW29)/ABS(AW29), 1)))) -> - | AZ29: =IF(AV29="-", "-", IF(AX29="-", "-", IF(ABS(AX29)=0, "-", ROUND(100*(AV29-AX29)/ABS(AX29), 1)))) -> - | BF29: １日当たり | BT29: =IF(BL29="-", "-", IF(BP29="-", "-", IF(ABS(BP29)=0, "-", ROUND(100*(BL29-BP29)/ABS(BP29), 10)))) -> - | BU29: =IF(BQ29="-", "-", IF(BS29="-", "-", IF(ABS(BS29)=0, "-", ROUND(100*(BQ29-BS29)/ABS(BS29), 1)))) -> - | BV29: =IF(BR29="-", "-", IF(BT29="-", "-", IF(ABS(BT29)=0, "-", ROUND(100*(BR29-BT29)/ABS(BT29), 1)))) -> -
B30: 支払地代 | AX30: =IF(AP30="-", "-", IF(AT30="-", "-", IF(ABS(AT30)=0, "-", ROUND(100*(AP30-AT30)/ABS(AT30), 10)))) -> - | AY30: =IF(AU30="-", "-", IF(AW30="-", "-", IF(ABS(AW30)=0, "-", ROUND(100*(AU30-AW30)/ABS(AW30), 1)))) -> - | AZ30: =IF(AV30="-", "-", IF(AX30="-", "-", IF(ABS(AX30)=0, "-", ROUND(100*(AV30-AX30)/ABS(AX30), 1)))) -> -
B31: 利子・地代算入生産費 | AX31: =IF(AP31="-", "-", IF(AT31="-", "-", IF(ABS(AT31)=0, "-", ROUND(100*(AP31-AT31)/ABS(AT31), 10)))) -> - | AY31: =IF(AU31="-", "-", IF(AW31="-", "-", IF(ABS(AW31)=0, "-", ROUND(100*(AU31-AW31)/ABS(AW31), 1)))) -> - | AZ31: =IF(AV31="-", "-", IF(AX31="-", "-", IF(ABS(AX31)=0, "-", ROUND(100*(AV31-AX31)/ABS(AX31), 1)))) -> -
B32: 自己資本利子 | AX32: =IF(AP32="-", "-", IF(AT32="-", "-", IF(ABS(AT32)=0, "-", ROUND(100*(AP32-AT32)/ABS(AT32), 10)))) -> - | AY32: =IF(AU32="-", "-", IF(AW32="-", "-", IF(ABS(AW32)=0, "-", ROUND(100*(AU32-AW32)/ABS(AW32), 1)))) -> - | AZ32: =IF(AV32="-", "-", IF(AX32="-", "-", IF(ABS(AX32)=0, "-", ROUND(100*(AV32-AX32)/ABS(AX32), 1)))) -> -
B33: 自作地地代 | AX33: =IF(AP33="-", "-", IF(AT33="-", "-", IF(ABS(AT33)=0, "-", ROUND(100*(AP33-AT33)/ABS(AT33), 10)))) -> - | AY33: =IF(AU33="-", "-", IF(AW33="-", "-", IF(ABS(AW33)=0, "-", ROUND(100*(AU33-AW33)/ABS(AW33), 1)))) -> - | AZ33: =IF(AV33="-", "-", IF(AX33="-", "-", IF(ABS(AX33)=0, "-", ROUND(100*(AV33-AX33)/ABS(AX33), 1)))) -> - | BE33: ［参考］各種助成措置を加えた場合 | BV33: 単位：円
B34: 全算入生産費 | AX34: =IF(AP34="-", "-", IF(AT34="-", "-", IF(ABS(AT34)=0, "-", ROUND(100*(AP34-AT34)/ABS(AT34), 10)))) -> - | AY34: =IF(AU34="-", "-", IF(AW34="-", "-", IF(ABS(AW34)=0, "-", ROUND(100*(AU34-AW34)/ABS(AW34), 1)))) -> - | AZ34: =IF(AV34="-", "-", IF(AX34="-", "-", IF(ABS(AX34)=0, "-", ROUND(100*(AV34-AX34)/ABS(AX34), 1)))) -> - | BL34: =IF($B$1<>"",$B$1,"") -> 0 | BP34: =IF($B$1<>"",$B$1-1,"") -> -1 | BT34: 増減率
BE35: 粗収益 | BT35: =IF(BL35="-", "-", IF(BP35="-", "-", IF(ABS(BP35)=0, "-", ROUND(100*(BL35-BP35)/ABS(BP35), 10)))) -> - | BU35: =IF(BQ35="-", "-", IF(BS35="-", "-", IF(ABS(BS35)=0, "-", ROUND(100*(BQ35-BS35)/ABS(BS35), 1)))) -> - | BV35: =IF(BR35="-", "-", IF(BT35="-", "-", IF(ABS(BT35)=0, "-", ROUND(100*(BR35-BT35)/ABS(BT35), 1)))) -> -
BE36: 生産費総額 | BT36: =IF(BL36="-", "-", IF(BP36="-", "-", IF(ABS(BP36)=0, "-", ROUND(100*(BL36-BP36)/ABS(BP36), 10)))) -> - | BU36: =IF(BQ36="-", "-", IF(BS36="-", "-", IF(ABS(BS36)=0, "-", ROUND(100*(BQ36-BS36)/ABS(BS36), 1)))) -> - | BV36: =IF(BR36="-", "-", IF(BT36="-", "-", IF(ABS(BT36)=0, "-", ROUND(100*(BR36-BT36)/ABS(BT36), 1)))) -> -
B37: ２ 資本額及び資本利子 | AD37: 単位：円 | BE37: 利潤 | BT37: =IF(BL37="-", "-", IF(BP37="-", "-", IF(ABS(BP37)=0, "-", ROUND(100*(BL37-BP37)/ABS(BP37), 10)))) -> - | BU37: =IF(BQ37="-", "-", IF(BS37="-", "-", IF(ABS(BS37)=0, "-", ROUND(100*(BQ37-BS37)/ABS(BS37), 1)))) -> - | BV37: =IF(BR37="-", "-", IF(BT37="-", "-", IF(ABS(BT37)=0, "-", ROUND(100*(BR37-BT37)/ABS(BT37), 1)))) -> -
I38: 資本額 | T38: 利子額 | BE38: 所得 | BT38: =IF(BL38="-", "-", IF(BP38="-", "-", IF(ABS(BP38)=0, "-", ROUND(100*(BL38-BP38)/ABS(BP38), 10)))) -> - | BU38: =IF(BQ38="-", "-", IF(BS38="-", "-", IF(ABS(BS38)=0, "-", ROUND(100*(BQ38-BS38)/ABS(BS38), 1)))) -> - | BV38: =IF(BR38="-", "-", IF(BT38="-", "-", IF(ABS(BT38)=0, "-", ROUND(100*(BR38-BT38)/ABS(BT38), 1)))) -> -
I39: =IF($B$1<>"",$B$1,"") -> 0 | M39: =IF($B$1<>"",$B$1-1,"") -> -1 | Q39: 増減率 | T39: =IF($B$1<>"",$B$1,"") -> 0 | X39: =IF($B$1<>"",$B$1-1,"") -> -1 | AB39: 増減率 | BF39: １日当たり | BT39: =IF(BL39="-", "-", IF(BP39="-", "-", IF(ABS(BP39)=0, "-", ROUND(100*(BL39-BP39)/ABS(BP39), 10)))) -> - | BU39: =IF(BQ39="-", "-", IF(BS39="-", "-", IF(ABS(BS39)=0, "-", ROUND(100*(BQ39-BS39)/ABS(BS39), 1)))) -> - | BV39: =IF(BR39="-", "-", IF(BT39="-", "-", IF(ABS(BT39)=0, "-", ROUND(100*(BR39-BT39)/ABS(BT39), 1)))) -> -
B40: 資本額 | Q40: =IF(I40="-", "-", IF(M40="-", "-", IF(ABS(M40)=0, "-", ROUND(100*(I40-M40)/ABS(M40), 10)))) -> - | R40: =IF(N40="-", "-", IF(P40="-", "-", IF(ABS(P40)=0, "-", ROUND(100*(N40-P40)/ABS(P40), 1)))) -> - | S40: =IF(O40="-", "-", IF(Q40="-", "-", IF(ABS(Q40)=0, "-", ROUND(100*(O40-Q40)/ABS(Q40), 1)))) -> - | AB40: =IF(T40="-", "-", IF(X40="-", "-", IF(ABS(X40)=0, "-", ROUND(100*(T40-X40)/ABS(X40), 10)))) -> - | AC40: =IF(Y40="-", "-", IF(AA40="-", "-", IF(ABS(AA40)=0, "-", ROUND(100*(Y40-AA40)/ABS(AA40), 1)))) -> - | AD40: =IF(Z40="-", "-", IF(AB40="-", "-", IF(ABS(AB40)=0, "-", ROUND(100*(Z40-AB40)/ABS(AB40), 1)))) -> - | BE40: 構成員労働報酬 | BT40: =IF(BL40="-", "-", IF(BP40="-", "-", IF(ABS(BP40)=0, "-", ROUND(100*(BL40-BP40)/ABS(BP40), 10)))) -> - | BU40: =IF(BQ40="-", "-", IF(BS40="-", "-", IF(ABS(BS40)=0, "-", ROUND(100*(BQ40-BS40)/ABS(BS40), 1)))) -> - | BV40: =IF(BR40="-", "-", IF(BT40="-", "-", IF(ABS(BT40)=0, "-", ROUND(100*(BR40-BT40)/ABS(BT40), 1)))) -> -
C41: 借入資本 | Q41: =IF(I41="-", "-", IF(M41="-", "-", IF(ABS(M41)=0, "-", ROUND(100*(I41-M41)/ABS(M41), 10)))) -> - | R41: =IF(N41="-", "-", IF(P41="-", "-", IF(ABS(P41)=0, "-", ROUND(100*(N41-P41)/ABS(P41), 1)))) -> - | S41: =IF(O41="-", "-", IF(Q41="-", "-", IF(ABS(Q41)=0, "-", ROUND(100*(O41-Q41)/ABS(Q41), 1)))) -> - | AB41: =IF(T41="-", "-", IF(X41="-", "-", IF(ABS(X41)=0, "-", ROUND(100*(T41-X41)/ABS(X41), 10)))) -> - | AC41: =IF(Y41="-", "-", IF(AA41="-", "-", IF(ABS(AA41)=0, "-", ROUND(100*(Y41-AA41)/ABS(AA41), 1)))) -> - | AD41: =IF(Z41="-", "-", IF(AB41="-", "-", IF(ABS(AB41)=0, "-", ROUND(100*(Z41-AB41)/ABS(AB41), 1)))) -> - | BF41: １日当たり | BT41: =IF(BL41="-", "-", IF(BP41="-", "-", IF(ABS(BP41)=0, "-", ROUND(100*(BL41-BP41)/ABS(BP41), 10)))) -> - | BU41: =IF(BQ41="-", "-", IF(BS41="-", "-", IF(ABS(BS41)=0, "-", ROUND(100*(BQ41-BS41)/ABS(BS41), 1)))) -> - | BV41: =IF(BR41="-", "-", IF(BT41="-", "-", IF(ABS(BT41)=0, "-", ROUND(100*(BR41-BT41)/ABS(BT41), 1)))) -> -
C42: 自己資本 | Q42: =IF(I42="-", "-", IF(M42="-", "-", IF(ABS(M42)=0, "-", ROUND(100*(I42-M42)/ABS(M42), 10)))) -> - | R42: =IF(N42="-", "-", IF(P42="-", "-", IF(ABS(P42)=0, "-", ROUND(100*(N42-P42)/ABS(P42), 1)))) -> - | S42: =IF(O42="-", "-", IF(Q42="-", "-", IF(ABS(Q42)=0, "-", ROUND(100*(O42-Q42)/ABS(Q42), 1)))) -> - | AB42: =IF(T42="-", "-", IF(X42="-", "-", IF(ABS(X42)=0, "-", ROUND(100*(T42-X42)/ABS(X42), 10)))) -> - | AC42: =IF(Y42="-", "-", IF(AA42="-", "-", IF(ABS(AA42)=0, "-", ROUND(100*(Y42-AA42)/ABS(AA42), 1)))) -> - | AD42: =IF(Z42="-", "-", IF(AB42="-", "-", IF(ABS(AB42)=0, "-", ROUND(100*(Z42-AB42)/ABS(AB42), 1)))) -> -
B43: 資産別内訳 | C43: 流動資本 | Q43: =IF(I43="-", "-", IF(M43="-", "-", IF(ABS(M43)=0, "-", ROUND(100*(I43-M43)/ABS(M43), 10)))) -> - | R43: =IF(N43="-", "-", IF(P43="-", "-", IF(ABS(P43)=0, "-", ROUND(100*(N43-P43)/ABS(P43), 1)))) -> - | S43: =IF(O43="-", "-", IF(Q43="-", "-", IF(ABS(Q43)=0, "-", ROUND(100*(O43-Q43)/ABS(Q43), 1)))) -> -
C44: 労賃資本 | Q44: =IF(I44="-", "-", IF(M44="-", "-", IF(ABS(M44)=0, "-", ROUND(100*(I44-M44)/ABS(M44), 10)))) -> - | R44: =IF(N44="-", "-", IF(P44="-", "-", IF(ABS(P44)=0, "-", ROUND(100*(N44-P44)/ABS(P44), 1)))) -> - | S44: =IF(O44="-", "-", IF(Q44="-", "-", IF(ABS(Q44)=0, "-", ROUND(100*(O44-Q44)/ABS(Q44), 1)))) -> -
C45: 固定資本 | Q45: =IF(I45="-", "-", IF(M45="-", "-", IF(ABS(M45)=0, "-", ROUND(100*(I45-M45)/ABS(M45), 10)))) -> - | R45: =IF(N45="-", "-", IF(P45="-", "-", IF(ABS(P45)=0, "-", ROUND(100*(N45-P45)/ABS(P45), 1)))) -> - | S45: =IF(O45="-", "-", IF(Q45="-", "-", IF(ABS(Q45)=0, "-", ROUND(100*(O45-Q45)/ABS(Q45), 1)))) -> -
D46: 建物・構築物 | Q46: =IF(I46="-", "-", IF(M46="-", "-", IF(ABS(M46)=0, "-", ROUND(100*(I46-M46)/ABS(M46), 10)))) -> - | R46: =IF(N46="-", "-", IF(P46="-", "-", IF(ABS(P46)=0, "-", ROUND(100*(N46-P46)/ABS(P46), 1)))) -> - | S46: =IF(O46="-", "-", IF(Q46="-", "-", IF(ABS(Q46)=0, "-", ROUND(100*(O46-Q46)/ABS(Q46), 1)))) -> - | BE46: ６ 農業共済金、各種助成措置の状況 | CG46: 単位：円
D47: 土地改良設備 | Q47: =IF(I47="-", "-", IF(M47="-", "-", IF(ABS(M47)=0, "-", ROUND(100*(I47-M47)/ABS(M47), 10)))) -> - | R47: =IF(N47="-", "-", IF(P47="-", "-", IF(ABS(P47)=0, "-", ROUND(100*(N47-P47)/ABS(P47), 1)))) -> - | S47: =IF(O47="-", "-", IF(Q47="-", "-", IF(ABS(Q47)=0, "-", ROUND(100*(O47-Q47)/ABS(Q47), 1)))) -> - | BL47: 拠出金 | BW47: 受取金
D48: 自動車 | Q48: =IF(I48="-", "-", IF(M48="-", "-", IF(ABS(M48)=0, "-", ROUND(100*(I48-M48)/ABS(M48), 10)))) -> - | R48: =IF(N48="-", "-", IF(P48="-", "-", IF(ABS(P48)=0, "-", ROUND(100*(N48-P48)/ABS(P48), 1)))) -> - | S48: =IF(O48="-", "-", IF(Q48="-", "-", IF(ABS(Q48)=0, "-", ROUND(100*(O48-Q48)/ABS(Q48), 1)))) -> - | BL48: =IF($B$1<>"",$B$1,"") -> 0 | BP48: =IF($B$1<>"",$B$1-1,"") -> -1 | BT48: 増減率 | BW48: =IF($B$1<>"",$B$1,"") -> 0 | CA48: =IF($B$1<>"",$B$1-1,"") -> -1 | CE48: 増減率
D49: 農機具等 | Q49: =IF(I49="-", "-", IF(M49="-", "-", IF(ABS(M49)=0, "-", ROUND(100*(I49-M49)/ABS(M49), 10)))) -> - | R49: =IF(N49="-", "-", IF(P49="-", "-", IF(ABS(P49)=0, "-", ROUND(100*(N49-P49)/ABS(P49), 1)))) -> - | S49: =IF(O49="-", "-", IF(Q49="-", "-", IF(ABS(Q49)=0, "-", ROUND(100*(O49-Q49)/ABS(Q49), 1)))) -> - | BT49: =IF(BL49="-", "-", IF(BP49="-", "-", IF(ABS(BP49)=0, "-", ROUND(100*(BL49-BP49)/ABS(BP49), 10)))) -> - | BU49: =IF(BQ49="-", "-", IF(BS49="-", "-", IF(ABS(BS49)=0, "-", ROUND(100*(BQ49-BS49)/ABS(BS49), 1)))) -> - | BV49: =IF(BR49="-", "-", IF(BT49="-", "-", IF(ABS(BT49)=0, "-", ROUND(100*(BR49-BT49)/ABS(BT49), 1)))) -> - | CE49: =IF(BW49="-", "-", IF(CA49="-", "-", IF(ABS(CA49)=0, "-", ROUND(100*(BW49-CA49)/ABS(CA49), 10)))) -> - | CF49: =IF(CB49="-", "-", IF(CD49="-", "-", IF(ABS(CD49)=0, "-", ROUND(100*(CB49-CD49)/ABS(CD49), 1)))) -> - | CG49: =IF(CC49="-", "-", IF(CE49="-", "-", IF(ABS(CE49)=0, "-", ROUND(100*(CC49-CE49)/ABS(CE49), 1)))) -> -
BT50: =IF(BL50="-", "-", IF(BP50="-", "-", IF(ABS(BP50)=0, "-", ROUND(100*(BL50-BP50)/ABS(BP50), 100)))) -> - | BU50: =IF(BQ50="-", "-", IF(BS50="-", "-", IF(ABS(BS50)=0, "-", ROUND(100*(BQ50-BS50)/ABS(BS50), 1)))) -> - | BV50: =IF(BR50="-", "-", IF(BT50="-", "-", IF(ABS(BT50)=0, "-", ROUND(100*(BR50-BT50)/ABS(BT50), 1)))) -> - | CE50: =IF(BW50="-", "-", IF(CA50="-", "-", IF(ABS(CA50)=0, "-", ROUND(100*(BW50-CA50)/ABS(CA50), 10)))) -> - | CF50: =IF(CB50="-", "-", IF(CD50="-", "-", IF(ABS(CD50)=0, "-", ROUND(100*(CB50-CD50)/ABS(CD50), 1)))) -> - | CG50: =IF(CC50="-", "-", IF(CE50="-", "-", IF(ABS(CE50)=0, "-", ROUND(100*(CC50-CE50)/ABS(CE50), 1)))) -> -
BT51: =IF(BL51="-", "-", IF(BP51="-", "-", IF(ABS(BP51)=0, "-", ROUND(100*(BL51-BP51)/ABS(BP51), 100)))) -> - | BU51: =IF(BQ51="-", "-", IF(BS51="-", "-", IF(ABS(BS51)=0, "-", ROUND(100*(BQ51-BS51)/ABS(BS51), 1)))) -> - | BV51: =IF(BR51="-", "-", IF(BT51="-", "-", IF(ABS(BT51)=0, "-", ROUND(100*(BR51-BT51)/ABS(BT51), 1)))) -> - | CE51: =IF(BW51="-", "-", IF(CA51="-", "-", IF(ABS(CA51)=0, "-", ROUND(100*(BW51-CA51)/ABS(CA51), 10)))) -> - | CF51: =IF(CB51="-", "-", IF(CD51="-", "-", IF(ABS(CD51)=0, "-", ROUND(100*(CB51-CD51)/ABS(CD51), 1)))) -> - | CG51: =IF(CC51="-", "-", IF(CE51="-", "-", IF(ABS(CE51)=0, "-", ROUND(100*(CC51-CE51)/ABS(CE51), 1)))) -> -
B52: ３ 借入金の資金種類別内訳 | AD52: 単位：円 | BT52: =IF(BL52="-", "-", IF(BP52="-", "-", IF(ABS(BP52)=0, "-", ROUND(100*(BL52-BP52)/ABS(BP52), 100)))) -> - | BU52: =IF(BQ52="-", "-", IF(BS52="-", "-", IF(ABS(BS52)=0, "-", ROUND(100*(BQ52-BS52)/ABS(BS52), 1)))) -> - | BV52: =IF(BR52="-", "-", IF(BT52="-", "-", IF(ABS(BT52)=0, "-", ROUND(100*(BR52-BT52)/ABS(BT52), 1)))) -> - | CE52: =IF(BW52="-", "-", IF(CA52="-", "-", IF(ABS(CA52)=0, "-", ROUND(100*(BW52-CA52)/ABS(CA52), 10)))) -> - | CF52: =IF(CB52="-", "-", IF(CD52="-", "-", IF(ABS(CD52)=0, "-", ROUND(100*(CB52-CD52)/ABS(CD52), 1)))) -> - | CG52: =IF(CC52="-", "-", IF(CE52="-", "-", IF(ABS(CE52)=0, "-", ROUND(100*(CC52-CE52)/ABS(CE52), 1)))) -> -
I53: 調査開始時未償還残高 | T53: 利子額 | BT53: =IF(BL53="-", "-", IF(BP53="-", "-", IF(ABS(BP53)=0, "-", ROUND(100*(BL53-BP53)/ABS(BP53), 10)))) -> - | BU53: =IF(BQ53="-", "-", IF(BS53="-", "-", IF(ABS(BS53)=0, "-", ROUND(100*(BQ53-BS53)/ABS(BS53), 1)))) -> - | BV53: =IF(BR53="-", "-", IF(BT53="-", "-", IF(ABS(BT53)=0, "-", ROUND(100*(BR53-BT53)/ABS(BT53), 1)))) -> - | CE53: =IF(BW53="-", "-", IF(CA53="-", "-", IF(ABS(CA53)=0, "-", ROUND(100*(BW53-CA53)/ABS(CA53), 10)))) -> - | CF53: =IF(CB53="-", "-", IF(CD53="-", "-", IF(ABS(CD53)=0, "-", ROUND(100*(CB53-CD53)/ABS(CD53), 1)))) -> - | CG53: =IF(CC53="-", "-", IF(CE53="-", "-", IF(ABS(CE53)=0, "-", ROUND(100*(CC53-CE53)/ABS(CE53), 1)))) -> -
I54: =IF($B$1<>"",$B$1,"") -> 0 | M54: =IF($B$1<>"",$B$1-1,"") -> -1 | Q54: 増減率 | T54: =IF($B$1<>"",$B$1,"") -> 0 | X54: =IF($B$1<>"",$B$1-1,"") -> -1 | AB54: 増減率 | BT54: =IF(BL54="-", "-", IF(BP54="-", "-", IF(ABS(BP54)=0, "-", ROUND(100*(BL54-BP54)/ABS(BP54), 10)))) -> - | BU54: =IF(BQ54="-", "-", IF(BS54="-", "-", IF(ABS(BS54)=0, "-", ROUND(100*(BQ54-BS54)/ABS(BS54), 1)))) -> - | BV54: =IF(BR54="-", "-", IF(BT54="-", "-", IF(ABS(BT54)=0, "-", ROUND(100*(BR54-BT54)/ABS(BT54), 1)))) -> - | CE54: =IF(BW54="-", "-", IF(CA54="-", "-", IF(ABS(CA54)=0, "-", ROUND(100*(BW54-CA54)/ABS(CA54), 10)))) -> - | CF54: =IF(CB54="-", "-", IF(CD54="-", "-", IF(ABS(CD54)=0, "-", ROUND(100*(CB54-CD54)/ABS(CD54), 1)))) -> - | CG54: =IF(CC54="-", "-", IF(CE54="-", "-", IF(ABS(CE54)=0, "-", ROUND(100*(CC54-CE54)/ABS(CE54), 1)))) -> -
B55: 借入金 | E55: 短期 | Q55: =IF(I55="-", "-", IF(M55="-", "-", IF(ABS(M55)=0, "-", ROUND(100*(I55-M55)/ABS(M55), 10)))) -> - | R55: =IF(N55="-", "-", IF(P55="-", "-", IF(ABS(P55)=0, "-", ROUND(100*(N55-P55)/ABS(P55), 1)))) -> - | S55: =IF(O55="-", "-", IF(Q55="-", "-", IF(ABS(Q55)=0, "-", ROUND(100*(O55-Q55)/ABS(Q55), 1)))) -> - | BT55: =IF(BL55="-", "-", IF(BP55="-", "-", IF(ABS(BP55)=0, "-", ROUND(100*(BL55-BP55)/ABS(BP55), 10)))) -> - | BU55: =IF(BQ55="-", "-", IF(BS55="-", "-", IF(ABS(BS55)=0, "-", ROUND(100*(BQ55-BS55)/ABS(BS55), 1)))) -> - | BV55: =IF(BR55="-", "-", IF(BT55="-", "-", IF(ABS(BT55)=0, "-", ROUND(100*(BR55-BT55)/ABS(BT55), 1)))) -> - | CE55: =IF(BW55="-", "-", IF(CA55="-", "-", IF(ABS(CA55)=0, "-", ROUND(100*(BW55-CA55)/ABS(CA55), 10)))) -> - | CF55: =IF(CB55="-", "-", IF(CD55="-", "-", IF(ABS(CD55)=0, "-", ROUND(100*(CB55-CD55)/ABS(CD55), 1)))) -> - | CG55: =IF(CC55="-", "-", IF(CE55="-", "-", IF(ABS(CE55)=0, "-", ROUND(100*(CC55-CE55)/ABS(CE55), 1)))) -> -
E56: 長期 | Q56: =IF(I56="-", "-", IF(M56="-", "-", IF(ABS(M56)=0, "-", ROUND(100*(I56-M56)/ABS(M56), 10)))) -> - | R56: =IF(N56="-", "-", IF(P56="-", "-", IF(ABS(P56)=0, "-", ROUND(100*(N56-P56)/ABS(P56), 1)))) -> - | S56: =IF(O56="-", "-", IF(Q56="-", "-", IF(ABS(Q56)=0, "-", ROUND(100*(O56-Q56)/ABS(Q56), 1)))) -> -
B57: 買掛未払金 | Q57: =IF(I57="-", "-", IF(M57="-", "-", IF(ABS(M57)=0, "-", ROUND(100*(I57-M57)/ABS(M57), 10)))) -> - | R57: =IF(N57="-", "-", IF(P57="-", "-", IF(ABS(P57)=0, "-", ROUND(100*(N57-P57)/ABS(P57), 1)))) -> - | S57: =IF(O57="-", "-", IF(Q57="-", "-", IF(ABS(Q57)=0, "-", ROUND(100*(O57-Q57)/ABS(Q57), 1)))) -> -
B58: 計 | Q58: =IF(I58="-", "-", IF(M58="-", "-", IF(ABS(M58)=0, "-", ROUND(100*(I58-M58)/ABS(M58), 10)))) -> - | R58: =IF(N58="-", "-", IF(P58="-", "-", IF(ABS(P58)=0, "-", ROUND(100*(N58-P58)/ABS(P58), 1)))) -> - | S58: =IF(O58="-", "-", IF(Q58="-", "-", IF(ABS(Q58)=0, "-", ROUND(100*(O58-Q58)/ABS(Q58), 1)))) -> - | AB58: =IF(T58="-", "-", IF(X58="-", "-", IF(ABS(X58)=0, "-", ROUND(100*(T58-X58)/ABS(X58), 10)))) -> - | AC58: =IF(Y58="-", "-", IF(AA58="-", "-", IF(ABS(AA58)=0, "-", ROUND(100*(Y58-AA58)/ABS(AA58), 1)))) -> - | AD58: =IF(Z58="-", "-", IF(AB58="-", "-", IF(ABS(AB58)=0, "-", ROUND(100*(Z58-AB58)/ABS(AB58), 1)))) -> -

Sheet No.2
B1: =AB4 | E1: 年産 米生産費統計結果（組織法人経営体） 集計結果検討表 Ｎｏ．２
G3: 集計番号 | J3: 集計名称 | Q3: 集計経営体数 | V3: 集計倍率 | AB3: 調査年 | AG3: 都道府県等 | AL3: 経営種類 | AQ3: 生産費区分 | AV3: 規模階層 | BA3: 平均値種類 | BF3: 加重・総和の別 | BK3: 集計区分
B4: 本年産 | G4: =IF(No.1!G4="","",No.1!G4) | J4: =IF(No.1!J4="","",No.1!J4) | Q4: =IF(No.1!Q4="","",No.1!Q4) | V4: =IF(No.1!V4="","",No.1!V4) | AB4: =IF(No.1!AB4="","",No.1!AB4) | AG4: =IF(No.1!AG4="","",No.1!AG4) | AH4: =IF(No.1!AH4="","",No.1!AH4) | AI4: =IF(No.1!AI4="","",No.1!AI4) | AJ4: =IF(No.1!AJ4="","",No.1!AJ4) | AK4: =IF(No.1!AK4="","",No.1!AK4) | AL4: =IF(No.1!AL4="","",No.1!AL4) | AM4: =IF(No.1!AM4="","",No.1!AM4) | AN4: =IF(No.1!AN4="","",No.1!AN4) | ... BO4: =IF(No.1!BO4="","",No.1!BO4)
B5: 前年産 | G5: =IF(No.1!G5="","",No.1!G5) | J5: =IF(No.1!J5="","",No.1!J5) | Q5: =IF(No.1!Q5="","",No.1!Q5) | V5: =IF(No.1!V5="","",No.1!V5)
B7: ７ 経営耕地（１経営体当たり） | AO7: 単位：ａ | AT7: 14 稲作作業の受託状況（１経営体当たり）
I8: 所有地 | T8: 借入地 | AE8: 計 | BB8: 数量
I9: =IF($B$1<>"",$B$1,"") | M9: =IF($B$1<>"",$B$1-1,"") | Q9: 増減率 | T9: =IF($B$1<>"",$B$1,"") | X9: =IF($B$1<>"",$B$1-1,"") | AB9: 増減率 | AE9: =IF($B$1<>"",$B$1,"") | AI9: =IF($B$1<>"",$B$1-1,"") | AM9: 増減率 | BB9: =IF($B$1<>"",$B$1,"") | BF9: =IF($B$1<>"",$B$1-1,"") | BJ9: 増減率
B10: 田 | Q10: =IF(I10="-", "-", IF(M10="-", "-", IF(ABS(M10)=0, "-", ROUND(100*(I10-M10)/ABS(M10), 10)))) -> - | R10: =IF(N10="-", "-", IF(P10="-", "-", IF(ABS(P10)=0, "-", ROUND(100*(N10-P10)/ABS(P10), 1)))) -> - | S10: =IF(O10="-", "-", IF(Q10="-", "-", IF(ABS(Q10)=0, "-", ROUND(100*(O10-Q10)/ABS(Q10), 1)))) -> - | AB10: =IF(T10="-", "-", IF(X10="-", "-", IF(ABS(X10)=0, "-", ROUND(100*(T10-X10)/ABS(X10), 10)))) -> - | AC10: =IF(Y10="-", "-", IF(AA10="-", "-", IF(ABS(AA10)=0, "-", ROUND(100*(Y10-AA10)/ABS(AA10), 1)))) -> - | AD10: =IF(Z10="-", "-", IF(AB10="-", "-", IF(ABS(AB10)=0, "-", ROUND(100*(Z10-AB10)/ABS(AB10), 1)))) -> - | AM10: =IF(AE10="-", "-", IF(AI10="-", "-", IF(ABS(AI10)=0, "-", ROUND(100*(AE10-AI10)/ABS(AI10), 10)))) -> - | AN10: =IF(AJ10="-", "-", IF(AL10="-", "-", IF(ABS(AL10)=0, "-", ROUND(100*(AJ10-AL10)/ABS(AL10), 1)))) -> - | AO10: =IF(AK10="-", "-", IF(AM10="-", "-", IF(ABS(AM10)=0, "-", ROUND(100*(AK10-AM10)/ABS(AM10), 1)))) -> - | AT10: 全作業 | BA10: ａ | BJ10: =IF(BB10="-", "-", IF(BF10="-", "-", IF(ABS(BF10)=0, "-", ROUND(100*(BB10-BF10)/ABS(BF10), 10)))) -> - | BK10: =IF(BG10="-", "-", IF(BI10="-", "-", IF(ABS(BI10)=0, "-", ROUND(100*(BG10-BI10)/ABS(BI10), 1)))) -> - | BL10: =IF(BH10="-", "-", IF(BJ10="-", "-", IF(ABS(BJ10)=0, "-", ROUND(100*(BH10-BJ10)/ABS(BJ10), 1)))) -> -
B11: 普通畑 | Q11: =IF(I11="-", "-", IF(M11="-", "-", IF(ABS(M11)=0, "-", ROUND(100*(I11-M11)/ABS(M11), 10)))) -> - | R11: =IF(N11="-", "-", IF(P11="-", "-", IF(ABS(P11)=0, "-", ROUND(100*(N11-P11)/ABS(P11), 1)))) -> - | S11: =IF(O11="-", "-", IF(Q11="-", "-", IF(ABS(Q11)=0, "-", ROUND(100*(O11-Q11)/ABS(Q11), 1)))) -> - | AB11: =IF(T11="-", "-", IF(X11="-", "-", IF(ABS(X11)=0, "-", ROUND(100*(T11-X11)/ABS(X11), 10)))) -> - | AC11: =IF(Y11="-", "-", IF(AA11="-", "-", IF(ABS(AA11)=0, "-", ROUND(100*(Y11-AA11)/ABS(AA11), 1)))) -> - | AD11: =IF(Z11="-", "-", IF(AB11="-", "-", IF(ABS(AB11)=0, "-", ROUND(100*(Z11-AB11)/ABS(AB11), 1)))) -> - | AM11: =IF(AE11="-", "-", IF(AI11="-", "-", IF(ABS(AI11)=0, "-", ROUND(100*(AE11-AI11)/ABS(AI11), 10)))) -> - | AN11: =IF(AJ11="-", "-", IF(AL11="-", "-", IF(ABS(AL11)=0, "-", ROUND(100*(AJ11-AL11)/ABS(AL11), 1)))) -> - | AO11: =IF(AK11="-", "-", IF(AM11="-", "-", IF(ABS(AM11)=0, "-", ROUND(100*(AK11-AM11)/ABS(AM11), 1)))) -> - | AT11: 耕うん・整地 | BA11: ａ | BJ11: =IF(BB11="-", "-", IF(BF11="-", "-", IF(ABS(BF11)=0, "-", ROUND(100*(BB11-BF11)/ABS(BF11), 10)))) -> - | BK11: =IF(BG11="-", "-", IF(BI11="-", "-", IF(ABS(BI11)=0, "-", ROUND(100*(BG11-BI11)/ABS(BI11), 1)))) -> - | BL11: =IF(BH11="-", "-", IF(BJ11="-", "-", IF(ABS(BJ11)=0, "-", ROUND(100*(BH11-BJ11)/ABS(BJ11), 1)))) -> -
B12: 樹園地 | Q12: =IF(I12="-", "-", IF(M12="-", "-", IF(ABS(M12)=0, "-", ROUND(100*(I12-M12)/ABS(M12), 10)))) -> - | R12: =IF(N12="-", "-", IF(P12="-", "-", IF(ABS(P12)=0, "-", ROUND(100*(N12-P12)/ABS(P12), 1)))) -> - | S12: =IF(O12="-", "-", IF(Q12="-", "-", IF(ABS(Q12)=0, "-", ROUND(100*(O12-Q12)/ABS(Q12), 1)))) -> - | AB12: =IF(T12="-", "-", IF(X12="-", "-", IF(ABS(X12)=0, "-", ROUND(100*(T12-X12)/ABS(X12), 10)))) -> - | AC12: =IF(Y12="-", "-", IF(AA12="-", "-", IF(ABS(AA12)=0, "-", ROUND(100*(Y12-AA12)/ABS(AA12), 1)))) -> - | AD12: =IF(Z12="-", "-", IF(AB12="-", "-", IF(ABS(AB12)=0, "-", ROUND(100*(Z12-AB12)/ABS(AB12), 1)))) -> - | AM12: =IF(AE12="-", "-", IF(AI12="-", "-", IF(ABS(AI12)=0, "-", ROUND(100*(AE12-AI12)/ABS(AI12), 10)))) -> - | AN12: =IF(AJ12="-", "-", IF(AL12="-", "-", IF(ABS(AL12)=0, "-", ROUND(100*(AJ12-AL12)/ABS(AL12), 1)))) -> - | AO12: =IF(AK12="-", "-", IF(AM12="-", "-", IF(ABS(AM12)=0, "-", ROUND(100*(AK12-AM12)/ABS(AM12), 1)))) -> - | AT12: 育苗 | BA12: ａ | BJ12: =IF(BB12="-", "-", IF(BF12="-", "-", IF(ABS(BF12)=0, "-", ROUND(100*(BB12-BF12)/ABS(BF12), 10)))) -> - | BK12: =IF(BG12="-", "-", IF(BI12="-", "-", IF(ABS(BI12)=0, "-", ROUND(100*(BG12-BI12)/ABS(BI12), 1)))) -> - | BL12: =IF(BH12="-", "-", IF(BJ12="-", "-", IF(ABS(BJ12)=0, "-", ROUND(100*(BH12-BJ12)/ABS(BJ12), 1)))) -> -
B13: 牧草地 | Q13: =IF(I13="-", "-", IF(M13="-", "-", IF(ABS(M13)=0, "-", ROUND(100*(I13-M13)/ABS(M13), 10)))) -> - | R13: =IF(N13="-", "-", IF(P13="-", "-", IF(ABS(P13)=0, "-", ROUND(100*(N13-P13)/ABS(P13), 1)))) -> - | S13: =IF(O13="-", "-", IF(Q13="-", "-", IF(ABS(Q13)=0, "-", ROUND(100*(O13-Q13)/ABS(Q13), 1)))) -> - | AB13: =IF(T13="-", "-", IF(X13="-", "-", IF(ABS(X13)=0, "-", ROUND(100*(T13-X13)/ABS(X13), 10)))) -> - | AC13: =IF(Y13="-", "-", IF(AA13="-", "-", IF(ABS(AA13)=0, "-", ROUND(100*(Y13-AA13)/ABS(AA13), 1)))) -> - | AD13: =IF(Z13="-", "-", IF(AB13="-", "-", IF(ABS(AB13)=0, "-", ROUND(100*(Z13-AB13)/ABS(AB13), 1)))) -> - | AM13: =IF(AE13="-", "-", IF(AI13="-", "-", IF(ABS(AI13)=0, "-", ROUND(100*(AE13-AI13)/ABS(AI13), 10)))) -> - | AN13: =IF(AJ13="-", "-", IF(AL13="-", "-", IF(ABS(AL13)=0, "-", ROUND(100*(AJ13-AL13)/ABS(AL13), 1)))) -> - | AO13: =IF(AK13="-", "-", IF(AM13="-", "-", IF(ABS(AM13)=0, "-", ROUND(100*(AK13-AM13)/ABS(AM13), 1)))) -> - | AT13: 田植 | BA13: ａ | BJ13: =IF(BB13="-", "-", IF(BF13="-", "-", IF(ABS(BF13)=0, "-", ROUND(100*(BB13-BF13)/ABS(BF13), 10)))) -> - | BK13: =IF(BG13="-", "-", IF(BI13="-", "-", IF(ABS(BI13)=0, "-", ROUND(100*(BG13-BI13)/ABS(BI13), 1)))) -> - | BL13: =IF(BH13="-", "-", IF(BJ13="-", "-", IF(ABS(BJ13)=0, "-", ROUND(100*(BH13-BJ13)/ABS(BJ13), 1)))) -> -
B14: 計 | Q14: =IF(I14="-", "-", IF(M14="-", "-", IF(ABS(M14)=0, "-", ROUND(100*(I14-M14)/ABS(M14), 10)))) -> - | R14: =IF(N14="-", "-", IF(P14="-", "-", IF(ABS(P14)=0, "-", ROUND(100*(N14-P14)/ABS(P14), 1)))) -> - | S14: =IF(O14="-", "-", IF(Q14="-", "-", IF(ABS(Q14)=0, "-", ROUND(100*(O14-Q14)/ABS(Q14), 1)))) -> - | AB14: =IF(T14="-", "-", IF(X14="-", "-", IF(ABS(X14)=0, "-", ROUND(100*(T14-X14)/ABS(X14), 10)))) -> - | AC14: =IF(Y14="-", "-", IF(AA14="-", "-", IF(ABS(AA14)=0, "-", ROUND(100*(Y14-AA14)/ABS(AA14), 1)))) -> - | AD14: =IF(Z14="-", "-", IF(AB14="-", "-", IF(ABS(AB14)=0, "-", ROUND(100*(Z14-AB14)/ABS(AB14), 1)))) -> - | AM14: =IF(AE14="-", "-", IF(AI14="-", "-", IF(ABS(AI14)=0, "-", ROUND(100*(AE14-AI14)/ABS(AI14), 10)))) -> - | AN14: =IF(AJ14="-", "-", IF(AL14="-", "-", IF(ABS(AL14)=0, "-", ROUND(100*(AJ14-AL14)/ABS(AL14), 1)))) -> - | AO14: =IF(AK14="-", "-", IF(AM14="-", "-", IF(ABS(AM14)=0, "-", ROUND(100*(AK14-AM14)/ABS(AM14), 1)))) -> - | AT14: 防除 | BA14: ａ | BJ14: =IF(BB14="-", "-", IF(BF14="-", "-", IF(ABS(BF14)=0, "-", ROUND(100*(BB14-BF14)/ABS(BF14), 10)))) -> - | BK14: =IF(BG14="-", "-", IF(BI14="-", "-", IF(ABS(BI14)=0, "-", ROUND(100*(BG14-BI14)/ABS(BI14), 1)))) -> - | BL14: =IF(BH14="-", "-", IF(BJ14="-", "-", IF(ABS(BJ14)=0, "-", ROUND(100*(BH14-BJ14)/ABS(BJ14), 1)))) -> -
AT15: 刈取・脱穀 | BA15: ａ | BJ15: =IF(BB15="-", "-", IF(BF15="-", "-", IF(ABS(BF15)=0, "-", ROUND(100*(BB15-BF15)/ABS(BF15), 10)))) -> - | BK15: =IF(BG15="-", "-", IF(BI15="-", "-", IF(ABS(BI15)=0, "-", ROUND(100*(BG15-BI15)/ABS(BI15), 1)))) -> - | BL15: =IF(BH15="-", "-", IF(BJ15="-", "-", IF(ABS(BJ15)=0, "-", ROUND(100*(BH15-BJ15)/ABS(BJ15), 1)))) -> -
AT16: 乾燥・調製 | BA16: kg | BJ16: =IF(BB16="-", "-", IF(BF16="-", "-", IF(ABS(BF16)=0, "-", ROUND(100*(BB16-BF16)/ABS(BF16), 10)))) -> - | BK16: =IF(BG16="-", "-", IF(BI16="-", "-", IF(ABS(BI16)=0, "-", ROUND(100*(BG16-BI16)/ABS(BI16), 1)))) -> - | BL16: =IF(BH16="-", "-", IF(BJ16="-", "-", IF(ABS(BJ16)=0, "-", ROUND(100*(BH16-BJ16)/ABS(BJ16), 1)))) -> -
B17: ８ 地 代（面積は１経営体当たり） | AO17: 単位：円、ａ
I18: 自作地 | T18: 借入地 | AE18: 計
I19: =IF($B$1<>"",$B$1,"") | M19: =IF($B$1<>"",$B$1-1,"") | Q19: 増減率 | T19: =IF($B$1<>"",$B$1,"") | X19: =IF($B$1<>"",$B$1-1,"") | AB19: 増減率 | AE19: =IF($B$1<>"",$B$1,"") | AI19: =IF($B$1<>"",$B$1-1,"") | AM19: 増減率 | AT19: 15 稲作作業の委託状況（１経営体当たり）
B20: 作付地 | D20: 作付実面積 | Q20: =IF(I20="-", "-", IF(M20="-", "-", IF(ABS(M20)=0, "-", ROUND(100*(I20-M20)/ABS(M20), 10)))) -> - | R20: =IF(N20="-", "-", IF(P20="-", "-", IF(ABS(P20)=0, "-", ROUND(100*(N20-P20)/ABS(P20), 1)))) -> - | S20: =IF(O20="-", "-", IF(Q20="-", "-", IF(ABS(Q20)=0, "-", ROUND(100*(O20-Q20)/ABS(Q20), 1)))) -> - | AB20: =IF(T20="-", "-", IF(X20="-", "-", IF(ABS(X20)=0, "-", ROUND(100*(T20-X20)/ABS(X20), 10)))) -> - | AC20: =IF(Y20="-", "-", IF(AA20="-", "-", IF(ABS(AA20)=0, "-", ROUND(100*(Y20-AA20)/ABS(AA20), 1)))) -> - | AD20: =IF(Z20="-", "-", IF(AB20="-", "-", IF(ABS(AB20)=0, "-", ROUND(100*(Z20-AB20)/ABS(AB20), 1)))) -> - | AM20: =IF(AE20="-", "-", IF(AI20="-", "-", IF(ABS(AI20)=0, "-", ROUND(100*(AE20-AI20)/ABS(AI20), 10)))) -> - | AN20: =IF(AJ20="-", "-", IF(AL20="-", "-", IF(ABS(AL20)=0, "-", ROUND(100*(AJ20-AL20)/ABS(AL20), 1)))) -> - | AO20: =IF(AK20="-", "-", IF(AM20="-", "-", IF(ABS(AM20)=0, "-", ROUND(100*(AK20-AM20)/ABS(AM20), 1)))) -> - | BB20: 数量
D21: 土地台帳面積 | Q21: =IF(I21="-", "-", IF(M21="-", "-", IF(ABS(M21)=0, "-", ROUND(100*(I21-M21)/ABS(M21), 10)))) -> - | R21: =IF(N21="-", "-", IF(P21="-", "-", IF(ABS(P21)=0, "-", ROUND(100*(N21-P21)/ABS(P21), 1)))) -> - | S21: =IF(O21="-", "-", IF(Q21="-", "-", IF(ABS(Q21)=0, "-", ROUND(100*(O21-Q21)/ABS(Q21), 1)))) -> - | AB21: =IF(T21="-", "-", IF(X21="-", "-", IF(ABS(X21)=0, "-", ROUND(100*(T21-X21)/ABS(X21), 10)))) -> - | AC21: =IF(Y21="-", "-", IF(AA21="-", "-", IF(ABS(AA21)=0, "-", ROUND(100*(Y21-AA21)/ABS(AA21), 1)))) -> - | AD21: =IF(Z21="-", "-", IF(AB21="-", "-", IF(ABS(AB21)=0, "-", ROUND(100*(Z21-AB21)/ABS(AB21), 1)))) -> - | AM21: =IF(AE21="-", "-", IF(AI21="-", "-", IF(ABS(AI21)=0, "-", ROUND(100*(AE21-AI21)/ABS(AI21), 10)))) -> - | AN21: =IF(AJ21="-", "-", IF(AL21="-", "-", IF(ABS(AL21)=0, "-", ROUND(100*(AJ21-AL21)/ABS(AL21), 1)))) -> - | AO21: =IF(AK21="-", "-", IF(AM21="-", "-", IF(ABS(AM21)=0, "-", ROUND(100*(AK21-AM21)/ABS(AM21), 1)))) -> - | BB21: =IF($B$1<>"",$B$1,"") | BF21: =IF($B$1<>"",$B$1-1,"") | BJ21: 増減率
D22: 地代総額 | Q22: =IF(I22="-", "-", IF(M22="-", "-", IF(ABS(M22)=0, "-", ROUND(100*(I22-M22)/ABS(M22), 10)))) -> - | R22: =IF(N22="-", "-", IF(P22="-", "-", IF(ABS(P22)=0, "-", ROUND(100*(N22-P22)/ABS(P22), 1)))) -> - | S22: =IF(O22="-", "-", IF(Q22="-", "-", IF(ABS(Q22)=0, "-", ROUND(100*(O22-Q22)/ABS(Q22), 1)))) -> - | AB22: =IF(T22="-", "-", IF(X22="-", "-", IF(ABS(X22)=0, "-", ROUND(100*(T22-X22)/ABS(X22), 10)))) -> - | AC22: =IF(Y22="-", "-", IF(AA22="-", "-", IF(ABS(AA22)=0, "-", ROUND(100*(Y22-AA22)/ABS(AA22), 1)))) -> - | AD22: =IF(Z22="-", "-", IF(AB22="-", "-", IF(ABS(AB22)=0, "-", ROUND(100*(Z22-AB22)/ABS(AB22), 1)))) -> - | AM22: =IF(AE22="-", "-", IF(AI22="-", "-", IF(ABS(AI22)=0, "-", ROUND(100*(AE22-AI22)/ABS(AI22), 10)))) -> - | AN22: =IF(AJ22="-", "-", IF(AL22="-", "-", IF(ABS(AL22)=0, "-", ROUND(100*(AJ22-AL22)/ABS(AL22), 1)))) -> - | AO22: =IF(AK22="-", "-", IF(AM22="-", "-", IF(ABS(AM22)=0, "-", ROUND(100*(AK22-AM22)/ABS(AM22), 1)))) -> - | AT22: 育苗 | BA22: ａ | BJ22: =IF(BB22="-", "-", IF(BF22="-", "-", IF(ABS(BF22)=0, "-", ROUND(100*(BB22-BF22)/ABS(BF22), 10)))) -> - | BK22: =IF(BG22="-", "-", IF(BI22="-", "-", IF(ABS(BI22)=0, "-", ROUND(100*(BG22-BI22)/ABS(BI22), 1)))) -> - | BL22: =IF(BH22="-", "-", IF(BJ22="-", "-", IF(ABS(BJ22)=0, "-", ROUND(100*(BH22-BJ22)/ABS(BJ22), 1)))) -> -
D23: 負担地代 | Q23: =IF(I23="-", "-", IF(M23="-", "-", IF(ABS(M23)=0, "-", ROUND(100*(I23-M23)/ABS(M23), 10)))) -> - | R23: =IF(N23="-", "-", IF(P23="-", "-", IF(ABS(P23)=0, "-", ROUND(100*(N23-P23)/ABS(P23), 1)))) -> - | S23: =IF(O23="-", "-", IF(Q23="-", "-", IF(ABS(Q23)=0, "-", ROUND(100*(O23-Q23)/ABS(Q23), 1)))) -> - | AB23: =IF(T23="-", "-", IF(X23="-", "-", IF(ABS(X23)=0, "-", ROUND(100*(T23-X23)/ABS(X23), 10)))) -> - | AC23: =IF(Y23="-", "-", IF(AA23="-", "-", IF(ABS(AA23)=0, "-", ROUND(100*(Y23-AA23)/ABS(AA23), 1)))) -> - | AD23: =IF(Z23="-", "-", IF(AB23="-", "-", IF(ABS(AB23)=0, "-", ROUND(100*(Z23-AB23)/ABS(AB23), 1)))) -> - | AM23: =IF(AE23="-", "-", IF(AI23="-", "-", IF(ABS(AI23)=0, "-", ROUND(100*(AE23-AI23)/ABS(AI23), 10)))) -> - | AN23: =IF(AJ23="-", "-", IF(AL23="-", "-", IF(ABS(AL23)=0, "-", ROUND(100*(AJ23-AL23)/ABS(AL23), 1)))) -> - | AO23: =IF(AK23="-", "-", IF(AM23="-", "-", IF(ABS(AM23)=0, "-", ROUND(100*(AK23-AM23)/ABS(AM23), 1)))) -> - | AT23: 防除 | BA23: ａ | BJ23: =IF(BB23="-", "-", IF(BF23="-", "-", IF(ABS(BF23)=0, "-", ROUND(100*(BB23-BF23)/ABS(BF23), 10)))) -> - | BK23: =IF(BG23="-", "-", IF(BI23="-", "-", IF(ABS(BI23)=0, "-", ROUND(100*(BG23-BI23)/ABS(BI23), 1)))) -> - | BL23: =IF(BH23="-", "-", IF(BJ23="-", "-", IF(ABS(BJ23)=0, "-", ROUND(100*(BH23-BJ23)/ABS(BJ23), 1)))) -> -
B24: 以 外作付地 | D24: 使用面積 | Q24: =IF(I24="-", "-", IF(M24="-", "-", IF(ABS(M24)=0, "-", ROUND(100*(I24-M24)/ABS(M24), 10)))) -> - | R24: =IF(N24="-", "-", IF(P24="-", "-", IF(ABS(P24)=0, "-", ROUND(100*(N24-P24)/ABS(P24), 1)))) -> - | S24: =IF(O24="-", "-", IF(Q24="-", "-", IF(ABS(Q24)=0, "-", ROUND(100*(O24-Q24)/ABS(Q24), 1)))) -> - | AB24: =IF(T24="-", "-", IF(X24="-", "-", IF(ABS(X24)=0, "-", ROUND(100*(T24-X24)/ABS(X24), 10)))) -> - | AC24: =IF(Y24="-", "-", IF(AA24="-", "-", IF(ABS(AA24)=0, "-", ROUND(100*(Y24-AA24)/ABS(AA24), 1)))) -> - | AD24: =IF(Z24="-", "-", IF(AB24="-", "-", IF(ABS(AB24)=0, "-", ROUND(100*(Z24-AB24)/ABS(AB24), 1)))) -> - | AM24: =IF(AE24="-", "-", IF(AI24="-", "-", IF(ABS(AI24)=0, "-", ROUND(100*(AE24-AI24)/ABS(AI24), 10)))) -> - | AN24: =IF(AJ24="-", "-", IF(AL24="-", "-", IF(ABS(AL24)=0, "-", ROUND(100*(AJ24-AL24)/ABS(AL24), 1)))) -> - | AO24: =IF(AK24="-", "-", IF(AM24="-", "-", IF(ABS(AM24)=0, "-", ROUND(100*(AK24-AM24)/ABS(AM24), 1)))) -> -
D25: 賃借料総額 | Q25: =IF(I25="-", "-", IF(M25="-", "-", IF(ABS(M25)=0, "-", ROUND(100*(I25-M25)/ABS(M25), 10)))) -> - | R25: =IF(N25="-", "-", IF(P25="-", "-", IF(ABS(P25)=0, "-", ROUND(100*(N25-P25)/ABS(P25), 1)))) -> - | S25: =IF(O25="-", "-", IF(Q25="-", "-", IF(ABS(Q25)=0, "-", ROUND(100*(O25-Q25)/ABS(Q25), 1)))) -> - | AB25: =IF(T25="-", "-", IF(X25="-", "-", IF(ABS(X25)=0, "-", ROUND(100*(T25-X25)/ABS(X25), 10)))) -> - | AC25: =IF(Y25="-", "-", IF(AA25="-", "-", IF(ABS(AA25)=0, "-", ROUND(100*(Y25-AA25)/ABS(AA25), 1)))) -> - | AD25: =IF(Z25="-", "-", IF(AB25="-", "-", IF(ABS(AB25)=0, "-", ROUND(100*(Z25-AB25)/ABS(AB25), 1)))) -> - | AM25: =IF(AE25="-", "-", IF(AI25="-", "-", IF(ABS(AI25)=0, "-", ROUND(100*(AE25-AI25)/ABS(AI25), 10)))) -> - | AN25: =IF(AJ25="-", "-", IF(AL25="-", "-", IF(ABS(AL25)=0, "-", ROUND(100*(AJ25-AL25)/ABS(AL25), 1)))) -> - | AO25: =IF(AK25="-", "-", IF(AM25="-", "-", IF(ABS(AM25)=0, "-", ROUND(100*(AK25-AM25)/ABS(AM25), 1)))) -> -
D26: 負担地代 | Q26: =IF(I26="-", "-", IF(M26="-", "-", IF(ABS(M26)=0, "-", ROUND(100*(I26-M26)/ABS(M26), 10)))) -> - | R26: =IF(N26="-", "-", IF(P26="-", "-", IF(ABS(P26)=0, "-", ROUND(100*(N26-P26)/ABS(P26), 1)))) -> - | S26: =IF(O26="-", "-", IF(Q26="-", "-", IF(ABS(Q26)=0, "-", ROUND(100*(O26-Q26)/ABS(Q26), 1)))) -> - | AB26: =IF(T26="-", "-", IF(X26="-", "-", IF(ABS(X26)=0, "-", ROUND(100*(T26-X26)/ABS(X26), 10)))) -> - | AC26: =IF(Y26="-", "-", IF(AA26="-", "-", IF(ABS(AA26)=0, "-", ROUND(100*(Y26-AA26)/ABS(AA26), 1)))) -> - | AD26: =IF(Z26="-", "-", IF(AB26="-", "-", IF(ABS(AB26)=0, "-", ROUND(100*(Z26-AB26)/ABS(AB26), 1)))) -> - | AM26: =IF(AE26="-", "-", IF(AI26="-", "-", IF(ABS(AI26)=0, "-", ROUND(100*(AE26-AI26)/ABS(AI26), 10)))) -> - | AN26: =IF(AJ26="-", "-", IF(AL26="-", "-", IF(ABS(AL26)=0, "-", ROUND(100*(AJ26-AL26)/ABS(AL26), 1)))) -> - | AO26: =IF(AK26="-", "-", IF(AM26="-", "-", IF(ABS(AM26)=0, "-", ROUND(100*(AK26-AM26)/ABS(AM26), 1)))) -> -
B27: 実勢地代 | Q27: =IF(I27="-", "-", IF(M27="-", "-", IF(ABS(M27)=0, "-", ROUND(100*(I27-M27)/ABS(M27), 10)))) -> - | R27: =IF(N27="-", "-", IF(P27="-", "-", IF(ABS(P27)=0, "-", ROUND(100*(N27-P27)/ABS(P27), 1)))) -> - | S27: =IF(O27="-", "-", IF(Q27="-", "-", IF(ABS(Q27)=0, "-", ROUND(100*(O27-Q27)/ABS(Q27), 1)))) -> - | AB27: =IF(T27="-", "-", IF(X27="-", "-", IF(ABS(X27)=0, "-", ROUND(100*(T27-X27)/ABS(X27), 10)))) -> - | AC27: =IF(Y27="-", "-", IF(AA27="-", "-", IF(ABS(AA27)=0, "-", ROUND(100*(Y27-AA27)/ABS(AA27), 1)))) -> - | AD27: =IF(Z27="-", "-", IF(AB27="-", "-", IF(ABS(AB27)=0, "-", ROUND(100*(Z27-AB27)/ABS(AB27), 1)))) -> - | AM27: =IF(AE27="-", "-", IF(AI27="-", "-", IF(ABS(AI27)=0, "-", ROUND(100*(AE27-AI27)/ABS(AI27), 10)))) -> - | AN27: =IF(AJ27="-", "-", IF(AL27="-", "-", IF(ABS(AL27)=0, "-", ROUND(100*(AJ27-AL27)/ABS(AL27), 1)))) -> - | AO27: =IF(AK27="-", "-", IF(AM27="-", "-", IF(ABS(AM27)=0, "-", ROUND(100*(AK27-AM27)/ABS(AM27), 1)))) -> -
B30: ９ 田の概況（総数） | X30: 10 「移植」「直まき」別作付面積（１経営体当たり）
I31: 該当の有無等 | AD31: 作付面積（ａ）
I32: =IF($B$1<>"",$B$1,"") | M32: =IF($B$1<>"",$B$1-1,"") | Q32: 増減率 | AD32: =IF($B$1<>"",$B$1,"") | AH32: =IF($B$1<>"",$B$1-1,"") | AL32: 増減率 | AT32: 16 うるち米の品種別作付面積（１経営体当たり） | CC32: 単位：ａ
B33: 田の団地数（1経営体当たり） | Q33: =IF(I33="-", "-", IF(M33="-", "-", IF(ABS(M33)=0, "-", ROUND(100*(I33-M33)/ABS(M33), 10)))) -> - | R33: =IF(N33="-", "-", IF(P33="-", "-", IF(ABS(P33)=0, "-", ROUND(100*(N33-P33)/ABS(P33), 1)))) -> - | S33: =IF(O33="-", "-", IF(Q33="-", "-", IF(ABS(Q33)=0, "-", ROUND(100*(O33-Q33)/ABS(Q33), 1)))) -> - | X33: 移植 | AL33: =IF(AD33="-", "-", IF(AH33="-", "-", IF(ABS(AH33)=0, "-", ROUND(100*(AD33-AH33)/ABS(AH33), 10)))) -> - | AM33: =IF(AI33="-", "-", IF(AK33="-", "-", IF(ABS(AK33)=0, "-", ROUND(100*(AI33-AK33)/ABS(AK33), 1)))) -> - | AN33: =IF(AJ33="-", "-", IF(AL33="-", "-", IF(ABS(AL33)=0, "-", ROUND(100*(AJ33-AL33)/ABS(AL33), 1)))) -> - | BA33: =IF($B$1<>"",$B$1,"") | BE33: =IF($B$1<>"",$B$1-1,"") | BI33: 増減率 | BS33: =IF($B$1<>"",$B$1,"") | BW33: =IF($B$1<>"",$B$1-1,"") | CA33: 増減率
B34: 田のうち 区画整理 済面積 | E34: 50％未満 | Q34: =IF(I34="-", "-", IF(M34="-", "-", IF(ABS(M34)=0, "-", ROUND(100*(I34-M34)/ABS(M34), 10)))) -> - | R34: =IF(N34="-", "-", IF(P34="-", "-", IF(ABS(P34)=0, "-", ROUND(100*(N34-P34)/ABS(P34), 1)))) -> - | S34: =IF(O34="-", "-", IF(Q34="-", "-", IF(ABS(Q34)=0, "-", ROUND(100*(O34-Q34)/ABS(Q34), 1)))) -> - | X34: 直まき | AL34: =IF(AD34="-", "-", IF(AH34="-", "-", IF(ABS(AH34)=0, "-", ROUND(100*(AD34-AH34)/ABS(AH34), 10)))) -> - | AM34: =IF(AI34="-", "-", IF(AK34="-", "-", IF(ABS(AK34)=0, "-", ROUND(100*(AI34-AK34)/ABS(AK34), 1)))) -> - | AN34: =IF(AJ34="-", "-", IF(AL34="-", "-", IF(ABS(AL34)=0, "-", ROUND(100*(AJ34-AL34)/ABS(AL34), 1)))) -> - | AT34: 計 | BI34: =IF(BA34="-", "-", IF(BE34="-", "-", IF(ABS(BE34)=0, "-", ROUND(100*(BA34-BE34)/ABS(BE34), 10)))) -> - | BJ34: =IF(BF34="-", "-", IF(BH34="-", "-", IF(ABS(BH34)=0, "-", ROUND(100*(BF34-BH34)/ABS(BH34), 1)))) -> - | BK34: =IF(BG34="-", "-", IF(BI34="-", "-", IF(ABS(BI34)=0, "-", ROUND(100*(BG34-BI34)/ABS(BI34), 1)))) -> -
E35: 50～80％ | Q35: =IF(I35="-", "-", IF(M35="-", "-", IF(ABS(M35)=0, "-", ROUND(100*(I35-M35)/ABS(M35), 10)))) -> - | R35: =IF(N35="-", "-", IF(P35="-", "-", IF(ABS(P35)=0, "-", ROUND(100*(N35-P35)/ABS(P35), 1)))) -> - | S35: =IF(O35="-", "-", IF(Q35="-", "-", IF(ABS(Q35)=0, "-", ROUND(100*(O35-Q35)/ABS(Q35), 1)))) -> - | X35: 計 | AL35: =IF(AD35="-", "-", IF(AH35="-", "-", IF(ABS(AH35)=0, "-", ROUND(100*(AD35-AH35)/ABS(AH35), 10)))) -> - | AM35: =IF(AI35="-", "-", IF(AK35="-", "-", IF(ABS(AK35)=0, "-", ROUND(100*(AI35-AK35)/ABS(AK35), 1)))) -> - | AN35: =IF(AJ35="-", "-", IF(AL35="-", "-", IF(ABS(AL35)=0, "-", ROUND(100*(AJ35-AL35)/ABS(AL35), 1)))) -> - | AT35: コード１ | BI35: =IF(BA35="-", "-", IF(BE35="-", "-", IF(ABS(BE35)=0, "-", ROUND(100*(BA35-BE35)/ABS(BE35), 10)))) -> - | BJ35: =IF(BF35="-", "-", IF(BH35="-", "-", IF(ABS(BH35)=0, "-", ROUND(100*(BF35-BH35)/ABS(BH35), 1)))) -> - | BK35: =IF(BG35="-", "-", IF(BI35="-", "-", IF(ABS(BI35)=0, "-", ROUND(100*(BG35-BI35)/ABS(BI35), 1)))) -> - | BL35: コード１６ | CA35: =IF(BS35="-", "-", IF(BW35="-", "-", IF(ABS(BW35)=0, "-", ROUND(100*(BS35-BW35)/ABS(BW35), 10)))) -> - | CB35: =IF(BX35="-", "-", IF(BZ35="-", "-", IF(ABS(BZ35)=0, "-", ROUND(100*(BX35-BZ35)/ABS(BZ35), 1)))) -> - | CC35: =IF(BY35="-", "-", IF(CA35="-", "-", IF(ABS(CA35)=0, "-", ROUND(100*(BY35-CA35)/ABS(CA35), 1)))) -> -
E36: 80％以上 | Q36: =IF(I36="-", "-", IF(M36="-", "-", IF(ABS(M36)=0, "-", ROUND(100*(I36-M36)/ABS(M36), 10)))) -> - | R36: =IF(N36="-", "-", IF(P36="-", "-", IF(ABS(P36)=0, "-", ROUND(100*(N36-P36)/ABS(P36), 1)))) -> - | S36: =IF(O36="-", "-", IF(Q36="-", "-", IF(ABS(Q36)=0, "-", ROUND(100*(O36-Q36)/ABS(Q36), 1)))) -> - | AT36: コード２ | BI36: =IF(BA36="-", "-", IF(BE36="-", "-", IF(ABS(BE36)=0, "-", ROUND(100*(BA36-BE36)/ABS(BE36), 10)))) -> - | BJ36: =IF(BF36="-", "-", IF(BH36="-", "-", IF(ABS(BH36)=0, "-", ROUND(100*(BF36-BH36)/ABS(BH36), 1)))) -> - | BK36: =IF(BG36="-", "-", IF(BI36="-", "-", IF(ABS(BI36)=0, "-", ROUND(100*(BG36-BI36)/ABS(BI36), 1)))) -> - | BL36: コード１７ | CA36: =IF(BS36="-", "-", IF(BW36="-", "-", IF(ABS(BW36)=0, "-", ROUND(100*(BS36-BW36)/ABS(BW36), 10)))) -> - | CB36: =IF(BX36="-", "-", IF(BZ36="-", "-", IF(ABS(BZ36)=0, "-", ROUND(100*(BX36-BZ36)/ABS(BZ36), 1)))) -> - | CC36: =IF(BY36="-", "-", IF(CA36="-", "-", IF(ABS(CA36)=0, "-", ROUND(100*(BY36-CA36)/ABS(CA36), 1)))) -> -
AT37: コード３ | BI37: =IF(BA37="-", "-", IF(BE37="-", "-", IF(ABS(BE37)=0, "-", ROUND(100*(BA37-BE37)/ABS(BE37), 10)))) -> - | BJ37: =IF(BF37="-", "-", IF(BH37="-", "-", IF(ABS(BH37)=0, "-", ROUND(100*(BF37-BH37)/ABS(BH37), 1)))) -> - | BK37: =IF(BG37="-", "-", IF(BI37="-", "-", IF(ABS(BI37)=0, "-", ROUND(100*(BG37-BI37)/ABS(BI37), 1)))) -> - | BL37: コード１８ | CA37: =IF(BS37="-", "-", IF(BW37="-", "-", IF(ABS(BW37)=0, "-", ROUND(100*(BS37-BW37)/ABS(BW37), 10)))) -> - | CB37: =IF(BX37="-", "-", IF(BZ37="-", "-", IF(ABS(BZ37)=0, "-", ROUND(100*(BX37-BZ37)/ABS(BZ37), 1)))) -> - | CC37: =IF(BY37="-", "-", IF(CA37="-", "-", IF(ABS(CA37)=0, "-", ROUND(100*(BY37-CA37)/ABS(CA37), 1)))) -> -
AT38: コード４ | BI38: =IF(BA38="-", "-", IF(BE38="-", "-", IF(ABS(BE38)=0, "-", ROUND(100*(BA38-BE38)/ABS(BE38), 10)))) -> - | BJ38: =IF(BF38="-", "-", IF(BH38="-", "-", IF(ABS(BH38)=0, "-", ROUND(100*(BF38-BH38)/ABS(BH38), 1)))) -> - | BK38: =IF(BG38="-", "-", IF(BI38="-", "-", IF(ABS(BI38)=0, "-", ROUND(100*(BG38-BI38)/ABS(BI38), 1)))) -> - | BL38: コード１９ | CA38: =IF(BS38="-", "-", IF(BW38="-", "-", IF(ABS(BW38)=0, "-", ROUND(100*(BS38-BW38)/ABS(BW38), 10)))) -> - | CB38: =IF(BX38="-", "-", IF(BZ38="-", "-", IF(ABS(BZ38)=0, "-", ROUND(100*(BX38-BZ38)/ABS(BZ38), 1)))) -> - | CC38: =IF(BY38="-", "-", IF(CA38="-", "-", IF(ABS(CA38)=0, "-", ROUND(100*(BY38-CA38)/ABS(CA38), 1)))) -> -
B39: 11 ほ場枚数及び面積（１経営体当たり） | AD39: 単位：枚、ａ | AT39: コード５ | BI39: =IF(BA39="-", "-", IF(BE39="-", "-", IF(ABS(BE39)=0, "-", ROUND(100*(BA39-BE39)/ABS(BE39), 10)))) -> - | BJ39: =IF(BF39="-", "-", IF(BH39="-", "-", IF(ABS(BH39)=0, "-", ROUND(100*(BF39-BH39)/ABS(BH39), 1)))) -> - | BK39: =IF(BG39="-", "-", IF(BI39="-", "-", IF(ABS(BI39)=0, "-", ROUND(100*(BG39-BI39)/ABS(BI39), 1)))) -> - | BL39: コード２０ | CA39: =IF(BS39="-", "-", IF(BW39="-", "-", IF(ABS(BW39)=0, "-", ROUND(100*(BS39-BW39)/ABS(BW39), 10)))) -> - | CB39: =IF(BX39="-", "-", IF(BZ39="-", "-", IF(ABS(BZ39)=0, "-", ROUND(100*(BX39-BZ39)/ABS(BZ39), 1)))) -> - | CC39: =IF(BY39="-", "-", IF(CA39="-", "-", IF(ABS(CA39)=0, "-", ROUND(100*(BY39-CA39)/ABS(CA39), 1)))) -> -
I40: 枚数 | T40: 面積 | AT40: コード６ | BI40: =IF(BA40="-", "-", IF(BE40="-", "-", IF(ABS(BE40)=0, "-", ROUND(100*(BA40-BE40)/ABS(BE40), 10)))) -> - | BJ40: =IF(BF40="-", "-", IF(BH40="-", "-", IF(ABS(BH40)=0, "-", ROUND(100*(BF40-BH40)/ABS(BH40), 1)))) -> - | BK40: =IF(BG40="-", "-", IF(BI40="-", "-", IF(ABS(BI40)=0, "-", ROUND(100*(BG40-BI40)/ABS(BI40), 1)))) -> - | BL40: コード２１ | CA40: =IF(BS40="-", "-", IF(BW40="-", "-", IF(ABS(BW40)=0, "-", ROUND(100*(BS40-BW40)/ABS(BW40), 10)))) -> - | CB40: =IF(BX40="-", "-", IF(BZ40="-", "-", IF(ABS(BZ40)=0, "-", ROUND(100*(BX40-BZ40)/ABS(BZ40), 1)))) -> - | CC40: =IF(BY40="-", "-", IF(CA40="-", "-", IF(ABS(CA40)=0, "-", ROUND(100*(BY40-CA40)/ABS(CA40), 1)))) -> -
I41: =IF($B$1<>"",$B$1,"") | M41: =IF($B$1<>"",$B$1-1,"") | Q41: 増減率 | T41: =IF($B$1<>"",$B$1,"") | X41: =IF($B$1<>"",$B$1-1,"") | AB41: 増減率 | AT41: コード７ | BI41: =IF(BA41="-", "-", IF(BE41="-", "-", IF(ABS(BE41)=0, "-", ROUND(100*(BA41-BE41)/ABS(BE41), 10)))) -> - | BJ41: =IF(BF41="-", "-", IF(BH41="-", "-", IF(ABS(BH41)=0, "-", ROUND(100*(BF41-BH41)/ABS(BH41), 1)))) -> - | BK41: =IF(BG41="-", "-", IF(BI41="-", "-", IF(ABS(BI41)=0, "-", ROUND(100*(BG41-BI41)/ABS(BI41), 1)))) -> - | BL41: コード２２ | CA41: =IF(BS41="-", "-", IF(BW41="-", "-", IF(ABS(BW41)=0, "-", ROUND(100*(BS41-BW41)/ABS(BW41), 10)))) -> - | CB41: =IF(BX41="-", "-", IF(BZ41="-", "-", IF(ABS(BZ41)=0, "-", ROUND(100*(BX41-BZ41)/ABS(BZ41), 1)))) -> - | CC41: =IF(BY41="-", "-", IF(CA41="-", "-", IF(ABS(CA41)=0, "-", ROUND(100*(BY41-CA41)/ABS(CA41), 1)))) -> -
B42: 未整理又は10a未満 | Q42: =IF(I42="-", "-", IF(M42="-", "-", IF(ABS(M42)=0, "-", ROUND(100*(I42-M42)/ABS(M42), 10)))) -> - | R42: =IF(N42="-", "-", IF(P42="-", "-", IF(ABS(P42)=0, "-", ROUND(100*(N42-P42)/ABS(P42), 1)))) -> - | S42: =IF(O42="-", "-", IF(Q42="-", "-", IF(ABS(Q42)=0, "-", ROUND(100*(O42-Q42)/ABS(Q42), 1)))) -> - | AB42: =IF(T42="-", "-", IF(X42="-", "-", IF(ABS(X42)=0, "-", ROUND(100*(T42-X42)/ABS(X42), 10)))) -> - | AC42: =IF(Y42="-", "-", IF(AA42="-", "-", IF(ABS(AA42)=0, "-", ROUND(100*(Y42-AA42)/ABS(AA42), 1)))) -> - | AD42: =IF(Z42="-", "-", IF(AB42="-", "-", IF(ABS(AB42)=0, "-", ROUND(100*(Z42-AB42)/ABS(AB42), 1)))) -> - | AT42: コード８ | BI42: =IF(BA42="-", "-", IF(BE42="-", "-", IF(ABS(BE42)=0, "-", ROUND(100*(BA42-BE42)/ABS(BE42), 10)))) -> - | BJ42: =IF(BF42="-", "-", IF(BH42="-", "-", IF(ABS(BH42)=0, "-", ROUND(100*(BF42-BH42)/ABS(BH42), 1)))) -> - | BK42: =IF(BG42="-", "-", IF(BI42="-", "-", IF(ABS(BI42)=0, "-", ROUND(100*(BG42-BI42)/ABS(BI42), 1)))) -> - | BL42: コード２３ | CA42: =IF(BS42="-", "-", IF(BW42="-", "-", IF(ABS(BW42)=0, "-", ROUND(100*(BS42-BW42)/ABS(BW42), 10)))) -> - | CB42: =IF(BX42="-", "-", IF(BZ42="-", "-", IF(ABS(BZ42)=0, "-", ROUND(100*(BX42-BZ42)/ABS(BZ42), 1)))) -> - | CC42: =IF(BY42="-", "-", IF(CA42="-", "-", IF(ABS(CA42)=0, "-", ROUND(100*(BY42-CA42)/ABS(CA42), 1)))) -> -
B43: 10～20ａ区画 | Q43: =IF(I43="-", "-", IF(M43="-", "-", IF(ABS(M43)=0, "-", ROUND(100*(I43-M43)/ABS(M43), 10)))) -> - | R43: =IF(N43="-", "-", IF(P43="-", "-", IF(ABS(P43)=0, "-", ROUND(100*(N43-P43)/ABS(P43), 1)))) -> - | S43: =IF(O43="-", "-", IF(Q43="-", "-", IF(ABS(Q43)=0, "-", ROUND(100*(O43-Q43)/ABS(Q43), 1)))) -> - | AB43: =IF(T43="-", "-", IF(X43="-", "-", IF(ABS(X43)=0, "-", ROUND(100*(T43-X43)/ABS(X43), 10)))) -> - | AC43: =IF(Y43="-", "-", IF(AA43="-", "-", IF(ABS(AA43)=0, "-", ROUND(100*(Y43-AA43)/ABS(AA43), 1)))) -> - | AD43: =IF(Z43="-", "-", IF(AB43="-", "-", IF(ABS(AB43)=0, "-", ROUND(100*(Z43-AB43)/ABS(AB43), 1)))) -> - | AT43: コード９ | BI43: =IF(BA43="-", "-", IF(BE43="-", "-", IF(ABS(BE43)=0, "-", ROUND(100*(BA43-BE43)/ABS(BE43), 10)))) -> - | BJ43: =IF(BF43="-", "-", IF(BH43="-", "-", IF(ABS(BH43)=0, "-", ROUND(100*(BF43-BH43)/ABS(BH43), 1)))) -> - | BK43: =IF(BG43="-", "-", IF(BI43="-", "-", IF(ABS(BI43)=0, "-", ROUND(100*(BG43-BI43)/ABS(BI43), 1)))) -> - | BL43: コード２４ | CA43: =IF(BS43="-", "-", IF(BW43="-", "-", IF(ABS(BW43)=0, "-", ROUND(100*(BS43-BW43)/ABS(BW43), 10)))) -> - | CB43: =IF(BX43="-", "-", IF(BZ43="-", "-", IF(ABS(BZ43)=0, "-", ROUND(100*(BX43-BZ43)/ABS(BZ43), 1)))) -> - | CC43: =IF(BY43="-", "-", IF(CA43="-", "-", IF(ABS(CA43)=0, "-", ROUND(100*(BY43-CA43)/ABS(CA43), 1)))) -> -
B44: 20～30ａ区画 | Q44: =IF(I44="-", "-", IF(M44="-", "-", IF(ABS(M44)=0, "-", ROUND(100*(I44-M44)/ABS(M44), 10)))) -> - | R44: =IF(N44="-", "-", IF(P44="-", "-", IF(ABS(P44)=0, "-", ROUND(100*(N44-P44)/ABS(P44), 1)))) -> - | S44: =IF(O44="-", "-", IF(Q44="-", "-", IF(ABS(Q44)=0, "-", ROUND(100*(O44-Q44)/ABS(Q44), 1)))) -> - | AB44: =IF(T44="-", "-", IF(X44="-", "-", IF(ABS(X44)=0, "-", ROUND(100*(T44-X44)/ABS(X44), 10)))) -> - | AC44: =IF(Y44="-", "-", IF(AA44="-", "-", IF(ABS(AA44)=0, "-", ROUND(100*(Y44-AA44)/ABS(AA44), 1)))) -> - | AD44: =IF(Z44="-", "-", IF(AB44="-", "-", IF(ABS(AB44)=0, "-", ROUND(100*(Z44-AB44)/ABS(AB44), 1)))) -> - | AT44: コード１０ | BI44: =IF(BA44="-", "-", IF(BE44="-", "-", IF(ABS(BE44)=0, "-", ROUND(100*(BA44-BE44)/ABS(BE44), 10)))) -> - | BJ44: =IF(BF44="-", "-", IF(BH44="-", "-", IF(ABS(BH44)=0, "-", ROUND(100*(BF44-BH44)/ABS(BH44), 1)))) -> - | BK44: =IF(BG44="-", "-", IF(BI44="-", "-", IF(ABS(BI44)=0, "-", ROUND(100*(BG44-BI44)/ABS(BI44), 1)))) -> - | BL44: コード２５ | CA44: =IF(BS44="-", "-", IF(BW44="-", "-", IF(ABS(BW44)=0, "-", ROUND(100*(BS44-BW44)/ABS(BW44), 10)))) -> - | CB44: =IF(BX44="-", "-", IF(BZ44="-", "-", IF(ABS(BZ44)=0, "-", ROUND(100*(BX44-BZ44)/ABS(BZ44), 1)))) -> - | CC44: =IF(BY44="-", "-", IF(CA44="-", "-", IF(ABS(CA44)=0, "-", ROUND(100*(BY44-CA44)/ABS(CA44), 1)))) -> -
B45: 30～50ａ区画 | Q45: =IF(I45="-", "-", IF(M45="-", "-", IF(ABS(M45)=0, "-", ROUND(100*(I45-M45)/ABS(M45), 10)))) -> - | R45: =IF(N45="-", "-", IF(P45="-", "-", IF(ABS(P45)=0, "-", ROUND(100*(N45-P45)/ABS(P45), 1)))) -> - | S45: =IF(O45="-", "-", IF(Q45="-", "-", IF(ABS(Q45)=0, "-", ROUND(100*(O45-Q45)/ABS(Q45), 1)))) -> - | AB45: =IF(T45="-", "-", IF(X45="-", "-", IF(ABS(X45)=0, "-", ROUND(100*(T45-X45)/ABS(X45), 10)))) -> - | AC45: =IF(Y45="-", "-", IF(AA45="-", "-", IF(ABS(AA45)=0, "-", ROUND(100*(Y45-AA45)/ABS(AA45), 1)))) -> - | AD45: =IF(Z45="-", "-", IF(AB45="-", "-", IF(ABS(AB45)=0, "-", ROUND(100*(Z45-AB45)/ABS(AB45), 1)))) -> - | AT45: コード１１ | BI45: =IF(BA45="-", "-", IF(BE45="-", "-", IF(ABS(BE45)=0, "-", ROUND(100*(BA45-BE45)/ABS(BE45), 10)))) -> - | BJ45: =IF(BF45="-", "-", IF(BH45="-", "-", IF(ABS(BH45)=0, "-", ROUND(100*(BF45-BH45)/ABS(BH45), 1)))) -> - | BK45: =IF(BG45="-", "-", IF(BI45="-", "-", IF(ABS(BI45)=0, "-", ROUND(100*(BG45-BI45)/ABS(BI45), 1)))) -> - | BL45: コード２６ | CA45: =IF(BS45="-", "-", IF(BW45="-", "-", IF(ABS(BW45)=0, "-", ROUND(100*(BS45-BW45)/ABS(BW45), 10)))) -> - | CB45: =IF(BX45="-", "-", IF(BZ45="-", "-", IF(ABS(BZ45)=0, "-", ROUND(100*(BX45-BZ45)/ABS(BZ45), 1)))) -> - | CC45: =IF(BY45="-", "-", IF(CA45="-", "-", IF(ABS(CA45)=0, "-", ROUND(100*(BY45-CA45)/ABS(CA45), 1)))) -> -
B46: 50～１hａ区画 | Q46: =IF(I46="-", "-", IF(M46="-", "-", IF(ABS(M46)=0, "-", ROUND(100*(I46-M46)/ABS(M46), 10)))) -> - | R46: =IF(N46="-", "-", IF(P46="-", "-", IF(ABS(P46)=0, "-", ROUND(100*(N46-P46)/ABS(P46), 1)))) -> - | S46: =IF(O46="-", "-", IF(Q46="-", "-", IF(ABS(Q46)=0, "-", ROUND(100*(O46-Q46)/ABS(Q46), 1)))) -> - | AB46: =IF(T46="-", "-", IF(X46="-", "-", IF(ABS(X46)=0, "-", ROUND(100*(T46-X46)/ABS(X46), 10)))) -> - | AC46: =IF(Y46="-", "-", IF(AA46="-", "-", IF(ABS(AA46)=0, "-", ROUND(100*(Y46-AA46)/ABS(AA46), 1)))) -> - | AD46: =IF(Z46="-", "-", IF(AB46="-", "-", IF(ABS(AB46)=0, "-", ROUND(100*(Z46-AB46)/ABS(AB46), 1)))) -> - | AT46: コード１２ | BI46: =IF(BA46="-", "-", IF(BE46="-", "-", IF(ABS(BE46)=0, "-", ROUND(100*(BA46-BE46)/ABS(BE46), 10)))) -> - | BJ46: =IF(BF46="-", "-", IF(BH46="-", "-", IF(ABS(BH46)=0, "-", ROUND(100*(BF46-BH46)/ABS(BH46), 1)))) -> - | BK46: =IF(BG46="-", "-", IF(BI46="-", "-", IF(ABS(BI46)=0, "-", ROUND(100*(BG46-BI46)/ABS(BI46), 1)))) -> - | BL46: コード２７ | CA46: =IF(BS46="-", "-", IF(BW46="-", "-", IF(ABS(BW46)=0, "-", ROUND(100*(BS46-BW46)/ABS(BW46), 10)))) -> - | CB46: =IF(BX46="-", "-", IF(BZ46="-", "-", IF(ABS(BZ46)=0, "-", ROUND(100*(BX46-BZ46)/ABS(BZ46), 1)))) -> - | CC46: =IF(BY46="-", "-", IF(CA46="-", "-", IF(ABS(CA46)=0, "-", ROUND(100*(BY46-CA46)/ABS(CA46), 1)))) -> -
B47: １ｈａ以上区画 | Q47: =IF(I47="-", "-", IF(M47="-", "-", IF(ABS(M47)=0, "-", ROUND(100*(I47-M47)/ABS(M47), 10)))) -> - | R47: =IF(N47="-", "-", IF(P47="-", "-", IF(ABS(P47)=0, "-", ROUND(100*(N47-P47)/ABS(P47), 1)))) -> - | S47: =IF(O47="-", "-", IF(Q47="-", "-", IF(ABS(Q47)=0, "-", ROUND(100*(O47-Q47)/ABS(Q47), 1)))) -> - | AB47: =IF(T47="-", "-", IF(X47="-", "-", IF(ABS(X47)=0, "-", ROUND(100*(T47-X47)/ABS(X47), 10)))) -> - | AC47: =IF(Y47="-", "-", IF(AA47="-", "-", IF(ABS(AA47)=0, "-", ROUND(100*(Y47-AA47)/ABS(AA47), 1)))) -> - | AD47: =IF(Z47="-", "-", IF(AB47="-", "-", IF(ABS(AB47)=0, "-", ROUND(100*(Z47-AB47)/ABS(AB47), 1)))) -> - | AT47: コード１３ | BI47: =IF(BA47="-", "-", IF(BE47="-", "-", IF(ABS(BE47)=0, "-", ROUND(100*(BA47-BE47)/ABS(BE47), 10)))) -> - | BJ47: =IF(BF47="-", "-", IF(BH47="-", "-", IF(ABS(BH47)=0, "-", ROUND(100*(BF47-BH47)/ABS(BH47), 1)))) -> - | BK47: =IF(BG47="-", "-", IF(BI47="-", "-", IF(ABS(BI47)=0, "-", ROUND(100*(BG47-BI47)/ABS(BI47), 1)))) -> - | BL47: コード２８ | CA47: =IF(BS47="-", "-", IF(BW47="-", "-", IF(ABS(BW47)=0, "-", ROUND(100*(BS47-BW47)/ABS(BW47), 10)))) -> - | CB47: =IF(BX47="-", "-", IF(BZ47="-", "-", IF(ABS(BZ47)=0, "-", ROUND(100*(BX47-BZ47)/ABS(BZ47), 1)))) -> - | CC47: =IF(BY47="-", "-", IF(CA47="-", "-", IF(ABS(CA47)=0, "-", ROUND(100*(BY47-CA47)/ABS(CA47), 1)))) -> -
B48: 計 | Q48: =IF(I48="-", "-", IF(M48="-", "-", IF(ABS(M48)=0, "-", ROUND(100*(I48-M48)/ABS(M48), 10)))) -> - | R48: =IF(N48="-", "-", IF(P48="-", "-", IF(ABS(P48)=0, "-", ROUND(100*(N48-P48)/ABS(P48), 1)))) -> - | S48: =IF(O48="-", "-", IF(Q48="-", "-", IF(ABS(Q48)=0, "-", ROUND(100*(O48-Q48)/ABS(Q48), 1)))) -> - | AB48: =IF(T48="-", "-", IF(X48="-", "-", IF(ABS(X48)=0, "-", ROUND(100*(T48-X48)/ABS(X48), 10)))) -> - | AC48: =IF(Y48="-", "-", IF(AA48="-", "-", IF(ABS(AA48)=0, "-", ROUND(100*(Y48-AA48)/ABS(AA48), 1)))) -> - | AD48: =IF(Z48="-", "-", IF(AB48="-", "-", IF(ABS(AB48)=0, "-", ROUND(100*(Z48-AB48)/ABS(AB48), 1)))) -> - | AT48: コード１４ | BI48: =IF(BA48="-", "-", IF(BE48="-", "-", IF(ABS(BE48)=0, "-", ROUND(100*(BA48-BE48)/ABS(BE48), 10)))) -> - | BJ48: =IF(BF48="-", "-", IF(BH48="-", "-", IF(ABS(BH48)=0, "-", ROUND(100*(BF48-BH48)/ABS(BH48), 1)))) -> - | BK48: =IF(BG48="-", "-", IF(BI48="-", "-", IF(ABS(BI48)=0, "-", ROUND(100*(BG48-BI48)/ABS(BI48), 1)))) -> - | BL48: コード２９ | CA48: =IF(BS48="-", "-", IF(BW48="-", "-", IF(ABS(BW48)=0, "-", ROUND(100*(BS48-BW48)/ABS(BW48), 10)))) -> - | CB48: =IF(BX48="-", "-", IF(BZ48="-", "-", IF(ABS(BZ48)=0, "-", ROUND(100*(BX48-BZ48)/ABS(BZ48), 1)))) -> - | CC48: =IF(BY48="-", "-", IF(CA48="-", "-", IF(ABS(CA48)=0, "-", ROUND(100*(BY48-CA48)/ABS(CA48), 1)))) -> -
AT49: コード１５ | BI49: =IF(BA49="-", "-", IF(BE49="-", "-", IF(ABS(BE49)=0, "-", ROUND(100*(BA49-BE49)/ABS(BE49), 10)))) -> - | BJ49: =IF(BF49="-", "-", IF(BH49="-", "-", IF(ABS(BH49)=0, "-", ROUND(100*(BF49-BH49)/ABS(BH49), 1)))) -> - | BK49: =IF(BG49="-", "-", IF(BI49="-", "-", IF(ABS(BI49)=0, "-", ROUND(100*(BG49-BI49)/ABS(BI49), 1)))) -> - | BL49: コード３０ | CA49: =IF(BS49="-", "-", IF(BW49="-", "-", IF(ABS(BW49)=0, "-", ROUND(100*(BS49-BW49)/ABS(BW49), 10)))) -> - | CB49: =IF(BX49="-", "-", IF(BZ49="-", "-", IF(ABS(BZ49)=0, "-", ROUND(100*(BX49-BZ49)/ABS(BZ49), 1)))) -> - | CC49: =IF(BY49="-", "-", IF(CA49="-", "-", IF(ABS(CA49)=0, "-", ROUND(100*(BY49-CA49)/ABS(CA49), 1)))) -> -
B51: 12 飼料用米作付状況（１経営体当たり） | Y51: 17 食用米の田植、収穫期間 | AO51: 単位：日
I52: 作付面積（ａ） | AE52: =IF($B$1<>"",$B$1,"") | AI52: =IF($B$1<>"",$B$1-1,"") | AM52: 増減率
I53: =IF($B$1<>"",$B$1,"") | M53: =IF($B$1<>"",$B$1-1,"") | Q53: 増減率 | Y53: 田植 | AM53: =IF(AE53="-", "-", IF(AI53="-", "-", IF(ABS(AI53)=0, "-", ROUND(100*(AE53-AI53)/ABS(AI53), 10)))) -> - | AN53: =IF(AJ53="-", "-", IF(AL53="-", "-", IF(ABS(AL53)=0, "-", ROUND(100*(AJ53-AL53)/ABS(AL53), 1)))) -> - | AO53: =IF(AK53="-", "-", IF(AM53="-", "-", IF(ABS(AM53)=0, "-", ROUND(100*(AK53-AM53)/ABS(AM53), 1)))) -> -
B54: 飼料用米 | Q54: =IF(I54="-", "-", IF(M54="-", "-", IF(ABS(M54)=0, "-", ROUND(100*(I54-M54)/ABS(M54), 10)))) -> - | R54: =IF(N54="-", "-", IF(P54="-", "-", IF(ABS(P54)=0, "-", ROUND(100*(N54-P54)/ABS(P54), 1)))) -> - | S54: =IF(O54="-", "-", IF(Q54="-", "-", IF(ABS(Q54)=0, "-", ROUND(100*(O54-Q54)/ABS(Q54), 1)))) -> - | Y54: 収穫 | AM54: =IF(AE54="-", "-", IF(AI54="-", "-", IF(ABS(AI54)=0, "-", ROUND(100*(AE54-AI54)/ABS(AI54), 10)))) -> - | AN54: =IF(AJ54="-", "-", IF(AL54="-", "-", IF(ABS(AL54)=0, "-", ROUND(100*(AJ54-AL54)/ABS(AL54), 1)))) -> - | AO54: =IF(AK54="-", "-", IF(AM54="-", "-", IF(ABS(AM54)=0, "-", ROUND(100*(AK54-AM54)/ABS(AM54), 1)))) -> -
B57: 13 団地への距離等 | R57: 単位：㎞
H58: =IF($B$1<>"",$B$1,"") | L58: =IF($B$1<>"",$B$1-1,"") | P58: 増減率
B59: ほ場間の距離 | P59: =IF(H59="-", "-", IF(L59="-", "-", IF(ABS(L59)=0, "-", ROUND(100*(H59-L59)/ABS(L59), 10)))) -> - | Q59: =IF(M59="-", "-", IF(O59="-", "-", IF(ABS(O59)=0, "-", ROUND(100*(M59-O59)/ABS(O59), 1)))) -> - | R59: =IF(N59="-", "-", IF(P59="-", "-", IF(ABS(P59)=0, "-", ROUND(100*(N59-P59)/ABS(P59), 1)))) -> -
B60: 団地への平均距離 | P60: =IF(H60="-", "-", IF(L60="-", "-", IF(ABS(L60)=0, "-", ROUND(100*(H60-L60)/ABS(L60), 10)))) -> - | Q60: =IF(M60="-", "-", IF(O60="-", "-", IF(ABS(O60)=0, "-", ROUND(100*(M60-O60)/ABS(O60), 1)))) -> - | R60: =IF(N60="-", "-", IF(P60="-", "-", IF(ABS(P60)=0, "-", ROUND(100*(N60-P60)/ABS(P60), 1)))) -> -

Sheet No.3
B1: =AB4 | E1: 年産 米生産費統計結果（組織法人経営体） 集計結果検討表 Ｎｏ．３
G3: 集計番号 | J3: 集計名称 | Q3: 集計経営体数 | V3: 集計倍率 | AB3: 調査年 | AG3: 都道府県等 | AL3: 経営種類 | AQ3: 生産費区分 | AV3: 規模階層 | BA3: 平均値種類 | BF3: 加重・総和の別 | BK3: 集計区分
B4: 本年産 | G4: =IF(No.1!G4="","",No.1!G4) | J4: =IF(No.1!J4="","",No.1!J4) | Q4: =IF(No.1!Q4="","",No.1!Q4) | V4: =IF(No.1!V4="","",No.1!V4) | AB4: =IF(No.1!AB4="","",No.1!AB4) | AG4: =IF(No.1!AG4="","",No.1!AG4) | AH4: =IF(No.1!AH4="","",No.1!AH4) | AI4: =IF(No.1!AI4="","",No.1!AI4) | AJ4: =IF(No.1!AJ4="","",No.1!AJ4) | AK4: =IF(No.1!AK4="","",No.1!AK4) | AL4: =IF(No.1!AL4="","",No.1!AL4) | AM4: =IF(No.1!AM4="","",No.1!AM4) | AN4: =IF(No.1!AN4="","",No.1!AN4) | ... BO4: =IF(No.1!BO4="","",No.1!BO4)
B5: 前年産 | G5: =IF(No.1!G5="","",No.1!G5) | J5: =IF(No.1!J5="","",No.1!J5) | Q5: =IF(No.1!Q5="","",No.1!Q5) | V5: =IF(No.1!V5="","",No.1!V5)
B7: 18 投下労働時間 | AO7: 単位：時間
I8: 構成員 | T8: 雇用 | AE8: 合計
I9: =IF($B$1<>"",$B$1,"") | M9: =IF($B$1<>"",$B$1-1,"") | Q9: 増減率 | T9: =IF($B$1<>"",$B$1,"") | X9: =IF($B$1<>"",$B$1-1,"") | AB9: 増減率 | AE9: =IF($B$1<>"",$B$1,"") | AI9: =IF($B$1<>"",$B$1-1,"") | AM9: 増減率
C10: 種子予措 | Q10: =IF(I10="-", "-", IF(M10="-", "-", IF(ABS(M10)=0, "-", ROUND(100*(I10-M10)/ABS(M10), 10)))) -> - | R10: =IF(N10="-", "-", IF(P10="-", "-", IF(ABS(P10)=0, "-", ROUND(100*(N10-P10)/ABS(P10), 1)))) -> - | S10: =IF(O10="-", "-", IF(Q10="-", "-", IF(ABS(Q10)=0, "-", ROUND(100*(O10-Q10)/ABS(Q10), 1)))) -> - | AB10: =IF(T10="-", "-", IF(X10="-", "-", IF(ABS(X10)=0, "-", ROUND(100*(T10-X10)/ABS(X10), 10)))) -> - | AC10: =IF(Y10="-", "-", IF(AA10="-", "-", IF(ABS(AA10)=0, "-", ROUND(100*(Y10-AA10)/ABS(AA10), 1)))) -> - | AD10: =IF(Z10="-", "-", IF(AB10="-", "-", IF(ABS(AB10)=0, "-", ROUND(100*(Z10-AB10)/ABS(AB10), 1)))) -> - | AM10: =IF(AE10="-", "-", IF(AI10="-", "-", IF(ABS(AI10)=0, "-", ROUND(100*(AE10-AI10)/ABS(AI10), 10)))) -> - | AN10: =IF(AJ10="-", "-", IF(AL10="-", "-", IF(ABS(AL10)=0, "-", ROUND(100*(AJ10-AL10)/ABS(AL10), 1)))) -> - | AO10: =IF(AK10="-", "-", IF(AM10="-", "-", IF(ABS(AM10)=0, "-", ROUND(100*(AK10-AM10)/ABS(AM10), 1)))) -> -
B11: 直接労働時間 | C11: 育苗 | Q11: =IF(I11="-", "-", IF(M11="-", "-", IF(ABS(M11)=0, "-", ROUND(100*(I11-M11)/ABS(M11), 10)))) -> - | R11: =IF(N11="-", "-", IF(P11="-", "-", IF(ABS(P11)=0, "-", ROUND(100*(N11-P11)/ABS(P11), 1)))) -> - | S11: =IF(O11="-", "-", IF(Q11="-", "-", IF(ABS(Q11)=0, "-", ROUND(100*(O11-Q11)/ABS(Q11), 1)))) -> - | AB11: =IF(T11="-", "-", IF(X11="-", "-", IF(ABS(X11)=0, "-", ROUND(100*(T11-X11)/ABS(X11), 10)))) -> - | AC11: =IF(Y11="-", "-", IF(AA11="-", "-", IF(ABS(AA11)=0, "-", ROUND(100*(Y11-AA11)/ABS(AA11), 1)))) -> - | AD11: =IF(Z11="-", "-", IF(AB11="-", "-", IF(ABS(AB11)=0, "-", ROUND(100*(Z11-AB11)/ABS(AB11), 1)))) -> - | AM11: =IF(AE11="-", "-", IF(AI11="-", "-", IF(ABS(AI11)=0, "-", ROUND(100*(AE11-AI11)/ABS(AI11), 10)))) -> - | AN11: =IF(AJ11="-", "-", IF(AL11="-", "-", IF(ABS(AL11)=0, "-", ROUND(100*(AJ11-AL11)/ABS(AL11), 1)))) -> - | AO11: =IF(AK11="-", "-", IF(AM11="-", "-", IF(ABS(AM11)=0, "-", ROUND(100*(AK11-AM11)/ABS(AM11), 1)))) -> -
C12: 耕起整地 | Q12: =IF(I12="-", "-", IF(M12="-", "-", IF(ABS(M12)=0, "-", ROUND(100*(I12-M12)/ABS(M12), 10)))) -> - | R12: =IF(N12="-", "-", IF(P12="-", "-", IF(ABS(P12)=0, "-", ROUND(100*(N12-P12)/ABS(P12), 1)))) -> - | S12: =IF(O12="-", "-", IF(Q12="-", "-", IF(ABS(Q12)=0, "-", ROUND(100*(O12-Q12)/ABS(Q12), 1)))) -> - | AB12: =IF(T12="-", "-", IF(X12="-", "-", IF(ABS(X12)=0, "-", ROUND(100*(T12-X12)/ABS(X12), 10)))) -> - | AC12: =IF(Y12="-", "-", IF(AA12="-", "-", IF(ABS(AA12)=0, "-", ROUND(100*(Y12-AA12)/ABS(AA12), 1)))) -> - | AD12: =IF(Z12="-", "-", IF(AB12="-", "-", IF(ABS(AB12)=0, "-", ROUND(100*(Z12-AB12)/ABS(AB12), 1)))) -> - | AM12: =IF(AE12="-", "-", IF(AI12="-", "-", IF(ABS(AI12)=0, "-", ROUND(100*(AE12-AI12)/ABS(AI12), 10)))) -> - | AN12: =IF(AJ12="-", "-", IF(AL12="-", "-", IF(ABS(AL12)=0, "-", ROUND(100*(AJ12-AL12)/ABS(AL12), 1)))) -> - | AO12: =IF(AK12="-", "-", IF(AM12="-", "-", IF(ABS(AM12)=0, "-", ROUND(100*(AK12-AM12)/ABS(AM12), 1)))) -> -
C13: 基肥 | Q13: =IF(I13="-", "-", IF(M13="-", "-", IF(ABS(M13)=0, "-", ROUND(100*(I13-M13)/ABS(M13), 10)))) -> - | R13: =IF(N13="-", "-", IF(P13="-", "-", IF(ABS(P13)=0, "-", ROUND(100*(N13-P13)/ABS(P13), 1)))) -> - | S13: =IF(O13="-", "-", IF(Q13="-", "-", IF(ABS(Q13)=0, "-", ROUND(100*(O13-Q13)/ABS(Q13), 1)))) -> - | AB13: =IF(T13="-", "-", IF(X13="-", "-", IF(ABS(X13)=0, "-", ROUND(100*(T13-X13)/ABS(X13), 10)))) -> - | AC13: =IF(Y13="-", "-", IF(AA13="-", "-", IF(ABS(AA13)=0, "-", ROUND(100*(Y13-AA13)/ABS(AA13), 1)))) -> - | AD13: =IF(Z13="-", "-", IF(AB13="-", "-", IF(ABS(AB13)=0, "-", ROUND(100*(Z13-AB13)/ABS(AB13), 1)))) -> - | AM13: =IF(AE13="-", "-", IF(AI13="-", "-", IF(ABS(AI13)=0, "-", ROUND(100*(AE13-AI13)/ABS(AI13), 10)))) -> - | AN13: =IF(AJ13="-", "-", IF(AL13="-", "-", IF(ABS(AL13)=0, "-", ROUND(100*(AJ13-AL13)/ABS(AL13), 1)))) -> - | AO13: =IF(AK13="-", "-", IF(AM13="-", "-", IF(ABS(AM13)=0, "-", ROUND(100*(AK13-AM13)/ABS(AM13), 1)))) -> -
C14: 直まき | Q14: =IF(I14="-", "-", IF(M14="-", "-", IF(ABS(M14)=0, "-", ROUND(100*(I14-M14)/ABS(M14), 10)))) -> - | R14: =IF(N14="-", "-", IF(P14="-", "-", IF(ABS(P14)=0, "-", ROUND(100*(N14-P14)/ABS(P14), 1)))) -> - | S14: =IF(O14="-", "-", IF(Q14="-", "-", IF(ABS(Q14)=0, "-", ROUND(100*(O14-Q14)/ABS(Q14), 1)))) -> - | AB14: =IF(T14="-", "-", IF(X14="-", "-", IF(ABS(X14)=0, "-", ROUND(100*(T14-X14)/ABS(X14), 10)))) -> - | AC14: =IF(Y14="-", "-", IF(AA14="-", "-", IF(ABS(AA14)=0, "-", ROUND(100*(Y14-AA14)/ABS(AA14), 1)))) -> - | AD14: =IF(Z14="-", "-", IF(AB14="-", "-", IF(ABS(AB14)=0, "-", ROUND(100*(Z14-AB14)/ABS(AB14), 1)))) -> - | AM14: =IF(AE14="-", "-", IF(AI14="-", "-", IF(ABS(AI14)=0, "-", ROUND(100*(AE14-AI14)/ABS(AI14), 10)))) -> - | AN14: =IF(AJ14="-", "-", IF(AL14="-", "-", IF(ABS(AL14)=0, "-", ROUND(100*(AJ14-AL14)/ABS(AL14), 1)))) -> - | AO14: =IF(AK14="-", "-", IF(AM14="-", "-", IF(ABS(AM14)=0, "-", ROUND(100*(AK14-AM14)/ABS(AM14), 1)))) -> -
C15: 田植 | Q15: =IF(I15="-", "-", IF(M15="-", "-", IF(ABS(M15)=0, "-", ROUND(100*(I15-M15)/ABS(M15), 10)))) -> - | R15: =IF(N15="-", "-", IF(P15="-", "-", IF(ABS(P15)=0, "-", ROUND(100*(N15-P15)/ABS(P15), 1)))) -> - | S15: =IF(O15="-", "-", IF(Q15="-", "-", IF(ABS(Q15)=0, "-", ROUND(100*(O15-Q15)/ABS(Q15), 1)))) -> - | AB15: =IF(T15="-", "-", IF(X15="-", "-", IF(ABS(X15)=0, "-", ROUND(100*(T15-X15)/ABS(X15), 10)))) -> - | AC15: =IF(Y15="-", "-", IF(AA15="-", "-", IF(ABS(AA15)=0, "-", ROUND(100*(Y15-AA15)/ABS(AA15), 1)))) -> - | AD15: =IF(Z15="-", "-", IF(AB15="-", "-", IF(ABS(AB15)=0, "-", ROUND(100*(Z15-AB15)/ABS(AB15), 1)))) -> - | AM15: =IF(AE15="-", "-", IF(AI15="-", "-", IF(ABS(AI15)=0, "-", ROUND(100*(AE15-AI15)/ABS(AI15), 10)))) -> - | AN15: =IF(AJ15="-", "-", IF(AL15="-", "-", IF(ABS(AL15)=0, "-", ROUND(100*(AJ15-AL15)/ABS(AL15), 1)))) -> - | AO15: =IF(AK15="-", "-", IF(AM15="-", "-", IF(ABS(AM15)=0, "-", ROUND(100*(AK15-AM15)/ABS(AM15), 1)))) -> -
C16: 追肥 | Q16: =IF(I16="-", "-", IF(M16="-", "-", IF(ABS(M16)=0, "-", ROUND(100*(I16-M16)/ABS(M16), 10)))) -> - | R16: =IF(N16="-", "-", IF(P16="-", "-", IF(ABS(P16)=0, "-", ROUND(100*(N16-P16)/ABS(P16), 1)))) -> - | S16: =IF(O16="-", "-", IF(Q16="-", "-", IF(ABS(Q16)=0, "-", ROUND(100*(O16-Q16)/ABS(Q16), 1)))) -> - | AB16: =IF(T16="-", "-", IF(X16="-", "-", IF(ABS(X16)=0, "-", ROUND(100*(T16-X16)/ABS(X16), 10)))) -> - | AC16: =IF(Y16="-", "-", IF(AA16="-", "-", IF(ABS(AA16)=0, "-", ROUND(100*(Y16-AA16)/ABS(AA16), 1)))) -> - | AD16: =IF(Z16="-", "-", IF(AB16="-", "-", IF(ABS(AB16)=0, "-", ROUND(100*(Z16-AB16)/ABS(AB16), 1)))) -> - | AM16: =IF(AE16="-", "-", IF(AI16="-", "-", IF(ABS(AI16)=0, "-", ROUND(100*(AE16-AI16)/ABS(AI16), 10)))) -> - | AN16: =IF(AJ16="-", "-", IF(AL16="-", "-", IF(ABS(AL16)=0, "-", ROUND(100*(AJ16-AL16)/ABS(AL16), 1)))) -> - | AO16: =IF(AK16="-", "-", IF(AM16="-", "-", IF(ABS(AM16)=0, "-", ROUND(100*(AK16-AM16)/ABS(AM16), 1)))) -> -
C17: 除草 | Q17: =IF(I17="-", "-", IF(M17="-", "-", IF(ABS(M17)=0, "-", ROUND(100*(I17-M17)/ABS(M17), 10)))) -> - | R17: =IF(N17="-", "-", IF(P17="-", "-", IF(ABS(P17)=0, "-", ROUND(100*(N17-P17)/ABS(P17), 1)))) -> - | S17: =IF(O17="-", "-", IF(Q17="-", "-", IF(ABS(Q17)=0, "-", ROUND(100*(O17-Q17)/ABS(Q17), 1)))) -> - | AB17: =IF(T17="-", "-", IF(X17="-", "-", IF(ABS(X17)=0, "-", ROUND(100*(T17-X17)/ABS(X17), 10)))) -> - | AC17: =IF(Y17="-", "-", IF(AA17="-", "-", IF(ABS(AA17)=0, "-", ROUND(100*(Y17-AA17)/ABS(AA17), 1)))) -> - | AD17: =IF(Z17="-", "-", IF(AB17="-", "-", IF(ABS(AB17)=0, "-", ROUND(100*(Z17-AB17)/ABS(AB17), 1)))) -> - | AM17: =IF(AE17="-", "-", IF(AI17="-", "-", IF(ABS(AI17)=0, "-", ROUND(100*(AE17-AI17)/ABS(AI17), 10)))) -> - | AN17: =IF(AJ17="-", "-", IF(AL17="-", "-", IF(ABS(AL17)=0, "-", ROUND(100*(AJ17-AL17)/ABS(AL17), 1)))) -> - | AO17: =IF(AK17="-", "-", IF(AM17="-", "-", IF(ABS(AM17)=0, "-", ROUND(100*(AK17-AM17)/ABS(AM17), 1)))) -> -
C18: 管理 | Q18: =IF(I18="-", "-", IF(M18="-", "-", IF(ABS(M18)=0, "-", ROUND(100*(I18-M18)/ABS(M18), 10)))) -> - | R18: =IF(N18="-", "-", IF(P18="-", "-", IF(ABS(P18)=0, "-", ROUND(100*(N18-P18)/ABS(P18), 1)))) -> - | S18: =IF(O18="-", "-", IF(Q18="-", "-", IF(ABS(Q18)=0, "-", ROUND(100*(O18-Q18)/ABS(Q18), 1)))) -> - | AB18: =IF(T18="-", "-", IF(X18="-", "-", IF(ABS(X18)=0, "-", ROUND(100*(T18-X18)/ABS(X18), 10)))) -> - | AC18: =IF(Y18="-", "-", IF(AA18="-", "-", IF(ABS(AA18)=0, "-", ROUND(100*(Y18-AA18)/ABS(AA18), 1)))) -> - | AD18: =IF(Z18="-", "-", IF(AB18="-", "-", IF(ABS(AB18)=0, "-", ROUND(100*(Z18-AB18)/ABS(AB18), 1)))) -> - | AM18: =IF(AE18="-", "-", IF(AI18="-", "-", IF(ABS(AI18)=0, "-", ROUND(100*(AE18-AI18)/ABS(AI18), 10)))) -> - | AN18: =IF(AJ18="-", "-", IF(AL18="-", "-", IF(ABS(AL18)=0, "-", ROUND(100*(AJ18-AL18)/ABS(AL18), 1)))) -> - | AO18: =IF(AK18="-", "-", IF(AM18="-", "-", IF(ABS(AM18)=0, "-", ROUND(100*(AK18-AM18)/ABS(AM18), 1)))) -> -
C19: 防除 | Q19: =IF(I19="-", "-", IF(M19="-", "-", IF(ABS(M19)=0, "-", ROUND(100*(I19-M19)/ABS(M19), 10)))) -> - | R19: =IF(N19="-", "-", IF(P19="-", "-", IF(ABS(P19)=0, "-", ROUND(100*(N19-P19)/ABS(P19), 1)))) -> - | S19: =IF(O19="-", "-", IF(Q19="-", "-", IF(ABS(Q19)=0, "-", ROUND(100*(O19-Q19)/ABS(Q19), 1)))) -> - | AB19: =IF(T19="-", "-", IF(X19="-", "-", IF(ABS(X19)=0, "-", ROUND(100*(T19-X19)/ABS(X19), 10)))) -> - | AC19: =IF(Y19="-", "-", IF(AA19="-", "-", IF(ABS(AA19)=0, "-", ROUND(100*(Y19-AA19)/ABS(AA19), 1)))) -> - | AD19: =IF(Z19="-", "-", IF(AB19="-", "-", IF(ABS(AB19)=0, "-", ROUND(100*(Z19-AB19)/ABS(AB19), 1)))) -> - | AM19: =IF(AE19="-", "-", IF(AI19="-", "-", IF(ABS(AI19)=0, "-", ROUND(100*(AE19-AI19)/ABS(AI19), 10)))) -> - | AN19: =IF(AJ19="-", "-", IF(AL19="-", "-", IF(ABS(AL19)=0, "-", ROUND(100*(AJ19-AL19)/ABS(AL19), 1)))) -> - | AO19: =IF(AK19="-", "-", IF(AM19="-", "-", IF(ABS(AM19)=0, "-", ROUND(100*(AK19-AM19)/ABS(AM19), 1)))) -> -
C20: 刈取脱穀 | Q20: =IF(I20="-", "-", IF(M20="-", "-", IF(ABS(M20)=0, "-", ROUND(100*(I20-M20)/ABS(M20), 10)))) -> - | R20: =IF(N20="-", "-", IF(P20="-", "-", IF(ABS(P20)=0, "-", ROUND(100*(N20-P20)/ABS(P20), 1)))) -> - | S20: =IF(O20="-", "-", IF(Q20="-", "-", IF(ABS(Q20)=0, "-", ROUND(100*(O20-Q20)/ABS(Q20), 1)))) -> - | AB20: =IF(T20="-", "-", IF(X20="-", "-", IF(ABS(X20)=0, "-", ROUND(100*(T20-X20)/ABS(X20), 10)))) -> - | AC20: =IF(Y20="-", "-", IF(AA20="-", "-", IF(ABS(AA20)=0, "-", ROUND(100*(Y20-AA20)/ABS(AA20), 1)))) -> - | AD20: =IF(Z20="-", "-", IF(AB20="-", "-", IF(ABS(AB20)=0, "-", ROUND(100*(Z20-AB20)/ABS(AB20), 1)))) -> - | AM20: =IF(AE20="-", "-", IF(AI20="-", "-", IF(ABS(AI20)=0, "-", ROUND(100*(AE20-AI20)/ABS(AI20), 10)))) -> - | AN20: =IF(AJ20="-", "-", IF(AL20="-", "-", IF(ABS(AL20)=0, "-", ROUND(100*(AJ20-AL20)/ABS(AL20), 1)))) -> - | AO20: =IF(AK20="-", "-", IF(AM20="-", "-", IF(ABS(AM20)=0, "-", ROUND(100*(AK20-AM20)/ABS(AM20), 1)))) -> -
C21: 乾燥 | Q21: =IF(I21="-", "-", IF(M21="-", "-", IF(ABS(M21)=0, "-", ROUND(100*(I21-M21)/ABS(M21), 10)))) -> - | R21: =IF(N21="-", "-", IF(P21="-", "-", IF(ABS(P21)=0, "-", ROUND(100*(N21-P21)/ABS(P21), 1)))) -> - | S21: =IF(O21="-", "-", IF(Q21="-", "-", IF(ABS(Q21)=0, "-", ROUND(100*(O21-Q21)/ABS(Q21), 1)))) -> - | AB21: =IF(T21="-", "-", IF(X21="-", "-", IF(ABS(X21)=0, "-", ROUND(100*(T21-X21)/ABS(X21), 10)))) -> - | AC21: =IF(Y21="-", "-", IF(AA21="-", "-", IF(ABS(AA21)=0, "-", ROUND(100*(Y21-AA21)/ABS(AA21), 1)))) -> - | AD21: =IF(Z21="-", "-", IF(AB21="-", "-", IF(ABS(AB21)=0, "-", ROUND(100*(Z21-AB21)/ABS(AB21), 1)))) -> - | AM21: =IF(AE21="-", "-", IF(AI21="-", "-", IF(ABS(AI21)=0, "-", ROUND(100*(AE21-AI21)/ABS(AI21), 10)))) -> - | AN21: =IF(AJ21="-", "-", IF(AL21="-", "-", IF(ABS(AL21)=0, "-", ROUND(100*(AJ21-AL21)/ABS(AL21), 1)))) -> - | AO21: =IF(AK21="-", "-", IF(AM21="-", "-", IF(ABS(AM21)=0, "-", ROUND(100*(AK21-AM21)/ABS(AM21), 1)))) -> -
C22: 生産管理 | Q22: =IF(I22="-", "-", IF(M22="-", "-", IF(ABS(M22)=0, "-", ROUND(100*(I22-M22)/ABS(M22), 10)))) -> - | R22: =IF(N22="-", "-", IF(P22="-", "-", IF(ABS(P22)=0, "-", ROUND(100*(N22-P22)/ABS(P22), 1)))) -> - | S22: =IF(O22="-", "-", IF(Q22="-", "-", IF(ABS(Q22)=0, "-", ROUND(100*(O22-Q22)/ABS(Q22), 1)))) -> - | AM22: =IF(AE22="-", "-", IF(AI22="-", "-", IF(ABS(AI22)=0, "-", ROUND(100*(AE22-AI22)/ABS(AI22), 10)))) -> - | AN22: =IF(AJ22="-", "-", IF(AL22="-", "-", IF(ABS(AL22)=0, "-", ROUND(100*(AJ22-AL22)/ABS(AL22), 1)))) -> - | AO22: =IF(AK22="-", "-", IF(AM22="-", "-", IF(ABS(AM22)=0, "-", ROUND(100*(AK22-AM22)/ABS(AM22), 1)))) -> -
B23: 計 | Q23: =IF(I23="-", "-", IF(M23="-", "-", IF(ABS(M23)=0, "-", ROUND(100*(I23-M23)/ABS(M23), 10)))) -> - | R23: =IF(N23="-", "-", IF(P23="-", "-", IF(ABS(P23)=0, "-", ROUND(100*(N23-P23)/ABS(P23), 1)))) -> - | S23: =IF(O23="-", "-", IF(Q23="-", "-", IF(ABS(Q23)=0, "-", ROUND(100*(O23-Q23)/ABS(Q23), 1)))) -> - | AB23: =IF(T23="-", "-", IF(X23="-", "-", IF(ABS(X23)=0, "-", ROUND(100*(T23-X23)/ABS(X23), 10)))) -> - | AC23: =IF(Y23="-", "-", IF(AA23="-", "-", IF(ABS(AA23)=0, "-", ROUND(100*(Y23-AA23)/ABS(AA23), 1)))) -> - | AD23: =IF(Z23="-", "-", IF(AB23="-", "-", IF(ABS(AB23)=0, "-", ROUND(100*(Z23-AB23)/ABS(AB23), 1)))) -> - | AM23: =IF(AE23="-", "-", IF(AI23="-", "-", IF(ABS(AI23)=0, "-", ROUND(100*(AE23-AI23)/ABS(AI23), 10)))) -> - | AN23: =IF(AJ23="-", "-", IF(AL23="-", "-", IF(ABS(AL23)=0, "-", ROUND(100*(AJ23-AL23)/ABS(AL23), 1)))) -> - | AO23: =IF(AK23="-", "-", IF(AM23="-", "-", IF(ABS(AM23)=0, "-", ROUND(100*(AK23-AM23)/ABS(AM23), 1)))) -> -
B24: 間接労働時間 | Q24: =IF(I24="-", "-", IF(M24="-", "-", IF(ABS(M24)=0, "-", ROUND(100*(I24-M24)/ABS(M24), 10)))) -> - | R24: =IF(N24="-", "-", IF(P24="-", "-", IF(ABS(P24)=0, "-", ROUND(100*(N24-P24)/ABS(P24), 1)))) -> - | S24: =IF(O24="-", "-", IF(Q24="-", "-", IF(ABS(Q24)=0, "-", ROUND(100*(O24-Q24)/ABS(Q24), 1)))) -> - | AB24: =IF(T24="-", "-", IF(X24="-", "-", IF(ABS(X24)=0, "-", ROUND(100*(T24-X24)/ABS(X24), 10)))) -> - | AC24: =IF(Y24="-", "-", IF(AA24="-", "-", IF(ABS(AA24)=0, "-", ROUND(100*(Y24-AA24)/ABS(AA24), 1)))) -> - | AD24: =IF(Z24="-", "-", IF(AB24="-", "-", IF(ABS(AB24)=0, "-", ROUND(100*(Z24-AB24)/ABS(AB24), 1)))) -> - | AM24: =IF(AE24="-", "-", IF(AI24="-", "-", IF(ABS(AI24)=0, "-", ROUND(100*(AE24-AI24)/ABS(AI24), 10)))) -> - | AN24: =IF(AJ24="-", "-", IF(AL24="-", "-", IF(ABS(AL24)=0, "-", ROUND(100*(AJ24-AL24)/ABS(AL24), 1)))) -> - | AO24: =IF(AK24="-", "-", IF(AM24="-", "-", IF(ABS(AM24)=0, "-", ROUND(100*(AK24-AM24)/ABS(AM24), 1)))) -> -
B25: 労働時間合計 | Q25: =IF(I25="-", "-", IF(M25="-", "-", IF(ABS(M25)=0, "-", ROUND(100*(I25-M25)/ABS(M25), 10)))) -> - | R25: =IF(N25="-", "-", IF(P25="-", "-", IF(ABS(P25)=0, "-", ROUND(100*(N25-P25)/ABS(P25), 1)))) -> - | S25: =IF(O25="-", "-", IF(Q25="-", "-", IF(ABS(Q25)=0, "-", ROUND(100*(O25-Q25)/ABS(Q25), 1)))) -> - | AB25: =IF(T25="-", "-", IF(X25="-", "-", IF(ABS(X25)=0, "-", ROUND(100*(T25-X25)/ABS(X25), 10)))) -> - | AC25: =IF(Y25="-", "-", IF(AA25="-", "-", IF(ABS(AA25)=0, "-", ROUND(100*(Y25-AA25)/ABS(AA25), 1)))) -> - | AD25: =IF(Z25="-", "-", IF(AB25="-", "-", IF(ABS(AB25)=0, "-", ROUND(100*(Z25-AB25)/ABS(AB25), 1)))) -> - | AM25: =IF(AE25="-", "-", IF(AI25="-", "-", IF(ABS(AI25)=0, "-", ROUND(100*(AE25-AI25)/ABS(AI25), 10)))) -> - | AN25: =IF(AJ25="-", "-", IF(AL25="-", "-", IF(ABS(AL25)=0, "-", ROUND(100*(AJ25-AL25)/ABS(AL25), 1)))) -> - | AO25: =IF(AK25="-", "-", IF(AM25="-", "-", IF(ABS(AM25)=0, "-", ROUND(100*(AK25-AM25)/ABS(AM25), 1)))) -> -
B28: 19 年齢階層別構成員労働時間及び労働評価 | AO28: 単位：時間、円
I29: 稲作負担構成員労働時間 | AE29: 稲作構成員 労働評価額
I30: 直 接 労 働 | T30: 間 接 労 働
I31: =IF($B$1<>"",$B$1,"") | M31: =IF($B$1<>"",$B$1-1,"") | Q31: 増減率 | T31: =IF($B$1<>"",$B$1,"") | X31: =IF($B$1<>"",$B$1-1,"") | AB31: 増減率 | AE31: =IF($B$1<>"",$B$1,"") | AI31: =IF($B$1<>"",$B$1-1,"") | AM31: 増減率
B32: ６５歳未満 | Q32: =IF(I32="-", "-", IF(M32="-", "-", IF(ABS(M32)=0, "-", ROUND(100*(I32-M32)/ABS(M32), 10)))) -> - | R32: =IF(N32="-", "-", IF(P32="-", "-", IF(ABS(P32)=0, "-", ROUND(100*(N32-P32)/ABS(P32), 1)))) -> - | S32: =IF(O32="-", "-", IF(Q32="-", "-", IF(ABS(Q32)=0, "-", ROUND(100*(O32-Q32)/ABS(Q32), 1)))) -> - | AB32: =IF(T32="-", "-", IF(X32="-", "-", IF(ABS(X32)=0, "-", ROUND(100*(T32-X32)/ABS(X32), 10)))) -> - | AC32: =IF(Y32="-", "-", IF(AA32="-", "-", IF(ABS(AA32)=0, "-", ROUND(100*(Y32-AA32)/ABS(AA32), 1)))) -> - | AD32: =IF(Z32="-", "-", IF(AB32="-", "-", IF(ABS(AB32)=0, "-", ROUND(100*(Z32-AB32)/ABS(AB32), 1)))) -> - | AM32: =IF(AE32="-", "-", IF(AI32="-", "-", IF(ABS(AI32)=0, "-", ROUND(100*(AE32-AI32)/ABS(AI32), 10)))) -> - | AN32: =IF(AJ32="-", "-", IF(AL32="-", "-", IF(ABS(AL32)=0, "-", ROUND(100*(AJ32-AL32)/ABS(AL32), 1)))) -> - | AO32: =IF(AK32="-", "-", IF(AM32="-", "-", IF(ABS(AM32)=0, "-", ROUND(100*(AK32-AM32)/ABS(AM32), 1)))) -> -
B33: ６５～７０ | Q33: =IF(I33="-", "-", IF(M33="-", "-", IF(ABS(M33)=0, "-", ROUND(100*(I33-M33)/ABS(M33), 10)))) -> - | R33: =IF(N33="-", "-", IF(P33="-", "-", IF(ABS(P33)=0, "-", ROUND(100*(N33-P33)/ABS(P33), 1)))) -> - | S33: =IF(O33="-", "-", IF(Q33="-", "-", IF(ABS(Q33)=0, "-", ROUND(100*(O33-Q33)/ABS(Q33), 1)))) -> - | AB33: =IF(T33="-", "-", IF(X33="-", "-", IF(ABS(X33)=0, "-", ROUND(100*(T33-X33)/ABS(X33), 10)))) -> - | AC33: =IF(Y33="-", "-", IF(AA33="-", "-", IF(ABS(AA33)=0, "-", ROUND(100*(Y33-AA33)/ABS(AA33), 1)))) -> - | AD33: =IF(Z33="-", "-", IF(AB33="-", "-", IF(ABS(AB33)=0, "-", ROUND(100*(Z33-AB33)/ABS(AB33), 1)))) -> - | AM33: =IF(AE33="-", "-", IF(AI33="-", "-", IF(ABS(AI33)=0, "-", ROUND(100*(AE33-AI33)/ABS(AI33), 10)))) -> - | AN33: =IF(AJ33="-", "-", IF(AL33="-", "-", IF(ABS(AL33)=0, "-", ROUND(100*(AJ33-AL33)/ABS(AL33), 1)))) -> - | AO33: =IF(AK33="-", "-", IF(AM33="-", "-", IF(ABS(AM33)=0, "-", ROUND(100*(AK33-AM33)/ABS(AM33), 1)))) -> -
B34: ７０～７５ | Q34: =IF(I34="-", "-", IF(M34="-", "-", IF(ABS(M34)=0, "-", ROUND(100*(I34-M34)/ABS(M34), 10)))) -> - | R34: =IF(N34="-", "-", IF(P34="-", "-", IF(ABS(P34)=0, "-", ROUND(100*(N34-P34)/ABS(P34), 1)))) -> - | S34: =IF(O34="-", "-", IF(Q34="-", "-", IF(ABS(Q34)=0, "-", ROUND(100*(O34-Q34)/ABS(Q34), 1)))) -> - | AB34: =IF(T34="-", "-", IF(X34="-", "-", IF(ABS(X34)=0, "-", ROUND(100*(T34-X34)/ABS(X34), 10)))) -> - | AC34: =IF(Y34="-", "-", IF(AA34="-", "-", IF(ABS(AA34)=0, "-", ROUND(100*(Y34-AA34)/ABS(AA34), 1)))) -> - | AD34: =IF(Z34="-", "-", IF(AB34="-", "-", IF(ABS(AB34)=0, "-", ROUND(100*(Z34-AB34)/ABS(AB34), 1)))) -> - | AM34: =IF(AE34="-", "-", IF(AI34="-", "-", IF(ABS(AI34)=0, "-", ROUND(100*(AE34-AI34)/ABS(AI34), 10)))) -> - | AN34: =IF(AJ34="-", "-", IF(AL34="-", "-", IF(ABS(AL34)=0, "-", ROUND(100*(AJ34-AL34)/ABS(AL34), 1)))) -> - | AO34: =IF(AK34="-", "-", IF(AM34="-", "-", IF(ABS(AM34)=0, "-", ROUND(100*(AK34-AM34)/ABS(AM34), 1)))) -> -
B35: ７５歳以上 | Q35: =IF(I35="-", "-", IF(M35="-", "-", IF(ABS(M35)=0, "-", ROUND(100*(I35-M35)/ABS(M35), 10)))) -> - | R35: =IF(N35="-", "-", IF(P35="-", "-", IF(ABS(P35)=0, "-", ROUND(100*(N35-P35)/ABS(P35), 1)))) -> - | S35: =IF(O35="-", "-", IF(Q35="-", "-", IF(ABS(Q35)=0, "-", ROUND(100*(O35-Q35)/ABS(Q35), 1)))) -> - | AB35: =IF(T35="-", "-", IF(X35="-", "-", IF(ABS(X35)=0, "-", ROUND(100*(T35-X35)/ABS(X35), 10)))) -> - | AC35: =IF(Y35="-", "-", IF(AA35="-", "-", IF(ABS(AA35)=0, "-", ROUND(100*(Y35-AA35)/ABS(AA35), 1)))) -> - | AD35: =IF(Z35="-", "-", IF(AB35="-", "-", IF(ABS(AB35)=0, "-", ROUND(100*(Z35-AB35)/ABS(AB35), 1)))) -> - | AM35: =IF(AE35="-", "-", IF(AI35="-", "-", IF(ABS(AI35)=0, "-", ROUND(100*(AE35-AI35)/ABS(AI35), 10)))) -> - | AN35: =IF(AJ35="-", "-", IF(AL35="-", "-", IF(ABS(AL35)=0, "-", ROUND(100*(AJ35-AL35)/ABS(AL35), 1)))) -> - | AO35: =IF(AK35="-", "-", IF(AM35="-", "-", IF(ABS(AM35)=0, "-", ROUND(100*(AK35-AM35)/ABS(AM35), 1)))) -> -
B36: 計 | Q36: =IF(I36="-", "-", IF(M36="-", "-", IF(ABS(M36)=0, "-", ROUND(100*(I36-M36)/ABS(M36), 10)))) -> - | R36: =IF(N36="-", "-", IF(P36="-", "-", IF(ABS(P36)=0, "-", ROUND(100*(N36-P36)/ABS(P36), 1)))) -> - | S36: =IF(O36="-", "-", IF(Q36="-", "-", IF(ABS(Q36)=0, "-", ROUND(100*(O36-Q36)/ABS(Q36), 1)))) -> - | AB36: =IF(T36="-", "-", IF(X36="-", "-", IF(ABS(X36)=0, "-", ROUND(100*(T36-X36)/ABS(X36), 10)))) -> - | AC36: =IF(Y36="-", "-", IF(AA36="-", "-", IF(ABS(AA36)=0, "-", ROUND(100*(Y36-AA36)/ABS(AA36), 1)))) -> - | AD36: =IF(Z36="-", "-", IF(AB36="-", "-", IF(ABS(AB36)=0, "-", ROUND(100*(Z36-AB36)/ABS(AB36), 1)))) -> - | AM36: =IF(AE36="-", "-", IF(AI36="-", "-", IF(ABS(AI36)=0, "-", ROUND(100*(AE36-AI36)/ABS(AI36), 10)))) -> - | AN36: =IF(AJ36="-", "-", IF(AL36="-", "-", IF(ABS(AL36)=0, "-", ROUND(100*(AJ36-AL36)/ABS(AL36), 1)))) -> - | AO36: =IF(AK36="-", "-", IF(AM36="-", "-", IF(ABS(AM36)=0, "-", ROUND(100*(AK36-AM36)/ABS(AM36), 1)))) -> -
B39: 20 構成員数等（１経営体当たり） | AT39: 21 労働時間及び労働費 | BV39: 単位：時間、円
I40: =IF($B$1<>"",$B$1,"") | M40: =IF($B$1<>"",$B$1-1,"") | Q40: 増減率 | BA40: 労働時間 | BL40: 労働費
B41: 構成員（人） | Q41: =IF(I41="-", "-", IF(M41="-", "-", IF(ABS(M41)=0, "-", ROUND(100*(I41-M41)/ABS(M41), 10)))) -> - | R41: =IF(N41="-", "-", IF(P41="-", "-", IF(ABS(P41)=0, "-", ROUND(100*(N41-P41)/ABS(P41), 1)))) -> - | S41: =IF(O41="-", "-", IF(Q41="-", "-", IF(ABS(Q41)=0, "-", ROUND(100*(O41-Q41)/ABS(Q41), 1)))) -> - | BA41: =IF($B$1<>"",$B$1,"") | BE41: =IF($B$1<>"",$B$1-1,"") | BI41: 増減率 | BL41: =IF($B$1<>"",$B$1,"") | BP41: =IF($B$1<>"",$B$1-1,"") | BT41: 増減率
B42: 農業年雇（人） | Q42: =IF(I42="-", "-", IF(M42="-", "-", IF(ABS(M42)=0, "-", ROUND(100*(I42-M42)/ABS(M42), 10)))) -> - | R42: =IF(N42="-", "-", IF(P42="-", "-", IF(ABS(P42)=0, "-", ROUND(100*(N42-P42)/ABS(P42), 1)))) -> - | S42: =IF(O42="-", "-", IF(Q42="-", "-", IF(ABS(Q42)=0, "-", ROUND(100*(O42-Q42)/ABS(Q42), 1)))) -> - | AT42: 稲作負担分 | AU42: 構成員 | BI42: =IF(BA42="-", "-", IF(BE42="-", "-", IF(ABS(BE42)=0, "-", ROUND(100*(BA42-BE42)/ABS(BE42), 10)))) -> - | BJ42: =IF(BF42="-", "-", IF(BH42="-", "-", IF(ABS(BH42)=0, "-", ROUND(100*(BF42-BH42)/ABS(BH42), 1)))) -> - | BK42: =IF(BG42="-", "-", IF(BI42="-", "-", IF(ABS(BI42)=0, "-", ROUND(100*(BG42-BI42)/ABS(BI42), 1)))) -> - | BT42: =IF(BL42="-", "-", IF(BP42="-", "-", IF(ABS(BP42)=0, "-", ROUND(100*(BL42-BP42)/ABS(BP42), 10)))) -> - | BU42: =IF(BQ42="-", "-", IF(BS42="-", "-", IF(ABS(BS42)=0, "-", ROUND(100*(BQ42-BS42)/ABS(BS42), 1)))) -> - | BV42: =IF(BR42="-", "-", IF(BT42="-", "-", IF(ABS(BT42)=0, "-", ROUND(100*(BR42-BT42)/ABS(BT42), 1)))) -> -
B43: 構成農家世帯（戸） | Q43: =IF(I43="-", "-", IF(M43="-", "-", IF(ABS(M43)=0, "-", ROUND(100*(I43-M43)/ABS(M43), 10)))) -> - | R43: =IF(N43="-", "-", IF(P43="-", "-", IF(ABS(P43)=0, "-", ROUND(100*(N43-P43)/ABS(P43), 1)))) -> - | S43: =IF(O43="-", "-", IF(Q43="-", "-", IF(ABS(Q43)=0, "-", ROUND(100*(O43-Q43)/ABS(Q43), 1)))) -> - | AV43: 直接労働 | BI43: =IF(BA43="-", "-", IF(BE43="-", "-", IF(ABS(BE43)=0, "-", ROUND(100*(BA43-BE43)/ABS(BE43), 10)))) -> - | BJ43: =IF(BF43="-", "-", IF(BH43="-", "-", IF(ABS(BH43)=0, "-", ROUND(100*(BF43-BH43)/ABS(BH43), 1)))) -> - | BK43: =IF(BG43="-", "-", IF(BI43="-", "-", IF(ABS(BI43)=0, "-", ROUND(100*(BG43-BI43)/ABS(BI43), 1)))) -> - | BT43: =IF(BL43="-", "-", IF(BP43="-", "-", IF(ABS(BP43)=0, "-", ROUND(100*(BL43-BP43)/ABS(BP43), 10)))) -> - | BU43: =IF(BQ43="-", "-", IF(BS43="-", "-", IF(ABS(BS43)=0, "-", ROUND(100*(BQ43-BS43)/ABS(BS43), 1)))) -> - | BV43: =IF(BR43="-", "-", IF(BT43="-", "-", IF(ABS(BT43)=0, "-", ROUND(100*(BR43-BT43)/ABS(BT43), 1)))) -> -
AV44: 間接労働 | BI44: =IF(BA44="-", "-", IF(BE44="-", "-", IF(ABS(BE44)=0, "-", ROUND(100*(BA44-BE44)/ABS(BE44), 10)))) -> - | BJ44: =IF(BF44="-", "-", IF(BH44="-", "-", IF(ABS(BH44)=0, "-", ROUND(100*(BF44-BH44)/ABS(BH44), 1)))) -> - | BK44: =IF(BG44="-", "-", IF(BI44="-", "-", IF(ABS(BI44)=0, "-", ROUND(100*(BG44-BI44)/ABS(BI44), 1)))) -> - | BT44: =IF(BL44="-", "-", IF(BP44="-", "-", IF(ABS(BP44)=0, "-", ROUND(100*(BL44-BP44)/ABS(BP44), 10)))) -> - | BU44: =IF(BQ44="-", "-", IF(BS44="-", "-", IF(ABS(BS44)=0, "-", ROUND(100*(BQ44-BS44)/ABS(BS44), 1)))) -> - | BV44: =IF(BR44="-", "-", IF(BT44="-", "-", IF(ABS(BT44)=0, "-", ROUND(100*(BR44-BT44)/ABS(BT44), 1)))) -> -
AU45: 雇用 | BI45: =IF(BA45="-", "-", IF(BE45="-", "-", IF(ABS(BE45)=0, "-", ROUND(100*(BA45-BE45)/ABS(BE45), 10)))) -> - | BJ45: =IF(BF45="-", "-", IF(BH45="-", "-", IF(ABS(BH45)=0, "-", ROUND(100*(BF45-BH45)/ABS(BH45), 1)))) -> - | BK45: =IF(BG45="-", "-", IF(BI45="-", "-", IF(ABS(BI45)=0, "-", ROUND(100*(BG45-BI45)/ABS(BI45), 1)))) -> - | BT45: =IF(BL45="-", "-", IF(BP45="-", "-", IF(ABS(BP45)=0, "-", ROUND(100*(BL45-BP45)/ABS(BP45), 10)))) -> - | BU45: =IF(BQ45="-", "-", IF(BS45="-", "-", IF(ABS(BS45)=0, "-", ROUND(100*(BQ45-BS45)/ABS(BS45), 1)))) -> - | BV45: =IF(BR45="-", "-", IF(BT45="-", "-", IF(ABS(BT45)=0, "-", ROUND(100*(BR45-BT45)/ABS(BT45), 1)))) -> -
AV46: 直接労働 | BI46: =IF(BA46="-", "-", IF(BE46="-", "-", IF(ABS(BE46)=0, "-", ROUND(100*(BA46-BE46)/ABS(BE46), 10)))) -> - | BJ46: =IF(BF46="-", "-", IF(BH46="-", "-", IF(ABS(BH46)=0, "-", ROUND(100*(BF46-BH46)/ABS(BH46), 1)))) -> - | BK46: =IF(BG46="-", "-", IF(BI46="-", "-", IF(ABS(BI46)=0, "-", ROUND(100*(BG46-BI46)/ABS(BI46), 1)))) -> - | BT46: =IF(BL46="-", "-", IF(BP46="-", "-", IF(ABS(BP46)=0, "-", ROUND(100*(BL46-BP46)/ABS(BP46), 10)))) -> - | BU46: =IF(BQ46="-", "-", IF(BS46="-", "-", IF(ABS(BS46)=0, "-", ROUND(100*(BQ46-BS46)/ABS(BS46), 1)))) -> - | BV46: =IF(BR46="-", "-", IF(BT46="-", "-", IF(ABS(BT46)=0, "-", ROUND(100*(BR46-BT46)/ABS(BT46), 1)))) -> -
AV47: 間接労働 | BI47: =IF(BA47="-", "-", IF(BE47="-", "-", IF(ABS(BE47)=0, "-", ROUND(100*(BA47-BE47)/ABS(BE47), 10)))) -> - | BJ47: =IF(BF47="-", "-", IF(BH47="-", "-", IF(ABS(BH47)=0, "-", ROUND(100*(BF47-BH47)/ABS(BH47), 1)))) -> - | BK47: =IF(BG47="-", "-", IF(BI47="-", "-", IF(ABS(BI47)=0, "-", ROUND(100*(BG47-BI47)/ABS(BI47), 1)))) -> - | BT47: =IF(BL47="-", "-", IF(BP47="-", "-", IF(ABS(BP47)=0, "-", ROUND(100*(BL47-BP47)/ABS(BP47), 10)))) -> - | BU47: =IF(BQ47="-", "-", IF(BS47="-", "-", IF(ABS(BS47)=0, "-", ROUND(100*(BQ47-BS47)/ABS(BS47), 1)))) -> - | BV47: =IF(BR47="-", "-", IF(BT47="-", "-", IF(ABS(BT47)=0, "-", ROUND(100*(BR47-BT47)/ABS(BT47), 1)))) -> -
AU48: 合計 | BI48: =IF(BA48="-", "-", IF(BE48="-", "-", IF(ABS(BE48)=0, "-", ROUND(100*(BA48-BE48)/ABS(BE48), 10)))) -> - | BJ48: =IF(BF48="-", "-", IF(BH48="-", "-", IF(ABS(BH48)=0, "-", ROUND(100*(BF48-BH48)/ABS(BH48), 1)))) -> - | BK48: =IF(BG48="-", "-", IF(BI48="-", "-", IF(ABS(BI48)=0, "-", ROUND(100*(BG48-BI48)/ABS(BI48), 1)))) -> - | BT48: =IF(BL48="-", "-", IF(BP48="-", "-", IF(ABS(BP48)=0, "-", ROUND(100*(BL48-BP48)/ABS(BP48), 10)))) -> - | BU48: =IF(BQ48="-", "-", IF(BS48="-", "-", IF(ABS(BS48)=0, "-", ROUND(100*(BQ48-BS48)/ABS(BS48), 1)))) -> - | BV48: =IF(BR48="-", "-", IF(BT48="-", "-", IF(ABS(BT48)=0, "-", ROUND(100*(BR48-BT48)/ABS(BT48), 1)))) -> -
AV49: 直接労働 | BI49: =IF(BA49="-", "-", IF(BE49="-", "-", IF(ABS(BE49)=0, "-", ROUND(100*(BA49-BE49)/ABS(BE49), 10)))) -> - | BJ49: =IF(BF49="-", "-", IF(BH49="-", "-", IF(ABS(BH49)=0, "-", ROUND(100*(BF49-BH49)/ABS(BH49), 1)))) -> - | BK49: =IF(BG49="-", "-", IF(BI49="-", "-", IF(ABS(BI49)=0, "-", ROUND(100*(BG49-BI49)/ABS(BI49), 1)))) -> - | BT49: =IF(BL49="-", "-", IF(BP49="-", "-", IF(ABS(BP49)=0, "-", ROUND(100*(BL49-BP49)/ABS(BP49), 10)))) -> - | BU49: =IF(BQ49="-", "-", IF(BS49="-", "-", IF(ABS(BS49)=0, "-", ROUND(100*(BQ49-BS49)/ABS(BS49), 1)))) -> - | BV49: =IF(BR49="-", "-", IF(BT49="-", "-", IF(ABS(BT49)=0, "-", ROUND(100*(BR49-BT49)/ABS(BT49), 1)))) -> -
AV50: 間接労働 | BI50: =IF(BA50="-", "-", IF(BE50="-", "-", IF(ABS(BE50)=0, "-", ROUND(100*(BA50-BE50)/ABS(BE50), 10)))) -> - | BJ50: =IF(BF50="-", "-", IF(BH50="-", "-", IF(ABS(BH50)=0, "-", ROUND(100*(BF50-BH50)/ABS(BH50), 1)))) -> - | BK50: =IF(BG50="-", "-", IF(BI50="-", "-", IF(ABS(BI50)=0, "-", ROUND(100*(BG50-BI50)/ABS(BI50), 1)))) -> - | BT50: =IF(BL50="-", "-", IF(BP50="-", "-", IF(ABS(BP50)=0, "-", ROUND(100*(BL50-BP50)/ABS(BP50), 10)))) -> - | BU50: =IF(BQ50="-", "-", IF(BS50="-", "-", IF(ABS(BS50)=0, "-", ROUND(100*(BQ50-BS50)/ABS(BS50), 1)))) -> - | BV50: =IF(BR50="-", "-", IF(BT50="-", "-", IF(ABS(BT50)=0, "-", ROUND(100*(BR50-BT50)/ABS(BT50), 1)))) -> -

Sheet No.4
B1: =AB4 | E1: 年産 米生産費統計結果（組織法人経営体） 集計結果検討表 Ｎｏ．４
G3: 集計番号 | J3: 集計名称 | Q3: 集計経営体数 | V3: 集計倍率 | AB3: 調査年 | AG3: 都道府県等 | AL3: 経営種類 | AQ3: 生産費区分 | AV3: 規模階層 | BA3: 平均値種類 | BF3: 加重・総和の別 | BK3: 集計区分
B4: 本年産 | G4: =IF(No.1!G4="","",No.1!G4) | J4: =IF(No.1!J4="","",No.1!J4) | Q4: =IF(No.1!Q4="","",No.1!Q4) | V4: =IF(No.1!V4="","",No.1!V4) | AB4: =IF(No.1!AB4="","",No.1!AB4) | AG4: =IF(No.1!AG4="","",No.1!AG4) | AH4: =IF(No.1!AH4="","",No.1!AH4) | AI4: =IF(No.1!AI4="","",No.1!AI4) | AJ4: =IF(No.1!AJ4="","",No.1!AJ4) | AK4: =IF(No.1!AK4="","",No.1!AK4) | AL4: =IF(No.1!AL4="","",No.1!AL4) | AM4: =IF(No.1!AM4="","",No.1!AM4) | AN4: =IF(No.1!AN4="","",No.1!AN4) | ... BO4: =IF(No.1!BO4="","",No.1!BO4)
B5: 前年産 | G5: =IF(No.1!G5="","",No.1!G5) | J5: =IF(No.1!J5="","",No.1!J5) | Q5: =IF(No.1!Q5="","",No.1!Q5) | V5: =IF(No.1!V5="","",No.1!V5)
B7: 22 原単位 | AP7: 単位：円、kg、ａ、Ｌ | AT7: 22 原単位（続き） | CH7: 単位：円、ａ、kg
J8: 数量 | U8: 価額 | AF8: 単価 | BB8: 数量 | BM8: 価額 | BX8: 単価
J9: =IF($B$1<>"",$B$1,"") | N9: =IF($B$1<>"",$B$1-1,"") | R9: 増減率 | U9: =IF($B$1<>"",$B$1,"") | Y9: =IF($B$1<>"",$B$1-1,"") | AC9: 増減率 | AF9: =IF($B$1<>"",$B$1,"") | AJ9: =IF($B$1<>"",$B$1-1,"") | AN9: 増減率 | BB9: =IF($B$1<>"",$B$1,"") | BF9: =IF($B$1<>"",$B$1-1,"") | BJ9: 増減率 | BM9: =IF($B$1<>"",$B$1,"") | BQ9: =IF($B$1<>"",$B$1-1,"") | BU9: 増減率 | BX9: =IF($B$1<>"",$B$1,"") | CB9: =IF($B$1<>"",$B$1-1,"") | CF9: 増減率
B10: 種苗費 | D10: 種子 もみ | F10: 購入 | R10: =IF(J10="-", "-", IF(N10="-", "-", IF(ABS(N10)=0, "-", ROUND(100*(J10-N10)/ABS(N10), 10)))) -> - | S10: =IF(O10="-", "-", IF(Q10="-", "-", IF(ABS(Q10)=0, "-", ROUND(100*(O10-Q10)/ABS(Q10), 1)))) -> - | T10: =IF(P10="-", "-", IF(R10="-", "-", IF(ABS(R10)=0, "-", ROUND(100*(P10-R10)/ABS(R10), 1)))) -> - | AC10: =IF(U10="-", "-", IF(Y10="-", "-", IF(ABS(Y10)=0, "-", ROUND(100*(U10-Y10)/ABS(Y10), 10)))) -> - | AD10: =IF(Z10="-", "-", IF(AB10="-", "-", IF(ABS(AB10)=0, "-", ROUND(100*(Z10-AB10)/ABS(AB10), 1)))) -> - | AE10: =IF(AA10="-", "-", IF(AC10="-", "-", IF(ABS(AC10)=0, "-", ROUND(100*(AA10-AC10)/ABS(AC10), 1)))) -> - | AN10: =IF(AF10="-", "-", IF(AJ10="-", "-", IF(ABS(AJ10)=0, "-", ROUND(100*(AF10-AJ10)/ABS(AJ10), 10)))) -> - | AO10: =IF(AK10="-", "-", IF(AM10="-", "-", IF(ABS(AM10)=0, "-", ROUND(100*(AK10-AM10)/ABS(AM10), 1)))) -> - | AP10: =IF(AL10="-", "-", IF(AN10="-", "-", IF(ABS(AN10)=0, "-", ROUND(100*(AL10-AN10)/ABS(AN10), 1)))) -> - | AT10: 賃借料及び料金 | AV10: 共 同 負担金 | AX10: 薬剤散布 | BU10: =IF(BM10="-", "-", IF(BQ10="-", "-", IF(ABS(BQ10)=0, "-", ROUND(100*(BM10-BQ10)/ABS(BQ10), 10)))) -> - | BV10: =IF(BR10="-", "-", IF(BT10="-", "-", IF(ABS(BT10)=0, "-", ROUND(100*(BR10-BT10)/ABS(BT10), 1)))) -> - | BW10: =IF(BS10="-", "-", IF(BU10="-", "-", IF(ABS(BU10)=0, "-", ROUND(100*(BS10-BU10)/ABS(BU10), 1)))) -> -
F11: 自給 | R11: =IF(J11="-", "-", IF(N11="-", "-", IF(ABS(N11)=0, "-", ROUND(100*(J11-N11)/ABS(N11), 10)))) -> - | S11: =IF(O11="-", "-", IF(Q11="-", "-", IF(ABS(Q11)=0, "-", ROUND(100*(O11-Q11)/ABS(Q11), 1)))) -> - | T11: =IF(P11="-", "-", IF(R11="-", "-", IF(ABS(R11)=0, "-", ROUND(100*(P11-R11)/ABS(R11), 1)))) -> - | AC11: =IF(U11="-", "-", IF(Y11="-", "-", IF(ABS(Y11)=0, "-", ROUND(100*(U11-Y11)/ABS(Y11), 10)))) -> - | AD11: =IF(Z11="-", "-", IF(AB11="-", "-", IF(ABS(AB11)=0, "-", ROUND(100*(Z11-AB11)/ABS(AB11), 1)))) -> - | AE11: =IF(AA11="-", "-", IF(AC11="-", "-", IF(ABS(AC11)=0, "-", ROUND(100*(AA11-AC11)/ABS(AC11), 1)))) -> - | AN11: =IF(AF11="-", "-", IF(AJ11="-", "-", IF(ABS(AJ11)=0, "-", ROUND(100*(AF11-AJ11)/ABS(AJ11), 10)))) -> - | AO11: =IF(AK11="-", "-", IF(AM11="-", "-", IF(ABS(AM11)=0, "-", ROUND(100*(AK11-AM11)/ABS(AM11), 1)))) -> - | AP11: =IF(AL11="-", "-", IF(AN11="-", "-", IF(ABS(AN11)=0, "-", ROUND(100*(AL11-AN11)/ABS(AN11), 1)))) -> - | AX11: 共同施設 | BU11: =IF(BM11="-", "-", IF(BQ11="-", "-", IF(ABS(BQ11)=0, "-", ROUND(100*(BM11-BQ11)/ABS(BQ11), 10)))) -> - | BV11: =IF(BR11="-", "-", IF(BT11="-", "-", IF(ABS(BT11)=0, "-", ROUND(100*(BR11-BT11)/ABS(BT11), 1)))) -> - | BW11: =IF(BS11="-", "-", IF(BU11="-", "-", IF(ABS(BU11)=0, "-", ROUND(100*(BS11-BU11)/ABS(BU11), 1)))) -> -
D12: 苗 | R12: =IF(J12="-", "-", IF(N12="-", "-", IF(ABS(N12)=0, "-", ROUND(100*(J12-N12)/ABS(N12), 10)))) -> - | S12: =IF(O12="-", "-", IF(Q12="-", "-", IF(ABS(Q12)=0, "-", ROUND(100*(O12-Q12)/ABS(Q12), 1)))) -> - | T12: =IF(P12="-", "-", IF(R12="-", "-", IF(ABS(R12)=0, "-", ROUND(100*(P12-R12)/ABS(R12), 1)))) -> - | AC12: =IF(U12="-", "-", IF(Y12="-", "-", IF(ABS(Y12)=0, "-", ROUND(100*(U12-Y12)/ABS(Y12), 10)))) -> - | AD12: =IF(Z12="-", "-", IF(AB12="-", "-", IF(ABS(AB12)=0, "-", ROUND(100*(Z12-AB12)/ABS(AB12), 1)))) -> - | AE12: =IF(AA12="-", "-", IF(AC12="-", "-", IF(ABS(AC12)=0, "-", ROUND(100*(AA12-AC12)/ABS(AC12), 1)))) -> - | AN12: =IF(AF12="-", "-", IF(AJ12="-", "-", IF(ABS(AJ12)=0, "-", ROUND(100*(AF12-AJ12)/ABS(AJ12), 10)))) -> - | AO12: =IF(AK12="-", "-", IF(AM12="-", "-", IF(ABS(AM12)=0, "-", ROUND(100*(AK12-AM12)/ABS(AM12), 1)))) -> - | AP12: =IF(AL12="-", "-", IF(AN12="-", "-", IF(ABS(AN12)=0, "-", ROUND(100*(AL12-AN12)/ABS(AN12), 1)))) -> - | AX12: 共同苗代 | BU12: =IF(BM12="-", "-", IF(BQ12="-", "-", IF(ABS(BQ12)=0, "-", ROUND(100*(BM12-BQ12)/ABS(BQ12), 10)))) -> - | BV12: =IF(BR12="-", "-", IF(BT12="-", "-", IF(ABS(BT12)=0, "-", ROUND(100*(BR12-BT12)/ABS(BT12), 1)))) -> - | BW12: =IF(BS12="-", "-", IF(BU12="-", "-", IF(ABS(BU12)=0, "-", ROUND(100*(BS12-BU12)/ABS(BU12), 1)))) -> -
D13: 計 | AC13: =IF(U13="-", "-", IF(Y13="-", "-", IF(ABS(Y13)=0, "-", ROUND(100*(U13-Y13)/ABS(Y13), 10)))) -> - | AD13: =IF(Z13="-", "-", IF(AB13="-", "-", IF(ABS(AB13)=0, "-", ROUND(100*(Z13-AB13)/ABS(AB13), 1)))) -> - | AE13: =IF(AA13="-", "-", IF(AC13="-", "-", IF(ABS(AC13)=0, "-", ROUND(100*(AA13-AC13)/ABS(AC13), 1)))) -> - | AV13: 農機具借料 | BU13: =IF(BM13="-", "-", IF(BQ13="-", "-", IF(ABS(BQ13)=0, "-", ROUND(100*(BM13-BQ13)/ABS(BQ13), 10)))) -> - | BV13: =IF(BR13="-", "-", IF(BT13="-", "-", IF(ABS(BT13)=0, "-", ROUND(100*(BR13-BT13)/ABS(BT13), 1)))) -> - | BW13: =IF(BS13="-", "-", IF(BU13="-", "-", IF(ABS(BU13)=0, "-", ROUND(100*(BS13-BU13)/ABS(BU13), 1)))) -> -
B14: 肥料費 | D14: 窒素質肥料 | R14: =IF(J14="-", "-", IF(N14="-", "-", IF(ABS(N14)=0, "-", ROUND(100*(J14-N14)/ABS(N14), 10)))) -> - | S14: =IF(O14="-", "-", IF(Q14="-", "-", IF(ABS(Q14)=0, "-", ROUND(100*(O14-Q14)/ABS(Q14), 1)))) -> - | T14: =IF(P14="-", "-", IF(R14="-", "-", IF(ABS(R14)=0, "-", ROUND(100*(P14-R14)/ABS(R14), 1)))) -> - | AC14: =IF(U14="-", "-", IF(Y14="-", "-", IF(ABS(Y14)=0, "-", ROUND(100*(U14-Y14)/ABS(Y14), 10)))) -> - | AD14: =IF(Z14="-", "-", IF(AB14="-", "-", IF(ABS(AB14)=0, "-", ROUND(100*(Z14-AB14)/ABS(AB14), 1)))) -> - | AE14: =IF(AA14="-", "-", IF(AC14="-", "-", IF(ABS(AC14)=0, "-", ROUND(100*(AA14-AC14)/ABS(AC14), 1)))) -> - | AN14: =IF(AF14="-", "-", IF(AJ14="-", "-", IF(ABS(AJ14)=0, "-", ROUND(100*(AF14-AJ14)/ABS(AJ14), 10)))) -> - | AO14: =IF(AK14="-", "-", IF(AM14="-", "-", IF(ABS(AM14)=0, "-", ROUND(100*(AK14-AM14)/ABS(AM14), 1)))) -> - | AP14: =IF(AL14="-", "-", IF(AN14="-", "-", IF(ABS(AN14)=0, "-", ROUND(100*(AL14-AN14)/ABS(AN14), 1)))) -> - | AV14: 航空防除賃 | BJ14: =IF(BB14="-", "-", IF(BF14="-", "-", IF(ABS(BF14)=0, "-", ROUND(100*(BB14-BF14)/ABS(BF14), 10)))) -> - | BK14: =IF(BG14="-", "-", IF(BI14="-", "-", IF(ABS(BI14)=0, "-", ROUND(100*(BG14-BI14)/ABS(BI14), 1)))) -> - | BL14: =IF(BH14="-", "-", IF(BJ14="-", "-", IF(ABS(BJ14)=0, "-", ROUND(100*(BH14-BJ14)/ABS(BJ14), 1)))) -> - | BU14: =IF(BM14="-", "-", IF(BQ14="-", "-", IF(ABS(BQ14)=0, "-", ROUND(100*(BM14-BQ14)/ABS(BQ14), 10)))) -> - | BV14: =IF(BR14="-", "-", IF(BT14="-", "-", IF(ABS(BT14)=0, "-", ROUND(100*(BR14-BT14)/ABS(BT14), 1)))) -> - | BW14: =IF(BS14="-", "-", IF(BU14="-", "-", IF(ABS(BU14)=0, "-", ROUND(100*(BS14-BU14)/ABS(BU14), 1)))) -> - | CF14: =IF(BX14="-", "-", IF(CB14="-", "-", IF(ABS(CB14)=0, "-", ROUND(100*(BX14-CB14)/ABS(CB14), 10)))) -> - | CG14: =IF(CC14="-", "-", IF(CE14="-", "-", IF(ABS(CE14)=0, "-", ROUND(100*(CC14-CE14)/ABS(CE14), 1)))) -> - | CH14: =IF(CD14="-", "-", IF(CF14="-", "-", IF(ABS(CF14)=0, "-", ROUND(100*(CD14-CF14)/ABS(CF14), 1)))) -> -
D15: りん酸質肥料 | R15: =IF(J15="-", "-", IF(N15="-", "-", IF(ABS(N15)=0, "-", ROUND(100*(J15-N15)/ABS(N15), 10)))) -> - | S15: =IF(O15="-", "-", IF(Q15="-", "-", IF(ABS(Q15)=0, "-", ROUND(100*(O15-Q15)/ABS(Q15), 1)))) -> - | T15: =IF(P15="-", "-", IF(R15="-", "-", IF(ABS(R15)=0, "-", ROUND(100*(P15-R15)/ABS(R15), 1)))) -> - | AC15: =IF(U15="-", "-", IF(Y15="-", "-", IF(ABS(Y15)=0, "-", ROUND(100*(U15-Y15)/ABS(Y15), 10)))) -> - | AD15: =IF(Z15="-", "-", IF(AB15="-", "-", IF(ABS(AB15)=0, "-", ROUND(100*(Z15-AB15)/ABS(AB15), 1)))) -> - | AE15: =IF(AA15="-", "-", IF(AC15="-", "-", IF(ABS(AC15)=0, "-", ROUND(100*(AA15-AC15)/ABS(AC15), 1)))) -> - | AN15: =IF(AF15="-", "-", IF(AJ15="-", "-", IF(ABS(AJ15)=0, "-", ROUND(100*(AF15-AJ15)/ABS(AJ15), 10)))) -> - | AO15: =IF(AK15="-", "-", IF(AM15="-", "-", IF(ABS(AM15)=0, "-", ROUND(100*(AK15-AM15)/ABS(AM15), 1)))) -> - | AP15: =IF(AL15="-", "-", IF(AN15="-", "-", IF(ABS(AN15)=0, "-", ROUND(100*(AL15-AN15)/ABS(AN15), 1)))) -> - | AV15: 賃耕料 | BJ15: =IF(BB15="-", "-", IF(BF15="-", "-", IF(ABS(BF15)=0, "-", ROUND(100*(BB15-BF15)/ABS(BF15), 10)))) -> - | BK15: =IF(BG15="-", "-", IF(BI15="-", "-", IF(ABS(BI15)=0, "-", ROUND(100*(BG15-BI15)/ABS(BI15), 1)))) -> - | BL15: =IF(BH15="-", "-", IF(BJ15="-", "-", IF(ABS(BJ15)=0, "-", ROUND(100*(BH15-BJ15)/ABS(BJ15), 1)))) -> - | BU15: =IF(BM15="-", "-", IF(BQ15="-", "-", IF(ABS(BQ15)=0, "-", ROUND(100*(BM15-BQ15)/ABS(BQ15), 10)))) -> - | BV15: =IF(BR15="-", "-", IF(BT15="-", "-", IF(ABS(BT15)=0, "-", ROUND(100*(BR15-BT15)/ABS(BT15), 1)))) -> - | BW15: =IF(BS15="-", "-", IF(BU15="-", "-", IF(ABS(BU15)=0, "-", ROUND(100*(BS15-BU15)/ABS(BU15), 1)))) -> - | CF15: =IF(BX15="-", "-", IF(CB15="-", "-", IF(ABS(CB15)=0, "-", ROUND(100*(BX15-CB15)/ABS(CB15), 10)))) -> - | CG15: =IF(CC15="-", "-", IF(CE15="-", "-", IF(ABS(CE15)=0, "-", ROUND(100*(CC15-CE15)/ABS(CE15), 1)))) -> - | CH15: =IF(CD15="-", "-", IF(CF15="-", "-", IF(ABS(CF15)=0, "-", ROUND(100*(CD15-CF15)/ABS(CF15), 1)))) -> -
D16: カリ質肥料 | R16: =IF(J16="-", "-", IF(N16="-", "-", IF(ABS(N16)=0, "-", ROUND(100*(J16-N16)/ABS(N16), 10)))) -> - | S16: =IF(O16="-", "-", IF(Q16="-", "-", IF(ABS(Q16)=0, "-", ROUND(100*(O16-Q16)/ABS(Q16), 1)))) -> - | T16: =IF(P16="-", "-", IF(R16="-", "-", IF(ABS(R16)=0, "-", ROUND(100*(P16-R16)/ABS(R16), 1)))) -> - | AC16: =IF(U16="-", "-", IF(Y16="-", "-", IF(ABS(Y16)=0, "-", ROUND(100*(U16-Y16)/ABS(Y16), 10)))) -> - | AD16: =IF(Z16="-", "-", IF(AB16="-", "-", IF(ABS(AB16)=0, "-", ROUND(100*(Z16-AB16)/ABS(AB16), 1)))) -> - | AE16: =IF(AA16="-", "-", IF(AC16="-", "-", IF(ABS(AC16)=0, "-", ROUND(100*(AA16-AC16)/ABS(AC16), 1)))) -> - | AN16: =IF(AF16="-", "-", IF(AJ16="-", "-", IF(ABS(AJ16)=0, "-", ROUND(100*(AF16-AJ16)/ABS(AJ16), 10)))) -> - | AO16: =IF(AK16="-", "-", IF(AM16="-", "-", IF(ABS(AM16)=0, "-", ROUND(100*(AK16-AM16)/ABS(AM16), 1)))) -> - | AP16: =IF(AL16="-", "-", IF(AN16="-", "-", IF(ABS(AN16)=0, "-", ROUND(100*(AL16-AN16)/ABS(AN16), 1)))) -> - | AV16: は種・田植賃 | BJ16: =IF(BB16="-", "-", IF(BF16="-", "-", IF(ABS(BF16)=0, "-", ROUND(100*(BB16-BF16)/ABS(BF16), 10)))) -> - | BK16: =IF(BG16="-", "-", IF(BI16="-", "-", IF(ABS(BI16)=0, "-", ROUND(100*(BG16-BI16)/ABS(BI16), 1)))) -> - | BL16: =IF(BH16="-", "-", IF(BJ16="-", "-", IF(ABS(BJ16)=0, "-", ROUND(100*(BH16-BJ16)/ABS(BJ16), 1)))) -> - | BU16: =IF(BM16="-", "-", IF(BQ16="-", "-", IF(ABS(BQ16)=0, "-", ROUND(100*(BM16-BQ16)/ABS(BQ16), 10)))) -> - | BV16: =IF(BR16="-", "-", IF(BT16="-", "-", IF(ABS(BT16)=0, "-", ROUND(100*(BR16-BT16)/ABS(BT16), 1)))) -> - | BW16: =IF(BS16="-", "-", IF(BU16="-", "-", IF(ABS(BU16)=0, "-", ROUND(100*(BS16-BU16)/ABS(BU16), 1)))) -> - | CF16: =IF(BX16="-", "-", IF(CB16="-", "-", IF(ABS(CB16)=0, "-", ROUND(100*(BX16-CB16)/ABS(CB16), 10)))) -> - | CG16: =IF(CC16="-", "-", IF(CE16="-", "-", IF(ABS(CE16)=0, "-", ROUND(100*(CC16-CE16)/ABS(CE16), 1)))) -> - | CH16: =IF(CD16="-", "-", IF(CF16="-", "-", IF(ABS(CF16)=0, "-", ROUND(100*(CD16-CF16)/ABS(CF16), 1)))) -> -
D17: けい酸質肥料 | R17: =IF(J17="-", "-", IF(N17="-", "-", IF(ABS(N17)=0, "-", ROUND(100*(J17-N17)/ABS(N17), 10)))) -> - | S17: =IF(O17="-", "-", IF(Q17="-", "-", IF(ABS(Q17)=0, "-", ROUND(100*(O17-Q17)/ABS(Q17), 1)))) -> - | T17: =IF(P17="-", "-", IF(R17="-", "-", IF(ABS(R17)=0, "-", ROUND(100*(P17-R17)/ABS(R17), 1)))) -> - | AC17: =IF(U17="-", "-", IF(Y17="-", "-", IF(ABS(Y17)=0, "-", ROUND(100*(U17-Y17)/ABS(Y17), 10)))) -> - | AD17: =IF(Z17="-", "-", IF(AB17="-", "-", IF(ABS(AB17)=0, "-", ROUND(100*(Z17-AB17)/ABS(AB17), 1)))) -> - | AE17: =IF(AA17="-", "-", IF(AC17="-", "-", IF(ABS(AC17)=0, "-", ROUND(100*(AA17-AC17)/ABS(AC17), 1)))) -> - | AN17: =IF(AF17="-", "-", IF(AJ17="-", "-", IF(ABS(AJ17)=0, "-", ROUND(100*(AF17-AJ17)/ABS(AJ17), 10)))) -> - | AO17: =IF(AK17="-", "-", IF(AM17="-", "-", IF(ABS(AM17)=0, "-", ROUND(100*(AK17-AM17)/ABS(AM17), 1)))) -> - | AP17: =IF(AL17="-", "-", IF(AN17="-", "-", IF(ABS(AN17)=0, "-", ROUND(100*(AL17-AN17)/ABS(AN17), 1)))) -> - | AV17: 収穫請負わせ賃 | BJ17: =IF(BB17="-", "-", IF(BF17="-", "-", IF(ABS(BF17)=0, "-", ROUND(100*(BB17-BF17)/ABS(BF17), 10)))) -> - | BK17: =IF(BG17="-", "-", IF(BI17="-", "-", IF(ABS(BI17)=0, "-", ROUND(100*(BG17-BI17)/ABS(BI17), 1)))) -> - | BL17: =IF(BH17="-", "-", IF(BJ17="-", "-", IF(ABS(BJ17)=0, "-", ROUND(100*(BH17-BJ17)/ABS(BJ17), 1)))) -> - | BU17: =IF(BM17="-", "-", IF(BQ17="-", "-", IF(ABS(BQ17)=0, "-", ROUND(100*(BM17-BQ17)/ABS(BQ17), 10)))) -> - | BV17: =IF(BR17="-", "-", IF(BT17="-", "-", IF(ABS(BT17)=0, "-", ROUND(100*(BR17-BT17)/ABS(BT17), 1)))) -> - | BW17: =IF(BS17="-", "-", IF(BU17="-", "-", IF(ABS(BU17)=0, "-", ROUND(100*(BS17-BU17)/ABS(BU17), 1)))) -> - | CF17: =IF(BX17="-", "-", IF(CB17="-", "-", IF(ABS(CB17)=0, "-", ROUND(100*(BX17-CB17)/ABS(CB17), 10)))) -> - | CG17: =IF(CC17="-", "-", IF(CE17="-", "-", IF(ABS(CE17)=0, "-", ROUND(100*(CC17-CE17)/ABS(CE17), 1)))) -> - | CH17: =IF(CD17="-", "-", IF(CF17="-", "-", IF(ABS(CF17)=0, "-", ROUND(100*(CD17-CF17)/ABS(CF17), 1)))) -> -
D18: 炭酸カルシウム（石灰含む） | R18: =IF(J18="-", "-", IF(N18="-", "-", IF(ABS(N18)=0, "-", ROUND(100*(J18-N18)/ABS(N18), 10)))) -> - | S18: =IF(O18="-", "-", IF(Q18="-", "-", IF(ABS(Q18)=0, "-", ROUND(100*(O18-Q18)/ABS(Q18), 1)))) -> - | T18: =IF(P18="-", "-", IF(R18="-", "-", IF(ABS(R18)=0, "-", ROUND(100*(P18-R18)/ABS(R18), 1)))) -> - | AC18: =IF(U18="-", "-", IF(Y18="-", "-", IF(ABS(Y18)=0, "-", ROUND(100*(U18-Y18)/ABS(Y18), 10)))) -> - | AD18: =IF(Z18="-", "-", IF(AB18="-", "-", IF(ABS(AB18)=0, "-", ROUND(100*(Z18-AB18)/ABS(AB18), 1)))) -> - | AE18: =IF(AA18="-", "-", IF(AC18="-", "-", IF(ABS(AC18)=0, "-", ROUND(100*(AA18-AC18)/ABS(AC18), 1)))) -> - | AN18: =IF(AF18="-", "-", IF(AJ18="-", "-", IF(ABS(AJ18)=0, "-", ROUND(100*(AF18-AJ18)/ABS(AJ18), 10)))) -> - | AO18: =IF(AK18="-", "-", IF(AM18="-", "-", IF(ABS(AM18)=0, "-", ROUND(100*(AK18-AM18)/ABS(AM18), 1)))) -> - | AP18: =IF(AL18="-", "-", IF(AN18="-", "-", IF(ABS(AN18)=0, "-", ROUND(100*(AL18-AN18)/ABS(AN18), 1)))) -> - | AV18: ライスセンター費 | BJ18: =IF(BB18="-", "-", IF(BF18="-", "-", IF(ABS(BF18)=0, "-", ROUND(100*(BB18-BF18)/ABS(BF18), 10)))) -> - | BK18: =IF(BG18="-", "-", IF(BI18="-", "-", IF(ABS(BI18)=0, "-", ROUND(100*(BG18-BI18)/ABS(BI18), 1)))) -> - | BL18: =IF(BH18="-", "-", IF(BJ18="-", "-", IF(ABS(BJ18)=0, "-", ROUND(100*(BH18-BJ18)/ABS(BJ18), 1)))) -> - | BU18: =IF(BM18="-", "-", IF(BQ18="-", "-", IF(ABS(BQ18)=0, "-", ROUND(100*(BM18-BQ18)/ABS(BQ18), 10)))) -> - | BV18: =IF(BR18="-", "-", IF(BT18="-", "-", IF(ABS(BT18)=0, "-", ROUND(100*(BR18-BT18)/ABS(BT18), 1)))) -> - | BW18: =IF(BS18="-", "-", IF(BU18="-", "-", IF(ABS(BU18)=0, "-", ROUND(100*(BS18-BU18)/ABS(BU18), 1)))) -> - | CF18: =IF(BX18="-", "-", IF(CB18="-", "-", IF(ABS(CB18)=0, "-", ROUND(100*(BX18-CB18)/ABS(CB18), 10)))) -> - | CG18: =IF(CC18="-", "-", IF(CE18="-", "-", IF(ABS(CE18)=0, "-", ROUND(100*(CC18-CE18)/ABS(CE18), 1)))) -> - | CH18: =IF(CD18="-", "-", IF(CF18="-", "-", IF(ABS(CF18)=0, "-", ROUND(100*(CD18-CF18)/ABS(CF18), 1)))) -> -
D19: 複合肥料 | R19: =IF(J19="-", "-", IF(N19="-", "-", IF(ABS(N19)=0, "-", ROUND(100*(J19-N19)/ABS(N19), 10)))) -> - | S19: =IF(O19="-", "-", IF(Q19="-", "-", IF(ABS(Q19)=0, "-", ROUND(100*(O19-Q19)/ABS(Q19), 1)))) -> - | T19: =IF(P19="-", "-", IF(R19="-", "-", IF(ABS(R19)=0, "-", ROUND(100*(P19-R19)/ABS(R19), 1)))) -> - | AC19: =IF(U19="-", "-", IF(Y19="-", "-", IF(ABS(Y19)=0, "-", ROUND(100*(U19-Y19)/ABS(Y19), 10)))) -> - | AD19: =IF(Z19="-", "-", IF(AB19="-", "-", IF(ABS(AB19)=0, "-", ROUND(100*(Z19-AB19)/ABS(AB19), 1)))) -> - | AE19: =IF(AA19="-", "-", IF(AC19="-", "-", IF(ABS(AC19)=0, "-", ROUND(100*(AA19-AC19)/ABS(AC19), 1)))) -> - | AN19: =IF(AF19="-", "-", IF(AJ19="-", "-", IF(ABS(AJ19)=0, "-", ROUND(100*(AF19-AJ19)/ABS(AJ19), 10)))) -> - | AO19: =IF(AK19="-", "-", IF(AM19="-", "-", IF(ABS(AM19)=0, "-", ROUND(100*(AK19-AM19)/ABS(AM19), 1)))) -> - | AP19: =IF(AL19="-", "-", IF(AN19="-", "-", IF(ABS(AN19)=0, "-", ROUND(100*(AL19-AN19)/ABS(AN19), 1)))) -> - | AV19: カントリーエレベーター費 | BJ19: =IF(BB19="-", "-", IF(BF19="-", "-", IF(ABS(BF19)=0, "-", ROUND(100*(BB19-BF19)/ABS(BF19), 10)))) -> - | BK19: =IF(BG19="-", "-", IF(BI19="-", "-", IF(ABS(BI19)=0, "-", ROUND(100*(BG19-BI19)/ABS(BI19), 1)))) -> - | BL19: =IF(BH19="-", "-", IF(BJ19="-", "-", IF(ABS(BJ19)=0, "-", ROUND(100*(BH19-BJ19)/ABS(BJ19), 1)))) -> - | BU19: =IF(BM19="-", "-", IF(BQ19="-", "-", IF(ABS(BQ19)=0, "-", ROUND(100*(BM19-BQ19)/ABS(BQ19), 10)))) -> - | BV19: =IF(BR19="-", "-", IF(BT19="-", "-", IF(ABS(BT19)=0, "-", ROUND(100*(BR19-BT19)/ABS(BT19), 1)))) -> - | BW19: =IF(BS19="-", "-", IF(BU19="-", "-", IF(ABS(BU19)=0, "-", ROUND(100*(BS19-BU19)/ABS(BU19), 1)))) -> - | CF19: =IF(BX19="-", "-", IF(CB19="-", "-", IF(ABS(CB19)=0, "-", ROUND(100*(BX19-CB19)/ABS(CB19), 10)))) -> - | CG19: =IF(CC19="-", "-", IF(CE19="-", "-", IF(ABS(CE19)=0, "-", ROUND(100*(CC19-CE19)/ABS(CE19), 1)))) -> - | CH19: =IF(CD19="-", "-", IF(CF19="-", "-", IF(ABS(CF19)=0, "-", ROUND(100*(CD19-CF19)/ABS(CF19), 1)))) -> -
D20: 土壌改良資材 | AC20: =IF(U20="-", "-", IF(Y20="-", "-", IF(ABS(Y20)=0, "-", ROUND(100*(U20-Y20)/ABS(Y20), 10)))) -> - | AD20: =IF(Z20="-", "-", IF(AB20="-", "-", IF(ABS(AB20)=0, "-", ROUND(100*(Z20-AB20)/ABS(AB20), 1)))) -> - | AE20: =IF(AA20="-", "-", IF(AC20="-", "-", IF(ABS(AC20)=0, "-", ROUND(100*(AA20-AC20)/ABS(AC20), 1)))) -> - | AV20: 上記以外の乾燥・調製委託料 | BJ20: =IF(BB20="-", "-", IF(BF20="-", "-", IF(ABS(BF20)=0, "-", ROUND(100*(BB20-BF20)/ABS(BF20), 10)))) -> - | BK20: =IF(BG20="-", "-", IF(BI20="-", "-", IF(ABS(BI20)=0, "-", ROUND(100*(BG20-BI20)/ABS(BI20), 1)))) -> - | BL20: =IF(BH20="-", "-", IF(BJ20="-", "-", IF(ABS(BJ20)=0, "-", ROUND(100*(BH20-BJ20)/ABS(BJ20), 1)))) -> - | BU20: =IF(BM20="-", "-", IF(BQ20="-", "-", IF(ABS(BQ20)=0, "-", ROUND(100*(BM20-BQ20)/ABS(BQ20), 10)))) -> - | BV20: =IF(BR20="-", "-", IF(BT20="-", "-", IF(ABS(BT20)=0, "-", ROUND(100*(BR20-BT20)/ABS(BT20), 1)))) -> - | BW20: =IF(BS20="-", "-", IF(BU20="-", "-", IF(ABS(BU20)=0, "-", ROUND(100*(BS20-BU20)/ABS(BU20), 1)))) -> - | CF20: =IF(BX20="-", "-", IF(CB20="-", "-", IF(ABS(CB20)=0, "-", ROUND(100*(BX20-CB20)/ABS(CB20), 10)))) -> - | CG20: =IF(CC20="-", "-", IF(CE20="-", "-", IF(ABS(CE20)=0, "-", ROUND(100*(CC20-CE20)/ABS(CE20), 1)))) -> - | CH20: =IF(CD20="-", "-", IF(CF20="-", "-", IF(ABS(CF20)=0, "-", ROUND(100*(CD20-CF20)/ABS(CF20), 1)))) -> -
D21: たい肥・きゅう肥 | R21: =IF(J21="-", "-", IF(N21="-", "-", IF(ABS(N21)=0, "-", ROUND(100*(J21-N21)/ABS(N21), 10)))) -> - | S21: =IF(O21="-", "-", IF(Q21="-", "-", IF(ABS(Q21)=0, "-", ROUND(100*(O21-Q21)/ABS(Q21), 1)))) -> - | T21: =IF(P21="-", "-", IF(R21="-", "-", IF(ABS(R21)=0, "-", ROUND(100*(P21-R21)/ABS(R21), 1)))) -> - | AC21: =IF(U21="-", "-", IF(Y21="-", "-", IF(ABS(Y21)=0, "-", ROUND(100*(U21-Y21)/ABS(Y21), 10)))) -> - | AD21: =IF(Z21="-", "-", IF(AB21="-", "-", IF(ABS(AB21)=0, "-", ROUND(100*(Z21-AB21)/ABS(AB21), 1)))) -> - | AE21: =IF(AA21="-", "-", IF(AC21="-", "-", IF(ABS(AC21)=0, "-", ROUND(100*(AA21-AC21)/ABS(AC21), 1)))) -> - | AN21: =IF(AF21="-", "-", IF(AJ21="-", "-", IF(ABS(AJ21)=0, "-", ROUND(100*(AF21-AJ21)/ABS(AJ21), 10)))) -> - | AO21: =IF(AK21="-", "-", IF(AM21="-", "-", IF(ABS(AM21)=0, "-", ROUND(100*(AK21-AM21)/ABS(AM21), 1)))) -> - | AP21: =IF(AL21="-", "-", IF(AN21="-", "-", IF(ABS(AN21)=0, "-", ROUND(100*(AL21-AN21)/ABS(AN21), 1)))) -> - | AV21: その他 | BJ21: =IF(BB21="-", "-", IF(BF21="-", "-", IF(ABS(BF21)=0, "-", ROUND(100*(BB21-BF21)/ABS(BF21), 10)))) -> - | BK21: =IF(BG21="-", "-", IF(BI21="-", "-", IF(ABS(BI21)=0, "-", ROUND(100*(BG21-BI21)/ABS(BI21), 1)))) -> - | BL21: =IF(BH21="-", "-", IF(BJ21="-", "-", IF(ABS(BJ21)=0, "-", ROUND(100*(BH21-BJ21)/ABS(BJ21), 1)))) -> - | BU21: =IF(BM21="-", "-", IF(BQ21="-", "-", IF(ABS(BQ21)=0, "-", ROUND(100*(BM21-BQ21)/ABS(BQ21), 10)))) -> - | BV21: =IF(BR21="-", "-", IF(BT21="-", "-", IF(ABS(BT21)=0, "-", ROUND(100*(BR21-BT21)/ABS(BT21), 1)))) -> - | BW21: =IF(BS21="-", "-", IF(BU21="-", "-", IF(ABS(BU21)=0, "-", ROUND(100*(BS21-BU21)/ABS(BU21), 1)))) -> - | CF21: =IF(BX21="-", "-", IF(CB21="-", "-", IF(ABS(CB21)=0, "-", ROUND(100*(BX21-CB21)/ABS(CB21), 10)))) -> - | CG21: =IF(CC21="-", "-", IF(CE21="-", "-", IF(ABS(CE21)=0, "-", ROUND(100*(CC21-CE21)/ABS(CE21), 1)))) -> - | CH21: =IF(CD21="-", "-", IF(CF21="-", "-", IF(ABS(CF21)=0, "-", ROUND(100*(CD21-CF21)/ABS(CF21), 1)))) -> -
D22: その他 | AC22: =IF(U22="-", "-", IF(Y22="-", "-", IF(ABS(Y22)=0, "-", ROUND(100*(U22-Y22)/ABS(Y22), 10)))) -> - | AD22: =IF(Z22="-", "-", IF(AB22="-", "-", IF(ABS(AB22)=0, "-", ROUND(100*(Z22-AB22)/ABS(AB22), 1)))) -> - | AE22: =IF(AA22="-", "-", IF(AC22="-", "-", IF(ABS(AC22)=0, "-", ROUND(100*(AA22-AC22)/ABS(AC22), 1)))) -> - | AV22: 計 | BU22: =IF(BM22="-", "-", IF(BQ22="-", "-", IF(ABS(BQ22)=0, "-", ROUND(100*(BM22-BQ22)/ABS(BQ22), 10)))) -> - | BV22: =IF(BR22="-", "-", IF(BT22="-", "-", IF(ABS(BT22)=0, "-", ROUND(100*(BR22-BT22)/ABS(BT22), 1)))) -> - | BW22: =IF(BS22="-", "-", IF(BU22="-", "-", IF(ABS(BU22)=0, "-", ROUND(100*(BS22-BU22)/ABS(BU22), 1)))) -> -
D23: 自給 | F23: たい肥 | R23: =IF(J23="-", "-", IF(N23="-", "-", IF(ABS(N23)=0, "-", ROUND(100*(J23-N23)/ABS(N23), 10)))) -> - | S23: =IF(O23="-", "-", IF(Q23="-", "-", IF(ABS(Q23)=0, "-", ROUND(100*(O23-Q23)/ABS(Q23), 1)))) -> - | T23: =IF(P23="-", "-", IF(R23="-", "-", IF(ABS(R23)=0, "-", ROUND(100*(P23-R23)/ABS(R23), 1)))) -> - | AC23: =IF(U23="-", "-", IF(Y23="-", "-", IF(ABS(Y23)=0, "-", ROUND(100*(U23-Y23)/ABS(Y23), 10)))) -> - | AD23: =IF(Z23="-", "-", IF(AB23="-", "-", IF(ABS(AB23)=0, "-", ROUND(100*(Z23-AB23)/ABS(AB23), 1)))) -> - | AE23: =IF(AA23="-", "-", IF(AC23="-", "-", IF(ABS(AC23)=0, "-", ROUND(100*(AA23-AC23)/ABS(AC23), 1)))) -> - | AN23: =IF(AF23="-", "-", IF(AJ23="-", "-", IF(ABS(AJ23)=0, "-", ROUND(100*(AF23-AJ23)/ABS(AJ23), 10)))) -> - | AO23: =IF(AK23="-", "-", IF(AM23="-", "-", IF(ABS(AM23)=0, "-", ROUND(100*(AK23-AM23)/ABS(AM23), 1)))) -> - | AP23: =IF(AL23="-", "-", IF(AN23="-", "-", IF(ABS(AN23)=0, "-", ROUND(100*(AL23-AN23)/ABS(AN23), 1)))) -> -
F24: きゅう肥 | R24: =IF(J24="-", "-", IF(N24="-", "-", IF(ABS(N24)=0, "-", ROUND(100*(J24-N24)/ABS(N24), 10)))) -> - | S24: =IF(O24="-", "-", IF(Q24="-", "-", IF(ABS(Q24)=0, "-", ROUND(100*(O24-Q24)/ABS(Q24), 1)))) -> - | T24: =IF(P24="-", "-", IF(R24="-", "-", IF(ABS(R24)=0, "-", ROUND(100*(P24-R24)/ABS(R24), 1)))) -> - | AC24: =IF(U24="-", "-", IF(Y24="-", "-", IF(ABS(Y24)=0, "-", ROUND(100*(U24-Y24)/ABS(Y24), 10)))) -> - | AD24: =IF(Z24="-", "-", IF(AB24="-", "-", IF(ABS(AB24)=0, "-", ROUND(100*(Z24-AB24)/ABS(AB24), 1)))) -> - | AE24: =IF(AA24="-", "-", IF(AC24="-", "-", IF(ABS(AC24)=0, "-", ROUND(100*(AA24-AC24)/ABS(AC24), 1)))) -> - | AN24: =IF(AF24="-", "-", IF(AJ24="-", "-", IF(ABS(AJ24)=0, "-", ROUND(100*(AF24-AJ24)/ABS(AJ24), 10)))) -> - | AO24: =IF(AK24="-", "-", IF(AM24="-", "-", IF(ABS(AM24)=0, "-", ROUND(100*(AK24-AM24)/ABS(AM24), 1)))) -> - | AP24: =IF(AL24="-", "-", IF(AN24="-", "-", IF(ABS(AN24)=0, "-", ROUND(100*(AL24-AN24)/ABS(AN24), 1)))) -> -
F25: 稲・麦わら | R25: =IF(J25="-", "-", IF(N25="-", "-", IF(ABS(N25)=0, "-", ROUND(100*(J25-N25)/ABS(N25), 10)))) -> - | S25: =IF(O25="-", "-", IF(Q25="-", "-", IF(ABS(Q25)=0, "-", ROUND(100*(O25-Q25)/ABS(Q25), 1)))) -> - | T25: =IF(P25="-", "-", IF(R25="-", "-", IF(ABS(R25)=0, "-", ROUND(100*(P25-R25)/ABS(R25), 1)))) -> - | AC25: =IF(U25="-", "-", IF(Y25="-", "-", IF(ABS(Y25)=0, "-", ROUND(100*(U25-Y25)/ABS(Y25), 10)))) -> - | AD25: =IF(Z25="-", "-", IF(AB25="-", "-", IF(ABS(AB25)=0, "-", ROUND(100*(Z25-AB25)/ABS(AB25), 1)))) -> - | AE25: =IF(AA25="-", "-", IF(AC25="-", "-", IF(ABS(AC25)=0, "-", ROUND(100*(AA25-AC25)/ABS(AC25), 1)))) -> - | AN25: =IF(AF25="-", "-", IF(AJ25="-", "-", IF(ABS(AJ25)=0, "-", ROUND(100*(AF25-AJ25)/ABS(AJ25), 10)))) -> - | AO25: =IF(AK25="-", "-", IF(AM25="-", "-", IF(ABS(AM25)=0, "-", ROUND(100*(AK25-AM25)/ABS(AM25), 1)))) -> - | AP25: =IF(AL25="-", "-", IF(AN25="-", "-", IF(ABS(AN25)=0, "-", ROUND(100*(AL25-AN25)/ABS(AN25), 1)))) -> -
F26: その他 | AC26: =IF(U26="-", "-", IF(Y26="-", "-", IF(ABS(Y26)=0, "-", ROUND(100*(U26-Y26)/ABS(Y26), 10)))) -> - | AD26: =IF(Z26="-", "-", IF(AB26="-", "-", IF(ABS(AB26)=0, "-", ROUND(100*(Z26-AB26)/ABS(AB26), 1)))) -> - | AE26: =IF(AA26="-", "-", IF(AC26="-", "-", IF(ABS(AC26)=0, "-", ROUND(100*(AA26-AC26)/ABS(AC26), 1)))) -> - | AT26: 23 物件税及び公課諸負担 | BL26: 単位：円
D27: 計 | AC27: =IF(U27="-", "-", IF(Y27="-", "-", IF(ABS(Y27)=0, "-", ROUND(100*(U27-Y27)/ABS(Y27), 10)))) -> - | AD27: =IF(Z27="-", "-", IF(AB27="-", "-", IF(ABS(AB27)=0, "-", ROUND(100*(Z27-AB27)/ABS(AB27), 1)))) -> - | AE27: =IF(AA27="-", "-", IF(AC27="-", "-", IF(ABS(AC27)=0, "-", ROUND(100*(AA27-AC27)/ABS(AC27), 1)))) -> - | BB27: =IF($B$1<>"",$B$1,"") | BF27: =IF($B$1<>"",$B$1-1,"") | BJ27: 増減率
B28: 農業薬剤費 | D28: 殺虫剤 | AC28: =IF(U28="-", "-", IF(Y28="-", "-", IF(ABS(Y28)=0, "-", ROUND(100*(U28-Y28)/ABS(Y28), 10)))) -> - | AD28: =IF(Z28="-", "-", IF(AB28="-", "-", IF(ABS(AB28)=0, "-", ROUND(100*(Z28-AB28)/ABS(AB28), 1)))) -> - | AE28: =IF(AA28="-", "-", IF(AC28="-", "-", IF(ABS(AC28)=0, "-", ROUND(100*(AA28-AC28)/ABS(AC28), 1)))) -> - | AT28: 物件税 | AV28: 固定資産税 | BJ28: =IF(BB28="-", "-", IF(BF28="-", "-", IF(ABS(BF28)=0, "-", ROUND(100*(BB28-BF28)/ABS(BF28), 10)))) -> - | BK28: =IF(BG28="-", "-", IF(BI28="-", "-", IF(ABS(BI28)=0, "-", ROUND(100*(BG28-BI28)/ABS(BI28), 1)))) -> - | BL28: =IF(BH28="-", "-", IF(BJ28="-", "-", IF(ABS(BJ28)=0, "-", ROUND(100*(BH28-BJ28)/ABS(BJ28), 1)))) -> -
D29: 殺菌剤 | AC29: =IF(U29="-", "-", IF(Y29="-", "-", IF(ABS(Y29)=0, "-", ROUND(100*(U29-Y29)/ABS(Y29), 10)))) -> - | AD29: =IF(Z29="-", "-", IF(AB29="-", "-", IF(ABS(AB29)=0, "-", ROUND(100*(Z29-AB29)/ABS(AB29), 1)))) -> - | AE29: =IF(AA29="-", "-", IF(AC29="-", "-", IF(ABS(AC29)=0, "-", ROUND(100*(AA29-AC29)/ABS(AC29), 1)))) -> - | AW29: 建物 | BJ29: =IF(BB29="-", "-", IF(BF29="-", "-", IF(ABS(BF29)=0, "-", ROUND(100*(BB29-BF29)/ABS(BF29), 10)))) -> - | BK29: =IF(BG29="-", "-", IF(BI29="-", "-", IF(ABS(BI29)=0, "-", ROUND(100*(BG29-BI29)/ABS(BI29), 1)))) -> - | BL29: =IF(BH29="-", "-", IF(BJ29="-", "-", IF(ABS(BJ29)=0, "-", ROUND(100*(BH29-BJ29)/ABS(BJ29), 1)))) -> -
D30: 殺虫殺菌剤 | AC30: =IF(U30="-", "-", IF(Y30="-", "-", IF(ABS(Y30)=0, "-", ROUND(100*(U30-Y30)/ABS(Y30), 10)))) -> - | AD30: =IF(Z30="-", "-", IF(AB30="-", "-", IF(ABS(AB30)=0, "-", ROUND(100*(Z30-AB30)/ABS(AB30), 1)))) -> - | AE30: =IF(AA30="-", "-", IF(AC30="-", "-", IF(ABS(AC30)=0, "-", ROUND(100*(AA30-AC30)/ABS(AC30), 1)))) -> - | AW30: 農機具 | BJ30: =IF(BB30="-", "-", IF(BF30="-", "-", IF(ABS(BF30)=0, "-", ROUND(100*(BB30-BF30)/ABS(BF30), 10)))) -> - | BK30: =IF(BG30="-", "-", IF(BI30="-", "-", IF(ABS(BI30)=0, "-", ROUND(100*(BG30-BI30)/ABS(BI30), 1)))) -> - | BL30: =IF(BH30="-", "-", IF(BJ30="-", "-", IF(ABS(BJ30)=0, "-", ROUND(100*(BH30-BJ30)/ABS(BJ30), 1)))) -> -
D31: 除草剤 | AC31: =IF(U31="-", "-", IF(Y31="-", "-", IF(ABS(Y31)=0, "-", ROUND(100*(U31-Y31)/ABS(Y31), 10)))) -> - | AD31: =IF(Z31="-", "-", IF(AB31="-", "-", IF(ABS(AB31)=0, "-", ROUND(100*(Z31-AB31)/ABS(AB31), 1)))) -> - | AE31: =IF(AA31="-", "-", IF(AC31="-", "-", IF(ABS(AC31)=0, "-", ROUND(100*(AA31-AC31)/ABS(AC31), 1)))) -> - | AV31: 自動車重量税 | BJ31: =IF(BB31="-", "-", IF(BF31="-", "-", IF(ABS(BF31)=0, "-", ROUND(100*(BB31-BF31)/ABS(BF31), 10)))) -> - | BK31: =IF(BG31="-", "-", IF(BI31="-", "-", IF(ABS(BI31)=0, "-", ROUND(100*(BG31-BI31)/ABS(BI31), 1)))) -> - | BL31: =IF(BH31="-", "-", IF(BJ31="-", "-", IF(ABS(BJ31)=0, "-", ROUND(100*(BH31-BJ31)/ABS(BJ31), 1)))) -> -
D32: その他 | AC32: =IF(U32="-", "-", IF(Y32="-", "-", IF(ABS(Y32)=0, "-", ROUND(100*(U32-Y32)/ABS(Y32), 10)))) -> - | AD32: =IF(Z32="-", "-", IF(AB32="-", "-", IF(ABS(AB32)=0, "-", ROUND(100*(Z32-AB32)/ABS(AB32), 1)))) -> - | AE32: =IF(AA32="-", "-", IF(AC32="-", "-", IF(ABS(AC32)=0, "-", ROUND(100*(AA32-AC32)/ABS(AC32), 1)))) -> - | AV32: 自動車税 | BJ32: =IF(BB32="-", "-", IF(BF32="-", "-", IF(ABS(BF32)=0, "-", ROUND(100*(BB32-BF32)/ABS(BF32), 10)))) -> - | BK32: =IF(BG32="-", "-", IF(BI32="-", "-", IF(ABS(BI32)=0, "-", ROUND(100*(BG32-BI32)/ABS(BI32), 1)))) -> - | BL32: =IF(BH32="-", "-", IF(BJ32="-", "-", IF(ABS(BJ32)=0, "-", ROUND(100*(BH32-BJ32)/ABS(BJ32), 1)))) -> -
D33: 計 | AC33: =IF(U33="-", "-", IF(Y33="-", "-", IF(ABS(Y33)=0, "-", ROUND(100*(U33-Y33)/ABS(Y33), 10)))) -> - | AD33: =IF(Z33="-", "-", IF(AB33="-", "-", IF(ABS(AB33)=0, "-", ROUND(100*(Z33-AB33)/ABS(AB33), 1)))) -> - | AE33: =IF(AA33="-", "-", IF(AC33="-", "-", IF(ABS(AC33)=0, "-", ROUND(100*(AA33-AC33)/ABS(AC33), 1)))) -> - | AV33: 不動産取得税 | BJ33: =IF(BB33="-", "-", IF(BF33="-", "-", IF(ABS(BF33)=0, "-", ROUND(100*(BB33-BF33)/ABS(BF33), 10)))) -> - | BK33: =IF(BG33="-", "-", IF(BI33="-", "-", IF(ABS(BI33)=0, "-", ROUND(100*(BG33-BI33)/ABS(BI33), 1)))) -> - | BL33: =IF(BH33="-", "-", IF(BJ33="-", "-", IF(ABS(BJ33)=0, "-", ROUND(100*(BH33-BJ33)/ABS(BJ33), 1)))) -> -
B34: 光熱動力費 | D34: 動力 燃料 | F34: 重油 | R34: =IF(J34="-", "-", IF(N34="-", "-", IF(ABS(N34)=0, "-", ROUND(100*(J34-N34)/ABS(N34), 10)))) -> - | S34: =IF(O34="-", "-", IF(Q34="-", "-", IF(ABS(Q34)=0, "-", ROUND(100*(O34-Q34)/ABS(Q34), 1)))) -> - | T34: =IF(P34="-", "-", IF(R34="-", "-", IF(ABS(R34)=0, "-", ROUND(100*(P34-R34)/ABS(R34), 1)))) -> - | AC34: =IF(U34="-", "-", IF(Y34="-", "-", IF(ABS(Y34)=0, "-", ROUND(100*(U34-Y34)/ABS(Y34), 10)))) -> - | AD34: =IF(Z34="-", "-", IF(AB34="-", "-", IF(ABS(AB34)=0, "-", ROUND(100*(Z34-AB34)/ABS(AB34), 1)))) -> - | AE34: =IF(AA34="-", "-", IF(AC34="-", "-", IF(ABS(AC34)=0, "-", ROUND(100*(AA34-AC34)/ABS(AC34), 1)))) -> - | AN34: =IF(AF34="-", "-", IF(AJ34="-", "-", IF(ABS(AJ34)=0, "-", ROUND(100*(AF34-AJ34)/ABS(AJ34), 10)))) -> - | AO34: =IF(AK34="-", "-", IF(AM34="-", "-", IF(ABS(AM34)=0, "-", ROUND(100*(AK34-AM34)/ABS(AM34), 1)))) -> - | AP34: =IF(AL34="-", "-", IF(AN34="-", "-", IF(ABS(AN34)=0, "-", ROUND(100*(AL34-AN34)/ABS(AN34), 1)))) -> - | AV34: 軽自動車税 | BJ34: =IF(BB34="-", "-", IF(BF34="-", "-", IF(ABS(BF34)=0, "-", ROUND(100*(BB34-BF34)/ABS(BF34), 10)))) -> - | BK34: =IF(BG34="-", "-", IF(BI34="-", "-", IF(ABS(BI34)=0, "-", ROUND(100*(BG34-BI34)/ABS(BI34), 1)))) -> - | BL34: =IF(BH34="-", "-", IF(BJ34="-", "-", IF(ABS(BJ34)=0, "-", ROUND(100*(BH34-BJ34)/ABS(BJ34), 1)))) -> -
F35: 軽油 | R35: =IF(J35="-", "-", IF(N35="-", "-", IF(ABS(N35)=0, "-", ROUND(100*(J35-N35)/ABS(N35), 10)))) -> - | S35: =IF(O35="-", "-", IF(Q35="-", "-", IF(ABS(Q35)=0, "-", ROUND(100*(O35-Q35)/ABS(Q35), 1)))) -> - | T35: =IF(P35="-", "-", IF(R35="-", "-", IF(ABS(R35)=0, "-", ROUND(100*(P35-R35)/ABS(R35), 1)))) -> - | AC35: =IF(U35="-", "-", IF(Y35="-", "-", IF(ABS(Y35)=0, "-", ROUND(100*(U35-Y35)/ABS(Y35), 10)))) -> - | AD35: =IF(Z35="-", "-", IF(AB35="-", "-", IF(ABS(AB35)=0, "-", ROUND(100*(Z35-AB35)/ABS(AB35), 1)))) -> - | AE35: =IF(AA35="-", "-", IF(AC35="-", "-", IF(ABS(AC35)=0, "-", ROUND(100*(AA35-AC35)/ABS(AC35), 1)))) -> - | AN35: =IF(AF35="-", "-", IF(AJ35="-", "-", IF(ABS(AJ35)=0, "-", ROUND(100*(AF35-AJ35)/ABS(AJ35), 10)))) -> - | AO35: =IF(AK35="-", "-", IF(AM35="-", "-", IF(ABS(AM35)=0, "-", ROUND(100*(AK35-AM35)/ABS(AM35), 1)))) -> - | AP35: =IF(AL35="-", "-", IF(AN35="-", "-", IF(ABS(AN35)=0, "-", ROUND(100*(AL35-AN35)/ABS(AN35), 1)))) -> - | AV35: 水利地益税 | BJ35: =IF(BB35="-", "-", IF(BF35="-", "-", IF(ABS(BF35)=0, "-", ROUND(100*(BB35-BF35)/ABS(BF35), 10)))) -> - | BK35: =IF(BG35="-", "-", IF(BI35="-", "-", IF(ABS(BI35)=0, "-", ROUND(100*(BG35-BI35)/ABS(BI35), 1)))) -> - | BL35: =IF(BH35="-", "-", IF(BJ35="-", "-", IF(ABS(BJ35)=0, "-", ROUND(100*(BH35-BJ35)/ABS(BJ35), 1)))) -> -
F36: 灯油 | R36: =IF(J36="-", "-", IF(N36="-", "-", IF(ABS(N36)=0, "-", ROUND(100*(J36-N36)/ABS(N36), 10)))) -> - | S36: =IF(O36="-", "-", IF(Q36="-", "-", IF(ABS(Q36)=0, "-", ROUND(100*(O36-Q36)/ABS(Q36), 1)))) -> - | T36: =IF(P36="-", "-", IF(R36="-", "-", IF(ABS(R36)=0, "-", ROUND(100*(P36-R36)/ABS(R36), 1)))) -> - | AC36: =IF(U36="-", "-", IF(Y36="-", "-", IF(ABS(Y36)=0, "-", ROUND(100*(U36-Y36)/ABS(Y36), 10)))) -> - | AD36: =IF(Z36="-", "-", IF(AB36="-", "-", IF(ABS(AB36)=0, "-", ROUND(100*(Z36-AB36)/ABS(AB36), 1)))) -> - | AE36: =IF(AA36="-", "-", IF(AC36="-", "-", IF(ABS(AC36)=0, "-", ROUND(100*(AA36-AC36)/ABS(AC36), 1)))) -> - | AN36: =IF(AF36="-", "-", IF(AJ36="-", "-", IF(ABS(AJ36)=0, "-", ROUND(100*(AF36-AJ36)/ABS(AJ36), 10)))) -> - | AO36: =IF(AK36="-", "-", IF(AM36="-", "-", IF(ABS(AM36)=0, "-", ROUND(100*(AK36-AM36)/ABS(AM36), 1)))) -> - | AP36: =IF(AL36="-", "-", IF(AN36="-", "-", IF(ABS(AN36)=0, "-", ROUND(100*(AL36-AN36)/ABS(AN36), 1)))) -> - | AV36: 都市計画税 | BJ36: =IF(BB36="-", "-", IF(BF36="-", "-", IF(ABS(BF36)=0, "-", ROUND(100*(BB36-BF36)/ABS(BF36), 10)))) -> - | BK36: =IF(BG36="-", "-", IF(BI36="-", "-", IF(ABS(BI36)=0, "-", ROUND(100*(BG36-BI36)/ABS(BI36), 1)))) -> - | BL36: =IF(BH36="-", "-", IF(BJ36="-", "-", IF(ABS(BJ36)=0, "-", ROUND(100*(BH36-BJ36)/ABS(BJ36), 1)))) -> -
F37: ガソリン | R37: =IF(J37="-", "-", IF(N37="-", "-", IF(ABS(N37)=0, "-", ROUND(100*(J37-N37)/ABS(N37), 10)))) -> - | S37: =IF(O37="-", "-", IF(Q37="-", "-", IF(ABS(Q37)=0, "-", ROUND(100*(O37-Q37)/ABS(Q37), 1)))) -> - | T37: =IF(P37="-", "-", IF(R37="-", "-", IF(ABS(R37)=0, "-", ROUND(100*(P37-R37)/ABS(R37), 1)))) -> - | AC37: =IF(U37="-", "-", IF(Y37="-", "-", IF(ABS(Y37)=0, "-", ROUND(100*(U37-Y37)/ABS(Y37), 10)))) -> - | AD37: =IF(Z37="-", "-", IF(AB37="-", "-", IF(ABS(AB37)=0, "-", ROUND(100*(Z37-AB37)/ABS(AB37), 1)))) -> - | AE37: =IF(AA37="-", "-", IF(AC37="-", "-", IF(ABS(AC37)=0, "-", ROUND(100*(AA37-AC37)/ABS(AC37), 1)))) -> - | AN37: =IF(AF37="-", "-", IF(AJ37="-", "-", IF(ABS(AJ37)=0, "-", ROUND(100*(AF37-AJ37)/ABS(AJ37), 10)))) -> - | AO37: =IF(AK37="-", "-", IF(AM37="-", "-", IF(ABS(AM37)=0, "-", ROUND(100*(AK37-AM37)/ABS(AM37), 1)))) -> - | AP37: =IF(AL37="-", "-", IF(AN37="-", "-", IF(ABS(AN37)=0, "-", ROUND(100*(AL37-AN37)/ABS(AN37), 1)))) -> - | AV37: 共同施設税 | BJ37: =IF(BB37="-", "-", IF(BF37="-", "-", IF(ABS(BF37)=0, "-", ROUND(100*(BB37-BF37)/ABS(BF37), 10)))) -> - | BK37: =IF(BG37="-", "-", IF(BI37="-", "-", IF(ABS(BI37)=0, "-", ROUND(100*(BG37-BI37)/ABS(BI37), 1)))) -> - | BL37: =IF(BH37="-", "-", IF(BJ37="-", "-", IF(ABS(BJ37)=0, "-", ROUND(100*(BH37-BJ37)/ABS(BJ37), 1)))) -> -
F38: 潤滑油 | R38: =IF(J38="-", "-", IF(N38="-", "-", IF(ABS(N38)=0, "-", ROUND(100*(J38-N38)/ABS(N38), 10)))) -> - | S38: =IF(O38="-", "-", IF(Q38="-", "-", IF(ABS(Q38)=0, "-", ROUND(100*(O38-Q38)/ABS(Q38), 1)))) -> - | T38: =IF(P38="-", "-", IF(R38="-", "-", IF(ABS(R38)=0, "-", ROUND(100*(P38-R38)/ABS(R38), 1)))) -> - | AC38: =IF(U38="-", "-", IF(Y38="-", "-", IF(ABS(Y38)=0, "-", ROUND(100*(U38-Y38)/ABS(Y38), 10)))) -> - | AD38: =IF(Z38="-", "-", IF(AB38="-", "-", IF(ABS(AB38)=0, "-", ROUND(100*(Z38-AB38)/ABS(AB38), 1)))) -> - | AE38: =IF(AA38="-", "-", IF(AC38="-", "-", IF(ABS(AC38)=0, "-", ROUND(100*(AA38-AC38)/ABS(AC38), 1)))) -> - | AN38: =IF(AF38="-", "-", IF(AJ38="-", "-", IF(ABS(AJ38)=0, "-", ROUND(100*(AF38-AJ38)/ABS(AJ38), 10)))) -> - | AO38: =IF(AK38="-", "-", IF(AM38="-", "-", IF(ABS(AM38)=0, "-", ROUND(100*(AK38-AM38)/ABS(AM38), 1)))) -> - | AP38: =IF(AL38="-", "-", IF(AN38="-", "-", IF(ABS(AN38)=0, "-", ROUND(100*(AL38-AN38)/ABS(AN38), 1)))) -> - | AV38: 小計 | BJ38: =IF(BB38="-", "-", IF(BF38="-", "-", IF(ABS(BF38)=0, "-", ROUND(100*(BB38-BF38)/ABS(BF38), 10)))) -> - | BK38: =IF(BG38="-", "-", IF(BI38="-", "-", IF(ABS(BI38)=0, "-", ROUND(100*(BG38-BI38)/ABS(BI38), 1)))) -> - | BL38: =IF(BH38="-", "-", IF(BJ38="-", "-", IF(ABS(BJ38)=0, "-", ROUND(100*(BH38-BJ38)/ABS(BJ38), 1)))) -> -
F39: 混合油 | R39: =IF(J39="-", "-", IF(N39="-", "-", IF(ABS(N39)=0, "-", ROUND(100*(J39-N39)/ABS(N39), 10)))) -> - | S39: =IF(O39="-", "-", IF(Q39="-", "-", IF(ABS(Q39)=0, "-", ROUND(100*(O39-Q39)/ABS(Q39), 1)))) -> - | T39: =IF(P39="-", "-", IF(R39="-", "-", IF(ABS(R39)=0, "-", ROUND(100*(P39-R39)/ABS(R39), 1)))) -> - | AC39: =IF(U39="-", "-", IF(Y39="-", "-", IF(ABS(Y39)=0, "-", ROUND(100*(U39-Y39)/ABS(Y39), 10)))) -> - | AD39: =IF(Z39="-", "-", IF(AB39="-", "-", IF(ABS(AB39)=0, "-", ROUND(100*(Z39-AB39)/ABS(AB39), 1)))) -> - | AE39: =IF(AA39="-", "-", IF(AC39="-", "-", IF(ABS(AC39)=0, "-", ROUND(100*(AA39-AC39)/ABS(AC39), 1)))) -> - | AN39: =IF(AF39="-", "-", IF(AJ39="-", "-", IF(ABS(AJ39)=0, "-", ROUND(100*(AF39-AJ39)/ABS(AJ39), 10)))) -> - | AO39: =IF(AK39="-", "-", IF(AM39="-", "-", IF(ABS(AM39)=0, "-", ROUND(100*(AK39-AM39)/ABS(AM39), 1)))) -> - | AP39: =IF(AL39="-", "-", IF(AN39="-", "-", IF(ABS(AN39)=0, "-", ROUND(100*(AL39-AN39)/ABS(AN39), 1)))) -> - | AT39: 公課諸負担 | AV39: 集落協議会費 | BJ39: =IF(BB39="-", "-", IF(BF39="-", "-", IF(ABS(BF39)=0, "-", ROUND(100*(BB39-BF39)/ABS(BF39), 10)))) -> - | BK39: =IF(BG39="-", "-", IF(BI39="-", "-", IF(ABS(BI39)=0, "-", ROUND(100*(BG39-BI39)/ABS(BI39), 1)))) -> - | BL39: =IF(BH39="-", "-", IF(BJ39="-", "-", IF(ABS(BJ39)=0, "-", ROUND(100*(BH39-BJ39)/ABS(BJ39), 1)))) -> -
D40: 電力料 | AC40: =IF(U40="-", "-", IF(Y40="-", "-", IF(ABS(Y40)=0, "-", ROUND(100*(U40-Y40)/ABS(Y40), 10)))) -> - | AD40: =IF(Z40="-", "-", IF(AB40="-", "-", IF(ABS(AB40)=0, "-", ROUND(100*(Z40-AB40)/ABS(AB40), 1)))) -> - | AE40: =IF(AA40="-", "-", IF(AC40="-", "-", IF(ABS(AC40)=0, "-", ROUND(100*(AA40-AC40)/ABS(AC40), 1)))) -> - | AV40: 農業協同組合費 | BJ40: =IF(BB40="-", "-", IF(BF40="-", "-", IF(ABS(BF40)=0, "-", ROUND(100*(BB40-BF40)/ABS(BF40), 10)))) -> - | BK40: =IF(BG40="-", "-", IF(BI40="-", "-", IF(ABS(BI40)=0, "-", ROUND(100*(BG40-BI40)/ABS(BI40), 1)))) -> - | BL40: =IF(BH40="-", "-", IF(BJ40="-", "-", IF(ABS(BJ40)=0, "-", ROUND(100*(BH40-BJ40)/ABS(BJ40), 1)))) -> -
D41: その他 | AC41: =IF(U41="-", "-", IF(Y41="-", "-", IF(ABS(Y41)=0, "-", ROUND(100*(U41-Y41)/ABS(Y41), 10)))) -> - | AD41: =IF(Z41="-", "-", IF(AB41="-", "-", IF(ABS(AB41)=0, "-", ROUND(100*(Z41-AB41)/ABS(AB41), 1)))) -> - | AE41: =IF(AA41="-", "-", IF(AC41="-", "-", IF(ABS(AC41)=0, "-", ROUND(100*(AA41-AC41)/ABS(AC41), 1)))) -> - | AV41: 農事実行組合費 | BJ41: =IF(BB41="-", "-", IF(BF41="-", "-", IF(ABS(BF41)=0, "-", ROUND(100*(BB41-BF41)/ABS(BF41), 10)))) -> - | BK41: =IF(BG41="-", "-", IF(BI41="-", "-", IF(ABS(BI41)=0, "-", ROUND(100*(BG41-BI41)/ABS(BI41), 1)))) -> - | BL41: =IF(BH41="-", "-", IF(BJ41="-", "-", IF(ABS(BJ41)=0, "-", ROUND(100*(BH41-BJ41)/ABS(BJ41), 1)))) -> -
D42: 自給 | AC42: =IF(U42="-", "-", IF(Y42="-", "-", IF(ABS(Y42)=0, "-", ROUND(100*(U42-Y42)/ABS(Y42), 10)))) -> - | AD42: =IF(Z42="-", "-", IF(AB42="-", "-", IF(ABS(AB42)=0, "-", ROUND(100*(Z42-AB42)/ABS(AB42), 1)))) -> - | AE42: =IF(AA42="-", "-", IF(AC42="-", "-", IF(ABS(AC42)=0, "-", ROUND(100*(AA42-AC42)/ABS(AC42), 1)))) -> - | AV42: 農業共済組合賦課金 | BJ42: =IF(BB42="-", "-", IF(BF42="-", "-", IF(ABS(BF42)=0, "-", ROUND(100*(BB42-BF42)/ABS(BF42), 10)))) -> - | BK42: =IF(BG42="-", "-", IF(BI42="-", "-", IF(ABS(BI42)=0, "-", ROUND(100*(BG42-BI42)/ABS(BI42), 1)))) -> - | BL42: =IF(BH42="-", "-", IF(BJ42="-", "-", IF(ABS(BJ42)=0, "-", ROUND(100*(BH42-BJ42)/ABS(BJ42), 1)))) -> -
D43: 計 | AC43: =IF(U43="-", "-", IF(Y43="-", "-", IF(ABS(Y43)=0, "-", ROUND(100*(U43-Y43)/ABS(Y43), 10)))) -> - | AD43: =IF(Z43="-", "-", IF(AB43="-", "-", IF(ABS(AB43)=0, "-", ROUND(100*(Z43-AB43)/ABS(AB43), 1)))) -> - | AE43: =IF(AA43="-", "-", IF(AC43="-", "-", IF(ABS(AC43)=0, "-", ROUND(100*(AA43-AC43)/ABS(AC43), 1)))) -> - | AV43: 自賠責保険 | BJ43: =IF(BB43="-", "-", IF(BF43="-", "-", IF(ABS(BF43)=0, "-", ROUND(100*(BB43-BF43)/ABS(BF43), 10)))) -> - | BK43: =IF(BG43="-", "-", IF(BI43="-", "-", IF(ABS(BI43)=0, "-", ROUND(100*(BG43-BI43)/ABS(BI43), 1)))) -> - | BL43: =IF(BH43="-", "-", IF(BJ43="-", "-", IF(ABS(BJ43)=0, "-", ROUND(100*(BH43-BJ43)/ABS(BJ43), 1)))) -> -
B44: 諸材料費 その他の | D44: 育苗用土（購入）（素土含む） | R44: =IF(J44="-", "-", IF(N44="-", "-", IF(ABS(N44)=0, "-", ROUND(100*(J44-N44)/ABS(N44), 10)))) -> - | S44: =IF(O44="-", "-", IF(Q44="-", "-", IF(ABS(Q44)=0, "-", ROUND(100*(O44-Q44)/ABS(Q44), 1)))) -> - | T44: =IF(P44="-", "-", IF(R44="-", "-", IF(ABS(R44)=0, "-", ROUND(100*(P44-R44)/ABS(R44), 1)))) -> - | AC44: =IF(U44="-", "-", IF(Y44="-", "-", IF(ABS(Y44)=0, "-", ROUND(100*(U44-Y44)/ABS(Y44), 10)))) -> - | AD44: =IF(Z44="-", "-", IF(AB44="-", "-", IF(ABS(AB44)=0, "-", ROUND(100*(Z44-AB44)/ABS(AB44), 1)))) -> - | AE44: =IF(AA44="-", "-", IF(AC44="-", "-", IF(ABS(AC44)=0, "-", ROUND(100*(AA44-AC44)/ABS(AC44), 1)))) -> - | AN44: =IF(AF44="-", "-", IF(AJ44="-", "-", IF(ABS(AJ44)=0, "-", ROUND(100*(AF44-AJ44)/ABS(AJ44), 10)))) -> - | AO44: =IF(AK44="-", "-", IF(AM44="-", "-", IF(ABS(AM44)=0, "-", ROUND(100*(AK44-AM44)/ABS(AM44), 1)))) -> - | AP44: =IF(AL44="-", "-", IF(AN44="-", "-", IF(ABS(AN44)=0, "-", ROUND(100*(AL44-AN44)/ABS(AN44), 1)))) -> - | AV44: 小計 | BJ44: =IF(BB44="-", "-", IF(BF44="-", "-", IF(ABS(BF44)=0, "-", ROUND(100*(BB44-BF44)/ABS(BF44), 10)))) -> - | BK44: =IF(BG44="-", "-", IF(BI44="-", "-", IF(ABS(BI44)=0, "-", ROUND(100*(BG44-BI44)/ABS(BI44), 1)))) -> - | BL44: =IF(BH44="-", "-", IF(BJ44="-", "-", IF(ABS(BJ44)=0, "-", ROUND(100*(BH44-BJ44)/ABS(BJ44), 1)))) -> -
D45: その他 | AC45: =IF(U45="-", "-", IF(Y45="-", "-", IF(ABS(Y45)=0, "-", ROUND(100*(U45-Y45)/ABS(Y45), 10)))) -> - | AD45: =IF(Z45="-", "-", IF(AB45="-", "-", IF(ABS(AB45)=0, "-", ROUND(100*(Z45-AB45)/ABS(AB45), 1)))) -> - | AE45: =IF(AA45="-", "-", IF(AC45="-", "-", IF(ABS(AC45)=0, "-", ROUND(100*(AA45-AC45)/ABS(AC45), 1)))) -> - | AT45: 合計 | BJ45: =IF(BB45="-", "-", IF(BF45="-", "-", IF(ABS(BF45)=0, "-", ROUND(100*(BB45-BF45)/ABS(BF45), 10)))) -> - | BK45: =IF(BG45="-", "-", IF(BI45="-", "-", IF(ABS(BI45)=0, "-", ROUND(100*(BG45-BI45)/ABS(BI45), 1)))) -> - | BL45: =IF(BH45="-", "-", IF(BJ45="-", "-", IF(ABS(BJ45)=0, "-", ROUND(100*(BH45-BJ45)/ABS(BJ45), 1)))) -> -
D46: 自給 | AC46: =IF(U46="-", "-", IF(Y46="-", "-", IF(ABS(Y46)=0, "-", ROUND(100*(U46-Y46)/ABS(Y46), 10)))) -> - | AD46: =IF(Z46="-", "-", IF(AB46="-", "-", IF(ABS(AB46)=0, "-", ROUND(100*(Z46-AB46)/ABS(AB46), 1)))) -> - | AE46: =IF(AA46="-", "-", IF(AC46="-", "-", IF(ABS(AC46)=0, "-", ROUND(100*(AA46-AC46)/ABS(AC46), 1)))) -> -
D47: 計 | AC47: =IF(U47="-", "-", IF(Y47="-", "-", IF(ABS(Y47)=0, "-", ROUND(100*(U47-Y47)/ABS(Y47), 10)))) -> - | AD47: =IF(Z47="-", "-", IF(AB47="-", "-", IF(ABS(AB47)=0, "-", ROUND(100*(Z47-AB47)/ABS(AB47), 1)))) -> - | AE47: =IF(AA47="-", "-", IF(AC47="-", "-", IF(ABS(AC47)=0, "-", ROUND(100*(AA47-AC47)/ABS(AC47), 1)))) -> -
B48: 及び水利費 土地改良 | D48: 土地改 良区費 | F48: 維持負担金 | AC48: =IF(U48="-", "-", IF(Y48="-", "-", IF(ABS(Y48)=0, "-", ROUND(100*(U48-Y48)/ABS(Y48), 10)))) -> - | AD48: =IF(Z48="-", "-", IF(AB48="-", "-", IF(ABS(AB48)=0, "-", ROUND(100*(Z48-AB48)/ABS(AB48), 1)))) -> - | AE48: =IF(AA48="-", "-", IF(AC48="-", "-", IF(ABS(AC48)=0, "-", ROUND(100*(AA48-AC48)/ABS(AC48), 1)))) -> -
F49: 償還金 | AC49: =IF(U49="-", "-", IF(Y49="-", "-", IF(ABS(Y49)=0, "-", ROUND(100*(U49-Y49)/ABS(Y49), 10)))) -> - | AD49: =IF(Z49="-", "-", IF(AB49="-", "-", IF(ABS(AB49)=0, "-", ROUND(100*(Z49-AB49)/ABS(AB49), 1)))) -> - | AE49: =IF(AA49="-", "-", IF(AC49="-", "-", IF(ABS(AC49)=0, "-", ROUND(100*(AA49-AC49)/ABS(AC49), 1)))) -> -
D50: 水利組合費 | AC50: =IF(U50="-", "-", IF(Y50="-", "-", IF(ABS(Y50)=0, "-", ROUND(100*(U50-Y50)/ABS(Y50), 10)))) -> - | AD50: =IF(Z50="-", "-", IF(AB50="-", "-", IF(ABS(AB50)=0, "-", ROUND(100*(Z50-AB50)/ABS(AB50), 1)))) -> - | AE50: =IF(AA50="-", "-", IF(AC50="-", "-", IF(ABS(AC50)=0, "-", ROUND(100*(AA50-AC50)/ABS(AC50), 1)))) -> -
D51: 揚水ポンプ組合費 | AC51: =IF(U51="-", "-", IF(Y51="-", "-", IF(ABS(Y51)=0, "-", ROUND(100*(U51-Y51)/ABS(Y51), 10)))) -> - | AD51: =IF(Z51="-", "-", IF(AB51="-", "-", IF(ABS(AB51)=0, "-", ROUND(100*(Z51-AB51)/ABS(AB51), 1)))) -> - | AE51: =IF(AA51="-", "-", IF(AC51="-", "-", IF(ABS(AC51)=0, "-", ROUND(100*(AA51-AC51)/ABS(AC51), 1)))) -> -
D52: その他 | AC52: =IF(U52="-", "-", IF(Y52="-", "-", IF(ABS(Y52)=0, "-", ROUND(100*(U52-Y52)/ABS(Y52), 10)))) -> - | AD52: =IF(Z52="-", "-", IF(AB52="-", "-", IF(ABS(AB52)=0, "-", ROUND(100*(Z52-AB52)/ABS(AB52), 1)))) -> - | AE52: =IF(AA52="-", "-", IF(AC52="-", "-", IF(ABS(AC52)=0, "-", ROUND(100*(AA52-AC52)/ABS(AC52), 1)))) -> -
D53: 計 | AC53: =IF(U53="-", "-", IF(Y53="-", "-", IF(ABS(Y53)=0, "-", ROUND(100*(U53-Y53)/ABS(Y53), 10)))) -> - | AD53: =IF(Z53="-", "-", IF(AB53="-", "-", IF(ABS(AB53)=0, "-", ROUND(100*(Z53-AB53)/ABS(AB53), 1)))) -> - | AE53: =IF(AA53="-", "-", IF(AC53="-", "-", IF(ABS(AC53)=0, "-", ROUND(100*(AA53-AC53)/ABS(AC53), 1)))) -> -

Sheet No.5
B1: =AB4 | E1: 年産 米生産費統計結果（組織法人経営体） 集計結果検討表 Ｎｏ．５
G3: 集計番号 | J3: 集計名称 | Q3: 集計経営体数 | V3: 集計倍率 | AB3: 調査年 | AG3: 都道府県等 | AL3: 経営種類 | AQ3: 生産費区分 | AV3: 規模階層 | BA3: 平均値種類 | BF3: 加重・総和の別 | BK3: 集計区分
B4: 本年産 | G4: =IF(No.1!G4="","",No.1!G4) | J4: =IF(No.1!J4="","",No.1!J4) | Q4: =IF(No.1!Q4="","",No.1!Q4) | V4: =IF(No.1!V4="","",No.1!V4) | AB4: =IF(No.1!AB4="","",No.1!AB4) | AG4: =IF(No.1!AG4="","",No.1!AG4) | AH4: =IF(No.1!AH4="","",No.1!AH4) | AI4: =IF(No.1!AI4="","",No.1!AI4) | AJ4: =IF(No.1!AJ4="","",No.1!AJ4) | AK4: =IF(No.1!AK4="","",No.1!AK4) | AL4: =IF(No.1!AL4="","",No.1!AL4) | AM4: =IF(No.1!AM4="","",No.1!AM4) | AN4: =IF(No.1!AN4="","",No.1!AN4) | ... BO4: =IF(No.1!BO4="","",No.1!BO4)
B5: 前年産 | G5: =IF(No.1!G5="","",No.1!G5) | J5: =IF(No.1!J5="","",No.1!J5) | Q5: =IF(No.1!Q5="","",No.1!Q5) | V5: =IF(No.1!V5="","",No.1!V5)
B7: 24 生産物の処分内訳 | AP7: 単位：円、kg | AU7: 25 減価償却費 | BX7: 単位：円、台
J8: 数量 | U8: 価額 | AF8: 単価 | BN8: 稲作負担分
J9: =IF($B$1<>"",$B$1,"") | N9: =IF($B$1<>"",$B$1-1,"") | R9: 増減率 | U9: =IF($B$1<>"",$B$1,"") | Y9: =IF($B$1<>"",$B$1-1,"") | AC9: 増減率 | AF9: =IF($B$1<>"",$B$1,"") | AJ9: =IF($B$1<>"",$B$1-1,"") | AN9: 増減率 | BC9: =IF($B$1<>"",$B$1,"") | BG9: =IF($B$1<>"",$B$1-1,"") | BK9: 増減率 | BN9: =IF($B$1<>"",$B$1,"") | BR9: =IF($B$1<>"",$B$1-1,"") | BV9: 増減率
B10: 玄米（予定を含む） | C10: 販売用 | E10: 主食用 | R10: =IF(J10="-", "-", IF(N10="-", "-", IF(ABS(N10)=0, "-", ROUND(100*(J10-N10)/ABS(N10), 10)))) -> - | S10: =IF(O10="-", "-", IF(Q10="-", "-", IF(ABS(Q10)=0, "-", ROUND(100*(O10-Q10)/ABS(Q10), 1)))) -> - | T10: =IF(P10="-", "-", IF(R10="-", "-", IF(ABS(R10)=0, "-", ROUND(100*(P10-R10)/ABS(R10), 1)))) -> - | AC10: =IF(U10="-", "-", IF(Y10="-", "-", IF(ABS(Y10)=0, "-", ROUND(100*(U10-Y10)/ABS(Y10), 10)))) -> - | AD10: =IF(Z10="-", "-", IF(AB10="-", "-", IF(ABS(AB10)=0, "-", ROUND(100*(Z10-AB10)/ABS(AB10), 1)))) -> - | AE10: =IF(AA10="-", "-", IF(AC10="-", "-", IF(ABS(AC10)=0, "-", ROUND(100*(AA10-AC10)/ABS(AC10), 1)))) -> - | AN10: =IF(AF10="-", "-", IF(AJ10="-", "-", IF(ABS(AJ10)=0, "-", ROUND(100*(AF10-AJ10)/ABS(AJ10), 10)))) -> - | AO10: =IF(AK10="-", "-", IF(AM10="-", "-", IF(ABS(AM10)=0, "-", ROUND(100*(AK10-AM10)/ABS(AM10), 1)))) -> - | AP10: =IF(AL10="-", "-", IF(AN10="-", "-", IF(ABS(AN10)=0, "-", ROUND(100*(AL10-AN10)/ABS(AN10), 1)))) -> - | AU10: 建物・構築物 | AV10: 住宅 | BV10: =IF(BN10="-", "-", IF(BR10="-", "-", IF(ABS(BR10)=0, "-", ROUND(100*(BN10-BR10)/ABS(BR10), 10)))) -> - | BW10: =IF(BS10="-", "-", IF(BU10="-", "-", IF(ABS(BU10)=0, "-", ROUND(100*(BS10-BU10)/ABS(BU10), 1)))) -> - | BX10: =IF(BT10="-", "-", IF(BV10="-", "-", IF(ABS(BV10)=0, "-", ROUND(100*(BT10-BV10)/ABS(BV10), 1)))) -> -
E11: 加工用 | R11: =IF(J11="-", "-", IF(N11="-", "-", IF(ABS(N11)=0, "-", ROUND(100*(J11-N11)/ABS(N11), 10)))) -> - | S11: =IF(O11="-", "-", IF(Q11="-", "-", IF(ABS(Q11)=0, "-", ROUND(100*(O11-Q11)/ABS(Q11), 1)))) -> - | T11: =IF(P11="-", "-", IF(R11="-", "-", IF(ABS(R11)=0, "-", ROUND(100*(P11-R11)/ABS(R11), 1)))) -> - | AC11: =IF(U11="-", "-", IF(Y11="-", "-", IF(ABS(Y11)=0, "-", ROUND(100*(U11-Y11)/ABS(Y11), 10)))) -> - | AD11: =IF(Z11="-", "-", IF(AB11="-", "-", IF(ABS(AB11)=0, "-", ROUND(100*(Z11-AB11)/ABS(AB11), 1)))) -> - | AE11: =IF(AA11="-", "-", IF(AC11="-", "-", IF(ABS(AC11)=0, "-", ROUND(100*(AA11-AC11)/ABS(AC11), 1)))) -> - | AN11: =IF(AF11="-", "-", IF(AJ11="-", "-", IF(ABS(AJ11)=0, "-", ROUND(100*(AF11-AJ11)/ABS(AJ11), 10)))) -> - | AO11: =IF(AK11="-", "-", IF(AM11="-", "-", IF(ABS(AM11)=0, "-", ROUND(100*(AK11-AM11)/ABS(AM11), 1)))) -> - | AP11: =IF(AL11="-", "-", IF(AN11="-", "-", IF(ABS(AN11)=0, "-", ROUND(100*(AL11-AN11)/ABS(AN11), 1)))) -> - | AV11: 事務所 | BV11: =IF(BN11="-", "-", IF(BR11="-", "-", IF(ABS(BR11)=0, "-", ROUND(100*(BN11-BR11)/ABS(BR11), 10)))) -> - | BW11: =IF(BS11="-", "-", IF(BU11="-", "-", IF(ABS(BU11)=0, "-", ROUND(100*(BS11-BU11)/ABS(BU11), 1)))) -> - | BX11: =IF(BT11="-", "-", IF(BV11="-", "-", IF(ABS(BV11)=0, "-", ROUND(100*(BT11-BV11)/ABS(BV11), 1)))) -> -
E12: 区分出荷 | R12: =IF(J12="-", "-", IF(N12="-", "-", IF(ABS(N12)=0, "-", ROUND(100*(J12-N12)/ABS(N12), 10)))) -> - | S12: =IF(O12="-", "-", IF(Q12="-", "-", IF(ABS(Q12)=0, "-", ROUND(100*(O12-Q12)/ABS(Q12), 1)))) -> - | T12: =IF(P12="-", "-", IF(R12="-", "-", IF(ABS(R12)=0, "-", ROUND(100*(P12-R12)/ABS(R12), 1)))) -> - | AC12: =IF(U12="-", "-", IF(Y12="-", "-", IF(ABS(Y12)=0, "-", ROUND(100*(U12-Y12)/ABS(Y12), 10)))) -> - | AD12: =IF(Z12="-", "-", IF(AB12="-", "-", IF(ABS(AB12)=0, "-", ROUND(100*(Z12-AB12)/ABS(AB12), 1)))) -> - | AE12: =IF(AA12="-", "-", IF(AC12="-", "-", IF(ABS(AC12)=0, "-", ROUND(100*(AA12-AC12)/ABS(AC12), 1)))) -> - | AN12: =IF(AF12="-", "-", IF(AJ12="-", "-", IF(ABS(AJ12)=0, "-", ROUND(100*(AF12-AJ12)/ABS(AJ12), 10)))) -> - | AO12: =IF(AK12="-", "-", IF(AM12="-", "-", IF(ABS(AM12)=0, "-", ROUND(100*(AK12-AM12)/ABS(AM12), 1)))) -> - | AP12: =IF(AL12="-", "-", IF(AN12="-", "-", IF(ABS(AN12)=0, "-", ROUND(100*(AL12-AN12)/ABS(AN12), 1)))) -> - | AV12: 納屋・倉庫 | BV12: =IF(BN12="-", "-", IF(BR12="-", "-", IF(ABS(BR12)=0, "-", ROUND(100*(BN12-BR12)/ABS(BR12), 10)))) -> - | BW12: =IF(BS12="-", "-", IF(BU12="-", "-", IF(ABS(BU12)=0, "-", ROUND(100*(BS12-BU12)/ABS(BU12), 1)))) -> - | BX12: =IF(BT12="-", "-", IF(BV12="-", "-", IF(ABS(BV12)=0, "-", ROUND(100*(BT12-BV12)/ABS(BV12), 1)))) -> -
E13: 小計 | R13: =IF(J13="-", "-", IF(N13="-", "-", IF(ABS(N13)=0, "-", ROUND(100*(J13-N13)/ABS(N13), 10)))) -> - | S13: =IF(O13="-", "-", IF(Q13="-", "-", IF(ABS(Q13)=0, "-", ROUND(100*(O13-Q13)/ABS(Q13), 1)))) -> - | T13: =IF(P13="-", "-", IF(R13="-", "-", IF(ABS(R13)=0, "-", ROUND(100*(P13-R13)/ABS(R13), 1)))) -> - | AC13: =IF(U13="-", "-", IF(Y13="-", "-", IF(ABS(Y13)=0, "-", ROUND(100*(U13-Y13)/ABS(Y13), 10)))) -> - | AD13: =IF(Z13="-", "-", IF(AB13="-", "-", IF(ABS(AB13)=0, "-", ROUND(100*(Z13-AB13)/ABS(AB13), 1)))) -> - | AE13: =IF(AA13="-", "-", IF(AC13="-", "-", IF(ABS(AC13)=0, "-", ROUND(100*(AA13-AC13)/ABS(AC13), 1)))) -> - | AN13: =IF(AF13="-", "-", IF(AJ13="-", "-", IF(ABS(AJ13)=0, "-", ROUND(100*(AF13-AJ13)/ABS(AJ13), 10)))) -> - | AO13: =IF(AK13="-", "-", IF(AM13="-", "-", IF(ABS(AM13)=0, "-", ROUND(100*(AK13-AM13)/ABS(AM13), 1)))) -> - | AP13: =IF(AL13="-", "-", IF(AN13="-", "-", IF(ABS(AN13)=0, "-", ROUND(100*(AL13-AN13)/ABS(AN13), 1)))) -> - | AV13: 作業場 | BV13: =IF(BN13="-", "-", IF(BR13="-", "-", IF(ABS(BR13)=0, "-", ROUND(100*(BN13-BR13)/ABS(BR13), 10)))) -> - | BW13: =IF(BS13="-", "-", IF(BU13="-", "-", IF(ABS(BU13)=0, "-", ROUND(100*(BS13-BU13)/ABS(BU13), 1)))) -> - | BX13: =IF(BT13="-", "-", IF(BV13="-", "-", IF(ABS(BV13)=0, "-", ROUND(100*(BT13-BV13)/ABS(BV13), 1)))) -> -
C14: 組織用 | E14: 種子用 | R14: =IF(J14="-", "-", IF(N14="-", "-", IF(ABS(N14)=0, "-", ROUND(100*(J14-N14)/ABS(N14), 10)))) -> - | S14: =IF(O14="-", "-", IF(Q14="-", "-", IF(ABS(Q14)=0, "-", ROUND(100*(O14-Q14)/ABS(Q14), 1)))) -> - | T14: =IF(P14="-", "-", IF(R14="-", "-", IF(ABS(R14)=0, "-", ROUND(100*(P14-R14)/ABS(R14), 1)))) -> - | AC14: =IF(U14="-", "-", IF(Y14="-", "-", IF(ABS(Y14)=0, "-", ROUND(100*(U14-Y14)/ABS(Y14), 10)))) -> - | AD14: =IF(Z14="-", "-", IF(AB14="-", "-", IF(ABS(AB14)=0, "-", ROUND(100*(Z14-AB14)/ABS(AB14), 1)))) -> - | AE14: =IF(AA14="-", "-", IF(AC14="-", "-", IF(ABS(AC14)=0, "-", ROUND(100*(AA14-AC14)/ABS(AC14), 1)))) -> - | AN14: =IF(AF14="-", "-", IF(AJ14="-", "-", IF(ABS(AJ14)=0, "-", ROUND(100*(AF14-AJ14)/ABS(AJ14), 10)))) -> - | AO14: =IF(AK14="-", "-", IF(AM14="-", "-", IF(ABS(AM14)=0, "-", ROUND(100*(AK14-AM14)/ABS(AM14), 1)))) -> - | AP14: =IF(AL14="-", "-", IF(AN14="-", "-", IF(ABS(AN14)=0, "-", ROUND(100*(AL14-AN14)/ABS(AN14), 1)))) -> - | AV14: 車庫 | BV14: =IF(BN14="-", "-", IF(BR14="-", "-", IF(ABS(BR14)=0, "-", ROUND(100*(BN14-BR14)/ABS(BR14), 10)))) -> - | BW14: =IF(BS14="-", "-", IF(BU14="-", "-", IF(ABS(BU14)=0, "-", ROUND(100*(BS14-BU14)/ABS(BU14), 1)))) -> - | BX14: =IF(BT14="-", "-", IF(BV14="-", "-", IF(ABS(BV14)=0, "-", ROUND(100*(BT14-BV14)/ABS(BV14), 1)))) -> -
E15: 飯米用 | R15: =IF(J15="-", "-", IF(N15="-", "-", IF(ABS(N15)=0, "-", ROUND(100*(J15-N15)/ABS(N15), 10)))) -> - | S15: =IF(O15="-", "-", IF(Q15="-", "-", IF(ABS(Q15)=0, "-", ROUND(100*(O15-Q15)/ABS(Q15), 1)))) -> - | T15: =IF(P15="-", "-", IF(R15="-", "-", IF(ABS(R15)=0, "-", ROUND(100*(P15-R15)/ABS(R15), 1)))) -> - | AC15: =IF(U15="-", "-", IF(Y15="-", "-", IF(ABS(Y15)=0, "-", ROUND(100*(U15-Y15)/ABS(Y15), 10)))) -> - | AD15: =IF(Z15="-", "-", IF(AB15="-", "-", IF(ABS(AB15)=0, "-", ROUND(100*(Z15-AB15)/ABS(AB15), 1)))) -> - | AE15: =IF(AA15="-", "-", IF(AC15="-", "-", IF(ABS(AC15)=0, "-", ROUND(100*(AA15-AC15)/ABS(AC15), 1)))) -> - | AN15: =IF(AF15="-", "-", IF(AJ15="-", "-", IF(ABS(AJ15)=0, "-", ROUND(100*(AF15-AJ15)/ABS(AJ15), 10)))) -> - | AO15: =IF(AK15="-", "-", IF(AM15="-", "-", IF(ABS(AM15)=0, "-", ROUND(100*(AK15-AM15)/ABS(AM15), 1)))) -> - | AP15: =IF(AL15="-", "-", IF(AN15="-", "-", IF(ABS(AN15)=0, "-", ROUND(100*(AL15-AN15)/ABS(AN15), 1)))) -> - | AV15: ライスセンター | BV15: =IF(BN15="-", "-", IF(BR15="-", "-", IF(ABS(BR15)=0, "-", ROUND(100*(BN15-BR15)/ABS(BR15), 10)))) -> - | BW15: =IF(BS15="-", "-", IF(BU15="-", "-", IF(ABS(BU15)=0, "-", ROUND(100*(BS15-BU15)/ABS(BU15), 1)))) -> - | BX15: =IF(BT15="-", "-", IF(BV15="-", "-", IF(ABS(BV15)=0, "-", ROUND(100*(BT15-BV15)/ABS(BV15), 1)))) -> -
E16: その他 | R16: =IF(J16="-", "-", IF(N16="-", "-", IF(ABS(N16)=0, "-", ROUND(100*(J16-N16)/ABS(N16), 10)))) -> - | S16: =IF(O16="-", "-", IF(Q16="-", "-", IF(ABS(Q16)=0, "-", ROUND(100*(O16-Q16)/ABS(Q16), 1)))) -> - | T16: =IF(P16="-", "-", IF(R16="-", "-", IF(ABS(R16)=0, "-", ROUND(100*(P16-R16)/ABS(R16), 1)))) -> - | AC16: =IF(U16="-", "-", IF(Y16="-", "-", IF(ABS(Y16)=0, "-", ROUND(100*(U16-Y16)/ABS(Y16), 10)))) -> - | AD16: =IF(Z16="-", "-", IF(AB16="-", "-", IF(ABS(AB16)=0, "-", ROUND(100*(Z16-AB16)/ABS(AB16), 1)))) -> - | AE16: =IF(AA16="-", "-", IF(AC16="-", "-", IF(ABS(AC16)=0, "-", ROUND(100*(AA16-AC16)/ABS(AC16), 1)))) -> - | AN16: =IF(AF16="-", "-", IF(AJ16="-", "-", IF(ABS(AJ16)=0, "-", ROUND(100*(AF16-AJ16)/ABS(AJ16), 10)))) -> - | AO16: =IF(AK16="-", "-", IF(AM16="-", "-", IF(ABS(AM16)=0, "-", ROUND(100*(AK16-AM16)/ABS(AM16), 1)))) -> - | AP16: =IF(AL16="-", "-", IF(AN16="-", "-", IF(ABS(AN16)=0, "-", ROUND(100*(AL16-AN16)/ABS(AN16), 1)))) -> - | AV16: 育苗ハウス | BV16: =IF(BN16="-", "-", IF(BR16="-", "-", IF(ABS(BR16)=0, "-", ROUND(100*(BN16-BR16)/ABS(BR16), 10)))) -> - | BW16: =IF(BS16="-", "-", IF(BU16="-", "-", IF(ABS(BU16)=0, "-", ROUND(100*(BS16-BU16)/ABS(BU16), 1)))) -> - | BX16: =IF(BT16="-", "-", IF(BV16="-", "-", IF(ABS(BV16)=0, "-", ROUND(100*(BT16-BV16)/ABS(BV16), 1)))) -> -
E17: 小計 | R17: =IF(J17="-", "-", IF(N17="-", "-", IF(ABS(N17)=0, "-", ROUND(100*(J17-N17)/ABS(N17), 10)))) -> - | S17: =IF(O17="-", "-", IF(Q17="-", "-", IF(ABS(Q17)=0, "-", ROUND(100*(O17-Q17)/ABS(Q17), 1)))) -> - | T17: =IF(P17="-", "-", IF(R17="-", "-", IF(ABS(R17)=0, "-", ROUND(100*(P17-R17)/ABS(R17), 1)))) -> - | AC17: =IF(U17="-", "-", IF(Y17="-", "-", IF(ABS(Y17)=0, "-", ROUND(100*(U17-Y17)/ABS(Y17), 10)))) -> - | AD17: =IF(Z17="-", "-", IF(AB17="-", "-", IF(ABS(AB17)=0, "-", ROUND(100*(Z17-AB17)/ABS(AB17), 1)))) -> - | AE17: =IF(AA17="-", "-", IF(AC17="-", "-", IF(ABS(AC17)=0, "-", ROUND(100*(AA17-AC17)/ABS(AC17), 1)))) -> - | AN17: =IF(AF17="-", "-", IF(AJ17="-", "-", IF(ABS(AJ17)=0, "-", ROUND(100*(AF17-AJ17)/ABS(AJ17), 10)))) -> - | AO17: =IF(AK17="-", "-", IF(AM17="-", "-", IF(ABS(AM17)=0, "-", ROUND(100*(AK17-AM17)/ABS(AM17), 1)))) -> - | AP17: =IF(AL17="-", "-", IF(AN17="-", "-", IF(ABS(AN17)=0, "-", ROUND(100*(AL17-AN17)/ABS(AN17), 1)))) -> - | AV17: 稲架 | BV17: =IF(BN17="-", "-", IF(BR17="-", "-", IF(ABS(BR17)=0, "-", ROUND(100*(BN17-BR17)/ABS(BR17), 10)))) -> - | BW17: =IF(BS17="-", "-", IF(BU17="-", "-", IF(ABS(BU17)=0, "-", ROUND(100*(BS17-BU17)/ABS(BU17), 1)))) -> - | BX17: =IF(BT17="-", "-", IF(BV17="-", "-", IF(ABS(BV17)=0, "-", ROUND(100*(BT17-BV17)/ABS(BV17), 1)))) -> -
C18: 合計 | R18: =IF(J18="-", "-", IF(N18="-", "-", IF(ABS(N18)=0, "-", ROUND(100*(J18-N18)/ABS(N18), 10)))) -> - | S18: =IF(O18="-", "-", IF(Q18="-", "-", IF(ABS(Q18)=0, "-", ROUND(100*(O18-Q18)/ABS(Q18), 1)))) -> - | T18: =IF(P18="-", "-", IF(R18="-", "-", IF(ABS(R18)=0, "-", ROUND(100*(P18-R18)/ABS(R18), 1)))) -> - | AC18: =IF(U18="-", "-", IF(Y18="-", "-", IF(ABS(Y18)=0, "-", ROUND(100*(U18-Y18)/ABS(Y18), 10)))) -> - | AD18: =IF(Z18="-", "-", IF(AB18="-", "-", IF(ABS(AB18)=0, "-", ROUND(100*(Z18-AB18)/ABS(AB18), 1)))) -> - | AE18: =IF(AA18="-", "-", IF(AC18="-", "-", IF(ABS(AC18)=0, "-", ROUND(100*(AA18-AC18)/ABS(AC18), 1)))) -> - | AN18: =IF(AF18="-", "-", IF(AJ18="-", "-", IF(ABS(AJ18)=0, "-", ROUND(100*(AF18-AJ18)/ABS(AJ18), 10)))) -> - | AO18: =IF(AK18="-", "-", IF(AM18="-", "-", IF(ABS(AM18)=0, "-", ROUND(100*(AK18-AM18)/ABS(AM18), 1)))) -> - | AP18: =IF(AL18="-", "-", IF(AN18="-", "-", IF(ABS(AN18)=0, "-", ROUND(100*(AL18-AN18)/ABS(AN18), 1)))) -> - | AV18: コンクリートけい畔 | BV18: =IF(BN18="-", "-", IF(BR18="-", "-", IF(ABS(BR18)=0, "-", ROUND(100*(BN18-BR18)/ABS(BR18), 10)))) -> - | BW18: =IF(BS18="-", "-", IF(BU18="-", "-", IF(ABS(BU18)=0, "-", ROUND(100*(BS18-BU18)/ABS(BU18), 1)))) -> - | BX18: =IF(BT18="-", "-", IF(BV18="-", "-", IF(ABS(BV18)=0, "-", ROUND(100*(BT18-BV18)/ABS(BV18), 1)))) -> -
B19: いなわら等 | C19: 販売 | E19: 加工用 | R19: =IF(J19="-", "-", IF(N19="-", "-", IF(ABS(N19)=0, "-", ROUND(100*(J19-N19)/ABS(N19), 10)))) -> - | S19: =IF(O19="-", "-", IF(Q19="-", "-", IF(ABS(Q19)=0, "-", ROUND(100*(O19-Q19)/ABS(Q19), 1)))) -> - | T19: =IF(P19="-", "-", IF(R19="-", "-", IF(ABS(R19)=0, "-", ROUND(100*(P19-R19)/ABS(R19), 1)))) -> - | AC19: =IF(U19="-", "-", IF(Y19="-", "-", IF(ABS(Y19)=0, "-", ROUND(100*(U19-Y19)/ABS(Y19), 10)))) -> - | AD19: =IF(Z19="-", "-", IF(AB19="-", "-", IF(ABS(AB19)=0, "-", ROUND(100*(Z19-AB19)/ABS(AB19), 1)))) -> - | AE19: =IF(AA19="-", "-", IF(AC19="-", "-", IF(ABS(AC19)=0, "-", ROUND(100*(AA19-AC19)/ABS(AC19), 1)))) -> - | AN19: =IF(AF19="-", "-", IF(AJ19="-", "-", IF(ABS(AJ19)=0, "-", ROUND(100*(AF19-AJ19)/ABS(AJ19), 10)))) -> - | AO19: =IF(AK19="-", "-", IF(AM19="-", "-", IF(ABS(AM19)=0, "-", ROUND(100*(AK19-AM19)/ABS(AM19), 1)))) -> - | AP19: =IF(AL19="-", "-", IF(AN19="-", "-", IF(ABS(AN19)=0, "-", ROUND(100*(AL19-AN19)/ABS(AN19), 1)))) -> - | AV19: 暗きょ排水施設 | BV19: =IF(BN19="-", "-", IF(BR19="-", "-", IF(ABS(BR19)=0, "-", ROUND(100*(BN19-BR19)/ABS(BR19), 10)))) -> - | BW19: =IF(BS19="-", "-", IF(BU19="-", "-", IF(ABS(BU19)=0, "-", ROUND(100*(BS19-BU19)/ABS(BU19), 1)))) -> - | BX19: =IF(BT19="-", "-", IF(BV19="-", "-", IF(ABS(BV19)=0, "-", ROUND(100*(BT19-BV19)/ABS(BV19), 1)))) -> -
E20: その他 | R20: =IF(J20="-", "-", IF(N20="-", "-", IF(ABS(N20)=0, "-", ROUND(100*(J20-N20)/ABS(N20), 10)))) -> - | S20: =IF(O20="-", "-", IF(Q20="-", "-", IF(ABS(Q20)=0, "-", ROUND(100*(O20-Q20)/ABS(Q20), 1)))) -> - | T20: =IF(P20="-", "-", IF(R20="-", "-", IF(ABS(R20)=0, "-", ROUND(100*(P20-R20)/ABS(R20), 1)))) -> - | AC20: =IF(U20="-", "-", IF(Y20="-", "-", IF(ABS(Y20)=0, "-", ROUND(100*(U20-Y20)/ABS(Y20), 10)))) -> - | AD20: =IF(Z20="-", "-", IF(AB20="-", "-", IF(ABS(AB20)=0, "-", ROUND(100*(Z20-AB20)/ABS(AB20), 1)))) -> - | AE20: =IF(AA20="-", "-", IF(AC20="-", "-", IF(ABS(AC20)=0, "-", ROUND(100*(AA20-AC20)/ABS(AC20), 1)))) -> - | AN20: =IF(AF20="-", "-", IF(AJ20="-", "-", IF(ABS(AJ20)=0, "-", ROUND(100*(AF20-AJ20)/ABS(AJ20), 10)))) -> - | AO20: =IF(AK20="-", "-", IF(AM20="-", "-", IF(ABS(AM20)=0, "-", ROUND(100*(AK20-AM20)/ABS(AM20), 1)))) -> - | AP20: =IF(AL20="-", "-", IF(AN20="-", "-", IF(ABS(AN20)=0, "-", ROUND(100*(AL20-AN20)/ABS(AN20), 1)))) -> - | AV20: 客土 | BV20: =IF(BN20="-", "-", IF(BR20="-", "-", IF(ABS(BR20)=0, "-", ROUND(100*(BN20-BR20)/ABS(BR20), 10)))) -> - | BW20: =IF(BS20="-", "-", IF(BU20="-", "-", IF(ABS(BU20)=0, "-", ROUND(100*(BS20-BU20)/ABS(BU20), 1)))) -> - | BX20: =IF(BT20="-", "-", IF(BV20="-", "-", IF(ABS(BV20)=0, "-", ROUND(100*(BT20-BV20)/ABS(BV20), 1)))) -> -
C21: 組織用 | E21: 生わら | R21: =IF(J21="-", "-", IF(N21="-", "-", IF(ABS(N21)=0, "-", ROUND(100*(J21-N21)/ABS(N21), 10)))) -> - | S21: =IF(O21="-", "-", IF(Q21="-", "-", IF(ABS(Q21)=0, "-", ROUND(100*(O21-Q21)/ABS(Q21), 1)))) -> - | T21: =IF(P21="-", "-", IF(R21="-", "-", IF(ABS(R21)=0, "-", ROUND(100*(P21-R21)/ABS(R21), 1)))) -> - | AV21: 作業道 | BV21: =IF(BN21="-", "-", IF(BR21="-", "-", IF(ABS(BR21)=0, "-", ROUND(100*(BN21-BR21)/ABS(BR21), 10)))) -> - | BW21: =IF(BS21="-", "-", IF(BU21="-", "-", IF(ABS(BU21)=0, "-", ROUND(100*(BS21-BU21)/ABS(BU21), 1)))) -> - | BX21: =IF(BT21="-", "-", IF(BV21="-", "-", IF(ABS(BV21)=0, "-", ROUND(100*(BT21-BV21)/ABS(BV21), 1)))) -> -
E22: 乾燥わら | R22: =IF(J22="-", "-", IF(N22="-", "-", IF(ABS(N22)=0, "-", ROUND(100*(J22-N22)/ABS(N22), 10)))) -> - | S22: =IF(O22="-", "-", IF(Q22="-", "-", IF(ABS(Q22)=0, "-", ROUND(100*(O22-Q22)/ABS(Q22), 1)))) -> - | T22: =IF(P22="-", "-", IF(R22="-", "-", IF(ABS(R22)=0, "-", ROUND(100*(P22-R22)/ABS(R22), 1)))) -> - | AC22: =IF(U22="-", "-", IF(Y22="-", "-", IF(ABS(Y22)=0, "-", ROUND(100*(U22-Y22)/ABS(Y22), 10)))) -> - | AD22: =IF(Z22="-", "-", IF(AB22="-", "-", IF(ABS(AB22)=0, "-", ROUND(100*(Z22-AB22)/ABS(AB22), 1)))) -> - | AE22: =IF(AA22="-", "-", IF(AC22="-", "-", IF(ABS(AC22)=0, "-", ROUND(100*(AA22-AC22)/ABS(AC22), 1)))) -> - | AN22: =IF(AF22="-", "-", IF(AJ22="-", "-", IF(ABS(AJ22)=0, "-", ROUND(100*(AF22-AJ22)/ABS(AJ22), 10)))) -> - | AO22: =IF(AK22="-", "-", IF(AM22="-", "-", IF(ABS(AM22)=0, "-", ROUND(100*(AK22-AM22)/ABS(AM22), 1)))) -> - | AP22: =IF(AL22="-", "-", IF(AN22="-", "-", IF(ABS(AN22)=0, "-", ROUND(100*(AL22-AN22)/ABS(AN22), 1)))) -> - | AV22: 用水路 | BV22: =IF(BN22="-", "-", IF(BR22="-", "-", IF(ABS(BR22)=0, "-", ROUND(100*(BN22-BR22)/ABS(BR22), 10)))) -> - | BW22: =IF(BS22="-", "-", IF(BU22="-", "-", IF(ABS(BU22)=0, "-", ROUND(100*(BS22-BU22)/ABS(BU22), 1)))) -> - | BX22: =IF(BT22="-", "-", IF(BV22="-", "-", IF(ABS(BV22)=0, "-", ROUND(100*(BT22-BV22)/ABS(BV22), 1)))) -> -
E23: その他 | R23: =IF(J23="-", "-", IF(N23="-", "-", IF(ABS(N23)=0, "-", ROUND(100*(J23-N23)/ABS(N23), 10)))) -> - | S23: =IF(O23="-", "-", IF(Q23="-", "-", IF(ABS(Q23)=0, "-", ROUND(100*(O23-Q23)/ABS(Q23), 1)))) -> - | T23: =IF(P23="-", "-", IF(R23="-", "-", IF(ABS(R23)=0, "-", ROUND(100*(P23-R23)/ABS(R23), 1)))) -> - | AV23: たい肥盤 | BV23: =IF(BN23="-", "-", IF(BR23="-", "-", IF(ABS(BR23)=0, "-", ROUND(100*(BN23-BR23)/ABS(BR23), 10)))) -> - | BW23: =IF(BS23="-", "-", IF(BU23="-", "-", IF(ABS(BU23)=0, "-", ROUND(100*(BS23-BU23)/ABS(BU23), 1)))) -> - | BX23: =IF(BT23="-", "-", IF(BV23="-", "-", IF(ABS(BV23)=0, "-", ROUND(100*(BT23-BV23)/ABS(BV23), 1)))) -> -
C24: いなわら小計 | R24: =IF(J24="-", "-", IF(N24="-", "-", IF(ABS(N24)=0, "-", ROUND(100*(J24-N24)/ABS(N24), 10)))) -> - | S24: =IF(O24="-", "-", IF(Q24="-", "-", IF(ABS(Q24)=0, "-", ROUND(100*(O24-Q24)/ABS(Q24), 1)))) -> - | T24: =IF(P24="-", "-", IF(R24="-", "-", IF(ABS(R24)=0, "-", ROUND(100*(P24-R24)/ABS(R24), 1)))) -> - | AC24: =IF(U24="-", "-", IF(Y24="-", "-", IF(ABS(Y24)=0, "-", ROUND(100*(U24-Y24)/ABS(Y24), 10)))) -> - | AD24: =IF(Z24="-", "-", IF(AB24="-", "-", IF(ABS(AB24)=0, "-", ROUND(100*(Z24-AB24)/ABS(AB24), 1)))) -> - | AE24: =IF(AA24="-", "-", IF(AC24="-", "-", IF(ABS(AC24)=0, "-", ROUND(100*(AA24-AC24)/ABS(AC24), 1)))) -> - | AV24: その他 | BV24: =IF(BN24="-", "-", IF(BR24="-", "-", IF(ABS(BR24)=0, "-", ROUND(100*(BN24-BR24)/ABS(BR24), 10)))) -> - | BW24: =IF(BS24="-", "-", IF(BU24="-", "-", IF(ABS(BU24)=0, "-", ROUND(100*(BS24-BU24)/ABS(BU24), 1)))) -> - | BX24: =IF(BT24="-", "-", IF(BV24="-", "-", IF(ABS(BV24)=0, "-", ROUND(100*(BT24-BV24)/ABS(BV24), 1)))) -> -
C25: くず米 | R25: =IF(J25="-", "-", IF(N25="-", "-", IF(ABS(N25)=0, "-", ROUND(100*(J25-N25)/ABS(N25), 10)))) -> - | S25: =IF(O25="-", "-", IF(Q25="-", "-", IF(ABS(Q25)=0, "-", ROUND(100*(O25-Q25)/ABS(Q25), 1)))) -> - | T25: =IF(P25="-", "-", IF(R25="-", "-", IF(ABS(R25)=0, "-", ROUND(100*(P25-R25)/ABS(R25), 1)))) -> - | AC25: =IF(U25="-", "-", IF(Y25="-", "-", IF(ABS(Y25)=0, "-", ROUND(100*(U25-Y25)/ABS(Y25), 10)))) -> - | AD25: =IF(Z25="-", "-", IF(AB25="-", "-", IF(ABS(AB25)=0, "-", ROUND(100*(Z25-AB25)/ABS(AB25), 1)))) -> - | AE25: =IF(AA25="-", "-", IF(AC25="-", "-", IF(ABS(AC25)=0, "-", ROUND(100*(AA25-AC25)/ABS(AC25), 1)))) -> - | AN25: =IF(AF25="-", "-", IF(AJ25="-", "-", IF(ABS(AJ25)=0, "-", ROUND(100*(AF25-AJ25)/ABS(AJ25), 10)))) -> - | AO25: =IF(AK25="-", "-", IF(AM25="-", "-", IF(ABS(AM25)=0, "-", ROUND(100*(AK25-AM25)/ABS(AM25), 1)))) -> - | AP25: =IF(AL25="-", "-", IF(AN25="-", "-", IF(ABS(AN25)=0, "-", ROUND(100*(AL25-AN25)/ABS(AN25), 1)))) -> - | AV25: 計 | BV25: =IF(BN25="-", "-", IF(BR25="-", "-", IF(ABS(BR25)=0, "-", ROUND(100*(BN25-BR25)/ABS(BR25), 10)))) -> - | BW25: =IF(BS25="-", "-", IF(BU25="-", "-", IF(ABS(BU25)=0, "-", ROUND(100*(BS25-BU25)/ABS(BU25), 1)))) -> - | BX25: =IF(BT25="-", "-", IF(BV25="-", "-", IF(ABS(BV25)=0, "-", ROUND(100*(BT25-BV25)/ABS(BV25), 1)))) -> -
C26: もみがら | R26: =IF(J26="-", "-", IF(N26="-", "-", IF(ABS(N26)=0, "-", ROUND(100*(J26-N26)/ABS(N26), 10)))) -> - | S26: =IF(O26="-", "-", IF(Q26="-", "-", IF(ABS(Q26)=0, "-", ROUND(100*(O26-Q26)/ABS(Q26), 1)))) -> - | T26: =IF(P26="-", "-", IF(R26="-", "-", IF(ABS(R26)=0, "-", ROUND(100*(P26-R26)/ABS(R26), 1)))) -> - | AC26: =IF(U26="-", "-", IF(Y26="-", "-", IF(ABS(Y26)=0, "-", ROUND(100*(U26-Y26)/ABS(Y26), 10)))) -> - | AD26: =IF(Z26="-", "-", IF(AB26="-", "-", IF(ABS(AB26)=0, "-", ROUND(100*(Z26-AB26)/ABS(AB26), 1)))) -> - | AE26: =IF(AA26="-", "-", IF(AC26="-", "-", IF(ABS(AC26)=0, "-", ROUND(100*(AA26-AC26)/ABS(AC26), 1)))) -> - | AN26: =IF(AF26="-", "-", IF(AJ26="-", "-", IF(ABS(AJ26)=0, "-", ROUND(100*(AF26-AJ26)/ABS(AJ26), 10)))) -> - | AO26: =IF(AK26="-", "-", IF(AM26="-", "-", IF(ABS(AM26)=0, "-", ROUND(100*(AK26-AM26)/ABS(AM26), 1)))) -> - | AP26: =IF(AL26="-", "-", IF(AN26="-", "-", IF(ABS(AN26)=0, "-", ROUND(100*(AL26-AN26)/ABS(AN26), 1)))) -> - | AX26: 処分差損失 | BV26: =IF(BN26="-", "-", IF(BR26="-", "-", IF(ABS(BR26)=0, "-", ROUND(100*(BN26-BR26)/ABS(BR26), 10)))) -> - | BW26: =IF(BS26="-", "-", IF(BU26="-", "-", IF(ABS(BU26)=0, "-", ROUND(100*(BS26-BU26)/ABS(BU26), 1)))) -> - | BX26: =IF(BT26="-", "-", IF(BV26="-", "-", IF(ABS(BV26)=0, "-", ROUND(100*(BT26-BV26)/ABS(BV26), 1)))) -> -
C27: 合計 | AC27: =IF(U27="-", "-", IF(Y27="-", "-", IF(ABS(Y27)=0, "-", ROUND(100*(U27-Y27)/ABS(Y27), 10)))) -> - | AD27: =IF(Z27="-", "-", IF(AB27="-", "-", IF(ABS(AB27)=0, "-", ROUND(100*(Z27-AB27)/ABS(AB27), 1)))) -> - | AE27: =IF(AA27="-", "-", IF(AC27="-", "-", IF(ABS(AC27)=0, "-", ROUND(100*(AA27-AC27)/ABS(AC27), 1)))) -> - | BC27: 使用台数（10経営体当たり） | BN27: 稲作負担分
AU28: 自動車 | AV28: 貨物自動車 | BK28: =IF(BC28="-", "-", IF(BG28="-", "-", IF(ABS(BG28)=0, "-", ROUND(100*(BC28-BG28)/ABS(BG28), 10)))) -> - | BL28: =IF(BH28="-", "-", IF(BJ28="-", "-", IF(ABS(BJ28)=0, "-", ROUND(100*(BH28-BJ28)/ABS(BJ28), 1)))) -> - | BM28: =IF(BI28="-", "-", IF(BK28="-", "-", IF(ABS(BK28)=0, "-", ROUND(100*(BI28-BK28)/ABS(BK28), 1)))) -> - | BV28: =IF(BN28="-", "-", IF(BR28="-", "-", IF(ABS(BR28)=0, "-", ROUND(100*(BN28-BR28)/ABS(BR28), 10)))) -> - | BW28: =IF(BS28="-", "-", IF(BU28="-", "-", IF(ABS(BU28)=0, "-", ROUND(100*(BS28-BU28)/ABS(BU28), 1)))) -> - | BX28: =IF(BT28="-", "-", IF(BV28="-", "-", IF(ABS(BV28)=0, "-", ROUND(100*(BT28-BV28)/ABS(BV28), 1)))) -> -
AV29: その他 | BV29: =IF(BN29="-", "-", IF(BR29="-", "-", IF(ABS(BR29)=0, "-", ROUND(100*(BN29-BR29)/ABS(BR29), 10)))) -> - | BW29: =IF(BS29="-", "-", IF(BU29="-", "-", IF(ABS(BU29)=0, "-", ROUND(100*(BS29-BU29)/ABS(BU29), 1)))) -> - | BX29: =IF(BT29="-", "-", IF(BV29="-", "-", IF(ABS(BV29)=0, "-", ROUND(100*(BT29-BV29)/ABS(BV29), 1)))) -> -
AV30: 計 | BV30: =IF(BN30="-", "-", IF(BR30="-", "-", IF(ABS(BR30)=0, "-", ROUND(100*(BN30-BR30)/ABS(BR30), 10)))) -> - | BW30: =IF(BS30="-", "-", IF(BU30="-", "-", IF(ABS(BU30)=0, "-", ROUND(100*(BS30-BU30)/ABS(BU30), 1)))) -> - | BX30: =IF(BT30="-", "-", IF(BV30="-", "-", IF(ABS(BV30)=0, "-", ROUND(100*(BT30-BV30)/ABS(BV30), 1)))) -> -
AX31: 処分差損失 | BV31: =IF(BN31="-", "-", IF(BR31="-", "-", IF(ABS(BR31)=0, "-", ROUND(100*(BN31-BR31)/ABS(BR31), 10)))) -> - | BW31: =IF(BS31="-", "-", IF(BU31="-", "-", IF(ABS(BU31)=0, "-", ROUND(100*(BS31-BU31)/ABS(BU31), 1)))) -> - | BX31: =IF(BT31="-", "-", IF(BV31="-", "-", IF(ABS(BV31)=0, "-", ROUND(100*(BT31-BV31)/ABS(BV31), 1)))) -> -
BC32: 使用台数（10経営体当たり） | BN32: 稲作負担分
AU33: 農機具 | AV33: 電動機 | BK33: =IF(BC33="-", "-", IF(BG33="-", "-", IF(ABS(BG33)=0, "-", ROUND(100*(BC33-BG33)/ABS(BG33), 10)))) -> - | BL33: =IF(BH33="-", "-", IF(BJ33="-", "-", IF(ABS(BJ33)=0, "-", ROUND(100*(BH33-BJ33)/ABS(BJ33), 1)))) -> - | BM33: =IF(BI33="-", "-", IF(BK33="-", "-", IF(ABS(BK33)=0, "-", ROUND(100*(BI33-BK33)/ABS(BK33), 1)))) -> - | BV33: =IF(BN33="-", "-", IF(BR33="-", "-", IF(ABS(BR33)=0, "-", ROUND(100*(BN33-BR33)/ABS(BR33), 10)))) -> - | BW33: =IF(BS33="-", "-", IF(BU33="-", "-", IF(ABS(BU33)=0, "-", ROUND(100*(BS33-BU33)/ABS(BU33), 1)))) -> - | BX33: =IF(BT33="-", "-", IF(BV33="-", "-", IF(ABS(BV33)=0, "-", ROUND(100*(BT33-BV33)/ABS(BV33), 1)))) -> -
B34: 任意項目 | AV34: 発動機 | BK34: =IF(BC34="-", "-", IF(BG34="-", "-", IF(ABS(BG34)=0, "-", ROUND(100*(BC34-BG34)/ABS(BG34), 10)))) -> - | BL34: =IF(BH34="-", "-", IF(BJ34="-", "-", IF(ABS(BJ34)=0, "-", ROUND(100*(BH34-BJ34)/ABS(BJ34), 1)))) -> - | BM34: =IF(BI34="-", "-", IF(BK34="-", "-", IF(ABS(BK34)=0, "-", ROUND(100*(BI34-BK34)/ABS(BK34), 1)))) -> - | BV34: =IF(BN34="-", "-", IF(BR34="-", "-", IF(ABS(BR34)=0, "-", ROUND(100*(BN34-BR34)/ABS(BR34), 10)))) -> - | BW34: =IF(BS34="-", "-", IF(BU34="-", "-", IF(ABS(BU34)=0, "-", ROUND(100*(BS34-BU34)/ABS(BU34), 1)))) -> - | BX34: =IF(BT34="-", "-", IF(BV34="-", "-", IF(ABS(BV34)=0, "-", ROUND(100*(BT34-BV34)/ABS(BV34), 1)))) -> -
J35: =IF($B$1<>"",$B$1,"") | N35: =IF($B$1<>"",$B$1-1,"") | R35: 増減率 | AV35: 揚水ポンプ | BK35: =IF(BC35="-", "-", IF(BG35="-", "-", IF(ABS(BG35)=0, "-", ROUND(100*(BC35-BG35)/ABS(BG35), 10)))) -> - | BL35: =IF(BH35="-", "-", IF(BJ35="-", "-", IF(ABS(BJ35)=0, "-", ROUND(100*(BH35-BJ35)/ABS(BJ35), 1)))) -> - | BM35: =IF(BI35="-", "-", IF(BK35="-", "-", IF(ABS(BK35)=0, "-", ROUND(100*(BI35-BK35)/ABS(BK35), 1)))) -> - | BV35: =IF(BN35="-", "-", IF(BR35="-", "-", IF(ABS(BR35)=0, "-", ROUND(100*(BN35-BR35)/ABS(BR35), 10)))) -> - | BW35: =IF(BS35="-", "-", IF(BU35="-", "-", IF(ABS(BU35)=0, "-", ROUND(100*(BS35-BU35)/ABS(BU35), 1)))) -> - | BX35: =IF(BT35="-", "-", IF(BV35="-", "-", IF(ABS(BV35)=0, "-", ROUND(100*(BT35-BV35)/ABS(BV35), 1)))) -> -
B36: 任意項目１ | R36: =IF(J36="-", "-", IF(N36="-", "-", IF(ABS(N36)=0, "-", ROUND(100*(J36-N36)/ABS(N36), 10)))) -> - | S36: =IF(O36="-", "-", IF(Q36="-", "-", IF(ABS(Q36)=0, "-", ROUND(100*(O36-Q36)/ABS(Q36), 1)))) -> - | T36: =IF(P36="-", "-", IF(R36="-", "-", IF(ABS(R36)=0, "-", ROUND(100*(P36-R36)/ABS(R36), 1)))) -> - | AV36: 乗用トラクター | AY36: 20馬力未満 | BK36: =IF(BC36="-", "-", IF(BG36="-", "-", IF(ABS(BG36)=0, "-", ROUND(100*(BC36-BG36)/ABS(BG36), 10)))) -> - | BL36: =IF(BH36="-", "-", IF(BJ36="-", "-", IF(ABS(BJ36)=0, "-", ROUND(100*(BH36-BJ36)/ABS(BJ36), 1)))) -> - | BM36: =IF(BI36="-", "-", IF(BK36="-", "-", IF(ABS(BK36)=0, "-", ROUND(100*(BI36-BK36)/ABS(BK36), 1)))) -> - | BV36: =IF(BN36="-", "-", IF(BR36="-", "-", IF(ABS(BR36)=0, "-", ROUND(100*(BN36-BR36)/ABS(BR36), 10)))) -> - | BW36: =IF(BS36="-", "-", IF(BU36="-", "-", IF(ABS(BU36)=0, "-", ROUND(100*(BS36-BU36)/ABS(BU36), 1)))) -> - | BX36: =IF(BT36="-", "-", IF(BV36="-", "-", IF(ABS(BV36)=0, "-", ROUND(100*(BT36-BV36)/ABS(BV36), 1)))) -> -
B37: 任意項目２ | R37: =IF(J37="-", "-", IF(N37="-", "-", IF(ABS(N37)=0, "-", ROUND(100*(J37-N37)/ABS(N37), 10)))) -> - | S37: =IF(O37="-", "-", IF(Q37="-", "-", IF(ABS(Q37)=0, "-", ROUND(100*(O37-Q37)/ABS(Q37), 1)))) -> - | T37: =IF(P37="-", "-", IF(R37="-", "-", IF(ABS(R37)=0, "-", ROUND(100*(P37-R37)/ABS(R37), 1)))) -> - | AY37: 20～50馬力未満 | BK37: =IF(BC37="-", "-", IF(BG37="-", "-", IF(ABS(BG37)=0, "-", ROUND(100*(BC37-BG37)/ABS(BG37), 10)))) -> - | BL37: =IF(BH37="-", "-", IF(BJ37="-", "-", IF(ABS(BJ37)=0, "-", ROUND(100*(BH37-BJ37)/ABS(BJ37), 1)))) -> - | BM37: =IF(BI37="-", "-", IF(BK37="-", "-", IF(ABS(BK37)=0, "-", ROUND(100*(BI37-BK37)/ABS(BK37), 1)))) -> - | BV37: =IF(BN37="-", "-", IF(BR37="-", "-", IF(ABS(BR37)=0, "-", ROUND(100*(BN37-BR37)/ABS(BR37), 10)))) -> - | BW37: =IF(BS37="-", "-", IF(BU37="-", "-", IF(ABS(BU37)=0, "-", ROUND(100*(BS37-BU37)/ABS(BU37), 1)))) -> - | BX37: =IF(BT37="-", "-", IF(BV37="-", "-", IF(ABS(BV37)=0, "-", ROUND(100*(BT37-BV37)/ABS(BV37), 1)))) -> -
B38: 任意項目３ | R38: =IF(J38="-", "-", IF(N38="-", "-", IF(ABS(N38)=0, "-", ROUND(100*(J38-N38)/ABS(N38), 10)))) -> - | S38: =IF(O38="-", "-", IF(Q38="-", "-", IF(ABS(Q38)=0, "-", ROUND(100*(O38-Q38)/ABS(Q38), 1)))) -> - | T38: =IF(P38="-", "-", IF(R38="-", "-", IF(ABS(R38)=0, "-", ROUND(100*(P38-R38)/ABS(R38), 1)))) -> - | AY38: 50～80馬力未満 | BK38: =IF(BC38="-", "-", IF(BG38="-", "-", IF(ABS(BG38)=0, "-", ROUND(100*(BC38-BG38)/ABS(BG38), 10)))) -> - | BL38: =IF(BH38="-", "-", IF(BJ38="-", "-", IF(ABS(BJ38)=0, "-", ROUND(100*(BH38-BJ38)/ABS(BJ38), 1)))) -> - | BM38: =IF(BI38="-", "-", IF(BK38="-", "-", IF(ABS(BK38)=0, "-", ROUND(100*(BI38-BK38)/ABS(BK38), 1)))) -> - | BV38: =IF(BN38="-", "-", IF(BR38="-", "-", IF(ABS(BR38)=0, "-", ROUND(100*(BN38-BR38)/ABS(BR38), 10)))) -> - | BW38: =IF(BS38="-", "-", IF(BU38="-", "-", IF(ABS(BU38)=0, "-", ROUND(100*(BS38-BU38)/ABS(BU38), 1)))) -> - | BX38: =IF(BT38="-", "-", IF(BV38="-", "-", IF(ABS(BV38)=0, "-", ROUND(100*(BT38-BV38)/ABS(BV38), 1)))) -> -
B39: 任意項目４ | R39: =IF(J39="-", "-", IF(N39="-", "-", IF(ABS(N39)=0, "-", ROUND(100*(J39-N39)/ABS(N39), 10)))) -> - | S39: =IF(O39="-", "-", IF(Q39="-", "-", IF(ABS(Q39)=0, "-", ROUND(100*(O39-Q39)/ABS(Q39), 1)))) -> - | T39: =IF(P39="-", "-", IF(R39="-", "-", IF(ABS(R39)=0, "-", ROUND(100*(P39-R39)/ABS(R39), 1)))) -> - | AY39: 80～100馬力未満 | BK39: =IF(BC39="-", "-", IF(BG39="-", "-", IF(ABS(BG39)=0, "-", ROUND(100*(BC39-BG39)/ABS(BG39), 10)))) -> - | BL39: =IF(BH39="-", "-", IF(BJ39="-", "-", IF(ABS(BJ39)=0, "-", ROUND(100*(BH39-BJ39)/ABS(BJ39), 1)))) -> - | BM39: =IF(BI39="-", "-", IF(BK39="-", "-", IF(ABS(BK39)=0, "-", ROUND(100*(BI39-BK39)/ABS(BK39), 1)))) -> - | BV39: =IF(BN39="-", "-", IF(BR39="-", "-", IF(ABS(BR39)=0, "-", ROUND(100*(BN39-BR39)/ABS(BR39), 10)))) -> - | BW39: =IF(BS39="-", "-", IF(BU39="-", "-", IF(ABS(BU39)=0, "-", ROUND(100*(BS39-BU39)/ABS(BU39), 1)))) -> - | BX39: =IF(BT39="-", "-", IF(BV39="-", "-", IF(ABS(BV39)=0, "-", ROUND(100*(BT39-BV39)/ABS(BV39), 1)))) -> -
B40: 任意項目５ | R40: =IF(J40="-", "-", IF(N40="-", "-", IF(ABS(N40)=0, "-", ROUND(100*(J40-N40)/ABS(N40), 10)))) -> - | S40: =IF(O40="-", "-", IF(Q40="-", "-", IF(ABS(Q40)=0, "-", ROUND(100*(O40-Q40)/ABS(Q40), 1)))) -> - | T40: =IF(P40="-", "-", IF(R40="-", "-", IF(ABS(R40)=0, "-", ROUND(100*(P40-R40)/ABS(R40), 1)))) -> - | AY40: 100馬力以上 | BK40: =IF(BC40="-", "-", IF(BG40="-", "-", IF(ABS(BG40)=0, "-", ROUND(100*(BC40-BG40)/ABS(BG40), 10)))) -> - | BL40: =IF(BH40="-", "-", IF(BJ40="-", "-", IF(ABS(BJ40)=0, "-", ROUND(100*(BH40-BJ40)/ABS(BJ40), 1)))) -> - | BM40: =IF(BI40="-", "-", IF(BK40="-", "-", IF(ABS(BK40)=0, "-", ROUND(100*(BI40-BK40)/ABS(BK40), 1)))) -> - | BV40: =IF(BN40="-", "-", IF(BR40="-", "-", IF(ABS(BR40)=0, "-", ROUND(100*(BN40-BR40)/ABS(BR40), 10)))) -> - | BW40: =IF(BS40="-", "-", IF(BU40="-", "-", IF(ABS(BU40)=0, "-", ROUND(100*(BS40-BU40)/ABS(BU40), 1)))) -> - | BX40: =IF(BT40="-", "-", IF(BV40="-", "-", IF(ABS(BV40)=0, "-", ROUND(100*(BT40-BV40)/ABS(BV40), 1)))) -> -
B41: 任意項目６ | R41: =IF(J41="-", "-", IF(N41="-", "-", IF(ABS(N41)=0, "-", ROUND(100*(J41-N41)/ABS(N41), 10)))) -> - | S41: =IF(O41="-", "-", IF(Q41="-", "-", IF(ABS(Q41)=0, "-", ROUND(100*(O41-Q41)/ABS(Q41), 1)))) -> - | T41: =IF(P41="-", "-", IF(R41="-", "-", IF(ABS(R41)=0, "-", ROUND(100*(P41-R41)/ABS(R41), 1)))) -> - | AV41: 歩行用トラクター | BK41: =IF(BC41="-", "-", IF(BG41="-", "-", IF(ABS(BG41)=0, "-", ROUND(100*(BC41-BG41)/ABS(BG41), 10)))) -> - | BL41: =IF(BH41="-", "-", IF(BJ41="-", "-", IF(ABS(BJ41)=0, "-", ROUND(100*(BH41-BJ41)/ABS(BJ41), 1)))) -> - | BM41: =IF(BI41="-", "-", IF(BK41="-", "-", IF(ABS(BK41)=0, "-", ROUND(100*(BI41-BK41)/ABS(BK41), 1)))) -> - | BV41: =IF(BN41="-", "-", IF(BR41="-", "-", IF(ABS(BR41)=0, "-", ROUND(100*(BN41-BR41)/ABS(BR41), 10)))) -> - | BW41: =IF(BS41="-", "-", IF(BU41="-", "-", IF(ABS(BU41)=0, "-", ROUND(100*(BS41-BU41)/ABS(BU41), 1)))) -> - | BX41: =IF(BT41="-", "-", IF(BV41="-", "-", IF(ABS(BV41)=0, "-", ROUND(100*(BT41-BV41)/ABS(BV41), 1)))) -> -
B42: 任意項目７ | R42: =IF(J42="-", "-", IF(N42="-", "-", IF(ABS(N42)=0, "-", ROUND(100*(J42-N42)/ABS(N42), 10)))) -> - | S42: =IF(O42="-", "-", IF(Q42="-", "-", IF(ABS(Q42)=0, "-", ROUND(100*(O42-Q42)/ABS(Q42), 1)))) -> - | T42: =IF(P42="-", "-", IF(R42="-", "-", IF(ABS(R42)=0, "-", ROUND(100*(P42-R42)/ABS(R42), 1)))) -> - | AV42: 電熱育苗機 | BK42: =IF(BC42="-", "-", IF(BG42="-", "-", IF(ABS(BG42)=0, "-", ROUND(100*(BC42-BG42)/ABS(BG42), 10)))) -> - | BL42: =IF(BH42="-", "-", IF(BJ42="-", "-", IF(ABS(BJ42)=0, "-", ROUND(100*(BH42-BJ42)/ABS(BJ42), 1)))) -> - | BM42: =IF(BI42="-", "-", IF(BK42="-", "-", IF(ABS(BK42)=0, "-", ROUND(100*(BI42-BK42)/ABS(BK42), 1)))) -> - | BV42: =IF(BN42="-", "-", IF(BR42="-", "-", IF(ABS(BR42)=0, "-", ROUND(100*(BN42-BR42)/ABS(BR42), 10)))) -> - | BW42: =IF(BS42="-", "-", IF(BU42="-", "-", IF(ABS(BU42)=0, "-", ROUND(100*(BS42-BU42)/ABS(BU42), 1)))) -> - | BX42: =IF(BT42="-", "-", IF(BV42="-", "-", IF(ABS(BV42)=0, "-", ROUND(100*(BT42-BV42)/ABS(BV42), 1)))) -> -
B43: 任意項目８ | R43: =IF(J43="-", "-", IF(N43="-", "-", IF(ABS(N43)=0, "-", ROUND(100*(J43-N43)/ABS(N43), 10)))) -> - | S43: =IF(O43="-", "-", IF(Q43="-", "-", IF(ABS(Q43)=0, "-", ROUND(100*(O43-Q43)/ABS(Q43), 1)))) -> - | T43: =IF(P43="-", "-", IF(R43="-", "-", IF(ABS(R43)=0, "-", ROUND(100*(P43-R43)/ABS(R43), 1)))) -> - | AV43: 田植機 | AY43: ２条植 | BK43: =IF(BC43="-", "-", IF(BG43="-", "-", IF(ABS(BG43)=0, "-", ROUND(100*(BC43-BG43)/ABS(BG43), 10)))) -> - | BL43: =IF(BH43="-", "-", IF(BJ43="-", "-", IF(ABS(BJ43)=0, "-", ROUND(100*(BH43-BJ43)/ABS(BJ43), 1)))) -> - | BM43: =IF(BI43="-", "-", IF(BK43="-", "-", IF(ABS(BK43)=0, "-", ROUND(100*(BI43-BK43)/ABS(BK43), 1)))) -> - | BV43: =IF(BN43="-", "-", IF(BR43="-", "-", IF(ABS(BR43)=0, "-", ROUND(100*(BN43-BR43)/ABS(BR43), 10)))) -> - | BW43: =IF(BS43="-", "-", IF(BU43="-", "-", IF(ABS(BU43)=0, "-", ROUND(100*(BS43-BU43)/ABS(BU43), 1)))) -> - | BX43: =IF(BT43="-", "-", IF(BV43="-", "-", IF(ABS(BV43)=0, "-", ROUND(100*(BT43-BV43)/ABS(BV43), 1)))) -> -
B44: 任意項目９ | R44: =IF(J44="-", "-", IF(N44="-", "-", IF(ABS(N44)=0, "-", ROUND(100*(J44-N44)/ABS(N44), 10)))) -> - | S44: =IF(O44="-", "-", IF(Q44="-", "-", IF(ABS(Q44)=0, "-", ROUND(100*(O44-Q44)/ABS(Q44), 1)))) -> - | T44: =IF(P44="-", "-", IF(R44="-", "-", IF(ABS(R44)=0, "-", ROUND(100*(P44-R44)/ABS(R44), 1)))) -> - | AY44: ３～５条植 | BK44: =IF(BC44="-", "-", IF(BG44="-", "-", IF(ABS(BG44)=0, "-", ROUND(100*(BC44-BG44)/ABS(BG44), 10)))) -> - | BL44: =IF(BH44="-", "-", IF(BJ44="-", "-", IF(ABS(BJ44)=0, "-", ROUND(100*(BH44-BJ44)/ABS(BJ44), 1)))) -> - | BM44: =IF(BI44="-", "-", IF(BK44="-", "-", IF(ABS(BK44)=0, "-", ROUND(100*(BI44-BK44)/ABS(BK44), 1)))) -> - | BV44: =IF(BN44="-", "-", IF(BR44="-", "-", IF(ABS(BR44)=0, "-", ROUND(100*(BN44-BR44)/ABS(BR44), 10)))) -> - | BW44: =IF(BS44="-", "-", IF(BU44="-", "-", IF(ABS(BU44)=0, "-", ROUND(100*(BS44-BU44)/ABS(BU44), 1)))) -> - | BX44: =IF(BT44="-", "-", IF(BV44="-", "-", IF(ABS(BV44)=0, "-", ROUND(100*(BT44-BV44)/ABS(BV44), 1)))) -> -
B45: 任意項目１０ | R45: =IF(J45="-", "-", IF(N45="-", "-", IF(ABS(N45)=0, "-", ROUND(100*(J45-N45)/ABS(N45), 10)))) -> - | S45: =IF(O45="-", "-", IF(Q45="-", "-", IF(ABS(Q45)=0, "-", ROUND(100*(O45-Q45)/ABS(Q45), 1)))) -> - | T45: =IF(P45="-", "-", IF(R45="-", "-", IF(ABS(R45)=0, "-", ROUND(100*(P45-R45)/ABS(R45), 1)))) -> - | AY45: ６～７条植 | BK45: =IF(BC45="-", "-", IF(BG45="-", "-", IF(ABS(BG45)=0, "-", ROUND(100*(BC45-BG45)/ABS(BG45), 10)))) -> - | BL45: =IF(BH45="-", "-", IF(BJ45="-", "-", IF(ABS(BJ45)=0, "-", ROUND(100*(BH45-BJ45)/ABS(BJ45), 1)))) -> - | BM45: =IF(BI45="-", "-", IF(BK45="-", "-", IF(ABS(BK45)=0, "-", ROUND(100*(BI45-BK45)/ABS(BK45), 1)))) -> - | BV45: =IF(BN45="-", "-", IF(BR45="-", "-", IF(ABS(BR45)=0, "-", ROUND(100*(BN45-BR45)/ABS(BR45), 10)))) -> - | BW45: =IF(BS45="-", "-", IF(BU45="-", "-", IF(ABS(BU45)=0, "-", ROUND(100*(BS45-BU45)/ABS(BU45), 1)))) -> - | BX45: =IF(BT45="-", "-", IF(BV45="-", "-", IF(ABS(BV45)=0, "-", ROUND(100*(BT45-BV45)/ABS(BV45), 1)))) -> -
AY46: ８条植以上 | BK46: =IF(BC46="-", "-", IF(BG46="-", "-", IF(ABS(BG46)=0, "-", ROUND(100*(BC46-BG46)/ABS(BG46), 10)))) -> - | BL46: =IF(BH46="-", "-", IF(BJ46="-", "-", IF(ABS(BJ46)=0, "-", ROUND(100*(BH46-BJ46)/ABS(BJ46), 1)))) -> - | BM46: =IF(BI46="-", "-", IF(BK46="-", "-", IF(ABS(BK46)=0, "-", ROUND(100*(BI46-BK46)/ABS(BK46), 1)))) -> - | BV46: =IF(BN46="-", "-", IF(BR46="-", "-", IF(ABS(BR46)=0, "-", ROUND(100*(BN46-BR46)/ABS(BR46), 10)))) -> - | BW46: =IF(BS46="-", "-", IF(BU46="-", "-", IF(ABS(BU46)=0, "-", ROUND(100*(BS46-BU46)/ABS(BU46), 1)))) -> - | BX46: =IF(BT46="-", "-", IF(BV46="-", "-", IF(ABS(BV46)=0, "-", ROUND(100*(BT46-BV46)/ABS(BV46), 1)))) -> -
AV47: 動力噴霧機 | BK47: =IF(BC47="-", "-", IF(BG47="-", "-", IF(ABS(BG47)=0, "-", ROUND(100*(BC47-BG47)/ABS(BG47), 10)))) -> - | BL47: =IF(BH47="-", "-", IF(BJ47="-", "-", IF(ABS(BJ47)=0, "-", ROUND(100*(BH47-BJ47)/ABS(BJ47), 1)))) -> - | BM47: =IF(BI47="-", "-", IF(BK47="-", "-", IF(ABS(BK47)=0, "-", ROUND(100*(BI47-BK47)/ABS(BK47), 1)))) -> - | BV47: =IF(BN47="-", "-", IF(BR47="-", "-", IF(ABS(BR47)=0, "-", ROUND(100*(BN47-BR47)/ABS(BR47), 10)))) -> - | BW47: =IF(BS47="-", "-", IF(BU47="-", "-", IF(ABS(BU47)=0, "-", ROUND(100*(BS47-BU47)/ABS(BU47), 1)))) -> - | BX47: =IF(BT47="-", "-", IF(BV47="-", "-", IF(ABS(BV47)=0, "-", ROUND(100*(BT47-BV47)/ABS(BV47), 1)))) -> -
AV48: 動力散粉機 | BK48: =IF(BC48="-", "-", IF(BG48="-", "-", IF(ABS(BG48)=0, "-", ROUND(100*(BC48-BG48)/ABS(BG48), 10)))) -> - | BL48: =IF(BH48="-", "-", IF(BJ48="-", "-", IF(ABS(BJ48)=0, "-", ROUND(100*(BH48-BJ48)/ABS(BJ48), 1)))) -> - | BM48: =IF(BI48="-", "-", IF(BK48="-", "-", IF(ABS(BK48)=0, "-", ROUND(100*(BI48-BK48)/ABS(BK48), 1)))) -> - | BV48: =IF(BN48="-", "-", IF(BR48="-", "-", IF(ABS(BR48)=0, "-", ROUND(100*(BN48-BR48)/ABS(BR48), 10)))) -> - | BW48: =IF(BS48="-", "-", IF(BU48="-", "-", IF(ABS(BU48)=0, "-", ROUND(100*(BS48-BU48)/ABS(BU48), 1)))) -> - | BX48: =IF(BT48="-", "-", IF(BV48="-", "-", IF(ABS(BV48)=0, "-", ROUND(100*(BT48-BV48)/ABS(BV48), 1)))) -> -
AV49: バインダー | BK49: =IF(BC49="-", "-", IF(BG49="-", "-", IF(ABS(BG49)=0, "-", ROUND(100*(BC49-BG49)/ABS(BG49), 10)))) -> - | BL49: =IF(BH49="-", "-", IF(BJ49="-", "-", IF(ABS(BJ49)=0, "-", ROUND(100*(BH49-BJ49)/ABS(BJ49), 1)))) -> - | BM49: =IF(BI49="-", "-", IF(BK49="-", "-", IF(ABS(BK49)=0, "-", ROUND(100*(BI49-BK49)/ABS(BK49), 1)))) -> - | BV49: =IF(BN49="-", "-", IF(BR49="-", "-", IF(ABS(BR49)=0, "-", ROUND(100*(BN49-BR49)/ABS(BR49), 10)))) -> - | BW49: =IF(BS49="-", "-", IF(BU49="-", "-", IF(ABS(BU49)=0, "-", ROUND(100*(BS49-BU49)/ABS(BU49), 1)))) -> - | BX49: =IF(BT49="-", "-", IF(BV49="-", "-", IF(ABS(BV49)=0, "-", ROUND(100*(BT49-BV49)/ABS(BV49), 1)))) -> -
AV50: 自脱型コ ンバイン | AY50: ３条以下 | BK50: =IF(BC50="-", "-", IF(BG50="-", "-", IF(ABS(BG50)=0, "-", ROUND(100*(BC50-BG50)/ABS(BG50), 10)))) -> - | BL50: =IF(BH50="-", "-", IF(BJ50="-", "-", IF(ABS(BJ50)=0, "-", ROUND(100*(BH50-BJ50)/ABS(BJ50), 1)))) -> - | BM50: =IF(BI50="-", "-", IF(BK50="-", "-", IF(ABS(BK50)=0, "-", ROUND(100*(BI50-BK50)/ABS(BK50), 1)))) -> - | BV50: =IF(BN50="-", "-", IF(BR50="-", "-", IF(ABS(BR50)=0, "-", ROUND(100*(BN50-BR50)/ABS(BR50), 10)))) -> - | BW50: =IF(BS50="-", "-", IF(BU50="-", "-", IF(ABS(BU50)=0, "-", ROUND(100*(BS50-BU50)/ABS(BU50), 1)))) -> - | BX50: =IF(BT50="-", "-", IF(BV50="-", "-", IF(ABS(BV50)=0, "-", ROUND(100*(BT50-BV50)/ABS(BV50), 1)))) -> -
AY51: ４～５条刈 | BK51: =IF(BC51="-", "-", IF(BG51="-", "-", IF(ABS(BG51)=0, "-", ROUND(100*(BC51-BG51)/ABS(BG51), 10)))) -> - | BL51: =IF(BH51="-", "-", IF(BJ51="-", "-", IF(ABS(BJ51)=0, "-", ROUND(100*(BH51-BJ51)/ABS(BJ51), 1)))) -> - | BM51: =IF(BI51="-", "-", IF(BK51="-", "-", IF(ABS(BK51)=0, "-", ROUND(100*(BI51-BK51)/ABS(BK51), 1)))) -> - | BV51: =IF(BN51="-", "-", IF(BR51="-", "-", IF(ABS(BR51)=0, "-", ROUND(100*(BN51-BR51)/ABS(BR51), 10)))) -> - | BW51: =IF(BS51="-", "-", IF(BU51="-", "-", IF(ABS(BU51)=0, "-", ROUND(100*(BS51-BU51)/ABS(BU51), 1)))) -> - | BX51: =IF(BT51="-", "-", IF(BV51="-", "-", IF(ABS(BV51)=0, "-", ROUND(100*(BT51-BV51)/ABS(BV51), 1)))) -> -
AY52: ６条以上 | BK52: =IF(BC52="-", "-", IF(BG52="-", "-", IF(ABS(BG52)=0, "-", ROUND(100*(BC52-BG52)/ABS(BG52), 10)))) -> - | BL52: =IF(BH52="-", "-", IF(BJ52="-", "-", IF(ABS(BJ52)=0, "-", ROUND(100*(BH52-BJ52)/ABS(BJ52), 1)))) -> - | BM52: =IF(BI52="-", "-", IF(BK52="-", "-", IF(ABS(BK52)=0, "-", ROUND(100*(BI52-BK52)/ABS(BK52), 1)))) -> - | BV52: =IF(BN52="-", "-", IF(BR52="-", "-", IF(ABS(BR52)=0, "-", ROUND(100*(BN52-BR52)/ABS(BR52), 10)))) -> - | BW52: =IF(BS52="-", "-", IF(BU52="-", "-", IF(ABS(BU52)=0, "-", ROUND(100*(BS52-BU52)/ABS(BU52), 1)))) -> - | BX52: =IF(BT52="-", "-", IF(BV52="-", "-", IF(ABS(BV52)=0, "-", ROUND(100*(BT52-BV52)/ABS(BV52), 1)))) -> -
AV53: 普通型コンバイン | BK53: =IF(BC53="-", "-", IF(BG53="-", "-", IF(ABS(BG53)=0, "-", ROUND(100*(BC53-BG53)/ABS(BG53), 10)))) -> - | BL53: =IF(BH53="-", "-", IF(BJ53="-", "-", IF(ABS(BJ53)=0, "-", ROUND(100*(BH53-BJ53)/ABS(BJ53), 1)))) -> - | BM53: =IF(BI53="-", "-", IF(BK53="-", "-", IF(ABS(BK53)=0, "-", ROUND(100*(BI53-BK53)/ABS(BK53), 1)))) -> - | BV53: =IF(BN53="-", "-", IF(BR53="-", "-", IF(ABS(BR53)=0, "-", ROUND(100*(BN53-BR53)/ABS(BR53), 10)))) -> - | BW53: =IF(BS53="-", "-", IF(BU53="-", "-", IF(ABS(BU53)=0, "-", ROUND(100*(BS53-BU53)/ABS(BU53), 1)))) -> - | BX53: =IF(BT53="-", "-", IF(BV53="-", "-", IF(ABS(BV53)=0, "-", ROUND(100*(BT53-BV53)/ABS(BV53), 1)))) -> -
AV54: 脱穀機 | BK54: =IF(BC54="-", "-", IF(BG54="-", "-", IF(ABS(BG54)=0, "-", ROUND(100*(BC54-BG54)/ABS(BG54), 10)))) -> - | BL54: =IF(BH54="-", "-", IF(BJ54="-", "-", IF(ABS(BJ54)=0, "-", ROUND(100*(BH54-BJ54)/ABS(BJ54), 1)))) -> - | BM54: =IF(BI54="-", "-", IF(BK54="-", "-", IF(ABS(BK54)=0, "-", ROUND(100*(BI54-BK54)/ABS(BK54), 1)))) -> - | BV54: =IF(BN54="-", "-", IF(BR54="-", "-", IF(ABS(BR54)=0, "-", ROUND(100*(BN54-BR54)/ABS(BR54), 10)))) -> - | BW54: =IF(BS54="-", "-", IF(BU54="-", "-", IF(ABS(BU54)=0, "-", ROUND(100*(BS54-BU54)/ABS(BU54), 1)))) -> - | BX54: =IF(BT54="-", "-", IF(BV54="-", "-", IF(ABS(BV54)=0, "-", ROUND(100*(BT54-BV54)/ABS(BV54), 1)))) -> -
AV55: もみすり機 | BK55: =IF(BC55="-", "-", IF(BG55="-", "-", IF(ABS(BG55)=0, "-", ROUND(100*(BC55-BG55)/ABS(BG55), 10)))) -> - | BL55: =IF(BH55="-", "-", IF(BJ55="-", "-", IF(ABS(BJ55)=0, "-", ROUND(100*(BH55-BJ55)/ABS(BJ55), 1)))) -> - | BM55: =IF(BI55="-", "-", IF(BK55="-", "-", IF(ABS(BK55)=0, "-", ROUND(100*(BI55-BK55)/ABS(BK55), 1)))) -> - | BV55: =IF(BN55="-", "-", IF(BR55="-", "-", IF(ABS(BR55)=0, "-", ROUND(100*(BN55-BR55)/ABS(BR55), 10)))) -> - | BW55: =IF(BS55="-", "-", IF(BU55="-", "-", IF(ABS(BU55)=0, "-", ROUND(100*(BS55-BU55)/ABS(BU55), 1)))) -> - | BX55: =IF(BT55="-", "-", IF(BV55="-", "-", IF(ABS(BV55)=0, "-", ROUND(100*(BT55-BV55)/ABS(BV55), 1)))) -> -
AV56: 乾燥機 | AY56: 静置式 | BK56: =IF(BC56="-", "-", IF(BG56="-", "-", IF(ABS(BG56)=0, "-", ROUND(100*(BC56-BG56)/ABS(BG56), 10)))) -> - | BL56: =IF(BH56="-", "-", IF(BJ56="-", "-", IF(ABS(BJ56)=0, "-", ROUND(100*(BH56-BJ56)/ABS(BJ56), 1)))) -> - | BM56: =IF(BI56="-", "-", IF(BK56="-", "-", IF(ABS(BK56)=0, "-", ROUND(100*(BI56-BK56)/ABS(BK56), 1)))) -> - | BV56: =IF(BN56="-", "-", IF(BR56="-", "-", IF(ABS(BR56)=0, "-", ROUND(100*(BN56-BR56)/ABS(BR56), 10)))) -> - | BW56: =IF(BS56="-", "-", IF(BU56="-", "-", IF(ABS(BU56)=0, "-", ROUND(100*(BS56-BU56)/ABS(BU56), 1)))) -> - | BX56: =IF(BT56="-", "-", IF(BV56="-", "-", IF(ABS(BV56)=0, "-", ROUND(100*(BT56-BV56)/ABS(BV56), 1)))) -> -
AY57: 循環式 | BK57: =IF(BC57="-", "-", IF(BG57="-", "-", IF(ABS(BG57)=0, "-", ROUND(100*(BC57-BG57)/ABS(BG57), 10)))) -> - | BL57: =IF(BH57="-", "-", IF(BJ57="-", "-", IF(ABS(BJ57)=0, "-", ROUND(100*(BH57-BJ57)/ABS(BJ57), 1)))) -> - | BM57: =IF(BI57="-", "-", IF(BK57="-", "-", IF(ABS(BK57)=0, "-", ROUND(100*(BI57-BK57)/ABS(BK57), 1)))) -> - | BV57: =IF(BN57="-", "-", IF(BR57="-", "-", IF(ABS(BR57)=0, "-", ROUND(100*(BN57-BR57)/ABS(BR57), 10)))) -> - | BW57: =IF(BS57="-", "-", IF(BU57="-", "-", IF(ABS(BU57)=0, "-", ROUND(100*(BS57-BU57)/ABS(BU57), 1)))) -> - | BX57: =IF(BT57="-", "-", IF(BV57="-", "-", IF(ABS(BV57)=0, "-", ROUND(100*(BT57-BV57)/ABS(BV57), 1)))) -> -
AV58: ドローン | BK58: =IF(BC58="-", "-", IF(BG58="-", "-", IF(ABS(BG58)=0, "-", ROUND(100*(BC58-BG58)/ABS(BG58), 10)))) -> - | BL58: =IF(BH58="-", "-", IF(BJ58="-", "-", IF(ABS(BJ58)=0, "-", ROUND(100*(BH58-BJ58)/ABS(BJ58), 1)))) -> - | BM58: =IF(BI58="-", "-", IF(BK58="-", "-", IF(ABS(BK58)=0, "-", ROUND(100*(BI58-BK58)/ABS(BK58), 1)))) -> - | BV58: =IF(BN58="-", "-", IF(BR58="-", "-", IF(ABS(BR58)=0, "-", ROUND(100*(BN58-BR58)/ABS(BR58), 10)))) -> - | BW58: =IF(BS58="-", "-", IF(BU58="-", "-", IF(ABS(BU58)=0, "-", ROUND(100*(BS58-BU58)/ABS(BU58), 1)))) -> - | BX58: =IF(BT58="-", "-", IF(BV58="-", "-", IF(ABS(BV58)=0, "-", ROUND(100*(BT58-BV58)/ABS(BV58), 1)))) -> -
AV59: その他 | BV59: =IF(BN59="-", "-", IF(BR59="-", "-", IF(ABS(BR59)=0, "-", ROUND(100*(BN59-BR59)/ABS(BR59), 10)))) -> - | BW59: =IF(BS59="-", "-", IF(BU59="-", "-", IF(ABS(BU59)=0, "-", ROUND(100*(BS59-BU59)/ABS(BU59), 1)))) -> - | BX59: =IF(BT59="-", "-", IF(BV59="-", "-", IF(ABS(BV59)=0, "-", ROUND(100*(BT59-BV59)/ABS(BV59), 1)))) -> -
AV60: 計 | BV60: =IF(BN60="-", "-", IF(BR60="-", "-", IF(ABS(BR60)=0, "-", ROUND(100*(BN60-BR60)/ABS(BR60), 10)))) -> - | BW60: =IF(BS60="-", "-", IF(BU60="-", "-", IF(ABS(BU60)=0, "-", ROUND(100*(BS60-BU60)/ABS(BU60), 1)))) -> - | BX60: =IF(BT60="-", "-", IF(BV60="-", "-", IF(ABS(BV60)=0, "-", ROUND(100*(BT60-BV60)/ABS(BV60), 1)))) -> -
AX61: 処分差損失 | BV61: =IF(BN61="-", "-", IF(BR61="-", "-", IF(ABS(BR61)=0, "-", ROUND(100*(BN61-BR61)/ABS(BR61), 10)))) -> - | BW61: =IF(BS61="-", "-", IF(BU61="-", "-", IF(ABS(BU61)=0, "-", ROUND(100*(BS61-BU61)/ABS(BU61), 1)))) -> - | BX61: =IF(BT61="-", "-", IF(BV61="-", "-", IF(ABS(BV61)=0, "-", ROUND(100*(BT61-BV61)/ABS(BV61), 1)))) -> -
BN62: 稲作負担分
AU63: 生産管理機器 | BV63: =IF(BN63="-", "-", IF(BR63="-", "-", IF(ABS(BR63)=0, "-", ROUND(100*(BN63-BR63)/ABS(BR63), 10)))) -> - | BW63: =IF(BS63="-", "-", IF(BU63="-", "-", IF(ABS(BU63)=0, "-", ROUND(100*(BS63-BU63)/ABS(BU63), 1)))) -> - | BX63: =IF(BT63="-", "-", IF(BV63="-", "-", IF(ABS(BV63)=0, "-", ROUND(100*(BT63-BV63)/ABS(BV63), 1)))) -> -
AV64: 処分差損失 | BV64: =IF(BN64="-", "-", IF(BR64="-", "-", IF(ABS(BR64)=0, "-", ROUND(100*(BN64-BR64)/ABS(BR64), 10)))) -> - | BW64: =IF(BS64="-", "-", IF(BU64="-", "-", IF(ABS(BU64)=0, "-", ROUND(100*(BS64-BU64)/ABS(BU64), 1)))) -> - | BX64: =IF(BT64="-", "-", IF(BV64="-", "-", IF(ABS(BV64)=0, "-", ROUND(100*(BT64-BV64)/ABS(BV64), 1)))) -> -

Sheet リスト
A2: 都道府県番号 | B2: コード | D2: 生産費区分 | E2: コード | G2: 集計区分 | H2: コード | J2: 米 | M2: 平均値種類 | N2: コード | P2: 加重・総和の別 | Q2: コード | S2: 経営種類 | T2: コード
A3: 全国 | B3: 0 | D3: 米 | E3: 80 | G3: 全調査対象 | H3: 1 | J3: 規模階層 | K3: コード | M3: 通常 | N3: 0 | P3: 加重平均 | Q3: 1 | S3: 個別経営体 | T3: 1
A4: 都府県平均 | B4: 60 | J4: 平均 | K4: 0 | M4: 総数 | N4: 1 | P4: 総和平均 | Q4: 2 | S4: 組織法人経営体 | T4: 2
A5: 北海道 | B5: 1 | J5: 5.0ha未満 | K5: 1 | M5: 10ａ当たり | N5: 2
A6: 東北 | B6: 61 | J6: 5.0～10.0 | K6: 2 | M6: 単位数量当たり | N6: 3 | Q6: コード | T6: コード
A7: 北陸 | B7: 62 | G7: 集計対象 | H7: 2 | J7: 10.0ha以上 | K7: 3 | M7: １経営体当たり | N7: 4 | Q7: ="="&No.1!BF4 -> = | T7: ="="&No.1!AL4 -> =
A8: 関東・東山 | B8: 63 | J8: 10.0～15.0 | K8: 4
A9: 東海 | B9: 67 | H9: コード | J9: 15.0ha以上 | K9: 5 | N9: コード
A10: 近畿 | B10: 68 | H10: ="="&No.1!BK4 -> = | J10: 15.0～20.0 | K10: 6 | N10: ="="&No.1!BA4 -> =
A11: 中国 | B11: 71 | J11: 20.0ha以上 | K11: 7
A12: 四国 | B12: 74 | J12: 20.0～30.0 | K12: 8
A13: 九州 | B13: 75 | J13: 30.0ha以上 | K13: 9
A14: 沖縄 | B14: 47 | J14: 30.0～50.0 | K14: 10
A15: 北関東 | B15: 64 | E15: コード | J15: 50.0ha以上 | K15: 11
A16: 南関東 | B16: 65 | E16: ="="&No.1!AQ4 -> = | J16: 50.0～100.0 | K16: 12
A17: 東山 | B17: 66 | J17: 100.0ha以上 | K17: 13
A18: 北東北 | B18: 69
A19: 南東北 | B19: 70 | K19: コード
