Workbook
Name 個別経営体: 'リスト '!$D$2:$D$6
Name 作業_Blank: 'リスト '!$H$2
Name 作業_牛乳: 'リスト '!$F$2:$F$12
Name 作業_牛乳以外: 'リスト '!$G$2:$G$11
Name 自給牧草給与割合: 設定!#REF!
Name 組織法人経営体: 'リスト '!$E$2:$E$3

Sheet 設定
C1: 畜産物生産費統計 設定シート
B2: 2020センサス番号<入力> | D2: 経営種類 | F2: 生産費区分
C5: 設定 | G5: 集計 <自動>
B6: 集計月 | C6: 作業者 | D6: 性別 | E6: 年齢 | F6: 雇用形態 | G6: 労働時間 | H6: 定型 | L6: 定型以外
B7: <選択> | C7: <入力> | D7: <選択> | E7: <入力> | F7: <選択> | H7: 飼料の調理・給与・給水 | I7: 敷料搬入・きゅう肥搬出 | J7: =IF($F$3="","",IF($F$3="牛乳","搾乳・牛乳処理・運搬","その他の飼育作業")) | K7: =IF($F$3="","",IF($F$3="牛乳","その他の飼育作業","")) | L7: =IF($D$3="組織法人経営体","内給飼料の生産","自給飼料の生産") -> 自給飼料の生産 | M7: 購入付帯労働時間 | N7: 建物・農機具等の修繕 | O7: 集会出席時間 | P7: 技術習得時間 | Q7: 簿記記帳時間 | R7: 経営管理労働時間
G8: 時間 | H8: 時間 | I8: 時間 | J8: 時間 | K8: 時間 | L8: 時間 | M8: 時間 | N8: 時間 | O8: 時間 | P8: 時間 | Q8: 時間 | R8: 時間
B9: <=12 | G9: =SUM(H9:R9) -> 0 | H9: =SUMIFS(月別入力!$I:$I,月別入力!$E:$E,$C9,月別入力!$B:$B,$B9,月別入力!$H:$H,$F9,月別入力!$D:$D,H$7) -> 0 | I9: =SUMIFS(月別入力!$I:$I,月別入力!$E:$E,$C9,月別入力!$B:$B,$B9,月別入力!$H:$H,$F9,月別入力!$D:$D,I$7) -> 0 | J9: =SUMIFS(月別入力!$I:$I,月別入力!$E:$E,$C9,月別入力!$B:$B,$B9,月別入力!$H:$H,$F9,月別入力!$D:$D,J$7) -> 0 | K9: =SUMIFS(月別入力!$I:$I,月別入力!$E:$E,$C9,月別入力!$B:$B,$B9,月別入力!$H:$H,$F9,月別入力!$D:$D,K$7) -> 0 | L9: =SUMIFS(月別入力!$I:$I,月別入力!$E:$E,$C9,月別入力!$B:$B,$B9,月別入力!$H:$H,$F9,月別入力!$D:$D,L$7) -> 0 | M9: =SUMIFS(月別入力!$I:$I,月別入力!$E:$E,$C9,月別入力!$B:$B,$B9,月別入力!$H:$H,$F9,月別入力!$D:$D,M$7) -> 0 | N9: =SUMIFS(月別入力!$I:$I,月別入力!$E:$E,$C9,月別入力!$B:$B,$B9,月別入力!$H:$H,$F9,月別入力!$D:$D,N$7) -> 0 | O9: =SUMIFS(月別入力!$I:$I,月別入力!$E:$E,$C9,月別入力!$B:$B,$B9,月別入力!$H:$H,$F9,月別入力!$D:$D,O$7) -> 0 | ... R9: =SUMIFS(月別入力!$I:$I,月別入力!$E:$E,$C9,月別入力!$B:$B,$B9,月別入力!$H:$H,$F9,月別入力!$D:$D,R$7) -> 0
B10: =B$9 -> <=12 | G10: =SUM(H10:R10) -> 0 | H10: =SUMIFS(月別入力!$I:$I,月別入力!$E:$E,$C10,月別入力!$B:$B,$B10,月別入力!$H:$H,$F10,月別入力!$D:$D,H$7) -> 0 | I10: =SUMIFS(月別入力!$I:$I,月別入力!$E:$E,$C10,月別入力!$B:$B,$B10,月別入力!$H:$H,$F10,月別入力!$D:$D,I$7) -> 0 | J10: =SUMIFS(月別入力!$I:$I,月別入力!$E:$E,$C10,月別入力!$B:$B,$B10,月別入力!$H:$H,$F10,月別入力!$D:$D,J$7) -> 0 | K10: =SUMIFS(月別入力!$I:$I,月別入力!$E:$E,$C10,月別入力!$B:$B,$B10,月別入力!$H:$H,$F10,月別入力!$D:$D,K$7) -> 0 | L10: =SUMIFS(月別入力!$I:$I,月別入力!$E:$E,$C10,月別入力!$B:$B,$B10,月別入力!$H:$H,$F10,月別入力!$D:$D,L$7) -> 0 | M10: =SUMIFS(月別入力!$I:$I,月別入力!$E:$E,$C10,月別入力!$B:$B,$B10,月別入力!$H:$H,$F10,月別入力!$D:$D,M$7) -> 0 | N10: =SUMIFS(月別入力!$I:$I,月別入力!$E:$E,$C10,月別入力!$B:$B,$B10,月別入力!$H:$H,$F10,月別入力!$D:$D,N$7) -> 0 | O10: =SUMIFS(月別入力!$I:$I,月別入力!$E:$E,$C10,月別入力!$B:$B,$B10,月別入力!$H:$H,$F10,月別入力!$D:$D,O$7) -> 0 | ... R10: =SUMIFS(月別入力!$I:$I,月別入力!$E:$E,$C10,月別入力!$B:$B,$B10,月別入力!$H:$H,$F10,月別入力!$D:$D,R$7) -> 0
B11: =B$9 -> <=12 | G11: =SUM(H11:R11) -> 0 | H11: =SUMIFS(月別入力!$I:$I,月別入力!$E:$E,$C11,月別入力!$B:$B,$B11,月別入力!$H:$H,$F11,月別入力!$D:$D,H$7) -> 0 | I11: =SUMIFS(月別入力!$I:$I,月別入力!$E:$E,$C11,月別入力!$B:$B,$B11,月別入力!$H:$H,$F11,月別入力!$D:$D,I$7) -> 0 | J11: =SUMIFS(月別入力!$I:$I,月別入力!$E:$E,$C11,月別入力!$B:$B,$B11,月別入力!$H:$H,$F11,月別入力!$D:$D,J$7) -> 0 | K11: =SUMIFS(月別入力!$I:$I,月別入力!$E:$E,$C11,月別入力!$B:$B,$B11,月別入力!$H:$H,$F11,月別入力!$D:$D,K$7) -> 0 | L11: =SUMIFS(月別入力!$I:$I,月別入力!$E:$E,$C11,月別入力!$B:$B,$B11,月別入力!$H:$H,$F11,月別入力!$D:$D,L$7) -> 0 | M11: =SUMIFS(月別入力!$I:$I,月別入力!$E:$E,$C11,月別入力!$B:$B,$B11,月別入力!$H:$H,$F11,月別入力!$D:$D,M$7) -> 0 | N11: =SUMIFS(月別入力!$I:$I,月別入力!$E:$E,$C11,月別入力!$B:$B,$B11,月別入力!$H:$H,$F11,月別入力!$D:$D,N$7) -> 0 | O11: =SUMIFS(月別入力!$I:$I,月別入力!$E:$E,$C11,月別入力!$B:$B,$B11,月別入力!$H:$H,$F11,月別入力!$D:$D,O$7) -> 0 | ... R11: =SUMIFS(月別入力!$I:$I,月別入力!$E:$E,$C11,月別入力!$B:$B,$B11,月別入力!$H:$H,$F11,月別入力!$D:$D,R$7) -> 0
B12: =B$9 -> <=12 | G12: =SUM(H12:R12) -> 0 | H12: =SUMIFS(月別入力!$I:$I,月別入力!$E:$E,$C12,月別入力!$B:$B,$B12,月別入力!$H:$H,$F12,月別入力!$D:$D,H$7) -> 0 | I12: =SUMIFS(月別入力!$I:$I,月別入力!$E:$E,$C12,月別入力!$B:$B,$B12,月別入力!$H:$H,$F12,月別入力!$D:$D,I$7) -> 0 | J12: =SUMIFS(月別入力!$I:$I,月別入力!$E:$E,$C12,月別入力!$B:$B,$B12,月別入力!$H:$H,$F12,月別入力!$D:$D,J$7) -> 0 | K12: =SUMIFS(月別入力!$I:$I,月別入力!$E:$E,$C12,月別入力!$B:$B,$B12,月別入力!$H:$H,$F12,月別入力!$D:$D,K$7) -> 0 | L12: =SUMIFS(月別入力!$I:$I,月別入力!$E:$E,$C12,月別入力!$B:$B,$B12,月別入力!$H:$H,$F12,月別入力!$D:$D,L$7) -> 0 | M12: =SUMIFS(月別入力!$I:$I,月別入力!$E:$E,$C12,月別入力!$B:$B,$B12,月別入力!$H:$H,$F12,月別入力!$D:$D,M$7) -> 0 | N12: =SUMIFS(月別入力!$I:$I,月別入力!$E:$E,$C12,月別入力!$B:$B,$B12,月別入力!$H:$H,$F12,月別入力!$D:$D,N$7) -> 0 | O12: =SUMIFS(月別入力!$I:$I,月別入力!$E:$E,$C12,月別入力!$B:$B,$B12,月別入力!$H:$H,$F12,月別入力!$D:$D,O$7) -> 0 | ... R12: =SUMIFS(月別入力!$I:$I,月別入力!$E:$E,$C12,月別入力!$B:$B,$B12,月別入力!$H:$H,$F12,月別入力!$D:$D,R$7) -> 0
B13: =B$9 -> <=12 | G13: =SUM(H13:R13) -> 0 | H13: =SUMIFS(月別入力!$I:$I,月別入力!$E:$E,$C13,月別入力!$B:$B,$B13,月別入力!$H:$H,$F13,月別入力!$D:$D,H$7) -> 0 | I13: =SUMIFS(月別入力!$I:$I,月別入力!$E:$E,$C13,月別入力!$B:$B,$B13,月別入力!$H:$H,$F13,月別入力!$D:$D,I$7) -> 0 | J13: =SUMIFS(月別入力!$I:$I,月別入力!$E:$E,$C13,月別入力!$B:$B,$B13,月別入力!$H:$H,$F13,月別入力!$D:$D,J$7) -> 0 | K13: =SUMIFS(月別入力!$I:$I,月別入力!$E:$E,$C13,月別入力!$B:$B,$B13,月別入力!$H:$H,$F13,月別入力!$D:$D,K$7) -> 0 | L13: =SUMIFS(月別入力!$I:$I,月別入力!$E:$E,$C13,月別入力!$B:$B,$B13,月別入力!$H:$H,$F13,月別入力!$D:$D,L$7) -> 0 | M13: =SUMIFS(月別入力!$I:$I,月別入力!$E:$E,$C13,月別入力!$B:$B,$B13,月別入力!$H:$H,$F13,月別入力!$D:$D,M$7) -> 0 | N13: =SUMIFS(月別入力!$I:$I,月別入力!$E:$E,$C13,月別入力!$B:$B,$B13,月別入力!$H:$H,$F13,月別入力!$D:$D,N$7) -> 0 | O13: =SUMIFS(月別入力!$I:$I,月別入力!$E:$E,$C13,月別入力!$B:$B,$B13,月別入力!$H:$H,$F13,月別入力!$D:$D,O$7) -> 0 | ... R13: =SUMIFS(月別入力!$I:$I,月別入力!$E:$E,$C13,月別入力!$B:$B,$B13,月別入力!$H:$H,$F13,月別入力!$D:$D,R$7) -> 0
B14: =B$9 -> <=12 | G14: =SUM(H14:R14) -> 0 | H14: =SUMIFS(月別入力!$I:$I,月別入力!$E:$E,$C14,月別入力!$B:$B,$B14,月別入力!$H:$H,$F14,月別入力!$D:$D,H$7) -> 0 | I14: =SUMIFS(月別入力!$I:$I,月別入力!$E:$E,$C14,月別入力!$B:$B,$B14,月別入力!$H:$H,$F14,月別入力!$D:$D,I$7) -> 0 | J14: =SUMIFS(月別入力!$I:$I,月別入力!$E:$E,$C14,月別入力!$B:$B,$B14,月別入力!$H:$H,$F14,月別入力!$D:$D,J$7) -> 0 | K14: =SUMIFS(月別入力!$I:$I,月別入力!$E:$E,$C14,月別入力!$B:$B,$B14,月別入力!$H:$H,$F14,月別入力!$D:$D,K$7) -> 0 | L14: =SUMIFS(月別入力!$I:$I,月別入力!$E:$E,$C14,月別入力!$B:$B,$B14,月別入力!$H:$H,$F14,月別入力!$D:$D,L$7) -> 0 | M14: =SUMIFS(月別入力!$I:$I,月別入力!$E:$E,$C14,月別入力!$B:$B,$B14,月別入力!$H:$H,$F14,月別入力!$D:$D,M$7) -> 0 | N14: =SUMIFS(月別入力!$I:$I,月別入力!$E:$E,$C14,月別入力!$B:$B,$B14,月別入力!$H:$H,$F14,月別入力!$D:$D,N$7) -> 0 | O14: =SUMIFS(月別入力!$I:$I,月別入力!$E:$E,$C14,月別入力!$B:$B,$B14,月別入力!$H:$H,$F14,月別入力!$D:$D,O$7) -> 0 | ... R14: =SUMIFS(月別入力!$I:$I,月別入力!$E:$E,$C14,月別入力!$B:$B,$B14,月別入力!$H:$H,$F14,月別入力!$D:$D,R$7) -> 0
B15: =B$9 -> <=12 | G15: =SUM(H15:R15) -> 0 | H15: =SUMIFS(月別入力!$I:$I,月別入力!$E:$E,$C15,月別入力!$B:$B,$B15,月別入力!$H:$H,$F15,月別入力!$D:$D,H$7) -> 0 | I15: =SUMIFS(月別入力!$I:$I,月別入力!$E:$E,$C15,月別入力!$B:$B,$B15,月別入力!$H:$H,$F15,月別入力!$D:$D,I$7) -> 0 | J15: =SUMIFS(月別入力!$I:$I,月別入力!$E:$E,$C15,月別入力!$B:$B,$B15,月別入力!$H:$H,$F15,月別入力!$D:$D,J$7) -> 0 | K15: =SUMIFS(月別入力!$I:$I,月別入力!$E:$E,$C15,月別入力!$B:$B,$B15,月別入力!$H:$H,$F15,月別入力!$D:$D,K$7) -> 0 | L15: =SUMIFS(月別入力!$I:$I,月別入力!$E:$E,$C15,月別入力!$B:$B,$B15,月別入力!$H:$H,$F15,月別入力!$D:$D,L$7) -> 0 | M15: =SUMIFS(月別入力!$I:$I,月別入力!$E:$E,$C15,月別入力!$B:$B,$B15,月別入力!$H:$H,$F15,月別入力!$D:$D,M$7) -> 0 | N15: =SUMIFS(月別入力!$I:$I,月別入力!$E:$E,$C15,月別入力!$B:$B,$B15,月別入力!$H:$H,$F15,月別入力!$D:$D,N$7) -> 0 | O15: =SUMIFS(月別入力!$I:$I,月別入力!$E:$E,$C15,月別入力!$B:$B,$B15,月別入力!$H:$H,$F15,月別入力!$D:$D,O$7) -> 0 | ... R15: =SUMIFS(月別入力!$I:$I,月別入力!$E:$E,$C15,月別入力!$B:$B,$B15,月別入力!$H:$H,$F15,月別入力!$D:$D,R$7) -> 0
B16: =B$9 -> <=12 | G16: =SUM(H16:R16) -> 0 | H16: =SUMIFS(月別入力!$I:$I,月別入力!$E:$E,$C16,月別入力!$B:$B,$B16,月別入力!$H:$H,$F16,月別入力!$D:$D,H$7) -> 0 | I16: =SUMIFS(月別入力!$I:$I,月別入力!$E:$E,$C16,月別入力!$B:$B,$B16,月別入力!$H:$H,$F16,月別入力!$D:$D,I$7) -> 0 | J16: =SUMIFS(月別入力!$I:$I,月別入力!$E:$E,$C16,月別入力!$B:$B,$B16,月別入力!$H:$H,$F16,月別入力!$D:$D,J$7) -> 0 | K16: =SUMIFS(月別入力!$I:$I,月別入力!$E:$E,$C16,月別入力!$B:$B,$B16,月別入力!$H:$H,$F16,月別入力!$D:$D,K$7) -> 0 | L16: =SUMIFS(月別入力!$I:$I,月別入力!$E:$E,$C16,月別入力!$B:$B,$B16,月別入力!$H:$H,$F16,月別入力!$D:$D,L$7) -> 0 | M16: =SUMIFS(月別入力!$I:$I,月別入力!$E:$E,$C16,月別入力!$B:$B,$B16,月別入力!$H:$H,$F16,月別入力!$D:$D,M$7) -> 0 | N16: =SUMIFS(月別入力!$I:$I,月別入力!$E:$E,$C16,月別入力!$B:$B,$B16,月別入力!$H:$H,$F16,月別入力!$D:$D,N$7) -> 0 | O16: =SUMIFS(月別入力!$I:$I,月別入力!$E:$E,$C16,月別入力!$B:$B,$B16,月別入力!$H:$H,$F16,月別入力!$D:$D,O$7) -> 0 | ... R16: =SUMIFS(月別入力!$I:$I,月別入力!$E:$E,$C16,月別入力!$B:$B,$B16,月別入力!$H:$H,$F16,月別入力!$D:$D,R$7) -> 0
B17: =B$9 -> <=12 | G17: =SUM(H17:R17) -> 0 | H17: =SUMIFS(月別入力!$I:$I,月別入力!$E:$E,$C17,月別入力!$B:$B,$B17,月別入力!$H:$H,$F17,月別入力!$D:$D,H$7) -> 0 | I17: =SUMIFS(月別入力!$I:$I,月別入力!$E:$E,$C17,月別入力!$B:$B,$B17,月別入力!$H:$H,$F17,月別入力!$D:$D,I$7) -> 0 | J17: =SUMIFS(月別入力!$I:$I,月別入力!$E:$E,$C17,月別入力!$B:$B,$B17,月別入力!$H:$H,$F17,月別入力!$D:$D,J$7) -> 0 | K17: =SUMIFS(月別入力!$I:$I,月別入力!$E:$E,$C17,月別入力!$B:$B,$B17,月別入力!$H:$H,$F17,月別入力!$D:$D,K$7) -> 0 | L17: =SUMIFS(月別入力!$I:$I,月別入力!$E:$E,$C17,月別入力!$B:$B,$B17,月別入力!$H:$H,$F17,月別入力!$D:$D,L$7) -> 0 | M17: =SUMIFS(月別入力!$I:$I,月別入力!$E:$E,$C17,月別入力!$B:$B,$B17,月別入力!$H:$H,$F17,月別入力!$D:$D,M$7) -> 0 | N17: =SUMIFS(月別入力!$I:$I,月別入力!$E:$E,$C17,月別入力!$B:$B,$B17,月別入力!$H:$H,$F17,月別入力!$D:$D,N$7) -> 0 | O17: =SUMIFS(月別入力!$I:$I,月別入力!$E:$E,$C17,月別入力!$B:$B,$B17,月別入力!$H:$H,$F17,月別入力!$D:$D,O$7) -> 0 | ... R17: =SUMIFS(月別入力!$I:$I,月別入力!$E:$E,$C17,月別入力!$B:$B,$B17,月別入力!$H:$H,$F17,月別入力!$D:$D,R$7) -> 0
B18: =B$9 -> <=12 | G18: =SUM(H18:R18) -> 0 | H18: =SUMIFS(月別入力!$I:$I,月別入力!$E:$E,$C18,月別入力!$B:$B,$B18,月別入力!$H:$H,$F18,月別入力!$D:$D,H$7) -> 0 | I18: =SUMIFS(月別入力!$I:$I,月別入力!$E:$E,$C18,月別入力!$B:$B,$B18,月別入力!$H:$H,$F18,月別入力!$D:$D,I$7) -> 0 | J18: =SUMIFS(月別入力!$I:$I,月別入力!$E:$E,$C18,月別入力!$B:$B,$B18,月別入力!$H:$H,$F18,月別入力!$D:$D,J$7) -> 0 | K18: =SUMIFS(月別入力!$I:$I,月別入力!$E:$E,$C18,月別入力!$B:$B,$B18,月別入力!$H:$H,$F18,月別入力!$D:$D,K$7) -> 0 | L18: =SUMIFS(月別入力!$I:$I,月別入力!$E:$E,$C18,月別入力!$B:$B,$B18,月別入力!$H:$H,$F18,月別入力!$D:$D,L$7) -> 0 | M18: =SUMIFS(月別入力!$I:$I,月別入力!$E:$E,$C18,月別入力!$B:$B,$B18,月別入力!$H:$H,$F18,月別入力!$D:$D,M$7) -> 0 | N18: =SUMIFS(月別入力!$I:$I,月別入力!$E:$E,$C18,月別入力!$B:$B,$B18,月別入力!$H:$H,$F18,月別入力!$D:$D,N$7) -> 0 | O18: =SUMIFS(月別入力!$I:$I,月別入力!$E:$E,$C18,月別入力!$B:$B,$B18,月別入力!$H:$H,$F18,月別入力!$D:$D,O$7) -> 0 | ... R18: =SUMIFS(月別入力!$I:$I,月別入力!$E:$E,$C18,月別入力!$B:$B,$B18,月別入力!$H:$H,$F18,月別入力!$D:$D,R$7) -> 0
B19: =B$9 -> <=12 | G19: =SUM(H19:R19) -> 0 | H19: =SUMIFS(月別入力!$I:$I,月別入力!$E:$E,$C19,月別入力!$B:$B,$B19,月別入力!$H:$H,$F19,月別入力!$D:$D,H$7) -> 0 | I19: =SUMIFS(月別入力!$I:$I,月別入力!$E:$E,$C19,月別入力!$B:$B,$B19,月別入力!$H:$H,$F19,月別入力!$D:$D,I$7) -> 0 | J19: =SUMIFS(月別入力!$I:$I,月別入力!$E:$E,$C19,月別入力!$B:$B,$B19,月別入力!$H:$H,$F19,月別入力!$D:$D,J$7) -> 0 | K19: =SUMIFS(月別入力!$I:$I,月別入力!$E:$E,$C19,月別入力!$B:$B,$B19,月別入力!$H:$H,$F19,月別入力!$D:$D,K$7) -> 0 | L19: =SUMIFS(月別入力!$I:$I,月別入力!$E:$E,$C19,月別入力!$B:$B,$B19,月別入力!$H:$H,$F19,月別入力!$D:$D,L$7) -> 0 | M19: =SUMIFS(月別入力!$I:$I,月別入力!$E:$E,$C19,月別入力!$B:$B,$B19,月別入力!$H:$H,$F19,月別入力!$D:$D,M$7) -> 0 | N19: =SUMIFS(月別入力!$I:$I,月別入力!$E:$E,$C19,月別入力!$B:$B,$B19,月別入力!$H:$H,$F19,月別入力!$D:$D,N$7) -> 0 | O19: =SUMIFS(月別入力!$I:$I,月別入力!$E:$E,$C19,月別入力!$B:$B,$B19,月別入力!$H:$H,$F19,月別入力!$D:$D,O$7) -> 0 | ... R19: =SUMIFS(月別入力!$I:$I,月別入力!$E:$E,$C19,月別入力!$B:$B,$B19,月別入力!$H:$H,$F19,月別入力!$D:$D,R$7) -> 0
B20: =B$9 -> <=12 | G20: =SUM(H20:R20) -> 0 | H20: =SUMIFS(月別入力!$I:$I,月別入力!$E:$E,$C20,月別入力!$B:$B,$B20,月別入力!$H:$H,$F20,月別入力!$D:$D,H$7) -> 0 | I20: =SUMIFS(月別入力!$I:$I,月別入力!$E:$E,$C20,月別入力!$B:$B,$B20,月別入力!$H:$H,$F20,月別入力!$D:$D,I$7) -> 0 | J20: =SUMIFS(月別入力!$I:$I,月別入力!$E:$E,$C20,月別入力!$B:$B,$B20,月別入力!$H:$H,$F20,月別入力!$D:$D,J$7) -> 0 | K20: =SUMIFS(月別入力!$I:$I,月別入力!$E:$E,$C20,月別入力!$B:$B,$B20,月別入力!$H:$H,$F20,月別入力!$D:$D,K$7) -> 0 | L20: =SUMIFS(月別入力!$I:$I,月別入力!$E:$E,$C20,月別入力!$B:$B,$B20,月別入力!$H:$H,$F20,月別入力!$D:$D,L$7) -> 0 | M20: =SUMIFS(月別入力!$I:$I,月別入力!$E:$E,$C20,月別入力!$B:$B,$B20,月別入力!$H:$H,$F20,月別入力!$D:$D,M$7) -> 0 | N20: =SUMIFS(月別入力!$I:$I,月別入力!$E:$E,$C20,月別入力!$B:$B,$B20,月別入力!$H:$H,$F20,月別入力!$D:$D,N$7) -> 0 | O20: =SUMIFS(月別入力!$I:$I,月別入力!$E:$E,$C20,月別入力!$B:$B,$B20,月別入力!$H:$H,$F20,月別入力!$D:$D,O$7) -> 0 | ... R20: =SUMIFS(月別入力!$I:$I,月別入力!$E:$E,$C20,月別入力!$B:$B,$B20,月別入力!$H:$H,$F20,月別入力!$D:$D,R$7) -> 0
B21: =B$9 -> <=12 | G21: =SUM(H21:R21) -> 0 | H21: =SUMIFS(月別入力!$I:$I,月別入力!$E:$E,$C21,月別入力!$B:$B,$B21,月別入力!$H:$H,$F21,月別入力!$D:$D,H$7) -> 0 | I21: =SUMIFS(月別入力!$I:$I,月別入力!$E:$E,$C21,月別入力!$B:$B,$B21,月別入力!$H:$H,$F21,月別入力!$D:$D,I$7) -> 0 | J21: =SUMIFS(月別入力!$I:$I,月別入力!$E:$E,$C21,月別入力!$B:$B,$B21,月別入力!$H:$H,$F21,月別入力!$D:$D,J$7) -> 0 | K21: =SUMIFS(月別入力!$I:$I,月別入力!$E:$E,$C21,月別入力!$B:$B,$B21,月別入力!$H:$H,$F21,月別入力!$D:$D,K$7) -> 0 | L21: =SUMIFS(月別入力!$I:$I,月別入力!$E:$E,$C21,月別入力!$B:$B,$B21,月別入力!$H:$H,$F21,月別入力!$D:$D,L$7) -> 0 | M21: =SUMIFS(月別入力!$I:$I,月別入力!$E:$E,$C21,月別入力!$B:$B,$B21,月別入力!$H:$H,$F21,月別入力!$D:$D,M$7) -> 0 | N21: =SUMIFS(月別入力!$I:$I,月別入力!$E:$E,$C21,月別入力!$B:$B,$B21,月別入力!$H:$H,$F21,月別入力!$D:$D,N$7) -> 0 | O21: =SUMIFS(月別入力!$I:$I,月別入力!$E:$E,$C21,月別入力!$B:$B,$B21,月別入力!$H:$H,$F21,月別入力!$D:$D,O$7) -> 0 | ... R21: =SUMIFS(月別入力!$I:$I,月別入力!$E:$E,$C21,月別入力!$B:$B,$B21,月別入力!$H:$H,$F21,月別入力!$D:$D,R$7) -> 0
... B36: =B$9 -> <=12 | G36: =SUM(H36:R36) -> 0 | H36: =SUMIFS(月別入力!$I:$I,月別入力!$E:$E,$C36,月別入力!$B:$B,$B36,月別入力!$H:$H,$F36,月別入力!$D:$D,H$7) -> 0 | I36: =SUMIFS(月別入力!$I:$I,月別入力!$E:$E,$C36,月別入力!$B:$B,$B36,月別入力!$H:$H,$F36,月別入力!$D:$D,I$7) -> 0 | J36: =SUMIFS(月別入力!$I:$I,月別入力!$E:$E,$C36,月別入力!$B:$B,$B36,月別入力!$H:$H,$F36,月別入力!$D:$D,J$7) -> 0 | K36: =SUMIFS(月別入力!$I:$I,月別入力!$E:$E,$C36,月別入力!$B:$B,$B36,月別入力!$H:$H,$F36,月別入力!$D:$D,K$7) -> 0 | L36: =SUMIFS(月別入力!$I:$I,月別入力!$E:$E,$C36,月別入力!$B:$B,$B36,月別入力!$H:$H,$F36,月別入力!$D:$D,L$7) -> 0 | M36: =SUMIFS(月別入力!$I:$I,月別入力!$E:$E,$C36,月別入力!$B:$B,$B36,月別入力!$H:$H,$F36,月別入力!$D:$D,M$7) -> 0 | N36: =SUMIFS(月別入力!$I:$I,月別入力!$E:$E,$C36,月別入力!$B:$B,$B36,月別入力!$H:$H,$F36,月別入力!$D:$D,N$7) -> 0 | O36: =SUMIFS(月別入力!$I:$I,月別入力!$E:$E,$C36,月別入力!$B:$B,$B36,月別入力!$H:$H,$F36,月別入力!$D:$D,O$7) -> 0 | ... R36: =SUMIFS(月別入力!$I:$I,月別入力!$E:$E,$C36,月別入力!$B:$B,$B36,月別入力!$H:$H,$F36,月別入力!$D:$D,R$7) -> 0
A37: =A$9 -> 0 | B37: =B$9 -> <=12 | G37: =SUM(H37:R37) -> 0 | H37: =SUMIFS(月別入力!$I:$I,月別入力!$E:$E,$C37,月別入力!$B:$B,$B37,月別入力!$H:$H,$F37,月別入力!$D:$D,H$7) -> 0 | I37: =SUMIFS(月別入力!$I:$I,月別入力!$E:$E,$C37,月別入力!$B:$B,$B37,月別入力!$H:$H,$F37,月別入力!$D:$D,I$7) -> 0 | J37: =SUMIFS(月別入力!$I:$I,月別入力!$E:$E,$C37,月別入力!$B:$B,$B37,月別入力!$H:$H,$F37,月別入力!$D:$D,J$7) -> 0 | K37: =SUMIFS(月別入力!$I:$I,月別入力!$E:$E,$C37,月別入力!$B:$B,$B37,月別入力!$H:$H,$F37,月別入力!$D:$D,K$7) -> 0 | L37: =SUMIFS(月別入力!$I:$I,月別入力!$E:$E,$C37,月別入力!$B:$B,$B37,月別入力!$H:$H,$F37,月別入力!$D:$D,L$7) -> 0 | M37: =SUMIFS(月別入力!$I:$I,月別入力!$E:$E,$C37,月別入力!$B:$B,$B37,月別入力!$H:$H,$F37,月別入力!$D:$D,M$7) -> 0 | N37: =SUMIFS(月別入力!$I:$I,月別入力!$E:$E,$C37,月別入力!$B:$B,$B37,月別入力!$H:$H,$F37,月別入力!$D:$D,N$7) -> 0 | O37: =SUMIFS(月別入力!$I:$I,月別入力!$E:$E,$C37,月別入力!$B:$B,$B37,月別入力!$H:$H,$F37,月別入力!$D:$D,O$7) -> 0 | ... R37: =SUMIFS(月別入力!$I:$I,月別入力!$E:$E,$C37,月別入力!$B:$B,$B37,月別入力!$H:$H,$F37,月別入力!$D:$D,R$7) -> 0
A38: =A$9 -> 0 | B38: =B$9 -> <=12 | G38: =SUM(H38:R38) -> 0 | H38: =SUMIFS(月別入力!$I:$I,月別入力!$E:$E,$C38,月別入力!$B:$B,$B38,月別入力!$H:$H,$F38,月別入力!$D:$D,H$7) -> 0 | I38: =SUMIFS(月別入力!$I:$I,月別入力!$E:$E,$C38,月別入力!$B:$B,$B38,月別入力!$H:$H,$F38,月別入力!$D:$D,I$7) -> 0 | J38: =SUMIFS(月別入力!$I:$I,月別入力!$E:$E,$C38,月別入力!$B:$B,$B38,月別入力!$H:$H,$F38,月別入力!$D:$D,J$7) -> 0 | K38: =SUMIFS(月別入力!$I:$I,月別入力!$E:$E,$C38,月別入力!$B:$B,$B38,月別入力!$H:$H,$F38,月別入力!$D:$D,K$7) -> 0 | L38: =SUMIFS(月別入力!$I:$I,月別入力!$E:$E,$C38,月別入力!$B:$B,$B38,月別入力!$H:$H,$F38,月別入力!$D:$D,L$7) -> 0 | M38: =SUMIFS(月別入力!$I:$I,月別入力!$E:$E,$C38,月別入力!$B:$B,$B38,月別入力!$H:$H,$F38,月別入力!$D:$D,M$7) -> 0 | N38: =SUMIFS(月別入力!$I:$I,月別入力!$E:$E,$C38,月別入力!$B:$B,$B38,月別入力!$H:$H,$F38,月別入力!$D:$D,N$7) -> 0 | O38: =SUMIFS(月別入力!$I:$I,月別入力!$E:$E,$C38,月別入力!$B:$B,$B38,月別入力!$H:$H,$F38,月別入力!$D:$D,O$7) -> 0 | ... R38: =SUMIFS(月別入力!$I:$I,月別入力!$E:$E,$C38,月別入力!$B:$B,$B38,月別入力!$H:$H,$F38,月別入力!$D:$D,R$7) -> 0
A39: =A$9 -> 0 | B39: =B$9 -> <=12 | G39: =SUM(H39:R39) -> 0 | H39: =SUMIFS(月別入力!$I:$I,月別入力!$E:$E,$C39,月別入力!$B:$B,$B39,月別入力!$H:$H,$F39,月別入力!$D:$D,H$7) -> 0 | I39: =SUMIFS(月別入力!$I:$I,月別入力!$E:$E,$C39,月別入力!$B:$B,$B39,月別入力!$H:$H,$F39,月別入力!$D:$D,I$7) -> 0 | J39: =SUMIFS(月別入力!$I:$I,月別入力!$E:$E,$C39,月別入力!$B:$B,$B39,月別入力!$H:$H,$F39,月別入力!$D:$D,J$7) -> 0 | K39: =SUMIFS(月別入力!$I:$I,月別入力!$E:$E,$C39,月別入力!$B:$B,$B39,月別入力!$H:$H,$F39,月別入力!$D:$D,K$7) -> 0 | L39: =SUMIFS(月別入力!$I:$I,月別入力!$E:$E,$C39,月別入力!$B:$B,$B39,月別入力!$H:$H,$F39,月別入力!$D:$D,L$7) -> 0 | M39: =SUMIFS(月別入力!$I:$I,月別入力!$E:$E,$C39,月別入力!$B:$B,$B39,月別入力!$H:$H,$F39,月別入力!$D:$D,M$7) -> 0 | N39: =SUMIFS(月別入力!$I:$I,月別入力!$E:$E,$C39,月別入力!$B:$B,$B39,月別入力!$H:$H,$F39,月別入力!$D:$D,N$7) -> 0 | O39: =SUMIFS(月別入力!$I:$I,月別入力!$E:$E,$C39,月別入力!$B:$B,$B39,月別入力!$H:$H,$F39,月別入力!$D:$D,O$7) -> 0 | ... R39: =SUMIFS(月別入力!$I:$I,月別入力!$E:$E,$C39,月別入力!$B:$B,$B39,月別入力!$H:$H,$F39,月別入力!$D:$D,R$7) -> 0
A40: =A$9 -> 0 | B40: =B$9 -> <=12 | G40: =SUM(H40:R40) -> 0 | H40: =SUMIFS(月別入力!$I:$I,月別入力!$E:$E,$C40,月別入力!$B:$B,$B40,月別入力!$H:$H,$F40,月別入力!$D:$D,H$7) -> 0 | I40: =SUMIFS(月別入力!$I:$I,月別入力!$E:$E,$C40,月別入力!$B:$B,$B40,月別入力!$H:$H,$F40,月別入力!$D:$D,I$7) -> 0 | J40: =SUMIFS(月別入力!$I:$I,月別入力!$E:$E,$C40,月別入力!$B:$B,$B40,月別入力!$H:$H,$F40,月別入力!$D:$D,J$7) -> 0 | K40: =SUMIFS(月別入力!$I:$I,月別入力!$E:$E,$C40,月別入力!$B:$B,$B40,月別入力!$H:$H,$F40,月別入力!$D:$D,K$7) -> 0 | L40: =SUMIFS(月別入力!$I:$I,月別入力!$E:$E,$C40,月別入力!$B:$B,$B40,月別入力!$H:$H,$F40,月別入力!$D:$D,L$7) -> 0 | M40: =SUMIFS(月別入力!$I:$I,月別入力!$E:$E,$C40,月別入力!$B:$B,$B40,月別入力!$H:$H,$F40,月別入力!$D:$D,M$7) -> 0 | N40: =SUMIFS(月別入力!$I:$I,月別入力!$E:$E,$C40,月別入力!$B:$B,$B40,月別入力!$H:$H,$F40,月別入力!$D:$D,N$7) -> 0 | O40: =SUMIFS(月別入力!$I:$I,月別入力!$E:$E,$C40,月別入力!$B:$B,$B40,月別入力!$H:$H,$F40,月別入力!$D:$D,O$7) -> 0 | ... R40: =SUMIFS(月別入力!$I:$I,月別入力!$E:$E,$C40,月別入力!$B:$B,$B40,月別入力!$H:$H,$F40,月別入力!$D:$D,R$7) -> 0
A41: =A$9 -> 0 | B41: =B$9 -> <=12 | G41: =SUM(H41:R41) -> 0 | H41: =SUMIFS(月別入力!$I:$I,月別入力!$E:$E,$C41,月別入力!$B:$B,$B41,月別入力!$H:$H,$F41,月別入力!$D:$D,H$7) -> 0 | I41: =SUMIFS(月別入力!$I:$I,月別入力!$E:$E,$C41,月別入力!$B:$B,$B41,月別入力!$H:$H,$F41,月別入力!$D:$D,I$7) -> 0 | J41: =SUMIFS(月別入力!$I:$I,月別入力!$E:$E,$C41,月別入力!$B:$B,$B41,月別入力!$H:$H,$F41,月別入力!$D:$D,J$7) -> 0 | K41: =SUMIFS(月別入力!$I:$I,月別入力!$E:$E,$C41,月別入力!$B:$B,$B41,月別入力!$H:$H,$F41,月別入力!$D:$D,K$7) -> 0 | L41: =SUMIFS(月別入力!$I:$I,月別入力!$E:$E,$C41,月別入力!$B:$B,$B41,月別入力!$H:$H,$F41,月別入力!$D:$D,L$7) -> 0 | M41: =SUMIFS(月別入力!$I:$I,月別入力!$E:$E,$C41,月別入力!$B:$B,$B41,月別入力!$H:$H,$F41,月別入力!$D:$D,M$7) -> 0 | N41: =SUMIFS(月別入力!$I:$I,月別入力!$E:$E,$C41,月別入力!$B:$B,$B41,月別入力!$H:$H,$F41,月別入力!$D:$D,N$7) -> 0 | O41: =SUMIFS(月別入力!$I:$I,月別入力!$E:$E,$C41,月別入力!$B:$B,$B41,月別入力!$H:$H,$F41,月別入力!$D:$D,O$7) -> 0 | ... R41: =SUMIFS(月別入力!$I:$I,月別入力!$E:$E,$C41,月別入力!$B:$B,$B41,月別入力!$H:$H,$F41,月別入力!$D:$D,R$7) -> 0
A42: =A$9 -> 0 | B42: =B$9 -> <=12 | G42: =SUM(H42:R42) -> 0 | H42: =SUMIFS(月別入力!$I:$I,月別入力!$E:$E,$C42,月別入力!$B:$B,$B42,月別入力!$H:$H,$F42,月別入力!$D:$D,H$7) -> 0 | I42: =SUMIFS(月別入力!$I:$I,月別入力!$E:$E,$C42,月別入力!$B:$B,$B42,月別入力!$H:$H,$F42,月別入力!$D:$D,I$7) -> 0 | J42: =SUMIFS(月別入力!$I:$I,月別入力!$E:$E,$C42,月別入力!$B:$B,$B42,月別入力!$H:$H,$F42,月別入力!$D:$D,J$7) -> 0 | K42: =SUMIFS(月別入力!$I:$I,月別入力!$E:$E,$C42,月別入力!$B:$B,$B42,月別入力!$H:$H,$F42,月別入力!$D:$D,K$7) -> 0 | L42: =SUMIFS(月別入力!$I:$I,月別入力!$E:$E,$C42,月別入力!$B:$B,$B42,月別入力!$H:$H,$F42,月別入力!$D:$D,L$7) -> 0 | M42: =SUMIFS(月別入力!$I:$I,月別入力!$E:$E,$C42,月別入力!$B:$B,$B42,月別入力!$H:$H,$F42,月別入力!$D:$D,M$7) -> 0 | N42: =SUMIFS(月別入力!$I:$I,月別入力!$E:$E,$C42,月別入力!$B:$B,$B42,月別入力!$H:$H,$F42,月別入力!$D:$D,N$7) -> 0 | O42: =SUMIFS(月別入力!$I:$I,月別入力!$E:$E,$C42,月別入力!$B:$B,$B42,月別入力!$H:$H,$F42,月別入力!$D:$D,O$7) -> 0 | ... R42: =SUMIFS(月別入力!$I:$I,月別入力!$E:$E,$C42,月別入力!$B:$B,$B42,月別入力!$H:$H,$F42,月別入力!$D:$D,R$7) -> 0
A43: =A$9 -> 0 | B43: =B$9 -> <=12 | G43: =SUM(H43:R43) -> 0 | H43: =SUMIFS(月別入力!$I:$I,月別入力!$E:$E,$C43,月別入力!$B:$B,$B43,月別入力!$H:$H,$F43,月別入力!$D:$D,H$7) -> 0 | I43: =SUMIFS(月別入力!$I:$I,月別入力!$E:$E,$C43,月別入力!$B:$B,$B43,月別入力!$H:$H,$F43,月別入力!$D:$D,I$7) -> 0 | J43: =SUMIFS(月別入力!$I:$I,月別入力!$E:$E,$C43,月別入力!$B:$B,$B43,月別入力!$H:$H,$F43,月別入力!$D:$D,J$7) -> 0 | K43: =SUMIFS(月別入力!$I:$I,月別入力!$E:$E,$C43,月別入力!$B:$B,$B43,月別入力!$H:$H,$F43,月別入力!$D:$D,K$7) -> 0 | L43: =SUMIFS(月別入力!$I:$I,月別入力!$E:$E,$C43,月別入力!$B:$B,$B43,月別入力!$H:$H,$F43,月別入力!$D:$D,L$7) -> 0 | M43: =SUMIFS(月別入力!$I:$I,月別入力!$E:$E,$C43,月別入力!$B:$B,$B43,月別入力!$H:$H,$F43,月別入力!$D:$D,M$7) -> 0 | N43: =SUMIFS(月別入力!$I:$I,月別入力!$E:$E,$C43,月別入力!$B:$B,$B43,月別入力!$H:$H,$F43,月別入力!$D:$D,N$7) -> 0 | O43: =SUMIFS(月別入力!$I:$I,月別入力!$E:$E,$C43,月別入力!$B:$B,$B43,月別入力!$H:$H,$F43,月別入力!$D:$D,O$7) -> 0 | ... R43: =SUMIFS(月別入力!$I:$I,月別入力!$E:$E,$C43,月別入力!$B:$B,$B43,月別入力!$H:$H,$F43,月別入力!$D:$D,R$7) -> 0
A44: =A$9 -> 0 | B44: =B$9 -> <=12 | G44: =SUM(H44:R44) -> 0 | H44: =SUMIFS(月別入力!$I:$I,月別入力!$E:$E,$C44,月別入力!$B:$B,$B44,月別入力!$H:$H,$F44,月別入力!$D:$D,H$7) -> 0 | I44: =SUMIFS(月別入力!$I:$I,月別入力!$E:$E,$C44,月別入力!$B:$B,$B44,月別入力!$H:$H,$F44,月別入力!$D:$D,I$7) -> 0 | J44: =SUMIFS(月別入力!$I:$I,月別入力!$E:$E,$C44,月別入力!$B:$B,$B44,月別入力!$H:$H,$F44,月別入力!$D:$D,J$7) -> 0 | K44: =SUMIFS(月別入力!$I:$I,月別入力!$E:$E,$C44,月別入力!$B:$B,$B44,月別入力!$H:$H,$F44,月別入力!$D:$D,K$7) -> 0 | L44: =SUMIFS(月別入力!$I:$I,月別入力!$E:$E,$C44,月別入力!$B:$B,$B44,月別入力!$H:$H,$F44,月別入力!$D:$D,L$7) -> 0 | M44: =SUMIFS(月別入力!$I:$I,月別入力!$E:$E,$C44,月別入力!$B:$B,$B44,月別入力!$H:$H,$F44,月別入力!$D:$D,M$7) -> 0 | N44: =SUMIFS(月別入力!$I:$I,月別入力!$E:$E,$C44,月別入力!$B:$B,$B44,月別入力!$H:$H,$F44,月別入力!$D:$D,N$7) -> 0 | O44: =SUMIFS(月別入力!$I:$I,月別入力!$E:$E,$C44,月別入力!$B:$B,$B44,月別入力!$H:$H,$F44,月別入力!$D:$D,O$7) -> 0 | ... R44: =SUMIFS(月別入力!$I:$I,月別入力!$E:$E,$C44,月別入力!$B:$B,$B44,月別入力!$H:$H,$F44,月別入力!$D:$D,R$7) -> 0
A45: =A$9 -> 0 | B45: =B$9 -> <=12 | G45: =SUM(H45:R45) -> 0 | H45: =SUMIFS(月別入力!$I:$I,月別入力!$E:$E,$C45,月別入力!$B:$B,$B45,月別入力!$H:$H,$F45,月別入力!$D:$D,H$7) -> 0 | I45: =SUMIFS(月別入力!$I:$I,月別入力!$E:$E,$C45,月別入力!$B:$B,$B45,月別入力!$H:$H,$F45,月別入力!$D:$D,I$7) -> 0 | J45: =SUMIFS(月別入力!$I:$I,月別入力!$E:$E,$C45,月別入力!$B:$B,$B45,月別入力!$H:$H,$F45,月別入力!$D:$D,J$7) -> 0 | K45: =SUMIFS(月別入力!$I:$I,月別入力!$E:$E,$C45,月別入力!$B:$B,$B45,月別入力!$H:$H,$F45,月別入力!$D:$D,K$7) -> 0 | L45: =SUMIFS(月別入力!$I:$I,月別入力!$E:$E,$C45,月別入力!$B:$B,$B45,月別入力!$H:$H,$F45,月別入力!$D:$D,L$7) -> 0 | M45: =SUMIFS(月別入力!$I:$I,月別入力!$E:$E,$C45,月別入力!$B:$B,$B45,月別入力!$H:$H,$F45,月別入力!$D:$D,M$7) -> 0 | N45: =SUMIFS(月別入力!$I:$I,月別入力!$E:$E,$C45,月別入力!$B:$B,$B45,月別入力!$H:$H,$F45,月別入力!$D:$D,N$7) -> 0 | O45: =SUMIFS(月別入力!$I:$I,月別入力!$E:$E,$C45,月別入力!$B:$B,$B45,月別入力!$H:$H,$F45,月別入力!$D:$D,O$7) -> 0 | ... R45: =SUMIFS(月別入力!$I:$I,月別入力!$E:$E,$C45,月別入力!$B:$B,$B45,月別入力!$H:$H,$F45,月別入力!$D:$D,R$7) -> 0
A46: =A$9 -> 0 | B46: =B$9 -> <=12 | G46: =SUM(H46:R46) -> 0 | H46: =SUMIFS(月別入力!$I:$I,月別入力!$E:$E,$C46,月別入力!$B:$B,$B46,月別入力!$H:$H,$F46,月別入力!$D:$D,H$7) -> 0 | I46: =SUMIFS(月別入力!$I:$I,月別入力!$E:$E,$C46,月別入力!$B:$B,$B46,月別入力!$H:$H,$F46,月別入力!$D:$D,I$7) -> 0 | J46: =SUMIFS(月別入力!$I:$I,月別入力!$E:$E,$C46,月別入力!$B:$B,$B46,月別入力!$H:$H,$F46,月別入力!$D:$D,J$7) -> 0 | K46: =SUMIFS(月別入力!$I:$I,月別入力!$E:$E,$C46,月別入力!$B:$B,$B46,月別入力!$H:$H,$F46,月別入力!$D:$D,K$7) -> 0 | L46: =SUMIFS(月別入力!$I:$I,月別入力!$E:$E,$C46,月別入力!$B:$B,$B46,月別入力!$H:$H,$F46,月別入力!$D:$D,L$7) -> 0 | M46: =SUMIFS(月別入力!$I:$I,月別入力!$E:$E,$C46,月別入力!$B:$B,$B46,月別入力!$H:$H,$F46,月別入力!$D:$D,M$7) -> 0 | N46: =SUMIFS(月別入力!$I:$I,月別入力!$E:$E,$C46,月別入力!$B:$B,$B46,月別入力!$H:$H,$F46,月別入力!$D:$D,N$7) -> 0 | O46: =SUMIFS(月別入力!$I:$I,月別入力!$E:$E,$C46,月別入力!$B:$B,$B46,月別入力!$H:$H,$F46,月別入力!$D:$D,O$7) -> 0 | ... R46: =SUMIFS(月別入力!$I:$I,月別入力!$E:$E,$C46,月別入力!$B:$B,$B46,月別入力!$H:$H,$F46,月別入力!$D:$D,R$7) -> 0
A47: =A$9 -> 0 | B47: =B$9 -> <=12 | G47: =SUM(H47:R47) -> 0 | H47: =SUMIFS(月別入力!$I:$I,月別入力!$E:$E,$C47,月別入力!$B:$B,$B47,月別入力!$H:$H,$F47,月別入力!$D:$D,H$7) -> 0 | I47: =SUMIFS(月別入力!$I:$I,月別入力!$E:$E,$C47,月別入力!$B:$B,$B47,月別入力!$H:$H,$F47,月別入力!$D:$D,I$7) -> 0 | J47: =SUMIFS(月別入力!$I:$I,月別入力!$E:$E,$C47,月別入力!$B:$B,$B47,月別入力!$H:$H,$F47,月別入力!$D:$D,J$7) -> 0 | K47: =SUMIFS(月別入力!$I:$I,月別入力!$E:$E,$C47,月別入力!$B:$B,$B47,月別入力!$H:$H,$F47,月別入力!$D:$D,K$7) -> 0 | L47: =SUMIFS(月別入力!$I:$I,月別入力!$E:$E,$C47,月別入力!$B:$B,$B47,月別入力!$H:$H,$F47,月別入力!$D:$D,L$7) -> 0 | M47: =SUMIFS(月別入力!$I:$I,月別入力!$E:$E,$C47,月別入力!$B:$B,$B47,月別入力!$H:$H,$F47,月別入力!$D:$D,M$7) -> 0 | N47: =SUMIFS(月別入力!$I:$I,月別入力!$E:$E,$C47,月別入力!$B:$B,$B47,月別入力!$H:$H,$F47,月別入力!$D:$D,N$7) -> 0 | O47: =SUMIFS(月別入力!$I:$I,月別入力!$E:$E,$C47,月別入力!$B:$B,$B47,月別入力!$H:$H,$F47,月別入力!$D:$D,O$7) -> 0 | ... R47: =SUMIFS(月別入力!$I:$I,月別入力!$E:$E,$C47,月別入力!$B:$B,$B47,月別入力!$H:$H,$F47,月別入力!$D:$D,R$7) -> 0
A48: =A$9 -> 0 | B48: =B$9 -> <=12 | G48: =SUM(H48:R48) -> 0 | H48: =SUMIFS(月別入力!$I:$I,月別入力!$E:$E,$C48,月別入力!$B:$B,$B48,月別入力!$H:$H,$F48,月別入力!$D:$D,H$7) -> 0 | I48: =SUMIFS(月別入力!$I:$I,月別入力!$E:$E,$C48,月別入力!$B:$B,$B48,月別入力!$H:$H,$F48,月別入力!$D:$D,I$7) -> 0 | J48: =SUMIFS(月別入力!$I:$I,月別入力!$E:$E,$C48,月別入力!$B:$B,$B48,月別入力!$H:$H,$F48,月別入力!$D:$D,J$7) -> 0 | K48: =SUMIFS(月別入力!$I:$I,月別入力!$E:$E,$C48,月別入力!$B:$B,$B48,月別入力!$H:$H,$F48,月別入力!$D:$D,K$7) -> 0 | L48: =SUMIFS(月別入力!$I:$I,月別入力!$E:$E,$C48,月別入力!$B:$B,$B48,月別入力!$H:$H,$F48,月別入力!$D:$D,L$7) -> 0 | M48: =SUMIFS(月別入力!$I:$I,月別入力!$E:$E,$C48,月別入力!$B:$B,$B48,月別入力!$H:$H,$F48,月別入力!$D:$D,M$7) -> 0 | N48: =SUMIFS(月別入力!$I:$I,月別入力!$E:$E,$C48,月別入力!$B:$B,$B48,月別入力!$H:$H,$F48,月別入力!$D:$D,N$7) -> 0 | O48: =SUMIFS(月別入力!$I:$I,月別入力!$E:$E,$C48,月別入力!$B:$B,$B48,月別入力!$H:$H,$F48,月別入力!$D:$D,O$7) -> 0 | ... R48: =SUMIFS(月別入力!$I:$I,月別入力!$E:$E,$C48,月別入力!$B:$B,$B48,月別入力!$H:$H,$F48,月別入力!$D:$D,R$7) -> 0
... A108: =A$9 -> 0 | B108: =B$9 -> <=12 | G108: =SUM(H108:R108) -> 0 | H108: =SUMIFS(月別入力!$I:$I,月別入力!$E:$E,$C108,月別入力!$B:$B,$B108,月別入力!$H:$H,$F108,月別入力!$D:$D,H$7) -> 0 | I108: =SUMIFS(月別入力!$I:$I,月別入力!$E:$E,$C108,月別入力!$B:$B,$B108,月別入力!$H:$H,$F108,月別入力!$D:$D,I$7) -> 0 | J108: =SUMIFS(月別入力!$I:$I,月別入力!$E:$E,$C108,月別入力!$B:$B,$B108,月別入力!$H:$H,$F108,月別入力!$D:$D,J$7) -> 0 | K108: =SUMIFS(月別入力!$I:$I,月別入力!$E:$E,$C108,月別入力!$B:$B,$B108,月別入力!$H:$H,$F108,月別入力!$D:$D,K$7) -> 0 | L108: =SUMIFS(月別入力!$I:$I,月別入力!$E:$E,$C108,月別入力!$B:$B,$B108,月別入力!$H:$H,$F108,月別入力!$D:$D,L$7) -> 0 | M108: =SUMIFS(月別入力!$I:$I,月別入力!$E:$E,$C108,月別入力!$B:$B,$B108,月別入力!$H:$H,$F108,月別入力!$D:$D,M$7) -> 0 | N108: =SUMIFS(月別入力!$I:$I,月別入力!$E:$E,$C108,月別入力!$B:$B,$B108,月別入力!$H:$H,$F108,月別入力!$D:$D,N$7) -> 0 | O108: =SUMIFS(月別入力!$I:$I,月別入力!$E:$E,$C108,月別入力!$B:$B,$B108,月別入力!$H:$H,$F108,月別入力!$D:$D,O$7) -> 0 | ... R108: =SUMIFS(月別入力!$I:$I,月別入力!$E:$E,$C108,月別入力!$B:$B,$B108,月別入力!$H:$H,$F108,月別入力!$D:$D,R$7) -> 0

Sheet 月別入力
B1: 畜産物生産費統計 入力シート（月別）
B2: 2020センサス番号 <自動>
B3: =設定!$B$3 -> 0
B5: 月 | C5: 作業 <入力> | D5: →集計分類 <選択> | E5: 作業者 <選択> | F5: 性別 <自動> | G5: 年齢 <自動> | H5: 雇用形態 <自動> | I5: 労働時間 <入力>
F7: =IFERROR(VLOOKUP($E7,設定!$C:$F,2,0),"") | G7: =IFERROR(VLOOKUP($E7,設定!$C:$F,3,0),"") | H7: =IFERROR(VLOOKUP($E7,設定!$C:$F,4,0),"")
F8: =IFERROR(VLOOKUP($E8,設定!$C:$F,2,0),"") | G8: =IFERROR(VLOOKUP($E8,設定!$C:$F,3,0),"") | H8: =IFERROR(VLOOKUP($E8,設定!$C:$F,4,0),"")
F9: =IFERROR(VLOOKUP($E9,設定!$C:$F,2,0),"") | G9: =IFERROR(VLOOKUP($E9,設定!$C:$F,3,0),"") | H9: =IFERROR(VLOOKUP($E9,設定!$C:$F,4,0),"")
F10: =IFERROR(VLOOKUP($E10,設定!$C:$F,2,0),"") | G10: =IFERROR(VLOOKUP($E10,設定!$C:$F,3,0),"") | H10: =IFERROR(VLOOKUP($E10,設定!$C:$F,4,0),"")
F11: =IFERROR(VLOOKUP($E11,設定!$C:$F,2,0),"") | G11: =IFERROR(VLOOKUP($E11,設定!$C:$F,3,0),"") | H11: =IFERROR(VLOOKUP($E11,設定!$C:$F,4,0),"")
F12: =IFERROR(VLOOKUP($E12,設定!$C:$F,2,0),"") | G12: =IFERROR(VLOOKUP($E12,設定!$C:$F,3,0),"") | H12: =IFERROR(VLOOKUP($E12,設定!$C:$F,4,0),"")
F13: =IFERROR(VLOOKUP($E13,設定!$C:$F,2,0),"") | G13: =IFERROR(VLOOKUP($E13,設定!$C:$F,3,0),"") | H13: =IFERROR(VLOOKUP($E13,設定!$C:$F,4,0),"")
F14: =IFERROR(VLOOKUP($E14,設定!$C:$F,2,0),"") | G14: =IFERROR(VLOOKUP($E14,設定!$C:$F,3,0),"") | H14: =IFERROR(VLOOKUP($E14,設定!$C:$F,4,0),"")
F15: =IFERROR(VLOOKUP($E15,設定!$C:$F,2,0),"") | G15: =IFERROR(VLOOKUP($E15,設定!$C:$F,3,0),"") | H15: =IFERROR(VLOOKUP($E15,設定!$C:$F,4,0),"")
F16: =IFERROR(VLOOKUP($E16,設定!$C:$F,2,0),"") | G16: =IFERROR(VLOOKUP($E16,設定!$C:$F,3,0),"") | H16: =IFERROR(VLOOKUP($E16,設定!$C:$F,4,0),"")
F17: =IFERROR(VLOOKUP($E17,設定!$C:$F,2,0),"") | G17: =IFERROR(VLOOKUP($E17,設定!$C:$F,3,0),"") | H17: =IFERROR(VLOOKUP($E17,設定!$C:$F,4,0),"")
F18: =IFERROR(VLOOKUP($E18,設定!$C:$F,2,0),"") | G18: =IFERROR(VLOOKUP($E18,設定!$C:$F,3,0),"") | H18: =IFERROR(VLOOKUP($E18,設定!$C:$F,4,0),"")
... F537: =IFERROR(VLOOKUP($E537,設定!$C:$F,2,0),"") | G537: =IFERROR(VLOOKUP($E537,設定!$C:$F,3,0),"") | H537: =IFERROR(VLOOKUP($E537,設定!$C:$F,4,0),"")

Sheet 【12】労働時間（個別・牛乳）
B2: 【12】作業別労働時間
S4: 労賃単価
C8: 氏 名 | D8: 性別 | E8: 年齢 | F8: 家族 ・ 雇用 | G8: 飼料の調理・ 給与・給水 | I8: 敷料搬入・きゅう肥搬出 | K8: 搾乳・牛乳 処理・運搬 | M8: その他の 飼育作業 | S8: 1：家族 2：雇用 3：ゆい・手間替え受け 4：手伝い・共同作業受け 5：同居人 | T8: 氏 名 | U8: 1：男 2：女 | V8: 年齢 | W8: 飼料の調理・給与・給水 | X8: 敷料搬入・きゅう肥搬出 | Y8: 搾乳・牛乳処理・運搬 | Z8: その他の 飼育作業 | AF8: 家族労働 | AL8: 雇用労働 | AY8: 家族労働 | BA8: 雇用労働
AF9: 計 | AH9: 家族 | AJ9: ゆい・手間替え受け | AL9: 計 | AN9: 雇用 | AP9: 手伝い・共同作業受け | AR9: 同居人 | BC9: 雇用 | BE9: 手伝い・共同作業受け、同居人
AF10: 男 | AG10: 女 | AH10: 男 | AI10: 女 | AJ10: 男 | AK10: 女 | AL10: 男 | AM10: 女 | AN10: 男 | AO10: 女 | AP10: 男 | AQ10: 女 | AR10: 男 | AS10: 女 | AY10: 男 | AZ10: 女 | BA10: 男 | BB10: 女 | BC10: 男 | BD10: 女 | BE10: 男 | BF10: 女
A11: =ROUND((ROW()-10)/2,0) -> 1 | C11: =IF(INDEX(設定!$C$9:$C$108,$A11,1)="","",INDEX(設定!$C$9:$C$108,$A11,1)) | D11: =IF(INDEX(設定!$D$9:$D$108,$A11,1)="","",INDEX(設定!$D$9:$D$108,$A11,1)) | E11: =IF(INDEX(設定!$E$9:$E$108,$A11,1)="","",INDEX(設定!$E$9:$E$108,$A11,1)) | F11: =IF(S11="","",IF(S11=1,"1：家族",IF(AND(S11>=2,S11<=5),"2：雇用",""))) | G11: =INT(INDEX(設定!$H$9:H$108,$A11,1)) -> 0 | H11: =IF(INDEX(設定!$H$9:$H$108,$A11,1)=0,"",ROUND(MOD(INDEX(設定!$H$9:$H$108,$A11,1),1)*60,0)) | I11: =INT(INDEX(設定!$I$9:$I$108,$A11,1)) -> 0 | J11: =IF(INDEX(設定!$I$9:$I$108,$A11,1)=0,"",ROUND(MOD(INDEX(設定!$I$9:$I$108,$A11,1),1)*60,0)) | K11: =INT(INDEX(設定!$J$9:$J$108,$A11,1)) -> 0 | L11: =IF(INDEX(設定!$J$9:$J$108,$A11,1)=0,"",ROUND(MOD(INDEX(設定!$J$9:$J$108,$A11,1),1)*60,0)) | M11: =INT(INDEX(設定!$K$9:$K$108,$A11,1)) -> 0 | N11: =IF(INDEX(設定!$K$9:$K$108,$A11,1)=0,"",ROUND(MOD(INDEX(設定!$K$9:$K$108,$A11,1),1)*60,0)) | S11: =IF(INDEX(設定!$F$9:$F$108,$A11,1)="","",VALUE(LEFT(INDEX(設定!$F$9:$F$108,$A11,1),1))) | T11: =IF(C11="","",C11) | U11: =IF(D11="","",IF(D11="1：男",1,IF(D11="2：女",2))) | V11: =IF(E11="","",E11) | W11: =IF(AND(G11="",H11="",G12=""),"",ROUND(SUM(G11,H11/60)*G12,1)) | X11: =IF(AND(I11="",J11="",I12=""),"",ROUND(SUM(I11,J11/60)*I12,1)) | Y11: =IF(AND(K11="",L11="",K12=""),"",ROUND(SUM(K11,L11/60)*K12,1)) | Z11: =IF(AND(M11="",N11="",M12=""),"",ROUND(SUM(M11,N11/60)*M12,1)) | AC11: 直接労働時間 | AF11: =SUM(AF12:AF15) -> 0 | AG11: =SUM(AG12:AG15) -> 0 | AL11: =AL16+AL21+AL26+AL31 -> 0 | AM11: =AM16+AM21+AM26+AM31 -> 0 | AN11: =AN16+AN21+AN26+AN31 -> 0 | AO11: =AO16+AO21+AO26+AO31 -> 0 | AP11: =AP12 -> 0 | AQ11: =AQ12 -> 0 | AR11: =SUM(AR12:AR15) -> 0 | AS11: =SUM(AS12:AS15) -> 0 | AV11: 直接労働費 | AY11: =SUM(AY12:AY15) -> 0 | AZ11: =SUM(AZ12:AZ15) -> 0 | BA11: =ROUND(BC11+BE11,0) -> 0 | BB11: =ROUND(BD11+BF11,0) -> 0 | BC11: =IFERROR($T$112*AN11/($AN$11+$AN$51),0) -> 0 | BD11: =IFERROR($T$113*AO11/($AO$11+$AO$51),0) -> 0 | BE11: =SUM(BE12:BE15) -> 0 | BF11: =SUM(BF12:BF15) -> 0
G12: =IF(SUM(G11:H11)>0,1,"") | I12: =IF(SUM(I11:J11)>0,1,"") | K12: =IF(SUM(K11:L11)>0,1,"") | M12: =IF(SUM(M11:N11)>0,1,"") | AD12: 65歳未満 | AF12: =AF17+AF22+AF27+AF32 -> 0 | AG12: =AG17+AG22+AG27+AG32 -> 0 | AH12: =AH17+AH22+AH27+AH32 -> 0 | AI12: =AI17+AI22+AI27+AI32 -> 0 | AJ12: =AJ17+AJ22+AJ27+AJ32 -> 0 | AK12: =AK17+AK22+AK27+AK32 -> 0 | AP12: =AP17+AP22+AP27+AP32 -> 0 | AQ12: =AQ17+AQ22+AQ27+AQ32 -> 0 | AR12: =AR17+AR22+AR27+AR32 -> 0 | AS12: =AS17+AS22+AS27+AS32 -> 0 | AW12: 65歳未満 | AY12: =AF12*$T$4 -> 0 | AZ12: =AG12*$T$4 -> 0 | BE12: =(AP12+AR12)*$T$4 -> 0 | BF12: =(AQ12+AS12)*$T$4 -> 0
A13: =ROUND((ROW()-10)/2,0) -> 2 | C13: =IF(INDEX(設定!$C$9:$C$108,$A13,1)="","",INDEX(設定!$C$9:$C$108,$A13,1)) | D13: =IF(INDEX(設定!$D$9:$D$108,$A13,1)="","",INDEX(設定!$D$9:$D$108,$A13,1)) | E13: =IF(INDEX(設定!$E$9:$E$108,$A13,1)="","",INDEX(設定!$E$9:$E$108,$A13,1)) | F13: =IF(S13="","",IF(S13=1,"1：家族",IF(AND(S13>=2,S13<=5),"2：雇用",""))) | G13: =INT(INDEX(設定!$H$9:H$108,$A13,1)) -> 0 | H13: =IF(INDEX(設定!$H$9:$H$108,$A13,1)=0,"",ROUND(MOD(INDEX(設定!$H$9:$H$108,$A13,1),1)*60,0)) | I13: =INT(INDEX(設定!$I$9:$I$108,$A13,1)) -> 0 | J13: =IF(INDEX(設定!$I$9:$I$108,$A13,1)=0,"",ROUND(MOD(INDEX(設定!$I$9:$I$108,$A13,1),1)*60,0)) | K13: =INT(INDEX(設定!$J$9:$J$108,$A13,1)) -> 0 | L13: =IF(INDEX(設定!$J$9:$J$108,$A13,1)=0,"",ROUND(MOD(INDEX(設定!$J$9:$J$108,$A13,1),1)*60,0)) | M13: =INT(INDEX(設定!$K$9:$K$108,$A13,1)) -> 0 | N13: =IF(INDEX(設定!$K$9:$K$108,$A13,1)=0,"",ROUND(MOD(INDEX(設定!$K$9:$K$108,$A13,1),1)*60,0)) | S13: =IF(INDEX(設定!$F$9:$F$108,$A13,1)="","",VALUE(LEFT(INDEX(設定!$F$9:$F$108,$A13,1),1))) | T13: =IF(C13="","",C13) | U13: =IF(D13="","",IF(D13="1：男",1,IF(D13="2：女",2))) | V13: =IF(E13="","",E13) | W13: =IF(AND(G13="",H13="",G14=""),"",ROUND(SUM(G13,H13/60)*G14,1)) | X13: =IF(AND(I13="",J13="",I14=""),"",ROUND(SUM(I13,J13/60)*I14,1)) | Y13: =IF(AND(K13="",L13="",K14=""),"",ROUND(SUM(K13,L13/60)*K14,1)) | Z13: =IF(AND(M13="",N13="",M14=""),"",ROUND(SUM(M13,N13/60)*M14,1)) | AD13: 65～70 | AF13: =AF18+AF23+AF28+AF33 -> 0 | AG13: =AG18+AG23+AG28+AG33 -> 0 | AH13: =AH18+AH23+AH28+AH33 -> 0 | AI13: =AI18+AI23+AI28+AI33 -> 0 | AR13: =AR18+AR23+AR28+AR33 -> 0 | AS13: =AS18+AS23+AS28+AS33 -> 0 | AW13: 65～70 | AY13: =AF13*$T$4*0.9 -> 0 | AZ13: =AG13*$T$4*0.9 -> 0 | BE13: =(AR13)*$T$4*0.9 -> 0 | BF13: =(AS13)*$T$4*0.9 -> 0
G14: =IF(SUM(G13:H13)>0,1,"") | I14: =IF(SUM(I13:J13)>0,1,"") | K14: =IF(SUM(K13:L13)>0,1,"") | M14: =IF(SUM(M13:N13)>0,1,"") | AD14: 70～75 | AF14: =AF19+AF24+AF29+AF34 -> 0 | AG14: =AG19+AG24+AG29+AG34 -> 0 | AH14: =AH19+AH24+AH29+AH34 -> 0 | AI14: =AI19+AI24+AI29+AI34 -> 0 | AR14: =AR19+AR24+AR29+AR34 -> 0 | AS14: =AS19+AS24+AS29+AS34 -> 0 | AW14: 70～75 | AY14: =AF14*$T$4*0.8 -> 0 | AZ14: =AG14*$T$4*0.8 -> 0 | BE14: =(AR14)*$T$4*0.8 -> 0 | BF14: =(AS14)*$T$4*0.8 -> 0
A15: =ROUND((ROW()-10)/2,0) -> 3 | C15: =IF(INDEX(設定!$C$9:$C$108,$A15,1)="","",INDEX(設定!$C$9:$C$108,$A15,1)) | D15: =IF(INDEX(設定!$D$9:$D$108,$A15,1)="","",INDEX(設定!$D$9:$D$108,$A15,1)) | E15: =IF(INDEX(設定!$E$9:$E$108,$A15,1)="","",INDEX(設定!$E$9:$E$108,$A15,1)) | F15: =IF(S15="","",IF(S15=1,"1：家族",IF(AND(S15>=2,S15<=5),"2：雇用",""))) | G15: =INT(INDEX(設定!$H$9:H$108,$A15,1)) -> 0 | H15: =IF(INDEX(設定!$H$9:$H$108,$A15,1)=0,"",ROUND(MOD(INDEX(設定!$H$9:$H$108,$A15,1),1)*60,0)) | I15: =INT(INDEX(設定!$I$9:$I$108,$A15,1)) -> 0 | J15: =IF(INDEX(設定!$I$9:$I$108,$A15,1)=0,"",ROUND(MOD(INDEX(設定!$I$9:$I$108,$A15,1),1)*60,0)) | K15: =INT(INDEX(設定!$J$9:$J$108,$A15,1)) -> 0 | L15: =IF(INDEX(設定!$J$9:$J$108,$A15,1)=0,"",ROUND(MOD(INDEX(設定!$J$9:$J$108,$A15,1),1)*60,0)) | M15: =INT(INDEX(設定!$K$9:$K$108,$A15,1)) -> 0 | N15: =IF(INDEX(設定!$K$9:$K$108,$A15,1)=0,"",ROUND(MOD(INDEX(設定!$K$9:$K$108,$A15,1),1)*60,0)) | S15: =IF(INDEX(設定!$F$9:$F$108,$A15,1)="","",VALUE(LEFT(INDEX(設定!$F$9:$F$108,$A15,1),1))) | T15: =IF(C15="","",C15) | U15: =IF(D15="","",IF(D15="1：男",1,IF(D15="2：女",2))) | V15: =IF(E15="","",E15) | W15: =IF(AND(G15="",H15="",G16=""),"",ROUND(SUM(G15,H15/60)*G16,1)) | X15: =IF(AND(I15="",J15="",I16=""),"",ROUND(SUM(I15,J15/60)*I16,1)) | Y15: =IF(AND(K15="",L15="",K16=""),"",ROUND(SUM(K15,L15/60)*K16,1)) | Z15: =IF(AND(M15="",N15="",M16=""),"",ROUND(SUM(M15,N15/60)*M16,1)) | AD15: 75歳以上 | AF15: =AF20+AF25+AF30+AF35 -> 0 | AG15: =AG20+AG25+AG30+AG35 -> 0 | AH15: =AH20+AH25+AH30+AH35 -> 0 | AI15: =AI20+AI25+AI30+AI35 -> 0 | AR15: =AR20+AR25+AR30+AR35 -> 0 | AS15: =AS20+AS25+AS30+AS35 -> 0 | AW15: 75歳以上 | AY15: =AF15*$T$4*0.7 -> 0 | AZ15: =AG15*$T$4*0.7 -> 0 | BE15: =(AR15)*$T$4*0.7 -> 0 | BF15: =(AS15)*$T$4*0.7 -> 0
G16: =IF(SUM(G15:H15)>0,1,"") | I16: =IF(SUM(I15:J15)>0,1,"") | K16: =IF(SUM(K15:L15)>0,1,"") | M16: =IF(SUM(M15:N15)>0,1,"") | AD16: 飼料の調理・ 給与・給水 | AF16: =SUM(AF17:AF20) -> 0 | AG16: =SUM(AG17:AG20) -> 0 | AL16: =AN16+AP16+AR16 -> 0 | AM16: =AO16+AQ16+AS16 -> 0 | AN16: =SUMIFS($W$11:$W$70,$S$11:$S$70,2,$U$11:$U$70,1) -> 0 | AO16: =SUMIFS($W$11:$W$70,$S$11:$S$70,2,$U$11:$U$70,2) -> 0 | AP16: =AP17 -> 0 | AQ16: =AQ17 -> 0 | AR16: =SUM(AR17:AR20) -> 0 | AS16: =SUM(AS17:AS20) -> 0
A17: =ROUND((ROW()-10)/2,0) -> 4 | C17: =IF(INDEX(設定!$C$9:$C$108,$A17,1)="","",INDEX(設定!$C$9:$C$108,$A17,1)) | D17: =IF(INDEX(設定!$D$9:$D$108,$A17,1)="","",INDEX(設定!$D$9:$D$108,$A17,1)) | E17: =IF(INDEX(設定!$E$9:$E$108,$A17,1)="","",INDEX(設定!$E$9:$E$108,$A17,1)) | F17: =IF(S17="","",IF(S17=1,"1：家族",IF(AND(S17>=2,S17<=5),"2：雇用",""))) | G17: =INT(INDEX(設定!$H$9:H$108,$A17,1)) -> 0 | H17: =IF(INDEX(設定!$H$9:$H$108,$A17,1)=0,"",ROUND(MOD(INDEX(設定!$H$9:$H$108,$A17,1),1)*60,0)) | I17: =INT(INDEX(設定!$I$9:$I$108,$A17,1)) -> 0 | J17: =IF(INDEX(設定!$I$9:$I$108,$A17,1)=0,"",ROUND(MOD(INDEX(設定!$I$9:$I$108,$A17,1),1)*60,0)) | K17: =INT(INDEX(設定!$J$9:$J$108,$A17,1)) -> 0 | L17: =IF(INDEX(設定!$J$9:$J$108,$A17,1)=0,"",ROUND(MOD(INDEX(設定!$J$9:$J$108,$A17,1),1)*60,0)) | M17: =INT(INDEX(設定!$K$9:$K$108,$A17,1)) -> 0 | N17: =IF(INDEX(設定!$K$9:$K$108,$A17,1)=0,"",ROUND(MOD(INDEX(設定!$K$9:$K$108,$A17,1),1)*60,0)) | S17: =IF(INDEX(設定!$F$9:$F$108,$A17,1)="","",VALUE(LEFT(INDEX(設定!$F$9:$F$108,$A17,1),1))) | T17: =IF(C17="","",C17) | U17: =IF(D17="","",IF(D17="1：男",1,IF(D17="2：女",2))) | V17: =IF(E17="","",E17) | W17: =IF(AND(G17="",H17="",G18=""),"",ROUND(SUM(G17,H17/60)*G18,1)) | X17: =IF(AND(I17="",J17="",I18=""),"",ROUND(SUM(I17,J17/60)*I18,1)) | Y17: =IF(AND(K17="",L17="",K18=""),"",ROUND(SUM(K17,L17/60)*K18,1)) | Z17: =IF(AND(M17="",N17="",M18=""),"",ROUND(SUM(M17,N17/60)*M18,1)) | AE17: 65歳未満 | AF17: =AH17+AJ17 -> 0 | AG17: =AI17+AK17 -> 0 | AH17: =SUMIFS($W$11:$W$70,$S$11:$S$70,1,$U$11:$U$70,1,$V$11:$V$70,"<65") -> 0 | AI17: =SUMIFS($W$11:$W$70,$S$11:$S$70,1,$U$11:$U$70,2,$V$11:$V$70,"<65") -> 0 | AJ17: =SUMIFS($W$11:$W$70,$S$11:$S$70,3,$U$11:$U$70,1) -> 0 | AK17: =SUMIFS($W$11:$W$70,$S$11:$S$70,3,$U$11:$U$70,2) -> 0 | AP17: =SUMIFS($W$11:$W$70,$S$11:$S$70,4,$U$11:$U$70,1) -> 0 | AQ17: =SUMIFS($W$11:$W$70,$S$11:$S$70,4,$U$11:$U$70,2) -> 0 | AR17: =SUMIFS($W$11:$W$70,$S$11:$S$70,5,$U$11:$U$70,1,$V$11:$V$70,"<65") -> 0 | AS17: =SUMIFS($W$11:$W$70,$S$11:$S$70,5,$U$11:$U$70,2,$V$11:$V$70,"<65") -> 0
G18: =IF(SUM(G17:H17)>0,1,"") | I18: =IF(SUM(I17:J17)>0,1,"") | K18: =IF(SUM(K17:L17)>0,1,"") | M18: =IF(SUM(M17:N17)>0,1,"") | AE18: 65～70 | AF18: =AH18+AJ18 -> 0 | AG18: =AI18+AK18 -> 0 | AH18: =SUMIFS($W$11:$W$70,$S$11:$S$70,1,$U$11:$U$70,1,$V$11:$V$70,">=65",$V$11:$V$70,"<70") -> 0 | AI18: =SUMIFS($W$11:$W$70,$S$11:$S$70,1,$U$11:$U$70,2,$V$11:$V$70,">=65",$V$11:$V$70,"<70") -> 0 | AR18: =SUMIFS($W$11:$W$70,$S$11:$S$70,5,$U$11:$U$70,1,$V$11:$V$70,">=65",$V$11:$V$70,"<70") -> 0 | AS18: =SUMIFS($W$11:$W$70,$S$11:$S$70,5,$U$11:$U$70,2,$V$11:$V$70,">=65",$V$11:$V$70,"<70") -> 0
A19: =ROUND((ROW()-10)/2,0) -> 5 | C19: =IF(INDEX(設定!$C$9:$C$108,$A19,1)="","",INDEX(設定!$C$9:$C$108,$A19,1)) | D19: =IF(INDEX(設定!$D$9:$D$108,$A19,1)="","",INDEX(設定!$D$9:$D$108,$A19,1)) | E19: =IF(INDEX(設定!$E$9:$E$108,$A19,1)="","",INDEX(設定!$E$9:$E$108,$A19,1)) | F19: =IF(S19="","",IF(S19=1,"1：家族",IF(AND(S19>=2,S19<=5),"2：雇用",""))) | G19: =INT(INDEX(設定!$H$9:H$108,$A19,1)) -> 0 | H19: =IF(INDEX(設定!$H$9:$H$108,$A19,1)=0,"",ROUND(MOD(INDEX(設定!$H$9:$H$108,$A19,1),1)*60,0)) | I19: =INT(INDEX(設定!$I$9:$I$108,$A19,1)) -> 0 | J19: =IF(INDEX(設定!$I$9:$I$108,$A19,1)=0,"",ROUND(MOD(INDEX(設定!$I$9:$I$108,$A19,1),1)*60,0)) | K19: =INT(INDEX(設定!$J$9:$J$108,$A19,1)) -> 0 | L19: =IF(INDEX(設定!$J$9:$J$108,$A19,1)=0,"",ROUND(MOD(INDEX(設定!$J$9:$J$108,$A19,1),1)*60,0)) | M19: =INT(INDEX(設定!$K$9:$K$108,$A19,1)) -> 0 | N19: =IF(INDEX(設定!$K$9:$K$108,$A19,1)=0,"",ROUND(MOD(INDEX(設定!$K$9:$K$108,$A19,1),1)*60,0)) | S19: =IF(INDEX(設定!$F$9:$F$108,$A19,1)="","",VALUE(LEFT(INDEX(設定!$F$9:$F$108,$A19,1),1))) | T19: =IF(C19="","",C19) | U19: =IF(D19="","",IF(D19="1：男",1,IF(D19="2：女",2))) | V19: =IF(E19="","",E19) | W19: =IF(AND(G19="",H19="",G20=""),"",ROUND(SUM(G19,H19/60)*G20,1)) | X19: =IF(AND(I19="",J19="",I20=""),"",ROUND(SUM(I19,J19/60)*I20,1)) | Y19: =IF(AND(K19="",L19="",K20=""),"",ROUND(SUM(K19,L19/60)*K20,1)) | Z19: =IF(AND(M19="",N19="",M20=""),"",ROUND(SUM(M19,N19/60)*M20,1)) | AE19: 70～75 | AF19: =AH19+AJ19 -> 0 | AG19: =AI19+AK19 -> 0 | AH19: =SUMIFS($W$11:$W$70,$S$11:$S$70,1,$U$11:$U$70,1,$V$11:$V$70,">=70",$V$11:$V$70,"<75") -> 0 | AI19: =SUMIFS($W$11:$W$70,$S$11:$S$70,1,$U$11:$U$70,2,$V$11:$V$70,">=70",$V$11:$V$70,"<75") -> 0 | AR19: =SUMIFS($W$11:$W$70,$S$11:$S$70,5,$U$11:$U$70,1,$V$11:$V$70,">=70",$V$11:$V$70,"<75") -> 0 | AS19: =SUMIFS($W$11:$W$70,$S$11:$S$70,5,$U$11:$U$70,2,$V$11:$V$70,">=70",$V$11:$V$70,"<75") -> 0
G20: =IF(SUM(G19:H19)>0,1,"") | I20: =IF(SUM(I19:J19)>0,1,"") | K20: =IF(SUM(K19:L19)>0,1,"") | M20: =IF(SUM(M19:N19)>0,1,"") | AE20: 75歳以上 | AF20: =AH20+AJ20 -> 0 | AG20: =AI20+AK20 -> 0 | AH20: =SUMIFS($W$11:$W$70,$S$11:$S$70,1,$U$11:$U$70,1,$V$11:$V$70,">=75") -> 0 | AI20: =SUMIFS($W$11:$W$70,$S$11:$S$70,1,$U$11:$U$70,2,$V$11:$V$70,">=75") -> 0 | AR20: =SUMIFS($W$11:$W$70,$S$11:$S$70,5,$U$11:$U$70,1,$V$11:$V$70,">=75") -> 0 | AS20: =SUMIFS($W$11:$W$70,$S$11:$S$70,5,$U$11:$U$70,2,$V$11:$V$70,">=75") -> 0
A21: =ROUND((ROW()-10)/2,0) -> 6 | C21: =IF(INDEX(設定!$C$9:$C$108,$A21,1)="","",INDEX(設定!$C$9:$C$108,$A21,1)) | D21: =IF(INDEX(設定!$D$9:$D$108,$A21,1)="","",INDEX(設定!$D$9:$D$108,$A21,1)) | E21: =IF(INDEX(設定!$E$9:$E$108,$A21,1)="","",INDEX(設定!$E$9:$E$108,$A21,1)) | F21: =IF(S21="","",IF(S21=1,"1：家族",IF(AND(S21>=2,S21<=5),"2：雇用",""))) | G21: =INT(INDEX(設定!$H$9:H$108,$A21,1)) -> 0 | H21: =IF(INDEX(設定!$H$9:$H$108,$A21,1)=0,"",ROUND(MOD(INDEX(設定!$H$9:$H$108,$A21,1),1)*60,0)) | I21: =INT(INDEX(設定!$I$9:$I$108,$A21,1)) -> 0 | J21: =IF(INDEX(設定!$I$9:$I$108,$A21,1)=0,"",ROUND(MOD(INDEX(設定!$I$9:$I$108,$A21,1),1)*60,0)) | K21: =INT(INDEX(設定!$J$9:$J$108,$A21,1)) -> 0 | L21: =IF(INDEX(設定!$J$9:$J$108,$A21,1)=0,"",ROUND(MOD(INDEX(設定!$J$9:$J$108,$A21,1),1)*60,0)) | M21: =INT(INDEX(設定!$K$9:$K$108,$A21,1)) -> 0 | N21: =IF(INDEX(設定!$K$9:$K$108,$A21,1)=0,"",ROUND(MOD(INDEX(設定!$K$9:$K$108,$A21,1),1)*60,0)) | S21: =IF(INDEX(設定!$F$9:$F$108,$A21,1)="","",VALUE(LEFT(INDEX(設定!$F$9:$F$108,$A21,1),1))) | T21: =IF(C21="","",C21) | U21: =IF(D21="","",IF(D21="1：男",1,IF(D21="2：女",2))) | V21: =IF(E21="","",E21) | W21: =IF(AND(G21="",H21="",G22=""),"",ROUND(SUM(G21,H21/60)*G22,1)) | X21: =IF(AND(I21="",J21="",I22=""),"",ROUND(SUM(I21,J21/60)*I22,1)) | Y21: =IF(AND(K21="",L21="",K22=""),"",ROUND(SUM(K21,L21/60)*K22,1)) | Z21: =IF(AND(M21="",N21="",M22=""),"",ROUND(SUM(M21,N21/60)*M22,1)) | AD21: 敷料搬入・ きゅう肥搬出 | AF21: =SUM(AF22:AF25) -> 0 | AG21: =SUM(AG22:AG25) -> 0 | AL21: =AN21+AP21+AR21 -> 0 | AM21: =AO21+AQ21+AS21 -> 0 | AN21: =SUMIFS($X$11:$X$70,$S$11:$S$70,2,$U$11:$U$70,1) -> 0 | AO21: =SUMIFS($X$11:$X$70,$S$11:$S$70,2,$U$11:$U$70,2) -> 0 | AP21: =AP22 -> 0 | AQ21: =AQ22 -> 0 | AR21: =SUM(AR22:AR25) -> 0 | AS21: =SUM(AS22:AS25) -> 0 | AW21: 敷料搬入・ きゅう肥搬出 | AY21: =SUM(AY22:AY25) -> 0 | AZ21: =SUM(AZ22:AZ25) -> 0 | BA21: =ROUND(BC21+BE21,0) -> 0 | BB21: =ROUND(BD21+BF21,0) -> 0 | BC21: =IFERROR($T$112*AN21/($AN$11+$AN$51),0) -> 0 | BD21: =IFERROR($T$113*AO21/($AO$11+$AO$51),0) -> 0 | BE21: =SUM(BE22:BE25) -> 0 | BF21: =SUM(BF22:BF25) -> 0
G22: =IF(SUM(G21:H21)>0,1,"") | I22: =IF(SUM(I21:J21)>0,1,"") | K22: =IF(SUM(K21:L21)>0,1,"") | M22: =IF(SUM(M21:N21)>0,1,"") | AE22: 65歳未満 | AF22: =AH22+AJ22 -> 0 | AG22: =AI22+AK22 -> 0 | AH22: =SUMIFS($X$11:$X$70,$S$11:$S$70,1,$U$11:$U$70,1,$V$11:$V$70,"<65") -> 0 | AI22: =SUMIFS($X$11:$X$70,$S$11:$S$70,1,$U$11:$U$70,2,$V$11:$V$70,"<65") -> 0 | AJ22: =SUMIFS($X$11:$X$70,$S$11:$S$70,3,$U$11:$U$70,1) -> 0 | AK22: =SUMIFS($X$11:$X$70,$S$11:$S$70,3,$U$11:$U$70,2) -> 0 | AP22: =SUMIFS($X$11:$X$70,$S$11:$S$70,4,$U$11:$U$70,1) -> 0 | AQ22: =SUMIFS($X$11:$X$70,$S$11:$S$70,4,$U$11:$U$70,2) -> 0 | AR22: =SUMIFS($X$11:$X$70,$S$11:$S$70,5,$U$11:$U$70,1,$V$11:$V$70,"<65") -> 0 | AS22: =SUMIFS($X$11:$X$70,$S$11:$S$70,5,$U$11:$U$70,2,$V$11:$V$70,"<65") -> 0 | AX22: 65歳未満 | AY22: =ROUND(AF22*$T$4,0) -> 0 | AZ22: =ROUND(AG22*$T$4,0) -> 0 | BE22: =(AP22+AR22)*$T$4 -> 0 | BF22: =(AQ22+AS22)*$T$4 -> 0
A23: =ROUND((ROW()-10)/2,0) -> 7 | C23: =IF(INDEX(設定!$C$9:$C$108,$A23,1)="","",INDEX(設定!$C$9:$C$108,$A23,1)) | D23: =IF(INDEX(設定!$D$9:$D$108,$A23,1)="","",INDEX(設定!$D$9:$D$108,$A23,1)) | E23: =IF(INDEX(設定!$E$9:$E$108,$A23,1)="","",INDEX(設定!$E$9:$E$108,$A23,1)) | F23: =IF(S23="","",IF(S23=1,"1：家族",IF(AND(S23>=2,S23<=5),"2：雇用",""))) | G23: =INT(INDEX(設定!$H$9:H$108,$A23,1)) -> 0 | H23: =IF(INDEX(設定!$H$9:$H$108,$A23,1)=0,"",ROUND(MOD(INDEX(設定!$H$9:$H$108,$A23,1),1)*60,0)) | I23: =INT(INDEX(設定!$I$9:$I$108,$A23,1)) -> 0 | J23: =IF(INDEX(設定!$I$9:$I$108,$A23,1)=0,"",ROUND(MOD(INDEX(設定!$I$9:$I$108,$A23,1),1)*60,0)) | K23: =INT(INDEX(設定!$J$9:$J$108,$A23,1)) -> 0 | L23: =IF(INDEX(設定!$J$9:$J$108,$A23,1)=0,"",ROUND(MOD(INDEX(設定!$J$9:$J$108,$A23,1),1)*60,0)) | M23: =INT(INDEX(設定!$K$9:$K$108,$A23,1)) -> 0 | N23: =IF(INDEX(設定!$K$9:$K$108,$A23,1)=0,"",ROUND(MOD(INDEX(設定!$K$9:$K$108,$A23,1),1)*60,0)) | S23: =IF(INDEX(設定!$F$9:$F$108,$A23,1)="","",VALUE(LEFT(INDEX(設定!$F$9:$F$108,$A23,1),1))) | T23: =IF(C23="","",C23) | U23: =IF(D23="","",IF(D23="1：男",1,IF(D23="2：女",2))) | V23: =IF(E23="","",E23) | W23: =IF(AND(G23="",H23="",G24=""),"",ROUND(SUM(G23,H23/60)*G24,1)) | X23: =IF(AND(I23="",J23="",I24=""),"",ROUND(SUM(I23,J23/60)*I24,1)) | Y23: =IF(AND(K23="",L23="",K24=""),"",ROUND(SUM(K23,L23/60)*K24,1)) | Z23: =IF(AND(M23="",N23="",M24=""),"",ROUND(SUM(M23,N23/60)*M24,1)) | AE23: 65～70 | AF23: =AH23+AJ23 -> 0 | AG23: =AI23+AK23 -> 0 | AH23: =SUMIFS($X$11:$X$70,$S$11:$S$70,1,$U$11:$U$70,1,$V$11:$V$70,">=65",$V$11:$V$70,"<70") -> 0 | AI23: =SUMIFS($X$11:$X$70,$S$11:$S$70,1,$U$11:$U$70,2,$V$11:$V$70,">=65",$V$11:$V$70,"<70") -> 0 | AR23: =SUMIFS($X$11:$X$70,$S$11:$S$70,5,$U$11:$U$70,1,$V$11:$V$70,">=65",$V$11:$V$70,"<70") -> 0 | AS23: =SUMIFS($X$11:$X$70,$S$11:$S$70,5,$U$11:$U$70,2,$V$11:$V$70,">=65",$V$11:$V$70,"<70") -> 0 | AX23: 65～70 | AY23: =ROUND(AF23*$T$4*0.9,0) -> 0 | AZ23: =ROUND(AG23*$T$4*0.9,0) -> 0 | BE23: =(AR23)*$T$4*0.9 -> 0 | BF23: =(AS23)*$T$4*0.9 -> 0
G24: =IF(SUM(G23:H23)>0,1,"") | I24: =IF(SUM(I23:J23)>0,1,"") | K24: =IF(SUM(K23:L23)>0,1,"") | M24: =IF(SUM(M23:N23)>0,1,"") | AE24: 70～75 | AF24: =AH24+AJ24 -> 0 | AG24: =AI24+AK24 -> 0 | AH24: =SUMIFS($X$11:$X$70,$S$11:$S$70,1,$U$11:$U$70,1,$V$11:$V$70,">=70",$V$11:$V$70,"<75") -> 0 | AI24: =SUMIFS($X$11:$X$70,$S$11:$S$70,1,$U$11:$U$70,2,$V$11:$V$70,">=70",$V$11:$V$70,"<75") -> 0 | AR24: =SUMIFS($X$11:$X$70,$S$11:$S$70,5,$U$11:$U$70,1,$V$11:$V$70,">=70",$V$11:$V$70,"<75") -> 0 | AS24: =SUMIFS($X$11:$X$70,$S$11:$S$70,5,$U$11:$U$70,2,$V$11:$V$70,">=70",$V$11:$V$70,"<75") -> 0 | AX24: 70～75 | AY24: =ROUND(AF24*$T$4*0.8,0) -> 0 | AZ24: =ROUND(AG24*$T$4*0.8,0) -> 0 | BE24: =(AR24)*$T$4*0.8 -> 0 | BF24: =(AS24)*$T$4*0.8 -> 0
A25: =ROUND((ROW()-10)/2,0) -> 8 | C25: =IF(INDEX(設定!$C$9:$C$108,$A25,1)="","",INDEX(設定!$C$9:$C$108,$A25,1)) | D25: =IF(INDEX(設定!$D$9:$D$108,$A25,1)="","",INDEX(設定!$D$9:$D$108,$A25,1)) | E25: =IF(INDEX(設定!$E$9:$E$108,$A25,1)="","",INDEX(設定!$E$9:$E$108,$A25,1)) | F25: =IF(S25="","",IF(S25=1,"1：家族",IF(AND(S25>=2,S25<=5),"2：雇用",""))) | G25: =INT(INDEX(設定!$H$9:H$108,$A25,1)) -> 0 | H25: =IF(INDEX(設定!$H$9:$H$108,$A25,1)=0,"",ROUND(MOD(INDEX(設定!$H$9:$H$108,$A25,1),1)*60,0)) | I25: =INT(INDEX(設定!$I$9:$I$108,$A25,1)) -> 0 | J25: =IF(INDEX(設定!$I$9:$I$108,$A25,1)=0,"",ROUND(MOD(INDEX(設定!$I$9:$I$108,$A25,1),1)*60,0)) | K25: =INT(INDEX(設定!$J$9:$J$108,$A25,1)) -> 0 | L25: =IF(INDEX(設定!$J$9:$J$108,$A25,1)=0,"",ROUND(MOD(INDEX(設定!$J$9:$J$108,$A25,1),1)*60,0)) | M25: =INT(INDEX(設定!$K$9:$K$108,$A25,1)) -> 0 | N25: =IF(INDEX(設定!$K$9:$K$108,$A25,1)=0,"",ROUND(MOD(INDEX(設定!$K$9:$K$108,$A25,1),1)*60,0)) | S25: =IF(INDEX(設定!$F$9:$F$108,$A25,1)="","",VALUE(LEFT(INDEX(設定!$F$9:$F$108,$A25,1),1))) | T25: =IF(C25="","",C25) | U25: =IF(D25="","",IF(D25="1：男",1,IF(D25="2：女",2))) | V25: =IF(E25="","",E25) | W25: =IF(AND(G25="",H25="",G26=""),"",ROUND(SUM(G25,H25/60)*G26,1)) | X25: =IF(AND(I25="",J25="",I26=""),"",ROUND(SUM(I25,J25/60)*I26,1)) | Y25: =IF(AND(K25="",L25="",K26=""),"",ROUND(SUM(K25,L25/60)*K26,1)) | Z25: =IF(AND(M25="",N25="",M26=""),"",ROUND(SUM(M25,N25/60)*M26,1)) | AE25: 75歳以上 | AF25: =AH25+AJ25 -> 0 | AG25: =AI25+AK25 -> 0 | AH25: =SUMIFS($X$11:$X$70,$S$11:$S$70,1,$U$11:$U$70,1,$V$11:$V$70,">=75") -> 0 | AI25: =SUMIFS($X$11:$X$70,$S$11:$S$70,1,$U$11:$U$70,2,$V$11:$V$70,">=75") -> 0 | AR25: =SUMIFS($X$11:$X$70,$S$11:$S$70,5,$U$11:$U$70,1,$V$11:$V$70,">=75") -> 0 | AS25: =SUMIFS($X$11:$X$70,$S$11:$S$70,5,$U$11:$U$70,2,$V$11:$V$70,">=75") -> 0 | AX25: 75歳以上 | AY25: =ROUND(AF25*$T$4*0.7,0) -> 0 | AZ25: =ROUND(AG25*$T$4*0.7,0) -> 0 | BE25: =(AR25)*$T$4*0.7 -> 0 | BF25: =(AS25)*$T$4*0.7 -> 0
G26: =IF(SUM(G25:H25)>0,1,"") | I26: =IF(SUM(I25:J25)>0,1,"") | K26: =IF(SUM(K25:L25)>0,1,"") | M26: =IF(SUM(M25:N25)>0,1,"") | AD26: 搾乳・牛乳処理・運搬 | AF26: =SUM(AF27:AF30) -> 0 | AG26: =SUM(AG27:AG30) -> 0 | AL26: =AN26+AP26+AR26 -> 0 | AM26: =AO26+AQ26+AS26 -> 0 | AN26: =SUMIFS($Y$11:$Y$70,$S$11:$S$70,2,$U$11:$U$70,1) -> 0 | AO26: =SUMIFS($Y$11:$Y$70,$S$11:$S$70,2,$U$11:$U$70,2) -> 0 | AP26: =AP27 -> 0 | AQ26: =AQ27 -> 0 | AR26: =SUM(AR27:AR30) -> 0 | AS26: =SUM(AS27:AS30) -> 0 | AW26: 搾乳・牛乳処理・運搬 | AY26: =SUM(AY27:AY30) -> 0 | AZ26: =SUM(AZ27:AZ30) -> 0 | BA26: =ROUND(BC26+BE26,0) -> 0 | BB26: =ROUND(BD26+BF26,0) -> 0 | BC26: =IFERROR($T$112*AN26/($AN$11+$AN$51),0) -> 0 | BD26: =IFERROR($T$113*AO26/($AO$11+$AO$51),0) -> 0 | BE26: =SUM(BE27:BE30) -> 0 | BF26: =SUM(BF27:BF30) -> 0
A27: =ROUND((ROW()-10)/2,0) -> 9 | C27: =IF(INDEX(設定!$C$9:$C$108,$A27,1)="","",INDEX(設定!$C$9:$C$108,$A27,1)) | D27: =IF(INDEX(設定!$D$9:$D$108,$A27,1)="","",INDEX(設定!$D$9:$D$108,$A27,1)) | E27: =IF(INDEX(設定!$E$9:$E$108,$A27,1)="","",INDEX(設定!$E$9:$E$108,$A27,1)) | F27: =IF(S27="","",IF(S27=1,"1：家族",IF(AND(S27>=2,S27<=5),"2：雇用",""))) | G27: =INT(INDEX(設定!$H$9:H$108,$A27,1)) -> 0 | H27: =IF(INDEX(設定!$H$9:$H$108,$A27,1)=0,"",ROUND(MOD(INDEX(設定!$H$9:$H$108,$A27,1),1)*60,0)) | I27: =INT(INDEX(設定!$I$9:$I$108,$A27,1)) -> 0 | J27: =IF(INDEX(設定!$I$9:$I$108,$A27,1)=0,"",ROUND(MOD(INDEX(設定!$I$9:$I$108,$A27,1),1)*60,0)) | K27: =INT(INDEX(設定!$J$9:$J$108,$A27,1)) -> 0 | L27: =IF(INDEX(設定!$J$9:$J$108,$A27,1)=0,"",ROUND(MOD(INDEX(設定!$J$9:$J$108,$A27,1),1)*60,0)) | M27: =INT(INDEX(設定!$K$9:$K$108,$A27,1)) -> 0 | N27: =IF(INDEX(設定!$K$9:$K$108,$A27,1)=0,"",ROUND(MOD(INDEX(設定!$K$9:$K$108,$A27,1),1)*60,0)) | S27: =IF(INDEX(設定!$F$9:$F$108,$A27,1)="","",VALUE(LEFT(INDEX(設定!$F$9:$F$108,$A27,1),1))) | T27: =IF(C27="","",C27) | U27: =IF(D27="","",IF(D27="1：男",1,IF(D27="2：女",2))) | V27: =IF(E27="","",E27) | W27: =IF(AND(G27="",H27="",G28=""),"",ROUND(SUM(G27,H27/60)*G28,1)) | X27: =IF(AND(I27="",J27="",I28=""),"",ROUND(SUM(I27,J27/60)*I28,1)) | Y27: =IF(AND(K27="",L27="",K28=""),"",ROUND(SUM(K27,L27/60)*K28,1)) | Z27: =IF(AND(M27="",N27="",M28=""),"",ROUND(SUM(M27,N27/60)*M28,1)) | AE27: 65歳未満 | AF27: =AH27+AJ27 -> 0 | AG27: =AI27+AK27 -> 0 | AH27: =SUMIFS($Y$11:$Y$70,$S$11:$S$70,1,$U$11:$U$70,1,$V$11:$V$70,"<65") -> 0 | AI27: =SUMIFS($Y$11:$Y$70,$S$11:$S$70,1,$U$11:$U$70,2,$V$11:$V$70,"<65") -> 0 | AJ27: =SUMIFS($Y$11:$Y$70,$S$11:$S$70,3,$U$11:$U$70,1) -> 0 | AK27: =SUMIFS($Y$11:$Y$70,$S$11:$S$70,3,$U$11:$U$70,2) -> 0 | AP27: =SUMIFS($Y$11:$Y$70,$S$11:$S$70,4,$U$11:$U$70,1) -> 0 | AQ27: =SUMIFS($Y$11:$Y$70,$S$11:$S$70,4,$U$11:$U$70,2) -> 0 | AR27: =SUMIFS($Y$11:$Y$70,$S$11:$S$70,5,$U$11:$U$70,1,$V$11:$V$70,"<65") -> 0 | AS27: =SUMIFS($Y$11:$Y$70,$S$11:$S$70,5,$U$11:$U$70,2,$V$11:$V$70,"<65") -> 0 | AX27: 65歳未満 | AY27: =ROUND(AF27*$T$4,0) -> 0 | AZ27: =ROUND(AG27*$T$4,0) -> 0 | BE27: =(AP27+AR27)*$T$4 -> 0 | BF27: =(AQ27+AS27)*$T$4 -> 0
G28: =IF(SUM(G27:H27)>0,1,"") | I28: =IF(SUM(I27:J27)>0,1,"") | K28: =IF(SUM(K27:L27)>0,1,"") | M28: =IF(SUM(M27:N27)>0,1,"") | AE28: 65～70 | AF28: =AH28+AJ28 -> 0 | AG28: =AI28+AK28 -> 0 | AH28: =SUMIFS($Y$11:$Y$70,$S$11:$S$70,1,$U$11:$U$70,1,$V$11:$V$70,">=65",$V$11:$V$70,"<70") -> 0 | AI28: =SUMIFS($Y$11:$Y$70,$S$11:$S$70,1,$U$11:$U$70,2,$V$11:$V$70,">=65",$V$11:$V$70,"<70") -> 0 | AR28: =SUMIFS($Y$11:$Y$70,$S$11:$S$70,5,$U$11:$U$70,1,$V$11:$V$70,">=65",$V$11:$V$70,"<70") -> 0 | AS28: =SUMIFS($Y$11:$Y$70,$S$11:$S$70,5,$U$11:$U$70,2,$V$11:$V$70,">=65",$V$11:$V$70,"<70") -> 0 | AX28: 65～70 | AY28: =ROUND(AF28*$T$4*0.9,0) -> 0 | AZ28: =ROUND(AG28*$T$4*0.9,0) -> 0 | BE28: =(AR28)*$T$4*0.9 -> 0 | BF28: =(AS28)*$T$4*0.9 -> 0
A29: =ROUND((ROW()-10)/2,0) -> 10 | C29: =IF(INDEX(設定!$C$9:$C$108,$A29,1)="","",INDEX(設定!$C$9:$C$108,$A29,1)) | D29: =IF(INDEX(設定!$D$9:$D$108,$A29,1)="","",INDEX(設定!$D$9:$D$108,$A29,1)) | E29: =IF(INDEX(設定!$E$9:$E$108,$A29,1)="","",INDEX(設定!$E$9:$E$108,$A29,1)) | F29: =IF(S29="","",IF(S29=1,"1：家族",IF(AND(S29>=2,S29<=5),"2：雇用",""))) | G29: =INT(INDEX(設定!$H$9:H$108,$A29,1)) -> 0 | H29: =IF(INDEX(設定!$H$9:$H$108,$A29,1)=0,"",ROUND(MOD(INDEX(設定!$H$9:$H$108,$A29,1),1)*60,0)) | I29: =INT(INDEX(設定!$I$9:$I$108,$A29,1)) -> 0 | J29: =IF(INDEX(設定!$I$9:$I$108,$A29,1)=0,"",ROUND(MOD(INDEX(設定!$I$9:$I$108,$A29,1),1)*60,0)) | K29: =INT(INDEX(設定!$J$9:$J$108,$A29,1)) -> 0 | L29: =IF(INDEX(設定!$J$9:$J$108,$A29,1)=0,"",ROUND(MOD(INDEX(設定!$J$9:$J$108,$A29,1),1)*60,0)) | M29: =INT(INDEX(設定!$K$9:$K$108,$A29,1)) -> 0 | N29: =IF(INDEX(設定!$K$9:$K$108,$A29,1)=0,"",ROUND(MOD(INDEX(設定!$K$9:$K$108,$A29,1),1)*60,0)) | S29: =IF(INDEX(設定!$F$9:$F$108,$A29,1)="","",VALUE(LEFT(INDEX(設定!$F$9:$F$108,$A29,1),1))) | T29: =IF(C29="","",C29) | U29: =IF(D29="","",IF(D29="1：男",1,IF(D29="2：女",2))) | V29: =IF(E29="","",E29) | W29: =IF(AND(G29="",H29="",G30=""),"",ROUND(SUM(G29,H29/60)*G30,1)) | X29: =IF(AND(I29="",J29="",I30=""),"",ROUND(SUM(I29,J29/60)*I30,1)) | Y29: =IF(AND(K29="",L29="",K30=""),"",ROUND(SUM(K29,L29/60)*K30,1)) | Z29: =IF(AND(M29="",N29="",M30=""),"",ROUND(SUM(M29,N29/60)*M30,1)) | AE29: 70～75 | AF29: =AH29+AJ29 -> 0 | AG29: =AI29+AK29 -> 0 | AH29: =SUMIFS($Y$11:$Y$70,$S$11:$S$70,1,$U$11:$U$70,1,$V$11:$V$70,">=70",$V$11:$V$70,"<75") -> 0 | AI29: =SUMIFS($Y$11:$Y$70,$S$11:$S$70,1,$U$11:$U$70,2,$V$11:$V$70,">=70",$V$11:$V$70,"<75") -> 0 | AR29: =SUMIFS($Y$11:$Y$70,$S$11:$S$70,5,$U$11:$U$70,1,$V$11:$V$70,">=70",$V$11:$V$70,"<75") -> 0 | AS29: =SUMIFS($Y$11:$Y$70,$S$11:$S$70,5,$U$11:$U$70,2,$V$11:$V$70,">=70",$V$11:$V$70,"<75") -> 0 | AX29: 70～75 | AY29: =ROUND(AF29*$T$4*0.8,0) -> 0 | AZ29: =ROUND(AG29*$T$4*0.8,0) -> 0 | BE29: =(AR29)*$T$4*0.8 -> 0 | BF29: =(AS29)*$T$4*0.8 -> 0
G30: =IF(SUM(G29:H29)>0,1,"") | I30: =IF(SUM(I29:J29)>0,1,"") | K30: =IF(SUM(K29:L29)>0,1,"") | M30: =IF(SUM(M29:N29)>0,1,"") | AE30: 75歳以上 | AF30: =AH30+AJ30 -> 0 | AG30: =AI30+AK30 -> 0 | AH30: =SUMIFS($Y$11:$Y$70,$S$11:$S$70,1,$U$11:$U$70,1,$V$11:$V$70,">=75") -> 0 | AI30: =SUMIFS($Y$11:$Y$70,$S$11:$S$70,1,$U$11:$U$70,2,$V$11:$V$70,">=75") -> 0 | AR30: =SUMIFS($Y$11:$Y$70,$S$11:$S$70,5,$U$11:$U$70,1,$V$11:$V$70,">=75") -> 0 | AS30: =SUMIFS($Y$11:$Y$70,$S$11:$S$70,5,$U$11:$U$70,2,$V$11:$V$70,">=75") -> 0 | AX30: 75歳以上 | AY30: =ROUND(AF30*$T$4*0.7,0) -> 0 | AZ30: =ROUND(AG30*$T$4*0.7,0) -> 0 | BE30: =(AR30)*$T$4*0.7 -> 0 | BF30: =(AS30)*$T$4*0.7 -> 0
A31: =ROUND((ROW()-10)/2,0) -> 11 | C31: =IF(INDEX(設定!$C$9:$C$108,$A31,1)="","",INDEX(設定!$C$9:$C$108,$A31,1)) | D31: =IF(INDEX(設定!$D$9:$D$108,$A31,1)="","",INDEX(設定!$D$9:$D$108,$A31,1)) | E31: =IF(INDEX(設定!$E$9:$E$108,$A31,1)="","",INDEX(設定!$E$9:$E$108,$A31,1)) | F31: =IF(S31="","",IF(S31=1,"1：家族",IF(AND(S31>=2,S31<=5),"2：雇用",""))) | G31: =INT(INDEX(設定!$H$9:H$108,$A31,1)) -> 0 | H31: =IF(INDEX(設定!$H$9:$H$108,$A31,1)=0,"",ROUND(MOD(INDEX(設定!$H$9:$H$108,$A31,1),1)*60,0)) | I31: =INT(INDEX(設定!$I$9:$I$108,$A31,1)) -> 0 | J31: =IF(INDEX(設定!$I$9:$I$108,$A31,1)=0,"",ROUND(MOD(INDEX(設定!$I$9:$I$108,$A31,1),1)*60,0)) | K31: =INT(INDEX(設定!$J$9:$J$108,$A31,1)) -> 0 | L31: =IF(INDEX(設定!$J$9:$J$108,$A31,1)=0,"",ROUND(MOD(INDEX(設定!$J$9:$J$108,$A31,1),1)*60,0)) | M31: =INT(INDEX(設定!$K$9:$K$108,$A31,1)) -> 0 | N31: =IF(INDEX(設定!$K$9:$K$108,$A31,1)=0,"",ROUND(MOD(INDEX(設定!$K$9:$K$108,$A31,1),1)*60,0)) | S31: =IF(INDEX(設定!$F$9:$F$108,$A31,1)="","",VALUE(LEFT(INDEX(設定!$F$9:$F$108,$A31,1),1))) | T31: =IF(C31="","",C31) | U31: =IF(D31="","",IF(D31="1：男",1,IF(D31="2：女",2))) | V31: =IF(E31="","",E31) | W31: =IF(AND(G31="",H31="",G32=""),"",ROUND(SUM(G31,H31/60)*G32,1)) | X31: =IF(AND(I31="",J31="",I32=""),"",ROUND(SUM(I31,J31/60)*I32,1)) | Y31: =IF(AND(K31="",L31="",K32=""),"",ROUND(SUM(K31,L31/60)*K32,1)) | Z31: =IF(AND(M31="",N31="",M32=""),"",ROUND(SUM(M31,N31/60)*M32,1)) | AD31: その他の 飼育作業 | AF31: =SUM(AF32:AF35) -> 0 | AG31: =SUM(AG32:AG35) -> 0 | AL31: =AN31+AP31+AR31 -> 0 | AM31: =AO31+AQ31+AS31 -> 0 | AN31: =SUMIFS($Z$11:$Z$70,$S$11:$S$70,2,$U$11:$U$70,1) -> 0 | AO31: =SUMIFS($Z$11:$Z$70,$S$11:$S$70,2,$U$11:$U$70,2) -> 0 | AP31: =AP32 -> 0 | AQ31: =AQ32 -> 0 | AR31: =SUM(AR32:AR35) -> 0 | AS31: =SUM(AS32:AS35) -> 0
G32: =IF(SUM(G31:H31)>0,1,"") | I32: =IF(SUM(I31:J31)>0,1,"") | K32: =IF(SUM(K31:L31)>0,1,"") | M32: =IF(SUM(M31:N31)>0,1,"") | AE32: 65歳未満 | AF32: =AH32+AJ32 -> 0 | AG32: =AI32+AK32 -> 0 | AH32: =SUMIFS($Z$11:$Z$70,$S$11:$S$70,1,$U$11:$U$70,1,$V$11:$V$70,"<65")+SUMIFS($W$77:$W$106,$S$77:$S$106,1,$U$77:$U$106,1,$V$77:$V$106,"<65") -> 0 | AI32: =SUMIFS($Z$11:$Z$70,$S$11:$S$70,1,$U$11:$U$70,2,$V$11:$V$70,"<65")+SUMIFS($W$77:$W$106,$S$77:$S$106,1,$U$77:$U$106,2,$V$77:$V$106,"<65") -> 0 | AJ32: =SUMIFS($Z$11:$Z$70,$S$11:$S$70,3,$U$11:$U$70,1) +SUMIFS($Y$77:$Y$106,$S$77:$S$106,3,$U$77:$U$106,1) -> 0 | AK32: =SUMIFS($Z$11:$Z$70,$S$11:$S$70,3,$U$11:$U$70,2) +SUMIFS($Y$77:$Y$106,$S$77:$S$106,3,$U$77:$U$106,2) -> 0 | AP32: =SUMIFS($Z$11:$Z$70,$S$11:$S$70,4,$U$11:$U$70,1) +SUMIFS($Y$77:$Y$106,$S$77:$S$106,4,$U$77:$U$106,1) -> 0 | AQ32: =SUMIFS($Z$11:$Z$70,$S$11:$S$70,4,$U$11:$U$70,2) +SUMIFS($Y$77:$Y$106,$S$77:$S$106,4,$U$77:$U$106,2) -> 0 | AR32: =SUMIFS($Z$11:$Z$70,$S$11:$S$70,5,$U$11:$U$70,1,$V$11:$V$70,"<65") -> 0 | AS32: =SUMIFS($Z$11:$Z$70,$S$11:$S$70,5,$U$11:$U$70,2,$V$11:$V$70,"<65") -> 0
A33: =ROUND((ROW()-10)/2,0) -> 12 | C33: =IF(INDEX(設定!$C$9:$C$108,$A33,1)="","",INDEX(設定!$C$9:$C$108,$A33,1)) | D33: =IF(INDEX(設定!$D$9:$D$108,$A33,1)="","",INDEX(設定!$D$9:$D$108,$A33,1)) | E33: =IF(INDEX(設定!$E$9:$E$108,$A33,1)="","",INDEX(設定!$E$9:$E$108,$A33,1)) | F33: =IF(S33="","",IF(S33=1,"1：家族",IF(AND(S33>=2,S33<=5),"2：雇用",""))) | G33: =INT(INDEX(設定!$H$9:H$108,$A33,1)) -> 0 | H33: =IF(INDEX(設定!$H$9:$H$108,$A33,1)=0,"",ROUND(MOD(INDEX(設定!$H$9:$H$108,$A33,1),1)*60,0)) | I33: =INT(INDEX(設定!$I$9:$I$108,$A33,1)) -> 0 | J33: =IF(INDEX(設定!$I$9:$I$108,$A33,1)=0,"",ROUND(MOD(INDEX(設定!$I$9:$I$108,$A33,1),1)*60,0)) | K33: =INT(INDEX(設定!$J$9:$J$108,$A33,1)) -> 0 | L33: =IF(INDEX(設定!$J$9:$J$108,$A33,1)=0,"",ROUND(MOD(INDEX(設定!$J$9:$J$108,$A33,1),1)*60,0)) | M33: =INT(INDEX(設定!$K$9:$K$108,$A33,1)) -> 0 | N33: =IF(INDEX(設定!$K$9:$K$108,$A33,1)=0,"",ROUND(MOD(INDEX(設定!$K$9:$K$108,$A33,1),1)*60,0)) | S33: =IF(INDEX(設定!$F$9:$F$108,$A33,1)="","",VALUE(LEFT(INDEX(設定!$F$9:$F$108,$A33,1),1))) | T33: =IF(C33="","",C33) | U33: =IF(D33="","",IF(D33="1：男",1,IF(D33="2：女",2))) | V33: =IF(E33="","",E33) | W33: =IF(AND(G33="",H33="",G34=""),"",ROUND(SUM(G33,H33/60)*G34,1)) | X33: =IF(AND(I33="",J33="",I34=""),"",ROUND(SUM(I33,J33/60)*I34,1)) | Y33: =IF(AND(K33="",L33="",K34=""),"",ROUND(SUM(K33,L33/60)*K34,1)) | Z33: =IF(AND(M33="",N33="",M34=""),"",ROUND(SUM(M33,N33/60)*M34,1)) | AE33: 65～70 | AF33: =AH33+AJ33 -> 0 | AG33: =AI33+AK33 -> 0 | AH33: =SUMIFS($Z$11:$Z$70,$S$11:$S$70,1,$U$11:$U$70,1,$V$11:$V$70,">=65",$V$11:$V$70,"<70")+SUMIFS($W$77:$W$106,$S$77:$S$106,1,$U$77:$U$106,1,$V$77:$V$106,">=65",$V$77:$V$106,"<70") -> 0 | AI33: =SUMIFS($Z$11:$Z$70,$S$11:$S$70,1,$U$11:$U$70,2,$V$11:$V$70,">=65",$V$11:$V$70,"<70")+SUMIFS($W$77:$W$106,$S$77:$S$106,1,$U$77:$U$106,2,$V$77:$V$106,">=65",$V$77:$V$106,"<70") -> 0 | AR33: =SUMIFS($Z$11:$Z$70,$S$11:$S$70,5,$U$11:$U$70,1,$V$11:$V$70,">=65",$V$11:$V$70,"<70") -> 0 | AS33: =SUMIFS($Z$11:$Z$70,$S$11:$S$70,5,$U$11:$U$70,2,$V$11:$V$70,">=65",$V$11:$V$70,"<70") -> 0
G34: =IF(SUM(G33:H33)>0,1,"") | I34: =IF(SUM(I33:J33)>0,1,"") | K34: =IF(SUM(K33:L33)>0,1,"") | M34: =IF(SUM(M33:N33)>0,1,"") | AE34: 70～75 | AF34: =AH34+AJ34 -> 0 | AG34: =AI34+AK34 -> 0 | AH34: =SUMIFS($Z$11:$Z$70,$S$11:$S$70,1,$U$11:$U$70,1,$V$11:$V$70,">=70",$V$11:$V$70,"<75")+SUMIFS($W$77:$W$106,$S$77:$S$106,1,$U$77:$U$106,1,$V$77:$V$106,">=70",$V$77:$V$106,"<75") -> 0 | AI34: =SUMIFS($Z$11:$Z$70,$S$11:$S$70,1,$U$11:$U$70,2,$V$11:$V$70,">=70",$V$11:$V$70,"<75")+SUMIFS($W$77:$W$106,$S$77:$S$106,1,$U$77:$U$106,2,$V$77:$V$106,">=70",$V$77:$V$106,"<75") -> 0 | AR34: =SUMIFS($Z$11:$Z$70,$S$11:$S$70,5,$U$11:$U$70,1,$V$11:$V$70,">=70",$V$11:$V$70,"<75") -> 0 | AS34: =SUMIFS($Z$11:$Z$70,$S$11:$S$70,5,$U$11:$U$70,2,$V$11:$V$70,">=70",$V$11:$V$70,"<75") -> 0
A35: =ROUND((ROW()-10)/2,0) -> 13 | C35: =IF(INDEX(設定!$C$9:$C$108,$A35,1)="","",INDEX(設定!$C$9:$C$108,$A35,1)) | D35: =IF(INDEX(設定!$D$9:$D$108,$A35,1)="","",INDEX(設定!$D$9:$D$108,$A35,1)) | E35: =IF(INDEX(設定!$E$9:$E$108,$A35,1)="","",INDEX(設定!$E$9:$E$108,$A35,1)) | F35: =IF(S35="","",IF(S35=1,"1：家族",IF(AND(S35>=2,S35<=5),"2：雇用",""))) | G35: =INT(INDEX(設定!$H$9:H$108,$A35,1)) -> 0 | H35: =IF(INDEX(設定!$H$9:$H$108,$A35,1)=0,"",ROUND(MOD(INDEX(設定!$H$9:$H$108,$A35,1),1)*60,0)) | I35: =INT(INDEX(設定!$I$9:$I$108,$A35,1)) -> 0 | J35: =IF(INDEX(設定!$I$9:$I$108,$A35,1)=0,"",ROUND(MOD(INDEX(設定!$I$9:$I$108,$A35,1),1)*60,0)) | K35: =INT(INDEX(設定!$J$9:$J$108,$A35,1)) -> 0 | L35: =IF(INDEX(設定!$J$9:$J$108,$A35,1)=0,"",ROUND(MOD(INDEX(設定!$J$9:$J$108,$A35,1),1)*60,0)) | M35: =INT(INDEX(設定!$K$9:$K$108,$A35,1)) -> 0 | N35: =IF(INDEX(設定!$K$9:$K$108,$A35,1)=0,"",ROUND(MOD(INDEX(設定!$K$9:$K$108,$A35,1),1)*60,0)) | S35: =IF(INDEX(設定!$F$9:$F$108,$A35,1)="","",VALUE(LEFT(INDEX(設定!$F$9:$F$108,$A35,1),1))) | T35: =IF(C35="","",C35) | U35: =IF(D35="","",IF(D35="1：男",1,IF(D35="2：女",2))) | V35: =IF(E35="","",E35) | W35: =IF(AND(G35="",H35="",G36=""),"",ROUND(SUM(G35,H35/60)*G36,1)) | X35: =IF(AND(I35="",J35="",I36=""),"",ROUND(SUM(I35,J35/60)*I36,1)) | Y35: =IF(AND(K35="",L35="",K36=""),"",ROUND(SUM(K35,L35/60)*K36,1)) | Z35: =IF(AND(M35="",N35="",M36=""),"",ROUND(SUM(M35,N35/60)*M36,1)) | AE35: 75歳以上 | AF35: =AH35+AJ35 -> 0 | AG35: =AI35+AK35 -> 0 | AH35: =SUMIFS($Z$11:$Z$70,$S$11:$S$70,1,$U$11:$U$70,1,$V$11:$V$70,">=75")+SUMIFS($W$77:$W$106,$S$77:$S$106,1,$U$77:$U$106,1,$V$77:$V$106,">=75") -> 0 | AI35: =SUMIFS($Z$11:$Z$70,$S$11:$S$70,1,$U$11:$U$70,2,$V$11:$V$70,">=75")+SUMIFS($W$77:$W$106,$S$77:$S$106,1,$U$77:$U$106,2,$V$77:$V$106,">=75") -> 0 | AR35: =SUMIFS($Z$11:$Z$70,$S$11:$S$70,5,$U$11:$U$70,1,$V$11:$V$70,">=75") -> 0 | AS35: =SUMIFS($Z$11:$Z$70,$S$11:$S$70,5,$U$11:$U$70,2,$V$11:$V$70,">=75") -> 0
G36: =IF(SUM(G35:H35)>0,1,"") | I36: =IF(SUM(I35:J35)>0,1,"") | K36: =IF(SUM(K35:L35)>0,1,"") | M36: =IF(SUM(M35:N35)>0,1,"") | AD36: 搾乳・牛乳処理・運搬以外 | AF36: =SUM(AF37:AF40) -> 0 | AG36: =SUM(AG37:AG40) -> 0 | AL36: =AN36+AP36+AR36 -> 0 | AM36: =AO36+AQ36+AS36 -> 0 | AN36: =AN16+AN21+AN31 -> 0 | AO36: =AO16+AO21+AO31 -> 0 | AP36: =AP37 -> 0 | AQ36: =AQ37 -> 0 | AR36: =SUM(AR37:AR40) -> 0 | AS36: =SUM(AS37:AS40) -> 0 | AW36: 搾乳・牛乳処理・運搬以外 | AY36: =SUM(AY37:AY40) -> 0 | AZ36: =SUM(AZ37:AZ40) -> 0 | BA36: =ROUND(BC36+BE36,0) -> 0 | BB36: =ROUND(BD36+BF36,0) -> 0 | BC36: =IFERROR($T$112*AN36/($AN$11+$AN$51),0) -> 0 | BD36: =IFERROR($T$113*AO36/($AO$11+$AO$51),0) -> 0 | BE36: =SUM(BE37:BE40) -> 0 | BF36: =SUM(BF37:BF40) -> 0
A37: =ROUND((ROW()-10)/2,0) -> 14 | C37: =IF(INDEX(設定!$C$9:$C$108,$A37,1)="","",INDEX(設定!$C$9:$C$108,$A37,1)) | D37: =IF(INDEX(設定!$D$9:$D$108,$A37,1)="","",INDEX(設定!$D$9:$D$108,$A37,1)) | E37: =IF(INDEX(設定!$E$9:$E$108,$A37,1)="","",INDEX(設定!$E$9:$E$108,$A37,1)) | F37: =IF(S37="","",IF(S37=1,"1：家族",IF(AND(S37>=2,S37<=5),"2：雇用",""))) | G37: =INT(INDEX(設定!$H$9:H$108,$A37,1)) -> 0 | H37: =IF(INDEX(設定!$H$9:$H$108,$A37,1)=0,"",ROUND(MOD(INDEX(設定!$H$9:$H$108,$A37,1),1)*60,0)) | I37: =INT(INDEX(設定!$I$9:$I$108,$A37,1)) -> 0 | J37: =IF(INDEX(設定!$I$9:$I$108,$A37,1)=0,"",ROUND(MOD(INDEX(設定!$I$9:$I$108,$A37,1),1)*60,0)) | K37: =INT(INDEX(設定!$J$9:$J$108,$A37,1)) -> 0 | L37: =IF(INDEX(設定!$J$9:$J$108,$A37,1)=0,"",ROUND(MOD(INDEX(設定!$J$9:$J$108,$A37,1),1)*60,0)) | M37: =INT(INDEX(設定!$K$9:$K$108,$A37,1)) -> 0 | N37: =IF(INDEX(設定!$K$9:$K$108,$A37,1)=0,"",ROUND(MOD(INDEX(設定!$K$9:$K$108,$A37,1),1)*60,0)) | S37: =IF(INDEX(設定!$F$9:$F$108,$A37,1)="","",VALUE(LEFT(INDEX(設定!$F$9:$F$108,$A37,1),1))) | T37: =IF(C37="","",C37) | U37: =IF(D37="","",IF(D37="1：男",1,IF(D37="2：女",2))) | V37: =IF(E37="","",E37) | W37: =IF(AND(G37="",H37="",G38=""),"",ROUND(SUM(G37,H37/60)*G38,1)) | X37: =IF(AND(I37="",J37="",I38=""),"",ROUND(SUM(I37,J37/60)*I38,1)) | Y37: =IF(AND(K37="",L37="",K38=""),"",ROUND(SUM(K37,L37/60)*K38,1)) | Z37: =IF(AND(M37="",N37="",M38=""),"",ROUND(SUM(M37,N37/60)*M38,1)) | AE37: 65歳未満 | AF37: =AF17+AF22+AF32 -> 0 | AG37: =AG17+AG22+AG32 -> 0 | AP37: =AP17+AP22+AP32 -> 0 | AQ37: =AQ17+AQ22+AQ32 -> 0 | AR37: =AR17+AR22+AR32 -> 0 | AS37: =AS17+AS22+AS32 -> 0 | AX37: 65歳未満 | AY37: =ROUND(AF37*$T$4,0) -> 0 | AZ37: =ROUND(AG37*$T$4,0) -> 0 | BE37: =(AP37+AR37)*$T$4 -> 0 | BF37: =(AQ37+AS37)*$T$4 -> 0
G38: =IF(SUM(G37:H37)>0,1,"") | I38: =IF(SUM(I37:J37)>0,1,"") | K38: =IF(SUM(K37:L37)>0,1,"") | M38: =IF(SUM(M37:N37)>0,1,"") | AE38: 65～70 | AF38: =AF18+AF23+AF33 -> 0 | AG38: =AG18+AG23+AG33 -> 0 | AR38: =AR18+AR23+AR33 -> 0 | AS38: =AS18+AS23+AS33 -> 0 | AX38: 65～70 | AY38: =ROUND(AF38*$T$4*0.9,0) -> 0 | AZ38: =ROUND(AG38*$T$4*0.9,0) -> 0 | BE38: =(AR38)*$T$4*0.9 -> 0 | BF38: =(AS38)*$T$4*0.9 -> 0
A39: =ROUND((ROW()-10)/2,0) -> 15 | C39: =IF(INDEX(設定!$C$9:$C$108,$A39,1)="","",INDEX(設定!$C$9:$C$108,$A39,1)) | D39: =IF(INDEX(設定!$D$9:$D$108,$A39,1)="","",INDEX(設定!$D$9:$D$108,$A39,1)) | E39: =IF(INDEX(設定!$E$9:$E$108,$A39,1)="","",INDEX(設定!$E$9:$E$108,$A39,1)) | F39: =IF(S39="","",IF(S39=1,"1：家族",IF(AND(S39>=2,S39<=5),"2：雇用",""))) | G39: =INT(INDEX(設定!$H$9:H$108,$A39,1)) -> 0 | H39: =IF(INDEX(設定!$H$9:$H$108,$A39,1)=0,"",ROUND(MOD(INDEX(設定!$H$9:$H$108,$A39,1),1)*60,0)) | I39: =INT(INDEX(設定!$I$9:$I$108,$A39,1)) -> 0 | J39: =IF(INDEX(設定!$I$9:$I$108,$A39,1)=0,"",ROUND(MOD(INDEX(設定!$I$9:$I$108,$A39,1),1)*60,0)) | K39: =INT(INDEX(設定!$J$9:$J$108,$A39,1)) -> 0 | L39: =IF(INDEX(設定!$J$9:$J$108,$A39,1)=0,"",ROUND(MOD(INDEX(設定!$J$9:$J$108,$A39,1),1)*60,0)) | M39: =INT(INDEX(設定!$K$9:$K$108,$A39,1)) -> 0 | N39: =IF(INDEX(設定!$K$9:$K$108,$A39,1)=0,"",ROUND(MOD(INDEX(設定!$K$9:$K$108,$A39,1),1)*60,0)) | S39: =IF(INDEX(設定!$F$9:$F$108,$A39,1)="","",VALUE(LEFT(INDEX(設定!$F$9:$F$108,$A39,1),1))) | T39: =IF(C39="","",C39) | U39: =IF(D39="","",IF(D39="1：男",1,IF(D39="2：女",2))) | V39: =IF(E39="","",E39) | W39: =IF(AND(G39="",H39="",G40=""),"",ROUND(SUM(G39,H39/60)*G40,1)) | X39: =IF(AND(I39="",J39="",I40=""),"",ROUND(SUM(I39,J39/60)*I40,1)) | Y39: =IF(AND(K39="",L39="",K40=""),"",ROUND(SUM(K39,L39/60)*K40,1)) | Z39: =IF(AND(M39="",N39="",M40=""),"",ROUND(SUM(M39,N39/60)*M40,1)) | AE39: 70～75 | AF39: =AF19+AF24+AF34 -> 0 | AG39: =AG19+AG24+AG34 -> 0 | AR39: =AR19+AR24+AR34 -> 0 | AS39: =AS19+AS24+AS34 -> 0 | AX39: 70～75 | AY39: =ROUND(AF39*$T$4*0.8,0) -> 0 | AZ39: =ROUND(AG39*$T$4*0.8,0) -> 0 | BE39: =(AR39)*$T$4*0.8 -> 0 | BF39: =(AS39)*$T$4*0.8 -> 0
G40: =IF(SUM(G39:H39)>0,1,"") | I40: =IF(SUM(I39:J39)>0,1,"") | K40: =IF(SUM(K39:L39)>0,1,"") | M40: =IF(SUM(M39:N39)>0,1,"") | AE40: 75歳以上 | AF40: =AF20+AF25+AF35 -> 0 | AG40: =AG20+AG25+AG35 -> 0 | AR40: =AR20+AR25+AR35 -> 0 | AS40: =AS20+AS25+AS35 -> 0 | AX40: 75歳以上 | AY40: =ROUND(AF40*$T$4*0.7,0) -> 0 | AZ40: =ROUND(AG40*$T$4*0.7,0) -> 0 | BE40: =(AR40)*$T$4*0.7 -> 0 | BF40: =(AS40)*$T$4*0.7 -> 0
A41: =ROUND((ROW()-10)/2,0) -> 16 | C41: =IF(INDEX(設定!$C$9:$C$108,$A41,1)="","",INDEX(設定!$C$9:$C$108,$A41,1)) | D41: =IF(INDEX(設定!$D$9:$D$108,$A41,1)="","",INDEX(設定!$D$9:$D$108,$A41,1)) | E41: =IF(INDEX(設定!$E$9:$E$108,$A41,1)="","",INDEX(設定!$E$9:$E$108,$A41,1)) | F41: =IF(S41="","",IF(S41=1,"1：家族",IF(AND(S41>=2,S41<=5),"2：雇用",""))) | G41: =INT(INDEX(設定!$H$9:H$108,$A41,1)) -> 0 | H41: =IF(INDEX(設定!$H$9:$H$108,$A41,1)=0,"",ROUND(MOD(INDEX(設定!$H$9:$H$108,$A41,1),1)*60,0)) | I41: =INT(INDEX(設定!$I$9:$I$108,$A41,1)) -> 0 | J41: =IF(INDEX(設定!$I$9:$I$108,$A41,1)=0,"",ROUND(MOD(INDEX(設定!$I$9:$I$108,$A41,1),1)*60,0)) | K41: =INT(INDEX(設定!$J$9:$J$108,$A41,1)) -> 0 | L41: =IF(INDEX(設定!$J$9:$J$108,$A41,1)=0,"",ROUND(MOD(INDEX(設定!$J$9:$J$108,$A41,1),1)*60,0)) | M41: =INT(INDEX(設定!$K$9:$K$108,$A41,1)) -> 0 | N41: =IF(INDEX(設定!$K$9:$K$108,$A41,1)=0,"",ROUND(MOD(INDEX(設定!$K$9:$K$108,$A41,1),1)*60,0)) | S41: =IF(INDEX(設定!$F$9:$F$108,$A41,1)="","",VALUE(LEFT(INDEX(設定!$F$9:$F$108,$A41,1),1))) | T41: =IF(C41="","",C41) | U41: =IF(D41="","",IF(D41="1：男",1,IF(D41="2：女",2))) | V41: =IF(E41="","",E41) | W41: =IF(AND(G41="",H41="",G42=""),"",ROUND(SUM(G41,H41/60)*G42,1)) | X41: =IF(AND(I41="",J41="",I42=""),"",ROUND(SUM(I41,J41/60)*I42,1)) | Y41: =IF(AND(K41="",L41="",K42=""),"",ROUND(SUM(K41,L41/60)*K42,1)) | Z41: =IF(AND(M41="",N41="",M42=""),"",ROUND(SUM(M41,N41/60)*M42,1)) | AC41: 間接労働時間 | AF41: =SUM(AF42:AF45) -> #REF! | AG41: =SUM(AG42:AG45) -> #REF! | AL41: =AL46+AL51 -> #REF! | AM41: =AM46+AM51 -> #REF! | AN41: =AN46+AN51 -> #REF! | AO41: =AO46+AO51 -> #REF! | AP41: =AP42 -> #REF! | AQ41: =AQ42 -> #REF! | AR41: =SUM(AR42:AR45) -> #REF! | AS41: =SUM(AS42:AS45) -> #REF! | AV41: 間接労働費 | AY41: =SUM(AY42:AY45) -> #REF! | AZ41: =SUM(AZ42:AZ45) -> #REF! | BA41: =ROUND(SUM(BA46,BA51),0) -> #REF! | BB41: =ROUND(SUM(BB46,BB51),0) -> #REF!
G42: =IF(SUM(G41:H41)>0,1,"") | I42: =IF(SUM(I41:J41)>0,1,"") | K42: =IF(SUM(K41:L41)>0,1,"") | M42: =IF(SUM(M41:N41)>0,1,"") | AD42: 65歳未満 | AF42: =AF47+AF52 -> #REF! | AG42: =AG47+AG52 -> #REF! | AH42: =AH47+AH52 -> #REF! | AI42: =AI47+AI52 -> #REF! | AJ42: =AJ47+AJ52 -> #REF! | AK42: =AK47+AK52 -> #REF! | AP42: =AP47+AP52 -> #REF! | AQ42: =AQ47+AQ52 -> #REF! | AR42: =AR47+AR52 -> #REF! | AS42: =AS47+AS52 -> #REF! | AW42: 65歳未満 | AY42: =AY47+AY52 -> #REF! | AZ42: =AZ47+AZ52 -> #REF! | BE42: =BE47+BE52 -> #REF! | BF42: =BF47+BF52 -> #REF!
A43: =ROUND((ROW()-10)/2,0) -> 17 | C43: =IF(INDEX(設定!$C$9:$C$108,$A43,1)="","",INDEX(設定!$C$9:$C$108,$A43,1)) | D43: =IF(INDEX(設定!$D$9:$D$108,$A43,1)="","",INDEX(設定!$D$9:$D$108,$A43,1)) | E43: =IF(INDEX(設定!$E$9:$E$108,$A43,1)="","",INDEX(設定!$E$9:$E$108,$A43,1)) | F43: =IF(S43="","",IF(S43=1,"1：家族",IF(AND(S43>=2,S43<=5),"2：雇用",""))) | G43: =INT(INDEX(設定!$H$9:H$108,$A43,1)) -> 0 | H43: =IF(INDEX(設定!$H$9:$H$108,$A43,1)=0,"",ROUND(MOD(INDEX(設定!$H$9:$H$108,$A43,1),1)*60,0)) | I43: =INT(INDEX(設定!$I$9:$I$108,$A43,1)) -> 0 | J43: =IF(INDEX(設定!$I$9:$I$108,$A43,1)=0,"",ROUND(MOD(INDEX(設定!$I$9:$I$108,$A43,1),1)*60,0)) | K43: =INT(INDEX(設定!$J$9:$J$108,$A43,1)) -> 0 | L43: =IF(INDEX(設定!$J$9:$J$108,$A43,1)=0,"",ROUND(MOD(INDEX(設定!$J$9:$J$108,$A43,1),1)*60,0)) | M43: =INT(INDEX(設定!$K$9:$K$108,$A43,1)) -> 0 | N43: =IF(INDEX(設定!$K$9:$K$108,$A43,1)=0,"",ROUND(MOD(INDEX(設定!$K$9:$K$108,$A43,1),1)*60,0)) | S43: =IF(INDEX(設定!$F$9:$F$108,$A43,1)="","",VALUE(LEFT(INDEX(設定!$F$9:$F$108,$A43,1),1))) | T43: =IF(C43="","",C43) | U43: =IF(D43="","",IF(D43="1：男",1,IF(D43="2：女",2))) | V43: =IF(E43="","",E43) | W43: =IF(AND(G43="",H43="",G44=""),"",ROUND(SUM(G43,H43/60)*G44,1)) | X43: =IF(AND(I43="",J43="",I44=""),"",ROUND(SUM(I43,J43/60)*I44,1)) | Y43: =IF(AND(K43="",L43="",K44=""),"",ROUND(SUM(K43,L43/60)*K44,1)) | Z43: =IF(AND(M43="",N43="",M44=""),"",ROUND(SUM(M43,N43/60)*M44,1)) | AD43: 65～70 | AF43: =AF48+AF53 -> #REF! | AG43: =AG48+AG53 -> #REF! | AH43: =AH48+AH53 -> #REF! | AI43: =AI48+AI53 -> #REF! | AR43: =AR48+AR53 -> #REF! | AS43: =AS48+AS53 -> #REF! | AW43: 65～70 | AY43: =AY48+AY53 -> #REF! | AZ43: =AZ48+AZ53 -> #REF! | BE43: =BE48+BE53 -> #REF! | BF43: =BF48+BF53 -> #REF!
G44: =IF(SUM(G43:H43)>0,1,"") | I44: =IF(SUM(I43:J43)>0,1,"") | K44: =IF(SUM(K43:L43)>0,1,"") | M44: =IF(SUM(M43:N43)>0,1,"") | AD44: 70～75 | AF44: =AF49+AF54 -> #REF! | AG44: =AG49+AG54 -> #REF! | AH44: =AH49+AH54 -> #REF! | AI44: =AI49+AI54 -> #REF! | AR44: =AR49+AR54 -> #REF! | AS44: =AS49+AS54 -> 0 | AW44: 70～75 | AY44: =AY49+AY54 -> #REF! | AZ44: =AZ49+AZ54 -> #REF! | BE44: =BE49+BE54 -> #REF! | BF44: =BF49+BF54 -> 0
A45: =ROUND((ROW()-10)/2,0) -> 18 | C45: =IF(INDEX(設定!$C$9:$C$108,$A45,1)="","",INDEX(設定!$C$9:$C$108,$A45,1)) | D45: =IF(INDEX(設定!$D$9:$D$108,$A45,1)="","",INDEX(設定!$D$9:$D$108,$A45,1)) | E45: =IF(INDEX(設定!$E$9:$E$108,$A45,1)="","",INDEX(設定!$E$9:$E$108,$A45,1)) | F45: =IF(S45="","",IF(S45=1,"1：家族",IF(AND(S45>=2,S45<=5),"2：雇用",""))) | G45: =INT(INDEX(設定!$H$9:H$108,$A45,1)) -> 0 | H45: =IF(INDEX(設定!$H$9:$H$108,$A45,1)=0,"",ROUND(MOD(INDEX(設定!$H$9:$H$108,$A45,1),1)*60,0)) | I45: =INT(INDEX(設定!$I$9:$I$108,$A45,1)) -> 0 | J45: =IF(INDEX(設定!$I$9:$I$108,$A45,1)=0,"",ROUND(MOD(INDEX(設定!$I$9:$I$108,$A45,1),1)*60,0)) | K45: =INT(INDEX(設定!$J$9:$J$108,$A45,1)) -> 0 | L45: =IF(INDEX(設定!$J$9:$J$108,$A45,1)=0,"",ROUND(MOD(INDEX(設定!$J$9:$J$108,$A45,1),1)*60,0)) | M45: =INT(INDEX(設定!$K$9:$K$108,$A45,1)) -> 0 | N45: =IF(INDEX(設定!$K$9:$K$108,$A45,1)=0,"",ROUND(MOD(INDEX(設定!$K$9:$K$108,$A45,1),1)*60,0)) | S45: =IF(INDEX(設定!$F$9:$F$108,$A45,1)="","",VALUE(LEFT(INDEX(設定!$F$9:$F$108,$A45,1),1))) | T45: =IF(C45="","",C45) | U45: =IF(D45="","",IF(D45="1：男",1,IF(D45="2：女",2))) | V45: =IF(E45="","",E45) | W45: =IF(AND(G45="",H45="",G46=""),"",ROUND(SUM(G45,H45/60)*G46,1)) | X45: =IF(AND(I45="",J45="",I46=""),"",ROUND(SUM(I45,J45/60)*I46,1)) | Y45: =IF(AND(K45="",L45="",K46=""),"",ROUND(SUM(K45,L45/60)*K46,1)) | Z45: =IF(AND(M45="",N45="",M46=""),"",ROUND(SUM(M45,N45/60)*M46,1)) | AD45: 75歳以上 | AF45: =AF50+AF55 -> #REF! | AG45: =AG50+AG55 -> #REF! | AH45: =AH50+AH55 -> #REF! | AI45: =AI50+AI55 -> #REF! | AR45: =AR50+AR55 -> #REF! | AS45: =AS50+AS55 -> #REF! | AW45: 75歳以上 | AY45: =AY50+AY55 -> #REF! | AZ45: =AZ50+AZ55 -> #REF! | BE45: =BE50+BE55 -> #REF! | BF45: =BF50+BF55 -> #REF!
G46: =IF(SUM(G45:H45)>0,1,"") | I46: =IF(SUM(I45:J45)>0,1,"") | K46: =IF(SUM(K45:L45)>0,1,"") | M46: =IF(SUM(M45:N45)>0,1,"") | AD46: 自給牧草 | AF46: =SUM(AF47:AF50) -> #REF! | AG46: =SUM(AG47:AG50) -> #REF! | AL46: =AN46+AP46+AR46 -> #REF! | AM46: =AO46+AQ46+AS46 -> #REF! | AN46: =SUMIFS($X$77:$X$106,$S$77:$S$106,2,$U$77:$U$106,1)*自給牧草給与割合/100 -> #REF! | AO46: =SUMIFS($X$77:$X$106,$S$77:$S$106,2,$U$77:$U$106,2)*自給牧草給与割合/100 -> #REF! | AP46: =AP47 -> #REF! | AQ46: =AQ47 -> #REF! | AR46: =SUM(AR47:AR50) -> #REF! | AS46: =SUM(AS47:AS50) -> #REF! | AW46: 自給牧草 | AY46: =SUM(AY47:AY50) -> #REF! | AZ46: =SUM(AZ47:AZ50) -> #REF! | BA46: =ROUND(BC46+BE46,0) -> #REF! | BB46: =ROUND(BD46+BF46,0) -> #REF! | BC46: =IF(U112="",0,U112) -> 0 | BD46: =IF(U113="",0,U113) -> 0 | BE46: =SUM(BE47:BE50) -> #REF! | BF46: =SUM(BF47:BF50) -> #REF!
A47: =ROUND((ROW()-10)/2,0) -> 19 | C47: =IF(INDEX(設定!$C$9:$C$108,$A47,1)="","",INDEX(設定!$C$9:$C$108,$A47,1)) | D47: =IF(INDEX(設定!$D$9:$D$108,$A47,1)="","",INDEX(設定!$D$9:$D$108,$A47,1)) | E47: =IF(INDEX(設定!$E$9:$E$108,$A47,1)="","",INDEX(設定!$E$9:$E$108,$A47,1)) | F47: =IF(S47="","",IF(S47=1,"1：家族",IF(AND(S47>=2,S47<=5),"2：雇用",""))) | G47: =INT(INDEX(設定!$H$9:H$108,$A47,1)) -> 0 | H47: =IF(INDEX(設定!$H$9:$H$108,$A47,1)=0,"",ROUND(MOD(INDEX(設定!$H$9:$H$108,$A47,1),1)*60,0)) | I47: =INT(INDEX(設定!$I$9:$I$108,$A47,1)) -> 0 | J47: =IF(INDEX(設定!$I$9:$I$108,$A47,1)=0,"",ROUND(MOD(INDEX(設定!$I$9:$I$108,$A47,1),1)*60,0)) | K47: =INT(INDEX(設定!$J$9:$J$108,$A47,1)) -> 0 | L47: =IF(INDEX(設定!$J$9:$J$108,$A47,1)=0,"",ROUND(MOD(INDEX(設定!$J$9:$J$108,$A47,1),1)*60,0)) | M47: =INT(INDEX(設定!$K$9:$K$108,$A47,1)) -> 0 | N47: =IF(INDEX(設定!$K$9:$K$108,$A47,1)=0,"",ROUND(MOD(INDEX(設定!$K$9:$K$108,$A47,1),1)*60,0)) | S47: =IF(INDEX(設定!$F$9:$F$108,$A47,1)="","",VALUE(LEFT(INDEX(設定!$F$9:$F$108,$A47,1),1))) | T47: =IF(C47="","",C47) | U47: =IF(D47="","",IF(D47="1：男",1,IF(D47="2：女",2))) | V47: =IF(E47="","",E47) | W47: =IF(AND(G47="",H47="",G48=""),"",ROUND(SUM(G47,H47/60)*G48,1)) | X47: =IF(AND(I47="",J47="",I48=""),"",ROUND(SUM(I47,J47/60)*I48,1)) | Y47: =IF(AND(K47="",L47="",K48=""),"",ROUND(SUM(K47,L47/60)*K48,1)) | Z47: =IF(AND(M47="",N47="",M48=""),"",ROUND(SUM(M47,N47/60)*M48,1)) | AE47: 65歳未満 | AF47: =AH47+AJ47 -> #REF! | AG47: =AI47+AK47 -> #REF! | AH47: =SUMIFS($X$77:$X$106,$S$77:$S$106,1,$U$77:$U$106,1,$V$77:$V$106,"<65")*自給牧草給与割合/100 -> #REF! | AI47: =SUMIFS($X$77:$X$106,$S$77:$S$106,1,$U$77:$U$106,2,$V$77:$V$106,"<65")*自給牧草給与割合/100 -> #REF! | AJ47: =SUMIFS($X$77:$X$106,$S$77:$S$106,3,$U$77:$U$106,1)*自給牧草給与割合/100 -> #REF! | AK47: =SUMIFS($X$77:$X$106,$S$77:$S$106,3,$U$77:$U$106,2)*自給牧草給与割合/100 -> #REF! | AP47: =SUMIFS($X$77:$X$106,$S$77:$S$106,4,$U$77:$U$106,1)*自給牧草給与割合/100 -> #REF! | AQ47: =SUMIFS($X$77:$X$106,$S$77:$S$106,4,$U$77:$U$106,2)*自給牧草給与割合/100 -> #REF! | AR47: =SUMIFS($X$77:$X$106,$S$77:$S$106,5,$U$77:$U$106,1,$V$77:$V$106,"<65")*自給牧草給与割合/100 -> #REF! | AS47: =SUMIFS($X$77:$X$106,$S$77:$S$106,5,$U$77:$U$106,2,$V$77:$V$106,"<65")*自給牧草給与割合/100 -> #REF! | AX47: 65歳未満 | AY47: =ROUND(AF47*$T$4,0) -> #REF! | AZ47: =ROUND(AG47*$T$4,0) -> #REF! | BE47: =(AP47+AR47)*$T$4 -> #REF! | BF47: =(AQ47+AS47)*$T$4 -> #REF!
G48: =IF(SUM(G47:H47)>0,1,"") | I48: =IF(SUM(I47:J47)>0,1,"") | K48: =IF(SUM(K47:L47)>0,1,"") | M48: =IF(SUM(M47:N47)>0,1,"") | AE48: 65～70 | AF48: =AH48+AJ48 -> #REF! | AG48: =AI48+AK48 -> #REF! | AH48: =SUMIFS($X$77:$X$106,$S$77:$S$106,1,$U$77:$U$106,1,$V$77:$V$106,">=65",$V$77:$V$106,"<70")*自給牧草給与割合/100 -> #REF! | AI48: =SUMIFS($X$77:$X$106,$S$77:$S$106,1,$U$77:$U$106,2,$V$77:$V$106,">=65",$V$77:$V$106,"<70")*自給牧草給与割合/100 -> #REF! | AR48: =SUMIFS($X$77:$X$106,$S$77:$S$106,5,$U$77:$U$106,1,$V$77:$V$106,">=65",$V$77:$V$106,"<70")*自給牧草給与割合/100 -> #REF! | AS48: =SUMIFS($X$77:$X$106,$S$77:$S$106,5,$U$77:$U$106,2,$V$77:$V$106,">=65",$V$77:$V$106,"<70")*自給牧草給与割合/100 -> #REF! | AX48: 65～70 | AY48: =ROUND(AF48*$T$4*0.9,0) -> #REF! | AZ48: =ROUND(AG48*$T$4*0.9,0) -> #REF! | BE48: =(AR48)*$T$4*0.9 -> #REF! | BF48: =(AS48)*$T$4*0.9 -> #REF!
A49: =ROUND((ROW()-10)/2,0) -> 20 | C49: =IF(INDEX(設定!$C$9:$C$108,$A49,1)="","",INDEX(設定!$C$9:$C$108,$A49,1)) | D49: =IF(INDEX(設定!$D$9:$D$108,$A49,1)="","",INDEX(設定!$D$9:$D$108,$A49,1)) | E49: =IF(INDEX(設定!$E$9:$E$108,$A49,1)="","",INDEX(設定!$E$9:$E$108,$A49,1)) | F49: =IF(S49="","",IF(S49=1,"1：家族",IF(AND(S49>=2,S49<=5),"2：雇用",""))) | G49: =INT(INDEX(設定!$H$9:H$108,$A49,1)) -> 0 | H49: =IF(INDEX(設定!$H$9:$H$108,$A49,1)=0,"",ROUND(MOD(INDEX(設定!$H$9:$H$108,$A49,1),1)*60,0)) | I49: =INT(INDEX(設定!$I$9:$I$108,$A49,1)) -> 0 | J49: =IF(INDEX(設定!$I$9:$I$108,$A49,1)=0,"",ROUND(MOD(INDEX(設定!$I$9:$I$108,$A49,1),1)*60,0)) | K49: =INT(INDEX(設定!$J$9:$J$108,$A49,1)) -> 0 | L49: =IF(INDEX(設定!$J$9:$J$108,$A49,1)=0,"",ROUND(MOD(INDEX(設定!$J$9:$J$108,$A49,1),1)*60,0)) | M49: =INT(INDEX(設定!$K$9:$K$108,$A49,1)) -> 0 | N49: =IF(INDEX(設定!$K$9:$K$108,$A49,1)=0,"",ROUND(MOD(INDEX(設定!$K$9:$K$108,$A49,1),1)*60,0)) | S49: =IF(INDEX(設定!$F$9:$F$108,$A49,1)="","",VALUE(LEFT(INDEX(設定!$F$9:$F$108,$A49,1),1))) | T49: =IF(C49="","",C49) | U49: =IF(D49="","",IF(D49="1：男",1,IF(D49="2：女",2))) | V49: =IF(E49="","",E49) | W49: =IF(AND(G49="",H49="",G50=""),"",ROUND(SUM(G49,H49/60)*G50,1)) | X49: =IF(AND(I49="",J49="",I50=""),"",ROUND(SUM(I49,J49/60)*I50,1)) | Y49: =IF(AND(K49="",L49="",K50=""),"",ROUND(SUM(K49,L49/60)*K50,1)) | Z49: =IF(AND(M49="",N49="",M50=""),"",ROUND(SUM(M49,N49/60)*M50,1)) | AE49: 70～75 | AF49: =AH49+AJ49 -> #REF! | AG49: =AI49+AK49 -> #REF! | AH49: =SUMIFS($X$77:$X$106,$S$77:$S$106,1,$U$77:$U$106,1,$V$77:$V$106,">=70",$V$77:$V$106,"<75")*自給牧草給与割合/100 -> #REF! | AI49: =SUMIFS($X$77:$X$106,$S$77:$S$106,1,$U$77:$U$106,2,$V$77:$V$106,">=70",$V$77:$V$106,"<75")*自給牧草給与割合/100 -> #REF! | AR49: =SUMIFS($X$77:$X$106,$S$77:$S$106,5,$U$77:$U$106,1,$V$77:$V$106,">=70",$V$77:$V$106,"<75")*自給牧草給与割合/100 -> #REF! | AS49: =SUMIFS($X$77:$X$106,$S$77:$S$106,5,$U$77:$U$106,2,$V$77:$V$106,">=70",$V$77:$V$106,"<75") -> 0 | AX49: 70～75 | AY49: =ROUND(AF49*$T$4*0.8,0) -> #REF! | AZ49: =ROUND(AG49*$T$4*0.8,0) -> #REF! | BE49: =(AR49)*$T$4*0.8 -> #REF! | BF49: =(AS49)*$T$4*0.8 -> 0
G50: =IF(SUM(G49:H49)>0,1,"") | I50: =IF(SUM(I49:J49)>0,1,"") | K50: =IF(SUM(K49:L49)>0,1,"") | M50: =IF(SUM(M49:N49)>0,1,"") | AE50: 75歳以上 | AF50: =AH50+AJ50 -> #REF! | AG50: =AI50+AK50 -> #REF! | AH50: =SUMIFS($X$77:$X$106,$S$77:$S$106,1,$U$77:$U$106,1,$V$77:$V$106,">=75")*自給牧草給与割合/100 -> #REF! | AI50: =SUMIFS($X$77:$X$106,$S$77:$S$106,1,$U$77:$U$106,2,$V$77:$V$106,">=75")*自給牧草給与割合/100 -> #REF! | AR50: =SUMIFS($X$77:$X$106,$S$77:$S$106,5,$U$77:$U$106,1,$V$77:$V$106,">=75")*自給牧草給与割合/100 -> #REF! | AS50: =SUMIFS($X$77:$X$106,$S$77:$S$106,5,$U$77:$U$106,2,$V$77:$V$106,">=75")*自給牧草給与割合/100 -> #REF! | AX50: 75歳以上 | AY50: =ROUND(AF50*$T$4*0.7,0) -> #REF! | AZ50: =ROUND(AG50*$T$4*0.7,0) -> #REF! | BE50: =(AR50)*$T$4*0.7 -> #REF! | BF50: =(AS50)*$T$4*0.7 -> #REF!
A51: =ROUND((ROW()-10)/2,0) -> 21 | C51: =IF(INDEX(設定!$C$9:$C$108,$A51,1)="","",INDEX(設定!$C$9:$C$108,$A51,1)) | D51: =IF(INDEX(設定!$D$9:$D$108,$A51,1)="","",INDEX(設定!$D$9:$D$108,$A51,1)) | E51: =IF(INDEX(設定!$E$9:$E$108,$A51,1)="","",INDEX(設定!$E$9:$E$108,$A51,1)) | F51: =IF(S51="","",IF(S51=1,"1：家族",IF(AND(S51>=2,S51<=5),"2：雇用",""))) | G51: =INT(INDEX(設定!$H$9:H$108,$A51,1)) -> 0 | H51: =IF(INDEX(設定!$H$9:$H$108,$A51,1)=0,"",ROUND(MOD(INDEX(設定!$H$9:$H$108,$A51,1),1)*60,0)) | I51: =INT(INDEX(設定!$I$9:$I$108,$A51,1)) -> 0 | J51: =IF(INDEX(設定!$I$9:$I$108,$A51,1)=0,"",ROUND(MOD(INDEX(設定!$I$9:$I$108,$A51,1),1)*60,0)) | K51: =INT(INDEX(設定!$J$9:$J$108,$A51,1)) -> 0 | L51: =IF(INDEX(設定!$J$9:$J$108,$A51,1)=0,"",ROUND(MOD(INDEX(設定!$J$9:$J$108,$A51,1),1)*60,0)) | M51: =INT(INDEX(設定!$K$9:$K$108,$A51,1)) -> 0 | N51: =IF(INDEX(設定!$K$9:$K$108,$A51,1)=0,"",ROUND(MOD(INDEX(設定!$K$9:$K$108,$A51,1),1)*60,0)) | S51: =IF(INDEX(設定!$F$9:$F$108,$A51,1)="","",VALUE(LEFT(INDEX(設定!$F$9:$F$108,$A51,1),1))) | T51: =IF(C51="","",C51) | U51: =IF(D51="","",IF(D51="1：男",1,IF(D51="2：女",2))) | V51: =IF(E51="","",E51) | W51: =IF(AND(G51="",H51="",G52=""),"",ROUND(SUM(G51,H51/60)*G52,1)) | X51: =IF(AND(I51="",J51="",I52=""),"",ROUND(SUM(I51,J51/60)*I52,1)) | Y51: =IF(AND(K51="",L51="",K52=""),"",ROUND(SUM(K51,L51/60)*K52,1)) | Z51: =IF(AND(M51="",N51="",M52=""),"",ROUND(SUM(M51,N51/60)*M52,1)) | AD51: 自給牧草以外 | AF51: =SUM(AF52:AF55) -> 0 | AG51: =SUM(AG52:AG55) -> 0 | AL51: =AN51+AP51+AR51 -> 0 | AM51: =AO51+AQ51+AS51 -> 0 | AN51: =SUMIFS($Y$77:$Y$106,$S$77:$S$106,2,$U$77:$U$106,1) -> 0 | AO51: =SUMIFS($Y$77:$Y$106,$S$77:$S$106,2,$U$77:$U$106,2) -> 0 | AR51: =SUM(AR52:AR55) -> 0 | AS51: =SUM(AS52:AS55) -> 0 | AW51: 自給牧草以外 | AY51: =SUM(AY52:AY55) -> 0 | AZ51: =SUM(AZ52:AZ55) -> 0 | BA51: =ROUND(BC51+BE51,0) -> 0 | BB51: =ROUND(BD51+BF51,0) -> 0 | BC51: =IFERROR($T$112*AN51/($AN$11+$AN$51),0) -> 0 | BD51: =IFERROR($T$113*AO51/($AO$11+$AO$51),0) -> 0 | BE51: =SUM(BE52:BE55) -> 0 | BF51: =SUM(BF52:BF55) -> 0
G52: =IF(SUM(G51:H51)>0,1,"") | I52: =IF(SUM(I51:J51)>0,1,"") | K52: =IF(SUM(K51:L51)>0,1,"") | M52: =IF(SUM(M51:N51)>0,1,"") | AE52: 65歳未満 | AF52: =AH52+AJ52 -> 0 | AG52: =AI52+AK52 -> 0 | AH52: =SUMIFS($Y$77:$Y$106,$S$77:$S$106,1,$U$77:$U$106,1,$V$77:$V$106,"<65") -> 0 | AI52: =SUMIFS($Y$77:$Y$106,$S$77:$S$106,1,$U$77:$U$106,2,$V$77:$V$106,"<65") -> 0 | AR52: =SUMIFS($Y$77:$Y$106,$S$77:$S$106,5,$U$77:$U$106,1,$V$77:$V$106,"<65") -> 0 | AS52: =SUMIFS($Y$77:$Y$106,$S$77:$S$106,5,$U$77:$U$106,2,$V$77:$V$106,"<65") -> 0 | AX52: 65歳未満 | AY52: =ROUND(AF52*$T$4,0) -> 0 | AZ52: =ROUND(AG52*$T$4,0) -> 0 | BE52: =(AR52)*$T$4 -> 0 | BF52: =(AS52)*$T$4 -> 0
A53: =ROUND((ROW()-10)/2,0) -> 22 | C53: =IF(INDEX(設定!$C$9:$C$108,$A53,1)="","",INDEX(設定!$C$9:$C$108,$A53,1)) | D53: =IF(INDEX(設定!$D$9:$D$108,$A53,1)="","",INDEX(設定!$D$9:$D$108,$A53,1)) | E53: =IF(INDEX(設定!$E$9:$E$108,$A53,1)="","",INDEX(設定!$E$9:$E$108,$A53,1)) | F53: =IF(S53="","",IF(S53=1,"1：家族",IF(AND(S53>=2,S53<=5),"2：雇用",""))) | G53: =INT(INDEX(設定!$H$9:H$108,$A53,1)) -> 0 | H53: =IF(INDEX(設定!$H$9:$H$108,$A53,1)=0,"",ROUND(MOD(INDEX(設定!$H$9:$H$108,$A53,1),1)*60,0)) | I53: =INT(INDEX(設定!$I$9:$I$108,$A53,1)) -> 0 | J53: =IF(INDEX(設定!$I$9:$I$108,$A53,1)=0,"",ROUND(MOD(INDEX(設定!$I$9:$I$108,$A53,1),1)*60,0)) | K53: =INT(INDEX(設定!$J$9:$J$108,$A53,1)) -> 0 | L53: =IF(INDEX(設定!$J$9:$J$108,$A53,1)=0,"",ROUND(MOD(INDEX(設定!$J$9:$J$108,$A53,1),1)*60,0)) | M53: =INT(INDEX(設定!$K$9:$K$108,$A53,1)) -> 0 | N53: =IF(INDEX(設定!$K$9:$K$108,$A53,1)=0,"",ROUND(MOD(INDEX(設定!$K$9:$K$108,$A53,1),1)*60,0)) | S53: =IF(INDEX(設定!$F$9:$F$108,$A53,1)="","",VALUE(LEFT(INDEX(設定!$F$9:$F$108,$A53,1),1))) | T53: =IF(C53="","",C53) | U53: =IF(D53="","",IF(D53="1：男",1,IF(D53="2：女",2))) | V53: =IF(E53="","",E53) | W53: =IF(AND(G53="",H53="",G54=""),"",ROUND(SUM(G53,H53/60)*G54,1)) | X53: =IF(AND(I53="",J53="",I54=""),"",ROUND(SUM(I53,J53/60)*I54,1)) | Y53: =IF(AND(K53="",L53="",K54=""),"",ROUND(SUM(K53,L53/60)*K54,1)) | Z53: =IF(AND(M53="",N53="",M54=""),"",ROUND(SUM(M53,N53/60)*M54,1)) | AE53: 65～70 | AF53: =AH53+AJ53 -> 0 | AG53: =AI53+AK53 -> 0 | AH53: =SUMIFS($Y$77:$Y$106,$S$77:$S$106,1,$U$77:$U$106,1,$V$77:$V$106,">=65",$V$77:$V$106,"<70") -> 0 | AI53: =SUMIFS($Y$77:$Y$106,$S$77:$S$106,1,$U$77:$U$106,2,$V$77:$V$106,">=65",$V$77:$V$106,"<70") -> 0 | AR53: =SUMIFS($Y$77:$Y$106,$S$77:$S$106,5,$U$77:$U$106,1,$V$77:$V$106,">=65",$V$77:$V$106,"<70") -> 0 | AS53: =SUMIFS($Y$77:$Y$106,$S$77:$S$106,5,$U$77:$U$106,2,$V$77:$V$106,">=65",$V$77:$V$106,"<70") -> 0 | AX53: 65～70 | AY53: =ROUND(AF53*$T$4*0.9,0) -> 0 | AZ53: =ROUND(AG53*$T$4*0.9,0) -> 0 | BE53: =(AR53)*$T$4*0.9 -> 0 | BF53: =(AS53)*$T$4*0.9 -> 0
G54: =IF(SUM(G53:H53)>0,1,"") | I54: =IF(SUM(I53:J53)>0,1,"") | K54: =IF(SUM(K53:L53)>0,1,"") | M54: =IF(SUM(M53:N53)>0,1,"") | AE54: 70～75 | AF54: =AH54+AJ54 -> 0 | AG54: =AI54+AK54 -> 0 | AH54: =SUMIFS($Y$77:$Y$106,$S$77:$S$106,1,$U$77:$U$106,1,$V$77:$V$106,">=70",$V$77:$V$106,"<75") -> 0 | AI54: =SUMIFS($Y$77:$Y$106,$S$77:$S$106,1,$U$77:$U$106,2,$V$77:$V$106,">=70",$V$77:$V$106,"<75") -> 0 | AR54: =SUMIFS($Y$77:$Y$106,$S$77:$S$106,5,$U$77:$U$106,1,$V$77:$V$106,">=70",$V$77:$V$106,"<75") -> 0 | AS54: =SUMIFS($Y$77:$Y$106,$S$77:$S$106,5,$U$77:$U$106,2,$V$77:$V$106,">=70",$V$77:$V$106,"<75") -> 0 | AX54: 70～75 | AY54: =ROUND(AF54*$T$4*0.8,0) -> 0 | AZ54: =ROUND(AG54*$T$4*0.8,0) -> 0 | BE54: =(AR54)*$T$4*0.8 -> 0 | BF54: =(AS54)*$T$4*0.8 -> 0
A55: =ROUND((ROW()-10)/2,0) -> 23 | C55: =IF(INDEX(設定!$C$9:$C$108,$A55,1)="","",INDEX(設定!$C$9:$C$108,$A55,1)) | D55: =IF(INDEX(設定!$D$9:$D$108,$A55,1)="","",INDEX(設定!$D$9:$D$108,$A55,1)) | E55: =IF(INDEX(設定!$E$9:$E$108,$A55,1)="","",INDEX(設定!$E$9:$E$108,$A55,1)) | F55: =IF(S55="","",IF(S55=1,"1：家族",IF(AND(S55>=2,S55<=5),"2：雇用",""))) | G55: =INT(INDEX(設定!$H$9:H$108,$A55,1)) -> 0 | H55: =IF(INDEX(設定!$H$9:$H$108,$A55,1)=0,"",ROUND(MOD(INDEX(設定!$H$9:$H$108,$A55,1),1)*60,0)) | I55: =INT(INDEX(設定!$I$9:$I$108,$A55,1)) -> 0 | J55: =IF(INDEX(設定!$I$9:$I$108,$A55,1)=0,"",ROUND(MOD(INDEX(設定!$I$9:$I$108,$A55,1),1)*60,0)) | K55: =INT(INDEX(設定!$J$9:$J$108,$A55,1)) -> 0 | L55: =IF(INDEX(設定!$J$9:$J$108,$A55,1)=0,"",ROUND(MOD(INDEX(設定!$J$9:$J$108,$A55,1),1)*60,0)) | M55: =INT(INDEX(設定!$K$9:$K$108,$A55,1)) -> 0 | N55: =IF(INDEX(設定!$K$9:$K$108,$A55,1)=0,"",ROUND(MOD(INDEX(設定!$K$9:$K$108,$A55,1),1)*60,0)) | S55: =IF(INDEX(設定!$F$9:$F$108,$A55,1)="","",VALUE(LEFT(INDEX(設定!$F$9:$F$108,$A55,1),1))) | T55: =IF(C55="","",C55) | U55: =IF(D55="","",IF(D55="1：男",1,IF(D55="2：女",2))) | V55: =IF(E55="","",E55) | W55: =IF(AND(G55="",H55="",G56=""),"",ROUND(SUM(G55,H55/60)*G56,1)) | X55: =IF(AND(I55="",J55="",I56=""),"",ROUND(SUM(I55,J55/60)*I56,1)) | Y55: =IF(AND(K55="",L55="",K56=""),"",ROUND(SUM(K55,L55/60)*K56,1)) | Z55: =IF(AND(M55="",N55="",M56=""),"",ROUND(SUM(M55,N55/60)*M56,1)) | AE55: 75歳以上 | AF55: =AH55+AJ55 -> 0 | AG55: =AI55+AK55 -> 0 | AH55: =SUMIFS($Y$77:$Y$106,$S$77:$S$106,1,$U$77:$U$106,1,$V$77:$V$106,">=75") -> 0 | AI55: =SUMIFS($Y$77:$Y$106,$S$77:$S$106,1,$U$77:$U$106,2,$V$77:$V$106,">=75") -> 0 | AR55: =SUMIFS($Y$77:$Y$106,$S$77:$S$106,5,$U$77:$U$106,1,$V$77:$V$106,">=75") -> 0 | AS55: =SUMIFS($Y$77:$Y$106,$S$77:$S$106,5,$U$77:$U$106,2,$V$77:$V$106,">=75") -> 0 | AX55: 75歳以上 | AY55: =ROUND(AF55*$T$4*0.7,0) -> 0 | AZ55: =ROUND(AG55*$T$4*0.7,0) -> 0 | BE55: =(AR55)*$T$4*0.7 -> 0 | BF55: =(AS55)*$T$4*0.7 -> 0
G56: =IF(SUM(G55:H55)>0,1,"") | I56: =IF(SUM(I55:J55)>0,1,"") | K56: =IF(SUM(K55:L55)>0,1,"") | M56: =IF(SUM(M55:N55)>0,1,"") | AC56: 労働時間合計 | AF56: =SUM(AF57:AF60) -> #REF! | AG56: =SUM(AG57:AG60) -> #REF! | AL56: =AL11+AL41 -> #REF! | AM56: =AM11+AM41 -> #REF! | AN56: =AN11+AN41 -> #REF! | AO56: =AO11+AO41 -> #REF! | AP56: =AP11+AP41 -> #REF! | AQ56: =AQ11+AQ41 -> #REF! | AR56: =AR11+AR41 -> #REF! | AS56: =AS11+AS41 -> #REF!
A57: =ROUND((ROW()-10)/2,0) -> 24 | C57: =IF(INDEX(設定!$C$9:$C$108,$A57,1)="","",INDEX(設定!$C$9:$C$108,$A57,1)) | D57: =IF(INDEX(設定!$D$9:$D$108,$A57,1)="","",INDEX(設定!$D$9:$D$108,$A57,1)) | E57: =IF(INDEX(設定!$E$9:$E$108,$A57,1)="","",INDEX(設定!$E$9:$E$108,$A57,1)) | F57: =IF(S57="","",IF(S57=1,"1：家族",IF(AND(S57>=2,S57<=5),"2：雇用",""))) | G57: =INT(INDEX(設定!$H$9:H$108,$A57,1)) -> 0 | H57: =IF(INDEX(設定!$H$9:$H$108,$A57,1)=0,"",ROUND(MOD(INDEX(設定!$H$9:$H$108,$A57,1),1)*60,0)) | I57: =INT(INDEX(設定!$I$9:$I$108,$A57,1)) -> 0 | J57: =IF(INDEX(設定!$I$9:$I$108,$A57,1)=0,"",ROUND(MOD(INDEX(設定!$I$9:$I$108,$A57,1),1)*60,0)) | K57: =INT(INDEX(設定!$J$9:$J$108,$A57,1)) -> 0 | L57: =IF(INDEX(設定!$J$9:$J$108,$A57,1)=0,"",ROUND(MOD(INDEX(設定!$J$9:$J$108,$A57,1),1)*60,0)) | M57: =INT(INDEX(設定!$K$9:$K$108,$A57,1)) -> 0 | N57: =IF(INDEX(設定!$K$9:$K$108,$A57,1)=0,"",ROUND(MOD(INDEX(設定!$K$9:$K$108,$A57,1),1)*60,0)) | S57: =IF(INDEX(設定!$F$9:$F$108,$A57,1)="","",VALUE(LEFT(INDEX(設定!$F$9:$F$108,$A57,1),1))) | T57: =IF(C57="","",C57) | U57: =IF(D57="","",IF(D57="1：男",1,IF(D57="2：女",2))) | V57: =IF(E57="","",E57) | W57: =IF(AND(G57="",H57="",G58=""),"",ROUND(SUM(G57,H57/60)*G58,1)) | X57: =IF(AND(I57="",J57="",I58=""),"",ROUND(SUM(I57,J57/60)*I58,1)) | Y57: =IF(AND(K57="",L57="",K58=""),"",ROUND(SUM(K57,L57/60)*K58,1)) | Z57: =IF(AND(M57="",N57="",M58=""),"",ROUND(SUM(M57,N57/60)*M58,1)) | AD57: 65歳未満 | AF57: =AF12+AF42 -> #REF! | AG57: =AG12+AG42 -> #REF! | AH57: =AH12+AH42 -> #REF! | AI57: =AI12+AI42 -> #REF! | AJ57: =AJ12+AJ42 -> #REF! | AK57: =AK12+AK42 -> #REF! | AP57: =AP12+AP42 -> #REF! | AQ57: =AQ12+AQ42 -> #REF! | AR57: =AR12+AR42 -> #REF! | AS57: =AS12+AS42 -> #REF!
G58: =IF(SUM(G57:H57)>0,1,"") | I58: =IF(SUM(I57:J57)>0,1,"") | K58: =IF(SUM(K57:L57)>0,1,"") | M58: =IF(SUM(M57:N57)>0,1,"") | AD58: 65～70 | AF58: =AF13+AF43 -> #REF! | AG58: =AG13+AG43 -> #REF! | AH58: =AH13+AH43 -> #REF! | AI58: =AI13+AI43 -> #REF! | AR58: =AR13+AR43 -> #REF! | AS58: =AS13+AS43 -> #REF!
A59: =ROUND((ROW()-10)/2,0) -> 25 | C59: =IF(INDEX(設定!$C$9:$C$108,$A59,1)="","",INDEX(設定!$C$9:$C$108,$A59,1)) | D59: =IF(INDEX(設定!$D$9:$D$108,$A59,1)="","",INDEX(設定!$D$9:$D$108,$A59,1)) | E59: =IF(INDEX(設定!$E$9:$E$108,$A59,1)="","",INDEX(設定!$E$9:$E$108,$A59,1)) | F59: =IF(S59="","",IF(S59=1,"1：家族",IF(AND(S59>=2,S59<=5),"2：雇用",""))) | G59: =INT(INDEX(設定!$H$9:H$108,$A59,1)) -> 0 | H59: =IF(INDEX(設定!$H$9:$H$108,$A59,1)=0,"",ROUND(MOD(INDEX(設定!$H$9:$H$108,$A59,1),1)*60,0)) | I59: =INT(INDEX(設定!$I$9:$I$108,$A59,1)) -> 0 | J59: =IF(INDEX(設定!$I$9:$I$108,$A59,1)=0,"",ROUND(MOD(INDEX(設定!$I$9:$I$108,$A59,1),1)*60,0)) | K59: =INT(INDEX(設定!$J$9:$J$108,$A59,1)) -> 0 | L59: =IF(INDEX(設定!$J$9:$J$108,$A59,1)=0,"",ROUND(MOD(INDEX(設定!$J$9:$J$108,$A59,1),1)*60,0)) | M59: =INT(INDEX(設定!$K$9:$K$108,$A59,1)) -> 0 | N59: =IF(INDEX(設定!$K$9:$K$108,$A59,1)=0,"",ROUND(MOD(INDEX(設定!$K$9:$K$108,$A59,1),1)*60,0)) | S59: =IF(INDEX(設定!$F$9:$F$108,$A59,1)="","",VALUE(LEFT(INDEX(設定!$F$9:$F$108,$A59,1),1))) | T59: =IF(C59="","",C59) | U59: =IF(D59="","",IF(D59="1：男",1,IF(D59="2：女",2))) | V59: =IF(E59="","",E59) | W59: =IF(AND(G59="",H59="",G60=""),"",ROUND(SUM(G59,H59/60)*G60,1)) | X59: =IF(AND(I59="",J59="",I60=""),"",ROUND(SUM(I59,J59/60)*I60,1)) | Y59: =IF(AND(K59="",L59="",K60=""),"",ROUND(SUM(K59,L59/60)*K60,1)) | Z59: =IF(AND(M59="",N59="",M60=""),"",ROUND(SUM(M59,N59/60)*M60,1)) | AD59: 70～75 | AF59: =AF14+AF44 -> #REF! | AG59: =AG14+AG44 -> #REF! | AH59: =AH14+AH44 -> #REF! | AI59: =AI14+AI44 -> #REF! | AR59: =AR14+AR44 -> #REF! | AS59: =AS14+AS44 -> 0
G60: =IF(SUM(G59:H59)>0,1,"") | I60: =IF(SUM(I59:J59)>0,1,"") | K60: =IF(SUM(K59:L59)>0,1,"") | M60: =IF(SUM(M59:N59)>0,1,"") | AD60: 75歳以上 | AF60: =AF15+AF45 -> #REF! | AG60: =AG15+AG45 -> #REF! | AH60: =AH15+AH45 -> #REF! | AI60: =AI15+AI45 -> #REF! | AR60: =AR15+AR45 -> #REF! | AS60: =AS15+AS45 -> #REF!
A61: =ROUND((ROW()-10)/2,0) -> 26 | C61: =IF(INDEX(設定!$C$9:$C$108,$A61,1)="","",INDEX(設定!$C$9:$C$108,$A61,1)) | D61: =IF(INDEX(設定!$D$9:$D$108,$A61,1)="","",INDEX(設定!$D$9:$D$108,$A61,1)) | E61: =IF(INDEX(設定!$E$9:$E$108,$A61,1)="","",INDEX(設定!$E$9:$E$108,$A61,1)) | F61: =IF(S61="","",IF(S61=1,"1：家族",IF(AND(S61>=2,S61<=5),"2：雇用",""))) | G61: =INT(INDEX(設定!$H$9:H$108,$A61,1)) -> 0 | H61: =IF(INDEX(設定!$H$9:$H$108,$A61,1)=0,"",ROUND(MOD(INDEX(設定!$H$9:$H$108,$A61,1),1)*60,0)) | I61: =INT(INDEX(設定!$I$9:$I$108,$A61,1)) -> 0 | J61: =IF(INDEX(設定!$I$9:$I$108,$A61,1)=0,"",ROUND(MOD(INDEX(設定!$I$9:$I$108,$A61,1),1)*60,0)) | K61: =INT(INDEX(設定!$J$9:$J$108,$A61,1)) -> 0 | L61: =IF(INDEX(設定!$J$9:$J$108,$A61,1)=0,"",ROUND(MOD(INDEX(設定!$J$9:$J$108,$A61,1),1)*60,0)) | M61: =INT(INDEX(設定!$K$9:$K$108,$A61,1)) -> 0 | N61: =IF(INDEX(設定!$K$9:$K$108,$A61,1)=0,"",ROUND(MOD(INDEX(設定!$K$9:$K$108,$A61,1),1)*60,0)) | S61: =IF(INDEX(設定!$F$9:$F$108,$A61,1)="","",VALUE(LEFT(INDEX(設定!$F$9:$F$108,$A61,1),1))) | T61: =IF(C61="","",C61) | U61: =IF(D61="","",IF(D61="1：男",1,IF(D61="2：女",2))) | V61: =IF(E61="","",E61) | W61: =IF(AND(G61="",H61="",G62=""),"",ROUND(SUM(G61,H61/60)*G62,1)) | X61: =IF(AND(I61="",J61="",I62=""),"",ROUND(SUM(I61,J61/60)*I62,1)) | Y61: =IF(AND(K61="",L61="",K62=""),"",ROUND(SUM(K61,L61/60)*K62,1)) | Z61: =IF(AND(M61="",N61="",M62=""),"",ROUND(SUM(M61,N61/60)*M62,1)) | AC61: 経営管理労働時間 | AF61: =SUMIFS($Z$77:$Z$106,$S$77:$S$106,1,$U$77:$U$106,1) -> 0 | AG61: =SUMIFS($Z$77:$Z$106,$S$77:$S$106,1,$U$77:$U$106,2) -> 0
G62: =IF(SUM(G61:H61)>0,1,"") | I62: =IF(SUM(I61:J61)>0,1,"") | K62: =IF(SUM(K61:L61)>0,1,"") | M62: =IF(SUM(M61:N61)>0,1,"")
A63: =ROUND((ROW()-10)/2,0) -> 27 | C63: =IF(INDEX(設定!$C$9:$C$108,$A63,1)="","",INDEX(設定!$C$9:$C$108,$A63,1)) | D63: =IF(INDEX(設定!$D$9:$D$108,$A63,1)="","",INDEX(設定!$D$9:$D$108,$A63,1)) | E63: =IF(INDEX(設定!$E$9:$E$108,$A63,1)="","",INDEX(設定!$E$9:$E$108,$A63,1)) | F63: =IF(S63="","",IF(S63=1,"1：家族",IF(AND(S63>=2,S63<=5),"2：雇用",""))) | G63: =INT(INDEX(設定!$H$9:H$108,$A63,1)) -> 0 | H63: =IF(INDEX(設定!$H$9:$H$108,$A63,1)=0,"",ROUND(MOD(INDEX(設定!$H$9:$H$108,$A63,1),1)*60,0)) | I63: =INT(INDEX(設定!$I$9:$I$108,$A63,1)) -> 0 | J63: =IF(INDEX(設定!$I$9:$I$108,$A63,1)=0,"",ROUND(MOD(INDEX(設定!$I$9:$I$108,$A63,1),1)*60,0)) | K63: =INT(INDEX(設定!$J$9:$J$108,$A63,1)) -> 0 | L63: =IF(INDEX(設定!$J$9:$J$108,$A63,1)=0,"",ROUND(MOD(INDEX(設定!$J$9:$J$108,$A63,1),1)*60,0)) | M63: =INT(INDEX(設定!$K$9:$K$108,$A63,1)) -> 0 | N63: =IF(INDEX(設定!$K$9:$K$108,$A63,1)=0,"",ROUND(MOD(INDEX(設定!$K$9:$K$108,$A63,1),1)*60,0)) | S63: =IF(INDEX(設定!$F$9:$F$108,$A63,1)="","",VALUE(LEFT(INDEX(設定!$F$9:$F$108,$A63,1),1))) | T63: =IF(C63="","",C63) | U63: =IF(D63="","",IF(D63="1：男",1,IF(D63="2：女",2))) | V63: =IF(E63="","",E63) | W63: =IF(AND(G63="",H63="",G64=""),"",ROUND(SUM(G63,H63/60)*G64,1)) | X63: =IF(AND(I63="",J63="",I64=""),"",ROUND(SUM(I63,J63/60)*I64,1)) | Y63: =IF(AND(K63="",L63="",K64=""),"",ROUND(SUM(K63,L63/60)*K64,1)) | Z63: =IF(AND(M63="",N63="",M64=""),"",ROUND(SUM(M63,N63/60)*M64,1))
G64: =IF(SUM(G63:H63)>0,1,"") | I64: =IF(SUM(I63:J63)>0,1,"") | K64: =IF(SUM(K63:L63)>0,1,"") | M64: =IF(SUM(M63:N63)>0,1,"")
A65: =ROUND((ROW()-10)/2,0) -> 28 | C65: =IF(INDEX(設定!$C$9:$C$108,$A65,1)="","",INDEX(設定!$C$9:$C$108,$A65,1)) | D65: =IF(INDEX(設定!$D$9:$D$108,$A65,1)="","",INDEX(設定!$D$9:$D$108,$A65,1)) | E65: =IF(INDEX(設定!$E$9:$E$108,$A65,1)="","",INDEX(設定!$E$9:$E$108,$A65,1)) | F65: =IF(S65="","",IF(S65=1,"1：家族",IF(AND(S65>=2,S65<=5),"2：雇用",""))) | G65: =INT(INDEX(設定!$H$9:H$108,$A65,1)) -> 0 | H65: =IF(INDEX(設定!$H$9:$H$108,$A65,1)=0,"",ROUND(MOD(INDEX(設定!$H$9:$H$108,$A65,1),1)*60,0)) | I65: =INT(INDEX(設定!$I$9:$I$108,$A65,1)) -> 0 | J65: =IF(INDEX(設定!$I$9:$I$108,$A65,1)=0,"",ROUND(MOD(INDEX(設定!$I$9:$I$108,$A65,1),1)*60,0)) | K65: =INT(INDEX(設定!$J$9:$J$108,$A65,1)) -> 0 | L65: =IF(INDEX(設定!$J$9:$J$108,$A65,1)=0,"",ROUND(MOD(INDEX(設定!$J$9:$J$108,$A65,1),1)*60,0)) | M65: =INT(INDEX(設定!$K$9:$K$108,$A65,1)) -> 0 | N65: =IF(INDEX(設定!$K$9:$K$108,$A65,1)=0,"",ROUND(MOD(INDEX(設定!$K$9:$K$108,$A65,1),1)*60,0)) | S65: =IF(INDEX(設定!$F$9:$F$108,$A65,1)="","",VALUE(LEFT(INDEX(設定!$F$9:$F$108,$A65,1),1))) | T65: =IF(C65="","",C65) | U65: =IF(D65="","",IF(D65="1：男",1,IF(D65="2：女",2))) | V65: =IF(E65="","",E65) | W65: =IF(AND(G65="",H65="",G66=""),"",ROUND(SUM(G65,H65/60)*G66,1)) | X65: =IF(AND(I65="",J65="",I66=""),"",ROUND(SUM(I65,J65/60)*I66,1)) | Y65: =IF(AND(K65="",L65="",K66=""),"",ROUND(SUM(K65,L65/60)*K66,1)) | Z65: =IF(AND(M65="",N65="",M66=""),"",ROUND(SUM(M65,N65/60)*M66,1))
G66: =IF(SUM(G65:H65)>0,1,"") | I66: =IF(SUM(I65:J65)>0,1,"") | K66: =IF(SUM(K65:L65)>0,1,"") | M66: =IF(SUM(M65:N65)>0,1,"")
A67: =ROUND((ROW()-10)/2,0) -> 29 | C67: =IF(INDEX(設定!$C$9:$C$108,$A67,1)="","",INDEX(設定!$C$9:$C$108,$A67,1)) | D67: =IF(INDEX(設定!$D$9:$D$108,$A67,1)="","",INDEX(設定!$D$9:$D$108,$A67,1)) | E67: =IF(INDEX(設定!$E$9:$E$108,$A67,1)="","",INDEX(設定!$E$9:$E$108,$A67,1)) | F67: =IF(S67="","",IF(S67=1,"1：家族",IF(AND(S67>=2,S67<=5),"2：雇用",""))) | G67: =INT(INDEX(設定!$H$9:H$108,$A67,1)) -> 0 | H67: =IF(INDEX(設定!$H$9:$H$108,$A67,1)=0,"",ROUND(MOD(INDEX(設定!$H$9:$H$108,$A67,1),1)*60,0)) | I67: =INT(INDEX(設定!$I$9:$I$108,$A67,1)) -> 0 | J67: =IF(INDEX(設定!$I$9:$I$108,$A67,1)=0,"",ROUND(MOD(INDEX(設定!$I$9:$I$108,$A67,1),1)*60,0)) | K67: =INT(INDEX(設定!$J$9:$J$108,$A67,1)) -> 0 | L67: =IF(INDEX(設定!$J$9:$J$108,$A67,1)=0,"",ROUND(MOD(INDEX(設定!$J$9:$J$108,$A67,1),1)*60,0)) | M67: =INT(INDEX(設定!$K$9:$K$108,$A67,1)) -> 0 | N67: =IF(INDEX(設定!$K$9:$K$108,$A67,1)=0,"",ROUND(MOD(INDEX(設定!$K$9:$K$108,$A67,1),1)*60,0)) | S67: =IF(INDEX(設定!$F$9:$F$108,$A67,1)="","",VALUE(LEFT(INDEX(設定!$F$9:$F$108,$A67,1),1))) | T67: =IF(C67="","",C67) | U67: =IF(D67="","",IF(D67="1：男",1,IF(D67="2：女",2))) | V67: =IF(E67="","",E67) | W67: =IF(AND(G67="",H67="",G68=""),"",ROUND(SUM(G67,H67/60)*G68,1)) | X67: =IF(AND(I67="",J67="",I68=""),"",ROUND(SUM(I67,J67/60)*I68,1)) | Y67: =IF(AND(K67="",L67="",K68=""),"",ROUND(SUM(K67,L67/60)*K68,1)) | Z67: =IF(AND(M67="",N67="",M68=""),"",ROUND(SUM(M67,N67/60)*M68,1))
G68: =IF(SUM(G67:H67)>0,1,"") | I68: =IF(SUM(I67:J67)>0,1,"") | K68: =IF(SUM(K67:L67)>0,1,"") | M68: =IF(SUM(M67:N67)>0,1,"")
A69: =ROUND((ROW()-10)/2,0) -> 30 | C69: =IF(INDEX(設定!$C$9:$C$108,$A69,1)="","",INDEX(設定!$C$9:$C$108,$A69,1)) | D69: =IF(INDEX(設定!$D$9:$D$108,$A69,1)="","",INDEX(設定!$D$9:$D$108,$A69,1)) | E69: =IF(INDEX(設定!$E$9:$E$108,$A69,1)="","",INDEX(設定!$E$9:$E$108,$A69,1)) | F69: =IF(S69="","",IF(S69=1,"1：家族",IF(AND(S69>=2,S69<=5),"2：雇用",""))) | G69: =INT(INDEX(設定!$H$9:H$108,$A69,1)) -> 0 | H69: =IF(INDEX(設定!$H$9:$H$108,$A69,1)=0,"",ROUND(MOD(INDEX(設定!$H$9:$H$108,$A69,1),1)*60,0)) | I69: =INT(INDEX(設定!$I$9:$I$108,$A69,1)) -> 0 | J69: =IF(INDEX(設定!$I$9:$I$108,$A69,1)=0,"",ROUND(MOD(INDEX(設定!$I$9:$I$108,$A69,1),1)*60,0)) | K69: =INT(INDEX(設定!$J$9:$J$108,$A69,1)) -> 0 | L69: =IF(INDEX(設定!$J$9:$J$108,$A69,1)=0,"",ROUND(MOD(INDEX(設定!$J$9:$J$108,$A69,1),1)*60,0)) | M69: =INT(INDEX(設定!$K$9:$K$108,$A69,1)) -> 0 | N69: =IF(INDEX(設定!$K$9:$K$108,$A69,1)=0,"",ROUND(MOD(INDEX(設定!$K$9:$K$108,$A69,1),1)*60,0)) | S69: =IF(INDEX(設定!$F$9:$F$108,$A69,1)="","",VALUE(LEFT(INDEX(設定!$F$9:$F$108,$A69,1),1))) | T69: =IF(C69="","",C69) | U69: =IF(D69="","",IF(D69="1：男",1,IF(D69="2：女",2))) | V69: =IF(E69="","",E69) | W69: =IF(AND(G69="",H69="",G70=""),"",ROUND(SUM(G69,H69/60)*G70,1)) | X69: =IF(AND(I69="",J69="",I70=""),"",ROUND(SUM(I69,J69/60)*I70,1)) | Y69: =IF(AND(K69="",L69="",K70=""),"",ROUND(SUM(K69,L69/60)*K70,1)) | Z69: =IF(AND(M69="",N69="",M70=""),"",ROUND(SUM(M69,N69/60)*M70,1))
G70: =IF(SUM(G69:H69)>0,1,"") | I70: =IF(SUM(I69:J69)>0,1,"") | K70: =IF(SUM(K69:L69)>0,1,"") | M70: =IF(SUM(M69:N69)>0,1,"")
B72: ２ 酪農に関する１以外の作業
S74: 1：家族 2：雇用 3：ゆい・手間替え受け 4：手伝い・共同作業受け 5：同居人 | T74: 氏 名 | U74: 1：男 2：女 | V74: 年齢 | W74: 生産管理 労働時間 | X74: 間接労働時間 | Z74: 経営管理 労働時間
C75: 氏 名 | D75: 性別 | E75: 年齢 | F75: 家族 ・ 雇用 | G75: 自給飼料の生産 | H75: 購入付帯労働時間 | I75: 建物・農機具等の修繕 | J75: 集会出席時間 | K75: 技術取得時間 | L75: 簿記記帳時間 | M75: 経営管理労働時間 | X75: 自給飼料の 生産 | Y75: 建物等の修繕 購入付帯労働
A77: 1 | C77: =IF(INDEX(設定!$C$9:$C$108,$A77,1)="","",INDEX(設定!$C$9:$C$108,$A77,1)) | D77: =IF(INDEX(設定!$D$9:$D$108,$A77,1)="","",INDEX(設定!$D$9:$D$108,$A77,1)) | E77: =IF(INDEX(設定!$E$9:$E$108,$A77,1)="","",INDEX(設定!$E$9:$E$108,$A77,1)) | F77: =IF(S77="","",IF(S77=1,"1：家族",IF(AND(S77>=2,S77<=5),"2：雇用",""))) | G77: =IF(INDEX(設定!L$9:L$108,$A77,1)=0,"",ROUND(INDEX(設定!L$9:L$108,$A77,1),1)) | H77: =IF(INDEX(設定!M$9:M$108,$A77,1)=0,"",ROUND(INDEX(設定!M$9:M$108,$A77,1),1)) | I77: =IF(INDEX(設定!N$9:N$108,$A77,1)=0,"",ROUND(INDEX(設定!N$9:N$108,$A77,1),1)) | J77: =IF(INDEX(設定!O$9:O$108,$A77,1)=0,"",ROUND(INDEX(設定!O$9:O$108,$A77,1),1)) | K77: =IF(INDEX(設定!P$9:P$108,$A77,1)=0,"",ROUND(INDEX(設定!P$9:P$108,$A77,1),1)) | L77: =IF(INDEX(設定!Q$9:Q$108,$A77,1)=0,"",ROUND(INDEX(設定!Q$9:Q$108,$A77,1),1)) | M77: =IF(INDEX(設定!R$9:R$108,$A77,1)=0,"",ROUND(INDEX(設定!R$9:R$108,$A77,1),1)) | S77: =IF(INDEX(設定!$F$9:$F$108,$A77,1)="","",VALUE(LEFT(INDEX(設定!$F$9:$F$108,$A77,1),1))) | T77: =IF(C77="","",C77) | U77: =IF(D77="","",IF(D77="1：男",1,IF(D77="2：女",2))) | V77: =IF(E77="","",E77) | W77: =SUM(J77:L77) -> 0 | X77: =G77 | Y77: =SUM(H77:I77) -> 0 | Z77: =M77
A78: 2 | C78: =IF(INDEX(設定!$C$9:$C$108,$A78,1)="","",INDEX(設定!$C$9:$C$108,$A78,1)) | D78: =IF(INDEX(設定!$D$9:$D$108,$A78,1)="","",INDEX(設定!$D$9:$D$108,$A78,1)) | E78: =IF(INDEX(設定!$E$9:$E$108,$A78,1)="","",INDEX(設定!$E$9:$E$108,$A78,1)) | F78: =IF(S78="","",IF(S78=1,"1：家族",IF(AND(S78>=2,S78<=5),"2：雇用",""))) | G78: =IF(INDEX(設定!L$9:L$108,$A78,1)=0,"",ROUND(INDEX(設定!L$9:L$108,$A78,1),1)) | H78: =IF(INDEX(設定!M$9:M$108,$A78,1)=0,"",ROUND(INDEX(設定!M$9:M$108,$A78,1),1)) | I78: =IF(INDEX(設定!N$9:N$108,$A78,1)=0,"",ROUND(INDEX(設定!N$9:N$108,$A78,1),1)) | J78: =IF(INDEX(設定!O$9:O$108,$A78,1)=0,"",ROUND(INDEX(設定!O$9:O$108,$A78,1),1)) | K78: =IF(INDEX(設定!P$9:P$108,$A78,1)=0,"",ROUND(INDEX(設定!P$9:P$108,$A78,1),1)) | L78: =IF(INDEX(設定!Q$9:Q$108,$A78,1)=0,"",ROUND(INDEX(設定!Q$9:Q$108,$A78,1),1)) | M78: =IF(INDEX(設定!R$9:R$108,$A78,1)=0,"",ROUND(INDEX(設定!R$9:R$108,$A78,1),1)) | S78: =IF(INDEX(設定!$F$9:$F$108,$A78,1)="","",VALUE(LEFT(INDEX(設定!$F$9:$F$108,$A78,1),1))) | T78: =IF(C78="","",C78) | U78: =IF(D78="","",IF(D78="1：男",1,IF(D78="2：女",2))) | V78: =IF(E78="","",E78) | W78: =SUM(J78:L78) -> 0 | X78: =G78 | Y78: =SUM(H78:I78) -> 0 | Z78: =M78
A79: 3 | C79: =IF(INDEX(設定!$C$9:$C$108,$A79,1)="","",INDEX(設定!$C$9:$C$108,$A79,1)) | D79: =IF(INDEX(設定!$D$9:$D$108,$A79,1)="","",INDEX(設定!$D$9:$D$108,$A79,1)) | E79: =IF(INDEX(設定!$E$9:$E$108,$A79,1)="","",INDEX(設定!$E$9:$E$108,$A79,1)) | F79: =IF(S79="","",IF(S79=1,"1：家族",IF(AND(S79>=2,S79<=5),"2：雇用",""))) | G79: =IF(INDEX(設定!L$9:L$108,$A79,1)=0,"",ROUND(INDEX(設定!L$9:L$108,$A79,1),1)) | H79: =IF(INDEX(設定!M$9:M$108,$A79,1)=0,"",ROUND(INDEX(設定!M$9:M$108,$A79,1),1)) | I79: =IF(INDEX(設定!N$9:N$108,$A79,1)=0,"",ROUND(INDEX(設定!N$9:N$108,$A79,1),1)) | J79: =IF(INDEX(設定!O$9:O$108,$A79,1)=0,"",ROUND(INDEX(設定!O$9:O$108,$A79,1),1)) | K79: =IF(INDEX(設定!P$9:P$108,$A79,1)=0,"",ROUND(INDEX(設定!P$9:P$108,$A79,1),1)) | L79: =IF(INDEX(設定!Q$9:Q$108,$A79,1)=0,"",ROUND(INDEX(設定!Q$9:Q$108,$A79,1),1)) | M79: =IF(INDEX(設定!R$9:R$108,$A79,1)=0,"",ROUND(INDEX(設定!R$9:R$108,$A79,1),1)) | S79: =IF(INDEX(設定!$F$9:$F$108,$A79,1)="","",VALUE(LEFT(INDEX(設定!$F$9:$F$108,$A79,1),1))) | T79: =IF(C79="","",C79) | U79: =IF(D79="","",IF(D79="1：男",1,IF(D79="2：女",2))) | V79: =IF(E79="","",E79) | W79: =SUM(J79:L79) -> 0 | X79: =G79 | Y79: =SUM(H79:I79) -> 0 | Z79: =M79
A80: 4 | C80: =IF(INDEX(設定!$C$9:$C$108,$A80,1)="","",INDEX(設定!$C$9:$C$108,$A80,1)) | D80: =IF(INDEX(設定!$D$9:$D$108,$A80,1)="","",INDEX(設定!$D$9:$D$108,$A80,1)) | E80: =IF(INDEX(設定!$E$9:$E$108,$A80,1)="","",INDEX(設定!$E$9:$E$108,$A80,1)) | F80: =IF(S80="","",IF(S80=1,"1：家族",IF(AND(S80>=2,S80<=5),"2：雇用",""))) | G80: =IF(INDEX(設定!L$9:L$108,$A80,1)=0,"",ROUND(INDEX(設定!L$9:L$108,$A80,1),1)) | H80: =IF(INDEX(設定!M$9:M$108,$A80,1)=0,"",ROUND(INDEX(設定!M$9:M$108,$A80,1),1)) | I80: =IF(INDEX(設定!N$9:N$108,$A80,1)=0,"",ROUND(INDEX(設定!N$9:N$108,$A80,1),1)) | J80: =IF(INDEX(設定!O$9:O$108,$A80,1)=0,"",ROUND(INDEX(設定!O$9:O$108,$A80,1),1)) | K80: =IF(INDEX(設定!P$9:P$108,$A80,1)=0,"",ROUND(INDEX(設定!P$9:P$108,$A80,1),1)) | L80: =IF(INDEX(設定!Q$9:Q$108,$A80,1)=0,"",ROUND(INDEX(設定!Q$9:Q$108,$A80,1),1)) | M80: =IF(INDEX(設定!R$9:R$108,$A80,1)=0,"",ROUND(INDEX(設定!R$9:R$108,$A80,1),1)) | S80: =IF(INDEX(設定!$F$9:$F$108,$A80,1)="","",VALUE(LEFT(INDEX(設定!$F$9:$F$108,$A80,1),1))) | T80: =IF(C80="","",C80) | U80: =IF(D80="","",IF(D80="1：男",1,IF(D80="2：女",2))) | V80: =IF(E80="","",E80) | W80: =SUM(J80:L80) -> 0 | X80: =G80 | Y80: =SUM(H80:I80) -> 0 | Z80: =M80
A81: 5 | C81: =IF(INDEX(設定!$C$9:$C$108,$A81,1)="","",INDEX(設定!$C$9:$C$108,$A81,1)) | D81: =IF(INDEX(設定!$D$9:$D$108,$A81,1)="","",INDEX(設定!$D$9:$D$108,$A81,1)) | E81: =IF(INDEX(設定!$E$9:$E$108,$A81,1)="","",INDEX(設定!$E$9:$E$108,$A81,1)) | F81: =IF(S81="","",IF(S81=1,"1：家族",IF(AND(S81>=2,S81<=5),"2：雇用",""))) | G81: =IF(INDEX(設定!L$9:L$108,$A81,1)=0,"",ROUND(INDEX(設定!L$9:L$108,$A81,1),1)) | H81: =IF(INDEX(設定!M$9:M$108,$A81,1)=0,"",ROUND(INDEX(設定!M$9:M$108,$A81,1),1)) | I81: =IF(INDEX(設定!N$9:N$108,$A81,1)=0,"",ROUND(INDEX(設定!N$9:N$108,$A81,1),1)) | J81: =IF(INDEX(設定!O$9:O$108,$A81,1)=0,"",ROUND(INDEX(設定!O$9:O$108,$A81,1),1)) | K81: =IF(INDEX(設定!P$9:P$108,$A81,1)=0,"",ROUND(INDEX(設定!P$9:P$108,$A81,1),1)) | L81: =IF(INDEX(設定!Q$9:Q$108,$A81,1)=0,"",ROUND(INDEX(設定!Q$9:Q$108,$A81,1),1)) | M81: =IF(INDEX(設定!R$9:R$108,$A81,1)=0,"",ROUND(INDEX(設定!R$9:R$108,$A81,1),1)) | S81: =IF(INDEX(設定!$F$9:$F$108,$A81,1)="","",VALUE(LEFT(INDEX(設定!$F$9:$F$108,$A81,1),1))) | T81: =IF(C81="","",C81) | U81: =IF(D81="","",IF(D81="1：男",1,IF(D81="2：女",2))) | V81: =IF(E81="","",E81) | W81: =SUM(J81:L81) -> 0 | X81: =G81 | Y81: =SUM(H81:I81) -> 0 | Z81: =M81
A82: 6 | C82: =IF(INDEX(設定!$C$9:$C$108,$A82,1)="","",INDEX(設定!$C$9:$C$108,$A82,1)) | D82: =IF(INDEX(設定!$D$9:$D$108,$A82,1)="","",INDEX(設定!$D$9:$D$108,$A82,1)) | E82: =IF(INDEX(設定!$E$9:$E$108,$A82,1)="","",INDEX(設定!$E$9:$E$108,$A82,1)) | F82: =IF(S82="","",IF(S82=1,"1：家族",IF(AND(S82>=2,S82<=5),"2：雇用",""))) | G82: =IF(INDEX(設定!L$9:L$108,$A82,1)=0,"",ROUND(INDEX(設定!L$9:L$108,$A82,1),1)) | H82: =IF(INDEX(設定!M$9:M$108,$A82,1)=0,"",ROUND(INDEX(設定!M$9:M$108,$A82,1),1)) | I82: =IF(INDEX(設定!N$9:N$108,$A82,1)=0,"",ROUND(INDEX(設定!N$9:N$108,$A82,1),1)) | J82: =IF(INDEX(設定!O$9:O$108,$A82,1)=0,"",ROUND(INDEX(設定!O$9:O$108,$A82,1),1)) | K82: =IF(INDEX(設定!P$9:P$108,$A82,1)=0,"",ROUND(INDEX(設定!P$9:P$108,$A82,1),1)) | L82: =IF(INDEX(設定!Q$9:Q$108,$A82,1)=0,"",ROUND(INDEX(設定!Q$9:Q$108,$A82,1),1)) | M82: =IF(INDEX(設定!R$9:R$108,$A82,1)=0,"",ROUND(INDEX(設定!R$9:R$108,$A82,1),1)) | S82: =IF(INDEX(設定!$F$9:$F$108,$A82,1)="","",VALUE(LEFT(INDEX(設定!$F$9:$F$108,$A82,1),1))) | T82: =IF(C82="","",C82) | U82: =IF(D82="","",IF(D82="1：男",1,IF(D82="2：女",2))) | V82: =IF(E82="","",E82) | W82: =SUM(J82:L82) -> 0 | X82: =G82 | Y82: =SUM(H82:I82) -> 0 | Z82: =M82
A83: 7 | C83: =IF(INDEX(設定!$C$9:$C$108,$A83,1)="","",INDEX(設定!$C$9:$C$108,$A83,1)) | D83: =IF(INDEX(設定!$D$9:$D$108,$A83,1)="","",INDEX(設定!$D$9:$D$108,$A83,1)) | E83: =IF(INDEX(設定!$E$9:$E$108,$A83,1)="","",INDEX(設定!$E$9:$E$108,$A83,1)) | F83: =IF(S83="","",IF(S83=1,"1：家族",IF(AND(S83>=2,S83<=5),"2：雇用",""))) | G83: =IF(INDEX(設定!L$9:L$108,$A83,1)=0,"",ROUND(INDEX(設定!L$9:L$108,$A83,1),1)) | H83: =IF(INDEX(設定!M$9:M$108,$A83,1)=0,"",ROUND(INDEX(設定!M$9:M$108,$A83,1),1)) | I83: =IF(INDEX(設定!N$9:N$108,$A83,1)=0,"",ROUND(INDEX(設定!N$9:N$108,$A83,1),1)) | J83: =IF(INDEX(設定!O$9:O$108,$A83,1)=0,"",ROUND(INDEX(設定!O$9:O$108,$A83,1),1)) | K83: =IF(INDEX(設定!P$9:P$108,$A83,1)=0,"",ROUND(INDEX(設定!P$9:P$108,$A83,1),1)) | L83: =IF(INDEX(設定!Q$9:Q$108,$A83,1)=0,"",ROUND(INDEX(設定!Q$9:Q$108,$A83,1),1)) | M83: =IF(INDEX(設定!R$9:R$108,$A83,1)=0,"",ROUND(INDEX(設定!R$9:R$108,$A83,1),1)) | S83: =IF(INDEX(設定!$F$9:$F$108,$A83,1)="","",VALUE(LEFT(INDEX(設定!$F$9:$F$108,$A83,1),1))) | T83: =IF(C83="","",C83) | U83: =IF(D83="","",IF(D83="1：男",1,IF(D83="2：女",2))) | V83: =IF(E83="","",E83) | W83: =SUM(J83:L83) -> 0 | X83: =G83 | Y83: =SUM(H83:I83) -> 0 | Z83: =M83
A84: 8 | C84: =IF(INDEX(設定!$C$9:$C$108,$A84,1)="","",INDEX(設定!$C$9:$C$108,$A84,1)) | D84: =IF(INDEX(設定!$D$9:$D$108,$A84,1)="","",INDEX(設定!$D$9:$D$108,$A84,1)) | E84: =IF(INDEX(設定!$E$9:$E$108,$A84,1)="","",INDEX(設定!$E$9:$E$108,$A84,1)) | F84: =IF(S84="","",IF(S84=1,"1：家族",IF(AND(S84>=2,S84<=5),"2：雇用",""))) | G84: =IF(INDEX(設定!L$9:L$108,$A84,1)=0,"",ROUND(INDEX(設定!L$9:L$108,$A84,1),1)) | H84: =IF(INDEX(設定!M$9:M$108,$A84,1)=0,"",ROUND(INDEX(設定!M$9:M$108,$A84,1),1)) | I84: =IF(INDEX(設定!N$9:N$108,$A84,1)=0,"",ROUND(INDEX(設定!N$9:N$108,$A84,1),1)) | J84: =IF(INDEX(設定!O$9:O$108,$A84,1)=0,"",ROUND(INDEX(設定!O$9:O$108,$A84,1),1)) | K84: =IF(INDEX(設定!P$9:P$108,$A84,1)=0,"",ROUND(INDEX(設定!P$9:P$108,$A84,1),1)) | L84: =IF(INDEX(設定!Q$9:Q$108,$A84,1)=0,"",ROUND(INDEX(設定!Q$9:Q$108,$A84,1),1)) | M84: =IF(INDEX(設定!R$9:R$108,$A84,1)=0,"",ROUND(INDEX(設定!R$9:R$108,$A84,1),1)) | S84: =IF(INDEX(設定!$F$9:$F$108,$A84,1)="","",VALUE(LEFT(INDEX(設定!$F$9:$F$108,$A84,1),1))) | T84: =IF(C84="","",C84) | U84: =IF(D84="","",IF(D84="1：男",1,IF(D84="2：女",2))) | V84: =IF(E84="","",E84) | W84: =SUM(J84:L84) -> 0 | X84: =G84 | Y84: =SUM(H84:I84) -> 0 | Z84: =M84
A85: 9 | C85: =IF(INDEX(設定!$C$9:$C$108,$A85,1)="","",INDEX(設定!$C$9:$C$108,$A85,1)) | D85: =IF(INDEX(設定!$D$9:$D$108,$A85,1)="","",INDEX(設定!$D$9:$D$108,$A85,1)) | E85: =IF(INDEX(設定!$E$9:$E$108,$A85,1)="","",INDEX(設定!$E$9:$E$108,$A85,1)) | F85: =IF(S85="","",IF(S85=1,"1：家族",IF(AND(S85>=2,S85<=5),"2：雇用",""))) | G85: =IF(INDEX(設定!L$9:L$108,$A85,1)=0,"",ROUND(INDEX(設定!L$9:L$108,$A85,1),1)) | H85: =IF(INDEX(設定!M$9:M$108,$A85,1)=0,"",ROUND(INDEX(設定!M$9:M$108,$A85,1),1)) | I85: =IF(INDEX(設定!N$9:N$108,$A85,1)=0,"",ROUND(INDEX(設定!N$9:N$108,$A85,1),1)) | J85: =IF(INDEX(設定!O$9:O$108,$A85,1)=0,"",ROUND(INDEX(設定!O$9:O$108,$A85,1),1)) | K85: =IF(INDEX(設定!P$9:P$108,$A85,1)=0,"",ROUND(INDEX(設定!P$9:P$108,$A85,1),1)) | L85: =IF(INDEX(設定!Q$9:Q$108,$A85,1)=0,"",ROUND(INDEX(設定!Q$9:Q$108,$A85,1),1)) | M85: =IF(INDEX(設定!R$9:R$108,$A85,1)=0,"",ROUND(INDEX(設定!R$9:R$108,$A85,1),1)) | S85: =IF(INDEX(設定!$F$9:$F$108,$A85,1)="","",VALUE(LEFT(INDEX(設定!$F$9:$F$108,$A85,1),1))) | T85: =IF(C85="","",C85) | U85: =IF(D85="","",IF(D85="1：男",1,IF(D85="2：女",2))) | V85: =IF(E85="","",E85) | W85: =SUM(J85:L85) -> 0 | X85: =G85 | Y85: =SUM(H85:I85) -> 0 | Z85: =M85
A86: 10 | C86: =IF(INDEX(設定!$C$9:$C$108,$A86,1)="","",INDEX(設定!$C$9:$C$108,$A86,1)) | D86: =IF(INDEX(設定!$D$9:$D$108,$A86,1)="","",INDEX(設定!$D$9:$D$108,$A86,1)) | E86: =IF(INDEX(設定!$E$9:$E$108,$A86,1)="","",INDEX(設定!$E$9:$E$108,$A86,1)) | F86: =IF(S86="","",IF(S86=1,"1：家族",IF(AND(S86>=2,S86<=5),"2：雇用",""))) | G86: =IF(INDEX(設定!L$9:L$108,$A86,1)=0,"",ROUND(INDEX(設定!L$9:L$108,$A86,1),1)) | H86: =IF(INDEX(設定!M$9:M$108,$A86,1)=0,"",ROUND(INDEX(設定!M$9:M$108,$A86,1),1)) | I86: =IF(INDEX(設定!N$9:N$108,$A86,1)=0,"",ROUND(INDEX(設定!N$9:N$108,$A86,1),1)) | J86: =IF(INDEX(設定!O$9:O$108,$A86,1)=0,"",ROUND(INDEX(設定!O$9:O$108,$A86,1),1)) | K86: =IF(INDEX(設定!P$9:P$108,$A86,1)=0,"",ROUND(INDEX(設定!P$9:P$108,$A86,1),1)) | L86: =IF(INDEX(設定!Q$9:Q$108,$A86,1)=0,"",ROUND(INDEX(設定!Q$9:Q$108,$A86,1),1)) | M86: =IF(INDEX(設定!R$9:R$108,$A86,1)=0,"",ROUND(INDEX(設定!R$9:R$108,$A86,1),1)) | S86: =IF(INDEX(設定!$F$9:$F$108,$A86,1)="","",VALUE(LEFT(INDEX(設定!$F$9:$F$108,$A86,1),1))) | T86: =IF(C86="","",C86) | U86: =IF(D86="","",IF(D86="1：男",1,IF(D86="2：女",2))) | V86: =IF(E86="","",E86) | W86: =SUM(J86:L86) -> 0 | X86: =G86 | Y86: =SUM(H86:I86) -> 0 | Z86: =M86
A87: 11 | C87: =IF(INDEX(設定!$C$9:$C$108,$A87,1)="","",INDEX(設定!$C$9:$C$108,$A87,1)) | D87: =IF(INDEX(設定!$D$9:$D$108,$A87,1)="","",INDEX(設定!$D$9:$D$108,$A87,1)) | E87: =IF(INDEX(設定!$E$9:$E$108,$A87,1)="","",INDEX(設定!$E$9:$E$108,$A87,1)) | F87: =IF(S87="","",IF(S87=1,"1：家族",IF(AND(S87>=2,S87<=5),"2：雇用",""))) | G87: =IF(INDEX(設定!L$9:L$108,$A87,1)=0,"",ROUND(INDEX(設定!L$9:L$108,$A87,1),1)) | H87: =IF(INDEX(設定!M$9:M$108,$A87,1)=0,"",ROUND(INDEX(設定!M$9:M$108,$A87,1),1)) | I87: =IF(INDEX(設定!N$9:N$108,$A87,1)=0,"",ROUND(INDEX(設定!N$9:N$108,$A87,1),1)) | J87: =IF(INDEX(設定!O$9:O$108,$A87,1)=0,"",ROUND(INDEX(設定!O$9:O$108,$A87,1),1)) | K87: =IF(INDEX(設定!P$9:P$108,$A87,1)=0,"",ROUND(INDEX(設定!P$9:P$108,$A87,1),1)) | L87: =IF(INDEX(設定!Q$9:Q$108,$A87,1)=0,"",ROUND(INDEX(設定!Q$9:Q$108,$A87,1),1)) | M87: =IF(INDEX(設定!R$9:R$108,$A87,1)=0,"",ROUND(INDEX(設定!R$9:R$108,$A87,1),1)) | S87: =IF(INDEX(設定!$F$9:$F$108,$A87,1)="","",VALUE(LEFT(INDEX(設定!$F$9:$F$108,$A87,1),1))) | T87: =IF(C87="","",C87) | U87: =IF(D87="","",IF(D87="1：男",1,IF(D87="2：女",2))) | V87: =IF(E87="","",E87) | W87: =SUM(J87:L87) -> 0 | X87: =G87 | Y87: =SUM(H87:I87) -> 0 | Z87: =M87
A88: 12 | C88: =IF(INDEX(設定!$C$9:$C$108,$A88,1)="","",INDEX(設定!$C$9:$C$108,$A88,1)) | D88: =IF(INDEX(設定!$D$9:$D$108,$A88,1)="","",INDEX(設定!$D$9:$D$108,$A88,1)) | E88: =IF(INDEX(設定!$E$9:$E$108,$A88,1)="","",INDEX(設定!$E$9:$E$108,$A88,1)) | F88: =IF(S88="","",IF(S88=1,"1：家族",IF(AND(S88>=2,S88<=5),"2：雇用",""))) | G88: =IF(INDEX(設定!L$9:L$108,$A88,1)=0,"",ROUND(INDEX(設定!L$9:L$108,$A88,1),1)) | H88: =IF(INDEX(設定!M$9:M$108,$A88,1)=0,"",ROUND(INDEX(設定!M$9:M$108,$A88,1),1)) | I88: =IF(INDEX(設定!N$9:N$108,$A88,1)=0,"",ROUND(INDEX(設定!N$9:N$108,$A88,1),1)) | J88: =IF(INDEX(設定!O$9:O$108,$A88,1)=0,"",ROUND(INDEX(設定!O$9:O$108,$A88,1),1)) | K88: =IF(INDEX(設定!P$9:P$108,$A88,1)=0,"",ROUND(INDEX(設定!P$9:P$108,$A88,1),1)) | L88: =IF(INDEX(設定!Q$9:Q$108,$A88,1)=0,"",ROUND(INDEX(設定!Q$9:Q$108,$A88,1),1)) | M88: =IF(INDEX(設定!R$9:R$108,$A88,1)=0,"",ROUND(INDEX(設定!R$9:R$108,$A88,1),1)) | S88: =IF(INDEX(設定!$F$9:$F$108,$A88,1)="","",VALUE(LEFT(INDEX(設定!$F$9:$F$108,$A88,1),1))) | T88: =IF(C88="","",C88) | U88: =IF(D88="","",IF(D88="1：男",1,IF(D88="2：女",2))) | V88: =IF(E88="","",E88) | W88: =SUM(J88:L88) -> 0 | X88: =G88 | Y88: =SUM(H88:I88) -> 0 | Z88: =M88
... A106: 30 | C106: =IF(INDEX(設定!$C$9:$C$108,$A106,1)="","",INDEX(設定!$C$9:$C$108,$A106,1)) | D106: =IF(INDEX(設定!$D$9:$D$108,$A106,1)="","",INDEX(設定!$D$9:$D$108,$A106,1)) | E106: =IF(INDEX(設定!$E$9:$E$108,$A106,1)="","",INDEX(設定!$E$9:$E$108,$A106,1)) | F106: =IF(S106="","",IF(S106=1,"1：家族",IF(AND(S106>=2,S106<=5),"2：雇用",""))) | G106: =IF(INDEX(設定!L$9:L$108,$A106,1)=0,"",ROUND(INDEX(設定!L$9:L$108,$A106,1),1)) | H106: =IF(INDEX(設定!M$9:M$108,$A106,1)=0,"",ROUND(INDEX(設定!M$9:M$108,$A106,1),1)) | I106: =IF(INDEX(設定!N$9:N$108,$A106,1)=0,"",ROUND(INDEX(設定!N$9:N$108,$A106,1),1)) | J106: =IF(INDEX(設定!O$9:O$108,$A106,1)=0,"",ROUND(INDEX(設定!O$9:O$108,$A106,1),1)) | K106: =IF(INDEX(設定!P$9:P$108,$A106,1)=0,"",ROUND(INDEX(設定!P$9:P$108,$A106,1),1)) | L106: =IF(INDEX(設定!Q$9:Q$108,$A106,1)=0,"",ROUND(INDEX(設定!Q$9:Q$108,$A106,1),1)) | M106: =IF(INDEX(設定!R$9:R$108,$A106,1)=0,"",ROUND(INDEX(設定!R$9:R$108,$A106,1),1)) | S106: =IF(INDEX(設定!$F$9:$F$108,$A106,1)="","",VALUE(LEFT(INDEX(設定!$F$9:$F$108,$A106,1),1))) | T106: =IF(C106="","",C106) | U106: =IF(D106="","",IF(D106="1：男",1,IF(D106="2：女",2))) | V106: =IF(E106="","",E106) | W106: =SUM(J106:L106) -> 0 | X106: =G106 | Y106: =SUM(H106:I106) -> 0 | Z106: =M106
C109: 雇用者（ヘルパー、研修生等）に支払った賃金（現物支給も含む。）を男女別に入力してください。 | S109: 支払賃金
C110: 区 分 | D110: 金 額（円） | E110: 負担割合（％） | S110: 区 分 | T110: 金額（円）
E111: 調査対象畜 | F111: 自給牧草 | T111: 調査対象畜 | U111: 自給牧草
C112: 男 | S112: 男 | T112: =IF(E112="","",ROUND(D112*E112%,0)) | U112: =IF(F112="","",ROUND(D112*(F112%),0))
C113: 女 | S113: 女 | T113: =IF(E113="","",ROUND(D113*E113%,0)) | U113: =IF(F113="","",ROUND(D113*(F113%),0))

Sheet 【12】労働時間（個別・牛乳以外）
B2: 【12】作業別労働時間
S4: 労賃単価
C8: 氏 名 | D8: 性別 | E8: 年齢 | F8: 家族 ・ 雇用 | G8: 飼料の調理・ 給与・給水 | I8: 敷料搬入・きゅう肥搬出 | K8: その他の 飼育作業 | S8: 1：家族 2：雇用 3：ゆい・手間替え受け 4：手伝い・共同作業受け 5：同居人 | T8: 氏 名 | U8: 1：男 2：女 | V8: 年齢 | W8: 飼料の調理・給与・給水 | X8: 敷料搬入・きゅう肥搬出 | Y8: その他の飼育作業 | AF8: 家族労働 | AL8: 雇用労働 | AY8: 家族労働 | BA8: 雇用労働
AF9: 計 | AH9: 家族 | AJ9: ゆい・手間替え受け | AL9: 計 | AN9: 雇用 | AP9: 手伝い・共同作業受け | AR9: 同居人 | BC9: 雇用 | BE9: 手伝い・共同作業受け、同居人
AF10: 男 | AG10: 女 | AH10: 男 | AI10: 女 | AJ10: 男 | AK10: 女 | AL10: 男 | AM10: 女 | AN10: 男 | AO10: 女 | AP10: 男 | AQ10: 女 | AR10: 男 | AS10: 女 | AY10: 男 | AZ10: 女 | BA10: 男 | BB10: 女 | BC10: 男 | BD10: 女 | BE10: 男 | BF10: 女
A11: =ROUND((ROW()-10)/2,0) -> 1 | C11: =IF(INDEX(設定!$C$9:$C$108,$A11,1)="","",INDEX(設定!$C$9:$C$108,$A11,1)) | D11: =IF(INDEX(設定!$D$9:$D$108,$A11,1)="","",INDEX(設定!$D$9:$D$108,$A11,1)) | E11: =IF(INDEX(設定!$E$9:$E$108,$A11,1)="","",INDEX(設定!$E$9:$E$108,$A11,1)) | F11: =IF(S11="","",IF(S11=1,"1：家族",IF(AND(S11>=2,S11<=5),"2：雇用",""))) | G11: =INT(INDEX(設定!$H$9:H$108,$A11,1)) -> 0 | H11: =IF(INDEX(設定!$H$9:$H$108,$A11,1)=0,"",ROUND(MOD(INDEX(設定!$H$9:$H$108,$A11,1),1)*60,0)) | I11: =INT(INDEX(設定!$I$9:$I$108,$A11,1)) -> 0 | J11: =IF(INDEX(設定!$I$9:$I$108,$A11,1)=0,"",ROUND(MOD(INDEX(設定!$I$9:$I$108,$A11,1),1)*60,0)) | K11: =INT(INDEX(設定!$J$9:$J$108,$A11,1)) -> 0 | L11: =IF(INDEX(設定!$J$9:$J$108,$A11,1)=0,"",ROUND(MOD(INDEX(設定!$J$9:$J$108,$A11,1),1)*60,0)) | S11: =IF(INDEX(設定!$F$9:$F$108,$A11,1)="","",VALUE(LEFT(INDEX(設定!$F$9:$F$108,$A11,1),1))) | T11: =IF(C11="","",C11) | U11: =IF(D11="","",IF(D11="1：男",1,IF(D11="2：女",2))) | V11: =IF(E11="","",E11) | W11: =IF(AND(G11="",H11="",G12=""),"",ROUND(SUM(G11,H11/60)*G12,1)) | X11: =IF(AND(I11="",J11="",I12=""),"",ROUND(SUM(I11,J11/60)*I12,1)) | Y11: =IF(AND(K11="",L11="",K12=""),"",ROUND(SUM(K11,L11/60)*K12,1)) | AC11: 直接労働時間 | AF11: =SUM(AF12:AF15) -> 0 | AG11: =SUM(AG12:AG15) -> 0 | AL11: =SUM(AL16,AL21,AL26) -> 0 | AM11: =SUM(AM16,AM21,AM26) -> 0 | AN11: =SUM(AN16,AN21,AN26) -> 0 | AO11: =SUM(AO16,AO21,AO26) -> 0 | AP11: =AP12 -> 0 | AQ11: =AQ12 -> 0 | AR11: =SUM(AR12:AR15) -> 0 | AS11: =SUM(AS12:AS15) -> 0 | AV11: 直接労働費 | AY11: =SUM(AY12:AY15) -> 0 | AZ11: =SUM(AZ12:AZ15) -> 0 | BA11: =ROUND(SUM(BC11,BE11),0) -> 0 | BB11: =ROUND(SUM(BD11,BF11),0) -> 0 | BC11: =IFERROR($T$112*($AN11/$AN$36),0) -> 0 | BD11: =IFERROR($T$113*($AO11/$AO$36),0) -> 0 | BE11: =SUM(BE12:BE15) -> 0 | BF11: =SUM(BF12:BF15) -> 0
G12: =IF(SUM(G11:H11)>0,1,"") | I12: =IF(SUM(I11:J11)>0,1,"") | K12: =IF(SUM(K11:L11)>0,1,"") | AD12: 65歳未満 | AF12: =SUM(AF17,AF22,AF27) -> 0 | AG12: =SUM(AG17,AG22,AG27) -> 0 | AH12: =SUM(AH17,AH22,AH27) -> 0 | AI12: =SUM(AI17,AI22,AI27) -> 0 | AJ12: =SUM(AJ17,AJ22,AJ27) -> 0 | AK12: =SUM(AK17,AK22,AK27) -> 0 | AP12: =SUM(AP17,AP22,AP27) -> 0 | AQ12: =SUM(AQ17,AQ22,AQ27) -> 0 | AR12: =SUM(AR17,AR22,AR27) -> 0 | AS12: =SUM(AS17,AS22,AS27) -> 0 | AW12: 65歳未満 | AY12: =ROUND(AF12*$T$4,0) -> 0 | AZ12: =ROUND(AG12*$T$4,0) -> 0 | BE12: =(AP12+AR12)*$T$4 -> 0 | BF12: =(AQ12+AS12)*$T$4 -> 0
A13: =ROUND((ROW()-10)/2,0) -> 2 | C13: =IF(INDEX(設定!$C$9:$C$108,$A13,1)="","",INDEX(設定!$C$9:$C$108,$A13,1)) | D13: =IF(INDEX(設定!$D$9:$D$108,$A13,1)="","",INDEX(設定!$D$9:$D$108,$A13,1)) | E13: =IF(INDEX(設定!$E$9:$E$108,$A13,1)="","",INDEX(設定!$E$9:$E$108,$A13,1)) | F13: =IF(S13="","",IF(S13=1,"1：家族",IF(AND(S13>=2,S13<=5),"2：雇用",""))) | G13: =INT(INDEX(設定!$H$9:H$108,$A13,1)) -> 0 | H13: =IF(INDEX(設定!$H$9:$H$108,$A13,1)=0,"",ROUND(MOD(INDEX(設定!$H$9:$H$108,$A13,1),1)*60,0)) | I13: =INT(INDEX(設定!$I$9:$I$108,$A13,1)) -> 0 | J13: =IF(INDEX(設定!$I$9:$I$108,$A13,1)=0,"",ROUND(MOD(INDEX(設定!$I$9:$I$108,$A13,1),1)*60,0)) | K13: =INT(INDEX(設定!$J$9:$J$108,$A13,1)) -> 0 | L13: =IF(INDEX(設定!$J$9:$J$108,$A13,1)=0,"",ROUND(MOD(INDEX(設定!$J$9:$J$108,$A13,1),1)*60,0)) | S13: =IF(INDEX(設定!$F$9:$F$108,$A13,1)="","",VALUE(LEFT(INDEX(設定!$F$9:$F$108,$A13,1),1))) | T13: =IF(C13="","",C13) | U13: =IF(D13="","",IF(D13="1：男",1,IF(D13="2：女",2))) | V13: =IF(E13="","",E13) | W13: =IF(AND(G13="",H13="",G14=""),"",ROUND(SUM(G13,H13/60)*G14,1)) | X13: =IF(AND(I13="",J13="",I14=""),"",ROUND(SUM(I13,J13/60)*I14,1)) | Y13: =IF(AND(K13="",L13="",K14=""),"",ROUND(SUM(K13,L13/60)*K14,1)) | AD13: 65～70 | AF13: =SUM(AF18,AF23,AF28) -> 0 | AG13: =SUM(AG18,AG23,AG28) -> 0 | AH13: =SUM(AH18,AH23,AH28) -> 0 | AI13: =SUM(AI18,AI23,AI28) -> 0 | AR13: =SUM(AR18,AR23,AR28) -> 0 | AS13: =SUM(AS18,AS23,AS28) -> 0 | AW13: 65～70 | AY13: =ROUND(AF13*$T$4*0.9,0) -> 0 | AZ13: =ROUND(AG13*$T$4*0.9,0) -> 0 | BE13: =(AP13+AR13)*$T$4*0.9 -> 0 | BF13: =(AQ13+AS13)*$T$4*0.9 -> 0
G14: =IF(SUM(G13:H13)>0,1,"") | I14: =IF(SUM(I13:J13)>0,1,"") | K14: =IF(SUM(K13:L13)>0,1,"") | AD14: 70～75 | AF14: =SUM(AF19,AF24,AF29) -> 0 | AG14: =SUM(AG19,AG24,AG29) -> 0 | AH14: =SUM(AH19,AH24,AH29) -> 0 | AI14: =SUM(AI19,AI24,AI29) -> 0 | AR14: =SUM(AR19,AR24,AR29) -> 0 | AS14: =SUM(AS19,AS24,AS29) -> 0 | AW14: 70～75 | AY14: =ROUND(AF14*$T$4*0.8,0) -> 0 | AZ14: =ROUND(AG14*$T$4*0.8,0) -> 0 | BE14: =(AP14+AR14)*$T$4*0.8 -> 0 | BF14: =(AQ14+AS14)*$T$4*0.8 -> 0
A15: =ROUND((ROW()-10)/2,0) -> 3 | C15: =IF(INDEX(設定!$C$9:$C$108,$A15,1)="","",INDEX(設定!$C$9:$C$108,$A15,1)) | D15: =IF(INDEX(設定!$D$9:$D$108,$A15,1)="","",INDEX(設定!$D$9:$D$108,$A15,1)) | E15: =IF(INDEX(設定!$E$9:$E$108,$A15,1)="","",INDEX(設定!$E$9:$E$108,$A15,1)) | F15: =IF(S15="","",IF(S15=1,"1：家族",IF(AND(S15>=2,S15<=5),"2：雇用",""))) | G15: =INT(INDEX(設定!$H$9:H$108,$A15,1)) -> 0 | H15: =IF(INDEX(設定!$H$9:$H$108,$A15,1)=0,"",ROUND(MOD(INDEX(設定!$H$9:$H$108,$A15,1),1)*60,0)) | I15: =INT(INDEX(設定!$I$9:$I$108,$A15,1)) -> 0 | J15: =IF(INDEX(設定!$I$9:$I$108,$A15,1)=0,"",ROUND(MOD(INDEX(設定!$I$9:$I$108,$A15,1),1)*60,0)) | K15: =INT(INDEX(設定!$J$9:$J$108,$A15,1)) -> 0 | L15: =IF(INDEX(設定!$J$9:$J$108,$A15,1)=0,"",ROUND(MOD(INDEX(設定!$J$9:$J$108,$A15,1),1)*60,0)) | S15: =IF(INDEX(設定!$F$9:$F$108,$A15,1)="","",VALUE(LEFT(INDEX(設定!$F$9:$F$108,$A15,1),1))) | T15: =IF(C15="","",C15) | U15: =IF(D15="","",IF(D15="1：男",1,IF(D15="2：女",2))) | V15: =IF(E15="","",E15) | W15: =IF(AND(G15="",H15="",G16=""),"",ROUND(SUM(G15,H15/60)*G16,1)) | X15: =IF(AND(I15="",J15="",I16=""),"",ROUND(SUM(I15,J15/60)*I16,1)) | Y15: =IF(AND(K15="",L15="",K16=""),"",ROUND(SUM(K15,L15/60)*K16,1)) | AD15: 75歳以上 | AF15: =SUM(AF20,AF25,AF30) -> 0 | AG15: =SUM(AG20,AG25,AG30) -> 0 | AH15: =SUM(AH20,AH25,AH30) -> 0 | AI15: =SUM(AI20,AI25,AI30) -> 0 | AR15: =SUM(AR20,AR25,AR30) -> 0 | AS15: =SUM(AS20,AS25,AS30) -> 0 | AW15: 75歳以上 | AY15: =ROUND(AF15*$T$4*0.7,0) -> 0 | AZ15: =ROUND(AG15*$T$4*0.7,0) -> 0 | BE15: =(AP15+AR15)*$T$4*0.7 -> 0 | BF15: =(AQ15+AS15)*$T$4*0.7 -> 0
G16: =IF(SUM(G15:H15)>0,1,"") | I16: =IF(SUM(I15:J15)>0,1,"") | K16: =IF(SUM(K15:L15)>0,1,"") | AD16: 飼料の調理・ 給与・給水 | AF16: =SUM(AF17:AF20) -> 0 | AG16: =SUM(AG17:AG20) -> 0 | AL16: =AN16+AP16+AR16 -> 0 | AM16: =AO16+AQ16+AS16 -> 0 | AN16: =SUMIFS($W$11:$W$70,$S$11:$S$70,2,$U$11:$U$70,1) -> 0 | AO16: =SUMIFS($W$11:$W$70,$S$11:$S$70,2,$U$11:$U$70,2) -> 0 | AP16: =AP17 -> 0 | AQ16: =AQ17 -> 0 | AR16: =SUM(AR17:AR20) -> 0 | AS16: =SUM(AS17:AS20) -> 0 | AW16: 敷料搬入・ きゅう肥搬出 | AY16: =SUM(AY17:AY20) -> 0 | AZ16: =SUM(AZ17:AZ20) -> 0 | BA16: =ROUND(BC16+BE16,0) -> 0 | BB16: =ROUND(BD16+BF16,0) -> 0 | BC16: =IFERROR($T$112*($AN21/$AN$36),0) -> 0 | BD16: =IFERROR($T$113*($AO21/$AO$36),0) -> 0 | BE16: =SUM(BE17:BE20) -> 0 | BF16: =SUM(BF17:BF20) -> 0
A17: =ROUND((ROW()-10)/2,0) -> 4 | C17: =IF(INDEX(設定!$C$9:$C$108,$A17,1)="","",INDEX(設定!$C$9:$C$108,$A17,1)) | D17: =IF(INDEX(設定!$D$9:$D$108,$A17,1)="","",INDEX(設定!$D$9:$D$108,$A17,1)) | E17: =IF(INDEX(設定!$E$9:$E$108,$A17,1)="","",INDEX(設定!$E$9:$E$108,$A17,1)) | F17: =IF(S17="","",IF(S17=1,"1：家族",IF(AND(S17>=2,S17<=5),"2：雇用",""))) | G17: =INT(INDEX(設定!$H$9:H$108,$A17,1)) -> 0 | H17: =IF(INDEX(設定!$H$9:$H$108,$A17,1)=0,"",ROUND(MOD(INDEX(設定!$H$9:$H$108,$A17,1),1)*60,0)) | I17: =INT(INDEX(設定!$I$9:$I$108,$A17,1)) -> 0 | J17: =IF(INDEX(設定!$I$9:$I$108,$A17,1)=0,"",ROUND(MOD(INDEX(設定!$I$9:$I$108,$A17,1),1)*60,0)) | K17: =INT(INDEX(設定!$J$9:$J$108,$A17,1)) -> 0 | L17: =IF(INDEX(設定!$J$9:$J$108,$A17,1)=0,"",ROUND(MOD(INDEX(設定!$J$9:$J$108,$A17,1),1)*60,0)) | S17: =IF(INDEX(設定!$F$9:$F$108,$A17,1)="","",VALUE(LEFT(INDEX(設定!$F$9:$F$108,$A17,1),1))) | T17: =IF(C17="","",C17) | U17: =IF(D17="","",IF(D17="1：男",1,IF(D17="2：女",2))) | V17: =IF(E17="","",E17) | W17: =IF(AND(G17="",H17="",G18=""),"",ROUND(SUM(G17,H17/60)*G18,1)) | X17: =IF(AND(I17="",J17="",I18=""),"",ROUND(SUM(I17,J17/60)*I18,1)) | Y17: =IF(AND(K17="",L17="",K18=""),"",ROUND(SUM(K17,L17/60)*K18,1)) | AE17: 65歳未満 | AF17: =AH17+AJ17 -> 0 | AG17: =AI17+AK17 -> 0 | AH17: =SUMIFS($W$11:$W$70,$S$11:$S$70,1,$U$11:$U$70,1,$V$11:$V$70,"<65") -> 0 | AI17: =SUMIFS($W$11:$W$70,$S$11:$S$70,1,$U$11:$U$70,2,$V$11:$V$70,"<65") -> 0 | AJ17: =SUMIFS($W$11:$W$70,$S$11:$S$70,3,$U$11:$U$70,1) -> 0 | AK17: =SUMIFS($W$11:$W$70,$S$11:$S$70,3,$U$11:$U$70,2) -> 0 | AP17: =SUMIFS($W$11:$W$70,$S$11:$S$70,4,$U$11:$U$70,1) -> 0 | AQ17: =SUMIFS($W$11:$W$70,$S$11:$S$70,4,$U$11:$U$70,2) -> 0 | AR17: =SUMIFS($W$11:$W$70,$S$11:$S$70,5,$U$11:$U$70,1,$V$11:$V$70,"<65") -> 0 | AS17: =SUMIFS($W$11:$W$70,$S$11:$S$70,5,$U$11:$U$70,2,$V$11:$V$70,"<65") -> 0 | AX17: 65歳未満 | AY17: =ROUND(AF22*$T$4,0) -> 0 | AZ17: =ROUND(AG22*$T$4,0) -> 0 | BE17: =(AP22+AR22)*$T$4 -> 0 | BF17: =(AQ22+AS22)*$T$4 -> 0
G18: =IF(SUM(G17:H17)>0,1,"") | I18: =IF(SUM(I17:J17)>0,1,"") | K18: =IF(SUM(K17:L17)>0,1,"") | AE18: 65～70 | AF18: =AH18+AJ18 -> 0 | AG18: =AI18+AK18 -> 0 | AH18: =SUMIFS($W$11:$W$70,$S$11:$S$70,1,$U$11:$U$70,1,$V$11:$V$70,">=65",$V$11:$V$70,"<70") -> 0 | AI18: =SUMIFS($W$11:$W$70,$S$11:$S$70,1,$U$11:$U$70,2,$V$11:$V$70,">=65",$V$11:$V$70,"<70") -> 0 | AR18: =SUMIFS($W$11:$W$70,$S$11:$S$70,5,$U$11:$U$70,1,$V$11:$V$70,">=65",$V$11:$V$70,"<70") -> 0 | AS18: =SUMIFS($W$11:$W$70,$S$11:$S$70,5,$U$11:$U$70,2,$V$11:$V$70,">=65",$V$11:$V$70,"<70") -> 0 | AX18: 65～70 | AY18: =ROUND(AF23*$T$4*0.9,0) -> 0 | AZ18: =ROUND(AG23*$T$4*0.9,0) -> 0 | BE18: =(AR23)*$T$4*0.9 -> 0 | BF18: =(AS23)*$T$4*0.9 -> 0
A19: =ROUND((ROW()-10)/2,0) -> 5 | C19: =IF(INDEX(設定!$C$9:$C$108,$A19,1)="","",INDEX(設定!$C$9:$C$108,$A19,1)) | D19: =IF(INDEX(設定!$D$9:$D$108,$A19,1)="","",INDEX(設定!$D$9:$D$108,$A19,1)) | E19: =IF(INDEX(設定!$E$9:$E$108,$A19,1)="","",INDEX(設定!$E$9:$E$108,$A19,1)) | F19: =IF(S19="","",IF(S19=1,"1：家族",IF(AND(S19>=2,S19<=5),"2：雇用",""))) | G19: =INT(INDEX(設定!$H$9:H$108,$A19,1)) -> 0 | H19: =IF(INDEX(設定!$H$9:$H$108,$A19,1)=0,"",ROUND(MOD(INDEX(設定!$H$9:$H$108,$A19,1),1)*60,0)) | I19: =INT(INDEX(設定!$I$9:$I$108,$A19,1)) -> 0 | J19: =IF(INDEX(設定!$I$9:$I$108,$A19,1)=0,"",ROUND(MOD(INDEX(設定!$I$9:$I$108,$A19,1),1)*60,0)) | K19: =INT(INDEX(設定!$J$9:$J$108,$A19,1)) -> 0 | L19: =IF(INDEX(設定!$J$9:$J$108,$A19,1)=0,"",ROUND(MOD(INDEX(設定!$J$9:$J$108,$A19,1),1)*60,0)) | S19: =IF(INDEX(設定!$F$9:$F$108,$A19,1)="","",VALUE(LEFT(INDEX(設定!$F$9:$F$108,$A19,1),1))) | T19: =IF(C19="","",C19) | U19: =IF(D19="","",IF(D19="1：男",1,IF(D19="2：女",2))) | V19: =IF(E19="","",E19) | W19: =IF(AND(G19="",H19="",G20=""),"",ROUND(SUM(G19,H19/60)*G20,1)) | X19: =IF(AND(I19="",J19="",I20=""),"",ROUND(SUM(I19,J19/60)*I20,1)) | Y19: =IF(AND(K19="",L19="",K20=""),"",ROUND(SUM(K19,L19/60)*K20,1)) | AE19: 70～75 | AF19: =AH19+AJ19 -> 0 | AG19: =AI19+AK19 -> 0 | AH19: =SUMIFS($W$11:$W$70,$S$11:$S$70,1,$U$11:$U$70,1,$V$11:$V$70,">=70",$V$11:$V$70,"<75") -> 0 | AI19: =SUMIFS($W$11:$W$70,$S$11:$S$70,1,$U$11:$U$70,2,$V$11:$V$70,">=70",$V$11:$V$70,"<75") -> 0 | AR19: =SUMIFS($W$11:$W$70,$S$11:$S$70,5,$U$11:$U$70,1,$V$11:$V$70,">=70",$V$11:$V$70,"<75") -> 0 | AS19: =SUMIFS($W$11:$W$70,$S$11:$S$70,5,$U$11:$U$70,2,$V$11:$V$70,">=70",$V$11:$V$70,"<75") -> 0 | AX19: 70～75 | AY19: =ROUND(AF24*$T$4*0.8,0) -> 0 | AZ19: =ROUND(AG24*$T$4*0.8,0) -> 0 | BE19: =(AR24)*$T$4*0.8 -> 0 | BF19: =(AS24)*$T$4*0.8 -> 0
G20: =IF(SUM(G19:H19)>0,1,"") | I20: =IF(SUM(I19:J19)>0,1,"") | K20: =IF(SUM(K19:L19)>0,1,"") | AE20: 75歳以上 | AF20: =AH20+AJ20 -> 0 | AG20: =AI20+AK20 -> 0 | AH20: =SUMIFS($W$11:$W$70,$S$11:$S$70,1,$U$11:$U$70,1,$V$11:$V$70,">=75") -> 0 | AI20: =SUMIFS($W$11:$W$70,$S$11:$S$70,1,$U$11:$U$70,2,$V$11:$V$70,">=75") -> 0 | AR20: =SUMIFS($W$11:$W$70,$S$11:$S$70,5,$U$11:$U$70,1,$V$11:$V$70,">=75") -> 0 | AS20: =SUMIFS($W$11:$W$70,$S$11:$S$70,5,$U$11:$U$70,2,$V$11:$V$70,">=75") -> 0 | AX20: 75歳以上 | AY20: =ROUND(AF25*$T$4*0.7,0) -> 0 | AZ20: =ROUND(AG25*$T$4*0.7,0) -> 0 | BE20: =(AR25)*$T$4*0.7 -> 0 | BF20: =(AS25)*$T$4*0.7 -> 0
A21: =ROUND((ROW()-10)/2,0) -> 6 | C21: =IF(INDEX(設定!$C$9:$C$108,$A21,1)="","",INDEX(設定!$C$9:$C$108,$A21,1)) | D21: =IF(INDEX(設定!$D$9:$D$108,$A21,1)="","",INDEX(設定!$D$9:$D$108,$A21,1)) | E21: =IF(INDEX(設定!$E$9:$E$108,$A21,1)="","",INDEX(設定!$E$9:$E$108,$A21,1)) | F21: =IF(S21="","",IF(S21=1,"1：家族",IF(AND(S21>=2,S21<=5),"2：雇用",""))) | G21: =INT(INDEX(設定!$H$9:H$108,$A21,1)) -> 0 | H21: =IF(INDEX(設定!$H$9:$H$108,$A21,1)=0,"",ROUND(MOD(INDEX(設定!$H$9:$H$108,$A21,1),1)*60,0)) | I21: =INT(INDEX(設定!$I$9:$I$108,$A21,1)) -> 0 | J21: =IF(INDEX(設定!$I$9:$I$108,$A21,1)=0,"",ROUND(MOD(INDEX(設定!$I$9:$I$108,$A21,1),1)*60,0)) | K21: =INT(INDEX(設定!$J$9:$J$108,$A21,1)) -> 0 | L21: =IF(INDEX(設定!$J$9:$J$108,$A21,1)=0,"",ROUND(MOD(INDEX(設定!$J$9:$J$108,$A21,1),1)*60,0)) | S21: =IF(INDEX(設定!$F$9:$F$108,$A21,1)="","",VALUE(LEFT(INDEX(設定!$F$9:$F$108,$A21,1),1))) | T21: =IF(C21="","",C21) | U21: =IF(D21="","",IF(D21="1：男",1,IF(D21="2：女",2))) | V21: =IF(E21="","",E21) | W21: =IF(AND(G21="",H21="",G22=""),"",ROUND(SUM(G21,H21/60)*G22,1)) | X21: =IF(AND(I21="",J21="",I22=""),"",ROUND(SUM(I21,J21/60)*I22,1)) | Y21: =IF(AND(K21="",L21="",K22=""),"",ROUND(SUM(K21,L21/60)*K22,1)) | AD21: 敷料搬入・ きゅう肥搬出 | AF21: =SUM(AF22:AF25) -> 0 | AG21: =SUM(AG22:AG25) -> 0 | AL21: =AN21+AP21+AR21 -> 0 | AM21: =AO21+AQ21+AS21 -> 0 | AN21: =SUMIFS($X$11:$X$70,$S$11:$S$70,2,$U$11:$U$70,1) -> 0 | AO21: =SUMIFS($X$11:$X$70,$S$11:$S$70,2,$U$11:$U$70,2) -> 0 | AP21: =AP22 -> 0 | AQ21: =AQ22 -> 0 | AR21: =SUM(AR22:AR25) -> 0 | AS21: =SUM(AS22:AS25) -> 0
G22: =IF(SUM(G21:H21)>0,1,"") | I22: =IF(SUM(I21:J21)>0,1,"") | K22: =IF(SUM(K21:L21)>0,1,"") | AE22: 65歳未満 | AF22: =AH22+AJ22 -> 0 | AG22: =AI22+AK22 -> 0 | AH22: =SUMIFS($X$11:$X$70,$S$11:$S$70,1,$U$11:$U$70,1,$V$11:$V$70,"<65") -> 0 | AI22: =SUMIFS($X$11:$X$70,$S$11:$S$70,1,$U$11:$U$70,2,$V$11:$V$70,"<65") -> 0 | AJ22: =SUMIFS($X$11:$X$70,$S$11:$S$70,3,$U$11:$U$70,1) -> 0 | AK22: =SUMIFS($X$11:$X$70,$S$11:$S$70,3,$U$11:$U$70,2) -> 0 | AP22: =SUMIFS($X$11:$X$70,$S$11:$S$70,4,$U$11:$U$70,1) -> 0 | AQ22: =SUMIFS($X$11:$X$70,$S$11:$S$70,4,$U$11:$U$70,2) -> 0 | AR22: =SUMIFS($X$11:$X$70,$S$11:$S$70,5,$U$11:$U$70,1,$V$11:$V$70,"<65") -> 0 | AS22: =SUMIFS($X$11:$X$70,$S$11:$S$70,5,$U$11:$U$70,2,$V$11:$V$70,"<65") -> 0
A23: =ROUND((ROW()-10)/2,0) -> 7 | C23: =IF(INDEX(設定!$C$9:$C$108,$A23,1)="","",INDEX(設定!$C$9:$C$108,$A23,1)) | D23: =IF(INDEX(設定!$D$9:$D$108,$A23,1)="","",INDEX(設定!$D$9:$D$108,$A23,1)) | E23: =IF(INDEX(設定!$E$9:$E$108,$A23,1)="","",INDEX(設定!$E$9:$E$108,$A23,1)) | F23: =IF(S23="","",IF(S23=1,"1：家族",IF(AND(S23>=2,S23<=5),"2：雇用",""))) | G23: =INT(INDEX(設定!$H$9:H$108,$A23,1)) -> 0 | H23: =IF(INDEX(設定!$H$9:$H$108,$A23,1)=0,"",ROUND(MOD(INDEX(設定!$H$9:$H$108,$A23,1),1)*60,0)) | I23: =INT(INDEX(設定!$I$9:$I$108,$A23,1)) -> 0 | J23: =IF(INDEX(設定!$I$9:$I$108,$A23,1)=0,"",ROUND(MOD(INDEX(設定!$I$9:$I$108,$A23,1),1)*60,0)) | K23: =INT(INDEX(設定!$J$9:$J$108,$A23,1)) -> 0 | L23: =IF(INDEX(設定!$J$9:$J$108,$A23,1)=0,"",ROUND(MOD(INDEX(設定!$J$9:$J$108,$A23,1),1)*60,0)) | S23: =IF(INDEX(設定!$F$9:$F$108,$A23,1)="","",VALUE(LEFT(INDEX(設定!$F$9:$F$108,$A23,1),1))) | T23: =IF(C23="","",C23) | U23: =IF(D23="","",IF(D23="1：男",1,IF(D23="2：女",2))) | V23: =IF(E23="","",E23) | W23: =IF(AND(G23="",H23="",G24=""),"",ROUND(SUM(G23,H23/60)*G24,1)) | X23: =IF(AND(I23="",J23="",I24=""),"",ROUND(SUM(I23,J23/60)*I24,1)) | Y23: =IF(AND(K23="",L23="",K24=""),"",ROUND(SUM(K23,L23/60)*K24,1)) | AE23: 65～70 | AF23: =AH23+AJ23 -> 0 | AG23: =AI23+AK23 -> 0 | AH23: =SUMIFS($X$11:$X$70,$S$11:$S$70,1,$U$11:$U$70,1,$V$11:$V$70,">=65",$V$11:$V$70,"<70") -> 0 | AI23: =SUMIFS($X$11:$X$70,$S$11:$S$70,1,$U$11:$U$70,2,$V$11:$V$70,">=65",$V$11:$V$70,"<70") -> 0 | AR23: =SUMIFS($X$11:$X$70,$S$11:$S$70,5,$U$11:$U$70,1,$V$11:$V$70,">=65",$V$11:$V$70,"<70") -> 0 | AS23: =SUMIFS($X$11:$X$70,$S$11:$S$70,5,$U$11:$U$70,2,$V$11:$V$70,">=65",$V$11:$V$70,"<70") -> 0
G24: =IF(SUM(G23:H23)>0,1,"") | I24: =IF(SUM(I23:J23)>0,1,"") | K24: =IF(SUM(K23:L23)>0,1,"") | AE24: 70～75 | AF24: =AH24+AJ24 -> 0 | AG24: =AI24+AK24 -> 0 | AH24: =SUMIFS($X$11:$X$70,$S$11:$S$70,1,$U$11:$U$70,1,$V$11:$V$70,">=70",$V$11:$V$70,"<75") -> 0 | AI24: =SUMIFS($X$11:$X$70,$S$11:$S$70,1,$U$11:$U$70,2,$V$11:$V$70,">=70",$V$11:$V$70,"<75") -> 0 | AR24: =SUMIFS($X$11:$X$70,$S$11:$S$70,5,$U$11:$U$70,1,$V$11:$V$70,">=70",$V$11:$V$70,"<75") -> 0 | AS24: =SUMIFS($X$11:$X$70,$S$11:$S$70,5,$U$11:$U$70,2,$V$11:$V$70,">=70",$V$11:$V$70,"<75") -> 0
A25: =ROUND((ROW()-10)/2,0) -> 8 | C25: =IF(INDEX(設定!$C$9:$C$108,$A25,1)="","",INDEX(設定!$C$9:$C$108,$A25,1)) | D25: =IF(INDEX(設定!$D$9:$D$108,$A25,1)="","",INDEX(設定!$D$9:$D$108,$A25,1)) | E25: =IF(INDEX(設定!$E$9:$E$108,$A25,1)="","",INDEX(設定!$E$9:$E$108,$A25,1)) | F25: =IF(S25="","",IF(S25=1,"1：家族",IF(AND(S25>=2,S25<=5),"2：雇用",""))) | G25: =INT(INDEX(設定!$H$9:H$108,$A25,1)) -> 0 | H25: =IF(INDEX(設定!$H$9:$H$108,$A25,1)=0,"",ROUND(MOD(INDEX(設定!$H$9:$H$108,$A25,1),1)*60,0)) | I25: =INT(INDEX(設定!$I$9:$I$108,$A25,1)) -> 0 | J25: =IF(INDEX(設定!$I$9:$I$108,$A25,1)=0,"",ROUND(MOD(INDEX(設定!$I$9:$I$108,$A25,1),1)*60,0)) | K25: =INT(INDEX(設定!$J$9:$J$108,$A25,1)) -> 0 | L25: =IF(INDEX(設定!$J$9:$J$108,$A25,1)=0,"",ROUND(MOD(INDEX(設定!$J$9:$J$108,$A25,1),1)*60,0)) | S25: =IF(INDEX(設定!$F$9:$F$108,$A25,1)="","",VALUE(LEFT(INDEX(設定!$F$9:$F$108,$A25,1),1))) | T25: =IF(C25="","",C25) | U25: =IF(D25="","",IF(D25="1：男",1,IF(D25="2：女",2))) | V25: =IF(E25="","",E25) | W25: =IF(AND(G25="",H25="",G26=""),"",ROUND(SUM(G25,H25/60)*G26,1)) | X25: =IF(AND(I25="",J25="",I26=""),"",ROUND(SUM(I25,J25/60)*I26,1)) | Y25: =IF(AND(K25="",L25="",K26=""),"",ROUND(SUM(K25,L25/60)*K26,1)) | AE25: 75歳以上 | AF25: =AH25+AJ25 -> 0 | AG25: =AI25+AK25 -> 0 | AH25: =SUMIFS($X$11:$X$70,$S$11:$S$70,1,$U$11:$U$70,1,$V$11:$V$70,">=75") -> 0 | AI25: =SUMIFS($X$11:$X$70,$S$11:$S$70,1,$U$11:$U$70,2,$V$11:$V$70,">=75") -> 0 | AR25: =SUMIFS($X$11:$X$70,$S$11:$S$70,5,$U$11:$U$70,1,$V$11:$V$70,">=75") -> 0 | AS25: =SUMIFS($X$11:$X$70,$S$11:$S$70,5,$U$11:$U$70,2,$V$11:$V$70,">=75") -> 0
G26: =IF(SUM(G25:H25)>0,1,"") | I26: =IF(SUM(I25:J25)>0,1,"") | K26: =IF(SUM(K25:L25)>0,1,"") | AD26: その他の 飼育作業 | AF26: =SUM(AF27:AF30) -> 0 | AG26: =SUM(AG27:AG30) -> 0 | AL26: =AN26+AP26+AR26 -> 0 | AM26: =AO26+AQ26+AS26 -> 0 | AN26: =SUMIFS($Y$11:$Y$70,$S$11:$S$70,2,$U$11:$U$70,1) -> 0 | AO26: =SUMIFS($Y$11:$Y$70,$S$11:$S$70,2,$U$11:$U$70,2) -> 0 | AP26: =AP27 -> 0 | AQ26: =AQ27 -> 0 | AR26: =SUM(AR27:AR30) -> 0 | AS26: =SUM(AS27:AS30) -> 0
A27: =ROUND((ROW()-10)/2,0) -> 9 | C27: =IF(INDEX(設定!$C$9:$C$108,$A27,1)="","",INDEX(設定!$C$9:$C$108,$A27,1)) | D27: =IF(INDEX(設定!$D$9:$D$108,$A27,1)="","",INDEX(設定!$D$9:$D$108,$A27,1)) | E27: =IF(INDEX(設定!$E$9:$E$108,$A27,1)="","",INDEX(設定!$E$9:$E$108,$A27,1)) | F27: =IF(S27="","",IF(S27=1,"1：家族",IF(AND(S27>=2,S27<=5),"2：雇用",""))) | G27: =INT(INDEX(設定!$H$9:H$108,$A27,1)) -> 0 | H27: =IF(INDEX(設定!$H$9:$H$108,$A27,1)=0,"",ROUND(MOD(INDEX(設定!$H$9:$H$108,$A27,1),1)*60,0)) | I27: =INT(INDEX(設定!$I$9:$I$108,$A27,1)) -> 0 | J27: =IF(INDEX(設定!$I$9:$I$108,$A27,1)=0,"",ROUND(MOD(INDEX(設定!$I$9:$I$108,$A27,1),1)*60,0)) | K27: =INT(INDEX(設定!$J$9:$J$108,$A27,1)) -> 0 | L27: =IF(INDEX(設定!$J$9:$J$108,$A27,1)=0,"",ROUND(MOD(INDEX(設定!$J$9:$J$108,$A27,1),1)*60,0)) | S27: =IF(INDEX(設定!$F$9:$F$108,$A27,1)="","",VALUE(LEFT(INDEX(設定!$F$9:$F$108,$A27,1),1))) | T27: =IF(C27="","",C27) | U27: =IF(D27="","",IF(D27="1：男",1,IF(D27="2：女",2))) | V27: =IF(E27="","",E27) | W27: =IF(AND(G27="",H27="",G28=""),"",ROUND(SUM(G27,H27/60)*G28,1)) | X27: =IF(AND(I27="",J27="",I28=""),"",ROUND(SUM(I27,J27/60)*I28,1)) | Y27: =IF(AND(K27="",L27="",K28=""),"",ROUND(SUM(K27,L27/60)*K28,1)) | AE27: 65歳未満 | AF27: =AH27+AJ27 -> 0 | AG27: =AI27+AK27 -> 0 | AH27: =SUMIFS($Y$11:$Y$70,$S$11:$S$70,1,$U$11:$U$70,1,$V$11:$V$70,"<65")+SUMIFS($W$77:$W$106,$S$77:$S$106,1,$U$77:$U$106,1,$V$77:$V$106,"<65") -> 0 | AI27: =SUMIFS($Y$11:$Y$70,$S$11:$S$70,1,$U$11:$U$70,2,$V$11:$V$70,"<65")+SUMIFS($W$77:$W$106,$S$77:$S$106,1,$U$77:$U$106,2,$V$77:$V$106,"<65") -> 0 | AJ27: =SUMIFS($Y$11:$Y$70,$S$11:$S$70,3,$U$11:$U$70,1) +SUMIFS($Y$77:$Y$106,$S$77:$S$106,3,$U$77:$U$106,1) -> 0 | AK27: =SUMIFS($Y$11:$Y$70,$S$11:$S$70,3,$U$11:$U$70,2) +SUMIFS($Y$77:$Y$106,$S$77:$S$106,3,$U$77:$U$106,2) -> 0 | AP27: =SUMIFS($Y$11:$Y$70,$S$11:$S$70,4,$U$11:$U$70,1) +SUMIFS($Y$77:$Y$106,$S$77:$S$106,4,$U$77:$U$106,1) -> 0 | AQ27: =SUMIFS($Y$11:$Y$70,$S$11:$S$70,4,$U$11:$U$70,2) +SUMIFS($Y$77:$Y$106,$S$77:$S$106,4,$U$77:$U$106,2) -> 0 | AR27: =SUMIFS($Y$11:$Y$70,$S$11:$S$70,5,$U$11:$U$70,1,$V$11:$V$70,"<65") -> 0 | AS27: =SUMIFS($Y$11:$Y$70,$S$11:$S$70,5,$U$11:$U$70,2,$V$11:$V$70,"<65") -> 0
G28: =IF(SUM(G27:H27)>0,1,"") | I28: =IF(SUM(I27:J27)>0,1,"") | K28: =IF(SUM(K27:L27)>0,1,"") | AE28: 65～70 | AF28: =AH28+AJ28 -> 0 | AG28: =AI28+AK28 -> 0 | AH28: =SUMIFS($Y$11:$Y$70,$S$11:$S$70,1,$U$11:$U$70,1,$V$11:$V$70,">=65",$V$11:$V$70,"<70")+SUMIFS($W$77:$W$106,$S$77:$S$106,1,$U$77:$U$106,1,$V$77:$V$106,">=65",$V$77:$V$106,"<70") -> 0 | AI28: =SUMIFS($Y$11:$Y$70,$S$11:$S$70,1,$U$11:$U$70,2,$V$11:$V$70,">=65",$V$11:$V$70,"<70")+SUMIFS($W$77:$W$106,$S$77:$S$106,1,$U$77:$U$106,2,$V$77:$V$106,">=65",$V$77:$V$106,"<70") -> 0 | AR28: =SUMIFS($Y$11:$Y$70,$S$11:$S$70,5,$U$11:$U$70,1,$V$11:$V$70,">=65",$V$11:$V$70,"<70") -> 0 | AS28: =SUMIFS($Y$11:$Y$70,$S$11:$S$70,5,$U$11:$U$70,2,$V$11:$V$70,">=65",$V$11:$V$70,"<70") -> 0
A29: =ROUND((ROW()-10)/2,0) -> 10 | C29: =IF(INDEX(設定!$C$9:$C$108,$A29,1)="","",INDEX(設定!$C$9:$C$108,$A29,1)) | D29: =IF(INDEX(設定!$D$9:$D$108,$A29,1)="","",INDEX(設定!$D$9:$D$108,$A29,1)) | E29: =IF(INDEX(設定!$E$9:$E$108,$A29,1)="","",INDEX(設定!$E$9:$E$108,$A29,1)) | F29: =IF(S29="","",IF(S29=1,"1：家族",IF(AND(S29>=2,S29<=5),"2：雇用",""))) | G29: =INT(INDEX(設定!$H$9:H$108,$A29,1)) -> 0 | H29: =IF(INDEX(設定!$H$9:$H$108,$A29,1)=0,"",ROUND(MOD(INDEX(設定!$H$9:$H$108,$A29,1),1)*60,0)) | I29: =INT(INDEX(設定!$I$9:$I$108,$A29,1)) -> 0 | J29: =IF(INDEX(設定!$I$9:$I$108,$A29,1)=0,"",ROUND(MOD(INDEX(設定!$I$9:$I$108,$A29,1),1)*60,0)) | K29: =INT(INDEX(設定!$J$9:$J$108,$A29,1)) -> 0 | L29: =IF(INDEX(設定!$J$9:$J$108,$A29,1)=0,"",ROUND(MOD(INDEX(設定!$J$9:$J$108,$A29,1),1)*60,0)) | S29: =IF(INDEX(設定!$F$9:$F$108,$A29,1)="","",VALUE(LEFT(INDEX(設定!$F$9:$F$108,$A29,1),1))) | T29: =IF(C29="","",C29) | U29: =IF(D29="","",IF(D29="1：男",1,IF(D29="2：女",2))) | V29: =IF(E29="","",E29) | W29: =IF(AND(G29="",H29="",G30=""),"",ROUND(SUM(G29,H29/60)*G30,1)) | X29: =IF(AND(I29="",J29="",I30=""),"",ROUND(SUM(I29,J29/60)*I30,1)) | Y29: =IF(AND(K29="",L29="",K30=""),"",ROUND(SUM(K29,L29/60)*K30,1)) | AE29: 70～75 | AF29: =AH29+AJ29 -> 0 | AG29: =AI29+AK29 -> 0 | AH29: =SUMIFS($Y$11:$Y$70,$S$11:$S$70,1,$U$11:$U$70,1,$V$11:$V$70,">=70",$V$11:$V$70,"<75")+SUMIFS($W$77:$W$106,$S$77:$S$106,1,$U$77:$U$106,1,$V$77:$V$106,">=70",$V$77:$V$106,"<75") -> 0 | AI29: =SUMIFS($Y$11:$Y$70,$S$11:$S$70,1,$U$11:$U$70,2,$V$11:$V$70,">=70",$V$11:$V$70,"<75")+SUMIFS($W$77:$W$106,$S$77:$S$106,1,$U$77:$U$106,2,$V$77:$V$106,">=70",$V$77:$V$106,"<75") -> 0 | AR29: =SUMIFS($Y$11:$Y$70,$S$11:$S$70,5,$U$11:$U$70,1,$V$11:$V$70,">=70",$V$11:$V$70,"<75") -> 0 | AS29: =SUMIFS($Y$11:$Y$70,$S$11:$S$70,5,$U$11:$U$70,2,$V$11:$V$70,">=70",$V$11:$V$70,"<75") -> 0
G30: =IF(SUM(G29:H29)>0,1,"") | I30: =IF(SUM(I29:J29)>0,1,"") | K30: =IF(SUM(K29:L29)>0,1,"") | AE30: 75歳以上 | AF30: =AH30+AJ30 -> 0 | AG30: =AI30+AK30 -> 0 | AH30: =SUMIFS($Y$11:$Y$70,$S$11:$S$70,1,$U$11:$U$70,1,$V$11:$V$70,">=75")+SUMIFS($W$77:$W$106,$S$77:$S$106,1,$U$77:$U$106,1,$V$77:$V$106,">=75") -> 0 | AI30: =SUMIFS($Y$11:$Y$70,$S$11:$S$70,1,$U$11:$U$70,2,$V$11:$V$70,">=75")+SUMIFS($W$77:$W$106,$S$77:$S$106,1,$U$77:$U$106,2,$V$77:$V$106,">=75") -> 0 | AR30: =SUMIFS($Y$11:$Y$70,$S$11:$S$70,5,$U$11:$U$70,1,$V$11:$V$70,">=75") -> 0 | AS30: =SUMIFS($Y$11:$Y$70,$S$11:$S$70,5,$U$11:$U$70,2,$V$11:$V$70,">=75") -> 0
A31: =ROUND((ROW()-10)/2,0) -> 11 | C31: =IF(INDEX(設定!$C$9:$C$108,$A31,1)="","",INDEX(設定!$C$9:$C$108,$A31,1)) | D31: =IF(INDEX(設定!$D$9:$D$108,$A31,1)="","",INDEX(設定!$D$9:$D$108,$A31,1)) | E31: =IF(INDEX(設定!$E$9:$E$108,$A31,1)="","",INDEX(設定!$E$9:$E$108,$A31,1)) | F31: =IF(S31="","",IF(S31=1,"1：家族",IF(AND(S31>=2,S31<=5),"2：雇用",""))) | G31: =INT(INDEX(設定!$H$9:H$108,$A31,1)) -> 0 | H31: =IF(INDEX(設定!$H$9:$H$108,$A31,1)=0,"",ROUND(MOD(INDEX(設定!$H$9:$H$108,$A31,1),1)*60,0)) | I31: =INT(INDEX(設定!$I$9:$I$108,$A31,1)) -> 0 | J31: =IF(INDEX(設定!$I$9:$I$108,$A31,1)=0,"",ROUND(MOD(INDEX(設定!$I$9:$I$108,$A31,1),1)*60,0)) | K31: =INT(INDEX(設定!$J$9:$J$108,$A31,1)) -> 0 | L31: =IF(INDEX(設定!$J$9:$J$108,$A31,1)=0,"",ROUND(MOD(INDEX(設定!$J$9:$J$108,$A31,1),1)*60,0)) | S31: =IF(INDEX(設定!$F$9:$F$108,$A31,1)="","",VALUE(LEFT(INDEX(設定!$F$9:$F$108,$A31,1),1))) | T31: =IF(C31="","",C31) | U31: =IF(D31="","",IF(D31="1：男",1,IF(D31="2：女",2))) | V31: =IF(E31="","",E31) | W31: =IF(AND(G31="",H31="",G32=""),"",ROUND(SUM(G31,H31/60)*G32,1)) | X31: =IF(AND(I31="",J31="",I32=""),"",ROUND(SUM(I31,J31/60)*I32,1)) | Y31: =IF(AND(K31="",L31="",K32=""),"",ROUND(SUM(K31,L31/60)*K32,1)) | AC31: 間接労働時間 | AF31: =SUM(AF32:AF35) -> 0 | AG31: =SUM(AG32:AG35) -> 0 | AL31: =AN31+AP31+AR31 -> 0 | AM31: =AO31+AQ31+AS31 -> 0 | AN31: =SUMIFS($X$77:$X$106,$S$77:$S$106,2,$U$77:$U$106,1)+SUMIFS($Y$77:$Y$106,$S$77:$S$106,2,$U$77:$U$106,1) -> 0 | AO31: =SUMIFS($X$77:$X$106,$S$77:$S$106,2,$U$77:$U$106,2)+SUMIFS($Y$77:$Y$106,$S$77:$S$106,2,$U$77:$U$106,2) -> 0 | AP31: =AP32 -> 0 | AQ31: =AQ32 -> 0 | AR31: =SUM(AR32:AR35) -> 0 | AS31: =SUM(AS32:AS35) -> 0 | AV31: 間接労働費 | AY31: =SUM(AY32:AY35) -> 0 | AZ31: =SUM(AZ32:AZ35) -> 0 | BA31: =ROUND(BC31+BE31,0) -> 0 | BB31: =ROUND(BD31+BF31,0) -> 0 | BC31: =IFERROR($T$112*($AN31/$AN$36),0) -> 0 | BD31: =IFERROR($T$113*($AO31/$AO$36),0) -> 0 | BE31: =SUM(BE32:BE35) -> 0 | BF31: =SUM(BF32:BF35) -> 0
G32: =IF(SUM(G31:H31)>0,1,"") | I32: =IF(SUM(I31:J31)>0,1,"") | K32: =IF(SUM(K31:L31)>0,1,"") | AD32: 65歳未満 | AF32: =AH32+AJ32 -> 0 | AG32: =AI32+AK32 -> 0 | AH32: =SUMIFS($X$77:$X$106,$S$77:$S$106,1,$U$77:$U$106,1,$V$77:$V$106,"<65")+SUMIFS($Y$77:$Y$106,$S$77:$S$106,1,$U$77:$U$106,1,$V$77:$V$106,"<65") -> 0 | AI32: =SUMIFS($X$77:$X$106,$S$77:$S$106,1,$U$77:$U$106,2,$V$77:$V$106,"<65")+SUMIFS($Y$77:$Y$106,$S$77:$S$106,1,$U$77:$U$106,2,$V$77:$V$106,"<65") -> 0 | AJ32: =SUMIFS($X$77:$X$106,$S$77:$S$106,3,$U$77:$U$106,1) -> 0 | AK32: =SUMIFS($X$77:$X$106,$S$77:$S$106,3,$U$77:$U$106,2) -> 0 | AP32: =SUMIFS($X$77:$X$106,$S$77:$S$106,4,$U$77:$U$106,1) -> 0 | AQ32: =SUMIFS($X$77:$X$106,$S$77:$S$106,4,$U$77:$U$106,2) -> 0 | AR32: =SUMIFS($X$77:$X$106,$S$77:$S$106,5,$U$77:$U$106,1,$V$77:$V$106,"<65")+SUMIFS($Y$77:$Y$106,$S$77:$S$106,5,$U$77:$U$106,1,$V$77:$V$106,"<65") -> 0 | AS32: =SUMIFS($X$77:$X$106,$S$77:$S$106,5,$U$77:$U$106,2,$V$77:$V$106,"<65")+SUMIFS($Y$77:$Y$106,$S$77:$S$106,5,$U$77:$U$106,2,$V$77:$V$106,"<65") -> 0 | AW32: 65歳未満 | AY32: =ROUND(AF32*$T$4,0) -> 0 | AZ32: =ROUND(AG32*$T$4,0) -> 0 | BE32: =(AP32+AR32)*$T$4 -> 0 | BF32: =(AQ32+AS32)*$T$4 -> 0
A33: =ROUND((ROW()-10)/2,0) -> 12 | C33: =IF(INDEX(設定!$C$9:$C$108,$A33,1)="","",INDEX(設定!$C$9:$C$108,$A33,1)) | D33: =IF(INDEX(設定!$D$9:$D$108,$A33,1)="","",INDEX(設定!$D$9:$D$108,$A33,1)) | E33: =IF(INDEX(設定!$E$9:$E$108,$A33,1)="","",INDEX(設定!$E$9:$E$108,$A33,1)) | F33: =IF(S33="","",IF(S33=1,"1：家族",IF(AND(S33>=2,S33<=5),"2：雇用",""))) | G33: =INT(INDEX(設定!$H$9:H$108,$A33,1)) -> 0 | H33: =IF(INDEX(設定!$H$9:$H$108,$A33,1)=0,"",ROUND(MOD(INDEX(設定!$H$9:$H$108,$A33,1),1)*60,0)) | I33: =INT(INDEX(設定!$I$9:$I$108,$A33,1)) -> 0 | J33: =IF(INDEX(設定!$I$9:$I$108,$A33,1)=0,"",ROUND(MOD(INDEX(設定!$I$9:$I$108,$A33,1),1)*60,0)) | K33: =INT(INDEX(設定!$J$9:$J$108,$A33,1)) -> 0 | L33: =IF(INDEX(設定!$J$9:$J$108,$A33,1)=0,"",ROUND(MOD(INDEX(設定!$J$9:$J$108,$A33,1),1)*60,0)) | S33: =IF(INDEX(設定!$F$9:$F$108,$A33,1)="","",VALUE(LEFT(INDEX(設定!$F$9:$F$108,$A33,1),1))) | T33: =IF(C33="","",C33) | U33: =IF(D33="","",IF(D33="1：男",1,IF(D33="2：女",2))) | V33: =IF(E33="","",E33) | W33: =IF(AND(G33="",H33="",G34=""),"",ROUND(SUM(G33,H33/60)*G34,1)) | X33: =IF(AND(I33="",J33="",I34=""),"",ROUND(SUM(I33,J33/60)*I34,1)) | Y33: =IF(AND(K33="",L33="",K34=""),"",ROUND(SUM(K33,L33/60)*K34,1)) | AD33: 65～70 | AF33: =AH33+AJ33 -> 0 | AG33: =AI33+AK33 -> 0 | AH33: =SUMIFS($X$77:$X$106,$S$77:$S$106,1,$U$77:$U$106,1,$V$77:$V$106,">=65",$V$77:$V$106,"<70")+SUMIFS($Y$77:$Y$106,$S$77:$S$106,1,$U$77:$U$106,1,$V$77:$V$106,">=65",$V$77:$V$106,"<70") -> 0 | AI33: =SUMIFS($X$77:$X$106,$S$77:$S$106,1,$U$77:$U$106,2,$V$77:$V$106,">=65",$V$77:$V$106,"<70")+SUMIFS($Y$77:$Y$106,$S$77:$S$106,1,$U$77:$U$106,2,$V$77:$V$106,">=65",$V$77:$V$106,"<70") -> 0 | AR33: =SUMIFS($X$77:$X$106,$S$77:$S$106,5,$U$77:$U$106,1,$V$77:$V$106,">=65",$V$77:$V$106,"<70")+SUMIFS($Y$77:$Y$106,$S$77:$S$106,5,$U$77:$U$106,1,$V$77:$V$106,">=65",$V$77:$V$106,"<70") -> 0 | AS33: =SUMIFS($X$77:$X$106,$S$77:$S$106,5,$U$77:$U$106,2,$V$77:$V$106,">=65",$V$77:$V$106,"<70")+SUMIFS($Y$77:$Y$106,$S$77:$S$106,5,$U$77:$U$106,2,$V$77:$V$106,">=65",$V$77:$V$106,"<70") -> 0 | AW33: 65～70 | AY33: =ROUND(AF33*$T$4*0.9,0) -> 0 | AZ33: =ROUND(AG33*$T$4*0.9,0) -> 0 | BE33: =AR33*$T$4*0.9 -> 0 | BF33: =AS33*$T$4*0.9 -> 0
G34: =IF(SUM(G33:H33)>0,1,"") | I34: =IF(SUM(I33:J33)>0,1,"") | K34: =IF(SUM(K33:L33)>0,1,"") | AD34: 70～75 | AF34: =AH34+AJ34 -> 0 | AG34: =AI34+AK34 -> 0 | AH34: =SUMIFS($X$77:$X$106,$S$77:$S$106,1,$U$77:$U$106,1,$V$77:$V$106,">=70",$V$77:$V$106,"<75")+SUMIFS($Y$77:$Y$106,$S$77:$S$106,1,$U$77:$U$106,1,$V$77:$V$106,">=70",$V$77:$V$106,"<75") -> 0 | AI34: =SUMIFS($X$77:$X$106,$S$77:$S$106,1,$U$77:$U$106,2,$V$77:$V$106,">=70",$V$77:$V$106,"<75")+SUMIFS($Y$77:$Y$106,$S$77:$S$106,1,$U$77:$U$106,2,$V$77:$V$106,">=70",$V$77:$V$106,"<75") -> 0 | AR34: =SUMIFS($X$77:$X$106,$S$77:$S$106,5,$U$77:$U$106,1,$V$77:$V$106,">=70",$V$77:$V$106,"<75")+SUMIFS($Y$77:$Y$106,$S$77:$S$106,5,$U$77:$U$106,1,$V$77:$V$106,">=70",$V$77:$V$106,"<75") -> 0 | AS34: =SUMIFS($X$77:$X$106,$S$77:$S$106,5,$U$77:$U$106,2,$V$77:$V$106,">=70",$V$77:$V$106,"<75")+SUMIFS($Y$77:$Y$106,$S$77:$S$106,5,$U$77:$U$106,2,$V$77:$V$106,">=70",$V$77:$V$106,"<75") -> 0 | AW34: 70～75 | AY34: =ROUND(AF34*$T$4*0.8,0) -> 0 | AZ34: =ROUND(AG34*$T$4*0.8,0) -> 0 | BE34: =AR34*$T$4*0.8 -> 0 | BF34: =AS34*$T$4*0.8 -> 0
A35: =ROUND((ROW()-10)/2,0) -> 13 | C35: =IF(INDEX(設定!$C$9:$C$108,$A35,1)="","",INDEX(設定!$C$9:$C$108,$A35,1)) | D35: =IF(INDEX(設定!$D$9:$D$108,$A35,1)="","",INDEX(設定!$D$9:$D$108,$A35,1)) | E35: =IF(INDEX(設定!$E$9:$E$108,$A35,1)="","",INDEX(設定!$E$9:$E$108,$A35,1)) | F35: =IF(S35="","",IF(S35=1,"1：家族",IF(AND(S35>=2,S35<=5),"2：雇用",""))) | G35: =INT(INDEX(設定!$H$9:H$108,$A35,1)) -> 0 | H35: =IF(INDEX(設定!$H$9:$H$108,$A35,1)=0,"",ROUND(MOD(INDEX(設定!$H$9:$H$108,$A35,1),1)*60,0)) | I35: =INT(INDEX(設定!$I$9:$I$108,$A35,1)) -> 0 | J35: =IF(INDEX(設定!$I$9:$I$108,$A35,1)=0,"",ROUND(MOD(INDEX(設定!$I$9:$I$108,$A35,1),1)*60,0)) | K35: =INT(INDEX(設定!$J$9:$J$108,$A35,1)) -> 0 | L35: =IF(INDEX(設定!$J$9:$J$108,$A35,1)=0,"",ROUND(MOD(INDEX(設定!$J$9:$J$108,$A35,1),1)*60,0)) | S35: =IF(INDEX(設定!$F$9:$F$108,$A35,1)="","",VALUE(LEFT(INDEX(設定!$F$9:$F$108,$A35,1),1))) | T35: =IF(C35="","",C35) | U35: =IF(D35="","",IF(D35="1：男",1,IF(D35="2：女",2))) | V35: =IF(E35="","",E35) | W35: =IF(AND(G35="",H35="",G36=""),"",ROUND(SUM(G35,H35/60)*G36,1)) | X35: =IF(AND(I35="",J35="",I36=""),"",ROUND(SUM(I35,J35/60)*I36,1)) | Y35: =IF(AND(K35="",L35="",K36=""),"",ROUND(SUM(K35,L35/60)*K36,1)) | AD35: 75歳以上 | AF35: =AH35+AJ35 -> 0 | AG35: =AI35+AK35 -> 0 | AH35: =SUMIFS($X$77:$X$106,$S$77:$S$106,1,$U$77:$U$106,1,$V$77:$V$106,">=75")+SUMIFS($Y$77:$Y$106,$S$77:$S$106,1,$U$77:$U$106,1,$V$77:$V$106,">=75") -> 0 | AI35: =SUMIFS($X$77:$X$106,$S$77:$S$106,1,$U$77:$U$106,2,$V$77:$V$106,">=75")+SUMIFS($Y$77:$Y$106,$S$77:$S$106,1,$U$77:$U$106,2,$V$77:$V$106,">=75") -> 0 | AR35: =SUMIFS($X$77:$X$106,$S$77:$S$106,5,$U$77:$U$106,1,$V$77:$V$106,">=75")+SUMIFS($Y$77:$Y$106,$S$77:$S$106,5,$U$77:$U$106,1,$V$77:$V$106,">=75") -> 0 | AS35: =SUMIFS($X$77:$X$106,$S$77:$S$106,5,$U$77:$U$106,2,$V$77:$V$106,">=75")+SUMIFS($Y$77:$Y$106,$S$77:$S$106,5,$U$77:$U$106,2,$V$77:$V$106,">=75") -> 0 | AW35: 75歳以上 | AY35: =ROUND(AF35*$T$4*0.7,0) -> 0 | AZ35: =ROUND(AG35*$T$4*0.7,0) -> 0 | BE35: =AR35*$T$4*0.7 -> 0 | BF35: =AS35*$T$4*0.7 -> 0
G36: =IF(SUM(G35:H35)>0,1,"") | I36: =IF(SUM(I35:J35)>0,1,"") | K36: =IF(SUM(K35:L35)>0,1,"") | AC36: 労働時間合計 | AF36: =SUM(AF37:AF40) -> 0 | AG36: =SUM(AG37:AG40) -> 0 | AL36: =AL11+AL31 -> 0 | AM36: =AM11+AM31 -> 0 | AN36: =AN11+AN31 -> 0 | AO36: =AO11+AO31 -> 0 | AP36: =AP11+AP31 -> 0 | AQ36: =AQ11+AQ31 -> 0 | AR36: =AR11+AR31 -> 0 | AS36: =AS11+AS31 -> 0 | AV36: 労働費 | AY36: =SUM(AY37:AY40) -> 0 | AZ36: =SUM(AZ37:AZ40) -> 0 | BA36: =SUM(BA11,BA31) -> 0 | BB36: =SUM(BB11,BB31) -> 0 | BC36: =SUM(BC11,BC31) -> 0 | BD36: =SUM(BD11,BD31) -> 0 | BE36: =SUM(BE37:BE40) -> 0 | BF36: =SUM(BF37:BF40) -> 0
A37: =ROUND((ROW()-10)/2,0) -> 14 | C37: =IF(INDEX(設定!$C$9:$C$108,$A37,1)="","",INDEX(設定!$C$9:$C$108,$A37,1)) | D37: =IF(INDEX(設定!$D$9:$D$108,$A37,1)="","",INDEX(設定!$D$9:$D$108,$A37,1)) | E37: =IF(INDEX(設定!$E$9:$E$108,$A37,1)="","",INDEX(設定!$E$9:$E$108,$A37,1)) | F37: =IF(S37="","",IF(S37=1,"1：家族",IF(AND(S37>=2,S37<=5),"2：雇用",""))) | G37: =INT(INDEX(設定!$H$9:H$108,$A37,1)) -> 0 | H37: =IF(INDEX(設定!$H$9:$H$108,$A37,1)=0,"",ROUND(MOD(INDEX(設定!$H$9:$H$108,$A37,1),1)*60,0)) | I37: =INT(INDEX(設定!$I$9:$I$108,$A37,1)) -> 0 | J37: =IF(INDEX(設定!$I$9:$I$108,$A37,1)=0,"",ROUND(MOD(INDEX(設定!$I$9:$I$108,$A37,1),1)*60,0)) | K37: =INT(INDEX(設定!$J$9:$J$108,$A37,1)) -> 0 | L37: =IF(INDEX(設定!$J$9:$J$108,$A37,1)=0,"",ROUND(MOD(INDEX(設定!$J$9:$J$108,$A37,1),1)*60,0)) | S37: =IF(INDEX(設定!$F$9:$F$108,$A37,1)="","",VALUE(LEFT(INDEX(設定!$F$9:$F$108,$A37,1),1))) | T37: =IF(C37="","",C37) | U37: =IF(D37="","",IF(D37="1：男",1,IF(D37="2：女",2))) | V37: =IF(E37="","",E37) | W37: =IF(AND(G37="",H37="",G38=""),"",ROUND(SUM(G37,H37/60)*G38,1)) | X37: =IF(AND(I37="",J37="",I38=""),"",ROUND(SUM(I37,J37/60)*I38,1)) | Y37: =IF(AND(K37="",L37="",K38=""),"",ROUND(SUM(K37,L37/60)*K38,1)) | AD37: 65歳未満 | AF37: =AF12+AF32 -> 0 | AG37: =AG12+AG32 -> 0 | AH37: =AH12+AH32 -> 0 | AI37: =AI12+AI32 -> 0 | AJ37: =AJ12+AJ32 -> 0 | AK37: =AK12+AK32 -> 0 | AP37: =AP12+AP32 -> 0 | AQ37: =AQ12+AQ32 -> 0 | AR37: =AR12+AR32 -> 0 | AS37: =AS12+AS32 -> 0 | AW37: 65歳未満 | AY37: =SUM(AY12,AY32) -> 0 | AZ37: =SUM(AZ12,AZ32) -> 0 | BE37: =SUM(BE12,BE32) -> 0 | BF37: =SUM(BF12,BF32) -> 0
G38: =IF(SUM(G37:H37)>0,1,"") | I38: =IF(SUM(I37:J37)>0,1,"") | K38: =IF(SUM(K37:L37)>0,1,"") | AD38: 65～70 | AF38: =AF13+AF33 -> 0 | AG38: =AG13+AG33 -> 0 | AH38: =AH13+AH33 -> 0 | AI38: =AI13+AI33 -> 0 | AR38: =AR13+AR33 -> 0 | AS38: =AS13+AS33 -> 0 | AW38: 65～70 | AY38: =SUM(AY13,AY33) -> 0 | AZ38: =SUM(AZ13,AZ33) -> 0 | BE38: =SUM(BE13,BE33) -> 0 | BF38: =SUM(BF13,BF33) -> 0
A39: =ROUND((ROW()-10)/2,0) -> 15 | C39: =IF(INDEX(設定!$C$9:$C$108,$A39,1)="","",INDEX(設定!$C$9:$C$108,$A39,1)) | D39: =IF(INDEX(設定!$D$9:$D$108,$A39,1)="","",INDEX(設定!$D$9:$D$108,$A39,1)) | E39: =IF(INDEX(設定!$E$9:$E$108,$A39,1)="","",INDEX(設定!$E$9:$E$108,$A39,1)) | F39: =IF(S39="","",IF(S39=1,"1：家族",IF(AND(S39>=2,S39<=5),"2：雇用",""))) | G39: =INT(INDEX(設定!$H$9:H$108,$A39,1)) -> 0 | H39: =IF(INDEX(設定!$H$9:$H$108,$A39,1)=0,"",ROUND(MOD(INDEX(設定!$H$9:$H$108,$A39,1),1)*60,0)) | I39: =INT(INDEX(設定!$I$9:$I$108,$A39,1)) -> 0 | J39: =IF(INDEX(設定!$I$9:$I$108,$A39,1)=0,"",ROUND(MOD(INDEX(設定!$I$9:$I$108,$A39,1),1)*60,0)) | K39: =INT(INDEX(設定!$J$9:$J$108,$A39,1)) -> 0 | L39: =IF(INDEX(設定!$J$9:$J$108,$A39,1)=0,"",ROUND(MOD(INDEX(設定!$J$9:$J$108,$A39,1),1)*60,0)) | S39: =IF(INDEX(設定!$F$9:$F$108,$A39,1)="","",VALUE(LEFT(INDEX(設定!$F$9:$F$108,$A39,1),1))) | T39: =IF(C39="","",C39) | U39: =IF(D39="","",IF(D39="1：男",1,IF(D39="2：女",2))) | V39: =IF(E39="","",E39) | W39: =IF(AND(G39="",H39="",G40=""),"",ROUND(SUM(G39,H39/60)*G40,1)) | X39: =IF(AND(I39="",J39="",I40=""),"",ROUND(SUM(I39,J39/60)*I40,1)) | Y39: =IF(AND(K39="",L39="",K40=""),"",ROUND(SUM(K39,L39/60)*K40,1)) | AD39: 70～75 | AF39: =AF14+AF34 -> 0 | AG39: =AG14+AG34 -> 0 | AH39: =AH14+AH34 -> 0 | AI39: =AI14+AI34 -> 0 | AR39: =AR14+AR34 -> 0 | AS39: =AS14+AS34 -> 0 | AW39: 70～75 | AY39: =SUM(AY14,AY34) -> 0 | AZ39: =SUM(AZ14,AZ34) -> 0 | BE39: =SUM(BE14,BE34) -> 0 | BF39: =SUM(BF14,BF34) -> 0
G40: =IF(SUM(G39:H39)>0,1,"") | I40: =IF(SUM(I39:J39)>0,1,"") | K40: =IF(SUM(K39:L39)>0,1,"") | AD40: 75歳以上 | AF40: =AF15+AF35 -> 0 | AG40: =AG15+AG35 -> 0 | AH40: =AH15+AH35 -> 0 | AI40: =AI15+AI35 -> 0 | AR40: =AR15+AR35 -> 0 | AS40: =AS15+AS35 -> 0 | AW40: 75歳以上 | AY40: =SUM(AY15,AY35) -> 0 | AZ40: =SUM(AZ15,AZ35) -> 0 | BE40: =SUM(BE15,BE35) -> 0 | BF40: =SUM(BF15,BF35) -> 0
A41: =ROUND((ROW()-10)/2,0) -> 16 | C41: =IF(INDEX(設定!$C$9:$C$108,$A41,1)="","",INDEX(設定!$C$9:$C$108,$A41,1)) | D41: =IF(INDEX(設定!$D$9:$D$108,$A41,1)="","",INDEX(設定!$D$9:$D$108,$A41,1)) | E41: =IF(INDEX(設定!$E$9:$E$108,$A41,1)="","",INDEX(設定!$E$9:$E$108,$A41,1)) | F41: =IF(S41="","",IF(S41=1,"1：家族",IF(AND(S41>=2,S41<=5),"2：雇用",""))) | G41: =INT(INDEX(設定!$H$9:H$108,$A41,1)) -> 0 | H41: =IF(INDEX(設定!$H$9:$H$108,$A41,1)=0,"",ROUND(MOD(INDEX(設定!$H$9:$H$108,$A41,1),1)*60,0)) | I41: =INT(INDEX(設定!$I$9:$I$108,$A41,1)) -> 0 | J41: =IF(INDEX(設定!$I$9:$I$108,$A41,1)=0,"",ROUND(MOD(INDEX(設定!$I$9:$I$108,$A41,1),1)*60,0)) | K41: =INT(INDEX(設定!$J$9:$J$108,$A41,1)) -> 0 | L41: =IF(INDEX(設定!$J$9:$J$108,$A41,1)=0,"",ROUND(MOD(INDEX(設定!$J$9:$J$108,$A41,1),1)*60,0)) | S41: =IF(INDEX(設定!$F$9:$F$108,$A41,1)="","",VALUE(LEFT(INDEX(設定!$F$9:$F$108,$A41,1),1))) | T41: =IF(C41="","",C41) | U41: =IF(D41="","",IF(D41="1：男",1,IF(D41="2：女",2))) | V41: =IF(E41="","",E41) | W41: =IF(AND(G41="",H41="",G42=""),"",ROUND(SUM(G41,H41/60)*G42,1)) | X41: =IF(AND(I41="",J41="",I42=""),"",ROUND(SUM(I41,J41/60)*I42,1)) | Y41: =IF(AND(K41="",L41="",K42=""),"",ROUND(SUM(K41,L41/60)*K42,1)) | AC41: 経営管理労働時間 | AF41: =SUMIFS($Z$77:$Z$106,$S$77:$S$106,1,$U$77:$U$106,1) -> 0 | AG41: =SUMIFS($Z$77:$Z$106,$S$77:$S$106,1,$U$77:$U$106,2) -> 0
G42: =IF(SUM(G41:H41)>0,1,"") | I42: =IF(SUM(I41:J41)>0,1,"") | K42: =IF(SUM(K41:L41)>0,1,"")
A43: =ROUND((ROW()-10)/2,0) -> 17 | C43: =IF(INDEX(設定!$C$9:$C$108,$A43,1)="","",INDEX(設定!$C$9:$C$108,$A43,1)) | D43: =IF(INDEX(設定!$D$9:$D$108,$A43,1)="","",INDEX(設定!$D$9:$D$108,$A43,1)) | E43: =IF(INDEX(設定!$E$9:$E$108,$A43,1)="","",INDEX(設定!$E$9:$E$108,$A43,1)) | F43: =IF(S43="","",IF(S43=1,"1：家族",IF(AND(S43>=2,S43<=5),"2：雇用",""))) | G43: =INT(INDEX(設定!$H$9:H$108,$A43,1)) -> 0 | H43: =IF(INDEX(設定!$H$9:$H$108,$A43,1)=0,"",ROUND(MOD(INDEX(設定!$H$9:$H$108,$A43,1),1)*60,0)) | I43: =INT(INDEX(設定!$I$9:$I$108,$A43,1)) -> 0 | J43: =IF(INDEX(設定!$I$9:$I$108,$A43,1)=0,"",ROUND(MOD(INDEX(設定!$I$9:$I$108,$A43,1),1)*60,0)) | K43: =INT(INDEX(設定!$J$9:$J$108,$A43,1)) -> 0 | L43: =IF(INDEX(設定!$J$9:$J$108,$A43,1)=0,"",ROUND(MOD(INDEX(設定!$J$9:$J$108,$A43,1),1)*60,0)) | S43: =IF(INDEX(設定!$F$9:$F$108,$A43,1)="","",VALUE(LEFT(INDEX(設定!$F$9:$F$108,$A43,1),1))) | T43: =IF(C43="","",C43) | U43: =IF(D43="","",IF(D43="1：男",1,IF(D43="2：女",2))) | V43: =IF(E43="","",E43) | W43: =IF(AND(G43="",H43="",G44=""),"",ROUND(SUM(G43,H43/60)*G44,1)) | X43: =IF(AND(I43="",J43="",I44=""),"",ROUND(SUM(I43,J43/60)*I44,1)) | Y43: =IF(AND(K43="",L43="",K44=""),"",ROUND(SUM(K43,L43/60)*K44,1))
G44: =IF(SUM(G43:H43)>0,1,"") | I44: =IF(SUM(I43:J43)>0,1,"") | K44: =IF(SUM(K43:L43)>0,1,"")
A45: =ROUND((ROW()-10)/2,0) -> 18 | C45: =IF(INDEX(設定!$C$9:$C$108,$A45,1)="","",INDEX(設定!$C$9:$C$108,$A45,1)) | D45: =IF(INDEX(設定!$D$9:$D$108,$A45,1)="","",INDEX(設定!$D$9:$D$108,$A45,1)) | E45: =IF(INDEX(設定!$E$9:$E$108,$A45,1)="","",INDEX(設定!$E$9:$E$108,$A45,1)) | F45: =IF(S45="","",IF(S45=1,"1：家族",IF(AND(S45>=2,S45<=5),"2：雇用",""))) | G45: =INT(INDEX(設定!$H$9:H$108,$A45,1)) -> 0 | H45: =IF(INDEX(設定!$H$9:$H$108,$A45,1)=0,"",ROUND(MOD(INDEX(設定!$H$9:$H$108,$A45,1),1)*60,0)) | I45: =INT(INDEX(設定!$I$9:$I$108,$A45,1)) -> 0 | J45: =IF(INDEX(設定!$I$9:$I$108,$A45,1)=0,"",ROUND(MOD(INDEX(設定!$I$9:$I$108,$A45,1),1)*60,0)) | K45: =INT(INDEX(設定!$J$9:$J$108,$A45,1)) -> 0 | L45: =IF(INDEX(設定!$J$9:$J$108,$A45,1)=0,"",ROUND(MOD(INDEX(設定!$J$9:$J$108,$A45,1),1)*60,0)) | S45: =IF(INDEX(設定!$F$9:$F$108,$A45,1)="","",VALUE(LEFT(INDEX(設定!$F$9:$F$108,$A45,1),1))) | T45: =IF(C45="","",C45) | U45: =IF(D45="","",IF(D45="1：男",1,IF(D45="2：女",2))) | V45: =IF(E45="","",E45) | W45: =IF(AND(G45="",H45="",G46=""),"",ROUND(SUM(G45,H45/60)*G46,1)) | X45: =IF(AND(I45="",J45="",I46=""),"",ROUND(SUM(I45,J45/60)*I46,1)) | Y45: =IF(AND(K45="",L45="",K46=""),"",ROUND(SUM(K45,L45/60)*K46,1))
G46: =IF(SUM(G45:H45)>0,1,"") | I46: =IF(SUM(I45:J45)>0,1,"") | K46: =IF(SUM(K45:L45)>0,1,"")
A47: =ROUND((ROW()-10)/2,0) -> 19 | C47: =IF(INDEX(設定!$C$9:$C$108,$A47,1)="","",INDEX(設定!$C$9:$C$108,$A47,1)) | D47: =IF(INDEX(設定!$D$9:$D$108,$A47,1)="","",INDEX(設定!$D$9:$D$108,$A47,1)) | E47: =IF(INDEX(設定!$E$9:$E$108,$A47,1)="","",INDEX(設定!$E$9:$E$108,$A47,1)) | F47: =IF(S47="","",IF(S47=1,"1：家族",IF(AND(S47>=2,S47<=5),"2：雇用",""))) | G47: =INT(INDEX(設定!$H$9:H$108,$A47,1)) -> 0 | H47: =IF(INDEX(設定!$H$9:$H$108,$A47,1)=0,"",ROUND(MOD(INDEX(設定!$H$9:$H$108,$A47,1),1)*60,0)) | I47: =INT(INDEX(設定!$I$9:$I$108,$A47,1)) -> 0 | J47: =IF(INDEX(設定!$I$9:$I$108,$A47,1)=0,"",ROUND(MOD(INDEX(設定!$I$9:$I$108,$A47,1),1)*60,0)) | K47: =INT(INDEX(設定!$J$9:$J$108,$A47,1)) -> 0 | L47: =IF(INDEX(設定!$J$9:$J$108,$A47,1)=0,"",ROUND(MOD(INDEX(設定!$J$9:$J$108,$A47,1),1)*60,0)) | S47: =IF(INDEX(設定!$F$9:$F$108,$A47,1)="","",VALUE(LEFT(INDEX(設定!$F$9:$F$108,$A47,1),1))) | T47: =IF(C47="","",C47) | U47: =IF(D47="","",IF(D47="1：男",1,IF(D47="2：女",2))) | V47: =IF(E47="","",E47) | W47: =IF(AND(G47="",H47="",G48=""),"",ROUND(SUM(G47,H47/60)*G48,1)) | X47: =IF(AND(I47="",J47="",I48=""),"",ROUND(SUM(I47,J47/60)*I48,1)) | Y47: =IF(AND(K47="",L47="",K48=""),"",ROUND(SUM(K47,L47/60)*K48,1))
G48: =IF(SUM(G47:H47)>0,1,"") | I48: =IF(SUM(I47:J47)>0,1,"") | K48: =IF(SUM(K47:L47)>0,1,"")
A49: =ROUND((ROW()-10)/2,0) -> 20 | C49: =IF(INDEX(設定!$C$9:$C$108,$A49,1)="","",INDEX(設定!$C$9:$C$108,$A49,1)) | D49: =IF(INDEX(設定!$D$9:$D$108,$A49,1)="","",INDEX(設定!$D$9:$D$108,$A49,1)) | E49: =IF(INDEX(設定!$E$9:$E$108,$A49,1)="","",INDEX(設定!$E$9:$E$108,$A49,1)) | F49: =IF(S49="","",IF(S49=1,"1：家族",IF(AND(S49>=2,S49<=5),"2：雇用",""))) | G49: =INT(INDEX(設定!$H$9:H$108,$A49,1)) -> 0 | H49: =IF(INDEX(設定!$H$9:$H$108,$A49,1)=0,"",ROUND(MOD(INDEX(設定!$H$9:$H$108,$A49,1),1)*60,0)) | I49: =INT(INDEX(設定!$I$9:$I$108,$A49,1)) -> 0 | J49: =IF(INDEX(設定!$I$9:$I$108,$A49,1)=0,"",ROUND(MOD(INDEX(設定!$I$9:$I$108,$A49,1),1)*60,0)) | K49: =INT(INDEX(設定!$J$9:$J$108,$A49,1)) -> 0 | L49: =IF(INDEX(設定!$J$9:$J$108,$A49,1)=0,"",ROUND(MOD(INDEX(設定!$J$9:$J$108,$A49,1),1)*60,0)) | S49: =IF(INDEX(設定!$F$9:$F$108,$A49,1)="","",VALUE(LEFT(INDEX(設定!$F$9:$F$108,$A49,1),1))) | T49: =IF(C49="","",C49) | U49: =IF(D49="","",IF(D49="1：男",1,IF(D49="2：女",2))) | V49: =IF(E49="","",E49) | W49: =IF(AND(G49="",H49="",G50=""),"",ROUND(SUM(G49,H49/60)*G50,1)) | X49: =IF(AND(I49="",J49="",I50=""),"",ROUND(SUM(I49,J49/60)*I50,1)) | Y49: =IF(AND(K49="",L49="",K50=""),"",ROUND(SUM(K49,L49/60)*K50,1))
G50: =IF(SUM(G49:H49)>0,1,"") | I50: =IF(SUM(I49:J49)>0,1,"") | K50: =IF(SUM(K49:L49)>0,1,"")
A51: =ROUND((ROW()-10)/2,0) -> 21 | C51: =IF(INDEX(設定!$C$9:$C$108,$A51,1)="","",INDEX(設定!$C$9:$C$108,$A51,1)) | D51: =IF(INDEX(設定!$D$9:$D$108,$A51,1)="","",INDEX(設定!$D$9:$D$108,$A51,1)) | E51: =IF(INDEX(設定!$E$9:$E$108,$A51,1)="","",INDEX(設定!$E$9:$E$108,$A51,1)) | F51: =IF(S51="","",IF(S51=1,"1：家族",IF(AND(S51>=2,S51<=5),"2：雇用",""))) | G51: =INT(INDEX(設定!$H$9:H$108,$A51,1)) -> 0 | H51: =IF(INDEX(設定!$H$9:$H$108,$A51,1)=0,"",ROUND(MOD(INDEX(設定!$H$9:$H$108,$A51,1),1)*60,0)) | I51: =INT(INDEX(設定!$I$9:$I$108,$A51,1)) -> 0 | J51: =IF(INDEX(設定!$I$9:$I$108,$A51,1)=0,"",ROUND(MOD(INDEX(設定!$I$9:$I$108,$A51,1),1)*60,0)) | K51: =INT(INDEX(設定!$J$9:$J$108,$A51,1)) -> 0 | L51: =IF(INDEX(設定!$J$9:$J$108,$A51,1)=0,"",ROUND(MOD(INDEX(設定!$J$9:$J$108,$A51,1),1)*60,0)) | S51: =IF(INDEX(設定!$F$9:$F$108,$A51,1)="","",VALUE(LEFT(INDEX(設定!$F$9:$F$108,$A51,1),1))) | T51: =IF(C51="","",C51) | U51: =IF(D51="","",IF(D51="1：男",1,IF(D51="2：女",2))) | V51: =IF(E51="","",E51) | W51: =IF(AND(G51="",H51="",G52=""),"",ROUND(SUM(G51,H51/60)*G52,1)) | X51: =IF(AND(I51="",J51="",I52=""),"",ROUND(SUM(I51,J51/60)*I52,1)) | Y51: =IF(AND(K51="",L51="",K52=""),"",ROUND(SUM(K51,L51/60)*K52,1))
G52: =IF(SUM(G51:H51)>0,1,"") | I52: =IF(SUM(I51:J51)>0,1,"") | K52: =IF(SUM(K51:L51)>0,1,"")
A53: =ROUND((ROW()-10)/2,0) -> 22 | C53: =IF(INDEX(設定!$C$9:$C$108,$A53,1)="","",INDEX(設定!$C$9:$C$108,$A53,1)) | D53: =IF(INDEX(設定!$D$9:$D$108,$A53,1)="","",INDEX(設定!$D$9:$D$108,$A53,1)) | E53: =IF(INDEX(設定!$E$9:$E$108,$A53,1)="","",INDEX(設定!$E$9:$E$108,$A53,1)) | F53: =IF(S53="","",IF(S53=1,"1：家族",IF(AND(S53>=2,S53<=5),"2：雇用",""))) | G53: =INT(INDEX(設定!$H$9:H$108,$A53,1)) -> 0 | H53: =IF(INDEX(設定!$H$9:$H$108,$A53,1)=0,"",ROUND(MOD(INDEX(設定!$H$9:$H$108,$A53,1),1)*60,0)) | I53: =INT(INDEX(設定!$I$9:$I$108,$A53,1)) -> 0 | J53: =IF(INDEX(設定!$I$9:$I$108,$A53,1)=0,"",ROUND(MOD(INDEX(設定!$I$9:$I$108,$A53,1),1)*60,0)) | K53: =INT(INDEX(設定!$J$9:$J$108,$A53,1)) -> 0 | L53: =IF(INDEX(設定!$J$9:$J$108,$A53,1)=0,"",ROUND(MOD(INDEX(設定!$J$9:$J$108,$A53,1),1)*60,0)) | S53: =IF(INDEX(設定!$F$9:$F$108,$A53,1)="","",VALUE(LEFT(INDEX(設定!$F$9:$F$108,$A53,1),1))) | T53: =IF(C53="","",C53) | U53: =IF(D53="","",IF(D53="1：男",1,IF(D53="2：女",2))) | V53: =IF(E53="","",E53) | W53: =IF(AND(G53="",H53="",G54=""),"",ROUND(SUM(G53,H53/60)*G54,1)) | X53: =IF(AND(I53="",J53="",I54=""),"",ROUND(SUM(I53,J53/60)*I54,1)) | Y53: =IF(AND(K53="",L53="",K54=""),"",ROUND(SUM(K53,L53/60)*K54,1))
G54: =IF(SUM(G53:H53)>0,1,"") | I54: =IF(SUM(I53:J53)>0,1,"") | K54: =IF(SUM(K53:L53)>0,1,"")
A55: =ROUND((ROW()-10)/2,0) -> 23 | C55: =IF(INDEX(設定!$C$9:$C$108,$A55,1)="","",INDEX(設定!$C$9:$C$108,$A55,1)) | D55: =IF(INDEX(設定!$D$9:$D$108,$A55,1)="","",INDEX(設定!$D$9:$D$108,$A55,1)) | E55: =IF(INDEX(設定!$E$9:$E$108,$A55,1)="","",INDEX(設定!$E$9:$E$108,$A55,1)) | F55: =IF(S55="","",IF(S55=1,"1：家族",IF(AND(S55>=2,S55<=5),"2：雇用",""))) | G55: =INT(INDEX(設定!$H$9:H$108,$A55,1)) -> 0 | H55: =IF(INDEX(設定!$H$9:$H$108,$A55,1)=0,"",ROUND(MOD(INDEX(設定!$H$9:$H$108,$A55,1),1)*60,0)) | I55: =INT(INDEX(設定!$I$9:$I$108,$A55,1)) -> 0 | J55: =IF(INDEX(設定!$I$9:$I$108,$A55,1)=0,"",ROUND(MOD(INDEX(設定!$I$9:$I$108,$A55,1),1)*60,0)) | K55: =INT(INDEX(設定!$J$9:$J$108,$A55,1)) -> 0 | L55: =IF(INDEX(設定!$J$9:$J$108,$A55,1)=0,"",ROUND(MOD(INDEX(設定!$J$9:$J$108,$A55,1),1)*60,0)) | S55: =IF(INDEX(設定!$F$9:$F$108,$A55,1)="","",VALUE(LEFT(INDEX(設定!$F$9:$F$108,$A55,1),1))) | T55: =IF(C55="","",C55) | U55: =IF(D55="","",IF(D55="1：男",1,IF(D55="2：女",2))) | V55: =IF(E55="","",E55) | W55: =IF(AND(G55="",H55="",G56=""),"",ROUND(SUM(G55,H55/60)*G56,1)) | X55: =IF(AND(I55="",J55="",I56=""),"",ROUND(SUM(I55,J55/60)*I56,1)) | Y55: =IF(AND(K55="",L55="",K56=""),"",ROUND(SUM(K55,L55/60)*K56,1))
G56: =IF(SUM(G55:H55)>0,1,"") | I56: =IF(SUM(I55:J55)>0,1,"") | K56: =IF(SUM(K55:L55)>0,1,"")
A57: =ROUND((ROW()-10)/2,0) -> 24 | C57: =IF(INDEX(設定!$C$9:$C$108,$A57,1)="","",INDEX(設定!$C$9:$C$108,$A57,1)) | D57: =IF(INDEX(設定!$D$9:$D$108,$A57,1)="","",INDEX(設定!$D$9:$D$108,$A57,1)) | E57: =IF(INDEX(設定!$E$9:$E$108,$A57,1)="","",INDEX(設定!$E$9:$E$108,$A57,1)) | F57: =IF(S57="","",IF(S57=1,"1：家族",IF(AND(S57>=2,S57<=5),"2：雇用",""))) | G57: =INT(INDEX(設定!$H$9:H$108,$A57,1)) -> 0 | H57: =IF(INDEX(設定!$H$9:$H$108,$A57,1)=0,"",ROUND(MOD(INDEX(設定!$H$9:$H$108,$A57,1),1)*60,0)) | I57: =INT(INDEX(設定!$I$9:$I$108,$A57,1)) -> 0 | J57: =IF(INDEX(設定!$I$9:$I$108,$A57,1)=0,"",ROUND(MOD(INDEX(設定!$I$9:$I$108,$A57,1),1)*60,0)) | K57: =INT(INDEX(設定!$J$9:$J$108,$A57,1)) -> 0 | L57: =IF(INDEX(設定!$J$9:$J$108,$A57,1)=0,"",ROUND(MOD(INDEX(設定!$J$9:$J$108,$A57,1),1)*60,0)) | S57: =IF(INDEX(設定!$F$9:$F$108,$A57,1)="","",VALUE(LEFT(INDEX(設定!$F$9:$F$108,$A57,1),1))) | T57: =IF(C57="","",C57) | U57: =IF(D57="","",IF(D57="1：男",1,IF(D57="2：女",2))) | V57: =IF(E57="","",E57) | W57: =IF(AND(G57="",H57="",G58=""),"",ROUND(SUM(G57,H57/60)*G58,1)) | X57: =IF(AND(I57="",J57="",I58=""),"",ROUND(SUM(I57,J57/60)*I58,1)) | Y57: =IF(AND(K57="",L57="",K58=""),"",ROUND(SUM(K57,L57/60)*K58,1))
G58: =IF(SUM(G57:H57)>0,1,"") | I58: =IF(SUM(I57:J57)>0,1,"") | K58: =IF(SUM(K57:L57)>0,1,"")
A59: =ROUND((ROW()-10)/2,0) -> 25 | C59: =IF(INDEX(設定!$C$9:$C$108,$A59,1)="","",INDEX(設定!$C$9:$C$108,$A59,1)) | D59: =IF(INDEX(設定!$D$9:$D$108,$A59,1)="","",INDEX(設定!$D$9:$D$108,$A59,1)) | E59: =IF(INDEX(設定!$E$9:$E$108,$A59,1)="","",INDEX(設定!$E$9:$E$108,$A59,1)) | F59: =IF(S59="","",IF(S59=1,"1：家族",IF(AND(S59>=2,S59<=5),"2：雇用",""))) | G59: =INT(INDEX(設定!$H$9:H$108,$A59,1)) -> 0 | H59: =IF(INDEX(設定!$H$9:$H$108,$A59,1)=0,"",ROUND(MOD(INDEX(設定!$H$9:$H$108,$A59,1),1)*60,0)) | I59: =INT(INDEX(設定!$I$9:$I$108,$A59,1)) -> 0 | J59: =IF(INDEX(設定!$I$9:$I$108,$A59,1)=0,"",ROUND(MOD(INDEX(設定!$I$9:$I$108,$A59,1),1)*60,0)) | K59: =INT(INDEX(設定!$J$9:$J$108,$A59,1)) -> 0 | L59: =IF(INDEX(設定!$J$9:$J$108,$A59,1)=0,"",ROUND(MOD(INDEX(設定!$J$9:$J$108,$A59,1),1)*60,0)) | S59: =IF(INDEX(設定!$F$9:$F$108,$A59,1)="","",VALUE(LEFT(INDEX(設定!$F$9:$F$108,$A59,1),1))) | T59: =IF(C59="","",C59) | U59: =IF(D59="","",IF(D59="1：男",1,IF(D59="2：女",2))) | V59: =IF(E59="","",E59) | W59: =IF(AND(G59="",H59="",G60=""),"",ROUND(SUM(G59,H59/60)*G60,1)) | X59: =IF(AND(I59="",J59="",I60=""),"",ROUND(SUM(I59,J59/60)*I60,1)) | Y59: =IF(AND(K59="",L59="",K60=""),"",ROUND(SUM(K59,L59/60)*K60,1))
G60: =IF(SUM(G59:H59)>0,1,"") | I60: =IF(SUM(I59:J59)>0,1,"") | K60: =IF(SUM(K59:L59)>0,1,"")
A61: =ROUND((ROW()-10)/2,0) -> 26 | C61: =IF(INDEX(設定!$C$9:$C$108,$A61,1)="","",INDEX(設定!$C$9:$C$108,$A61,1)) | D61: =IF(INDEX(設定!$D$9:$D$108,$A61,1)="","",INDEX(設定!$D$9:$D$108,$A61,1)) | E61: =IF(INDEX(設定!$E$9:$E$108,$A61,1)="","",INDEX(設定!$E$9:$E$108,$A61,1)) | F61: =IF(S61="","",IF(S61=1,"1：家族",IF(AND(S61>=2,S61<=5),"2：雇用",""))) | G61: =INT(INDEX(設定!$H$9:H$108,$A61,1)) -> 0 | H61: =IF(INDEX(設定!$H$9:$H$108,$A61,1)=0,"",ROUND(MOD(INDEX(設定!$H$9:$H$108,$A61,1),1)*60,0)) | I61: =INT(INDEX(設定!$I$9:$I$108,$A61,1)) -> 0 | J61: =IF(INDEX(設定!$I$9:$I$108,$A61,1)=0,"",ROUND(MOD(INDEX(設定!$I$9:$I$108,$A61,1),1)*60,0)) | K61: =INT(INDEX(設定!$J$9:$J$108,$A61,1)) -> 0 | L61: =IF(INDEX(設定!$J$9:$J$108,$A61,1)=0,"",ROUND(MOD(INDEX(設定!$J$9:$J$108,$A61,1),1)*60,0)) | S61: =IF(INDEX(設定!$F$9:$F$108,$A61,1)="","",VALUE(LEFT(INDEX(設定!$F$9:$F$108,$A61,1),1))) | T61: =IF(C61="","",C61) | U61: =IF(D61="","",IF(D61="1：男",1,IF(D61="2：女",2))) | V61: =IF(E61="","",E61) | W61: =IF(AND(G61="",H61="",G62=""),"",ROUND(SUM(G61,H61/60)*G62,1)) | X61: =IF(AND(I61="",J61="",I62=""),"",ROUND(SUM(I61,J61/60)*I62,1)) | Y61: =IF(AND(K61="",L61="",K62=""),"",ROUND(SUM(K61,L61/60)*K62,1))
G62: =IF(SUM(G61:H61)>0,1,"") | I62: =IF(SUM(I61:J61)>0,1,"") | K62: =IF(SUM(K61:L61)>0,1,"")
A63: =ROUND((ROW()-10)/2,0) -> 27 | C63: =IF(INDEX(設定!$C$9:$C$108,$A63,1)="","",INDEX(設定!$C$9:$C$108,$A63,1)) | D63: =IF(INDEX(設定!$D$9:$D$108,$A63,1)="","",INDEX(設定!$D$9:$D$108,$A63,1)) | E63: =IF(INDEX(設定!$E$9:$E$108,$A63,1)="","",INDEX(設定!$E$9:$E$108,$A63,1)) | F63: =IF(S63="","",IF(S63=1,"1：家族",IF(AND(S63>=2,S63<=5),"2：雇用",""))) | G63: =INT(INDEX(設定!$H$9:H$108,$A63,1)) -> 0 | H63: =IF(INDEX(設定!$H$9:$H$108,$A63,1)=0,"",ROUND(MOD(INDEX(設定!$H$9:$H$108,$A63,1),1)*60,0)) | I63: =INT(INDEX(設定!$I$9:$I$108,$A63,1)) -> 0 | J63: =IF(INDEX(設定!$I$9:$I$108,$A63,1)=0,"",ROUND(MOD(INDEX(設定!$I$9:$I$108,$A63,1),1)*60,0)) | K63: =INT(INDEX(設定!$J$9:$J$108,$A63,1)) -> 0 | L63: =IF(INDEX(設定!$J$9:$J$108,$A63,1)=0,"",ROUND(MOD(INDEX(設定!$J$9:$J$108,$A63,1),1)*60,0)) | S63: =IF(INDEX(設定!$F$9:$F$108,$A63,1)="","",VALUE(LEFT(INDEX(設定!$F$9:$F$108,$A63,1),1))) | T63: =IF(C63="","",C63) | U63: =IF(D63="","",IF(D63="1：男",1,IF(D63="2：女",2))) | V63: =IF(E63="","",E63) | W63: =IF(AND(G63="",H63="",G64=""),"",ROUND(SUM(G63,H63/60)*G64,1)) | X63: =IF(AND(I63="",J63="",I64=""),"",ROUND(SUM(I63,J63/60)*I64,1)) | Y63: =IF(AND(K63="",L63="",K64=""),"",ROUND(SUM(K63,L63/60)*K64,1))
G64: =IF(SUM(G63:H63)>0,1,"") | I64: =IF(SUM(I63:J63)>0,1,"") | K64: =IF(SUM(K63:L63)>0,1,"")
A65: =ROUND((ROW()-10)/2,0) -> 28 | C65: =IF(INDEX(設定!$C$9:$C$108,$A65,1)="","",INDEX(設定!$C$9:$C$108,$A65,1)) | D65: =IF(INDEX(設定!$D$9:$D$108,$A65,1)="","",INDEX(設定!$D$9:$D$108,$A65,1)) | E65: =IF(INDEX(設定!$E$9:$E$108,$A65,1)="","",INDEX(設定!$E$9:$E$108,$A65,1)) | F65: =IF(S65="","",IF(S65=1,"1：家族",IF(AND(S65>=2,S65<=5),"2：雇用",""))) | G65: =INT(INDEX(設定!$H$9:H$108,$A65,1)) -> 0 | H65: =IF(INDEX(設定!$H$9:$H$108,$A65,1)=0,"",ROUND(MOD(INDEX(設定!$H$9:$H$108,$A65,1),1)*60,0)) | I65: =INT(INDEX(設定!$I$9:$I$108,$A65,1)) -> 0 | J65: =IF(INDEX(設定!$I$9:$I$108,$A65,1)=0,"",ROUND(MOD(INDEX(設定!$I$9:$I$108,$A65,1),1)*60,0)) | K65: =INT(INDEX(設定!$J$9:$J$108,$A65,1)) -> 0 | L65: =IF(INDEX(設定!$J$9:$J$108,$A65,1)=0,"",ROUND(MOD(INDEX(設定!$J$9:$J$108,$A65,1),1)*60,0)) | S65: =IF(INDEX(設定!$F$9:$F$108,$A65,1)="","",VALUE(LEFT(INDEX(設定!$F$9:$F$108,$A65,1),1))) | T65: =IF(C65="","",C65) | U65: =IF(D65="","",IF(D65="1：男",1,IF(D65="2：女",2))) | V65: =IF(E65="","",E65) | W65: =IF(AND(G65="",H65="",G66=""),"",ROUND(SUM(G65,H65/60)*G66,1)) | X65: =IF(AND(I65="",J65="",I66=""),"",ROUND(SUM(I65,J65/60)*I66,1)) | Y65: =IF(AND(K65="",L65="",K66=""),"",ROUND(SUM(K65,L65/60)*K66,1))
G66: =IF(SUM(G65:H65)>0,1,"") | I66: =IF(SUM(I65:J65)>0,1,"") | K66: =IF(SUM(K65:L65)>0,1,"")
A67: =ROUND((ROW()-10)/2,0) -> 29 | C67: =IF(INDEX(設定!$C$9:$C$108,$A67,1)="","",INDEX(設定!$C$9:$C$108,$A67,1)) | D67: =IF(INDEX(設定!$D$9:$D$108,$A67,1)="","",INDEX(設定!$D$9:$D$108,$A67,1)) | E67: =IF(INDEX(設定!$E$9:$E$108,$A67,1)="","",INDEX(設定!$E$9:$E$108,$A67,1)) | F67: =IF(S67="","",IF(S67=1,"1：家族",IF(AND(S67>=2,S67<=5),"2：雇用",""))) | G67: =INT(INDEX(設定!$H$9:H$108,$A67,1)) -> 0 | H67: =IF(INDEX(設定!$H$9:$H$108,$A67,1)=0,"",ROUND(MOD(INDEX(設定!$H$9:$H$108,$A67,1),1)*60,0)) | I67: =INT(INDEX(設定!$I$9:$I$108,$A67,1)) -> 0 | J67: =IF(INDEX(設定!$I$9:$I$108,$A67,1)=0,"",ROUND(MOD(INDEX(設定!$I$9:$I$108,$A67,1),1)*60,0)) | K67: =INT(INDEX(設定!$J$9:$J$108,$A67,1)) -> 0 | L67: =IF(INDEX(設定!$J$9:$J$108,$A67,1)=0,"",ROUND(MOD(INDEX(設定!$J$9:$J$108,$A67,1),1)*60,0)) | S67: =IF(INDEX(設定!$F$9:$F$108,$A67,1)="","",VALUE(LEFT(INDEX(設定!$F$9:$F$108,$A67,1),1))) | T67: =IF(C67="","",C67) | U67: =IF(D67="","",IF(D67="1：男",1,IF(D67="2：女",2))) | V67: =IF(E67="","",E67) | W67: =IF(AND(G67="",H67="",G68=""),"",ROUND(SUM(G67,H67/60)*G68,1)) | X67: =IF(AND(I67="",J67="",I68=""),"",ROUND(SUM(I67,J67/60)*I68,1)) | Y67: =IF(AND(K67="",L67="",K68=""),"",ROUND(SUM(K67,L67/60)*K68,1))
G68: =IF(SUM(G67:H67)>0,1,"") | I68: =IF(SUM(I67:J67)>0,1,"") | K68: =IF(SUM(K67:L67)>0,1,"")
A69: =ROUND((ROW()-10)/2,0) -> 30 | C69: =IF(INDEX(設定!$C$9:$C$108,$A69,1)="","",INDEX(設定!$C$9:$C$108,$A69,1)) | D69: =IF(INDEX(設定!$D$9:$D$108,$A69,1)="","",INDEX(設定!$D$9:$D$108,$A69,1)) | E69: =IF(INDEX(設定!$E$9:$E$108,$A69,1)="","",INDEX(設定!$E$9:$E$108,$A69,1)) | F69: =IF(S69="","",IF(S69=1,"1：家族",IF(AND(S69>=2,S69<=5),"2：雇用",""))) | G69: =INT(INDEX(設定!$H$9:H$108,$A69,1)) -> 0 | H69: =IF(INDEX(設定!$H$9:$H$108,$A69,1)=0,"",ROUND(MOD(INDEX(設定!$H$9:$H$108,$A69,1),1)*60,0)) | I69: =INT(INDEX(設定!$I$9:$I$108,$A69,1)) -> 0 | J69: =IF(INDEX(設定!$I$9:$I$108,$A69,1)=0,"",ROUND(MOD(INDEX(設定!$I$9:$I$108,$A69,1),1)*60,0)) | K69: =INT(INDEX(設定!$J$9:$J$108,$A69,1)) -> 0 | L69: =IF(INDEX(設定!$J$9:$J$108,$A69,1)=0,"",ROUND(MOD(INDEX(設定!$J$9:$J$108,$A69,1),1)*60,0)) | S69: =IF(INDEX(設定!$F$9:$F$108,$A69,1)="","",VALUE(LEFT(INDEX(設定!$F$9:$F$108,$A69,1),1))) | T69: =IF(C69="","",C69) | U69: =IF(D69="","",IF(D69="1：男",1,IF(D69="2：女",2))) | V69: =IF(E69="","",E69) | W69: =IF(AND(G69="",H69="",G70=""),"",ROUND(SUM(G69,H69/60)*G70,1)) | X69: =IF(AND(I69="",J69="",I70=""),"",ROUND(SUM(I69,J69/60)*I70,1)) | Y69: =IF(AND(K69="",L69="",K70=""),"",ROUND(SUM(K69,L69/60)*K70,1))
G70: =IF(SUM(G69:H69)>0,1,"") | I70: =IF(SUM(I69:J69)>0,1,"") | K70: =IF(SUM(K69:L69)>0,1,"")
B72: ２ 調査対象畜に関する１以外の作業
S74: 1：家族 2：雇用 3：ゆい・手間替え受け 4：手伝い・共同作業受け 5：同居人 | T74: 氏 名 | U74: 1：男 2：女 | V74: 年齢 | W74: 生産管理 労働時間 | X74: 間接労働時間 | Z74: 経営管理 労働時間
C75: 氏 名 | D75: 性別 | E75: 年齢 | F75: 家族 ・ 雇用 | G75: 自給飼料の生産 | H75: 購入付帯労働時間 | I75: 建物・農機具等の修繕 | J75: 集会出席時間 | K75: 技術取得時間 | L75: 簿記記帳時間 | M75: 経営管理労働時間 | X75: 自給飼料の 生産 | Y75: 建物等の修繕 購入付帯労働
A77: 1 | C77: =IF(INDEX(設定!$C$9:$C$108,$A77,1)="","",INDEX(設定!$C$9:$C$108,$A77,1)) | D77: =IF(INDEX(設定!$D$9:$D$108,$A77,1)="","",INDEX(設定!$D$9:$D$108,$A77,1)) | E77: =IF(INDEX(設定!$E$9:$E$108,$A77,1)="","",INDEX(設定!$E$9:$E$108,$A77,1)) | F77: =IF(S77="","",IF(S77=1,"1：家族",IF(AND(S77>=2,S77<=5),"2：雇用",""))) | G77: =IF(INDEX(設定!L$9:L$108,$A77,1)=0,"",ROUND(INDEX(設定!L$9:L$108,$A77,1),1)) | H77: =IF(INDEX(設定!M$9:M$108,$A77,1)=0,"",ROUND(INDEX(設定!M$9:M$108,$A77,1),1)) | I77: =IF(INDEX(設定!N$9:N$108,$A77,1)=0,"",ROUND(INDEX(設定!N$9:N$108,$A77,1),1)) | J77: =IF(INDEX(設定!O$9:O$108,$A77,1)=0,"",ROUND(INDEX(設定!O$9:O$108,$A77,1),1)) | K77: =IF(INDEX(設定!P$9:P$108,$A77,1)=0,"",ROUND(INDEX(設定!P$9:P$108,$A77,1),1)) | L77: =IF(INDEX(設定!Q$9:Q$108,$A77,1)=0,"",ROUND(INDEX(設定!Q$9:Q$108,$A77,1),1)) | M77: =IF(INDEX(設定!R$9:R$108,$A77,1)=0,"",ROUND(INDEX(設定!R$9:R$108,$A77,1),1)) | S77: =IF(INDEX(設定!$F$9:$F$108,$A77,1)="","",VALUE(LEFT(INDEX(設定!$F$9:$F$108,$A77,1),1))) | T77: =IF(C77="","",C77) | U77: =IF(D77="","",IF(D77="1：男",1,IF(D77="2：女",2))) | V77: =IF(E77="","",E77) | W77: =SUM(J77:L77) -> 0 | X77: =G77 | Y77: =SUM(H77:I77) -> 0 | Z77: =M77
A78: 2 | C78: =IF(INDEX(設定!$C$9:$C$108,$A78,1)="","",INDEX(設定!$C$9:$C$108,$A78,1)) | D78: =IF(INDEX(設定!$D$9:$D$108,$A78,1)="","",INDEX(設定!$D$9:$D$108,$A78,1)) | E78: =IF(INDEX(設定!$E$9:$E$108,$A78,1)="","",INDEX(設定!$E$9:$E$108,$A78,1)) | F78: =IF(S78="","",IF(S78=1,"1：家族",IF(AND(S78>=2,S78<=5),"2：雇用",""))) | G78: =IF(INDEX(設定!L$9:L$108,$A78,1)=0,"",ROUND(INDEX(設定!L$9:L$108,$A78,1),1)) | H78: =IF(INDEX(設定!M$9:M$108,$A78,1)=0,"",ROUND(INDEX(設定!M$9:M$108,$A78,1),1)) | I78: =IF(INDEX(設定!N$9:N$108,$A78,1)=0,"",ROUND(INDEX(設定!N$9:N$108,$A78,1),1)) | J78: =IF(INDEX(設定!O$9:O$108,$A78,1)=0,"",ROUND(INDEX(設定!O$9:O$108,$A78,1),1)) | K78: =IF(INDEX(設定!P$9:P$108,$A78,1)=0,"",ROUND(INDEX(設定!P$9:P$108,$A78,1),1)) | L78: =IF(INDEX(設定!Q$9:Q$108,$A78,1)=0,"",ROUND(INDEX(設定!Q$9:Q$108,$A78,1),1)) | M78: =IF(INDEX(設定!R$9:R$108,$A78,1)=0,"",ROUND(INDEX(設定!R$9:R$108,$A78,1),1)) | S78: =IF(INDEX(設定!$F$9:$F$108,$A78,1)="","",VALUE(LEFT(INDEX(設定!$F$9:$F$108,$A78,1),1))) | T78: =IF(C78="","",C78) | U78: =IF(D78="","",IF(D78="1：男",1,IF(D78="2：女",2))) | V78: =IF(E78="","",E78) | W78: =SUM(J78:L78) -> 0 | X78: =G78 | Y78: =SUM(H78:I78) -> 0 | Z78: =M78
A79: 3 | C79: =IF(INDEX(設定!$C$9:$C$108,$A79,1)="","",INDEX(設定!$C$9:$C$108,$A79,1)) | D79: =IF(INDEX(設定!$D$9:$D$108,$A79,1)="","",INDEX(設定!$D$9:$D$108,$A79,1)) | E79: =IF(INDEX(設定!$E$9:$E$108,$A79,1)="","",INDEX(設定!$E$9:$E$108,$A79,1)) | F79: =IF(S79="","",IF(S79=1,"1：家族",IF(AND(S79>=2,S79<=5),"2：雇用",""))) | G79: =IF(INDEX(設定!L$9:L$108,$A79,1)=0,"",ROUND(INDEX(設定!L$9:L$108,$A79,1),1)) | H79: =IF(INDEX(設定!M$9:M$108,$A79,1)=0,"",ROUND(INDEX(設定!M$9:M$108,$A79,1),1)) | I79: =IF(INDEX(設定!N$9:N$108,$A79,1)=0,"",ROUND(INDEX(設定!N$9:N$108,$A79,1),1)) | J79: =IF(INDEX(設定!O$9:O$108,$A79,1)=0,"",ROUND(INDEX(設定!O$9:O$108,$A79,1),1)) | K79: =IF(INDEX(設定!P$9:P$108,$A79,1)=0,"",ROUND(INDEX(設定!P$9:P$108,$A79,1),1)) | L79: =IF(INDEX(設定!Q$9:Q$108,$A79,1)=0,"",ROUND(INDEX(設定!Q$9:Q$108,$A79,1),1)) | M79: =IF(INDEX(設定!R$9:R$108,$A79,1)=0,"",ROUND(INDEX(設定!R$9:R$108,$A79,1),1)) | S79: =IF(INDEX(設定!$F$9:$F$108,$A79,1)="","",VALUE(LEFT(INDEX(設定!$F$9:$F$108,$A79,1),1))) | T79: =IF(C79="","",C79) | U79: =IF(D79="","",IF(D79="1：男",1,IF(D79="2：女",2))) | V79: =IF(E79="","",E79) | W79: =SUM(J79:L79) -> 0 | X79: =G79 | Y79: =SUM(H79:I79) -> 0 | Z79: =M79
A80: 4 | C80: =IF(INDEX(設定!$C$9:$C$108,$A80,1)="","",INDEX(設定!$C$9:$C$108,$A80,1)) | D80: =IF(INDEX(設定!$D$9:$D$108,$A80,1)="","",INDEX(設定!$D$9:$D$108,$A80,1)) | E80: =IF(INDEX(設定!$E$9:$E$108,$A80,1)="","",INDEX(設定!$E$9:$E$108,$A80,1)) | F80: =IF(S80="","",IF(S80=1,"1：家族",IF(AND(S80>=2,S80<=5),"2：雇用",""))) | G80: =IF(INDEX(設定!L$9:L$108,$A80,1)=0,"",ROUND(INDEX(設定!L$9:L$108,$A80,1),1)) | H80: =IF(INDEX(設定!M$9:M$108,$A80,1)=0,"",ROUND(INDEX(設定!M$9:M$108,$A80,1),1)) | I80: =IF(INDEX(設定!N$9:N$108,$A80,1)=0,"",ROUND(INDEX(設定!N$9:N$108,$A80,1),1)) | J80: =IF(INDEX(設定!O$9:O$108,$A80,1)=0,"",ROUND(INDEX(設定!O$9:O$108,$A80,1),1)) | K80: =IF(INDEX(設定!P$9:P$108,$A80,1)=0,"",ROUND(INDEX(設定!P$9:P$108,$A80,1),1)) | L80: =IF(INDEX(設定!Q$9:Q$108,$A80,1)=0,"",ROUND(INDEX(設定!Q$9:Q$108,$A80,1),1)) | M80: =IF(INDEX(設定!R$9:R$108,$A80,1)=0,"",ROUND(INDEX(設定!R$9:R$108,$A80,1),1)) | S80: =IF(INDEX(設定!$F$9:$F$108,$A80,1)="","",VALUE(LEFT(INDEX(設定!$F$9:$F$108,$A80,1),1))) | T80: =IF(C80="","",C80) | U80: =IF(D80="","",IF(D80="1：男",1,IF(D80="2：女",2))) | V80: =IF(E80="","",E80) | W80: =SUM(J80:L80) -> 0 | X80: =G80 | Y80: =SUM(H80:I80) -> 0 | Z80: =M80
A81: 5 | C81: =IF(INDEX(設定!$C$9:$C$108,$A81,1)="","",INDEX(設定!$C$9:$C$108,$A81,1)) | D81: =IF(INDEX(設定!$D$9:$D$108,$A81,1)="","",INDEX(設定!$D$9:$D$108,$A81,1)) | E81: =IF(INDEX(設定!$E$9:$E$108,$A81,1)="","",INDEX(設定!$E$9:$E$108,$A81,1)) | F81: =IF(S81="","",IF(S81=1,"1：家族",IF(AND(S81>=2,S81<=5),"2：雇用",""))) | G81: =IF(INDEX(設定!L$9:L$108,$A81,1)=0,"",ROUND(INDEX(設定!L$9:L$108,$A81,1),1)) | H81: =IF(INDEX(設定!M$9:M$108,$A81,1)=0,"",ROUND(INDEX(設定!M$9:M$108,$A81,1),1)) | I81: =IF(INDEX(設定!N$9:N$108,$A81,1)=0,"",ROUND(INDEX(設定!N$9:N$108,$A81,1),1)) | J81: =IF(INDEX(設定!O$9:O$108,$A81,1)=0,"",ROUND(INDEX(設定!O$9:O$108,$A81,1),1)) | K81: =IF(INDEX(設定!P$9:P$108,$A81,1)=0,"",ROUND(INDEX(設定!P$9:P$108,$A81,1),1)) | L81: =IF(INDEX(設定!Q$9:Q$108,$A81,1)=0,"",ROUND(INDEX(設定!Q$9:Q$108,$A81,1),1)) | M81: =IF(INDEX(設定!R$9:R$108,$A81,1)=0,"",ROUND(INDEX(設定!R$9:R$108,$A81,1),1)) | S81: =IF(INDEX(設定!$F$9:$F$108,$A81,1)="","",VALUE(LEFT(INDEX(設定!$F$9:$F$108,$A81,1),1))) | T81: =IF(C81="","",C81) | U81: =IF(D81="","",IF(D81="1：男",1,IF(D81="2：女",2))) | V81: =IF(E81="","",E81) | W81: =SUM(J81:L81) -> 0 | X81: =G81 | Y81: =SUM(H81:I81) -> 0 | Z81: =M81
A82: 6 | C82: =IF(INDEX(設定!$C$9:$C$108,$A82,1)="","",INDEX(設定!$C$9:$C$108,$A82,1)) | D82: =IF(INDEX(設定!$D$9:$D$108,$A82,1)="","",INDEX(設定!$D$9:$D$108,$A82,1)) | E82: =IF(INDEX(設定!$E$9:$E$108,$A82,1)="","",INDEX(設定!$E$9:$E$108,$A82,1)) | F82: =IF(S82="","",IF(S82=1,"1：家族",IF(AND(S82>=2,S82<=5),"2：雇用",""))) | G82: =IF(INDEX(設定!L$9:L$108,$A82,1)=0,"",ROUND(INDEX(設定!L$9:L$108,$A82,1),1)) | H82: =IF(INDEX(設定!M$9:M$108,$A82,1)=0,"",ROUND(INDEX(設定!M$9:M$108,$A82,1),1)) | I82: =IF(INDEX(設定!N$9:N$108,$A82,1)=0,"",ROUND(INDEX(設定!N$9:N$108,$A82,1),1)) | J82: =IF(INDEX(設定!O$9:O$108,$A82,1)=0,"",ROUND(INDEX(設定!O$9:O$108,$A82,1),1)) | K82: =IF(INDEX(設定!P$9:P$108,$A82,1)=0,"",ROUND(INDEX(設定!P$9:P$108,$A82,1),1)) | L82: =IF(INDEX(設定!Q$9:Q$108,$A82,1)=0,"",ROUND(INDEX(設定!Q$9:Q$108,$A82,1),1)) | M82: =IF(INDEX(設定!R$9:R$108,$A82,1)=0,"",ROUND(INDEX(設定!R$9:R$108,$A82,1),1)) | S82: =IF(INDEX(設定!$F$9:$F$108,$A82,1)="","",VALUE(LEFT(INDEX(設定!$F$9:$F$108,$A82,1),1))) | T82: =IF(C82="","",C82) | U82: =IF(D82="","",IF(D82="1：男",1,IF(D82="2：女",2))) | V82: =IF(E82="","",E82) | W82: =SUM(J82:L82) -> 0 | X82: =G82 | Y82: =SUM(H82:I82) -> 0 | Z82: =M82
A83: 7 | C83: =IF(INDEX(設定!$C$9:$C$108,$A83,1)="","",INDEX(設定!$C$9:$C$108,$A83,1)) | D83: =IF(INDEX(設定!$D$9:$D$108,$A83,1)="","",INDEX(設定!$D$9:$D$108,$A83,1)) | E83: =IF(INDEX(設定!$E$9:$E$108,$A83,1)="","",INDEX(設定!$E$9:$E$108,$A83,1)) | F83: =IF(S83="","",IF(S83=1,"1：家族",IF(AND(S83>=2,S83<=5),"2：雇用",""))) | G83: =IF(INDEX(設定!L$9:L$108,$A83,1)=0,"",ROUND(INDEX(設定!L$9:L$108,$A83,1),1)) | H83: =IF(INDEX(設定!M$9:M$108,$A83,1)=0,"",ROUND(INDEX(設定!M$9:M$108,$A83,1),1)) | I83: =IF(INDEX(設定!N$9:N$108,$A83,1)=0,"",ROUND(INDEX(設定!N$9:N$108,$A83,1),1)) | J83: =IF(INDEX(設定!O$9:O$108,$A83,1)=0,"",ROUND(INDEX(設定!O$9:O$108,$A83,1),1)) | K83: =IF(INDEX(設定!P$9:P$108,$A83,1)=0,"",ROUND(INDEX(設定!P$9:P$108,$A83,1),1)) | L83: =IF(INDEX(設定!Q$9:Q$108,$A83,1)=0,"",ROUND(INDEX(設定!Q$9:Q$108,$A83,1),1)) | M83: =IF(INDEX(設定!R$9:R$108,$A83,1)=0,"",ROUND(INDEX(設定!R$9:R$108,$A83,1),1)) | S83: =IF(INDEX(設定!$F$9:$F$108,$A83,1)="","",VALUE(LEFT(INDEX(設定!$F$9:$F$108,$A83,1),1))) | T83: =IF(C83="","",C83) | U83: =IF(D83="","",IF(D83="1：男",1,IF(D83="2：女",2))) | V83: =IF(E83="","",E83) | W83: =SUM(J83:L83) -> 0 | X83: =G83 | Y83: =SUM(H83:I83) -> 0 | Z83: =M83
A84: 8 | C84: =IF(INDEX(設定!$C$9:$C$108,$A84,1)="","",INDEX(設定!$C$9:$C$108,$A84,1)) | D84: =IF(INDEX(設定!$D$9:$D$108,$A84,1)="","",INDEX(設定!$D$9:$D$108,$A84,1)) | E84: =IF(INDEX(設定!$E$9:$E$108,$A84,1)="","",INDEX(設定!$E$9:$E$108,$A84,1)) | F84: =IF(S84="","",IF(S84=1,"1：家族",IF(AND(S84>=2,S84<=5),"2：雇用",""))) | G84: =IF(INDEX(設定!L$9:L$108,$A84,1)=0,"",ROUND(INDEX(設定!L$9:L$108,$A84,1),1)) | H84: =IF(INDEX(設定!M$9:M$108,$A84,1)=0,"",ROUND(INDEX(設定!M$9:M$108,$A84,1),1)) | I84: =IF(INDEX(設定!N$9:N$108,$A84,1)=0,"",ROUND(INDEX(設定!N$9:N$108,$A84,1),1)) | J84: =IF(INDEX(設定!O$9:O$108,$A84,1)=0,"",ROUND(INDEX(設定!O$9:O$108,$A84,1),1)) | K84: =IF(INDEX(設定!P$9:P$108,$A84,1)=0,"",ROUND(INDEX(設定!P$9:P$108,$A84,1),1)) | L84: =IF(INDEX(設定!Q$9:Q$108,$A84,1)=0,"",ROUND(INDEX(設定!Q$9:Q$108,$A84,1),1)) | M84: =IF(INDEX(設定!R$9:R$108,$A84,1)=0,"",ROUND(INDEX(設定!R$9:R$108,$A84,1),1)) | S84: =IF(INDEX(設定!$F$9:$F$108,$A84,1)="","",VALUE(LEFT(INDEX(設定!$F$9:$F$108,$A84,1),1))) | T84: =IF(C84="","",C84) | U84: =IF(D84="","",IF(D84="1：男",1,IF(D84="2：女",2))) | V84: =IF(E84="","",E84) | W84: =SUM(J84:L84) -> 0 | X84: =G84 | Y84: =SUM(H84:I84) -> 0 | Z84: =M84
A85: 9 | C85: =IF(INDEX(設定!$C$9:$C$108,$A85,1)="","",INDEX(設定!$C$9:$C$108,$A85,1)) | D85: =IF(INDEX(設定!$D$9:$D$108,$A85,1)="","",INDEX(設定!$D$9:$D$108,$A85,1)) | E85: =IF(INDEX(設定!$E$9:$E$108,$A85,1)="","",INDEX(設定!$E$9:$E$108,$A85,1)) | F85: =IF(S85="","",IF(S85=1,"1：家族",IF(AND(S85>=2,S85<=5),"2：雇用",""))) | G85: =IF(INDEX(設定!L$9:L$108,$A85,1)=0,"",ROUND(INDEX(設定!L$9:L$108,$A85,1),1)) | H85: =IF(INDEX(設定!M$9:M$108,$A85,1)=0,"",ROUND(INDEX(設定!M$9:M$108,$A85,1),1)) | I85: =IF(INDEX(設定!N$9:N$108,$A85,1)=0,"",ROUND(INDEX(設定!N$9:N$108,$A85,1),1)) | J85: =IF(INDEX(設定!O$9:O$108,$A85,1)=0,"",ROUND(INDEX(設定!O$9:O$108,$A85,1),1)) | K85: =IF(INDEX(設定!P$9:P$108,$A85,1)=0,"",ROUND(INDEX(設定!P$9:P$108,$A85,1),1)) | L85: =IF(INDEX(設定!Q$9:Q$108,$A85,1)=0,"",ROUND(INDEX(設定!Q$9:Q$108,$A85,1),1)) | M85: =IF(INDEX(設定!R$9:R$108,$A85,1)=0,"",ROUND(INDEX(設定!R$9:R$108,$A85,1),1)) | S85: =IF(INDEX(設定!$F$9:$F$108,$A85,1)="","",VALUE(LEFT(INDEX(設定!$F$9:$F$108,$A85,1),1))) | T85: =IF(C85="","",C85) | U85: =IF(D85="","",IF(D85="1：男",1,IF(D85="2：女",2))) | V85: =IF(E85="","",E85) | W85: =SUM(J85:L85) -> 0 | X85: =G85 | Y85: =SUM(H85:I85) -> 0 | Z85: =M85
A86: 10 | C86: =IF(INDEX(設定!$C$9:$C$108,$A86,1)="","",INDEX(設定!$C$9:$C$108,$A86,1)) | D86: =IF(INDEX(設定!$D$9:$D$108,$A86,1)="","",INDEX(設定!$D$9:$D$108,$A86,1)) | E86: =IF(INDEX(設定!$E$9:$E$108,$A86,1)="","",INDEX(設定!$E$9:$E$108,$A86,1)) | F86: =IF(S86="","",IF(S86=1,"1：家族",IF(AND(S86>=2,S86<=5),"2：雇用",""))) | G86: =IF(INDEX(設定!L$9:L$108,$A86,1)=0,"",ROUND(INDEX(設定!L$9:L$108,$A86,1),1)) | H86: =IF(INDEX(設定!M$9:M$108,$A86,1)=0,"",ROUND(INDEX(設定!M$9:M$108,$A86,1),1)) | I86: =IF(INDEX(設定!N$9:N$108,$A86,1)=0,"",ROUND(INDEX(設定!N$9:N$108,$A86,1),1)) | J86: =IF(INDEX(設定!O$9:O$108,$A86,1)=0,"",ROUND(INDEX(設定!O$9:O$108,$A86,1),1)) | K86: =IF(INDEX(設定!P$9:P$108,$A86,1)=0,"",ROUND(INDEX(設定!P$9:P$108,$A86,1),1)) | L86: =IF(INDEX(設定!Q$9:Q$108,$A86,1)=0,"",ROUND(INDEX(設定!Q$9:Q$108,$A86,1),1)) | M86: =IF(INDEX(設定!R$9:R$108,$A86,1)=0,"",ROUND(INDEX(設定!R$9:R$108,$A86,1),1)) | S86: =IF(INDEX(設定!$F$9:$F$108,$A86,1)="","",VALUE(LEFT(INDEX(設定!$F$9:$F$108,$A86,1),1))) | T86: =IF(C86="","",C86) | U86: =IF(D86="","",IF(D86="1：男",1,IF(D86="2：女",2))) | V86: =IF(E86="","",E86) | W86: =SUM(J86:L86) -> 0 | X86: =G86 | Y86: =SUM(H86:I86) -> 0 | Z86: =M86
A87: 11 | C87: =IF(INDEX(設定!$C$9:$C$108,$A87,1)="","",INDEX(設定!$C$9:$C$108,$A87,1)) | D87: =IF(INDEX(設定!$D$9:$D$108,$A87,1)="","",INDEX(設定!$D$9:$D$108,$A87,1)) | E87: =IF(INDEX(設定!$E$9:$E$108,$A87,1)="","",INDEX(設定!$E$9:$E$108,$A87,1)) | F87: =IF(S87="","",IF(S87=1,"1：家族",IF(AND(S87>=2,S87<=5),"2：雇用",""))) | G87: =IF(INDEX(設定!L$9:L$108,$A87,1)=0,"",ROUND(INDEX(設定!L$9:L$108,$A87,1),1)) | H87: =IF(INDEX(設定!M$9:M$108,$A87,1)=0,"",ROUND(INDEX(設定!M$9:M$108,$A87,1),1)) | I87: =IF(INDEX(設定!N$9:N$108,$A87,1)=0,"",ROUND(INDEX(設定!N$9:N$108,$A87,1),1)) | J87: =IF(INDEX(設定!O$9:O$108,$A87,1)=0,"",ROUND(INDEX(設定!O$9:O$108,$A87,1),1)) | K87: =IF(INDEX(設定!P$9:P$108,$A87,1)=0,"",ROUND(INDEX(設定!P$9:P$108,$A87,1),1)) | L87: =IF(INDEX(設定!Q$9:Q$108,$A87,1)=0,"",ROUND(INDEX(設定!Q$9:Q$108,$A87,1),1)) | M87: =IF(INDEX(設定!R$9:R$108,$A87,1)=0,"",ROUND(INDEX(設定!R$9:R$108,$A87,1),1)) | S87: =IF(INDEX(設定!$F$9:$F$108,$A87,1)="","",VALUE(LEFT(INDEX(設定!$F$9:$F$108,$A87,1),1))) | T87: =IF(C87="","",C87) | U87: =IF(D87="","",IF(D87="1：男",1,IF(D87="2：女",2))) | V87: =IF(E87="","",E87) | W87: =SUM(J87:L87) -> 0 | X87: =G87 | Y87: =SUM(H87:I87) -> 0 | Z87: =M87
A88: 12 | C88: =IF(INDEX(設定!$C$9:$C$108,$A88,1)="","",INDEX(設定!$C$9:$C$108,$A88,1)) | D88: =IF(INDEX(設定!$D$9:$D$108,$A88,1)="","",INDEX(設定!$D$9:$D$108,$A88,1)) | E88: =IF(INDEX(設定!$E$9:$E$108,$A88,1)="","",INDEX(設定!$E$9:$E$108,$A88,1)) | F88: =IF(S88="","",IF(S88=1,"1：家族",IF(AND(S88>=2,S88<=5),"2：雇用",""))) | G88: =IF(INDEX(設定!L$9:L$108,$A88,1)=0,"",ROUND(INDEX(設定!L$9:L$108,$A88,1),1)) | H88: =IF(INDEX(設定!M$9:M$108,$A88,1)=0,"",ROUND(INDEX(設定!M$9:M$108,$A88,1),1)) | I88: =IF(INDEX(設定!N$9:N$108,$A88,1)=0,"",ROUND(INDEX(設定!N$9:N$108,$A88,1),1)) | J88: =IF(INDEX(設定!O$9:O$108,$A88,1)=0,"",ROUND(INDEX(設定!O$9:O$108,$A88,1),1)) | K88: =IF(INDEX(設定!P$9:P$108,$A88,1)=0,"",ROUND(INDEX(設定!P$9:P$108,$A88,1),1)) | L88: =IF(INDEX(設定!Q$9:Q$108,$A88,1)=0,"",ROUND(INDEX(設定!Q$9:Q$108,$A88,1),1)) | M88: =IF(INDEX(設定!R$9:R$108,$A88,1)=0,"",ROUND(INDEX(設定!R$9:R$108,$A88,1),1)) | S88: =IF(INDEX(設定!$F$9:$F$108,$A88,1)="","",VALUE(LEFT(INDEX(設定!$F$9:$F$108,$A88,1),1))) | T88: =IF(C88="","",C88) | U88: =IF(D88="","",IF(D88="1：男",1,IF(D88="2：女",2))) | V88: =IF(E88="","",E88) | W88: =SUM(J88:L88) -> 0 | X88: =G88 | Y88: =SUM(H88:I88) -> 0 | Z88: =M88
... A106: 30 | C106: =IF(INDEX(設定!$C$9:$C$108,$A106,1)="","",INDEX(設定!$C$9:$C$108,$A106,1)) | D106: =IF(INDEX(設定!$D$9:$D$108,$A106,1)="","",INDEX(設定!$D$9:$D$108,$A106,1)) | E106: =IF(INDEX(設定!$E$9:$E$108,$A106,1)="","",INDEX(設定!$E$9:$E$108,$A106,1)) | F106: =IF(S106="","",IF(S106=1,"1：家族",IF(AND(S106>=2,S106<=5),"2：雇用",""))) | G106: =IF(INDEX(設定!L$9:L$108,$A106,1)=0,"",ROUND(INDEX(設定!L$9:L$108,$A106,1),1)) | H106: =IF(INDEX(設定!M$9:M$108,$A106,1)=0,"",ROUND(INDEX(設定!M$9:M$108,$A106,1),1)) | I106: =IF(INDEX(設定!N$9:N$108,$A106,1)=0,"",ROUND(INDEX(設定!N$9:N$108,$A106,1),1)) | J106: =IF(INDEX(設定!O$9:O$108,$A106,1)=0,"",ROUND(INDEX(設定!O$9:O$108,$A106,1),1)) | K106: =IF(INDEX(設定!P$9:P$108,$A106,1)=0,"",ROUND(INDEX(設定!P$9:P$108,$A106,1),1)) | L106: =IF(INDEX(設定!Q$9:Q$108,$A106,1)=0,"",ROUND(INDEX(設定!Q$9:Q$108,$A106,1),1)) | M106: =IF(INDEX(設定!R$9:R$108,$A106,1)=0,"",ROUND(INDEX(設定!R$9:R$108,$A106,1),1)) | S106: =IF(INDEX(設定!$F$9:$F$108,$A106,1)="","",VALUE(LEFT(INDEX(設定!$F$9:$F$108,$A106,1),1))) | T106: =IF(C106="","",C106) | U106: =IF(D106="","",IF(D106="1：男",1,IF(D106="2：女",2))) | V106: =IF(E106="","",E106) | W106: =SUM(J106:L106) -> 0 | X106: =G106 | Y106: =SUM(H106:I106) -> 0 | Z106: =M106
C109: 雇用者（ヘルパー、研修生等）に支払った賃金（現物支給も含む。）を男女別に入力してください。 | S109: 支払賃金
C110: 区 分 | D110: 金 額（円） | E110: 負担割合（％） | S110: 区 分 | T110: 金額（円）
E111: 調査対象畜 | F111: 自給牧草 | T111: 調査対象畜 | U111: 自給牧草
C112: 男 | S112: 男 | T112: =IF(E112="","",ROUND(D112*E112%,0)) | U112: =IF(F112="","",ROUND(D112*(F112%),0))
C113: 女 | S113: 女 | T113: =IF(E113="","",ROUND(D113*E113%,0)) | U113: =IF(F113="","",ROUND(D113*(F113%),0))

Sheet 【12】労働時間（経営分析・牛乳）
C1: 畜産物生産費統計 調査票貼付シート
C8: １ 構成員
C10: 作 業 種 類 | D10: 内 容 例 示 | X10: 構成員の年齢別労働時間
X11: 65歳未満 | Y11: 65～69歳 | Z11: 70～74歳 | AA11: 75歳以上
C12: 飼料の調理・給与・給水 | D12: 飼料材料の裁断・粉砕・挽割煮炊き、麦・豆類の水浸および芽出し、飼料の混配合などの調理・給与・給水 | X12: =ROUND(SUMIFS(設定!$H$9:$H$108,設定!$E$9:$E$108,"<65",設定!$F$9:$F$108,"=1：構成員"),1) -> 0 | Y12: =ROUND(SUMIFS(設定!$H$9:$H$108,設定!$E$9:$E$108,">=65",設定!$E$9:$E$108,"<70",設定!$F$9:$F$108,"=1：構成員"),1) -> 0 | Z12: =ROUND(SUMIFS(設定!$H$9:$H$108,設定!$E$9:$E$108,">=70",設定!$E$9:$E$108,"<75",設定!$F$9:$F$108,"=1：構成員"),1) -> 0 | AA12: =ROUND(SUMIFS(設定!$H$9:$H$108,設定!$E$9:$E$108,">=75",設定!$F$9:$F$108,"=1：構成員"),1) -> 0
C13: 敷料搬入・きゅう肥搬出 | D13: 稲わら・敷草等敷料の畜舎への投入、ふんかき、きゅう肥（尿を含む。）の最寄り場所（たい肥舎等）までの運搬作業 | X13: =ROUND(SUMIFS(設定!$I$9:$I$108,設定!$E$9:$E$108,"<65",設定!$F$9:$F$108,"=1：構成員"),1) -> 0 | Y13: =ROUND(SUMIFS(設定!$I$9:$I$108,設定!$E$9:$E$108,">=65",設定!$E$9:$E$108,"<70",設定!$F$9:$F$108,"=1：構成員"),1) -> 0 | Z13: =ROUND(SUMIFS(設定!$I$9:$I$108,設定!$E$9:$E$108,">=70",設定!$E$9:$E$108,"<75",設定!$F$9:$F$108,"=1：構成員"),1) -> 0 | AA13: =ROUND(SUMIFS(設定!$I$9:$I$108,設定!$E$9:$E$108,">=75",設定!$F$9:$F$108,"=1：構成員"),1) -> 0
C14: 搾乳・牛乳処理・運搬 | D14: 乳房の清拭・搾乳準備・搾乳・搾乳後の濾過・冷却などの作業、搾乳関係器具の消毒・殺菌などの作業、販売のため最寄りの集乳所までの運搬作業 | X14: =ROUND(SUMIFS(設定!$J$9:$J$108,設定!$E$9:$E$108,"<65",設定!$F$9:$F$108,"=1：構成員"),1) -> 0 | Y14: =ROUND(SUMIFS(設定!$J$9:$J$108,設定!$E$9:$E$108,">=65",設定!$E$9:$E$108,"<70",設定!$F$9:$F$108,"=1：構成員"),1) -> 0 | Z14: =ROUND(SUMIFS(設定!$J$9:$J$108,設定!$E$9:$E$108,">=70",設定!$E$9:$E$108,"<75",設定!$F$9:$F$108,"=1：構成員"),1) -> 0 | AA14: =ROUND(SUMIFS(設定!$J$9:$J$108,設定!$E$9:$E$108,">=75",設定!$F$9:$F$108,"=1：構成員"),1) -> 0
C15: その他の飼育作業 | D15: 手入・運動・放牧作業、きゅう肥の処理（切り返し、加工）作業、衛生管理（殺虫剤の散布等） | X15: =ROUND(SUMIFS(設定!$K$9:$K$108,設定!$E$9:$E$108,"<65",設定!$F$9:$F$108,"=1：構成員"),1) -> 0 | Y15: =ROUND(SUMIFS(設定!$K$9:$K$108,設定!$E$9:$E$108,">=65",設定!$E$9:$E$108,"<70",設定!$F$9:$F$108,"=1：構成員"),1) -> 0 | Z15: =ROUND(SUMIFS(設定!$K$9:$K$108,設定!$E$9:$E$108,">=70",設定!$E$9:$E$108,"<75",設定!$F$9:$F$108,"=1：構成員"),1) -> 0 | AA15: =ROUND(SUMIFS(設定!$K$9:$K$108,設定!$E$9:$E$108,">=75",設定!$F$9:$F$108,"=1：構成員"),1) -> 0
C16: 生産管理 | D16: 集会出席、技術習得、簿記記帳（税務申告は含まない。）等 | X16: =ROUND(SUM(SUMIFS(設定!$O$9:$O$108,設定!$E$9:$E$108,"<65",設定!$F$9:$F$108,"=1：構成員"),SUMIFS(設定!$P$9:$P$108,設定!$E$9:$E$108,"<65",設定!$F$9:$F$108,"=1：構成員"),SUMIFS(設定!$Q$9:$Q$108,設定!$E$9:$E$108,"<65",設定!$F$9:$F$108,"=1：構成員")),1) -> 0 | Y16: =ROUND(SUM(SUMIFS(設定!$O$9:$O$108,設定!$E$9:$E$108,">=65",設定!$E$9:$E$108,"<70",設定!$F$9:$F$108,"=1：構成員"),SUMIFS(設定!$P$9:$P$108,設定!$E$9:$E$108,">=65",設定!$E$9:$E$108,"<70",設定!$F$9:$F$108,"=1：構成員"),SUMIFS(設定!$Q$9:$Q$108,設定!$E$9:$E$108,">=65",設定!$E$9:$E$108,"<70",設定!$F$9:$F$108,"=1：構成員")),1) -> 0 | Z16: =ROUND(SUM(SUMIFS(設定!$O$9:$O$108,設定!$E$9:$E$108,">=70",設定!$E$9:$E$108,"<75",設定!$F$9:$F$108,"=1：構成員"),SUMIFS(設定!$P$9:$P$108,設定!$E$9:$E$108,">=70",設定!$E$9:$E$108,"<75",設定!$F$9:$F$108,"=1：構成員"),SUMIFS(設定!$Q$9:$Q$108,設定!$E$9:$E$108,">=70",設定!$E$9:$E$108,"<75",設定!$F$9:$F$108,"=1：構成員")),1) -> 0 | AA16: =ROUND(SUM(SUMIFS(設定!$O$9:$O$108,設定!$E$9:$E$108,">=75",設定!$F$9:$F$108,"=1：構成員"),SUMIFS(設定!$P$9:$P$108,設定!$E$9:$E$108,">=75",設定!$F$9:$F$108,"=1：構成員"),SUMIFS(設定!$Q$9:$Q$108,設定!$E$9:$E$108,">=75",設定!$F$9:$F$108,"=1：構成員")),1) -> 0
C17: 内給飼料（牧草等）の生産 | D17: 整地、耕起、施肥、種まき、肥培管理、収穫、乾燥、貯蔵等 | X17: =ROUND(SUMIFS(設定!$L$9:$L$108,設定!$E$9:$E$108,"<65",設定!$F$9:$F$108,"=1：構成員"),1) -> 0 | Y17: =ROUND(SUMIFS(設定!$L$9:$L$108,設定!$E$9:$E$108,">=65",設定!$E$9:$E$108,"<70",設定!$F$9:$F$108,"=1：構成員"),1) -> 0 | Z17: =ROUND(SUMIFS(設定!$L$9:$L$108,設定!$E$9:$E$108,">=70",設定!$E$9:$E$108,"<75",設定!$F$9:$F$108,"=1：構成員"),1) -> 0 | AA17: =ROUND(SUMIFS(設定!$L$9:$L$108,設定!$E$9:$E$108,">=75",設定!$F$9:$F$108,"=1：構成員"),1) -> 0
C18: 上記以外の労働 | D18: 建物、自動車、農機具等の修繕や、購入資材の調達等 | X18: =ROUND(SUM(SUMIFS(設定!$M$9:$M$108,設定!$E$9:$E$108,"<65",設定!$F$9:$F$108,"=1：構成員"),SUMIFS(設定!$N$9:$N$108,設定!$E$9:$E$108,"<65",設定!$F$9:$F$108,"=1：構成員")),1) -> 0 | Y18: =ROUND(SUM(SUMIFS(設定!$M$9:$M$108,設定!$E$9:$E$108,">=65",設定!$E$9:$E$108,"<70",設定!$F$9:$F$108,"=1：構成員"),SUMIFS(設定!$N$9:$N$108,設定!$E$9:$E$108,">=65",設定!$E$9:$E$108,"<70",設定!$F$9:$F$108,"=1：構成員")),1) -> 0 | Z18: =ROUND(SUM(SUMIFS(設定!$M$9:$M$108,設定!$E$9:$E$108,">=70",設定!$E$9:$E$108,"<75",設定!$F$9:$F$108,"=1：構成員"),SUMIFS(設定!$N$9:$N$108,設定!$E$9:$E$108,">=70",設定!$E$9:$E$108,"<75",設定!$F$9:$F$108,"=1：構成員")),1) -> 0 | AA18: =ROUND(SUM(SUMIFS(設定!$M$9:$M$108,設定!$E$9:$E$108,">=75",設定!$F$9:$F$108,"=1：構成員"),SUMIFS(設定!$N$9:$N$108,設定!$E$9:$E$108,">=75",設定!$F$9:$F$108,"=1：構成員")),1) -> 0
C22: ２ 雇用
C24: 作 業 種 類 | D24: 内 容 例 示 | X24: 労働時間
C26: 飼料の調理・給与・給水 | D26: 飼料材料の裁断・粉砕・挽割煮炊き、麦・豆類の水浸および芽出し、飼料の混配合などの調理・給与・給水 | X26: =ROUND(SUMIFS(設定!$H$9:$H$108,設定!$F$9:$F$108,"=2：雇用"),1) -> 0
C27: 敷料搬入・きゅう肥搬出 | D27: 稲わら・敷草等敷料の畜舎への投入、ふんかき、きゅう肥（尿を含む。）の最寄り場所（たい肥舎等）までの運搬作業 | X27: =ROUND(SUMIFS(設定!$I$9:$I$108,設定!$F$9:$F$108,"=2：雇用"),1) -> 0
C28: 搾乳・牛乳処理・運搬 | D28: 乳房の清拭・搾乳準備・搾乳・搾乳後の濾過・冷却などの作業、搾乳関係器具の消毒・殺菌などの作業、販売のため最寄りの集乳所までの運搬作業 | X28: =ROUND(SUMIFS(設定!$J$9:$J$108,設定!$F$9:$F$108,"=2：雇用"),1) -> 0
C29: その他の飼育作業 | D29: 手入・運動・放牧作業、きゅう肥の処理（切り返し、加工）作業、衛生管理（殺虫剤の散布等） | X29: =ROUND(SUMIFS(設定!$K$9:$K$108,設定!$F$9:$F$108,"=2：雇用"),1) -> 0
C30: 内給飼料（牧草等）の生産 | D30: 整地、耕起、施肥、種まき、肥培管理、収穫、乾燥、貯蔵等 | X30: =ROUND(SUMIFS(設定!$L$9:$L$108,設定!$F$9:$F$108,"=2：雇用"),1) -> 0
C31: 上記以外の労働 | D31: 建物、自動車、農機具等の修繕や、購入資材の調達等 | X31: =ROUND(SUM(SUMIFS(設定!$M$9:$M$108,設定!$F$9:$F$108,"=2：雇用"),SUMIFS(設定!$N$9:$N$108,設定!$F$9:$F$108,"=2：雇用")),1) -> 0

Sheet 【12】労働時間（経営分析・牛乳以外）
C1: 畜産物生産費統計 調査票貼付シート
C8: １ 構成員
C10: 作 業 種 類 | D10: 内 容 例 示 | X10: 構成員の年齢別労働時間
X11: 65歳未満 | Y11: 65～69歳 | Z11: 70～74歳 | AA11: 75歳以上
C12: 飼料の調理・給与・給水 | D12: 飼料材料の裁断・粉砕・挽割煮炊き、麦・豆類の水浸および芽出し、飼料の混配合などの調理・給与・給水 | X12: =ROUND(SUMIFS(設定!$H$9:$H$108,設定!$E$9:$E$108,"<65",設定!$F$9:$F$108,"=1：構成員"),1) -> 0 | Y12: =ROUND(SUMIFS(設定!$H$9:$H$108,設定!$E$9:$E$108,">=65",設定!$E$9:$E$108,"<70",設定!$F$9:$F$108,"=1：構成員"),1) -> 0 | Z12: =ROUND(SUMIFS(設定!$H$9:$H$108,設定!$E$9:$E$108,">=70",設定!$E$9:$E$108,"<75",設定!$F$9:$F$108,"=1：構成員"),1) -> 0 | AA12: =ROUND(SUMIFS(設定!$H$9:$H$108,設定!$E$9:$E$108,">=75",設定!$F$9:$F$108,"=1：構成員"),1) -> 0
C13: 敷料搬入・きゅう肥搬出 | D13: 稲わら・敷草等敷料の畜舎への投入、ふんかき、きゅう肥（尿を含む。）の最寄り場所（たい肥舎等）までの運搬作業 | X13: =ROUND(SUMIFS(設定!$I$9:$I$108,設定!$E$9:$E$108,"<65",設定!$F$9:$F$108,"=1：構成員"),1) -> 0 | Y13: =ROUND(SUMIFS(設定!$I$9:$I$108,設定!$E$9:$E$108,">=65",設定!$E$9:$E$108,"<70",設定!$F$9:$F$108,"=1：構成員"),1) -> 0 | Z13: =ROUND(SUMIFS(設定!$I$9:$I$108,設定!$E$9:$E$108,">=70",設定!$E$9:$E$108,"<75",設定!$F$9:$F$108,"=1：構成員"),1) -> 0 | AA13: =ROUND(SUMIFS(設定!$I$9:$I$108,設定!$E$9:$E$108,">=75",設定!$F$9:$F$108,"=1：構成員"),1) -> 0
C14: その他の飼育作業 | D14: 手入・運動・放牧作業、きゅう肥の処理（切り返し、加工）作業、衛生管理（殺虫剤の散布等） | X14: =ROUND(SUMIFS(設定!$J$9:$J$108,設定!$E$9:$E$108,"<65",設定!$F$9:$F$108,"=1：構成員"),1) -> 0 | Y14: =ROUND(SUMIFS(設定!$J$9:$J$108,設定!$E$9:$E$108,">=65",設定!$E$9:$E$108,"<70",設定!$F$9:$F$108,"=1：構成員"),1) -> 0 | Z14: =ROUND(SUMIFS(設定!$J$9:$J$108,設定!$E$9:$E$108,">=70",設定!$E$9:$E$108,"<75",設定!$F$9:$F$108,"=1：構成員"),1) -> 0 | AA14: =ROUND(SUMIFS(設定!$J$9:$J$108,設定!$E$9:$E$108,">=75",設定!$F$9:$F$108,"=1：構成員"),1) -> 0
C15: 生産管理 | D15: 集会出席、技術習得、簿記記帳（税務申告は含まない。）等 | X15: =ROUND(SUM(SUMIFS(設定!$O$9:$O$108,設定!$E$9:$E$108,"<65",設定!$F$9:$F$108,"=1：構成員"),SUMIFS(設定!$P$9:$P$108,設定!$E$9:$E$108,"<65",設定!$F$9:$F$108,"=1：構成員"),SUMIFS(設定!$Q$9:$Q$108,設定!$E$9:$E$108,"<65",設定!$F$9:$F$108,"=1：構成員")),1) -> 0 | Y15: =ROUND(SUM(SUMIFS(設定!$O$9:$O$108,設定!$E$9:$E$108,">=65",設定!$E$9:$E$108,"<70",設定!$F$9:$F$108,"=1：構成員"),SUMIFS(設定!$P$9:$P$108,設定!$E$9:$E$108,">=65",設定!$E$9:$E$108,"<70",設定!$F$9:$F$108,"=1：構成員"),SUMIFS(設定!$Q$9:$Q$108,設定!$E$9:$E$108,">=65",設定!$E$9:$E$108,"<70",設定!$F$9:$F$108,"=1：構成員")),1) -> 0 | Z15: =ROUND(SUM(SUMIFS(設定!$O$9:$O$108,設定!$E$9:$E$108,">=70",設定!$E$9:$E$108,"<75",設定!$F$9:$F$108,"=1：構成員"),SUMIFS(設定!$P$9:$P$108,設定!$E$9:$E$108,">=70",設定!$E$9:$E$108,"<75",設定!$F$9:$F$108,"=1：構成員"),SUMIFS(設定!$Q$9:$Q$108,設定!$E$9:$E$108,">=70",設定!$E$9:$E$108,"<75",設定!$F$9:$F$108,"=1：構成員")),1) -> 0 | AA15: =ROUND(SUM(SUMIFS(設定!$O$9:$O$108,設定!$E$9:$E$108,">=75",設定!$F$9:$F$108,"=1：構成員"),SUMIFS(設定!$P$9:$P$108,設定!$E$9:$E$108,">=75",設定!$F$9:$F$108,"=1：構成員"),SUMIFS(設定!$Q$9:$Q$108,設定!$E$9:$E$108,">=75",設定!$F$9:$F$108,"=1：構成員")),1) -> 0
C16: 内給飼料（牧草等）の生産 | D16: 整地、耕起、施肥、種まき、肥培管理、収穫、乾燥、貯蔵等 | X16: =ROUND(SUMIFS(設定!$L$9:$L$108,設定!$E$9:$E$108,"<65",設定!$F$9:$F$108,"=1：構成員"),1) -> 0 | Y16: =ROUND(SUMIFS(設定!$L$9:$L$108,設定!$E$9:$E$108,">=65",設定!$E$9:$E$108,"<70",設定!$F$9:$F$108,"=1：構成員"),1) -> 0 | Z16: =ROUND(SUMIFS(設定!$L$9:$L$108,設定!$E$9:$E$108,">=70",設定!$E$9:$E$108,"<75",設定!$F$9:$F$108,"=1：構成員"),1) -> 0 | AA16: =ROUND(SUMIFS(設定!$L$9:$L$108,設定!$E$9:$E$108,">=75",設定!$F$9:$F$108,"=1：構成員"),1) -> 0
C17: 上記以外の労働 | D17: 建物、自動車、農機具等の修繕や、購入資材の調達等 | X17: =ROUND(SUM(SUMIFS(設定!$M$9:$M$108,設定!$E$9:$E$108,"<65",設定!$F$9:$F$108,"=1：構成員"),SUMIFS(設定!$N$9:$N$108,設定!$E$9:$E$108,"<65",設定!$F$9:$F$108,"=1：構成員")),1) -> 0 | Y17: =ROUND(SUM(SUMIFS(設定!$M$9:$M$108,設定!$E$9:$E$108,">=65",設定!$E$9:$E$108,"<70",設定!$F$9:$F$108,"=1：構成員"),SUMIFS(設定!$N$9:$N$108,設定!$E$9:$E$108,">=65",設定!$E$9:$E$108,"<70",設定!$F$9:$F$108,"=1：構成員")),1) -> 0 | Z17: =ROUND(SUM(SUMIFS(設定!$M$9:$M$108,設定!$E$9:$E$108,">=70",設定!$E$9:$E$108,"<75",設定!$F$9:$F$108,"=1：構成員"),SUMIFS(設定!$N$9:$N$108,設定!$E$9:$E$108,">=70",設定!$E$9:$E$108,"<75",設定!$F$9:$F$108,"=1：構成員")),1) -> 0 | AA17: =ROUND(SUM(SUMIFS(設定!$M$9:$M$108,設定!$E$9:$E$108,">=75",設定!$F$9:$F$108,"=1：構成員"),SUMIFS(設定!$N$9:$N$108,設定!$E$9:$E$108,">=75",設定!$F$9:$F$108,"=1：構成員")),1) -> 0
C21: ２ 雇用
C23: 作 業 種 類 | D23: 内 容 例 示 | X23: 労働時間
C24: 飼料の調理・給与・給水 | D24: 飼料材料の裁断・粉砕・挽割煮炊き、麦・豆類の水浸および芽出し、飼料の混配合などの調理・給与・給水 | X24: =ROUND(SUMIFS(設定!$H$9:$H$108,設定!$F$9:$F$108,"=2：雇用"),1) -> 0
C25: 敷料搬入・きゅう肥搬出 | D25: 稲わら・敷草等敷料の畜舎への投入、ふんかき、きゅう肥（尿を含む。）の最寄り場所（たい肥舎等）までの運搬作業 | X25: =ROUND(SUMIFS(設定!$I$9:$I$108,設定!$F$9:$F$108,"=2：雇用"),1) -> 0
C26: その他の飼育作業 | D26: 手入・運動・放牧作業、きゅう肥の処理（切り返し、加工）作業、衛生管理（殺虫剤の散布等） | X26: =ROUND(SUMIFS(設定!$J$9:$J$108,設定!$F$9:$F$108,"=2：雇用"),1) -> 0
C27: 内給飼料（牧草等）の生産 | D27: 整地、耕起、施肥、種まき、肥培管理、収穫、乾燥、貯蔵等 | X27: =ROUND(SUMIFS(設定!$L$9:$L$108,設定!$F$9:$F$108,"=2：雇用"),1) -> 0
C28: 上記以外の労働 | D28: 建物、自動車、農機具等の修繕や、購入資材の調達等 | X28: =ROUND(SUM(SUMIFS(設定!$M$9:$M$108,設定!$F$9:$F$108,"=2：雇用"),SUMIFS(設定!$N$9:$N$108,設定!$F$9:$F$108,"=2：雇用")),1) -> 0

Sheet リスト 
A1: 経営種類 | B1: 生産費区分 | C1: 性別 | D1: 雇用形態（個別） | E1: 雇用形態（組織） | F1: 作業_牛乳 | G1: 作業_牛乳以外 | H1: =IF(設定!F3="","作業_Blank",IF(設定!F3="牛乳",F1,G1)) -> 作業_Blank | I1: =IF(OR(設定!$D$3="",設定!$F$3=""),"", IF(AND(設定!$D$3="個別経営体",設定!$F$3="牛乳"),"【12】労働時間（個別・定型・牛乳）", IF(AND(設定!$D$3="個別経営体",設定!$F$3<>"牛乳"),"【12】労働時間（個別・定型・牛乳以外）", IF(AND(設定!$D$3="組織法人経営体",設定!$F$3="牛乳"),"【12】労働時間（経営分析・牛乳）", IF(AND(設定!$D$3="組織法人経営体",設定!$F$3<>"牛乳"),"【12】労働時間（経営分析・牛乳以外）",""))))) | J1: =IF(OR(設定!$D$3="",設定!$F$3=""),"", IF(AND(設定!$D$3="個別経営体",設定!$F$3="牛乳"),"【12】労働時間（個別・定型・牛乳）」と「【12】労働時間（個別・定型以外）", IF(AND(設定!$D$3="個別経営体",設定!$F$3<>"牛乳"),"【12】労働時間（個別・定型・牛乳以外）」と「【12】労働時間（個別・定型以外）", IF(AND(設定!$D$3="組織法人経営体",設定!$F$3="牛乳"),"【12】労働時間（経営分析・牛乳）", IF(AND(設定!$D$3="組織法人経営体",設定!$F$3<>"牛乳"),"【12】労働時間（経営分析・牛乳以外）","")))))
A2: 個別経営体 | B2: 牛乳 | C2: 1：男 | D2: 1：家族 | E2: 1：構成員 | F2: 飼料の調理・給与・給水 | G2: 飼料の調理・給与・給水
A3: 組織法人経営体 | B3: 子牛 | C3: 2：女 | D3: 2：雇用 | E3: 2：雇用 | F3: 敷料搬入・きゅう肥搬出 | G3: 敷料搬入・きゅう肥搬出
B4: 乳用雄育成牛 | D4: 3：ゆい・手間替え受け | F4: 搾乳・牛乳処理・運搬 | G4: その他の飼育作業
B5: 交雑種育成牛 | D5: 4：手伝い・共同作業受け | F5: その他の飼育作業 | G5: =IF(設定!$D$3="個別経営体","自給飼料の生産",IF(設定!$D$3="組織法人経営体","内給飼料の生産",""))
B6: 去勢若齢肥育牛 | D6: 5：同居人 | F6: =IF(設定!$D$3="個別経営体","自給飼料の生産",IF(設定!$D$3="組織法人経営体","内給飼料の生産","")) | G6: 購入付帯労働時間
B7: 乳用雄肥育牛 | F7: 購入付帯労働時間 | G7: 建物・農機具等の修繕
B8: 交雑種肥育牛 | F8: 建物・農機具等の修繕 | G8: 集会出席時間
B9: 肥育豚 | F9: 集会出席時間 | G9: 技術習得時間
F10: 技術習得時間 | G10: 簿記記帳時間
F11: 簿記記帳時間 | G11: 経営管理労働時間
F12: 経営管理労働時間
